Workbook

Sheet 変更履歴
A1: Ｐｈａｓｅ 外部設計工程 | BJ1: HOKUREN INTERNAL USE ONLY
A2: 帳票設計書 変更履歴 | AV2: 様式No. | AZ2: F4109-0 | BD2: PAGE
A3: システム名 | H3: 統合会計システム | AV3: 作成日 | AZ3: 2025/8/29
A4: サブシステム名 | H4: 部門提供 | AV4: 更新日
A6: 機能Ｎｏ． | H6: 8.6.3 | P6: 帳票名 | V6: 販売品勘定整理帳
A8: 管理番号 | I8: 案件名 / 障害・問合せ件名
B10: 24058 | I10: 基幹システム再構築 会計システム外部設計

Sheet 1.帳票レイアウト
A1: Ｐｈａｓｅ 外部設計工程 | EC1: HOKUREN INTERNAL USE ONLY
A2: 帳 票 レ イ ア ウ ト
A3: システム名 | L3: 統合会計システム | CR3: 様 式 № | DB3: F4109-1 | DK3: ＰＡＧＥ
A4: 業務名 | L4: 部門提供 | CR4: 作成日 | DB4: 2025/8/29 | DK4: 更新日
A6: 帳 票 名 | L6: 販売品勘定整理帳
A7: 0 | K7: 1 | U7: 2 | AE7: 3 | AO7: 4 | AY7: 5 | BI7: 6 | BS7: 7 | CC7: 8 | CM7: 9 | CW7: 0 | DG7: 1 | DQ7: 2 | EA7: 3
A8: 0 | B8: =(A8+1) -> 1 | C8: =(B8+1) -> 2 | D8: =(C8+1) -> 3 | E8: =(D8+1) -> 4 | F8: =(E8+1) -> 5 | G8: =(F8+1) -> 6 | H8: =(G8+1) -> 7 | I8: =(H8+1) -> 8 | J8: =(I8+1) -> 9 | K8: 0 | L8: =(K8+1) -> 1 | M8: =(L8+1) -> 2 | N8: =(M8+1) -> 3 | O8: =(N8+1) -> 4 | P8: =(O8+1) -> 5 | Q8: =(P8+1) -> 6 | R8: =(Q8+1) -> 7 | S8: =(R8+1) -> 8 | T8: =(S8+1) -> 9 | U8: 0 | V8: =(U8+1) -> 1 | W8: =(V8+1) -> 2 | X8: =(W8+1) -> 3 | Y8: =(X8+1) -> 4 | Z8: =(Y8+1) -> 5 | AA8: =(Z8+1) -> 6 | AB8: =(AA8+1) -> 7 | AC8: =(AB8+1) -> 8 | AD8: =(AC8+1) -> 9 | AE8: 0 | AF8: =(AE8+1) -> 1 | AG8: =(AF8+1) -> 2 | AH8: =(AG8+1) -> 3 | AI8: =(AH8+1) -> 4 | AJ8: =(AI8+1) -> 5 | AK8: =(AJ8+1) -> 6 | AL8: =(AK8+1) -> 7 | AM8: =(AL8+1) -> 8 | AN8: =(AM8+1) -> 9 | AO8: 0 | AP8: =(AO8+1) -> 1 | AQ8: =(AP8+1) -> 2 | AR8: =(AQ8+1) -> 3 | AS8: =(AR8+1) -> 4 | AT8: =(AS8+1) -> 5 | AU8: =(AT8+1) -> 6 | AV8: =(AU8+1) -> 7 | AW8: =(AV8+1) -> 8 | AX8: =(AW8+1) -> 9 | AY8: 0 | AZ8: =(AY8+1) -> 1 | BA8: =(AZ8+1) -> 2 | BB8: =(BA8+1) -> 3 | BC8: =(BB8+1) -> 4 | BD8: =(BC8+1) -> 5 | BE8: =(BD8+1) -> 6 | BF8: =(BE8+1) -> 7 | BG8: =(BF8+1) -> 8 | BH8: =(BG8+1) -> 9 | BI8: 0 | BJ8: =(BI8+1) -> 1 | BK8: =(BJ8+1) -> 2 | BL8: =(BK8+1) -> 3 | BM8: =(BL8+1) -> 4 | BN8: =(BM8+1) -> 5 | BO8: =(BN8+1) -> 6 | BP8: =(BO8+1) -> 7 | BQ8: =(BP8+1) -> 8 | BR8: =(BQ8+1) -> 9 | BS8: 0 | BT8: =(BS8+1) -> 1 | BU8: =(BT8+1) -> 2 | BV8: =(BU8+1) -> 3 | BW8: =(BV8+1) -> 4 | BX8: =(BW8+1) -> 5 | BY8: =(BX8+1) -> 6 | BZ8: =(BY8+1) -> 7 | CA8: =(BZ8+1) -> 8 | CB8: =(CA8+1) -> 9 | CC8: 0 | CD8: =(CC8+1) -> 1 | CE8: =(CD8+1) -> 2 | CF8: =(CE8+1) -> 3 | CG8: =(CF8+1) -> 4 | CH8: =(CG8+1) -> 5 | CI8: =(CH8+1) -> 6 | CJ8: =(CI8+1) -> 7 | CK8: =(CJ8+1) -> 8 | CL8: =(CK8+1) -> 9 | CM8: 0 | CN8: =(CM8+1) -> 1 | CO8: =(CN8+1) -> 2 | CP8: =(CO8+1) -> 3 | CQ8: =(CP8+1) -> 4 | CR8: =(CQ8+1) -> 5 | CS8: =(CR8+1) -> 6 | CT8: =(CS8+1) -> 7 | CU8: =(CT8+1) -> 8 | CV8: =(CU8+1) -> 9 | CW8: 0 | CX8: =(CW8+1) -> 1 | CY8: =(CX8+1) -> 2 | CZ8: =(CY8+1) -> 3 | DA8: =(CZ8+1) -> 4 | DB8: =(DA8+1) -> 5 | DC8: =(DB8+1) -> 6 | DD8: =(DC8+1) -> 7 | DE8: =(DD8+1) -> 8 | DF8: =(DE8+1) -> 9 | DG8: 0 | DH8: =(DG8+1) -> 1 | DI8: =(DH8+1) -> 2 | DJ8: =(DI8+1) -> 3 | DK8: =(DJ8+1) -> 4 | DL8: =(DK8+1) -> 5 | DM8: =(DL8+1) -> 6 | DN8: =(DM8+1) -> 7 | DO8: =(DN8+1) -> 8 | DP8: =(DO8+1) -> 9 | DQ8: 0 | DR8: =(DQ8+1) -> 1 | DS8: =(DR8+1) -> 2 | DT8: =(DS8+1) -> 3 | DU8: =(DT8+1) -> 4 | DV8: =(DU8+1) -> 5 | DW8: =(DV8+1) -> 6 | DX8: =(DW8+1) -> 7 | DY8: =(DX8+1) -> 8 | DZ8: =(DY8+1) -> 9 | EA8: 0 | EB8: =(EA8+1) -> 1 | EC8: =(EB8+1) -> 2
A9: =A8+1 -> 1 | B9: XXXXXX | AX9: ＊販売品勘定整理帳＊ | BZ9: ZZZ9 年 Z9月 Z9 日 | CW9: 9999/Z9/Z9 HH:MM：SS | DK9: PAGE：Z,ZZ9
A10: =A9+1 -> 2 | DL10: （ZZ,ZZ9）
A11: =A10+1 -> 3 | F11: 業種 | N11: XX | R11: ＸＸＸＸＸＸＸＸＸＸＸＸＸＸＸ
A12: =A11+1 -> 4 | F12: 受払組織 | N12: XX | R12: ＸＸＸＸＸＸＸＸＸＸＸＸＸＸＸ | AL12: XXX | AP12: ＸＸＸＸＸＸＸＸＸＸＸＸＸＸＸ
A13: =A12+1 -> 5 | F13: 出力年月日 | N13: ZZZ9年Z9月Z9日 | CF13: 上段：日計 ／ 中段：月計 ／ 下段：累計 単位：円
A14: =A12+1 -> 5 | D14: 商品名 | AK14: 借方 | BE14: 貸方 | BY14: 残高 | CS14: 売上金額 手数料 | DC14: 費用 純益 | DM14: 手数料率 純益率
A15: =A14+1 -> 6 | AF15: 単位
A16: =A15+1 -> 7 | D16: 出力制御 | AK16: 数量（分子） 数量（仮数） | AU16: 単価 金額 | BE16: 数量（分子） 数量（仮数） | BO16: 単価 売上原価 | BY16: 数量（分子） 数量（仮数） | CI16: 単価 金額
A17: =A16+1 -> 8 | D17: (収支管理品目） | L17: 年産 | AD17: （取扱）
A18: =A17+1 -> 9 | D18: ＸＸＸＸＸＸＸＸＸＸＸＸＸＸＸＸＸＸＸＸＸＸＸＸＸ | AK18: Z,ZZZ,ZZZ,ZZZ.ZZ9 | AU18: Z,ZZZ,ZZZ,ZZZ.ZZ9 | BE18: Z,ZZZ,ZZZ,ZZZ.ZZ9 | BO18: Z,ZZZ,ZZZ,ZZZ.ZZ9 | BY18: Z,ZZZ,ZZZ,ZZZ.ZZ9 | CI18: Z,ZZZ,ZZZ,ZZZ.ZZ9 | CS18: Z,ZZZ,ZZZ,ZZZ,ZZ9 | DC18: Z,ZZZ,ZZZ,ZZZ,ZZ9 | DM18: ZZZZ.9
A19: =A18+1 -> 10 | AF19: ＸＸＸＸ | AK19: Z,ZZZ,ZZZ,ZZZ,ZZ9 | AU19: Z,ZZZ,ZZZ,ZZZ,ZZ9 | BE19: Z,ZZZ,ZZZ,ZZZ,ZZ9 | BO19: Z,ZZZ,ZZZ,ZZZ,ZZ9 | BY19: Z,ZZZ,ZZZ,ZZZ,ZZ9 | CI19: Z,ZZZ,ZZZ,ZZZ,ZZ9 | CS19: Z,ZZZ,ZZZ,ZZZ,ZZ9 | DC19: Z,ZZZ,ZZZ,ZZZ,ZZ9 | DM19: ZZZZ.9
A20: =A19+1 -> 11 | D20: XXXXXX | AK20: Z,ZZZ,ZZZ,ZZZ.ZZ9 | AU20: Z,ZZZ,ZZZ,ZZZ.ZZ9 | BE20: Z,ZZZ,ZZZ,ZZZ.ZZ9 | BO20: Z,ZZZ,ZZZ,ZZZ.ZZ9 | BY20: Z,ZZZ,ZZZ,ZZZ.ZZ9 | CI20: Z,ZZZ,ZZZ,ZZZ.ZZ9 | CS20: Z,ZZZ,ZZZ,ZZZ,ZZ9 | DC20: Z,ZZZ,ZZZ,ZZZ,ZZ9 | DM20: ZZZZ.9
A21: =A20+1 -> 12 | D21: （XXXXXX） | J21: XXXX | AC21: （ＸＸ） | AK21: Z,ZZZ,ZZZ,ZZZ,ZZ9 | AU21: Z,ZZZ,ZZZ,ZZZ,ZZ9 | BE21: Z,ZZZ,ZZZ,ZZZ,ZZ9 | BO21: Z,ZZZ,ZZZ,ZZZ,ZZ9 | BY21: Z,ZZZ,ZZZ,ZZZ,ZZ9 | CI21: Z,ZZZ,ZZZ,ZZZ,ZZ9 | CS21: Z,ZZZ,ZZZ,ZZZ,ZZ9 | DC21: Z,ZZZ,ZZZ,ZZZ,ZZ9 | DM21: ZZZZ.9
A22: =A21+1 -> 13 | AK22: Z,ZZZ,ZZZ,ZZZ.ZZ9 | AU22: Z,ZZZ,ZZZ,ZZZ.ZZ9 | BE22: Z,ZZZ,ZZZ,ZZZ.ZZ9 | BO22: Z,ZZZ,ZZZ,ZZZ.ZZ9 | BY22: Z,ZZZ,ZZZ,ZZZ.ZZ9 | CI22: Z,ZZZ,ZZZ,ZZZ.ZZ9 | CS22: Z,ZZZ,ZZZ,ZZZ,ZZ9 | DC22: Z,ZZZ,ZZZ,ZZZ,ZZ9 | DM22: ZZZZ.9
A23: =A22+1 -> 14 | AK23: Z,ZZZ,ZZZ,ZZZ,ZZ9 | AU23: Z,ZZZ,ZZZ,ZZZ,ZZ9 | BE23: Z,ZZZ,ZZZ,ZZZ,ZZ9 | BO23: Z,ZZZ,ZZZ,ZZZ,ZZ9 | BY23: Z,ZZZ,ZZZ,ZZZ,ZZ9 | CI23: Z,ZZZ,ZZZ,ZZZ,ZZ9 | CS23: Z,ZZZ,ZZZ,ZZZ,ZZ9 | DC23: Z,ZZZ,ZZZ,ZZZ,ZZ9 | DM23: ZZZZ.9
A24: =A23+1 -> 15 | D24: ＸＸＸＸＸＸＸＸＸＸＸＸＸＸＸＸＸＸＸＸＸＸＸＸＸ | AK24: Z,ZZZ,ZZZ,ZZZ.ZZ9 | AU24: Z,ZZZ,ZZZ,ZZZ.ZZ9 | BE24: Z,ZZZ,ZZZ,ZZZ.ZZ9 | BO24: Z,ZZZ,ZZZ,ZZZ.ZZ9 | BY24: Z,ZZZ,ZZZ,ZZZ.ZZ9 | CI24: Z,ZZZ,ZZZ,ZZZ.ZZ9 | CS24: Z,ZZZ,ZZZ,ZZZ,ZZ9 | DC24: Z,ZZZ,ZZZ,ZZZ,ZZ9 | DM24: ZZZZ.9
A25: =A24+1 -> 16 | AF25: ＸＸＸＸ | AK25: Z,ZZZ,ZZZ,ZZZ,ZZ9 | AU25: Z,ZZZ,ZZZ,ZZZ,ZZ9 | BE25: Z,ZZZ,ZZZ,ZZZ,ZZ9 | BO25: Z,ZZZ,ZZZ,ZZZ,ZZ9 | BY25: Z,ZZZ,ZZZ,ZZZ,ZZ9 | CI25: Z,ZZZ,ZZZ,ZZZ,ZZ9 | CS25: Z,ZZZ,ZZZ,ZZZ,ZZ9 | DC25: Z,ZZZ,ZZZ,ZZZ,ZZ9 | DM25: ZZZZ.9
A26: =A25+1 -> 17 | D26: XXXXXX | AK26: Z,ZZZ,ZZZ,ZZZ.ZZ9 | AU26: Z,ZZZ,ZZZ,ZZZ.ZZ9 | BE26: Z,ZZZ,ZZZ,ZZZ.ZZ9 | BO26: Z,ZZZ,ZZZ,ZZZ.ZZ9 | BY26: Z,ZZZ,ZZZ,ZZZ.ZZ9 | CI26: Z,ZZZ,ZZZ,ZZZ.ZZ9 | CS26: Z,ZZZ,ZZZ,ZZZ,ZZ9 | DC26: Z,ZZZ,ZZZ,ZZZ,ZZ9 | DM26: ZZZZ.9
A27: =A26+1 -> 18 | D27: （XXXXXX） | J27: XXXX | AC27: （ＸＸ） | AK27: Z,ZZZ,ZZZ,ZZZ,ZZ9 | AU27: Z,ZZZ,ZZZ,ZZZ,ZZ9 | BE27: Z,ZZZ,ZZZ,ZZZ,ZZ9 | BO27: Z,ZZZ,ZZZ,ZZZ,ZZ9 | BY27: Z,ZZZ,ZZZ,ZZZ,ZZ9 | CI27: Z,ZZZ,ZZZ,ZZZ,ZZ9 | CS27: Z,ZZZ,ZZZ,ZZZ,ZZ9 | DC27: Z,ZZZ,ZZZ,ZZZ,ZZ9 | DM27: ZZZZ.9
A28: =A27+1 -> 19 | AK28: Z,ZZZ,ZZZ,ZZZ.ZZ9 | AU28: Z,ZZZ,ZZZ,ZZZ.ZZ9 | BE28: Z,ZZZ,ZZZ,ZZZ.ZZ9 | BO28: Z,ZZZ,ZZZ,ZZZ.ZZ9 | BY28: Z,ZZZ,ZZZ,ZZZ.ZZ9 | CI28: Z,ZZZ,ZZZ,ZZZ.ZZ9 | CS28: Z,ZZZ,ZZZ,ZZZ,ZZ9 | DC28: Z,ZZZ,ZZZ,ZZZ,ZZ9 | DM28: ZZZZ.9
A29: =A28+1 -> 20 | AK29: Z,ZZZ,ZZZ,ZZZ,ZZ9 | AU29: Z,ZZZ,ZZZ,ZZZ,ZZ9 | BE29: Z,ZZZ,ZZZ,ZZZ,ZZ9 | BO29: Z,ZZZ,ZZZ,ZZZ,ZZ9 | BY29: Z,ZZZ,ZZZ,ZZZ,ZZ9 | CI29: Z,ZZZ,ZZZ,ZZZ,ZZ9 | CS29: Z,ZZZ,ZZZ,ZZZ,ZZ9 | DC29: Z,ZZZ,ZZZ,ZZZ,ZZ9 | DM29: ZZZZ.9
A30: =A29+1 -> 21 | D30: ＸＸＸＸＸＸＸＸＸＸＸＸＸＸＸＸＸＸＸＸＸＸＸＸＸ | AK30: Z,ZZZ,ZZZ,ZZZ.ZZ9 | AU30: Z,ZZZ,ZZZ,ZZZ.ZZ9 | BE30: Z,ZZZ,ZZZ,ZZZ.ZZ9 | BO30: Z,ZZZ,ZZZ,ZZZ.ZZ9 | BY30: Z,ZZZ,ZZZ,ZZZ.ZZ9 | CI30: Z,ZZZ,ZZZ,ZZZ.ZZ9 | CS30: Z,ZZZ,ZZZ,ZZZ,ZZ9 | DC30: Z,ZZZ,ZZZ,ZZZ,ZZ9 | DM30: ZZZZ.9
A31: =A30+1 -> 22 | AF31: ＸＸＸＸ | AK31: Z,ZZZ,ZZZ,ZZZ,ZZ9 | AU31: Z,ZZZ,ZZZ,ZZZ,ZZ9 | BE31: Z,ZZZ,ZZZ,ZZZ,ZZ9 | BO31: Z,ZZZ,ZZZ,ZZZ,ZZ9 | BY31: Z,ZZZ,ZZZ,ZZZ,ZZ9 | CI31: Z,ZZZ,ZZZ,ZZZ,ZZ9 | CS31: Z,ZZZ,ZZZ,ZZZ,ZZ9 | DC31: Z,ZZZ,ZZZ,ZZZ,ZZ9 | DM31: ZZZZ.9
A32: =A31+1 -> 23 | D32: XXXXXX | AK32: Z,ZZZ,ZZZ,ZZZ.ZZ9 | AU32: Z,ZZZ,ZZZ,ZZZ.ZZ9 | BE32: Z,ZZZ,ZZZ,ZZZ.ZZ9 | BO32: Z,ZZZ,ZZZ,ZZZ.ZZ9 | BY32: Z,ZZZ,ZZZ,ZZZ.ZZ9 | CI32: Z,ZZZ,ZZZ,ZZZ.ZZ9 | CS32: Z,ZZZ,ZZZ,ZZZ,ZZ9 | DC32: Z,ZZZ,ZZZ,ZZZ,ZZ9 | DM32: ZZZZ.9
A33: =A32+1 -> 24 | D33: （XXXXXX） | J33: XXXX | AC33: （ＸＸ） | AK33: Z,ZZZ,ZZZ,ZZZ,ZZ9 | AU33: Z,ZZZ,ZZZ,ZZZ,ZZ9 | BE33: Z,ZZZ,ZZZ,ZZZ,ZZ9 | BO33: Z,ZZZ,ZZZ,ZZZ,ZZ9 | BY33: Z,ZZZ,ZZZ,ZZZ,ZZ9 | CI33: Z,ZZZ,ZZZ,ZZZ,ZZ9 | CS33: Z,ZZZ,ZZZ,ZZZ,ZZ9 | DC33: Z,ZZZ,ZZZ,ZZZ,ZZ9 | DM33: ZZZZ.9
A34: =A33+1 -> 25 | AK34: Z,ZZZ,ZZZ,ZZZ.ZZ9 | AU34: Z,ZZZ,ZZZ,ZZZ.ZZ9 | BE34: Z,ZZZ,ZZZ,ZZZ.ZZ9 | BO34: Z,ZZZ,ZZZ,ZZZ.ZZ9 | BY34: Z,ZZZ,ZZZ,ZZZ.ZZ9 | CI34: Z,ZZZ,ZZZ,ZZZ.ZZ9 | CS34: Z,ZZZ,ZZZ,ZZZ,ZZ9 | DC34: Z,ZZZ,ZZZ,ZZZ,ZZ9 | DM34: ZZZZ.9
A35: =A34+1 -> 26 | AK35: Z,ZZZ,ZZZ,ZZZ,ZZ9 | AU35: Z,ZZZ,ZZZ,ZZZ,ZZ9 | BE35: Z,ZZZ,ZZZ,ZZZ,ZZ9 | BO35: Z,ZZZ,ZZZ,ZZZ,ZZ9 | BY35: Z,ZZZ,ZZZ,ZZZ,ZZ9 | CI35: Z,ZZZ,ZZZ,ZZZ,ZZ9 | CS35: Z,ZZZ,ZZZ,ZZZ,ZZ9 | DC35: Z,ZZZ,ZZZ,ZZZ,ZZ9 | DM35: ZZZZ.9
A36: =A35+1 -> 27 | D36: ＸＸＸＸＸＸＸＸＸＸＸＸＸＸＸＸＸＸＸＸＸＸＸＸＸ | AK36: Z,ZZZ,ZZZ,ZZZ.ZZ9 | AU36: Z,ZZZ,ZZZ,ZZZ.ZZ9 | BE36: Z,ZZZ,ZZZ,ZZZ.ZZ9 | BO36: Z,ZZZ,ZZZ,ZZZ.ZZ9 | BY36: Z,ZZZ,ZZZ,ZZZ.ZZ9 | CI36: Z,ZZZ,ZZZ,ZZZ.ZZ9 | CS36: Z,ZZZ,ZZZ,ZZZ,ZZ9 | DC36: Z,ZZZ,ZZZ,ZZZ,ZZ9 | DM36: ZZZZ.9
A37: =A36+1 -> 28 | AK37: Z,ZZZ,ZZZ,ZZZ,ZZ9 | AU37: Z,ZZZ,ZZZ,ZZZ,ZZ9 | BE37: Z,ZZZ,ZZZ,ZZZ,ZZ9 | BO37: Z,ZZZ,ZZZ,ZZZ,ZZ9 | BY37: Z,ZZZ,ZZZ,ZZZ,ZZ9 | CI37: Z,ZZZ,ZZZ,ZZZ,ZZ9 | CS37: Z,ZZZ,ZZZ,ZZZ,ZZ9 | DC37: Z,ZZZ,ZZZ,ZZZ,ZZ9 | DM37: ZZZZ.9
A38: =A37+1 -> 29 | AK38: Z,ZZZ,ZZZ,ZZZ.ZZ9 | AU38: Z,ZZZ,ZZZ,ZZZ.ZZ9 | BE38: Z,ZZZ,ZZZ,ZZZ.ZZ9 | BO38: Z,ZZZ,ZZZ,ZZZ.ZZ9 | BY38: Z,ZZZ,ZZZ,ZZZ.ZZ9 | CI38: Z,ZZZ,ZZZ,ZZZ.ZZ9 | CS38: Z,ZZZ,ZZZ,ZZZ,ZZ9 | DC38: Z,ZZZ,ZZZ,ZZZ,ZZ9 | DM38: ZZZZ.9
A39: =A38+1 -> 30 | D39: XXXXXX | T39: ＊収支管理品目（大）計 | AK39: Z,ZZZ,ZZZ,ZZZ,ZZ9 | AU39: Z,ZZZ,ZZZ,ZZZ,ZZ9 | BE39: Z,ZZZ,ZZZ,ZZZ,ZZ9 | BO39: Z,ZZZ,ZZZ,ZZZ,ZZ9 | BY39: Z,ZZZ,ZZZ,ZZZ,ZZ9 | CI39: Z,ZZZ,ZZZ,ZZZ,ZZ9 | CS39: Z,ZZZ,ZZZ,ZZZ,ZZ9 | DC39: Z,ZZZ,ZZZ,ZZZ,ZZ9 | DM39: ZZZZ.9
A40: =A39+1 -> 31 | D40: （XXXXXX） | J40: XXXX | AK40: Z,ZZZ,ZZZ,ZZZ.ZZ9 | AU40: Z,ZZZ,ZZZ,ZZZ.ZZ9 | BE40: Z,ZZZ,ZZZ,ZZZ.ZZ9 | BO40: Z,ZZZ,ZZZ,ZZZ.ZZ9 | BY40: Z,ZZZ,ZZZ,ZZZ.ZZ9 | CI40: Z,ZZZ,ZZZ,ZZZ.ZZ9 | CS40: Z,ZZZ,ZZZ,ZZZ,ZZ9 | DC40: Z,ZZZ,ZZZ,ZZZ,ZZ9 | DM40: ZZZZ.9
A41: =A40+1 -> 32 | AK41: Z,ZZZ,ZZZ,ZZZ,ZZ9 | AU41: Z,ZZZ,ZZZ,ZZZ,ZZ9 | BE41: Z,ZZZ,ZZZ,ZZZ,ZZ9 | BO41: Z,ZZZ,ZZZ,ZZZ,ZZ9 | BY41: Z,ZZZ,ZZZ,ZZZ,ZZ9 | CI41: Z,ZZZ,ZZZ,ZZZ,ZZ9 | CS41: Z,ZZZ,ZZZ,ZZZ,ZZ9 | DC41: Z,ZZZ,ZZZ,ZZZ,ZZ9 | DM41: ZZZZ.9
A42: =A41+1 -> 33 | D42: ＸＸＸＸＸＸＸＸＸＸＸＸＸＸＸＸＸＸＸＸＸＸＸＸＸ | AK42: Z,ZZZ,ZZZ,ZZZ.ZZ9 | AU42: Z,ZZZ,ZZZ,ZZZ.ZZ9 | BE42: Z,ZZZ,ZZZ,ZZZ.ZZ9 | BO42: Z,ZZZ,ZZZ,ZZZ.ZZ9 | BY42: Z,ZZZ,ZZZ,ZZZ.ZZ9 | CI42: Z,ZZZ,ZZZ,ZZZ.ZZ9 | CS42: Z,ZZZ,ZZZ,ZZZ,ZZ9 | DC42: Z,ZZZ,ZZZ,ZZZ,ZZ9 | DM42: ZZZZ.9
A43: =A42+1 -> 34 | AK43: Z,ZZZ,ZZZ,ZZZ,ZZ9 | AU43: Z,ZZZ,ZZZ,ZZZ,ZZ9 | BE43: Z,ZZZ,ZZZ,ZZZ,ZZ9 | BO43: Z,ZZZ,ZZZ,ZZZ,ZZ9 | BY43: Z,ZZZ,ZZZ,ZZZ,ZZ9 | CI43: Z,ZZZ,ZZZ,ZZZ,ZZ9 | CS43: Z,ZZZ,ZZZ,ZZZ,ZZ9 | DC43: Z,ZZZ,ZZZ,ZZZ,ZZ9 | DM43: ZZZZ.9
A44: =A43+1 -> 35 | D44: XXXXXX | AK44: Z,ZZZ,ZZZ,ZZZ.ZZ9 | AU44: Z,ZZZ,ZZZ,ZZZ.ZZ9 | BE44: Z,ZZZ,ZZZ,ZZZ.ZZ9 | BO44: Z,ZZZ,ZZZ,ZZZ.ZZ9 | BY44: Z,ZZZ,ZZZ,ZZZ.ZZ9 | CI44: Z,ZZZ,ZZZ,ZZZ.ZZ9 | CS44: Z,ZZZ,ZZZ,ZZZ,ZZ9 | DC44: Z,ZZZ,ZZZ,ZZZ,ZZ9 | DM44: ZZZZ.9
A45: =A44+1 -> 36 | D45: （XXXXXX） | T45: ＊＊会計情報品目計 | AK45: Z,ZZZ,ZZZ,ZZZ,ZZ9 | AU45: Z,ZZZ,ZZZ,ZZZ,ZZ9 | BE45: Z,ZZZ,ZZZ,ZZZ,ZZ9 | BO45: Z,ZZZ,ZZZ,ZZZ,ZZ9 | BY45: Z,ZZZ,ZZZ,ZZZ,ZZ9 | CI45: Z,ZZZ,ZZZ,ZZZ,ZZ9 | CS45: Z,ZZZ,ZZZ,ZZZ,ZZ9 | DC45: Z,ZZZ,ZZZ,ZZZ,ZZ9 | DM45: ZZZZ.9
A46: =A45+1 -> 37 | AK46: Z,ZZZ,ZZZ,ZZZ.ZZ9 | AU46: Z,ZZZ,ZZZ,ZZZ.ZZ9 | BE46: Z,ZZZ,ZZZ,ZZZ.ZZ9 | BO46: Z,ZZZ,ZZZ,ZZZ.ZZ9 | BY46: Z,ZZZ,ZZZ,ZZZ.ZZ9 | CI46: Z,ZZZ,ZZZ,ZZZ.ZZ9 | CS46: Z,ZZZ,ZZZ,ZZZ,ZZ9 | DC46: Z,ZZZ,ZZZ,ZZZ,ZZ9 | DM46: ZZZZ.9
A47: =A46+1 -> 38 | AK47: Z,ZZZ,ZZZ,ZZZ,ZZ9 | AU47: Z,ZZZ,ZZZ,ZZZ,ZZ9 | BE47: Z,ZZZ,ZZZ,ZZZ,ZZ9 | BO47: Z,ZZZ,ZZZ,ZZZ,ZZ9 | BY47: Z,ZZZ,ZZZ,ZZZ,ZZ9 | CI47: Z,ZZZ,ZZZ,ZZZ,ZZ9 | CS47: Z,ZZZ,ZZZ,ZZZ,ZZ9 | DC47: Z,ZZZ,ZZZ,ZZZ,ZZ9 | DM47: ZZZZ.9
A48: =A47+1 -> 39 | AK48: Z,ZZZ,ZZZ,ZZZ.ZZ9 | AU48: Z,ZZZ,ZZZ,ZZZ.ZZ9 | BE48: Z,ZZZ,ZZZ,ZZZ.ZZ9 | BO48: Z,ZZZ,ZZZ,ZZZ.ZZ9 | BY48: Z,ZZZ,ZZZ,ZZZ.ZZ9 | CI48: Z,ZZZ,ZZZ,ZZZ.ZZ9 | CS48: Z,ZZZ,ZZZ,ZZZ,ZZ9 | DC48: Z,ZZZ,ZZZ,ZZZ,ZZ9 | DM48: ZZZZ.9
A49: =A48+1 -> 40 | AK49: Z,ZZZ,ZZZ,ZZZ,ZZ9 | AU49: Z,ZZZ,ZZZ,ZZZ,ZZ9 | BE49: Z,ZZZ,ZZZ,ZZZ,ZZ9 | BO49: Z,ZZZ,ZZZ,ZZZ,ZZ9 | BY49: Z,ZZZ,ZZZ,ZZZ,ZZ9 | CI49: Z,ZZZ,ZZZ,ZZZ,ZZ9 | CS49: Z,ZZZ,ZZZ,ZZZ,ZZ9 | DC49: Z,ZZZ,ZZZ,ZZZ,ZZ9 | DM49: ZZZZ.9
A50: =A49+1 -> 41 | AK50: Z,ZZZ,ZZZ,ZZZ.ZZ9 | AU50: Z,ZZZ,ZZZ,ZZZ.ZZ9 | BE50: Z,ZZZ,ZZZ,ZZZ.ZZ9 | BO50: Z,ZZZ,ZZZ,ZZZ.ZZ9 | BY50: Z,ZZZ,ZZZ,ZZZ.ZZ9 | CI50: Z,ZZZ,ZZZ,ZZZ.ZZ9 | CS50: Z,ZZZ,ZZZ,ZZZ,ZZ9 | DC50: Z,ZZZ,ZZZ,ZZZ,ZZ9 | DM50: ZZZZ.9
A51: =A50+1 -> 42 | T51: ＊＊＊受払組織計 | AK51: Z,ZZZ,ZZZ,ZZZ,ZZ9 | AU51: Z,ZZZ,ZZZ,ZZZ,ZZ9 | BE51: Z,ZZZ,ZZZ,ZZZ,ZZ9 | BO51: Z,ZZZ,ZZZ,ZZZ,ZZ9 | BY51: Z,ZZZ,ZZZ,ZZZ,ZZ9 | CI51: Z,ZZZ,ZZZ,ZZZ,ZZ9 | CS51: Z,ZZZ,ZZZ,ZZZ,ZZ9 | DC51: Z,ZZZ,ZZZ,ZZZ,ZZ9 | DM51: ZZZZ.9
A52: =A51+1 -> 43 | AK52: Z,ZZZ,ZZZ,ZZZ.ZZ9 | AU52: Z,ZZZ,ZZZ,ZZZ.ZZ9 | BE52: Z,ZZZ,ZZZ,ZZZ.ZZ9 | BO52: Z,ZZZ,ZZZ,ZZZ.ZZ9 | BY52: Z,ZZZ,ZZZ,ZZZ.ZZ9 | CI52: Z,ZZZ,ZZZ,ZZZ.ZZ9 | CS52: Z,ZZZ,ZZZ,ZZZ,ZZ9 | DC52: Z,ZZZ,ZZZ,ZZZ,ZZ9 | DM52: ZZZZ.9
A53: =A52+1 -> 44 | AK53: Z,ZZZ,ZZZ,ZZZ,ZZ9 | AU53: Z,ZZZ,ZZZ,ZZZ,ZZ9 | BE53: Z,ZZZ,ZZZ,ZZZ,ZZ9 | BO53: Z,ZZZ,ZZZ,ZZZ,ZZ9 | BY53: Z,ZZZ,ZZZ,ZZZ,ZZ9 | CI53: Z,ZZZ,ZZZ,ZZZ,ZZ9 | CS53: Z,ZZZ,ZZZ,ZZZ,ZZ9 | DC53: Z,ZZZ,ZZZ,ZZZ,ZZ9 | DM53: ZZZZ.9
A54: =A53+1 -> 45 | AK54: Z,ZZZ,ZZZ,ZZZ.ZZ9 | AU54: Z,ZZZ,ZZZ,ZZZ.ZZ9 | BE54: Z,ZZZ,ZZZ,ZZZ.ZZ9 | BO54: Z,ZZZ,ZZZ,ZZZ.ZZ9 | BY54: Z,ZZZ,ZZZ,ZZZ.ZZ9 | CI54: Z,ZZZ,ZZZ,ZZZ.ZZ9 | CS54: Z,ZZZ,ZZZ,ZZZ,ZZ9 | DC54: Z,ZZZ,ZZZ,ZZZ,ZZ9 | DM54: ZZZZ.9
A55: =A54+1 -> 46 | AK55: Z,ZZZ,ZZZ,ZZZ,ZZ9 | AU55: Z,ZZZ,ZZZ,ZZZ,ZZ9 | BE55: Z,ZZZ,ZZZ,ZZZ,ZZ9 | BO55: Z,ZZZ,ZZZ,ZZZ,ZZ9 | BY55: Z,ZZZ,ZZZ,ZZZ,ZZ9 | CI55: Z,ZZZ,ZZZ,ZZZ,ZZ9 | CS55: Z,ZZZ,ZZZ,ZZZ,ZZ9 | DC55: Z,ZZZ,ZZZ,ZZZ,ZZ9 | DM55: ZZZZ.9
A56: =A55+1 -> 47 | AK56: Z,ZZZ,ZZZ,ZZZ.ZZ9 | AU56: Z,ZZZ,ZZZ,ZZZ.ZZ9 | BE56: Z,ZZZ,ZZZ,ZZZ.ZZ9 | BO56: Z,ZZZ,ZZZ,ZZZ.ZZ9 | BY56: Z,ZZZ,ZZZ,ZZZ.ZZ9 | CI56: Z,ZZZ,ZZZ,ZZZ.ZZ9 | CS56: Z,ZZZ,ZZZ,ZZZ,ZZ9 | DC56: Z,ZZZ,ZZZ,ZZZ,ZZ9 | DM56: ZZZZ.9
A57: =A56+1 -> 48 | T57: ＊＊＊＊業種計 | AK57: Z,ZZZ,ZZZ,ZZZ,ZZ9 | AU57: Z,ZZZ,ZZZ,ZZZ,ZZ9 | BE57: Z,ZZZ,ZZZ,ZZZ,ZZ9 | BO57: Z,ZZZ,ZZZ,ZZZ,ZZ9 | BY57: Z,ZZZ,ZZZ,ZZZ,ZZ9 | CI57: Z,ZZZ,ZZZ,ZZZ,ZZ9 | CS57: Z,ZZZ,ZZZ,ZZZ,ZZ9 | DC57: Z,ZZZ,ZZZ,ZZZ,ZZ9 | DM57: ZZZZ.9
A58: =A57+1 -> 49 | AK58: Z,ZZZ,ZZZ,ZZZ.ZZ9 | AU58: Z,ZZZ,ZZZ,ZZZ.ZZ9 | BE58: Z,ZZZ,ZZZ,ZZZ.ZZ9 | BO58: Z,ZZZ,ZZZ,ZZZ.ZZ9 | BY58: Z,ZZZ,ZZZ,ZZZ.ZZ9 | CI58: Z,ZZZ,ZZZ,ZZZ.ZZ9 | CS58: Z,ZZZ,ZZZ,ZZZ,ZZ9 | DC58: Z,ZZZ,ZZZ,ZZZ,ZZ9 | DM58: ZZZZ.9
A59: =A58+1 -> 50 | AK59: Z,ZZZ,ZZZ,ZZZ,ZZ9 | AU59: Z,ZZZ,ZZZ,ZZZ,ZZ9 | BE59: Z,ZZZ,ZZZ,ZZZ,ZZ9 | BO59: Z,ZZZ,ZZZ,ZZZ,ZZ9 | BY59: Z,ZZZ,ZZZ,ZZZ,ZZ9 | CI59: Z,ZZZ,ZZZ,ZZZ,ZZ9 | CS59: Z,ZZZ,ZZZ,ZZZ,ZZ9 | DC59: Z,ZZZ,ZZZ,ZZZ,ZZ9 | DM59: ZZZZ.9
A60: =A59+1 -> 51
A61: =A60+1 -> 52
A62: =A61+1 -> 53
A63: =A62+1 -> 54
A64: =A63+1 -> 55
A65: =A64+1 -> 56
A66: =A65+1 -> 57
A67: =A66+1 -> 58
A68: =A67+1 -> 59
A69: =A68+1 -> 60
A70: =A69+1 -> 61
A71: =A70+1 -> 62
... A75: =A74+1 -> 66

Sheet 1.帳票イメージ
A1: Ｐｈａｓｅ 外部設計工程 | EC1: HOKUREN INTERNAL USE ONLY
A2: 帳 票 レ イ ア ウ ト
A3: システム名 | L3: 統合会計システム | CR3: 様 式 № | DB3: F4109-1 | DK3: ＰＡＧＥ
A4: 業務名 | L4: 部門提供 | CR4: 作成日 | DB4: 2025/8/29 | DK4: 更新日
A6: 帳 票 名 | L6: 販売品勘定整理帳
A7: 0 | K7: 1 | U7: 2 | AE7: 3 | AO7: 4 | AY7: 5 | BI7: 6 | BS7: 7 | CC7: 8 | CM7: 9 | CW7: 0 | DG7: 1 | DQ7: 2 | EA7: 3
A8: 0 | B8: =(A8+1) -> 1 | C8: =(B8+1) -> 2 | D8: =(C8+1) -> 3 | E8: =(D8+1) -> 4 | F8: =(E8+1) -> 5 | G8: =(F8+1) -> 6 | H8: =(G8+1) -> 7 | I8: =(H8+1) -> 8 | J8: =(I8+1) -> 9 | K8: 0 | L8: =(K8+1) -> 1 | M8: =(L8+1) -> 2 | N8: =(M8+1) -> 3 | O8: =(N8+1) -> 4 | P8: =(O8+1) -> 5 | Q8: =(P8+1) -> 6 | R8: =(Q8+1) -> 7 | S8: =(R8+1) -> 8 | T8: =(S8+1) -> 9 | U8: 0 | V8: =(U8+1) -> 1 | W8: =(V8+1) -> 2 | X8: =(W8+1) -> 3 | Y8: =(X8+1) -> 4 | Z8: =(Y8+1) -> 5 | AA8: =(Z8+1) -> 6 | AB8: =(AA8+1) -> 7 | AC8: =(AB8+1) -> 8 | AD8: =(AC8+1) -> 9 | AE8: 0 | AF8: =(AE8+1) -> 1 | AG8: =(AF8+1) -> 2 | AH8: =(AG8+1) -> 3 | AI8: =(AH8+1) -> 4 | AJ8: =(AI8+1) -> 5 | AK8: =(AJ8+1) -> 6 | AL8: =(AK8+1) -> 7 | AM8: =(AL8+1) -> 8 | AN8: =(AM8+1) -> 9 | AO8: 0 | AP8: =(AO8+1) -> 1 | AQ8: =(AP8+1) -> 2 | AR8: =(AQ8+1) -> 3 | AS8: =(AR8+1) -> 4 | AT8: =(AS8+1) -> 5 | AU8: =(AT8+1) -> 6 | AV8: =(AU8+1) -> 7 | AW8: =(AV8+1) -> 8 | AX8: =(AW8+1) -> 9 | AY8: 0 | AZ8: =(AY8+1) -> 1 | BA8: =(AZ8+1) -> 2 | BB8: =(BA8+1) -> 3 | BC8: =(BB8+1) -> 4 | BD8: =(BC8+1) -> 5 | BE8: =(BD8+1) -> 6 | BF8: =(BE8+1) -> 7 | BG8: =(BF8+1) -> 8 | BH8: =(BG8+1) -> 9 | BI8: 0 | BJ8: =(BI8+1) -> 1 | BK8: =(BJ8+1) -> 2 | BL8: =(BK8+1) -> 3 | BM8: =(BL8+1) -> 4 | BN8: =(BM8+1) -> 5 | BO8: =(BN8+1) -> 6 | BP8: =(BO8+1) -> 7 | BQ8: =(BP8+1) -> 8 | BR8: =(BQ8+1) -> 9 | BS8: 0 | BT8: =(BS8+1) -> 1 | BU8: =(BT8+1) -> 2 | BV8: =(BU8+1) -> 3 | BW8: =(BV8+1) -> 4 | BX8: =(BW8+1) -> 5 | BY8: =(BX8+1) -> 6 | BZ8: =(BY8+1) -> 7 | CA8: =(BZ8+1) -> 8 | CB8: =(CA8+1) -> 9 | CC8: 0 | CD8: =(CC8+1) -> 1 | CE8: =(CD8+1) -> 2 | CF8: =(CE8+1) -> 3 | CG8: =(CF8+1) -> 4 | CH8: =(CG8+1) -> 5 | CI8: =(CH8+1) -> 6 | CJ8: =(CI8+1) -> 7 | CK8: =(CJ8+1) -> 8 | CL8: =(CK8+1) -> 9 | CM8: 0 | CN8: =(CM8+1) -> 1 | CO8: =(CN8+1) -> 2 | CP8: =(CO8+1) -> 3 | CQ8: =(CP8+1) -> 4 | CR8: =(CQ8+1) -> 5 | CS8: =(CR8+1) -> 6 | CT8: =(CS8+1) -> 7 | CU8: =(CT8+1) -> 8 | CV8: =(CU8+1) -> 9 | CW8: 0 | CX8: =(CW8+1) -> 1 | CY8: =(CX8+1) -> 2 | CZ8: =(CY8+1) -> 3 | DA8: =(CZ8+1) -> 4 | DB8: =(DA8+1) -> 5 | DC8: =(DB8+1) -> 6 | DD8: =(DC8+1) -> 7 | DE8: =(DD8+1) -> 8 | DF8: =(DE8+1) -> 9 | DG8: 0 | DH8: =(DG8+1) -> 1 | DI8: =(DH8+1) -> 2 | DJ8: =(DI8+1) -> 3 | DK8: =(DJ8+1) -> 4 | DL8: =(DK8+1) -> 5 | DM8: =(DL8+1) -> 6 | DN8: =(DM8+1) -> 7 | DO8: =(DN8+1) -> 8 | DP8: =(DO8+1) -> 9 | DQ8: 0 | DR8: =(DQ8+1) -> 1 | DS8: =(DR8+1) -> 2 | DT8: =(DS8+1) -> 3 | DU8: =(DT8+1) -> 4 | DV8: =(DU8+1) -> 5 | DW8: =(DV8+1) -> 6 | DX8: =(DW8+1) -> 7 | DY8: =(DX8+1) -> 8 | DZ8: =(DY8+1) -> 9 | EA8: 0 | EB8: =(EA8+1) -> 1 | EC8: =(EB8+1) -> 2
A9: =A8+1 -> 1 | AX9: ＊販売品勘定整理帳＊ | BZ9: 2025年03月03日 | CW9: 2025/03/03 00:00:00 | DK9: PAGE： 1
A10: =A9+1 -> 2 | DL10: （1）
A11: =A10+1 -> 3 | F11: 業種 | N11: 31 | R11: 飼料
A12: =A11+1 -> 4 | F12: 受払組織 | N12: 1 | R12: 函館支所 | AL12: 212 | AP12: 酪農畜産課
A13: =A12+1 -> 5 | F13: 出力年月日 | N13: 2025年03月03日 | CF13: 上段：日計 ／ 中段：月計 ／ 下段：累計 単位：円
A14: =A12+1 -> 5 | D14: 商品名 | AK14: 借方 | BE14: 貸方 | BY14: 残高 | CS14: 売上金額 手数料 | DC14: 費用 純益 | DM14: 手数料率 純益率
A15: =A14+1 -> 6 | AF15: 単位
A16: =A15+1 -> 7 | D16: 出力制御 | AK16: 数量（分子） 数量（仮数） | AU16: 単価 金額 | BE16: 数量（分子） 数量（仮数） | BO16: 単価 売上原価 | BY16: 数量（分子） 数量（仮数） | CI16: 単価 金額
A17: =A16+1 -> 8 | D17: (収支管理品目） | L17: 年産 | AD17: （取扱）
A18: =A17+1 -> 9 | D18: 原卵
A19: =A18+1 -> 10 | AD19: Ｋｇ | AU19: -4 | BO19: -4 | CS19: 4 | DC19: 4
A20: =A19+1 -> 11 | D20: 131216
A21: =A20+1 -> 12 | D21: （006000） | AC21: （買取） | AU21: -78 | BO21: -78 | CS21: 78 | DC21: 78
A22: =A21+1 -> 13 | CI22: 165.41
A23: =A22+1 -> 14 | AU23: -41,150 | BO23: -41,150 | CS23: 41150 | DC23: 41150
A24: =A23+1 -> 15 | D24: 破卵 | AU24: 108.35 | BO24: 120.09 | CS24: 105850 | DM24: 15.2
A25: =A24+1 -> 16 | AD25: Ｋｇ | AK25: 222 | AU25: 24054 | BE25: 820 | BO25: 89803 | CS25: 16047 | DC25: 16047 | DM25: 15.2
A26: =A25+1 -> 17 | D26: 131217 | AU26: 107.55 | BE26: .600 | BO26: 126.97 | CS26: 822105 | DM26: 15.3
A27: =A26+1 -> 18 | D27: （006003） | AC27: （買取） | AK27: 6786 | AU27: 729824 | BE27: 6474 | BO27: 696246 | CS27: 125859 | DC27: 125859 | DM27: 15.3
A28: =A27+1 -> 19 | AK28: .600 | AU28: 113.14 | BE28: .800 | BO28: 135.86 | BY28: .800 | CI28: 110.05 | CS28: 3546376 | DM28: 16.7
A29: =A28+1 -> 20 | AK29: 26477 | AU29: 2995648 | BE29: 26103 | BO29: 2954511 | BY29: 373 | CI29: 41137 | CS29: 591865 | DC29: 591865 | DM29: 16.7
A30: =A29+1 -> 21 | D30: 正卵Ｄ／Ｂ | AU30: 184.62 | BO30: 181.38 | CS30: 913225 | DM30: 3.8
A31: =A30+1 -> 22 | AD31: Ｋｇ | AK31: 1795 | AU31: 331384 | BE31: 5035 | BO31: 878660 | CS31: 34565 | DC31: 34565 | DM31: 3.8
A32: =A31+1 -> 23 | D32: 131218 | AU32: 166.72 | BO32: 177.53 | CS32: 11103084 | DM32: 5.7
A33: =A32+1 -> 24 | D33: （006005） | AC33: （買取） | AK33: 60181 | AU33: 10033549 | BE33: 62541 | BO33: 10471963 | CS33: 631121 | DC33: 631121 | DM33: 5.7
A34: =A33+1 -> 25 | AU34: 179.36 | BO34: 190.67 | CI34: 169.23 | CS34: 48822185 | DM34: 5.9
A35: =A34+1 -> 26 | AK35: 256776 | AU35: 46055204 | BE35: 256056 | BO35: 45933358 | BY35: 720 | CI35: 121846 | CS35: 2888827 | DC35: 2888827 | DM35: 5.9
A36: =A35+1 -> 27 | D36: 特殊卵Ｄ／Ｂ | AU36: 191.87
A37: =A36+1 -> 28 | AD37: Ｋｇ | AK37: -350 | AU37: -67,155 | BO37: -1,944 | CS37: 1944 | DC37: 1944
A38: =A37+1 -> 29 | D38: 131219
A39: =A38+1 -> 30 | D39: （006007） | AC39: （買取） | AU39: -1,944 | BO39: -1,944 | CS39: 1944 | DC39: 1944
A40: =A39+1 -> 31 | CI40: 191.87
A41: =A40+1 -> 32 | AU41: 59681 | BO41: 59681 | CS41: -59,681 | DC41: -59,681
A42: =A41+1 -> 33 | D42: 化粧箱卵 | AK42: .160 | AU42: 184.90 | BO42: 290.71 | CS42: 61676 | DM42: 36.4
A43: =A42+1 -> 34 | AD43: Ｋｇ | AK43: 212 | AU43: 39229 | BO43: 39229 | CS43: 22447 | DC43: 22447 | DM43: 36.4
A44: =A43+1 -> 35 | D44: 131220 | AK44: .280 | AU44: 190.14 | BO44: 245.64 | CS44: 145244 | DM44: 22.6
A45: =A44+1 -> 36 | D45: （006017） | AC45: （買取） | AK45: 591 | AU45: 112427 | BO45: 112427 | CS45: 32817 | DC45: 32817 | DM45: 22.6
A46: =A45+1 -> 37 | AK46: .180 | AU46: 210.65 | BO46: 232.85 | CI46: 190.14 | CS46: 1180120 | DM46: 9.5
A47: =A46+1 -> 38 | AK47: 5068 | AU47: 1067608 | BO47: 1067608 | CS47: 112512 | DC47: 112512 | DM47: 9.5
A48: =A47+1 -> 39 | D48: パック卵 ＬＬ | AK48: .680 | AU48: 179.37 | BE48: .680 | BO48: 182.19 | CS48: 2128 | DM48: 1.6
A49: =A48+1 -> 40 | AD49: Ｋｇ | AK49: 11 | AU49: 2095 | BE49: 11 | BO49: 2095 | CS49: 33 | DC49: 33 | DM49: 1.6
A50: =A49+1 -> 41 | D50: 131221 | AK50: .620 | AU50: 174.43 | BE50: .620 | BO50: 181.10 | CS50: 256362 | DM50: 3.7
A51: =A50+1 -> 42 | D51: （006009） | T51: （買取） | AK51: 1415 | AU51: 246932 | BE51: 1415 | BO51: 246932 | CS51: 9430 | DC51: 9430 | DM51: 3.7
A52: =A51+1 -> 43 | AK52: .960 | AU52: 193.64 | BE52: .960 | BO52: 193.53 | CI52: 174.43 | CS52: 932793 | DM52: -.1
A53: =A52+1 -> 44 | AK53: 4819 | AU53: 933349 | BE53: 4819 | BO53: 933349 | CS53: -556 | DC53: -556 | DM53: -.1
A54: =A53+1 -> 45
A55: =A54+1 -> 46
A56: =A55+1 -> 47
A57: =A56+1 -> 48
A58: =A57+1 -> 49
A59: =A58+1 -> 50
A60: =A59+1 -> 51
A61: =A60+1 -> 52
A62: =A61+1 -> 53
A63: =A62+1 -> 54
A64: =A63+1 -> 55
A65: =A64+1 -> 56
... A75: =A74+1 -> 66

Sheet 2.条件表
A1: Ｐｈａｓｅ 外部設計工程 | BJ1: HOKUREN INTERNAL USE ONLY
A2: 帳票説明書 （作成条件表） | AV2: 様式No. | AZ2: F4109-2 | BD2: PAGE
A3: システム名 | H3: 統合会計システム | AV3: 作成日 | AZ3: 2025/8/29
A4: 業務名 | H4: 部門提供 | AV4: 更新日 | AZ4: =IF(ISBLANK(変更履歴!AZ4),"",変更履歴!AZ4)
A6: 機能Ｎｏ． | H6: 8.6.3 | P6: 帳票名 | Y6: 販売品勘定整理帳 | AV6: データストア№ | BD6: D08060302
A8: 【帳票 用途】
E9: １．販売品の受払実績を把握する。
E10: ２．画面より随時で出力可能とし、日計・月計・累計の３段で出力する。
A12: 作成処理 概要 | G12: 入力ファイル ： | AE12: 対象とするデータの条件 ：
H13: D07080102 | AF13: 勘定整理帳情報照会にて帳票出力対象と選択された
I14: 販売品勘定整理帳 | AF14: 販売品データを対象とする。
G15: 留意事項：
H16: なし
A20: 帳票ＩＤ
A21: 印刷箇所 | H21: □ | J21: センター印刷（ 1 部） | AE21: 印刷装置 | AM21: ■ | AO21: レーザープリンター
H22: ■ | J22: オンライン印刷（ ） | AM22: □ | AO22: インパクトプリンター
H23: □ | J23: その他 | AM23: □ | AO23: その他
J24: （ | AB24: ） | AO24: （ | BI24: ）
A25: 印刷用紙 | H25: ■ | J25: Ａ４カット紙 | AE25: 作成サイクル | AM25: 随時 | AW25: 帳票管理ｓ 保管 | BC25: 世代数
H26: □ | J26: 連続用紙 | O26: （ | R26: ｲﾝﾁx | AC26: ｲﾝﾁ | AD26: ）
H27: □ | J27: 定型用紙 | O27: （ | AD27: ） | AE27: センター印刷時 配布箇所 | BC27: 期間日数 | BG27: 10年
H28: □ | J28: その他 | O28: （ | AD28: ）
A29: 印字サイズ | AE29: 処理タイプ | AM29: □ | AO29: バッチ | AS29: （ 日中 ・ 夜間 ）
H30: 132 | P30: 桁 | AM30: ■ | AO30: オンライン画面起動
H31: 66 | P31: 行 | AM31: □ | AO31: その他 | AS31: （ | BI31: ）
A34: ページ番号 採番条件 | H34: □ | J34: 一連番号で採番（１から連番） | AK34: □ | AM34: ページ番号印字なし
H35: ■ | J35: ページ番号採番条件あり
J36: 受払組織毎に１から連番
J37: 下段の括弧内に１からの連番も印字
A38: 改ページ条件 | H38: １．明細行を44行印字した場合
H39: ２．業種、受払組織、会計情報品目が変わった場合
A42: １ページ 明細数 | G42: 44行
A44: 入力ファイルソートキー （明細印字順） | G44: 1: | I44: 業種 | AH44: 昇順／降順 | AJ44: 10: | BI44: 昇順／降順
G45: 2: | I45: 受払組織 | AH45: 昇順／降順 | AJ45: 11: | BI45: 昇順／降順
G46: 3: | I46: 会計情報品目 | AH46: 昇順／降順 | AJ46: 12: | BI46: 昇順／降順
G47: 4: | I47: 収支管理品目大分類 | AH47: 昇順／降順 | AJ47: 13: | BI47: 昇順／降順
G48: 5: | I48: 出力制御CD | AH48: 昇順／降順 | AJ48: 14: | BI48: 昇順／降順
G49: 6: | I49: 収支管理品目 | AH49: 昇順／降順 | AJ49: 15: | BI49: 昇順／降順
G50: 7: | I50: 年産 | AH50: 昇順／降順 | AJ50: 16: | BI50: 昇順／降順
G51: 8: | AH51: 昇順／降順 | AJ51: 17: | BI51: 昇順／降順
G52: 9: | AH52: 昇順／降順 | AJ52: 18: | BI52: 昇順／降順
A54: 合計等 印字条件 明細行の合計計算、合計行の集計計算等について記載する。
H55: １．収支管理品目（大）計 | U55: 明細印字順１～４のいずれかが変わった場合
H56: ２．会計情報品目計 | U56: 明細印字順１～３のいずれかが変わった場合
H57: ３．受払組織計 | U57: 明細印字順１～２のいずれかが変わった場合
H58: ４．業種計 | U58: 明細印字順１が変わった場合

Sheet 3.項目説明
A1: Ｐｈａｓｅ 外部設計工程 | BJ1: HOKUREN INTERNAL USE ONLY
A2: 帳票説明書 （項目説明） | AV2: 様式No. | AZ2: F4109-3 | BD2: PAGE
A3: システム名 | H3: 統合会計システム | AV3: 作成日 | AZ3: 2025/8/29
A4: 業務名 | H4: 部門提供 | AV4: 更新日 | AZ4: =IF(ISBLANK(変更履歴!AZ4),"",変更履歴!AZ4)
A6: 機能Ｎｏ． | H6: ='2.条件表'!H6 -> 8.6.3 | P6: 帳票名 | Y6: ='2.条件表'!Y6 -> 販売品勘定整理帳 | AV6: データストア№ | BD6: ='2.条件表'!BD6 -> D08060302
A8: № | D8: 項目名 | R8: 桁数 | U8: 編集パターン | AE8: 項目編集説明
D9: 【ヘッダ】
A10: 1 | D10: 帳票ID | R10: 6 | U10: XXXXXX | AE10: 帳票ID
A11: 2 | D11: 帳票タイトル | R11: 10 | U11: 全角10文字 | AE11: 帳票タイトル
A12: 3 | D12: 基準年月日 | R12: 11 | U12: YYYY年MM月DD日 | AE12: 作成基準の年月日
A13: 4 | D13: 作成日 | R13: 10 | U13: 9999/Z9/Z9 | AE13: 作成年月日
A14: 5 | D14: 作成時刻 | R14: 8 | U14: HH:MM:SS | AE14: 作成時刻
A15: 6 | D15: ページ数 | R15: 5 | U15: Z,ZZ9 | AE15: ページ連番。初期値１
A16: 7 | D16: 合計ページ数 | R16: 6 | U16: ZZ,ZZ9 | AE16: ページの合計
A17: 8 | D17: 業種コード | R17: 2 | U17: XX | AE17: 業種コード
A18: 9 | D18: 業種名称 | R18: 15 | U18: 全角15文字 | AE18: 業種コードに対する名称
A19: 10 | D19: 事業所コード | R19: 2 | U19: XX | AE19: 事業所コード
A20: 11 | D20: 事業所名称 | R20: 15 | U20: 全角15文字 | AE20: 事業所コードに対する名称
A21: 12 | D21: 組織コード | R21: 4 | U21: XXXX | AE21: "4"+課コード
... A23: 14 | D23: 出力年月日 | R23: 11 | U23: YYYY年MM月DD日 | AE23: 出力年月日
D24: 【明細】
A25: 15 | D25: 商品名 | R25: 25 | U25: 全角25文字 | AE25: 収支管理品目の名称
A26: 16 | D26: 単位 | R26: 4 | U26: 全角4文字 | AE26: 数量単位の名称
A27: 17 | D27: 出力制御CD | R27: 6 | U27: XXXXXX | AE27: 出力制御CD
A28: 18 | D28: 収支管理品目コード | R28: 6 | U28: XXXXXX | AE28: 収支管理品目コード
A29: 19 | D29: 年産 | R29: 4 | U29: XXXX | AE29: 年産
A30: 20 | D30: 取扱区分 | R30: 4 | U30: 全角4文字 | AE30: 取扱区分(「買取」「受託」「直送」「原料」)
A31: 21 | D31: 借方-数量（分子） | R31: 14,3 | U31: -Z,ZZZ,ZZZ,ZZZ.ZZ9 | AE31: 借方数量（分子）
A32: 22 | D32: 借方-数量（仮数） | R32: 14 | U32: -Z,ZZZ,ZZZ,ZZZ,ZZ9 | AE32: 借方数量（仮数）
A33: 23 | D33: 借方-単価 | R33: 14,3 | U33: -Z,ZZZ,ZZZ,ZZZ.ZZ9 | AE33: 借方単価
A34: 24 | D34: 借方-金額 | R34: 18 | U34: -Z,ZZZ,ZZZ,ZZZ,ZZ9 | AE34: 借方金額
A35: 25 | D35: 貸方-数量（分子） | R35: 14,3 | U35: -Z,ZZZ,ZZZ,ZZZ.ZZ9 | AE35: 貸方数量（分子）
A36: 26 | D36: 貸方-数量（仮数） | R36: 14 | U36: -Z,ZZZ,ZZZ,ZZZ,ZZ9 | AE36: 貸方数量（仮数）
A37: 27 | D37: 貸方-単価 | R37: 14,3 | U37: -Z,ZZZ,ZZZ,ZZZ.ZZ9 | AE37: 貸方単価
A38: 28 | D38: 貸方-売上原価 | R38: 18 | U38: -Z,ZZZ,ZZZ,ZZZ,ZZ9 | AE38: 貸方売上原価
A39: 29 | D39: 残高-数量（分子） | R39: 14,3 | U39: -Z,ZZZ,ZZZ,ZZZ.ZZ9 | AE39: 残高数量（分子）
A40: 30 | D40: 残高-数量（仮数） | R40: 14 | U40: -Z,ZZZ,ZZZ,ZZZ,ZZ9 | AE40: 残高数量（仮数）
A41: 31 | D41: 残高-単価 | R41: 14,3 | U41: -Z,ZZZ,ZZZ,ZZZ.ZZ9 | AE41: 残高単価
A42: 32 | D42: 残高-金額 | R42: 18 | U42: -Z,ZZZ,ZZZ,ZZZ,ZZ9 | AE42: 残高金額
A43: 33 | D43: 売上金額 | R43: 18 | U43: -Z,ZZZ,ZZZ,ZZZ,ZZ9 | AE43: 売上金額
A44: 34 | D44: 手数料 | R44: 18 | U44: -Z,ZZZ,ZZZ,ZZZ,ZZ9 | AE44: 手数料
A45: 35 | D45: 費用 | R45: 18 | U45: -Z,ZZZ,ZZZ,ZZZ,ZZ9 | AE45: 費用
A46: 36 | D46: 純益 | R46: 18 | U46: -Z,ZZZ,ZZZ,ZZZ,ZZ9 | AE46: 純益
A47: 37 | D47: 手数料率 | R47: 4,1 | U47: ZZZZ.9 | AE47: 手数料率
A48: 38 | D48: 純益率 | R48: 4,1 | U48: ZZZZ.9 | AE48: 純益率
D49: 【収支管理品目（大）計】
A50: 39 | D50: 商品名 | R50: 25 | U50: 全角25文字 | AE50: 収支管理品目大分類名
A51: 40 | D51: 収支管理品目コード | R51: 6 | U51: XXXXXX | AE51: 収支管理品目大分類コード
A52: 41 | D52: 年産 | R52: 4 | U52: XXXX | AE52: 年産
A53: 42 | D53: 合計行タイトル | R53: 8 | U53: 全角8文字 | AE53: 「＊収支管理品目（大）計」
A54: 43 | D54: 借方-数量（分子） | R54: 14,3 | U54: -Z,ZZZ,ZZZ,ZZZ.ZZ9 | AE54: 借方数量（分子）
A55: 44 | D55: 借方-数量（仮数） | R55: 14 | U55: -Z,ZZZ,ZZZ,ZZZ,ZZ9 | AE55: 借方数量（仮数）
A56: 45 | D56: 借方-単価 | R56: 14,3 | U56: -Z,ZZZ,ZZZ,ZZZ.ZZ9 | AE56: 借方単価
A57: 46 | D57: 借方-金額 | R57: 18 | U57: -Z,ZZZ,ZZZ,ZZZ,ZZ9 | AE57: 借方金額
A58: 47 | D58: 貸方-数量（分子） | R58: 14,3 | U58: -Z,ZZZ,ZZZ,ZZZ.ZZ9 | AE58: 貸方数量（分子）
A59: 48 | D59: 貸方-数量（仮数） | R59: 14 | U59: -Z,ZZZ,ZZZ,ZZZ,ZZ9 | AE59: 貸方数量（仮数）
A60: 49 | D60: 貸方-単価 | R60: 14,3 | U60: -Z,ZZZ,ZZZ,ZZZ.ZZ9 | AE60: 貸方単価
A61: 50 | D61: 貸方-売上原価 | R61: 18 | U61: -Z,ZZZ,ZZZ,ZZZ,ZZ9 | AE61: 貸方売上原価
A62: 51 | D62: 残高-数量（分子） | R62: 14,3 | U62: -Z,ZZZ,ZZZ,ZZZ.ZZ9 | AE62: 残高数量（分子）
A63: 52 | D63: 残高-数量（仮数） | R63: 14 | U63: -Z,ZZZ,ZZZ,ZZZ,ZZ9 | AE63: 残高数量（仮数）
A64: 53 | D64: 残高-単価 | R64: 14,3 | U64: -Z,ZZZ,ZZZ,ZZZ.ZZ9 | AE64: 残高単価
A65: 54 | D65: 残高-金額 | R65: 18 | U65: -Z,ZZZ,ZZZ,ZZZ,ZZ9 | AE65: 残高金額
A66: 55 | D66: 売上金額 | R66: 18 | U66: -Z,ZZZ,ZZZ,ZZZ,ZZ9 | AE66: 売上金額
A67: 56 | D67: 手数料 | R67: 18 | U67: -Z,ZZZ,ZZZ,ZZZ,ZZ9 | AE67: 手数料
A68: 57 | D68: 費用 | R68: 18 | U68: -Z,ZZZ,ZZZ,ZZZ,ZZ9 | AE68: 費用
A69: 58 | D69: 純益 | R69: 18 | U69: -Z,ZZZ,ZZZ,ZZZ,ZZ9 | AE69: 純益
A70: 59 | D70: 手数料率 | R70: 4,1 | U70: ZZZZ.9 | AE70: 手数料率
A71: 60 | D71: 純益率 | R71: 4,1 | U71: ZZZZ.9 | AE71: 純益率
D72: 【会計情報品目計】
A73: 61 | D73: 商品名 | R73: 25 | U73: 全角25文字 | AE73: 会計情報品目名
A74: 62 | D74: 収支管理品目コード | R74: 6 | U74: XXXXXX | AE74: 会計情報品目コード
A75: 63 | D75: 合計行タイトル | R75: 8 | U75: 全角8文字 | AE75: 「＊＊会計情報品目計」
A76: 64 | D76: 借方-数量（分子） | R76: 14,3 | U76: -Z,ZZZ,ZZZ,ZZZ.ZZ9 | AE76: 借方数量（分子）
A77: 65 | D77: 借方-数量（仮数） | R77: 14 | U77: -Z,ZZZ,ZZZ,ZZZ,ZZ9 | AE77: 借方数量（仮数）
A78: 66 | D78: 借方-単価 | R78: 14,3 | U78: -Z,ZZZ,ZZZ,ZZZ.ZZ9 | AE78: 借方単価
A79: 67 | D79: 借方-金額 | R79: 18 | U79: -Z,ZZZ,ZZZ,ZZZ,ZZ9 | AE79: 借方金額
A80: 68 | D80: 貸方-数量（分子） | R80: 14,3 | U80: -Z,ZZZ,ZZZ,ZZZ.ZZ9 | AE80: 貸方数量（分子）
A81: 69 | D81: 貸方-数量（仮数） | R81: 14 | U81: -Z,ZZZ,ZZZ,ZZZ,ZZ9 | AE81: 貸方数量（仮数）
A82: 70 | D82: 貸方-単価 | R82: 14,3 | U82: -Z,ZZZ,ZZZ,ZZZ.ZZ9 | AE82: 貸方単価
A83: 71 | D83: 貸方-売上原価 | R83: 18 | U83: -Z,ZZZ,ZZZ,ZZZ,ZZ9 | AE83: 貸方売上原価
A84: 72 | D84: 残高-数量（分子） | R84: 14,3 | U84: -Z,ZZZ,ZZZ,ZZZ.ZZ9 | AE84: 残高数量（分子）
A85: 73 | D85: 残高-数量（仮数） | R85: 14 | U85: -Z,ZZZ,ZZZ,ZZZ,ZZ9 | AE85: 残高数量（仮数）
A86: 74 | D86: 残高-単価 | R86: 14,3 | U86: -Z,ZZZ,ZZZ,ZZZ.ZZ9 | AE86: 残高単価
A87: 75 | D87: 残高-金額 | R87: 18 | U87: -Z,ZZZ,ZZZ,ZZZ,ZZ9 | AE87: 残高金額
A88: 76 | D88: 売上金額 | R88: 18 | U88: -Z,ZZZ,ZZZ,ZZZ,ZZ9 | AE88: 売上金額
A89: 77 | D89: 手数料 | R89: 18 | U89: -Z,ZZZ,ZZZ,ZZZ,ZZ9 | AE89: 手数料
A90: 78 | D90: 費用 | R90: 18 | U90: -Z,ZZZ,ZZZ,ZZZ,ZZ9 | AE90: 費用
A91: 79 | D91: 純益 | R91: 18 | U91: -Z,ZZZ,ZZZ,ZZZ,ZZ9 | AE91: 純益
A92: 80 | D92: 手数料率 | R92: 4,1 | U92: ZZZZ.9 | AE92: 手数料率
A93: 81 | D93: 純益率 | R93: 4,1 | U93: ZZZZ.9 | AE93: 純益率
D94: 【受払組織計】
A95: 82 | D95: 合計行タイトル | R95: 7 | U95: 全角7文字 | AE95: 「＊＊＊受払組織計」
A96: 83 | D96: 借方-数量（分子） | R96: 14,3 | U96: -Z,ZZZ,ZZZ,ZZZ.ZZ9 | AE96: 借方数量（分子）
A97: 84 | D97: 借方-数量（仮数） | R97: 14 | U97: -Z,ZZZ,ZZZ,ZZZ,ZZ9 | AE97: 借方数量（仮数）
A98: 85 | D98: 借方-単価 | R98: 14,3 | U98: -Z,ZZZ,ZZZ,ZZZ.ZZ9 | AE98: 借方単価
A99: 86 | D99: 借方-金額 | R99: 18 | U99: -Z,ZZZ,ZZZ,ZZZ,ZZ9 | AE99: 借方金額
A100: 87 | D100: 貸方-数量（分子） | R100: 14,3 | U100: -Z,ZZZ,ZZZ,ZZZ.ZZ9 | AE100: 貸方数量（分子）
A101: 88 | D101: 貸方-数量（仮数） | R101: 14 | U101: -Z,ZZZ,ZZZ,ZZZ,ZZ9 | AE101: 貸方数量（仮数）
A102: 89 | D102: 貸方-単価 | R102: 14,3 | U102: -Z,ZZZ,ZZZ,ZZZ.ZZ9 | AE102: 貸方単価
A103: 90 | D103: 貸方-売上原価 | R103: 18 | U103: -Z,ZZZ,ZZZ,ZZZ,ZZ9 | AE103: 貸方売上原価
...
