Workbook
Name 【債権】最新データ辞書: #REF!
Name ステータスリスト: #REF!
Name 形式: #REF!
Name 項目辞書: #REF!
Name 項目辞書: #REF!
Name 重要度リスト: #REF!
Name 媒体: #REF!
Name 分類リスト: #REF!
Name 連携方法: #REF!

Sheet 表紙
F46: ProActive
B48: 変更履歴
B50: 項番 | C50: 変更発生日 | D50: 変更者 | E50: 変更箇所 | F50: 変更内容
B51: 1 | C51: 45898 | D51: SCSK位田 | F51: 新規作成
B52: 2
B53: 3
B54: 4
B55: 5
B56: 6
B57: 7
B58: 8
B59: 9
B60: 10
B61: 11
B62: 12
B63: 13
... B80: 30

Sheet 業務機能概要
A1: ドキュメント名 | L1: サブシステム | Q1: 業務機能名 | AJ1: 作成者 | AO1: =表紙!D51 -> SCSK位田 | AT1: 更新者
A2: 業務機能概要書 | G2: 業務機能概要 | L2: 業務共通 | Q2: 取引先マスタ自動取込 | AJ2: 作成日付 | AO2: =表紙!C51 -> 45898 | AT2: 更新日付
B4: 【目的・役割】
C5: ・ | D5: ホクレン様のシステムでは、伝票入力は部門システムやスクラッチ開発する機能で実施し、また、マスタ情報の管理も共通マスタや会計マスタのマスタ管理システムで実施する。
D6: このため、ProActiveC4では、仕訳、支払などの業務データや組織、勘定科目、取引先などのマスタ情報を外部のシステムから取込む必要がある。
D7: マスタデータは夜間処理にて、スクラッチ開発するマスタ（ProActiveC4外のシステム）の情報と同期をとる必要がある。
B10: 【利用者】
C11: ・ | D11: バッチ実行
B14: 【利用頻度】
C15: ・ | D15: 日次 | H15: ※ | I15: 取引先マスタを新規登録してすぐに、スクラッチで伝票入力することがあるため、日中連動も実施する。
B18: 【対象要件定義書】
C19: ・ | D19: 要件定義書(他システムとのデータ連動)
B22: 【処理概要】
C23: １) | D23: ファイルによってデータ連動される取引先、支払先（決済条件含む）の情報をProActiveC4標準の「取引先マスタ取込データ」の処理を使用してProActiveC4に取込む。
D24: バッチファイルで定義された取込ディレクトリに配置されている連動データ（取込用のCSVファイル）の情報を取得する。
D25: ※ | E25: 取引先は支払先ではない取引相手（仕訳上、科目の内訳情報として使用される取引相手先）と定義する
D26: ※ | E26: 取引先、支払先はそれぞれ別の連動データとして別ファイルで作成される想定
F27: 取引先取込ファイル | O27: ： | P27: TORISK_YYYYMMDDHHMMSSmmm.csv
F28: 支払先取込ファイル | O28: ： | P28: SHHARSK_YYYYMMDDHHMMSSmmm.csv
C31: ２) | D31: 1)で取得した取込ファイルをINPUTとして、取引先マスタ外部データ取込をバッチ実行する。（オンライン機能「取引先マスタ外部データ取込」の動作を踏襲する。）
D32: ※標準の取引先マスタ外部データ取込はオンライン処理可能なままとする
D34: 2-1. | F34: 取引先マスタ自動取込バッチ
F35: 標準機能の取引先外部データ取込をバッチダイレクトで実行する。（※取込対象を取引先として実行する）
D37: 2-2. | F37: 支払先マスタ自動取込バッチ
F38: 標準機能の取引先外部データ取込をバッチダイレクトで実行する。（※取込対象を支払先として実行する）
C40: 3) | D40: バッチ実行される取引先マスタ外部データ取込は、ProActiveC4外のタスク管理用のミドルウェア（以下、タスクスケジューラ）から実行する想定とする。
D41: 正常終了、対象データがない場合は、「異常なし」のステータスをタスクスケジューラに返却する。
D42: エラー終了の場合は、「エラーあり」のステータスをタスクスケジューラに返却する。
D45: [実行情報]
D46: No | F46: パラメータ | O46: 内容
D47: 1 | F47: ※イベント概要参照
D50: [終了情報]
D51: 戻り値 | F51: 内容 | O51: 内容
D52: 0 | F52: 正常終了
D53: 1 | F53: 異常終了 | O53: 業務エラー/システムエラー発生時 | AJ53: ※「補足1 取込結果判定」シート参照
B56: 【共通要件】
D57: 共通要件内容 | J57: 対応内容（標準準拠の場合、記載省略）
D58: セキュリティ | J58: 部門制限、本人制限の機能性は実装しない。
D59: 承認WF | J59: 対応なし。承認WFの利用は不可とする。
D60: 組織変更 | J60: 対応なし。当機能は仕訳に関係しないため、組織変更を考慮しない。
B63: 【前提・制約事項】
C64: １) | D64: ProActiveC4の各データの取込機能では、固定の取込フォーマットがあるため、該当するフォーマットに合わせて連動データが作成される前提とする。
D65: （データ作成は、連動元システムまたは、連動処理（ProActiveC4外）で実施する）
D66: ※ | E66: 取引先マスタ外部データ取込では、取込項目のタイトルの行も必要となる
C68: ２) | D68: ProActiveC4に連動されるデータ（CSVファイル）は、ProActiveC4のバッチサーバから参照可能な場所に配置されることを前提とする。
C70: ３) | D70: データ取込をバッチ実行した情報は、ProActiveC4標準の「バッチジョブ」として扱われ、「バッチジョブ状況一覧」機能で状況の確認が可能となる。
D71: 状況の確認は上記機能で実施する方針として、個別にエラーログ出力等の機能性は開発しない。
C73: ４) | D73: ProActiveC4標準の取引先外部データ取込処理をバッチ実行可能とする改修を実施するが、実行する取込処理は標準どおりとする。
D74: 以下のようなケースでは、標準の取込処理にも改修が必要となるため、別途対応工数を見積もることとする。
E75: ① | F75: 禁止文字の置き換え、エスケープ文字の考慮が取込処理側で必要となる（文字を置き換えした上で取込処理が必要となる）
C78: ５) | D78: 取引先マスタ情報は確定情報が連動されるため、取引先マスタの登録、取込時にはProActiveC4の承認機能は使用しない想定とする。
D79: （「承認システム設定」の「取引先取込」、「取引先支払先取込」については「承認WF使用」を使用しない設定としておく）
C81: ６) | D81: 取引先マスタの取込時には、マスタへの登録は即時反映する設定とする。
D82: （「会社情報設定」の「取引先外部取込設定」は「即時で反映する」と設定しておく）
C84: ７) | D84: 取引先マスタのデータは、差分連動の形式とする。このため、ProActiveC4側で取込処理前に登録済のデータの削除する処理は実施しない。
D85: 差分データは、①新規追加、②既存データの修正の2種類とし、業務上不要となったデータは「使用不可フラグ」を更新するため、②既存データの修正と同じ扱いとする。
C87: ８) | D87: 以下のProActiveC4禁止文字は連動ファイルにて使用しない前提とする。
E88: 禁止文字 | J88: 名称
E89: ― | J89: ダッシュ（全角）
E90: ∥ | J90: 双柱
E91: ￤ | J91: 破断線
C93: ９) | D93: ProActiveC4へ連動するファイルはコマンドにて移動等の操作を実施するため、ファイル名には空白を使用しない前提とする。
B96: 【主な取り扱い情報】
C97: ①バッチ実行時
D98: № | E98: 取り扱う情報 | O98: I/O | Q98: 用途
D99: 1 | E99: 取引先 | O99: OUT | Q99: 取引先マスタ情報を登録する。
D100: 2 | E100: 取引先外部取込履歴 | O100: OUT | Q100: 取引先マスタ取込の履歴を登録する。
D101: 3 | E101: 支払先 | O101: OUT | Q101: 取引先マスタ（支払先）情報を登録する。
D102: 4 | E102: 支払決済条件 | O102: OUT | Q102: 支払決済条件情報を登録する。
D103: 5 | E103: 支払決済期日 | O103: OUT | Q103: 支払決済条件情報を登録する。
D104: 6 | E104: バッチジョブ | O104: OUT | Q104: バッチ実行結果を反映する。
D105: 7 | E105: バッチジョブエラー | O105: OUT | Q105: バッチ実行結果を反映する。

Sheet 画面遷移図
A1: ドキュメント名 | L1: サブシステム | Q1: 業務機能名 | AJ1: 作成者 | AO1: =表紙!D51 -> SCSK位田 | AT1: 更新者 | AY1: SCSK相坂
A2: 業務機能概要書 | G2: 画面遷移図 | L2: =業務機能概要!L2 -> 業務共通 | Q2: =業務機能概要!Q2 -> 取引先マスタ自動取込 | AJ2: 作成日付 | AO2: =表紙!C51 -> 45898 | AT2: 更新日付 | AY2: 44103
B4: 【メニュー起動時の画面遷移】

Sheet 画面レイアウト
A1: ドキュメント名 | AH1: サブシステム | AX1: 業務機能名 | DF1: 作成者 | DV1: =表紙!D51 -> SCSK位田 | EL1: 更新者
A2: 業務機能概要書 | R2: 画面レイアウト | AH2: =業務機能概要!L2 -> 業務共通 | AX2: =業務機能概要!Q2 -> 取引先マスタ自動取込 | DF2: 作成日付 | DV2: =表紙!C51 -> 45898 | EL2: 更新日付
A3: 画面名 | FD3: 画面№ | FM3: ①
B4: 0 | H4: 40 | R4: 110 | AB4: 180 | AL4: 250 | AV4: 320 | BF4: 390 | BP4: 460 | BZ4: 530 | CJ4: 600 | CT4: 670 | DD4: 740 | DN4: 810 | DX4: 880 | EH4: 950 | EO4: 999 | ER4: ＜補足説明＞
A5: 0
A6: 5
A7: 20
A8: 35
A9: 50
A10: 65
A11: 80
A12: 95
A13: 110
A14: 125
A15: 140
A16: 155
... A47: 620
A57: 画面名 | J57: 自動消込確定情報登録画面 | FD57: 画面№ | FM57: ②
B58: 0 | H58: 40 | R58: 110 | AB58: 180 | AL58: 250 | AV58: 320 | BF58: 390 | BP58: 460 | BZ58: 530 | CJ58: 600 | CT58: 670 | DD58: 740 | DN58: 810 | DX58: 880 | EH58: 950 | EO58: 999 | ER58: ＜補足説明＞
A59: 0
A60: 5
A61: 20
A62: 35
A63: 50
A64: 65
A65: 80
A66: 95
A67: 110
A68: 125
A69: 140
A70: 155
... A101: 620
A111: 画面名 | FD111: 画面№ | FM111: ①
B112: 0 | H112: 40 | R112: 110 | AB112: 180 | AL112: 250 | AV112: 320 | BF112: 390 | BP112: 460 | BZ112: 530 | CJ112: 600 | CT112: 670 | DD112: 740 | DN112: 810 | DX112: 880 | EH112: 950 | EO112: 999 | ER112: ＜補足説明＞
A113: 0
A114: 5
A115: 20
A116: 35
A117: 50
A118: 65
A119: 80
A120: 95
A121: 110
A122: 125
A123: 140
A124: 155
... A155: 620
A165: 画面名 | FD165: 画面№ | FM165: ①
B166: 0 | H166: 40 | R166: 110 | AB166: 180 | AL166: 250 | AV166: 320 | BF166: 390 | BP166: 460 | BZ166: 530 | CJ166: 600 | CT166: 670 | DD166: 740 | DN166: 810 | DX166: 880 | EH166: 950 | EO166: 999 | ER166: ＜補足説明＞
A167: 0
A168: 5
A169: 20
A170: 35
A171: 50
A172: 65
A173: 80
A174: 95
A175: 110
A176: 125
A177: 140
A178: 155
... A209: 620
C221: 出力されるCSVファイル例

Sheet 項目概要
A1: ドキュメント名 | L1: サブシステム | Q1: 業務機能名 | AJ1: 作成者 | AO1: =表紙!D51 -> SCSK位田 | AT1: 更新者 | BE1: ○ | BF1: IN | BG1: 文字列
A2: 業務機能概要書 | G2: 項目概要 | L2: =業務機能概要!L2 -> 業務共通 | Q2: =業務機能概要!Q2 -> 取引先マスタ自動取込 | AJ2: 作成日付 | AO2: =表紙!C51 -> 45898 | AT2: 更新日付 | BE2: － | BF2: OUT | BG2: 数値
BF3: IN/OUT | BG3: 半英数
A4: 【画面項目説明】 | BG4: 半カナ
BG5: コード
B6: [①自動消込確定情報登録画面] | AQ6: ※追加及び変更項目のみ記載 | BG6: 日付
B7: № | C7: ラベル | J7: 項目名 | Q7: I/O | S7: 必須 | U7: 型 | W7: 桁数 | Y7: ソート | AA7: 初期表示 | AE7: 備考 | BG7: －
B8: 【ヘッダ部】
B9: 1 | C9: 一覧を最大化 | J9: 一覧を最大化ボタン | Q9: IN | S9: － | U9: － | W9: － | Y9: ー | AA9: ー
B10: 2 | Q10: IN | S10: ○ | U10: 日付 | W10: 8 | Y10: ー | AA10: システム日付
B11: 3 | Q11: OUT | S11: － | U11: コード | W11: 12 | Y11: ー | AA11: ー
B12: 4 | Q12: IN | S12: ○ | U12: コード | W12: 10 | Y12: ー | AA12: ー
Q13: IN | S13: － | U13: － | W13: ー | Y13: ー | AA13: ー
Q14: OUT | S14: － | U14: 文字列 | W14: 20 | Y14: ー | AA14: ー
B15: 5 | Q15: IN | S15: ○ | U15: コード | W15: 15 | Y15: ー | AA15: ー
Q16: IN | S16: － | U16: － | W16: ー | Y16: ー | AA16: ー
Q17: OUT | S17: － | U17: 文字列 | W17: 20 | Y17: ー | AA17: ー
B18: 6 | Q18: IN | S18: ○ | U18: － | W18: ー | Y18: ー
B20: 7 | Q20: IN | S20: ○ | U20: 数値 | W20: 13 | Y20: ー | AA20: ー
B21: 【】
B22: 1
B25: 2
B28: 3
B30: 4
B31: 5
B32: 【】 | AE32: ※ソート順は画面レイアウトシートの補足説明欄参照。
B33: 1
B34: 2
B35: 2
B36: 3
B37: 2
B38: 3
B39: 4
B40: 5
B41: 6
B42: 7
B43: 8
B44: 9
... B52: 16
B53: 【フッタ部】
B54: 1
B55: 2
B57: 3
B58: 4
B59: 5
B60: 6
B61: 7
B62: 8
B63: 9
B64: 10

Sheet イベント概要
A1: ドキュメント名 | L1: サブシステム | Q1: 業務機能名 | AJ1: 作成者 | AO1: =表紙!D51 -> SCSK位田 | AT1: 更新者
A2: 業務機能概要書 | G2: イベント概要 | L2: =業務機能概要!L2 -> 業務共通 | Q2: =業務機能概要!Q2 -> 取引先マスタ自動取込 | AJ2: 作成日付 | AO2: =表紙!C51 -> 45898 | AT2: 更新日付
A4: 【画面イベント処理】
EV5: 注１）初期表示は全ての
B6: № | C6: イベント名 | J6: 処理説明 | EV6: データを処理対象とする
B7: =IF(C7="","",MAX(B$6:B6)+1) -> 1 | C7: 取引先マスタ自動取込バッチイベント | J7: 1. | K7: バッチファイルで定義されたディレクトリに配置された取込用のCSVファイルをINPUTとし、
B8: =IF(C8="","",MAX(B$6:B7)+1) | K8: ProActiveC4標準機能の取引先外部データ取込を実行する。（※取込対象は取引先として実行する）
K9: ＜パラメータ＞
K10: ・ | L10: 会社コード | T10: ： | U10: バッチ実行用のxmlで指定された会社コード
K11: ・ | L11: 取込対象 | T11: ： | U11: 取引先
K12: ・ | L12: 取引先取込CSVファイル | T12: ： | U12: バッチファイルのパラメータにて指定されたファイル
B13: =IF(C13="","",MAX(B$6:B8)+1)
B14: =IF(C14="","",MAX(B$6:B13)+1) | K14: 取込用のCSVファイルが取得できなかった場合は、処理を中断する。バッチ実行結果はエラーとする。
K15: 取得できた場合は、後続の処理を継続する。
K16: ※ | L16: 上記のファイル取得、エラーハンドリングはバッチファイルで実施する（アプリケーションでの考慮は不要）
K17: ※ | L17: 取込用CSVのファイルサイズが0byteの場合は、正常として処理終了する。（バッチファイルにてファイルを正常処理フォルダへ移動する）
J19: ２．実行結果をバッチジョブ情報に反映する。
K20: ■ | L20: 取込対象ファイルが存在しなかった場合
M21: 今回のデータ連動では、連動対象データが存在しない場合は0byteファイルが連動され、バッチファイルにて処理対象外とするため
M22: ProActiveのプログラムでデータが存在しない場合のハンドリングは不要となる。
K24: ■ | L24: 上記以外の場合
M25: 標準仕様に準じる
B26: =IF(C26="","",MAX(B$6:B14)+1)
B27: =IF(C27="","",MAX(B$6:B15)+1) | J27: ３．実行結果をバッチジョブ情報に反映する。
B28: =IF(C28="","",MAX(B$6:B26)+1) | K28: ■ | L28: 業務エラー（マスタの存在チェックエラーなど）の場合 | AK28: ※ | AL28: ProActiveC4標準の仕様では、業務エラーがあった場合
B29: =IF(C29="","",MAX(B$6:B28)+1) | L29: ※エラー内容に１つでもNULL以外のメッセージが設定されていた場合 | AL29: 「正常終了」となるが、エラー対処が必要となるため、
B30: =IF(C30="","",MAX(B$6:B29)+1) | M30: 進行状況 | Q30: ： | R30: エラー | AL30: 処理結果は「エラー」とする
B31: =IF(C31="","",MAX(B$6:B30)+1) | M31: 機能 | Q31: ： | R31: 取引先取込処理実行バッチ
M32: メッセージ内容 | Q32: ： | R32: 「取込データにエラーが存在しています。取引先外部取込履歴一覧照会より、取引先外部取込チェックリストを出力して内容をご確認ください。」 | BD32: AE99_CMCST02
B33: =IF(C33="","",MAX(B$6:B31)+1) | K33: ■ | L33: 上記以外の場合
B34: =IF(C34="","",MAX(B$6:B33)+1) | M34: 標準仕様に準じる
J36: ４．バッチ実行結果の終了情報を返却する。
K37: ■ | L37: 正常終了できた場合
M38: 「0:正常終了」
K39: ■ | L39: エラーが発生した場合（※ProActiveC4標準機能の取引先外部データ取込でエラーが発生した場合は当ケースに該当する）
M40: 「1:異常終了」
J42: ５．取込処理後、取込用のCSVファイルは処理済用ファイルのディレクトリに移動する
K43: ※ | L43: アプリケーションではなくバッチファイルでファイル移動する
K44: ※ | L44: 正常用、エラー用のディレクトリを作成して処理結果によって移動先ディレクトリを分岐させる
B49: 2 | C49: 支払先マスタ自動取込バッチイベント | J49: 1. | K49: バッチファイルで定義されたディレクトリに配置された取込用のCSVファイルをINPUTとし、
K50: ProActiveC4標準機能の取引先外部データ取込を実行する。（※取込対象は支払先として実行する）
K51: ＜パラメータ＞
K52: ・ | L52: 会社コード | T52: ： | U52: バッチ実行用のxmlで指定された会社コード
K53: ・ | L53: 取込対象 | T53: ： | U53: 支払先
K54: ・ | L54: 取引先取込CSVファイル | T54: ： | U54: バッチファイルのパラメータにて指定されたファイル
K56: 取込用のCSVファイルが取得できなかった場合は、処理を中断する。バッチ実行結果はエラーとする。
K57: 取得できた場合は、後続の処理を継続する。
K58: ※ | L58: 上記のファイル取得、エラーハンドリングはバッチファイルで実施する（アプリケーションでの考慮は不要）
J61: ２．実行結果をバッチジョブ情報に反映する。
K62: ■ | L62: 取込対象ファイルが存在しなかった場合
M63: 今回のデータ連動では、連動対象データが存在しない場合は0byteファイルが連動され、バッチファイルにて処理対象外とするため
M64: ProActiveのプログラムでデータが存在しない場合のハンドリングは不要となる。
K66: ■ | L66: 上記以外の場合
M67: 標準仕様に準じる
J69: ３．実行結果をバッチジョブ情報に反映する。
K70: ■ | L70: 業務エラー（マスタの存在チェックエラーなど）の場合 | AK70: ※ | AL70: ProActiveC4標準の仕様では、業務エラーがあった場合
L71: ※エラー内容に１つでもNULL以外のメッセージが設定されていた場合 | AL71: 「正常終了」となるが、エラー対処が必要となるため、
M72: 進行状況 | Q72: ： | R72: エラー | AL72: 処理結果は「エラー」とする
M73: 機能 | Q73: ： | R73: 支払先取込処理実行バッチ | BD73: AE99_CMCST02
M74: メッセージ内容 | Q74: ： | R74: 「取込データにエラーが存在しています。取引先外部取込履歴一覧照会より、取引先外部取込チェックリストを出力して内容をご確認ください。」
K75: ■ | L75: 上記以外の場合
M76: 標準仕様に準じる
J78: ４．バッチ実行結果の終了情報を返却する。
K79: ■ | L79: 正常終了できた場合
M80: 「0:正常終了」
K81: ■ | L81: エラーが発生した場合（※ProActiveC4標準機能の取引先外部データ取込でエラーが発生した場合は当ケースに該当する）
M82: 「1:異常終了」
J84: ５．取込処理後、取込用のCSVファイルは処理済用ファイルのディレクトリに移動する
K85: ※ | L85: アプリケーションではなくバッチファイルでファイル移動する
K86: ※ | L86: 正常用、エラー用のディレクトリを作成して処理結果によって移動先ディレクトリを分岐させる
B88: =IF(C88="","",MAX(B$6:B34)+1)

Sheet チェック仕様
A1: ドキュメント名 | L1: サブシステム | Q1: 業務機能名 | AJ1: 作成者 | AO1: =表紙!D51 -> SCSK位田 | AT1: 更新者
A2: 業務機能概要書 | G2: チェック仕様 | L2: =業務機能概要!L2 -> 業務共通 | Q2: =業務機能概要!Q2 -> 取引先マスタ自動取込 | AJ2: 作成日付 | AO2: =表紙!C51 -> 45898 | AT2: 更新日付
A4: 【チェック処理】
B6: １．初期処理時
B7: № | C7: 項目名 | L7: 条件必須 | O7: 存在 | R7: 範囲 | U7: 関連 | X7: その他 | AA7: 内容
B8: =IF(C8="","",MAX(B7:B$7)+1) -> 1 | C8: － | X8: ○
B9: =IF(C9="","",MAX(B$7:B8)+1)
B10: =IF(C10="","",MAX(B$7:B9)+1)
B11: =IF(C11="","",MAX(B$7:B10)+1)
B13: ２．検索ボタン押下時
B14: № | C14: 項目名 | L14: 条件必須 | O14: 存在 | R14: 範囲 | U14: 関連 | X14: その他 | AA14: 内容
B15: =IF(C15="","",MAX(B$14:B14)+1)
B16: =IF(C16="","",MAX(B$14:B15)+1)
B17: =IF(C17="","",MAX(B$14:B16)+1)
B18: =IF(C18="","",MAX(B$14:B17)+1)
B19: =IF(C19="","",MAX(B$14:B18)+1)
B20: =IF(C20="","",MAX(B$14:B19)+1)
B21: =IF(C21="","",MAX(B$14:B20)+1)
B22: =IF(C22="","",MAX(B$14:B21)+1)
B23: =IF(C23="","",MAX(B$14:B22)+1)
B24: =IF(C24="","",MAX(B$14:B23)+1)
B25: =IF(C25="","",MAX(B$14:B24)+1)
B26: =IF(C26="","",MAX(B$14:B25)+1)
... B31: =IF(C31="","",MAX(B$14:B30)+1)
B33: ３．データ取込ボタン
B34: № | C34: 項目名 | L34: 条件必須 | O34: 存在 | R34: 範囲 | U34: 関連 | X34: その他 | AA34: 内容
B35: =IF(C35="","",MAX(B$34:B34)+1)
B36: =IF(C36="","",MAX(B$34:B35)+1)
B37: =IF(C37="","",MAX(B$34:B36)+1)
B38: =IF(C38="","",MAX(B$34:B37)+1)
B39: =IF(C39="","",MAX(B$34:B38)+1)
B40: =IF(C40="","",MAX(B$34:B39)+1)
B41: =IF(C41="","",MAX(B$34:B40)+1)
B42: =IF(C42="","",MAX(B$34:B41)+1)
B43: =IF(C43="","",MAX(B$34:B42)+1)
B44: =IF(C44="","",MAX(B$34:B40)+1)
B45: =IF(C45="","",MAX(B$34:B44)+1)
B46: =IF(C46="","",MAX(B$34:B45)+1)
B47: 4
B48: =IF(C48="","",MAX(B$34:B47)+1)
B49: 4
B50: =IF(C50="","",MAX(B$34:B49)+1)
B51: =IF(C51="","",MAX(B48:B$60)+1)
B52: =IF(C52="","",MAX(B46:B$60)+1)
B53: =IF(C53="","",MAX(B47:B$60)+1)
B54: =IF(C54="","",MAX(B48:B$60)+1)
B55: =IF(C55="","",MAX(B51:B$60)+1)
B56: =IF(C56="","",MAX(B$7:B51)+1)
B57: =IF(C57="","",MAX(B$34:B48)+1)
B59: ４．登録ボタン
B60: № | C60: 項目名 | L60: 条件必須 | O60: 存在 | R60: 範囲 | U60: 関連 | X60: その他 | AA60: 内容
B62: =IF(C62="","",MAX(B$60:B61)+1)
B63: =IF(C63="","",MAX(B$60:B62)+1)
B64: =IF(C64="","",MAX(B$60:B63)+1)
B65: =IF(C65="","",MAX(B$60:B64)+1)
B66: =IF(C66="","",MAX(B$60:B65)+1)
B67: =IF(C67="","",MAX(B$60:B66)+1)
B68: =IF(C68="","",MAX(B$60:B67)+1)
B69: =IF(C69="","",MAX(B$60:B68)+1)
B70: =IF(C70="","",MAX(B$60:B69)+1)
B71: =IF(C71="","",MAX(B$60:B70)+1)
B72: =IF(C72="","",MAX(B$60:B71)+1)
B73: =IF(C73="","",MAX(B$60:B72)+1)
... B92: =IF(C92="","",MAX(B$60:B91)+1)

Sheet 出力CSV定義
A1: ドキュメント名 | E1: サブシステム | G1: 業務機能名 | P1: 作成者 | R1: =表紙!D51 -> SCSK位田 | T1: 更新者
A2: 業務機能概要書 | C2: 出力CSV定義 | E2: =業務機能概要!L2 -> 業務共通 | G2: =業務機能概要!Q2 -> 取引先マスタ自動取込 | P2: 作成日 | R2: =表紙!C51 -> 45898 | T2: 更新日
A4: データ名 | I4: ヘッダ行 | K4: あり | M4: なし | N4: ダブルクォーテーション | Q4: あり | S4: なし | X4: 文字列
A5: ﾌｧｲﾙ形式・ﾚｺｰﾄﾞ長 | D5: 固定長（ | G5: Byte） | I5: 可変長（区切り文字［ ，(カンマ) ］） | M5: バイナリデータ | P5: その他（ ） | X5: 半英数
A6: 文字コード | D6: UNI（Win系） | F6: EBCDIC(K) | I6: その他（UTF-8） | M6: 改行コード | O6: LF(UNIX系) | Q6: CRLF(Win系) | T6: なし | X6: 半カナ
A7: 全角(2byte)文字項目 | D7: あり | F7: なし | M7: 数値編集 | O7: 左詰め | Q7: 右詰め［ゼロ埋め］ | T7: 右詰め［スペース埋め］ | X7: コード
A8: 特記事項 | C8: 出力順：起票日付、仕訳伝票番号、仕訳自動作成フラグ、仕訳伝票行番号 | J8: ※「"」が含まれる項目は「""」に変換する。 | X8: 数値
A9: No. | B9: 項目名 | E9: 必須 | F9: 型 | G9: 桁数 | H9: 開始位置 | I9: 備考 | X9: 日付
H10: /列 | X10: 時間
A11: 1 | F11: 日付 | G11: 8 | H11: A | X11: 年月
A12: 2 | F12: 半英数 | G12: 12 | H12: B | X12: 区分
A13: 3 | F13: コード | G13: 10 | H13: C | X13: フラグ
A14: 4 | F14: 文字列 | G14: 40 | H14: D | X14: -
A15: 5
A16: 6
A17: 7
A18: 8
A19: 9
A20: 10
A21: 11
A22: 12
A23: 13
A24: 14
A25: 15

Sheet 出力CSVサンプル

Sheet 取込フォーマット定義（一般支払先）
A1: ドキュメント名 | E1: サブシステム | G1: 業務機能名 | P1: 作成者 | R1: SCSK位田 | T1: 更新者
A2: 業務機能概要書 | C2: 取込フォーマット定義 | E2: 業務共通 | G2: 取引先マスタ自動取込 | P2: 作成日 | R2: =表紙!C51 -> 45898 | T2: 更新日
A4: データ名 | C4: 支払先外部データ取込フォーマット | I4: ヘッダ行 | K4: あり | M4: なし | N4: ダブルクォーテーション | Q4: あり | S4: なし | X4: 文字列
A5: ﾌｧｲﾙ形式・ﾚｺｰﾄﾞ長 | D5: 固定長（ | G5: Byte） | I5: 可変長（区切り文字［ ，(カンマ) ］） | M5: バイナリデータ | P5: その他（ ） | X5: 半英数
A6: 文字コード | D6: UNI（Win系） | F6: EBCDIC(K) | I6: その他（ UTF-8） | M6: 改行コード | O6: LF(UNIX系) | Q6: CRLF(Win系) | T6: なし | X6: 半カナ
A7: 全角(2byte)文字項目 | D7: あり | F7: なし | M7: 数値編集 | O7: 左詰め | Q7: 右詰め［ゼロ埋め］ | T7: 右詰め［スペース埋め］ | X7: コード
A8: 特記事項 | C8: 取込ファイルには、取込項目のタイトル行が必要となる | X8: 数値
A9: No. | B9: 項目名 | E9: 必須 | F9: 型 | G9: 桁数 | H9: 開始位置 | I9: 項目説明 | O9: 設定値 | X9: 日付
H10: /列 | X10: 時間
A11: 1 | B11: 編集区分 | E11: 〇 | F11: 区分 | G11: 1 | H11: =SUBSTITUTE(SUBSTITUTE(ADDRESS(1,A11),"$1",""),"$","") -> A | I11: 新規追加データの場合は「1:新規」、 | O11: 左記のとおり設定 | X11: 年月
I12: 既存データの修正および削除（使用不可フラグを１に更新）の場合は「２:修正」
I13: 既存支払先に対して、決済条件を追加する際も「２：修正」を使用する | X13: 区分
A14: =MAX(A$11:A11)+1 -> 2 | B14: 新規変更区分名称 | F14: 文字列 | G14: 4 | H14: =SUBSTITUTE(SUBSTITUTE(ADDRESS(1,A14),"$1",""),"$","") -> B | I14: 空白 | O14: 設定なし | X14: フラグ
A15: =MAX(A$11:A14)+1 -> 3 | B15: 取引先区分コード | E15: 〇 | F15: コード | G15: 2 | H15: =SUBSTITUTE(SUBSTITUTE(ADDRESS(1,A15),"$1",""),"$","") -> C | I15: 「00:初期導入」 | O15: 「00:初期導入」（固定値） | X15: -
A16: =MAX(A$11:A15)+1 -> 4 | B16: 取引先区分名 | F16: 文字列 | G16: 20 | H16: =SUBSTITUTE(SUBSTITUTE(ADDRESS(1,A16),"$1",""),"$","") -> D | I16: 空白 | O16: 設定なし
A17: =MAX(A$11:A16)+1 -> 5 | B17: 取引先コード | E17: △ | F17: コード | G17: 15 | H17: =SUBSTITUTE(SUBSTITUTE(ADDRESS(1,A17),"$1",""),"$","") -> E | I17: 支払先を一意に特定するコード | O17: 一般支払先のコード（9桁）
A18: =MAX(A$11:A17)+1 -> 6 | B18: 社内取引部門表示コード | E18: △ | F18: コード | G18: 15 | H18: =SUBSTITUTE(SUBSTITUTE(ADDRESS(1,A18),"$1",""),"$","") -> F | I18: 空白 | O18: 設定なし
A19: =MAX(A$11:A18)+1 -> 7 | B19: 社内取引部門名（略） | F19: 文字列 | G19: 20 | H19: =SUBSTITUTE(SUBSTITUTE(ADDRESS(1,A19),"$1",""),"$","") -> G | I19: 空白 | O19: 設定なし
A20: =MAX(A$11:A19)+1 -> 8 | B20: 適格請求書発行事業者登録番号 | F20: 文字列 | G20: 14 | H20: =SUBSTITUTE(SUBSTITUTE(ADDRESS(1,A20),"$1",""),"$","") -> H | I20: 空白 | O20: 設定なし
A21: =MAX(A$11:A20)+1 -> 9 | B21: 企業コード | E21: △ | F21: コード | G21: 15 | H21: =SUBSTITUTE(SUBSTITUTE(ADDRESS(1,A21),"$1",""),"$","") -> I | I21: 空白 | O21: 設定なし
A22: =MAX(A$11:A21)+1 -> 10 | B22: 企業名（略） | F22: 文字列 | G22: 20 | H22: =SUBSTITUTE(SUBSTITUTE(ADDRESS(1,A22),"$1",""),"$","") -> J | I22: 空白 | O22: 設定なし
A23: =MAX(A$11:A22)+1 -> 11 | B23: 得意先フラグ | F23: フラグ | G23: 1 | H23: =SUBSTITUTE(SUBSTITUTE(ADDRESS(1,A23),"$1",""),"$","") -> K | I23: 「0:得意先として使用しない」 | O23: ０（固定値）
A24: =MAX(A$11:A23)+1 -> 12 | B24: 需要家フラグ | F24: フラグ | G24: 1 | H24: =SUBSTITUTE(SUBSTITUTE(ADDRESS(1,A24),"$1",""),"$","") -> L | I24: 「0:需要家として使用しない」 | O24: ０（固定値）
A25: =MAX(A$11:A24)+1 -> 13 | B25: 出荷先フラグ | F25: フラグ | G25: 1 | H25: =SUBSTITUTE(SUBSTITUTE(ADDRESS(1,A25),"$1",""),"$","") -> M | I25: 「0:出荷先として使用しない」 | O25: ０（固定値）
A26: =MAX(A$11:A25)+1 -> 14 | B26: 仕入先フラグ | F26: フラグ | G26: 1 | H26: =SUBSTITUTE(SUBSTITUTE(ADDRESS(1,A26),"$1",""),"$","") -> N | I26: 「0:仕入先として使用しない」 | O26: ０（固定値）
A27: =MAX(A$11:A26)+1 -> 15 | B27: 入荷元フラグ | F27: フラグ | G27: 1 | H27: =SUBSTITUTE(SUBSTITUTE(ADDRESS(1,A27),"$1",""),"$","") -> O | I27: 「0:入荷元として使用しない」 | O27: ０（固定値）
A28: =MAX(A$11:A27)+1 -> 16 | B28: 請求先フラグ | F28: フラグ | G28: 1 | H28: =SUBSTITUTE(SUBSTITUTE(ADDRESS(1,A28),"$1",""),"$","") -> P | I28: 「0:請求先として使用しない」 | O28: ０（固定値）
A29: =MAX(A$11:A28)+1 -> 17 | B29: 支払先フラグ | F29: フラグ | G29: 1 | H29: =SUBSTITUTE(SUBSTITUTE(ADDRESS(1,A29),"$1",""),"$","") -> Q | I29: 「1:支払先として使用する」 | O29: １（固定値）
A30: =MAX(A$11:A29)+1 -> 18 | B30: 諸口取引先フラグ | F30: フラグ | G30: 1 | H30: =SUBSTITUTE(SUBSTITUTE(ADDRESS(1,A30),"$1",""),"$","") -> R | I30: 「0:取引先」 | O30: 0 | P30: ※諸口支払先の場合は１
A31: =MAX(A$11:A30)+1 -> 19 | B31: 取引先名１ | E31: 〇 | F31: 文字列 | G31: 50 | H31: =SUBSTITUTE(SUBSTITUTE(ADDRESS(1,A31),"$1",""),"$","") -> S | I31: 取引先の名称 | O31: 名称住所マスタ.取引先名（漢字）の先頭50桁(25文字) | T31: ※取引先名：全角50文字(法人30文字、店舗20文字) | X31: ※連動元システムでは常に全角で情報を保持
A32: =MAX(A$11:A31)+1 -> 20 | B32: 取引先名２ | F32: 文字列 | G32: 50 | H32: =SUBSTITUTE(SUBSTITUTE(ADDRESS(1,A32),"$1",""),"$","") -> T | I32: 取引先の名称 | O32: 名称住所マスタ.取引先名（漢字）の51～100桁(25文字)
A33: =MAX(A$11:A32)+1 -> 21 | B33: 取引先名（略） | E33: 〇 | F33: 文字列 | G33: 20 | H33: =SUBSTITUTE(SUBSTITUTE(ADDRESS(1,A33),"$1",""),"$","") -> U | I33: 取引先の略称 | O33: 名称住所マスタ.取引先略称名（漢字）の先頭20桁(10文字) | T33: ※取引先名（略）：全角25文字（法人13文字、店舗12文字） | X33: ※連動元システムでは常に全角で情報を保持
A34: =MAX(A$11:A33)+1 -> 22 | B34: 取引先名（カナ） | E34: 〇 | F34: 半カナ | G34: 40 | H34: =SUBSTITUTE(SUBSTITUTE(ADDRESS(1,A34),"$1",""),"$","") -> V | I34: 取引先のカナ名称 | O34: 名称住所マスタ.取引先略称名（カナ）の先頭40桁 | T34: ※カナ略称：半角50文字（法人26文字、店舗24文字）
A35: =MAX(A$11:A34)+1 -> 23 | B35: 取引先名（英字） | F35: 半英数 | G35: 40 | H35: =SUBSTITUTE(SUBSTITUTE(ADDRESS(1,A35),"$1",""),"$","") -> W | I35: 空白 | O35: 設定なし
A36: =MAX(A$11:A35)+1 -> 24 | B36: 休日パターンコード | F36: コード | G36: 5 | H36: =SUBSTITUTE(SUBSTITUTE(ADDRESS(1,A36),"$1",""),"$","") -> X | I36: 空白 | O36: 設定なし
A37: =MAX(A$11:A36)+1 -> 25 | B37: 休日パターン名 | F37: 文字列 | G37: 40 | H37: =SUBSTITUTE(SUBSTITUTE(ADDRESS(1,A37),"$1",""),"$","") -> Y | I37: 空白 | O37: 設定なし
A38: =MAX(A$11:A37)+1 -> 26 | B38: 国コード | F38: コード | G38: 3 | H38: =SUBSTITUTE(SUBSTITUTE(ADDRESS(1,A38),"$1",""),"$","") -> Z | I38: 空白 | O38: 設定なし
A39: =MAX(A$11:A38)+1 -> 27 | B39: 国名称 | F39: 文字列 | G39: 20 | H39: =SUBSTITUTE(SUBSTITUTE(ADDRESS(1,A39),"$1",""),"$","") -> AA | I39: 空白 | O39: 設定なし
A40: =MAX(A$11:A39)+1 -> 28 | B40: 取引先地域分類値コード | F40: コード | G40: 4 | H40: =SUBSTITUTE(SUBSTITUTE(ADDRESS(1,A40),"$1",""),"$","") -> AB | I40: 空白 | O40: 設定なし
A41: =MAX(A$11:A40)+1 -> 29 | B41: 取引先地域分類値 | F41: 文字列 | G41: 20 | H41: =SUBSTITUTE(SUBSTITUTE(ADDRESS(1,A41),"$1",""),"$","") -> AC | I41: 空白 | O41: 設定なし
A42: =MAX(A$11:A41)+1 -> 30 | B42: 郵便番号 | F42: 半英数 | G42: 8 | H42: =SUBSTITUTE(SUBSTITUTE(ADDRESS(1,A42),"$1",""),"$","") -> AD | I42: 空白 | O42: 設定なし
A43: =MAX(A$11:A42)+1 -> 31 | B43: 住所１ | F43: 文字列 | G43: 100 | H43: =SUBSTITUTE(SUBSTITUTE(ADDRESS(1,A43),"$1",""),"$","") -> AE | I43: 空白 | O43: 設定なし
A44: =MAX(A$11:A43)+1 -> 32 | B44: 住所２ | F44: 文字列 | G44: 100 | H44: =SUBSTITUTE(SUBSTITUTE(ADDRESS(1,A44),"$1",""),"$","") -> AF | I44: 空白 | O44: 設定なし
A45: =MAX(A$11:A44)+1 -> 33 | B45: 住所３ | F45: 文字列 | G45: 100 | H45: =SUBSTITUTE(SUBSTITUTE(ADDRESS(1,A45),"$1",""),"$","") -> AG | I45: 空白 | O45: 設定なし
A46: =MAX(A$11:A45)+1 -> 34 | B46: ＴＥＬ | F46: 半英数 | G46: 20 | H46: =SUBSTITUTE(SUBSTITUTE(ADDRESS(1,A46),"$1",""),"$","") -> AH | I46: 空白 | O46: 設定なし
... A70: =MAX(A$11:A69)+1 -> 58 | B70: 分類値１０ | F70: 文字列 | G70: 20 | H70: =SUBSTITUTE(SUBSTITUTE(ADDRESS(1,A70),"$1",""),"$","") -> BF | I70: 空白 | O70: 設定なし
A71: =MAX(A$11:A70)+1 -> 59 | B71: 使用不可フラグ | E71: 〇 | F71: フラグ | G71: 1 | H71: =SUBSTITUTE(SUBSTITUTE(ADDRESS(1,A71),"$1",""),"$","") -> BG | I71: 「0:使用可」 | O71: データ連動時は常に「０：使用可」
A72: =MAX(A$11:A71)+1 -> 60 | B72: 取引先所在地区分 | E72: 〇 | F72: 区分 | G72: 1 | H72: =SUBSTITUTE(SUBSTITUTE(ADDRESS(1,A72),"$1",""),"$","") -> BH | I72: 「0:国内」 | O72: ０（固定値）
A73: =MAX(A$11:A72)+1 -> 61 | B73: 取引先所在地区分名 | F73: 文字列 | G73: 4 | H73: =SUBSTITUTE(SUBSTITUTE(ADDRESS(1,A73),"$1",""),"$","") -> BI | I73: 空白 | O73: 設定なし
A74: =MAX(A$11:A73)+1 -> 62 | B74: 国内取引フラグ | E74: △ | F74: フラグ | G74: 1 | H74: =SUBSTITUTE(SUBSTITUTE(ADDRESS(1,A74),"$1",""),"$","") -> BJ | I74: 「1:使用する」 | O74: １（固定値）
A75: =MAX(A$11:A74)+1 -> 63 | B75: 外為取引フラグ | E75: △ | F75: フラグ | G75: 1 | H75: =SUBSTITUTE(SUBSTITUTE(ADDRESS(1,A75),"$1",""),"$","") -> BK | I75: 「0:使用しない」 | O75: ０（固定値）
A76: =MAX(A$11:A75)+1 -> 64 | B76: 通貨コード | E76: △ | F76: コード | G76: 3 | H76: =SUBSTITUTE(SUBSTITUTE(ADDRESS(1,A76),"$1",""),"$","") -> BL | I76: 空白 | O76: 設定なし
A77: =MAX(A$11:A76)+1 -> 65 | B77: 消費税端数計算区分 | F77: 区分 | G77: 1 | H77: =SUBSTITUTE(SUBSTITUTE(ADDRESS(1,A77),"$1",""),"$","") -> BM | I77: 「1:切り捨て」 | O77: 設定なし | Q77: ※ブランク時は3：四捨五入が採用される
A78: =MAX(A$11:A77)+1 -> 66 | B78: 消費税計算単位区分 | F78: 区分 | G78: 1 | H78: =SUBSTITUTE(SUBSTITUTE(ADDRESS(1,A78),"$1",""),"$","") -> BN | I78: 「2:明細単位」 | O78: ２：明細単位
A79: =MAX(A$11:A78)+1 -> 67 | B79: 取引金額端数処理区分 | F79: 区分 | G79: 1 | H79: =SUBSTITUTE(SUBSTITUTE(ADDRESS(1,A79),"$1",""),"$","") -> BO | I79: 「1:切り捨て」 | O79: 設定なし | Q79: ※ブランク時は3：四捨五入が採用される
A80: =MAX(A$11:A79)+1 -> 68 | B80: 承認申請状況区分名 | F80: 文字列 | G80: 6 | H80: =SUBSTITUTE(SUBSTITUTE(ADDRESS(1,A80),"$1",""),"$","") -> BP | I80: 空白 | O80: 設定なし
A81: =MAX(A$11:A80)+1 -> 69 | B81: 承認申請番号 | F81: コード | G81: 20 | H81: =SUBSTITUTE(SUBSTITUTE(ADDRESS(1,A81),"$1",""),"$","") -> BQ | I81: 空白 | O81: 設定なし
A82: =MAX(A$11:A81)+1 -> 70 | B82: 承認申請日付 | F82: 日付 | G82: 8 | H82: =SUBSTITUTE(SUBSTITUTE(ADDRESS(1,A82),"$1",""),"$","") -> BR | I82: 空白 | O82: 設定なし
A83: =MAX(A$11:A82)+1 -> 71 | B83: 承認申請者名 | F83: 文字列 | G83: 22 | H83: =SUBSTITUTE(SUBSTITUTE(ADDRESS(1,A83),"$1",""),"$","") -> BS | I83: 空白 | O83: 設定なし
A84: =MAX(A$11:A83)+1 -> 72 | B84: 承認申請部門名（略） | F84: 文字列 | G84: 20 | H84: =SUBSTITUTE(SUBSTITUTE(ADDRESS(1,A84),"$1",""),"$","") -> BT | I84: 空白 | O84: 設定なし
A85: =MAX(A$11:A84)+1 -> 73 | B85: 登録者名 | F85: 文字列 | G85: 22 | H85: =SUBSTITUTE(SUBSTITUTE(ADDRESS(1,A85),"$1",""),"$","") -> BU | I85: 空白 | O85: 設定なし
A86: =MAX(A$11:A85)+1 -> 74 | B86: 登録日時 | F86: 数値 | G86: 17 | H86: =SUBSTITUTE(SUBSTITUTE(ADDRESS(1,A86),"$1",""),"$","") -> BV | I86: 空白 | O86: 設定なし
A87: =MAX(A$11:A86)+1 -> 75 | B87: 更新者名 | F87: 文字列 | G87: 22 | H87: =SUBSTITUTE(SUBSTITUTE(ADDRESS(1,A87),"$1",""),"$","") -> BW | I87: 空白 | O87: 設定なし
A88: =MAX(A$11:A87)+1 -> 76 | B88: 更新日時 | F88: 数値 | G88: 17 | H88: =SUBSTITUTE(SUBSTITUTE(ADDRESS(1,A88),"$1",""),"$","") -> BX | I88: 空白 | O88: 設定なし
A89: =MAX(A$11:A88)+1 -> 77 | B89: 得意先担当者コード | F89: 半英数 | G89: 15 | H89: =SUBSTITUTE(SUBSTITUTE(ADDRESS(1,A89),"$1",""),"$","") -> BY | I89: 空白 | O89: 設定なし
A90: =MAX(A$11:A89)+1 -> 78 | B90: 得意先担当者名 | F90: 文字列 | G90: 22 | H90: =SUBSTITUTE(SUBSTITUTE(ADDRESS(1,A90),"$1",""),"$","") -> BZ | I90: 空白 | O90: 設定なし
A91: =MAX(A$11:A90)+1 -> 79 | B91: 得意先担当部門表示コード | F91: コード | G91: 10 | H91: =SUBSTITUTE(SUBSTITUTE(ADDRESS(1,A91),"$1",""),"$","") -> CA | I91: 空白 | O91: 設定なし
... A170: =MAX(A$11:A169)+1 -> 158 | B170: 預り源泉対象初期値フラグ | F170: フラグ | G170: 1 | H170: =SUBSTITUTE(SUBSTITUTE(ADDRESS(1,A170),"$1",""),"$","") -> FB | I170: 「0:チェックしない」 | O170: ０（固定値）
A171: =MAX(A$11:A170)+1 -> 159 | B171: 預り源泉税端数計算区分 | E171: 〇 | F171: 区分 | G171: 1 | H171: =SUBSTITUTE(SUBSTITUTE(ADDRESS(1,A171),"$1",""),"$","") -> FC | I171: 「1:切り捨て」 | O171: １（固定値）
A172: =MAX(A$11:A171)+1 -> 160 | B172: 支払消費税差額計算フラグ | F172: フラグ | G172: 1 | H172: =SUBSTITUTE(SUBSTITUTE(ADDRESS(1,A172),"$1",""),"$","") -> FD | I172: 「0:計算しない」 | O172: ０（固定値）
A173: =MAX(A$11:A172)+1 -> 161 | B173: 取込支払消費税差額計算フラグ | F173: フラグ | G173: 1 | H173: =SUBSTITUTE(SUBSTITUTE(ADDRESS(1,A173),"$1",""),"$","") -> FE | I173: 「0:計算しない」 | O173: ０（固定値）
A174: =MAX(A$11:A173)+1 -> 162 | B174: 共通支払先フラグ | F174: フラグ | G174: 1 | H174: =SUBSTITUTE(SUBSTITUTE(ADDRESS(1,A174),"$1",""),"$","") -> FF | I174: 空白 | O174: 設定なし | R174: → 0（固定値）
A175: =MAX(A$11:A174)+1 -> 163 | B175: 支払書内容確認コメント | F175: 文字列 | G175: 100 | H175: =SUBSTITUTE(SUBSTITUTE(ADDRESS(1,A175),"$1",""),"$","") -> FG | I175: 空白 | O175: 設定なし
A176: =MAX(A$11:A175)+1 -> 164 | B176: 支払決済条件行番号 | E176: △ | F176: 数値 | G176: 3 | H176: =SUBSTITUTE(SUBSTITUTE(ADDRESS(1,A176),"$1",""),"$","") -> FH | I176: 1から連番で採番する。 | O176: *支払決済条件コードと同じ値を設定
A177: =MAX(A$11:A176)+1 -> 165 | B177: 支払決済条件コード | F177: コード | G177: 3 | H177: =SUBSTITUTE(SUBSTITUTE(ADDRESS(1,A177),"$1",""),"$","") -> FI | I177: 001～連番 | O177: 001～020：振込以外の支払方法の場合に採番、021～999：決済条件マスタに登録されている振込払の場合に採番
A178: =MAX(A$11:A177)+1 -> 166 | B178: 支払決済条件名 | E178: △ | F178: 文字列 | G178: 80 | H178: =SUBSTITUTE(SUBSTITUTE(ADDRESS(1,A178),"$1",""),"$","") -> FJ | I178: 支払決済条件の名称 | O178: 振込以外は、支払方法の名称（納付書、自動引落については、"支払方法の名称+（信連）"、"支払方法の名称+（道銀）"のような出金口座が識別できる名称をセット）を設定。振込の場合は支払先口座として設定されている金融機関マスタの銀行名（漢字）(30byte)＋本・支店名（漢字）(20byte)を設定。
A182: =MAX(A$11:A181)+1 -> 167 | B182: 支払決済条件名（略） | E182: △ | F182: 文字列 | G182: 20 | H182: =SUBSTITUTE(SUBSTITUTE(ADDRESS(1,A182),"$1",""),"$","") -> FK | I182: 支払決済条件名の略称 | O182: 支払決済条件名に設定した値から20byte切り出した値
A183: =MAX(A$11:A182)+1 -> 168 | B183: 取引形態区分 | E183: △ | F183: 区分 | G183: 1 | H183: =SUBSTITUTE(SUBSTITUTE(ADDRESS(1,A183),"$1",""),"$","") -> FL | I183: 「1:国内取引」 | O183: １（固定値）
A184: =MAX(A$11:A183)+1 -> 169 | B184: 支払締区分 | E184: △ | F184: 区分 | G184: 1 | H184: =SUBSTITUTE(SUBSTITUTE(ADDRESS(1,A184),"$1",""),"$","") -> FM | I184: 「2:随時取引」 | O184: ２（固定値）
A185: =MAX(A$11:A184)+1 -> 170 | B185: 支払締名寄フラグ | E185: △ | F185: フラグ | G185: 1 | H185: =SUBSTITUTE(SUBSTITUTE(ADDRESS(1,A185),"$1",""),"$","") -> FN | I185: 「0:名寄せしない」 | O185: ０（固定値）
A186: =MAX(A$11:A185)+1 -> 171 | B186: 名寄部門表示コード | F186: コード | G186: 10 | H186: =SUBSTITUTE(SUBSTITUTE(ADDRESS(1,A186),"$1",""),"$","") -> FO | I186: 空白 | O186: 設定なし
A187: =MAX(A$11:A186)+1 -> 172 | B187: 名寄部門名（略） | F187: 文字列 | G187: 20 | H187: =SUBSTITUTE(SUBSTITUTE(ADDRESS(1,A187),"$1",""),"$","") -> FP | I187: 空白 | O187: 設定なし
A188: =MAX(A$11:A187)+1 -> 173 | B188: 名寄部門基準日付 | F188: 日付 | G188: 8 | H188: =SUBSTITUTE(SUBSTITUTE(ADDRESS(1,A188),"$1",""),"$","") -> FQ | I188: 空白 | O188: 設定なし
A189: =MAX(A$11:A188)+1 -> 174 | B189: 支払通知書書式区分 | E189: △ | F189: 区分 | G189: 1 | H189: =SUBSTITUTE(SUBSTITUTE(ADDRESS(1,A189),"$1",""),"$","") -> FR | I189: ‘1：鑑のみ’、‘2：取引内容も含む’、‘3：発行時に選択’、‘9：出力しない’より選択 | O189: 設定なし | R189: → 3（固定値） | T189: ※諸口支払先の場合、3のみ許容
A190: =MAX(A$11:A189)+1 -> 175 | B190: 支払通知書品目内訳表示フラグ | E190: △ | F190: フラグ | G190: 1 | H190: =SUBSTITUTE(SUBSTITUTE(ADDRESS(1,A190),"$1",""),"$","") -> FS | I190: ‘0：表示しない’、‘1：表示する’より選択 | O190: 設定なし | R190: → 0（固定値）
A191: =MAX(A$11:A190)+1 -> 176 | B191: 支払基準金額 | E191: △ | F191: 数値 | G191: 13 | H191: =SUBSTITUTE(SUBSTITUTE(ADDRESS(1,A191),"$1",""),"$","") -> FT | I191: 空白 | O191: 設定なし | R191: → 0（固定値）
A192: =MAX(A$11:A191)+1 -> 177 | B192: 支払決済条件使用不可フラグ | E192: △ | F192: フラグ | G192: 1 | H192: =SUBSTITUTE(SUBSTITUTE(ADDRESS(1,A192),"$1",""),"$","") -> FU | I192: 「0:使用する」 | O192: ０（固定値）
A193: =MAX(A$11:A192)+1 -> 178 | B193: 分割条件（未満） | E193: △ | F193: 区分 | G193: 1 | H193: =SUBSTITUTE(SUBSTITUTE(ADDRESS(1,A193),"$1",""),"$","") -> FV | I193: 「1:分割しない」 | O193: １（固定値）
A194: =MAX(A$11:A193)+1 -> 179 | B194: 分割率（未満） | E194: △ | F194: 数値 | G194: 3 | H194: =SUBSTITUTE(SUBSTITUTE(ADDRESS(1,A194),"$1",""),"$","") -> FW | I194: 空白 | O194: 設定なし
A195: =MAX(A$11:A194)+1 -> 180 | B195: 端数桁数（未満） | E195: △ | F195: 数値 | G195: 2 | H195: =SUBSTITUTE(SUBSTITUTE(ADDRESS(1,A195),"$1",""),"$","") -> FX | I195: 空白 | O195: 設定なし
A196: =MAX(A$11:A195)+1 -> 181 | B196: 端数区分（未満） | E196: △ | F196: 区分 | G196: 1 | H196: =SUBSTITUTE(SUBSTITUTE(ADDRESS(1,A196),"$1",""),"$","") -> FY | I196: 空白 | O196: 設定なし
A197: =MAX(A$11:A196)+1 -> 182 | B197: 分割基準金額（未満） | E197: △ | F197: 数値 | G197: 13 | H197: =SUBSTITUTE(SUBSTITUTE(ADDRESS(1,A197),"$1",""),"$","") -> FZ | I197: 空白 | O197: 設定なし
A198: =MAX(A$11:A197)+1 -> 183 | B198: 支払方法コード（未満１） | E198: △ | F198: コード | G198: 3 | H198: =SUBSTITUTE(SUBSTITUTE(ADDRESS(1,A198),"$1",""),"$","") -> GA | I198: 決済条件マスタ（AN923）．決済条件区分 | O198: 決済条件マスタ.回収支払方法区分
A199: =MAX(A$11:A198)+1 -> 184 | B199: 支払方法名（未満１） | F199: 文字列 | G199: 20 | H199: =SUBSTITUTE(SUBSTITUTE(ADDRESS(1,A199),"$1",""),"$","") -> GB | I199: 空白 | O199: 設定なし
A200: =MAX(A$11:A199)+1 -> 185 | B200: 休日考慮区分（未満１） | E200: △ | F200: 区分 | G200: 1 | H200: =SUBSTITUTE(SUBSTITUTE(ADDRESS(1,A200),"$1",""),"$","") -> GC | I200: 銀行が休日の場合の期日前後の制御を指定。 | O200: ９：考慮しない（固定値） | R200: ※ProActive側では支払予定日付を導出せず、連動元システム側で設定する
I201: 1:休日前、2:休日後月跨ぎ、3:休日後月跨がない、9:考慮しない、のいずれか。
A202: =MAX(A$11:A201)+1 -> 186 | B202: 出金口座コード（未満１） | F202: コード | G202: 8 | H202: =SUBSTITUTE(SUBSTITUTE(ADDRESS(1,A202),"$1",""),"$","") -> GD | I202: 出金口座の自社口座コード（振込の場合は設定不要） | O202: ホクレン口座マスタのホクレン口座コードを設定 （納付書や一括決済などの支払方法は、出金口座ごとに支払決済条件を分岐させる）
I203: ※債務システム設定、金融機関マスタ、部門別口座マスタを活用。
I204: 「補足2 出金口座の導出」シート参照。
A205: =MAX(A$11:A202)+1 -> 187 | B205: 出金口座名（未満１） | F205: 文字列 | G205: 20 | H205: =SUBSTITUTE(SUBSTITUTE(ADDRESS(1,A205),"$1",""),"$","") -> GE | I205: 空白 | O205: 設定なし
...

Sheet 取込フォーマット定義（支払先） bk
A1: ドキュメント名 | E1: サブシステム | G1: 業務機能名 | P1: 作成者 | R1: =表紙!D51 -> SCSK位田 | T1: 更新者
A2: 業務機能概要書 | C2: 取込フォーマット定義 | E2: =業務機能概要!L2 -> 業務共通 | G2: =業務機能概要!Q2 -> 取引先マスタ自動取込 | P2: 作成日 | R2: =表紙!C51 -> 45898 | T2: 更新日
A4: データ名 | C4: 支払先外部データ取込フォーマット | I4: ヘッダ行 | K4: あり | M4: なし | N4: ダブルクォーテーション | Q4: あり | S4: なし | X4: 文字列
A5: ﾌｧｲﾙ形式・ﾚｺｰﾄﾞ長 | D5: 固定長（ | G5: Byte） | I5: 可変長（区切り文字［ ，(カンマ) ］） | M5: バイナリデータ | P5: その他（ ） | X5: 半英数
A6: 文字コード | D6: UNI（Win系） | F6: EBCDIC(K) | I6: その他（ UTF-8） | M6: 改行コード | O6: LF(UNIX系) | Q6: CRLF(Win系) | T6: なし | X6: 半カナ
A7: 全角(2byte)文字項目 | D7: あり | F7: なし | M7: 数値編集 | O7: 左詰め | Q7: 右詰め［ゼロ埋め］ | T7: 右詰め［スペース埋め］ | X7: コード
A8: 特記事項 | C8: 取込ファイルには、取込項目のタイトル行が必要となる | X8: 数値
A9: No. | B9: 項目名 | E9: 必須 | F9: 型 | G9: 桁数 | H9: 開始位置 | I9: 備考 | X9: 日付
H10: /列 | X10: 時間
A11: 1 | B11: 編集区分 | E11: 〇 | F11: 区分 | G11: 1 | H11: =SUBSTITUTE(SUBSTITUTE(ADDRESS(1,A11),"$1",""),"$","") -> A | I11: 新規追加データの場合は「1:新規」、既存データの修正および削除（使用不可フラグを１に更新）の場合は「２:修正」 ※連動元システム側でセットする | X11: 年月
A12: =MAX(A$11:A11)+1 -> 2 | B12: 新規変更区分名称 | F12: 文字列 | G12: 4 | H12: =SUBSTITUTE(SUBSTITUTE(ADDRESS(1,A12),"$1",""),"$","") -> B | I12: 空白 | X12: 区分
A13: =MAX(A$11:A12)+1 -> 3 | B13: 取引先区分コード | E13: 〇 | F13: コード | G13: 2 | H13: =SUBSTITUTE(SUBSTITUTE(ADDRESS(1,A13),"$1",""),"$","") -> C | I13: 「00:初期導入」 | X13: フラグ
A14: =MAX(A$11:A13)+1 -> 4 | B14: 取引先区分名 | F14: 文字列 | G14: 20 | H14: =SUBSTITUTE(SUBSTITUTE(ADDRESS(1,A14),"$1",""),"$","") -> D | I14: 空白 | X14: -
A15: =MAX(A$11:A14)+1 -> 5 | B15: 取引先コード | E15: △ | F15: コード | G15: 15 | H15: =SUBSTITUTE(SUBSTITUTE(ADDRESS(1,A15),"$1",""),"$","") -> E | I15: 名称住所マスタ（AN910）．取引先コード ※名称住所マスタ（AN910）．取引先枝番コードも連結？支払先を一意に特定する番号としたい。 | X15: ★連動元のテーブル情報が決定後に設定値を設計する
A16: =MAX(A$11:A15)+1 -> 6 | B16: 社内取引部門表示コード | E16: △ | F16: コード | G16: 15 | H16: =SUBSTITUTE(SUBSTITUTE(ADDRESS(1,A16),"$1",""),"$","") -> F | I16: 空白
A17: =MAX(A$11:A16)+1 -> 7 | B17: 社内取引部門名（略） | F17: 文字列 | G17: 20 | H17: =SUBSTITUTE(SUBSTITUTE(ADDRESS(1,A17),"$1",""),"$","") -> G | I17: 空白
A18: =MAX(A$11:A17)+1 -> 8 | B18: 適格請求書発行事業者登録番号 | F18: 文字列 | G18: 14 | H18: =SUBSTITUTE(SUBSTITUTE(ADDRESS(1,A18),"$1",""),"$","") -> H | I18: 空白
A19: =MAX(A$11:A18)+1 -> 9 | B19: 企業コード | E19: △ | F19: コード | G19: 15 | H19: =SUBSTITUTE(SUBSTITUTE(ADDRESS(1,A19),"$1",""),"$","") -> I | I19: 空白
A20: =MAX(A$11:A19)+1 -> 10 | B20: 企業名（略） | F20: 文字列 | G20: 20 | H20: =SUBSTITUTE(SUBSTITUTE(ADDRESS(1,A20),"$1",""),"$","") -> J | I20: 空白
A21: =MAX(A$11:A20)+1 -> 11 | B21: 得意先フラグ | F21: フラグ | G21: 1 | H21: =SUBSTITUTE(SUBSTITUTE(ADDRESS(1,A21),"$1",""),"$","") -> K | I21: 「0:得意先として使用しない」
A22: =MAX(A$11:A21)+1 -> 12 | B22: 需要家フラグ | F22: フラグ | G22: 1 | H22: =SUBSTITUTE(SUBSTITUTE(ADDRESS(1,A22),"$1",""),"$","") -> L | I22: 「0:需要家として使用しない」
A23: =MAX(A$11:A22)+1 -> 13 | B23: 出荷先フラグ | F23: フラグ | G23: 1 | H23: =SUBSTITUTE(SUBSTITUTE(ADDRESS(1,A23),"$1",""),"$","") -> M | I23: 「0:出荷先として使用しない」
A24: =MAX(A$11:A23)+1 -> 14 | B24: 仕入先フラグ | F24: フラグ | G24: 1 | H24: =SUBSTITUTE(SUBSTITUTE(ADDRESS(1,A24),"$1",""),"$","") -> N | I24: 「0:仕入先として使用しない」
A25: =MAX(A$11:A24)+1 -> 15 | B25: 入荷元フラグ | F25: フラグ | G25: 1 | H25: =SUBSTITUTE(SUBSTITUTE(ADDRESS(1,A25),"$1",""),"$","") -> O | I25: 「0:入荷元として使用しない」
A26: =MAX(A$11:A25)+1 -> 16 | B26: 請求先フラグ | F26: フラグ | G26: 1 | H26: =SUBSTITUTE(SUBSTITUTE(ADDRESS(1,A26),"$1",""),"$","") -> P | I26: 「0:請求先として使用しない」
A27: =MAX(A$11:A26)+1 -> 17 | B27: 支払先フラグ | F27: フラグ | G27: 1 | H27: =SUBSTITUTE(SUBSTITUTE(ADDRESS(1,A27),"$1",""),"$","") -> Q | I27: 「1:支払先として使用する」
A28: =MAX(A$11:A27)+1 -> 18 | B28: 諸口取引先フラグ | F28: フラグ | G28: 1 | H28: =SUBSTITUTE(SUBSTITUTE(ADDRESS(1,A28),"$1",""),"$","") -> R | I28: 「0:取引先」
A29: =MAX(A$11:A28)+1 -> 19 | B29: 取引先名１ | E29: 〇 | F29: 文字列 | G29: 50 | H29: =SUBSTITUTE(SUBSTITUTE(ADDRESS(1,A29),"$1",""),"$","") -> S | I29: 名称住所マスタ（AN910）．取引先略称名（漢字） | X29: ★連動元のテーブル情報が決定後に設定値を設計する
A30: =MAX(A$11:A29)+1 -> 20 | B30: 取引先名２ | F30: 文字列 | G30: 50 | H30: =SUBSTITUTE(SUBSTITUTE(ADDRESS(1,A30),"$1",""),"$","") -> T | I30: 空白
A31: =MAX(A$11:A30)+1 -> 21 | B31: 取引先名（略） | E31: 〇 | F31: 文字列 | G31: 20 | H31: =SUBSTITUTE(SUBSTITUTE(ADDRESS(1,A31),"$1",""),"$","") -> U | I31: 名称住所マスタ（AN910）．取引先略称名（漢字） ※20byteに省略する必要あり | X31: ★連動元のテーブル情報が決定後に設定値を設計する
A32: =MAX(A$11:A31)+1 -> 22 | B32: 取引先名（カナ） | E32: 〇 | F32: 半カナ | G32: 40 | H32: =SUBSTITUTE(SUBSTITUTE(ADDRESS(1,A32),"$1",""),"$","") -> V | I32: 名称住所マスタ（AN910）．取引先略称名（カナ） | X32: ★連動元のテーブル情報が決定後に設定値を設計する
A33: =MAX(A$11:A32)+1 -> 23 | B33: 取引先名（英字） | F33: 半英数 | G33: 40 | H33: =SUBSTITUTE(SUBSTITUTE(ADDRESS(1,A33),"$1",""),"$","") -> W | I33: 空白
A34: =MAX(A$11:A33)+1 -> 24 | B34: 休日パターンコード | F34: コード | G34: 5 | H34: =SUBSTITUTE(SUBSTITUTE(ADDRESS(1,A34),"$1",""),"$","") -> X | I34: 空白
A35: =MAX(A$11:A34)+1 -> 25 | B35: 休日パターン名 | F35: 文字列 | G35: 40 | H35: =SUBSTITUTE(SUBSTITUTE(ADDRESS(1,A35),"$1",""),"$","") -> Y | I35: 空白
A36: =MAX(A$11:A35)+1 -> 26 | B36: 国コード | F36: コード | G36: 3 | H36: =SUBSTITUTE(SUBSTITUTE(ADDRESS(1,A36),"$1",""),"$","") -> Z | I36: 空白
A37: =MAX(A$11:A36)+1 -> 27 | B37: 国名称 | F37: 文字列 | G37: 20 | H37: =SUBSTITUTE(SUBSTITUTE(ADDRESS(1,A37),"$1",""),"$","") -> AA | I37: 空白
A38: =MAX(A$11:A37)+1 -> 28 | B38: 取引先地域分類値コード | F38: コード | G38: 4 | H38: =SUBSTITUTE(SUBSTITUTE(ADDRESS(1,A38),"$1",""),"$","") -> AB | I38: 空白
A39: =MAX(A$11:A38)+1 -> 29 | B39: 取引先地域分類値 | F39: 文字列 | G39: 20 | H39: =SUBSTITUTE(SUBSTITUTE(ADDRESS(1,A39),"$1",""),"$","") -> AC | I39: 空白
A40: =MAX(A$11:A39)+1 -> 30 | B40: 郵便番号 | F40: 半英数 | G40: 8 | H40: =SUBSTITUTE(SUBSTITUTE(ADDRESS(1,A40),"$1",""),"$","") -> AD | I40: 空白
A41: =MAX(A$11:A40)+1 -> 31 | B41: 住所１ | F41: 文字列 | G41: 100 | H41: =SUBSTITUTE(SUBSTITUTE(ADDRESS(1,A41),"$1",""),"$","") -> AE | I41: 空白
A42: =MAX(A$11:A41)+1 -> 32 | B42: 住所２ | F42: 文字列 | G42: 100 | H42: =SUBSTITUTE(SUBSTITUTE(ADDRESS(1,A42),"$1",""),"$","") -> AF | I42: 空白
A43: =MAX(A$11:A42)+1 -> 33 | B43: 住所３ | F43: 文字列 | G43: 100 | H43: =SUBSTITUTE(SUBSTITUTE(ADDRESS(1,A43),"$1",""),"$","") -> AG | I43: 空白
A44: =MAX(A$11:A43)+1 -> 34 | B44: ＴＥＬ | F44: 半英数 | G44: 20 | H44: =SUBSTITUTE(SUBSTITUTE(ADDRESS(1,A44),"$1",""),"$","") -> AH | I44: 空白
... A68: =MAX(A$11:A67)+1 -> 58 | B68: 分類値１０ | F68: 文字列 | G68: 20 | H68: =SUBSTITUTE(SUBSTITUTE(ADDRESS(1,A68),"$1",""),"$","") -> BF | I68: 空白
A69: =MAX(A$11:A68)+1 -> 59 | B69: 使用不可フラグ | E69: 〇 | F69: フラグ | G69: 1 | H69: =SUBSTITUTE(SUBSTITUTE(ADDRESS(1,A69),"$1",""),"$","") -> BG | I69: 「0:使用可」
A70: =MAX(A$11:A69)+1 -> 60 | B70: 取引先所在地区分 | E70: 〇 | F70: 区分 | G70: 1 | H70: =SUBSTITUTE(SUBSTITUTE(ADDRESS(1,A70),"$1",""),"$","") -> BH | I70: 「0:国内」
A71: =MAX(A$11:A70)+1 -> 61 | B71: 取引先所在地区分名 | F71: 文字列 | G71: 4 | H71: =SUBSTITUTE(SUBSTITUTE(ADDRESS(1,A71),"$1",""),"$","") -> BI | I71: 空白
A72: =MAX(A$11:A71)+1 -> 62 | B72: 国内取引フラグ | E72: △ | F72: フラグ | G72: 1 | H72: =SUBSTITUTE(SUBSTITUTE(ADDRESS(1,A72),"$1",""),"$","") -> BJ | I72: 「1:使用する」
A73: =MAX(A$11:A72)+1 -> 63 | B73: 外為取引フラグ | E73: △ | F73: フラグ | G73: 1 | H73: =SUBSTITUTE(SUBSTITUTE(ADDRESS(1,A73),"$1",""),"$","") -> BK | I73: 「0:使用しない」
A74: =MAX(A$11:A73)+1 -> 64 | B74: 通貨コード | E74: △ | F74: コード | G74: 3 | H74: =SUBSTITUTE(SUBSTITUTE(ADDRESS(1,A74),"$1",""),"$","") -> BL | I74: 空白
A75: =MAX(A$11:A74)+1 -> 65 | B75: 消費税端数計算区分 | F75: 区分 | G75: 1 | H75: =SUBSTITUTE(SUBSTITUTE(ADDRESS(1,A75),"$1",""),"$","") -> BM | I75: 「1:切り捨て」 | K75: 【要ヒアリング】 支払先ごとに変動するか？
A76: =MAX(A$11:A75)+1 -> 66 | B76: 消費税計算単位区分 | F76: 区分 | G76: 1 | H76: =SUBSTITUTE(SUBSTITUTE(ADDRESS(1,A76),"$1",""),"$","") -> BN | I76: 「2:明細単位」
A77: =MAX(A$11:A76)+1 -> 67 | B77: 取引金額端数処理区分 | F77: 区分 | G77: 1 | H77: =SUBSTITUTE(SUBSTITUTE(ADDRESS(1,A77),"$1",""),"$","") -> BO | I77: 「1:切り捨て」 | K77: 【要ヒアリング】 支払先ごとに変動するか？
A78: =MAX(A$11:A77)+1 -> 68 | B78: 承認申請状況区分名 | F78: 文字列 | G78: 6 | H78: =SUBSTITUTE(SUBSTITUTE(ADDRESS(1,A78),"$1",""),"$","") -> BP | I78: 空白
A79: =MAX(A$11:A78)+1 -> 69 | B79: 承認申請番号 | F79: コード | G79: 20 | H79: =SUBSTITUTE(SUBSTITUTE(ADDRESS(1,A79),"$1",""),"$","") -> BQ | I79: 空白
A80: =MAX(A$11:A79)+1 -> 70 | B80: 承認申請日付 | F80: 日付 | G80: 8 | H80: =SUBSTITUTE(SUBSTITUTE(ADDRESS(1,A80),"$1",""),"$","") -> BR | I80: 空白
A81: =MAX(A$11:A80)+1 -> 71 | B81: 承認申請者名 | F81: 文字列 | G81: 22 | H81: =SUBSTITUTE(SUBSTITUTE(ADDRESS(1,A81),"$1",""),"$","") -> BS | I81: 空白
A82: =MAX(A$11:A81)+1 -> 72 | B82: 承認申請部門名（略） | F82: 文字列 | G82: 20 | H82: =SUBSTITUTE(SUBSTITUTE(ADDRESS(1,A82),"$1",""),"$","") -> BT | I82: 空白
A83: =MAX(A$11:A82)+1 -> 73 | B83: 登録者名 | F83: 文字列 | G83: 22 | H83: =SUBSTITUTE(SUBSTITUTE(ADDRESS(1,A83),"$1",""),"$","") -> BU | I83: 空白
A84: =MAX(A$11:A83)+1 -> 74 | B84: 登録日時 | F84: 数値 | G84: 17 | H84: =SUBSTITUTE(SUBSTITUTE(ADDRESS(1,A84),"$1",""),"$","") -> BV | I84: 空白
A85: =MAX(A$11:A84)+1 -> 75 | B85: 更新者名 | F85: 文字列 | G85: 22 | H85: =SUBSTITUTE(SUBSTITUTE(ADDRESS(1,A85),"$1",""),"$","") -> BW | I85: 空白
A86: =MAX(A$11:A85)+1 -> 76 | B86: 更新日時 | F86: 数値 | G86: 17 | H86: =SUBSTITUTE(SUBSTITUTE(ADDRESS(1,A86),"$1",""),"$","") -> BX | I86: 空白
A87: =MAX(A$11:A86)+1 -> 77 | B87: 得意先担当者コード | F87: 半英数 | G87: 15 | H87: =SUBSTITUTE(SUBSTITUTE(ADDRESS(1,A87),"$1",""),"$","") -> BY | I87: 空白
A88: =MAX(A$11:A87)+1 -> 78 | B88: 得意先担当者名 | F88: 文字列 | G88: 22 | H88: =SUBSTITUTE(SUBSTITUTE(ADDRESS(1,A88),"$1",""),"$","") -> BZ | I88: 空白
A89: =MAX(A$11:A88)+1 -> 79 | B89: 得意先担当部門表示コード | F89: コード | G89: 10 | H89: =SUBSTITUTE(SUBSTITUTE(ADDRESS(1,A89),"$1",""),"$","") -> CA | I89: 空白
... A168: =MAX(A$11:A167)+1 -> 158 | B168: 預り源泉対象初期値フラグ | F168: フラグ | G168: 1 | H168: =SUBSTITUTE(SUBSTITUTE(ADDRESS(1,A168),"$1",""),"$","") -> FB | I168: 「0:チェックしない」
A169: =MAX(A$11:A168)+1 -> 159 | B169: 預り源泉税端数計算区分 | E169: 〇 | F169: 区分 | G169: 1 | H169: =SUBSTITUTE(SUBSTITUTE(ADDRESS(1,A169),"$1",""),"$","") -> FC | I169: 「1:切り捨て」
A170: =MAX(A$11:A169)+1 -> 160 | B170: 支払消費税差額計算フラグ | F170: フラグ | G170: 1 | H170: =SUBSTITUTE(SUBSTITUTE(ADDRESS(1,A170),"$1",""),"$","") -> FD | I170: 「0:計算しない」
A171: =MAX(A$11:A170)+1 -> 161 | B171: 取込支払消費税差額計算フラグ | F171: フラグ | G171: 1 | H171: =SUBSTITUTE(SUBSTITUTE(ADDRESS(1,A171),"$1",""),"$","") -> FE | I171: 「0:計算しない」
A172: =MAX(A$11:A171)+1 -> 162 | B172: 共通支払先フラグ | F172: フラグ | G172: 1 | H172: =SUBSTITUTE(SUBSTITUTE(ADDRESS(1,A172),"$1",""),"$","") -> FF | I172: 空白
A173: =MAX(A$11:A172)+1 -> 163 | B173: 支払書内容確認コメント | F173: 文字列 | G173: 100 | H173: =SUBSTITUTE(SUBSTITUTE(ADDRESS(1,A173),"$1",""),"$","") -> FG | I173: 空白
A174: =MAX(A$11:A173)+1 -> 164 | B174: 支払決済条件行番号 | E174: △ | F174: 数値 | G174: 3 | H174: =SUBSTITUTE(SUBSTITUTE(ADDRESS(1,A174),"$1",""),"$","") -> FH | I174: 1から連番で採番する。一つの支払先ごとに「振込先口座ごと、支払方法ごと」に決済方法をグループ化する。 | X174: ★連動元のテーブル情報が決定後に設定値を設計する
A175: =MAX(A$11:A174)+1 -> 165 | B175: 支払決済条件コード | F175: コード | G175: 3 | H175: =SUBSTITUTE(SUBSTITUTE(ADDRESS(1,A175),"$1",""),"$","") -> FI | I175: 001～連番 | X175: ★連動元のテーブル情報が決定後に設定値を設計する
A176: =MAX(A$11:A175)+1 -> 166 | B176: 支払決済条件名 | E176: △ | F176: 文字列 | G176: 80 | H176: =SUBSTITUTE(SUBSTITUTE(ADDRESS(1,A176),"$1",""),"$","") -> FJ | I176: 支払決済条件行番号は「振込先口座ごと、支払方法ごと、出金口座ごと」に採番している。 | X176: ★連動元のテーブル情報が決定後に設定値を設計する
I177: 対象となる振込先口座、支払方法、出金口座の名称を連結させた名称とする。
I179: 振込先口座の名称は以下の条件で取得される、「金融機関マスタ（AN913）．銀行名（漢字）」（22byte）とする。
I180: 金融機関マスタ（AN913）．銀行コード = 金融機関口座マスタ（AN925）．銀行コード
I182: 支払方法は「決済条件マスタ（AN923）．決済条件区分」（2byte）とする。
I184: 出金口座は「決済条件マスタ（AN923）．分類口座コード」（2byte）とする。
A185: =MAX(A$11:A184)+1 -> 167 | B185: 支払決済条件名（略） | E185: △ | F185: 文字列 | G185: 20 | H185: =SUBSTITUTE(SUBSTITUTE(ADDRESS(1,A185),"$1",""),"$","") -> FK | I185: 支払決済条件名の先頭20byte | X185: ★連動元のテーブル情報が決定後に設定値を設計する
A186: =MAX(A$11:A185)+1 -> 168 | B186: 取引形態区分 | E186: △ | F186: 区分 | G186: 1 | H186: =SUBSTITUTE(SUBSTITUTE(ADDRESS(1,A186),"$1",""),"$","") -> FL | I186: 「1:国内取引」
A187: =MAX(A$11:A186)+1 -> 169 | B187: 支払締区分 | E187: △ | F187: 区分 | G187: 1 | H187: =SUBSTITUTE(SUBSTITUTE(ADDRESS(1,A187),"$1",""),"$","") -> FM | I187: 「2:随時取引」
A188: =MAX(A$11:A187)+1 -> 170 | B188: 支払締名寄フラグ | E188: △ | F188: フラグ | G188: 1 | H188: =SUBSTITUTE(SUBSTITUTE(ADDRESS(1,A188),"$1",""),"$","") -> FN | I188: 「0:名寄せしない」
A189: =MAX(A$11:A188)+1 -> 171 | B189: 名寄部門表示コード | F189: コード | G189: 10 | H189: =SUBSTITUTE(SUBSTITUTE(ADDRESS(1,A189),"$1",""),"$","") -> FO | I189: 空白
A190: =MAX(A$11:A189)+1 -> 172 | B190: 名寄部門名（略） | F190: 文字列 | G190: 20 | H190: =SUBSTITUTE(SUBSTITUTE(ADDRESS(1,A190),"$1",""),"$","") -> FP | I190: 空白
A191: =MAX(A$11:A190)+1 -> 173 | B191: 名寄部門基準日付 | F191: 日付 | G191: 8 | H191: =SUBSTITUTE(SUBSTITUTE(ADDRESS(1,A191),"$1",""),"$","") -> FQ | I191: 空白
A192: =MAX(A$11:A191)+1 -> 174 | B192: 支払通知書書式区分 | E192: △ | F192: 区分 | G192: 1 | H192: =SUBSTITUTE(SUBSTITUTE(ADDRESS(1,A192),"$1",""),"$","") -> FR | I192: 空白
A193: =MAX(A$11:A192)+1 -> 175 | B193: 支払通知書品目内訳表示フラグ | E193: △ | F193: フラグ | G193: 1 | H193: =SUBSTITUTE(SUBSTITUTE(ADDRESS(1,A193),"$1",""),"$","") -> FS | I193: 空白
A194: =MAX(A$11:A193)+1 -> 176 | B194: 支払基準金額 | E194: △ | F194: 数値 | G194: 13 | H194: =SUBSTITUTE(SUBSTITUTE(ADDRESS(1,A194),"$1",""),"$","") -> FT | I194: 空白
A195: =MAX(A$11:A194)+1 -> 177 | B195: 支払決済条件使用不可フラグ | E195: △ | F195: フラグ | G195: 1 | H195: =SUBSTITUTE(SUBSTITUTE(ADDRESS(1,A195),"$1",""),"$","") -> FU | I195: 「0:使用する」
A196: =MAX(A$11:A195)+1 -> 178 | B196: 分割条件（未満） | E196: △ | F196: 区分 | G196: 1 | H196: =SUBSTITUTE(SUBSTITUTE(ADDRESS(1,A196),"$1",""),"$","") -> FV | I196: 「1:分割しない」
A197: =MAX(A$11:A196)+1 -> 179 | B197: 分割率（未満） | E197: △ | F197: 数値 | G197: 3 | H197: =SUBSTITUTE(SUBSTITUTE(ADDRESS(1,A197),"$1",""),"$","") -> FW | I197: 空白
A198: =MAX(A$11:A197)+1 -> 180 | B198: 端数桁数（未満） | E198: △ | F198: 数値 | G198: 2 | H198: =SUBSTITUTE(SUBSTITUTE(ADDRESS(1,A198),"$1",""),"$","") -> FX | I198: 空白
A199: =MAX(A$11:A198)+1 -> 181 | B199: 端数区分（未満） | E199: △ | F199: 区分 | G199: 1 | H199: =SUBSTITUTE(SUBSTITUTE(ADDRESS(1,A199),"$1",""),"$","") -> FY | I199: 空白
A200: =MAX(A$11:A199)+1 -> 182 | B200: 分割基準金額（未満） | E200: △ | F200: 数値 | G200: 13 | H200: =SUBSTITUTE(SUBSTITUTE(ADDRESS(1,A200),"$1",""),"$","") -> FZ | I200: 空白
A201: =MAX(A$11:A200)+1 -> 183 | B201: 支払方法コード（未満１） | E201: △ | F201: コード | G201: 3 | H201: =SUBSTITUTE(SUBSTITUTE(ADDRESS(1,A201),"$1",""),"$","") -> GA | I201: 決済条件マスタ（AN923）．決済条件区分 | X201: ★連動元のテーブル情報が決定後に設定値を設計する
A202: =MAX(A$11:A201)+1 -> 184 | B202: 支払方法名（未満１） | F202: 文字列 | G202: 20 | H202: =SUBSTITUTE(SUBSTITUTE(ADDRESS(1,A202),"$1",""),"$","") -> GB | I202: 空白
A203: =MAX(A$11:A202)+1 -> 185 | B203: 休日考慮区分（未満１） | E203: △ | F203: 区分 | G203: 1 | H203: =SUBSTITUTE(SUBSTITUTE(ADDRESS(1,A203),"$1",""),"$","") -> GC | I203: 銀行が休日の場合の期日前後の制御を指定。
I204: 1:休日前、2:休日後月跨ぎ、3:休日後月跨がない、9:考慮しない、のいずれか。 | O204: 【要ヒアリング】 支払予定日が休日の場合に休日考慮をどうするか？
A205: =MAX(A$11:A204)+1 -> 186 | B205: 出金口座コード（未満１） | F205: コード | G205: 8 | H205: =SUBSTITUTE(SUBSTITUTE(ADDRESS(1,A205),"$1",""),"$","") -> GD | I205: 出金口座の自社口座コード
...

Sheet 取込フォーマット定義（職員）※支払先
A1: ドキュメント名 | E1: サブシステム | G1: 業務機能名 | P1: 作成者 | R1: SCSK位田 | T1: 更新者
A2: 業務機能概要書 | C2: 取込フォーマット定義 | E2: 業務共通 | G2: 取引先マスタ自動取込 | P2: 作成日 | R2: =表紙!C51 -> 45898 | T2: 更新日
A4: データ名 | C4: 支払先外部データ取込フォーマット | I4: ヘッダ行 | K4: あり | M4: なし | N4: ダブルクォーテーション | Q4: あり | S4: なし | X4: 文字列
A5: ﾌｧｲﾙ形式・ﾚｺｰﾄﾞ長 | D5: 固定長（ | G5: Byte） | I5: 可変長（区切り文字［ ，(カンマ) ］） | M5: バイナリデータ | P5: その他（ ） | X5: 半英数
A6: 文字コード | D6: UNI（Win系） | F6: EBCDIC(K) | I6: その他（ UTF-8） | M6: 改行コード | O6: LF(UNIX系) | Q6: CRLF(Win系) | T6: なし | X6: 半カナ
A7: 全角(2byte)文字項目 | D7: あり | F7: なし | M7: 数値編集 | O7: 左詰め | Q7: 右詰め［ゼロ埋め］ | T7: 右詰め［スペース埋め］ | X7: コード
A8: 特記事項 | C8: 取込ファイルには、取込項目のタイトル行が必要となる | X8: 数値
A9: No. | B9: 項目名 | E9: 必須 | F9: 型 | G9: 桁数 | H9: 開始位置 | I9: 項目説明 | O9: 設定値 | X9: 日付
H10: /列 | X10: 時間
A11: 1 | B11: 編集区分 | E11: 〇 | F11: 区分 | G11: 1 | H11: =SUBSTITUTE(SUBSTITUTE(ADDRESS(1,A11),"$1",""),"$","") -> A | I11: 新規追加データの場合は「1:新規」、 | O11: 左記のとおり設定 | X11: 年月
I12: 既存データの修正および削除（使用不可フラグを１に更新）の場合は「２:修正」
I13: 既存支払先に対して、決済条件を追加する際も「２：修正」を使用する | X13: 区分
A14: =MAX(A$11:A11)+1 -> 2 | B14: 新規変更区分名称 | F14: 文字列 | G14: 4 | H14: =SUBSTITUTE(SUBSTITUTE(ADDRESS(1,A14),"$1",""),"$","") -> B | I14: 空白 | O14: 設定なし | X14: 区分
A15: =MAX(A$11:A14)+1 -> 3 | B15: 取引先区分コード | E15: 〇 | F15: コード | G15: 2 | H15: =SUBSTITUTE(SUBSTITUTE(ADDRESS(1,A15),"$1",""),"$","") -> C | I15: 「00:初期導入」 | O15: 「00:初期導入」（固定値） | X15: フラグ
A16: =MAX(A$11:A15)+1 -> 4 | B16: 取引先区分名 | F16: 文字列 | G16: 20 | H16: =SUBSTITUTE(SUBSTITUTE(ADDRESS(1,A16),"$1",""),"$","") -> D | I16: 空白 | O16: 設定なし | X16: -
A17: =MAX(A$11:A16)+1 -> 5 | B17: 取引先コード | E17: △ | F17: コード | G17: 15 | H17: =SUBSTITUTE(SUBSTITUTE(ADDRESS(1,A17),"$1",""),"$","") -> E | I17: 支払先を一意に特定するコード | O17: 職員コード
A18: =MAX(A$11:A17)+1 -> 6 | B18: 社内取引部門表示コード | E18: △ | F18: コード | G18: 15 | H18: =SUBSTITUTE(SUBSTITUTE(ADDRESS(1,A18),"$1",""),"$","") -> F | I18: 空白 | O18: 設定なし
A19: =MAX(A$11:A18)+1 -> 7 | B19: 社内取引部門名（略） | F19: 文字列 | G19: 20 | H19: =SUBSTITUTE(SUBSTITUTE(ADDRESS(1,A19),"$1",""),"$","") -> G | I19: 空白 | O19: 設定なし
A20: =MAX(A$11:A19)+1 -> 8 | B20: 適格請求書発行事業者登録番号 | F20: 文字列 | G20: 14 | H20: =SUBSTITUTE(SUBSTITUTE(ADDRESS(1,A20),"$1",""),"$","") -> H | I20: 空白 | O20: 設定なし
A21: =MAX(A$11:A20)+1 -> 9 | B21: 企業コード | E21: △ | F21: コード | G21: 15 | H21: =SUBSTITUTE(SUBSTITUTE(ADDRESS(1,A21),"$1",""),"$","") -> I | I21: 空白 | O21: 設定なし
A22: =MAX(A$11:A21)+1 -> 10 | B22: 企業名（略） | F22: 文字列 | G22: 20 | H22: =SUBSTITUTE(SUBSTITUTE(ADDRESS(1,A22),"$1",""),"$","") -> J | I22: 空白 | O22: 設定なし
A23: =MAX(A$11:A22)+1 -> 11 | B23: 得意先フラグ | F23: フラグ | G23: 1 | H23: =SUBSTITUTE(SUBSTITUTE(ADDRESS(1,A23),"$1",""),"$","") -> K | I23: 「0:得意先として使用しない」 | O23: ０（固定値）
A24: =MAX(A$11:A23)+1 -> 12 | B24: 需要家フラグ | F24: フラグ | G24: 1 | H24: =SUBSTITUTE(SUBSTITUTE(ADDRESS(1,A24),"$1",""),"$","") -> L | I24: 「0:需要家として使用しない」 | O24: ０（固定値）
A25: =MAX(A$11:A24)+1 -> 13 | B25: 出荷先フラグ | F25: フラグ | G25: 1 | H25: =SUBSTITUTE(SUBSTITUTE(ADDRESS(1,A25),"$1",""),"$","") -> M | I25: 「0:出荷先として使用しない」 | O25: ０（固定値）
A26: =MAX(A$11:A25)+1 -> 14 | B26: 仕入先フラグ | F26: フラグ | G26: 1 | H26: =SUBSTITUTE(SUBSTITUTE(ADDRESS(1,A26),"$1",""),"$","") -> N | I26: 「0:仕入先として使用しない」 | O26: ０（固定値）
A27: =MAX(A$11:A26)+1 -> 15 | B27: 入荷元フラグ | F27: フラグ | G27: 1 | H27: =SUBSTITUTE(SUBSTITUTE(ADDRESS(1,A27),"$1",""),"$","") -> O | I27: 「0:入荷元として使用しない」 | O27: ０（固定値）
A28: =MAX(A$11:A27)+1 -> 16 | B28: 請求先フラグ | F28: フラグ | G28: 1 | H28: =SUBSTITUTE(SUBSTITUTE(ADDRESS(1,A28),"$1",""),"$","") -> P | I28: 「0:請求先として使用しない」 | O28: ０（固定値）
A29: =MAX(A$11:A28)+1 -> 17 | B29: 支払先フラグ | F29: フラグ | G29: 1 | H29: =SUBSTITUTE(SUBSTITUTE(ADDRESS(1,A29),"$1",""),"$","") -> Q | I29: 「1:支払先として使用する」 | O29: １（固定値）
A30: =MAX(A$11:A29)+1 -> 18 | B30: 諸口取引先フラグ | F30: フラグ | G30: 1 | H30: =SUBSTITUTE(SUBSTITUTE(ADDRESS(1,A30),"$1",""),"$","") -> R | I30: 「0:取引先」 | O30: 0
A31: =MAX(A$11:A30)+1 -> 19 | B31: 取引先名１ | E31: 〇 | F31: 文字列 | G31: 50 | H31: =SUBSTITUTE(SUBSTITUTE(ADDRESS(1,A31),"$1",""),"$","") -> S | I31: 取引先の名称 | O31: 名称住所マスタ.取引先名（漢字）の先頭50桁(25文字) | T31: ※取引先名：全角50文字(法人30文字、店舗20文字) | X31: ※連動元システムでは常に全角で情報を保持
A32: =MAX(A$11:A31)+1 -> 20 | B32: 取引先名２ | F32: 文字列 | G32: 50 | H32: =SUBSTITUTE(SUBSTITUTE(ADDRESS(1,A32),"$1",""),"$","") -> T | I32: 空白 | O32: 名称住所マスタ.取引先名（漢字）の51～100桁(25文字)
A33: =MAX(A$11:A32)+1 -> 21 | B33: 取引先名（略） | E33: 〇 | F33: 文字列 | G33: 20 | H33: =SUBSTITUTE(SUBSTITUTE(ADDRESS(1,A33),"$1",""),"$","") -> U | I33: 取引先の略称 | O33: 名称住所マスタ.取引先略称名（漢字）の先頭20桁(10文字) | T33: ※取引先名（略）：全角25文字（法人13文字、店舗12文字） | X33: ※連動元システムでは常に全角で情報を保持
A34: =MAX(A$11:A33)+1 -> 22 | B34: 取引先名（カナ） | E34: 〇 | F34: 半カナ | G34: 40 | H34: =SUBSTITUTE(SUBSTITUTE(ADDRESS(1,A34),"$1",""),"$","") -> V | I34: 取引先のカナ名称 | O34: 名称住所マスタ.取引先略称名（カナ）の先頭40桁 | T34: ※カナ略称：半角50文字（法人26文字、店舗24文字）
A35: =MAX(A$11:A34)+1 -> 23 | B35: 取引先名（英字） | F35: 半英数 | G35: 40 | H35: =SUBSTITUTE(SUBSTITUTE(ADDRESS(1,A35),"$1",""),"$","") -> W | I35: 空白 | O35: 設定なし
A36: =MAX(A$11:A35)+1 -> 24 | B36: 休日パターンコード | F36: コード | G36: 5 | H36: =SUBSTITUTE(SUBSTITUTE(ADDRESS(1,A36),"$1",""),"$","") -> X | I36: 空白 | O36: 設定なし
A37: =MAX(A$11:A36)+1 -> 25 | B37: 休日パターン名 | F37: 文字列 | G37: 40 | H37: =SUBSTITUTE(SUBSTITUTE(ADDRESS(1,A37),"$1",""),"$","") -> Y | I37: 空白 | O37: 設定なし
A38: =MAX(A$11:A37)+1 -> 26 | B38: 国コード | F38: コード | G38: 3 | H38: =SUBSTITUTE(SUBSTITUTE(ADDRESS(1,A38),"$1",""),"$","") -> Z | I38: 空白 | O38: 設定なし
A39: =MAX(A$11:A38)+1 -> 27 | B39: 国名称 | F39: 文字列 | G39: 20 | H39: =SUBSTITUTE(SUBSTITUTE(ADDRESS(1,A39),"$1",""),"$","") -> AA | I39: 空白 | O39: 設定なし
A40: =MAX(A$11:A39)+1 -> 28 | B40: 取引先地域分類値コード | F40: コード | G40: 4 | H40: =SUBSTITUTE(SUBSTITUTE(ADDRESS(1,A40),"$1",""),"$","") -> AB | I40: 空白 | O40: 設定なし
A41: =MAX(A$11:A40)+1 -> 29 | B41: 取引先地域分類値 | F41: 文字列 | G41: 20 | H41: =SUBSTITUTE(SUBSTITUTE(ADDRESS(1,A41),"$1",""),"$","") -> AC | I41: 空白 | O41: 設定なし
A42: =MAX(A$11:A41)+1 -> 30 | B42: 郵便番号 | F42: 半英数 | G42: 8 | H42: =SUBSTITUTE(SUBSTITUTE(ADDRESS(1,A42),"$1",""),"$","") -> AD | I42: 空白 | O42: 設定なし
A43: =MAX(A$11:A42)+1 -> 31 | B43: 住所１ | F43: 文字列 | G43: 100 | H43: =SUBSTITUTE(SUBSTITUTE(ADDRESS(1,A43),"$1",""),"$","") -> AE | I43: 空白 | O43: 設定なし
A44: =MAX(A$11:A43)+1 -> 32 | B44: 住所２ | F44: 文字列 | G44: 100 | H44: =SUBSTITUTE(SUBSTITUTE(ADDRESS(1,A44),"$1",""),"$","") -> AF | I44: 空白 | O44: 設定なし
A45: =MAX(A$11:A44)+1 -> 33 | B45: 住所３ | F45: 文字列 | G45: 100 | H45: =SUBSTITUTE(SUBSTITUTE(ADDRESS(1,A45),"$1",""),"$","") -> AG | I45: 空白 | O45: 設定なし
A46: =MAX(A$11:A45)+1 -> 34 | B46: ＴＥＬ | F46: 半英数 | G46: 20 | H46: =SUBSTITUTE(SUBSTITUTE(ADDRESS(1,A46),"$1",""),"$","") -> AH | I46: 空白 | O46: 設定なし
... A70: =MAX(A$11:A69)+1 -> 58 | B70: 分類値１０ | F70: 文字列 | G70: 20 | H70: =SUBSTITUTE(SUBSTITUTE(ADDRESS(1,A70),"$1",""),"$","") -> BF | I70: 空白 | O70: 設定なし
A71: =MAX(A$11:A70)+1 -> 59 | B71: 使用不可フラグ | E71: 〇 | F71: フラグ | G71: 1 | H71: =SUBSTITUTE(SUBSTITUTE(ADDRESS(1,A71),"$1",""),"$","") -> BG | I71: 「0:使用可」 | O71: 編集区分が削除場合は１それ以外は０ ⇒ データ連動時は常に「０：使用可」
A72: =MAX(A$11:A71)+1 -> 60 | B72: 取引先所在地区分 | E72: 〇 | F72: 区分 | G72: 1 | H72: =SUBSTITUTE(SUBSTITUTE(ADDRESS(1,A72),"$1",""),"$","") -> BH | I72: 「0:国内」 | O72: ０（固定値）
A73: =MAX(A$11:A72)+1 -> 61 | B73: 取引先所在地区分名 | F73: 文字列 | G73: 4 | H73: =SUBSTITUTE(SUBSTITUTE(ADDRESS(1,A73),"$1",""),"$","") -> BI | I73: 空白 | O73: 設定なし
A74: =MAX(A$11:A73)+1 -> 62 | B74: 国内取引フラグ | E74: △ | F74: フラグ | G74: 1 | H74: =SUBSTITUTE(SUBSTITUTE(ADDRESS(1,A74),"$1",""),"$","") -> BJ | I74: 「1:使用する」 | O74: １（固定値）
A75: =MAX(A$11:A74)+1 -> 63 | B75: 外為取引フラグ | E75: △ | F75: フラグ | G75: 1 | H75: =SUBSTITUTE(SUBSTITUTE(ADDRESS(1,A75),"$1",""),"$","") -> BK | I75: 「0:使用しない」 | O75: ０（固定値）
A76: =MAX(A$11:A75)+1 -> 64 | B76: 通貨コード | E76: △ | F76: コード | G76: 3 | H76: =SUBSTITUTE(SUBSTITUTE(ADDRESS(1,A76),"$1",""),"$","") -> BL | I76: 空白 | O76: 設定なし
A77: =MAX(A$11:A76)+1 -> 65 | B77: 消費税端数計算区分 | F77: 区分 | G77: 1 | H77: =SUBSTITUTE(SUBSTITUTE(ADDRESS(1,A77),"$1",""),"$","") -> BM | I77: 「1:切り捨て」 | O77: 設定なし | Q77: ※ブランク時は3：四捨五入が採用される
A78: =MAX(A$11:A77)+1 -> 66 | B78: 消費税計算単位区分 | F78: 区分 | G78: 1 | H78: =SUBSTITUTE(SUBSTITUTE(ADDRESS(1,A78),"$1",""),"$","") -> BN | I78: 「2:明細単位」 | O78: ２：明細単位
A79: =MAX(A$11:A78)+1 -> 67 | B79: 取引金額端数処理区分 | F79: 区分 | G79: 1 | H79: =SUBSTITUTE(SUBSTITUTE(ADDRESS(1,A79),"$1",""),"$","") -> BO | I79: 「1:切り捨て」 | O79: 設定なし | Q79: ※ブランク時は3：四捨五入が採用される
A80: =MAX(A$11:A79)+1 -> 68 | B80: 承認申請状況区分名 | F80: 文字列 | G80: 6 | H80: =SUBSTITUTE(SUBSTITUTE(ADDRESS(1,A80),"$1",""),"$","") -> BP | I80: 空白 | O80: 設定なし
A81: =MAX(A$11:A80)+1 -> 69 | B81: 承認申請番号 | F81: コード | G81: 20 | H81: =SUBSTITUTE(SUBSTITUTE(ADDRESS(1,A81),"$1",""),"$","") -> BQ | I81: 空白 | O81: 設定なし
A82: =MAX(A$11:A81)+1 -> 70 | B82: 承認申請日付 | F82: 日付 | G82: 8 | H82: =SUBSTITUTE(SUBSTITUTE(ADDRESS(1,A82),"$1",""),"$","") -> BR | I82: 空白 | O82: 設定なし
A83: =MAX(A$11:A82)+1 -> 71 | B83: 承認申請者名 | F83: 文字列 | G83: 22 | H83: =SUBSTITUTE(SUBSTITUTE(ADDRESS(1,A83),"$1",""),"$","") -> BS | I83: 空白 | O83: 設定なし
A84: =MAX(A$11:A83)+1 -> 72 | B84: 承認申請部門名（略） | F84: 文字列 | G84: 20 | H84: =SUBSTITUTE(SUBSTITUTE(ADDRESS(1,A84),"$1",""),"$","") -> BT | I84: 空白 | O84: 設定なし
A85: =MAX(A$11:A84)+1 -> 73 | B85: 登録者名 | F85: 文字列 | G85: 22 | H85: =SUBSTITUTE(SUBSTITUTE(ADDRESS(1,A85),"$1",""),"$","") -> BU | I85: 空白 | O85: 設定なし
A86: =MAX(A$11:A85)+1 -> 74 | B86: 登録日時 | F86: 数値 | G86: 17 | H86: =SUBSTITUTE(SUBSTITUTE(ADDRESS(1,A86),"$1",""),"$","") -> BV | I86: 空白 | O86: 設定なし
A87: =MAX(A$11:A86)+1 -> 75 | B87: 更新者名 | F87: 文字列 | G87: 22 | H87: =SUBSTITUTE(SUBSTITUTE(ADDRESS(1,A87),"$1",""),"$","") -> BW | I87: 空白 | O87: 設定なし
A88: =MAX(A$11:A87)+1 -> 76 | B88: 更新日時 | F88: 数値 | G88: 17 | H88: =SUBSTITUTE(SUBSTITUTE(ADDRESS(1,A88),"$1",""),"$","") -> BX | I88: 空白 | O88: 設定なし
A89: =MAX(A$11:A88)+1 -> 77 | B89: 得意先担当者コード | F89: 半英数 | G89: 15 | H89: =SUBSTITUTE(SUBSTITUTE(ADDRESS(1,A89),"$1",""),"$","") -> BY | I89: 空白 | O89: 設定なし
A90: =MAX(A$11:A89)+1 -> 78 | B90: 得意先担当者名 | F90: 文字列 | G90: 22 | H90: =SUBSTITUTE(SUBSTITUTE(ADDRESS(1,A90),"$1",""),"$","") -> BZ | I90: 空白 | O90: 設定なし
A91: =MAX(A$11:A90)+1 -> 79 | B91: 得意先担当部門表示コード | F91: コード | G91: 10 | H91: =SUBSTITUTE(SUBSTITUTE(ADDRESS(1,A91),"$1",""),"$","") -> CA | I91: 空白 | O91: 設定なし
... A170: =MAX(A$11:A169)+1 -> 158 | B170: 預り源泉対象初期値フラグ | F170: フラグ | G170: 1 | H170: =SUBSTITUTE(SUBSTITUTE(ADDRESS(1,A170),"$1",""),"$","") -> FB | I170: 「0:チェックしない」 | O170: ０（固定値）
A171: =MAX(A$11:A170)+1 -> 159 | B171: 預り源泉税端数計算区分 | E171: 〇 | F171: 区分 | G171: 1 | H171: =SUBSTITUTE(SUBSTITUTE(ADDRESS(1,A171),"$1",""),"$","") -> FC | I171: 「1:切り捨て」 | O171: １（固定値）
A172: =MAX(A$11:A171)+1 -> 160 | B172: 支払消費税差額計算フラグ | F172: フラグ | G172: 1 | H172: =SUBSTITUTE(SUBSTITUTE(ADDRESS(1,A172),"$1",""),"$","") -> FD | I172: 「0:計算しない」 | O172: ０（固定値）
A173: =MAX(A$11:A172)+1 -> 161 | B173: 取込支払消費税差額計算フラグ | F173: フラグ | G173: 1 | H173: =SUBSTITUTE(SUBSTITUTE(ADDRESS(1,A173),"$1",""),"$","") -> FE | I173: 「0:計算しない」 | O173: ０（固定値）
A174: =MAX(A$11:A173)+1 -> 162 | B174: 共通支払先フラグ | F174: フラグ | G174: 1 | H174: =SUBSTITUTE(SUBSTITUTE(ADDRESS(1,A174),"$1",""),"$","") -> FF | I174: 空白 | O174: 設定なし | R174: → 0（固定値）
A175: =MAX(A$11:A174)+1 -> 163 | B175: 支払書内容確認コメント | F175: 文字列 | G175: 100 | H175: =SUBSTITUTE(SUBSTITUTE(ADDRESS(1,A175),"$1",""),"$","") -> FG | I175: 空白 | O175: 設定なし
A176: =MAX(A$11:A175)+1 -> 164 | B176: 支払決済条件行番号 | E176: △ | F176: 数値 | G176: 3 | H176: =SUBSTITUTE(SUBSTITUTE(ADDRESS(1,A176),"$1",""),"$","") -> FH | I176: 1から連番で採番する。 | O176: *支払決済条件コードと同じ値を設定
A177: =MAX(A$11:A176)+1 -> 165 | B177: 支払決済条件コード | F177: コード | G177: 3 | H177: =SUBSTITUTE(SUBSTITUTE(ADDRESS(1,A177),"$1",""),"$","") -> FI | I177: 001～連番 | O177: 001～020：振込以外の支払方法の場合に採番、021～999：決済条件マスタに登録されている振込払の場合に採番
A178: =MAX(A$11:A177)+1 -> 166 | B178: 支払決済条件名 | E178: △ | F178: 文字列 | G178: 80 | H178: =SUBSTITUTE(SUBSTITUTE(ADDRESS(1,A178),"$1",""),"$","") -> FJ | I178: 支払決済条件の名称 | O178: 振込以外は、支払方法の名称（納付書、自動引落については、"支払方法の名称+（信連）"、"支払方法の名称+（道銀）"のような出金口座が識別できる名称をセット）を設定。振込の場合は支払先口座として設定されている金融機関マスタの銀行名（漢字）(30byte)＋本・支店名（漢字）(20byte)を設定。
A182: =MAX(A$11:A181)+1 -> 167 | B182: 支払決済条件名（略） | E182: △ | F182: 文字列 | G182: 20 | H182: =SUBSTITUTE(SUBSTITUTE(ADDRESS(1,A182),"$1",""),"$","") -> FK | I182: 支払決済条件名の略称 | O182: 支払決済条件名に設定した値から20byte切り出した値
A183: =MAX(A$11:A182)+1 -> 168 | B183: 取引形態区分 | E183: △ | F183: 区分 | G183: 1 | H183: =SUBSTITUTE(SUBSTITUTE(ADDRESS(1,A183),"$1",""),"$","") -> FL | I183: 「1:国内取引」 | O183: １（固定値）
A184: =MAX(A$11:A183)+1 -> 169 | B184: 支払締区分 | E184: △ | F184: 区分 | G184: 1 | H184: =SUBSTITUTE(SUBSTITUTE(ADDRESS(1,A184),"$1",""),"$","") -> FM | I184: 「2:随時取引」 | O184: ２（固定値）
A185: =MAX(A$11:A184)+1 -> 170 | B185: 支払締名寄フラグ | E185: △ | F185: フラグ | G185: 1 | H185: =SUBSTITUTE(SUBSTITUTE(ADDRESS(1,A185),"$1",""),"$","") -> FN | I185: 「0:名寄せしない」 | O185: ０（固定値）
A186: =MAX(A$11:A185)+1 -> 171 | B186: 名寄部門表示コード | F186: コード | G186: 10 | H186: =SUBSTITUTE(SUBSTITUTE(ADDRESS(1,A186),"$1",""),"$","") -> FO | I186: 空白 | O186: 設定なし
A187: =MAX(A$11:A186)+1 -> 172 | B187: 名寄部門名（略） | F187: 文字列 | G187: 20 | H187: =SUBSTITUTE(SUBSTITUTE(ADDRESS(1,A187),"$1",""),"$","") -> FP | I187: 空白 | O187: 設定なし
A188: =MAX(A$11:A187)+1 -> 173 | B188: 名寄部門基準日付 | F188: 日付 | G188: 8 | H188: =SUBSTITUTE(SUBSTITUTE(ADDRESS(1,A188),"$1",""),"$","") -> FQ | I188: 空白 | O188: 設定なし
A189: =MAX(A$11:A188)+1 -> 174 | B189: 支払通知書書式区分 | E189: △ | F189: 区分 | G189: 1 | H189: =SUBSTITUTE(SUBSTITUTE(ADDRESS(1,A189),"$1",""),"$","") -> FR | I189: 空白 | O189: 設定なし | R189: → 3（固定値） | T189: ※諸口支払先の場合、3のみ許容
A190: =MAX(A$11:A189)+1 -> 175 | B190: 支払通知書品目内訳表示フラグ | E190: △ | F190: フラグ | G190: 1 | H190: =SUBSTITUTE(SUBSTITUTE(ADDRESS(1,A190),"$1",""),"$","") -> FS | I190: 空白 | O190: 設定なし | R190: → 0（固定値）
A191: =MAX(A$11:A190)+1 -> 176 | B191: 支払基準金額 | E191: △ | F191: 数値 | G191: 13 | H191: =SUBSTITUTE(SUBSTITUTE(ADDRESS(1,A191),"$1",""),"$","") -> FT | I191: 空白 | O191: 設定なし | R191: → 0（固定値）
A192: =MAX(A$11:A191)+1 -> 177 | B192: 支払決済条件使用不可フラグ | E192: △ | F192: フラグ | G192: 1 | H192: =SUBSTITUTE(SUBSTITUTE(ADDRESS(1,A192),"$1",""),"$","") -> FU | I192: 「0:使用する」 | O192: ０（固定値）
A193: =MAX(A$11:A192)+1 -> 178 | B193: 分割条件（未満） | E193: △ | F193: 区分 | G193: 1 | H193: =SUBSTITUTE(SUBSTITUTE(ADDRESS(1,A193),"$1",""),"$","") -> FV | I193: 「1:分割しない」 | O193: １（固定値）
A194: =MAX(A$11:A193)+1 -> 179 | B194: 分割率（未満） | E194: △ | F194: 数値 | G194: 3 | H194: =SUBSTITUTE(SUBSTITUTE(ADDRESS(1,A194),"$1",""),"$","") -> FW | I194: 空白 | O194: 設定なし
A195: =MAX(A$11:A194)+1 -> 180 | B195: 端数桁数（未満） | E195: △ | F195: 数値 | G195: 2 | H195: =SUBSTITUTE(SUBSTITUTE(ADDRESS(1,A195),"$1",""),"$","") -> FX | I195: 空白 | O195: 設定なし
A196: =MAX(A$11:A195)+1 -> 181 | B196: 端数区分（未満） | E196: △ | F196: 区分 | G196: 1 | H196: =SUBSTITUTE(SUBSTITUTE(ADDRESS(1,A196),"$1",""),"$","") -> FY | I196: 空白 | O196: 設定なし
A197: =MAX(A$11:A196)+1 -> 182 | B197: 分割基準金額（未満） | E197: △ | F197: 数値 | G197: 13 | H197: =SUBSTITUTE(SUBSTITUTE(ADDRESS(1,A197),"$1",""),"$","") -> FZ | I197: 空白 | O197: 設定なし
A198: =MAX(A$11:A197)+1 -> 183 | B198: 支払方法コード（未満１） | E198: △ | F198: コード | G198: 3 | H198: =SUBSTITUTE(SUBSTITUTE(ADDRESS(1,A198),"$1",""),"$","") -> GA | I198: 決済条件マスタ（AN923）．決済条件区分 | O198: 決済条件マスタ.回収支払方法区分
A199: =MAX(A$11:A198)+1 -> 184 | B199: 支払方法名（未満１） | F199: 文字列 | G199: 20 | H199: =SUBSTITUTE(SUBSTITUTE(ADDRESS(1,A199),"$1",""),"$","") -> GB | I199: 空白 | O199: 設定なし
A200: =MAX(A$11:A199)+1 -> 185 | B200: 休日考慮区分（未満１） | E200: △ | F200: 区分 | G200: 1 | H200: =SUBSTITUTE(SUBSTITUTE(ADDRESS(1,A200),"$1",""),"$","") -> GC | I200: 銀行が休日の場合の期日前後の制御を指定。 | O200: ９：考慮しない（固定値）
I201: 1:休日前、2:休日後月跨ぎ、3:休日後月跨がない、9:考慮しない、のいずれか。
A202: =MAX(A$11:A201)+1 -> 186 | B202: 出金口座コード（未満１） | F202: コード | G202: 8 | H202: =SUBSTITUTE(SUBSTITUTE(ADDRESS(1,A202),"$1",""),"$","") -> GD | I202: 出金口座の自社口座コード（振込の場合は設定不要） | O202: ホクレン口座マスタのホクレン口座コードを設定（職員に対して、納付書や自動引落なとはありえないので未設定でも問題無い）
I203: ※債務システム設定、金融機関マスタ、部門別口座マスタを活用。
I204: 「補足2 出金口座の導出」シート参照。
A205: =MAX(A$11:A202)+1 -> 187 | B205: 出金口座名（未満１） | F205: 文字列 | G205: 20 | H205: =SUBSTITUTE(SUBSTITUTE(ADDRESS(1,A205),"$1",""),"$","") -> GE | I205: 空白 | O205: 設定なし
...

Sheet 取込フォーマット定義（取引先）
A1: ドキュメント名 | E1: サブシステム | G1: 業務機能名 | P1: 作成者 | R1: =表紙!D51 -> SCSK位田 | T1: 更新者
A2: 業務機能概要書 | C2: 取込フォーマット定義 | E2: =業務機能概要!L2 -> 業務共通 | G2: =業務機能概要!Q2 -> 取引先マスタ自動取込 | P2: 作成日 | R2: =表紙!C51 -> 45898 | T2: 更新日
A4: データ名 | C4: 取引先外部データ取込フォーマット | I4: ヘッダ行 | K4: あり | M4: なし | N4: ダブルクォーテーション | Q4: あり | S4: なし | X4: 文字列
A5: ﾌｧｲﾙ形式・ﾚｺｰﾄﾞ長 | D5: 固定長（ | G5: Byte） | I5: 可変長（区切り文字［ ，(カンマ) ］） | M5: バイナリデータ | P5: その他（ ） | X5: 半英数
A6: 文字コード | D6: UNI（Win系） | F6: EBCDIC(K) | I6: その他（ UTF-8） | M6: 改行コード | O6: LF(UNIX系) | Q6: CRLF(Win系) | T6: なし | X6: 半カナ
A7: 全角(2byte)文字項目 | D7: あり | F7: なし | M7: 数値編集 | O7: 左詰め | Q7: 右詰め［ゼロ埋め］ | T7: 右詰め［スペース埋め］ | X7: コード
A8: 特記事項 | C8: 取込ファイルには、取込項目のタイトル行が必要となる | X8: 数値
A9: No. | B9: 項目名 | E9: 必須 | F9: 型 | G9: 桁数 | H9: 開始位置 | I9: 備考 | X9: 日付
H10: /列 | X10: 時間
A11: 1 | B11: 編集区分 | E11: 〇 | F11: 区分 | G11: 1 | H11: =SUBSTITUTE(SUBSTITUTE(ADDRESS(1,A11),"$1",""),"$","") -> A | I11: 新規追加データの場合は「1:新規」、 | O11: 左記のとおり設定 | X11: 年月
I12: 既存データの修正および削除（使用不可フラグを１に更新）の場合は「２:修正」 | X12: 区分
X13: フラグ
A14: =MAX(A$11:A11)+1 -> 2 | B14: 新規変更区分名称 | F14: 文字列 | G14: 4 | H14: =SUBSTITUTE(SUBSTITUTE(ADDRESS(1,A14),"$1",""),"$","") -> B | I14: 空白 | O14: 設定なし | X14: -
A15: =MAX(A$11:A14)+1 -> 3 | B15: 取引先区分コード | E15: 〇 | F15: コード | G15: 2 | H15: =SUBSTITUTE(SUBSTITUTE(ADDRESS(1,A15),"$1",""),"$","") -> C | I15: 「00:初期導入」 | O15: 「00:初期導入」（固定値）
A16: =MAX(A$11:A15)+1 -> 4 | B16: 取引先区分名 | F16: 文字列 | G16: 20 | H16: =SUBSTITUTE(SUBSTITUTE(ADDRESS(1,A16),"$1",""),"$","") -> D | I16: 空白 | O16: 設定なし
A17: =MAX(A$11:A16)+1 -> 5 | B17: 取引先コード | E17: △ | F17: コード | G17: 15 | H17: =SUBSTITUTE(SUBSTITUTE(ADDRESS(1,A17),"$1",""),"$","") -> E | I17: 取引先を一意に特定するコード | O17: 取引先コード（9桁）
A18: =MAX(A$11:A17)+1 -> 6 | B18: 社内取引部門表示コード | E18: △ | F18: コード | G18: 15 | H18: =SUBSTITUTE(SUBSTITUTE(ADDRESS(1,A18),"$1",""),"$","") -> F | I18: 空白 | O18: 設定なし
A19: =MAX(A$11:A18)+1 -> 7 | B19: 社内取引部門名（略） | F19: 文字列 | G19: 20 | H19: =SUBSTITUTE(SUBSTITUTE(ADDRESS(1,A19),"$1",""),"$","") -> G | I19: 空白 | O19: 設定なし
A20: =MAX(A$11:A19)+1 -> 8 | B20: 適格請求書発行事業者登録番号 | F20: 文字列 | G20: 14 | H20: =SUBSTITUTE(SUBSTITUTE(ADDRESS(1,A20),"$1",""),"$","") -> H | I20: 空白 | O20: 設定なし
A21: =MAX(A$11:A20)+1 -> 9 | B21: 企業コード | E21: △ | F21: コード | G21: 15 | H21: =SUBSTITUTE(SUBSTITUTE(ADDRESS(1,A21),"$1",""),"$","") -> I | I21: 空白 | O21: 設定なし
A22: =MAX(A$11:A21)+1 -> 10 | B22: 企業名（略） | F22: 文字列 | G22: 20 | H22: =SUBSTITUTE(SUBSTITUTE(ADDRESS(1,A22),"$1",""),"$","") -> J | I22: 空白 | O22: 設定なし
A23: =MAX(A$11:A22)+1 -> 11 | B23: 得意先フラグ | F23: フラグ | G23: 1 | H23: =SUBSTITUTE(SUBSTITUTE(ADDRESS(1,A23),"$1",""),"$","") -> K | I23: 「0:得意先として使用しない」 | O23: ０（固定値）
A24: =MAX(A$11:A23)+1 -> 12 | B24: 需要家フラグ | F24: フラグ | G24: 1 | H24: =SUBSTITUTE(SUBSTITUTE(ADDRESS(1,A24),"$1",""),"$","") -> L | I24: 「0:需要家として使用しない」 | O24: ０（固定値）
A25: =MAX(A$11:A24)+1 -> 13 | B25: 出荷先フラグ | F25: フラグ | G25: 1 | H25: =SUBSTITUTE(SUBSTITUTE(ADDRESS(1,A25),"$1",""),"$","") -> M | I25: 「0:出荷先として使用しない」 | O25: ０（固定値）
A26: =MAX(A$11:A25)+1 -> 14 | B26: 仕入先フラグ | F26: フラグ | G26: 1 | H26: =SUBSTITUTE(SUBSTITUTE(ADDRESS(1,A26),"$1",""),"$","") -> N | I26: 「0:仕入先として使用しない」 | O26: ０（固定値）
A27: =MAX(A$11:A26)+1 -> 15 | B27: 入荷元フラグ | F27: フラグ | G27: 1 | H27: =SUBSTITUTE(SUBSTITUTE(ADDRESS(1,A27),"$1",""),"$","") -> O | I27: 「0:入荷元として使用しない」 | O27: ０（固定値）
A28: =MAX(A$11:A27)+1 -> 16 | B28: 請求先フラグ | F28: フラグ | G28: 1 | H28: =SUBSTITUTE(SUBSTITUTE(ADDRESS(1,A28),"$1",""),"$","") -> P | I28: 「0:請求先として使用しない」 | O28: ０（固定値）
A29: =MAX(A$11:A28)+1 -> 17 | B29: 支払先フラグ | F29: フラグ | G29: 1 | H29: =SUBSTITUTE(SUBSTITUTE(ADDRESS(1,A29),"$1",""),"$","") -> Q | I29: 「0:支払先として使用しない」 | O29: ０（固定値）
A30: =MAX(A$11:A29)+1 -> 18 | B30: 諸口取引先フラグ | F30: フラグ | G30: 1 | H30: =SUBSTITUTE(SUBSTITUTE(ADDRESS(1,A30),"$1",""),"$","") -> R | I30: 「0:取引先」 | O30: 0
A31: =MAX(A$11:A30)+1 -> 19 | B31: 取引先名１ | E31: 〇 | F31: 文字列 | G31: 50 | H31: =SUBSTITUTE(SUBSTITUTE(ADDRESS(1,A31),"$1",""),"$","") -> S | I31: 取引先の名称 | O31: 名称住所マスタ.取引先名（漢字）の先頭50桁(25文字) | T31: ※取引先名：全角50文字(法人30文字、店舗20文字) | X31: ※連動元システムでは常に全角で情報を保持
A32: =MAX(A$11:A31)+1 -> 20 | B32: 取引先名２ | F32: 文字列 | G32: 50 | H32: =SUBSTITUTE(SUBSTITUTE(ADDRESS(1,A32),"$1",""),"$","") -> T | I32: 空白 | O32: 名称住所マスタ.取引先名（漢字）の51～100桁(25文字)
A33: =MAX(A$11:A32)+1 -> 21 | B33: 取引先名（略） | E33: 〇 | F33: 文字列 | G33: 20 | H33: =SUBSTITUTE(SUBSTITUTE(ADDRESS(1,A33),"$1",""),"$","") -> U | I33: 取引先の略称 | O33: 名称住所マスタ.取引先略称名（漢字）の先頭20桁(10文字) | T33: ※取引先名（略）：全角25文字（法人13文字、店舗12文字） | X33: ※連動元システムでは常に全角で情報を保持
A34: =MAX(A$11:A33)+1 -> 22 | B34: 取引先名（カナ） | E34: 〇 | F34: 半カナ | G34: 40 | H34: =SUBSTITUTE(SUBSTITUTE(ADDRESS(1,A34),"$1",""),"$","") -> V | I34: 取引先のカナ名称 | O34: 名称住所マスタ.取引先略称名（カナ）の先頭40桁 | T34: ※カナ略称：半角50文字（法人26文字、店舗24文字）
A35: =MAX(A$11:A34)+1 -> 23 | B35: 取引先名（英字） | F35: 半英数 | G35: 40 | H35: =SUBSTITUTE(SUBSTITUTE(ADDRESS(1,A35),"$1",""),"$","") -> W | I35: 空白 | O35: 設定なし
A36: =MAX(A$11:A35)+1 -> 24 | B36: 休日パターンコード | F36: コード | G36: 5 | H36: =SUBSTITUTE(SUBSTITUTE(ADDRESS(1,A36),"$1",""),"$","") -> X | I36: 空白 | O36: 設定なし
A37: =MAX(A$11:A36)+1 -> 25 | B37: 休日パターン名 | F37: 文字列 | G37: 40 | H37: =SUBSTITUTE(SUBSTITUTE(ADDRESS(1,A37),"$1",""),"$","") -> Y | I37: 空白 | O37: 設定なし
A38: =MAX(A$11:A37)+1 -> 26 | B38: 国コード | F38: コード | G38: 3 | H38: =SUBSTITUTE(SUBSTITUTE(ADDRESS(1,A38),"$1",""),"$","") -> Z | I38: 空白 | O38: 設定なし
A39: =MAX(A$11:A38)+1 -> 27 | B39: 国名称 | F39: 文字列 | G39: 20 | H39: =SUBSTITUTE(SUBSTITUTE(ADDRESS(1,A39),"$1",""),"$","") -> AA | I39: 空白 | O39: 設定なし
A40: =MAX(A$11:A39)+1 -> 28 | B40: 取引先地域分類値コード | F40: コード | G40: 4 | H40: =SUBSTITUTE(SUBSTITUTE(ADDRESS(1,A40),"$1",""),"$","") -> AB | I40: 空白 | O40: 設定なし
A41: =MAX(A$11:A40)+1 -> 29 | B41: 取引先地域分類値 | F41: 文字列 | G41: 20 | H41: =SUBSTITUTE(SUBSTITUTE(ADDRESS(1,A41),"$1",""),"$","") -> AC | I41: 空白 | O41: 設定なし
A42: =MAX(A$11:A41)+1 -> 30 | B42: 郵便番号 | F42: 半英数 | G42: 8 | H42: =SUBSTITUTE(SUBSTITUTE(ADDRESS(1,A42),"$1",""),"$","") -> AD | I42: 空白 | O42: 設定なし
A43: =MAX(A$11:A42)+1 -> 31 | B43: 住所１ | F43: 文字列 | G43: 100 | H43: =SUBSTITUTE(SUBSTITUTE(ADDRESS(1,A43),"$1",""),"$","") -> AE | I43: 空白 | O43: 設定なし
A44: =MAX(A$11:A43)+1 -> 32 | B44: 住所２ | F44: 文字列 | G44: 100 | H44: =SUBSTITUTE(SUBSTITUTE(ADDRESS(1,A44),"$1",""),"$","") -> AF | I44: 空白 | O44: 設定なし
A45: =MAX(A$11:A44)+1 -> 33 | B45: 住所３ | F45: 文字列 | G45: 100 | H45: =SUBSTITUTE(SUBSTITUTE(ADDRESS(1,A45),"$1",""),"$","") -> AG | I45: 空白 | O45: 設定なし
A46: =MAX(A$11:A45)+1 -> 34 | B46: ＴＥＬ | F46: 半英数 | G46: 20 | H46: =SUBSTITUTE(SUBSTITUTE(ADDRESS(1,A46),"$1",""),"$","") -> AH | I46: 空白 | O46: 設定なし
... A70: =MAX(A$11:A69)+1 -> 58 | B70: 分類値１０ | F70: 文字列 | G70: 20 | H70: =SUBSTITUTE(SUBSTITUTE(ADDRESS(1,A70),"$1",""),"$","") -> BF | I70: 空白 | O70: 設定なし
A71: =MAX(A$11:A70)+1 -> 59 | B71: 使用不可フラグ | E71: 〇 | F71: フラグ | G71: 1 | H71: =SUBSTITUTE(SUBSTITUTE(ADDRESS(1,A71),"$1",""),"$","") -> BG | I71: 「0:使用可」 | O71: データ連動時は常に「０：使用可」
A72: =MAX(A$11:A71)+1 -> 60 | B72: 取引先所在地区分 | E72: 〇 | F72: 区分 | G72: 1 | H72: =SUBSTITUTE(SUBSTITUTE(ADDRESS(1,A72),"$1",""),"$","") -> BH | I72: 「0:国内」 | O72: ０（固定値）
A73: =MAX(A$11:A72)+1 -> 61 | B73: 取引先所在地区分名 | F73: 文字列 | G73: 4 | H73: =SUBSTITUTE(SUBSTITUTE(ADDRESS(1,A73),"$1",""),"$","") -> BI | I73: 空白 | O73: 設定なし
A74: =MAX(A$11:A73)+1 -> 62 | B74: 国内取引フラグ | E74: △ | F74: フラグ | G74: 1 | H74: =SUBSTITUTE(SUBSTITUTE(ADDRESS(1,A74),"$1",""),"$","") -> BJ | I74: 「1:使用する」 | O74: １（固定値）
A75: =MAX(A$11:A74)+1 -> 63 | B75: 外為取引フラグ | E75: △ | F75: フラグ | G75: 1 | H75: =SUBSTITUTE(SUBSTITUTE(ADDRESS(1,A75),"$1",""),"$","") -> BK | I75: 「0:使用しない」 | O75: ０（固定値）
A76: =MAX(A$11:A75)+1 -> 64 | B76: 通貨コード | E76: △ | F76: コード | G76: 3 | H76: =SUBSTITUTE(SUBSTITUTE(ADDRESS(1,A76),"$1",""),"$","") -> BL | I76: 空白 | O76: 設定なし
A77: =MAX(A$11:A76)+1 -> 65 | B77: 消費税端数計算区分 | F77: 区分 | G77: 1 | H77: =SUBSTITUTE(SUBSTITUTE(ADDRESS(1,A77),"$1",""),"$","") -> BM | I77: 「1:切り捨て」 | O77: 設定なし | Q77: ※ブランク時は3：四捨五入が採用される
A78: =MAX(A$11:A77)+1 -> 66 | B78: 消費税計算単位区分 | F78: 区分 | G78: 1 | H78: =SUBSTITUTE(SUBSTITUTE(ADDRESS(1,A78),"$1",""),"$","") -> BN | I78: 「2:明細単位」 | O78: ２：明細単位
A79: =MAX(A$11:A78)+1 -> 67 | B79: 取引金額端数処理区分 | F79: 区分 | G79: 1 | H79: =SUBSTITUTE(SUBSTITUTE(ADDRESS(1,A79),"$1",""),"$","") -> BO | I79: 「1:切り捨て」 | O79: 設定なし | Q79: ※ブランク時は3：四捨五入が採用される
A80: =MAX(A$11:A79)+1 -> 68 | B80: 承認申請状況区分名 | F80: 文字列 | G80: 6 | H80: =SUBSTITUTE(SUBSTITUTE(ADDRESS(1,A80),"$1",""),"$","") -> BP | I80: 空白 | O80: 設定なし
A81: =MAX(A$11:A80)+1 -> 69 | B81: 承認申請番号 | F81: コード | G81: 20 | H81: =SUBSTITUTE(SUBSTITUTE(ADDRESS(1,A81),"$1",""),"$","") -> BQ | I81: 空白 | O81: 設定なし
A82: =MAX(A$11:A81)+1 -> 70 | B82: 承認申請日付 | F82: 日付 | G82: 8 | H82: =SUBSTITUTE(SUBSTITUTE(ADDRESS(1,A82),"$1",""),"$","") -> BR | I82: 空白 | O82: 設定なし
A83: =MAX(A$11:A82)+1 -> 71 | B83: 承認申請者名 | F83: 文字列 | G83: 22 | H83: =SUBSTITUTE(SUBSTITUTE(ADDRESS(1,A83),"$1",""),"$","") -> BS | I83: 空白 | O83: 設定なし
A84: =MAX(A$11:A83)+1 -> 72 | B84: 承認申請部門名（略） | F84: 文字列 | G84: 20 | H84: =SUBSTITUTE(SUBSTITUTE(ADDRESS(1,A84),"$1",""),"$","") -> BT | I84: 空白 | O84: 設定なし
A85: =MAX(A$11:A84)+1 -> 73 | B85: 登録者名 | F85: 文字列 | G85: 22 | H85: =SUBSTITUTE(SUBSTITUTE(ADDRESS(1,A85),"$1",""),"$","") -> BU | I85: 空白 | O85: 設定なし
A86: =MAX(A$11:A85)+1 -> 74 | B86: 登録日時 | F86: 数値 | G86: 17 | H86: =SUBSTITUTE(SUBSTITUTE(ADDRESS(1,A86),"$1",""),"$","") -> BV | I86: 空白 | O86: 設定なし
A87: =MAX(A$11:A86)+1 -> 75 | B87: 更新者名 | F87: 文字列 | G87: 22 | H87: =SUBSTITUTE(SUBSTITUTE(ADDRESS(1,A87),"$1",""),"$","") -> BW | I87: 空白 | O87: 設定なし
A88: =MAX(A$11:A87)+1 -> 76 | B88: 更新日時 | F88: 数値 | G88: 17 | H88: =SUBSTITUTE(SUBSTITUTE(ADDRESS(1,A88),"$1",""),"$","") -> BX | I88: 空白 | O88: 設定なし
A89: =MAX(A$11:A88)+1 -> 77 | B89: 得意先担当者コード | F89: 半英数 | G89: 15 | H89: =SUBSTITUTE(SUBSTITUTE(ADDRESS(1,A89),"$1",""),"$","") -> BY | I89: 空白 | O89: 設定なし
A90: =MAX(A$11:A89)+1 -> 78 | B90: 得意先担当者名 | F90: 文字列 | G90: 22 | H90: =SUBSTITUTE(SUBSTITUTE(ADDRESS(1,A90),"$1",""),"$","") -> BZ | I90: 空白 | O90: 設定なし
A91: =MAX(A$11:A90)+1 -> 79 | B91: 得意先担当部門表示コード | F91: コード | G91: 10 | H91: =SUBSTITUTE(SUBSTITUTE(ADDRESS(1,A91),"$1",""),"$","") -> CA | I91: 空白 | O91: 設定なし
... A168: =MAX(A$11:A167)+1 -> 156 | B168: 下請事業者フラグ | F168: フラグ | G168: 1 | H168: =SUBSTITUTE(SUBSTITUTE(ADDRESS(1,A168),"$1",""),"$","") -> EZ | I168: 空白 | O168: 設定なし

Sheet 取込データサンプル（支払先）
A1: 編集区分 | B1: 新規変更区分名称 | C1: 取引先区分コード | D1: 取引先区分名 | E1: 取引先コード | F1: 社内取引部門表示コード | G1: 社内取引部門名（略） | H1: 適格請求書発行事業者登録番号 | I1: 企業コード | J1: 企業名（略） | K1: 得意先フラグ | L1: 需要家フラグ | M1: 出荷先フラグ | N1: 仕入先フラグ | O1: 入荷元フラグ | P1: 請求先フラグ | Q1: 支払先フラグ | R1: 諸口取引先フラグ | S1: 取引先名１ | T1: 取引先名２ | U1: 取引先名（略） | V1: 取引先名（カナ） | W1: 取引先名（英字） | X1: 休日パターンコード | Y1: 休日パターン名 | Z1: 国コード | AA1: 国名称 | AB1: 取引先地域分類値コード | AC1: 取引先地域分類値 | AD1: 郵便番号 | AE1: 住所１ | AF1: 住所２ | AG1: 住所３ | AH1: ＴＥＬ | AI1: ＦＡＸ | AJ1: 取引開始日付 | AK1: 取引終了日付 | AL1: 備考 | AM1: 分類値コード１ | AN1: 分類値１ | AO1: 分類値コード２ | AP1: 分類値２ | AQ1: 分類値コード３ | AR1: 分類値３ | AS1: 分類値コード４ | AT1: 分類値４ | AU1: 分類値コード５ | AV1: 分類値５ | AW1: 分類値コード６ | AX1: 分類値６ | AY1: 分類値コード７ | AZ1: 分類値７ | BA1: 分類値コード８ | BB1: 分類値８ | BC1: 分類値コード９ | BD1: 分類値９ | BE1: 分類値コード１０ | BF1: 分類値１０ | BG1: 使用不可フラグ | BH1: 取引先所在地区分 | BI1: 取引先所在地区分名 | BJ1: 国内取引フラグ | BK1: 外為取引フラグ | BL1: 通貨コード | BM1: 消費税端数計算区分 | BN1: 消費税計算単位区分 | BO1: 取引金額端数処理区分 | BP1: 承認申請状況区分名 | BQ1: 承認申請番号 | BR1: 承認申請日付 | BS1: 承認申請者名 | BT1: 承認申請部門名（略） | BU1: 登録者名 | BV1: 登録日時 | BW1: 更新者名 | BX1: 更新日時 | BY1: 得意先担当者コード | BZ1: 得意先担当者名 | CA1: 得意先担当部門表示コード | CB1: 得意先担当部門名（略） | CC1: 得意先先方担当者名 | CD1: 得意先先方担当者ＭＡＩＬ | CE1: 得意先先方担当者ＴＥＬ | CF1: 得意先分類値コード１ | CG1: 得意先分類値１ | CH1: 得意先分類値コード２ | CI1: 得意先分類値２ | CJ1: 得意先分類値コード３ | CK1: 得意先分類値３ | CL1: 得意先分類値コード４ | CM1: 得意先分類値４ | CN1: 得意先分類値コード５ | CO1: 得意先分類値５ | CP1: 得意先備考 | CQ1: 得意先ランク分類値コード | CR1: 得意先ランク分類値 | CS1: 得意先インコタームズ１ | CT1: 得意先インコタームズ２ | CU1: 売上消費税区分 | CV1: 売上消費税計算区分 | CW1: 得意先貿易輸送手段区分 | CX1: 得意先貿易輸送手段区分名 | CY1: 検収リードタイム | CZ1: 請求案内伝票値引表示フラグ | DA1: 納品書金額表示フラグ | DB1: 輸送手段コード１ | DC1: 輸送手段名１ | DD1: 輸送手段コード２ | DE1: 輸送手段名２ | DF1: 倉庫コード１ | DG1: 倉庫名（略）１ | DH1: 倉庫１配送リードタイム（輸送１） | DI1: 倉庫１配送リードタイム（輸送２） | DJ1: 倉庫コード２ | DK1: 倉庫名（略）２ | DL1: 倉庫２配送リードタイム（輸送１） | DM1: 倉庫２配送リードタイム（輸送２） | DN1: 倉庫コード３ | DO1: 倉庫名（略）３ | DP1: 倉庫３配送リードタイム（輸送１） | DQ1: 倉庫３配送リードタイム（輸送２） | DR1: 倉庫コード４ | DS1: 倉庫名（略）４ | DT1: 倉庫４配送リードタイム（輸送１） | DU1: 倉庫４配送リードタイム（輸送２） | DV1: 倉庫コード５ | DW1: 倉庫名（略）５ | DX1: 倉庫５配送リードタイム（輸送１） | DY1: 倉庫５配送リードタイム（輸送２） | DZ1: 仕入先担当者コード | EA1: 仕入先担当者名 | EB1: 仕入先担当部門表示コード | EC1: 仕入先担当部門名（略） | ED1: 仕入先先方担当者名 | EE1: 仕入先先方担当者ＭＡＩＬ | EF1: 仕入先先方担当者ＴＥＬ | EG1: 仕入先分類値コード１ | EH1: 仕入先分類値１ | EI1: 仕入先分類値コード２ | EJ1: 仕入先分類値２ | EK1: 仕入先分類値コード３ | EL1: 仕入先分類値３ | EM1: 仕入先分類値コード４ | EN1: 仕入先分類値４ | EO1: 仕入先分類値コード５ | EP1: 仕入先分類値５ | EQ1: 仕入先備考 | ER1: 仕入先ランク分類値コード | ES1: 仕入先ランク分類値 | ET1: 仕入先インコタームズ１ | EU1: 仕入先インコタームズ２ | EV1: 仕入消費税区分 | EW1: 仕入消費税計算区分 | EX1: 仕入先貿易輸送手段区分 | EY1: 仕入先貿易輸送手段区分名 | EZ1: 下請事業者フラグ | FA1: 支払通知書出力内容 | FB1: 預り源泉対象初期値フラグ | FC1: 預り源泉税端数計算区分 | FD1: 支払消費税差額計算フラグ | FE1: 取込支払消費税差額計算フラグ | FF1: 共通支払先フラグ | FG1: 支払書内容確認コメント | FH1: 支払決済条件行番号 | FI1: 支払決済条件コード | FJ1: 支払決済条件名 | FK1: 支払決済条件名（略） | FL1: 取引形態区分 | FM1: 支払締区分 | FN1: 支払締名寄フラグ | FO1: 名寄部門表示コード | FP1: 名寄部門名（略） | FQ1: 名寄部門基準日付 | FR1: 支払通知書書式区分 | FS1: 支払通知書品目内訳表示フラグ | FT1: 支払基準金額 | FU1: 支払決済条件使用不可フラグ | FV1: 分割条件（未満） | FW1: 分割率（未満） | FX1: 端数桁数（未満） | FY1: 端数区分（未満） | FZ1: 分割基準金額（未満） | GA1: 支払方法コード（未満１） | GB1: 支払方法名（未満１） | GC1: 休日考慮区分（未満１） | GD1: 出金口座コード（未満１） | GE1: 出金口座名（未満１） | GF1: 支払方法コード（未満２） | GG1: 支払方法名（未満２） | GH1: 休日考慮区分（未満２） | GI1: 出金口座コード（未満２） | GJ1: 出金口座名（未満２） | GK1: 分割条件（以上） | GL1: 分割率（以上） | GM1: 端数桁数（以上） | GN1: 端数区分（以上） | GO1: 分割基準金額（以上） | GP1: 支払方法コード（以上１） | GQ1: 支払方法名（以上１） | GR1: 休日考慮区分（以上１） | GS1: 出金口座コード（以上１） | GT1: 出金口座名（以上１） | GU1: 支払方法コード（以上２） | GV1: 支払方法名（以上２） | GW1: 休日考慮区分（以上２） | GX1: 出金口座コード（以上２） | GY1: 出金口座名（以上２） | GZ1: 振込先金融機関コード | HA1: 振込先金融機関名 | HB1: 振込先金融機関店舗コード | HC1: 振込先金融機関店舗名 | HD1: 振込先銀行口座種別区分 | HE1: 振込先銀行口座番号 | HF1: 振込先銀行口座名義人名 | HG1: 振込先銀行口座名義人名（カナ） | HH1: 先方負担振込手数料フラグ | HI1: 振込先郵便口座番号 | HJ1: 振込先郵便口座名義人名 | HK1: 振込先郵便口座名義人名（カナ） | HL1: 手形支払サイト | HM1: 支払手形期日指定月数 | HN1: 支払手形期日指定日 | HO1: 支払手形休日区分 | HP1: 手形種類コード | HQ1: 手形種類名 | HR1: 期日振込サイト | HS1: 期日指定月数 | HT1: 期日指定日 | HU1: 休日区分 | HV1: 外国送金種類区分 | HW1: 外国送金受取方法区分 | HX1: 外国送金先方負担手数料フラグ | HY1: 外国送金目的（英字） | HZ1: 外国送金メッセージ（英字） | IA1: 外国送金受取人名（英字） | IB1: 外国送金受取人住所（英字） | IC1: 外国送金受取人口座番号 | ID1: 外国送金支払先銀行名（英字） | IE1: 外国送金支払先銀行支店名（英字） | IF1: 外国送金支払先銀行住所（英字） | IG1: コルレス先経由銀行名（英字） | IH1: コルレス先経由銀行支店名（英字） | II1: コルレス先経由銀行住所（英字） | IJ1: 非コルレス先経由銀行名（英字） | IK1: 非コルレス先経由銀行支店名（英字） | IL1: 非コルレス先経由銀行住所（英字） | IM1: 支払締日 | IN1: 期日サイクル区分（未満１） | IO1: 期日指定月数（未満１） | IP1: 期日指定支払日（未満１） | IQ1: 期日指定日数（未満１） | IR1: 期日サイクル区分（未満２） | IS1: 期日指定月数（未満２） | IT1: 期日指定支払日（未満２） | IU1: 期日指定日数（未満２） | IV1: 期日サイクル区分（以上１） | IW1: 期日指定月数（以上１） | IX1: 期日指定支払日（以上１） | IY1: 期日指定日数（以上１） | IZ1: 期日サイクル区分（以上２） | JA1: 期日指定月数（以上２） | JB1: 期日指定支払日（以上２） | JC1: 期日指定日数（以上２）
A2: 1 | C2: 0 | D2: 初期導入 | E2: 100120001 | H2: 10000000000001 | K2: 0 | L2: 0 | M2: 0 | N2: 0 | O2: 0 | P2: 0 | Q2: 0 | R2: 0 | S2: 新函館農協 本店 | U2: 新函館農協 本店 | V2: ｼﾝﾊｺﾀﾞﾃﾉｳｷｮｳ | BG2: 0 | BH2: 0 | BI2: 国内 | BJ2: 1 | BK2: 0 | BM2: 3 | BN2: 1 | BO2: 3 | BP2: － | BU2: 住商 二郎 | BV2: 2.0230712e+16 | BW2: 住商 一郎 | BX2: 2.0240415e+16 | CZ2: 0 | DA2: 0 | EZ2: 0 | FB2: 0 | FC2: 1 | FD2: 1 | FE2: 0 | FF2: 0
A3: 1 | C3: 0 | D3: 初期導入 | E3: 100120002 | H3: 10000000000002 | K3: 0 | L3: 0 | M3: 0 | N3: 0 | O3: 0 | P3: 1 | Q3: 1 | R3: 0 | S3: 新函館農協 米穀畑作課 | U3: 新函館農協 米穀畑 | V3: ｼﾝﾊｺﾀﾞﾃﾉｳｷｮｳ | AM3: 2 | AN3: グループ間取引 | BG3: 0 | BH3: 0 | BI3: 国内 | BJ3: 1 | BK3: 0 | BM3: 3 | BN3: 1 | BO3: 3 | BP3: － | BU3: 住商 二郎 | BV3: 2.0230712e+16 | BW3: 住商 一郎 | BX3: 2.0240802e+16 | CZ3: 0 | DA3: 0 | EZ3: 0 | FB3: 0 | FC3: 1 | FD3: 1 | FE3: 1 | FF3: 0 | FG3: 送付後、1カ月以内にご連絡がない場合は、内容を確認済みとさせていただきます。 | FH3: 1 | FI3: 1 | FJ3: 翌月末支払 | FK3: 翌月末支払 | FL3: 1 | FM3: 2 | FN3: 0 | FR3: 2 | FS3: 0 | FT3: 0 | FU3: 0 | FV3: 1 | GA3: S02 | GB3: 振込-ＦＢ | GC3: 1 | GZ3: 19 | HA3: 北海道銀行 | HB3: 101 | HC3: 本店 | HD3: 1 | HE3: 3334444 | HF3: 新函館農協 米穀畑 | HG3: ｼﾝﾊｺﾀﾞﾃﾉｳｷﾖｳ | HH3: 0 | IM3: 0 | IN3: 1 | IO3: 1 | IP3: 99
A4: 1 | C4: 0 | D4: 初期導入 | E4: 100120002 | H4: 10000000000002 | K4: 0 | L4: 0 | M4: 0 | N4: 0 | O4: 0 | P4: 1 | Q4: 1 | R4: 0 | S4: 新函館農協 米穀畑作課 | U4: 新函館農協 米穀畑 | V4: ｼﾝﾊｺﾀﾞﾃﾉｳｷｮｳ | AM4: 2 | AN4: グループ間取引 | BG4: 0 | BH4: 0 | BI4: 国内 | BJ4: 1 | BK4: 0 | BM4: 3 | BN4: 1 | BO4: 3 | BP4: － | BU4: 住商 二郎 | BV4: 2.0230712e+16 | BW4: 住商 一郎 | BX4: 2.0240802e+16 | CZ4: 0 | DA4: 0 | EZ4: 0 | FB4: 0 | FC4: 1 | FD4: 1 | FE4: 1 | FF4: 0 | FG4: 送付後、1カ月以内にご連絡がない場合は、内容を確認済みとさせていただきます。 | FH4: 2 | FI4: 2 | FJ4: 翌月末-引落 | FK4: 翌月末-引落 | FL4: 1 | FM4: 2 | FN4: 0 | FR4: 2 | FS4: 0 | FT4: 0 | FU4: 0 | FV4: 1 | GA4: S06 | GB4: 引落 | GC4: 1 | GD4: 00190001 | GE4: 北海道銀行 本店 | IM4: 0 | IN4: 1 | IO4: 1 | IP4: 99
A5: 1 | C5: 0 | D5: 初期導入 | E5: 100120002 | H5: 10000000000002 | K5: 0 | L5: 0 | M5: 0 | N5: 0 | O5: 0 | P5: 1 | Q5: 1 | R5: 0 | S5: 新函館農協 米穀畑作課 | U5: 新函館農協 米穀畑 | V5: ｼﾝﾊｺﾀﾞﾃﾉｳｷｮｳ | AM5: 2 | AN5: グループ間取引 | BG5: 0 | BH5: 0 | BI5: 国内 | BJ5: 1 | BK5: 0 | BM5: 3 | BN5: 1 | BO5: 3 | BP5: － | BU5: 住商 二郎 | BV5: 2.0230712e+16 | BW5: 住商 一郎 | BX5: 2.0240802e+16 | CZ5: 0 | DA5: 0 | EZ5: 0 | FB5: 0 | FC5: 1 | FD5: 1 | FE5: 1 | FF5: 0 | FG5: 送付後、1カ月以内にご連絡がない場合は、内容を確認済みとさせていただきます。 | FH5: 3 | FI5: 3 | FJ5: 一括決済用 | FK5: 一括決済用_手形 | FL5: 1 | FM5: 2 | FN5: 0 | FR5: 2 | FS5: 0 | FT5: 0 | FU5: 0 | FV5: 1 | GA5: S07 | GB5: 支払手形 | GC5: 1 | HL5: 20 | HM5: 1 | HN5: 20 | HO5: 1 | HP5: ST005 | HQ5: 支払手形_一括決済 | IM5: 0 | IN5: 1 | IO5: 1 | IP5: 99
A6: 1 | C6: 0 | D6: 初期導入 | E6: 100120002 | H6: 10000000000002 | K6: 0 | L6: 0 | M6: 0 | N6: 0 | O6: 0 | P6: 1 | Q6: 1 | R6: 0 | S6: 新函館農協 米穀畑作課 | U6: 新函館農協 米穀畑 | V6: ｼﾝﾊｺﾀﾞﾃﾉｳｷｮｳ | AM6: 2 | AN6: グループ間取引 | BG6: 0 | BH6: 0 | BI6: 国内 | BJ6: 1 | BK6: 0 | BM6: 3 | BN6: 1 | BO6: 3 | BP6: － | BU6: 住商 二郎 | BV6: 2.0230712e+16 | BW6: 住商 一郎 | BX6: 2.0240802e+16 | CZ6: 0 | DA6: 0 | EZ6: 0 | FB6: 0 | FC6: 1 | FD6: 1 | FE6: 1 | FF6: 0 | FG6: 送付後、1カ月以内にご連絡がない場合は、内容を確認済みとさせていただきます。 | FH6: 4 | FI6: 4 | FJ6: 翌月末支払い定時 | FK6: 翌月末定時 | FL6: 1 | FM6: 1 | FN6: 1 | FR6: 2 | FS6: 0 | FT6: 0 | FU6: 0 | FV6: 1 | GA6: S02 | GB6: 振込-ＦＢ | GC6: 1 | GZ6: 18 | HA6: 北洋銀行 | HB6: 28 | HC6: 本店 | HD6: 1 | HE6: 2222555 | HF6: 新函館農協定時 | HG6: ｼﾝﾊｺﾀﾞﾃﾉｳｷﾖｳﾃｲｼﾞ | HH6: 0 | IM6: 99 | IN6: 1 | IO6: 1 | IP6: 99
A7: 1 | C7: 0 | D7: 初期導入 | E7: 100120002 | H7: 10000000000002 | K7: 0 | L7: 0 | M7: 0 | N7: 0 | O7: 0 | P7: 1 | Q7: 1 | R7: 0 | S7: 新函館農協 米穀畑作課 | U7: 新函館農協 米穀畑 | V7: ｼﾝﾊｺﾀﾞﾃﾉｳｷｮｳ | AM7: 2 | AN7: グループ間取引 | BG7: 0 | BH7: 0 | BI7: 国内 | BJ7: 1 | BK7: 0 | BM7: 3 | BN7: 1 | BO7: 3 | BP7: － | BU7: 住商 二郎 | BV7: 2.0230712e+16 | BW7: 住商 一郎 | BX7: 2.0240802e+16 | CZ7: 0 | DA7: 0 | EZ7: 0 | FB7: 0 | FC7: 1 | FD7: 1 | FE7: 1 | FF7: 0 | FG7: 送付後、1カ月以内にご連絡がない場合は、内容を確認済みとさせていただきます。 | FH7: 5 | FI7: 5 | FJ7: 一括決済_振込 | FK7: 一括決済_振込 | FL7: 1 | FM7: 2 | FN7: 0 | FR7: 2 | FS7: 0 | FT7: 0 | FU7: 0 | FV7: 1 | GA7: S02 | GB7: 振込-ＦＢ | GC7: 1 | GD7: 00190004 | GE7: 北海道銀行ｲｯｶﾂｹｯｻｲ | GZ7: 19 | HA7: 北海道銀行 | HB7: 101 | HC7: 本店 | HD7: 1 | HE7: 7777777 | HF7: 口座名義人新函館 | HG7: ｼﾝﾊｺﾀﾞﾃﾞ | HH7: 0 | IM7: 0 | IN7: 1 | IO7: 1 | IP7: 20
A8: 1 | C8: 0 | D8: 初期導入 | E8: 100120002 | H8: 10000000000002 | K8: 0 | L8: 0 | M8: 0 | N8: 0 | O8: 0 | P8: 1 | Q8: 1 | R8: 0 | S8: 新函館農協 米穀畑作課 | U8: 新函館農協 米穀畑 | V8: ｼﾝﾊｺﾀﾞﾃﾉｳｷｮｳ | AM8: 2 | AN8: グループ間取引 | BG8: 0 | BH8: 0 | BI8: 国内 | BJ8: 1 | BK8: 0 | BM8: 3 | BN8: 1 | BO8: 3 | BP8: － | BU8: 住商 二郎 | BV8: 2.0230712e+16 | BW8: 住商 一郎 | BX8: 2.0240802e+16 | CZ8: 0 | DA8: 0 | EZ8: 0 | FB8: 0 | FC8: 1 | FD8: 1 | FE8: 1 | FF8: 0 | FG8: 送付後、1カ月以内にご連絡がない場合は、内容を確認済みとさせていただきます。 | FH8: 6 | FI8: 6 | FJ8: 納付書支払 | FK8: 納付書支払 | FL8: 1 | FM8: 2 | FN8: 0 | FR8: 3 | FS8: 0 | FT8: 0 | FU8: 0 | FV8: 1 | GA8: S04 | GB8: 振込-総合 | GC8: 1 | GZ8: 19 | HA8: 北海道銀行 | HB8: 104 | HC8: 南一条支店 | HD8: 1 | HE8: 6667777 | HF8: ホクレン | HG8: ﾎｸﾚﾝ | HH8: 0 | IM8: 0 | IN8: 1 | IO8: 1 | IP8: 99
A9: 1 | C9: 0 | D9: 初期導入 | E9: 108000000 | H9: 10000000000003 | K9: 0 | L9: 0 | M9: 0 | N9: 0 | O9: 0 | P9: 0 | Q9: 1 | R9: 0 | S9: 北海道銀行 | U9: 北海道銀行 | V9: ﾎｯｶｲﾄﾞｳｷﾞﾝｺｳ | BG9: 0 | BH9: 0 | BI9: 国内 | BJ9: 1 | BK9: 0 | BM9: 3 | BN9: 1 | BO9: 3 | BP9: － | BU9: 住商 一郎 | BV9: 2.0230906e+16 | BW9: 住商 一郎 | BX9: 2.0240415e+16 | CZ9: 0 | DA9: 0 | EZ9: 0 | FB9: 0 | FC9: 1 | FD9: 1 | FE9: 0 | FF9: 0 | FG9: 送付後、1カ月以内にご連絡がない場合は内容を確認済みとさせていただきます。 | FH9: 1 | FI9: 1 | FJ9: 末締め翌月末支払 | FK9: 末締め翌月末支払 | FL9: 1 | FM9: 2 | FN9: 0 | FR9: 3 | FS9: 0 | FT9: 0 | FU9: 0 | FV9: 1 | GA9: S04 | GB9: 振込-総合 | GC9: 1 | GZ9: 1 | HA9: みずほ | HB9: 1 | HC9: 丸の内 | HD9: 2 | HE9: 7654321 | HF9: ホッカイドウギンコウ | HG9: ﾎﾂｶｲﾄﾞｳｷﾞﾝｺｳ | HH9: 0 | IM9: 0 | IN9: 1 | IO9: 1 | IP9: 99
A10: 1 | C10: 0 | D10: 初期導入 | E10: 1082521003 | H10: 10000000000004 | K10: 0 | L10: 0 | M10: 0 | N10: 0 | O10: 0 | P10: 1 | Q10: 1 | R10: 0 | S10: ㈱ホクレン商事 営業部 | U10: ホクレン商事 営業部 | V10: ﾎｸﾚﾝ | AM10: 2 | AN10: グループ間取引 | BG10: 0 | BH10: 0 | BI10: 国内 | BJ10: 1 | BK10: 0 | BM10: 3 | BN10: 1 | BO10: 3 | BP10: － | BU10: 住商 二郎 | BV10: 2.0230712e+16 | BW10: 住商 一郎 | BX10: 2.0240807e+16 | CZ10: 0 | DA10: 0 | EZ10: 0 | FB10: 0 | FC10: 1 | FD10: 1 | FE10: 1 | FF10: 0 | FG10: 送付後、1カ月以内にご連絡がない場合は内容を確認済みとさせていただきます。 | FH10: 1 | FI10: 1 | FJ10: 随時支払 FB振込 | FK10: 随時支払 FB振込 | FL10: 1 | FM10: 2 | FN10: 0 | FR10: 3 | FS10: 0 | FT10: 0 | FU10: 0 | FV10: 1 | GA10: S02 | GB10: 振込-ＦＢ | GC10: 1 | GZ10: 1 | HA10: みずほ | HB10: 2 | HC10: 築地 | HD10: 2 | HE10: 1234567 | HF10: ホクレン商事 | HG10: ﾎｸﾚﾝｼﾖｳｼﾞ | HH10: 0 | IM10: 0 | IN10: 2 | IQ10: 10
A11: 1 | C11: 0 | D11: 初期導入 | E11: 1082521003 | H11: 10000000000004 | K11: 0 | L11: 0 | M11: 0 | N11: 0 | O11: 0 | P11: 1 | Q11: 1 | R11: 0 | S11: ㈱ホクレン商事 営業部 | U11: ホクレン商事 営業部 | V11: ﾎｸﾚﾝ | AM11: 2 | AN11: グループ間取引 | BG11: 0 | BH11: 0 | BI11: 国内 | BJ11: 1 | BK11: 0 | BM11: 3 | BN11: 1 | BO11: 3 | BP11: － | BU11: 住商 二郎 | BV11: 2.0230712e+16 | BW11: 住商 一郎 | BX11: 2.0240807e+16 | CZ11: 0 | DA11: 0 | EZ11: 0 | FB11: 0 | FC11: 1 | FD11: 1 | FE11: 1 | FF11: 0 | FG11: 送付後、1カ月以内にご連絡がない場合は内容を確認済みとさせていただきます。 | FH11: 2 | FI11: 2 | FJ11: 随時支払 引落 | FK11: 随時支払 引落 | FL11: 1 | FM11: 2 | FN11: 0 | FR11: 3 | FS11: 0 | FT11: 0 | FU11: 0 | FV11: 1 | GA11: S06 | GB11: 引落 | GC11: 1 | IM11: 0 | IN11: 2 | IQ11: 10
A12: 1 | C12: 0 | D12: 初期導入 | E12: 1082521003 | H12: 10000000000004 | K12: 0 | L12: 0 | M12: 0 | N12: 0 | O12: 0 | P12: 1 | Q12: 1 | R12: 0 | S12: ㈱ホクレン商事 営業部 | U12: ホクレン商事 営業部 | V12: ﾎｸﾚﾝ | AM12: 2 | AN12: グループ間取引 | BG12: 0 | BH12: 0 | BI12: 国内 | BJ12: 1 | BK12: 0 | BM12: 3 | BN12: 1 | BO12: 3 | BP12: － | BU12: 住商 二郎 | BV12: 2.0230712e+16 | BW12: 住商 一郎 | BX12: 2.0240807e+16 | CZ12: 0 | DA12: 0 | EZ12: 0 | FB12: 0 | FC12: 1 | FD12: 1 | FE12: 1 | FF12: 0 | FG12: 送付後、1カ月以内にご連絡がない場合は内容を確認済みとさせていただきます。 | FH12: 3 | FI12: 3 | FJ12: 随時支払 納付書 | FK12: 随時支払 納付書 | FL12: 1 | FM12: 2 | FN12: 0 | FR12: 3 | FS12: 0 | FT12: 0 | FU12: 0 | FV12: 1 | GA12: S04 | GB12: 振込-総合 | GC12: 1 | GZ12: 1 | HA12: みずほ | HB12: 1 | HC12: 丸の内 | HD12: 2 | HE12: 2345678 | HF12: ホクレンショウジ | HG12: ﾎｸﾚﾝｼﾖｳｼﾞ | HH12: 0 | IM12: 0 | IN12: 2 | IQ12: 10
A13: 1 | C13: 0 | D13: 初期導入 | E13: 1082521003 | H13: 10000000000004 | K13: 0 | L13: 0 | M13: 0 | N13: 0 | O13: 0 | P13: 1 | Q13: 1 | R13: 0 | S13: ㈱ホクレン商事 営業部 | U13: ホクレン商事 営業部 | V13: ﾎｸﾚﾝ | AM13: 2 | AN13: グループ間取引 | BG13: 0 | BH13: 0 | BI13: 国内 | BJ13: 1 | BK13: 0 | BM13: 3 | BN13: 1 | BO13: 3 | BP13: － | BU13: 住商 二郎 | BV13: 2.0230712e+16 | BW13: 住商 一郎 | BX13: 2.0240807e+16 | CZ13: 0 | DA13: 0 | EZ13: 0 | FB13: 0 | FC13: 1 | FD13: 1 | FE13: 1 | FF13: 0 | FG13: 送付後、1カ月以内にご連絡がない場合は内容を確認済みとさせていただきます。 | FH13: 4 | FI13: 4 | FJ13: 一括決済_手形 | FK13: 一括決済_手形 | FL13: 1 | FM13: 2 | FN13: 0 | FR13: 1 | FS13: 0 | FT13: 0 | FU13: 0 | FV13: 1 | GA13: S07 | GB13: 支払手形 | GC13: 1 | HL13: 60 | HM13: 2 | HN13: 30 | HO13: 1 | HP13: ST005 | HQ13: 支払手形_一括決済 | IM13: 0 | IN13: 1 | IO13: 2 | IP13: 99
A14: 1 | C14: 0 | D14: 初期導入 | E14: 108400001 | H14: 10000000000005 | K14: 0 | L14: 0 | M14: 0 | N14: 0 | O14: 0 | P14: 1 | Q14: 1 | R14: 0 | S14: 全国農業協同組合連合会 本所 | U14: 全農連 本所 | V14: ｾﾞﾝﾉｳﾘﾝ | BG14: 0 | BH14: 0 | BI14: 国内 | BJ14: 1 | BK14: 0 | BM14: 3 | BN14: 1 | BO14: 3 | BP14: － | BU14: 住商 二郎 | BV14: 2.0230712e+16 | BW14: 住商 一郎 | BX14: 2.0240628e+16 | CZ14: 0 | DA14: 0 | EZ14: 0 | FB14: 0 | FC14: 1 | FD14: 1 | FE14: 1 | FF14: 0 | FG14: 送付後、1カ月以内にご連絡がない場合は内容を確認済みとさせていただきます。 | FH14: 1 | FI14: 1 | FJ14: 翌月末支払-北洋銀行 | FK14: 翌月末支払-北洋銀行 | FL14: 1 | FM14: 2 | FN14: 0 | FR14: 2 | FS14: 0 | FT14: 0 | FU14: 0 | FV14: 1 | GA14: S02 | GB14: 振込-ＦＢ | GC14: 1 | GZ14: 18 | HA14: 北洋銀行 | HB14: 28 | HC14: 本店 | HD14: 1 | HE14: 2229999 | HF14: 全農連 北洋銀行 | HG14: ｾﾞﾝﾉｳﾚﾝﾎｸﾖｳｷﾞﾝｺｳ | HH14: 0 | IM14: 0 | IN14: 1 | IO14: 1 | IP14: 99
A15: 1 | C15: 0 | D15: 初期導入 | E15: 108400001 | H15: 10000000000005 | K15: 0 | L15: 0 | M15: 0 | N15: 0 | O15: 0 | P15: 1 | Q15: 1 | R15: 0 | S15: 全国農業協同組合連合会 本所 | U15: 全農連 本所 | V15: ｾﾞﾝﾉｳﾘﾝ | BG15: 0 | BH15: 0 | BI15: 国内 | BJ15: 1 | BK15: 0 | BM15: 3 | BN15: 1 | BO15: 3 | BP15: － | BU15: 住商 二郎 | BV15: 2.0230712e+16 | BW15: 住商 一郎 | BX15: 2.0240628e+16 | CZ15: 0 | DA15: 0 | EZ15: 0 | FB15: 0 | FC15: 1 | FD15: 1 | FE15: 1 | FF15: 0 | FG15: 送付後、1カ月以内にご連絡がない場合は内容を確認済みとさせていただきます。 | FH15: 2 | FI15: 2 | FJ15: 納付書支払 | FK15: 納付書支払 | FL15: 1 | FM15: 2 | FN15: 0 | FR15: 3 | FS15: 0 | FT15: 0 | FU15: 0 | FV15: 1 | GA15: S04 | GB15: 振込-総合 | GC15: 1 | GZ15: 20 | HA15: 北海道信金 | HB15: 113 | HC15: 大通南支店 | HD15: 1 | HE15: 9998888 | HF15: 全農連 | HG15: ｾﾞﾝﾉｳﾚﾝ | HH15: 0 | IM15: 0 | IN15: 1 | IO15: 1 | IP15: 99
A16: 1 | C16: 0 | D16: 初期導入 | E16: 108400002 | H16: 10000000000006 | K16: 0 | L16: 0 | M16: 0 | N16: 0 | O16: 0 | P16: 0 | Q16: 1 | R16: 0 | S16: JA新函館 | U16: JA新函館 | V16: JA | BG16: 0 | BH16: 0 | BI16: 国内 | BJ16: 1 | BK16: 0 | BM16: 3 | BN16: 1 | BO16: 3 | BP16: － | BU16: 住商 一郎 | BV16: 2.0230713e+16 | BW16: 住商 一郎 | BX16: 2.0240807e+16 | CZ16: 0 | DA16: 0 | EZ16: 0 | FB16: 0 | FC16: 1 | FD16: 1 | FE16: 0 | FF16: 0 | FH16: 1 | FI16: 1 | FJ16: 翌月末支払随時 | FK16: 翌月末支払随時 | FL16: 1 | FM16: 2 | FN16: 0 | FR16: 3 | FS16: 0 | FT16: 0 | FU16: 0 | FV16: 1 | GA16: S02 | GB16: 振込-ＦＢ | GC16: 1 | GZ16: 18 | HA16: 北洋銀行 | HB16: 485 | HC16: 札幌市役所支店 | HD16: 1 | HE16: 6543333 | HF16: JA新函館 | HG16: ｼﾞｴｲｴｲｼﾝﾊｺﾀﾞﾃ | HH16: 0 | IM16: 0 | IN16: 1 | IO16: 1 | IP16: 99
A17: 1 | C17: 0 | D17: 初期導入 | E17: 108400002 | H17: 10000000000006 | K17: 0 | L17: 0 | M17: 0 | N17: 0 | O17: 0 | P17: 0 | Q17: 1 | R17: 0 | S17: JA新函館 | U17: JA新函館 | V17: JA | BG17: 0 | BH17: 0 | BI17: 国内 | BJ17: 1 | BK17: 0 | BM17: 3 | BN17: 1 | BO17: 3 | BP17: － | BU17: 住商 一郎 | BV17: 2.0230713e+16 | BW17: 住商 一郎 | BX17: 2.0240807e+16 | CZ17: 0 | DA17: 0 | EZ17: 0 | FB17: 0 | FC17: 1 | FD17: 1 | FE17: 0 | FF17: 0 | FH17: 2 | FI17: 2 | FJ17: 納付書支払 | FK17: 納付書支払 | FL17: 1 | FM17: 2 | FN17: 0 | FR17: 3 | FS17: 0 | FT17: 0 | FU17: 0 | FV17: 1 | GA17: S04 | GB17: 振込-総合 | GC17: 1 | GZ17: 18 | HA17: 北洋銀行 | HB17: 28 | HC17: 本店 | HD17: 1 | HE17: 7777776 | HF17: JA新函館 | HG17: ｼﾞｴｲｴｲｼﾝﾊｺﾀﾞﾃ | HH17: 0 | IM17: 0 | IN17: 1 | IO17: 1 | IP17: 99
A18: 1 | C18: 0 | D18: 初期導入 | E18: 108400002 | H18: 10000000000006 | K18: 0 | L18: 0 | M18: 0 | N18: 0 | O18: 0 | P18: 0 | Q18: 1 | R18: 0 | S18: JA新函館 | U18: JA新函館 | V18: JA | BG18: 0 | BH18: 0 | BI18: 国内 | BJ18: 1 | BK18: 0 | BM18: 3 | BN18: 1 | BO18: 3 | BP18: － | BU18: 住商 一郎 | BV18: 2.0230713e+16 | BW18: 住商 一郎 | BX18: 2.0240807e+16 | CZ18: 0 | DA18: 0 | EZ18: 0 | FB18: 0 | FC18: 1 | FD18: 1 | FE18: 0 | FF18: 0 | FH18: 3 | FI18: 3 | FJ18: 仕入金額を前渡金で充当 | FK18: 前渡金にて充当 | FL18: 1 | FM18: 2 | FN18: 0 | FR18: 3 | FS18: 0 | FT18: 0 | FU18: 0 | FV18: 1 | GA18: ZZ | GB18: 振込-その他 | GC18: 1 | GD18: 00300001 | GE18: 前渡金充当 本所用 | GZ18: 19 | HA18: 北海道銀行 | HB18: 101 | HC18: 本店 | HD18: 1 | HE18: 2224444 | HF18: JA新函館 | HG18: ｼﾞｴｲｴｲｼﾝﾊｺﾀﾞﾃ | HH18: 0 | IM18: 0 | IN18: 1 | IO18: 1 | IP18: 99
A19: 1 | C19: 0 | D19: 初期導入 | E19: 108400002 | H19: 10000000000006 | K19: 0 | L19: 0 | M19: 0 | N19: 0 | O19: 0 | P19: 0 | Q19: 1 | R19: 0 | S19: JA新函館 | U19: JA新函館 | V19: JA | BG19: 0 | BH19: 0 | BI19: 国内 | BJ19: 1 | BK19: 0 | BM19: 3 | BN19: 1 | BO19: 3 | BP19: － | BU19: 住商 一郎 | BV19: 2.0230713e+16 | BW19: 住商 一郎 | BX19: 2.0240807e+16 | CZ19: 0 | DA19: 0 | EZ19: 0 | FB19: 0 | FC19: 1 | FD19: 1 | FE19: 0 | FF19: 0 | FH19: 4 | FI19: 4 | FJ19: 一括決済_手形 | FK19: 一括決済_手形 | FL19: 1 | FM19: 2 | FN19: 0 | FR19: 1 | FS19: 0 | FT19: 0 | FU19: 0 | FV19: 1 | GA19: S07 | GB19: 支払手形 | GC19: 1 | HL19: 90 | HM19: 1 | HN19: 99 | HO19: 1 | HP19: ST005 | HQ19: 支払手形_一括決済 | IM19: 0 | IN19: 1 | IO19: 1 | IP19: 99
A20: 1 | C20: 0 | D20: 初期導入 | E20: 108400003 | H20: 10000000000007 | K20: 0 | L20: 0 | M20: 0 | N20: 0 | O20: 0 | P20: 0 | Q20: 0 | R20: 0 | S20: 全農 | U20: 全農 | V20: ｾﾞﾝｺｳ | BG20: 0 | BH20: 0 | BI20: 国内 | BJ20: 1 | BK20: 0 | BM20: 3 | BN20: 1 | BO20: 3 | BP20: － | BU20: 住商 一郎 | BV20: 2.0230713e+16 | BW20: 住商 一郎 | BX20: 2.0240415e+16 | CZ20: 0 | DA20: 0 | EZ20: 0 | FB20: 0 | FC20: 1 | FD20: 1 | FE20: 0 | FF20: 0
A21: 1 | C21: 0 | D21: 初期導入 | E21: 108400004 | H21: 10000000000008 | K21: 0 | L21: 0 | M21: 0 | N21: 0 | O21: 0 | P21: 0 | Q21: 0 | R21: 0 | S21: 青果市場 | U21: 青果市場 | V21: ｾｲｶ | BG21: 0 | BH21: 0 | BI21: 国内 | BJ21: 1 | BK21: 0 | BM21: 3 | BN21: 1 | BO21: 3 | BP21: － | BU21: 住商 一郎 | BV21: 2.0230713e+16 | BW21: 住商 一郎 | BX21: 2.0240415e+16 | CZ21: 0 | DA21: 0 | EZ21: 0 | FB21: 0 | FC21: 1 | FD21: 1 | FE21: 0 | FF21: 0
A22: 1 | C22: 0 | D22: 初期導入 | E22: 108400005 | H22: 10000000000009 | K22: 0 | L22: 0 | M22: 0 | N22: 0 | O22: 0 | P22: 0 | Q22: 0 | R22: 0 | S22: JAきたみらい | U22: JAきたみらい | V22: ja | BG22: 0 | BH22: 0 | BI22: 国内 | BJ22: 1 | BK22: 0 | BM22: 3 | BN22: 1 | BO22: 3 | BP22: － | BU22: 住商 一郎 | BV22: 2.0230713e+16 | BW22: 住商 一郎 | BX22: 2.0240415e+16 | CZ22: 0 | DA22: 0 | EZ22: 0 | FB22: 0 | FC22: 1 | FD22: 1 | FE22: 0 | FF22: 0
A23: 1 | C23: 0 | D23: 初期導入 | E23: 108400006 | K23: 0 | L23: 0 | M23: 0 | N23: 0 | O23: 0 | P23: 0 | Q23: 0 | R23: 0 | S23: 新函館農協 | U23: 新函館農協 | V23: ﾊｺﾀﾞﾃ | BG23: 0 | BH23: 0 | BI23: 国内 | BJ23: 1 | BK23: 0 | BM23: 3 | BN23: 1 | BO23: 3 | BP23: － | BU23: 住商 一郎 | BV23: 2.0230713e+16 | BW23: 住商 一郎 | BX23: 2.0230713e+16 | CZ23: 0 | DA23: 0 | EZ23: 0 | FB23: 0 | FC23: 1 | FD23: 1 | FE23: 0 | FF23: 0
A24: 1 | C24: 0 | D24: 初期導入 | E24: 108521001 | H24: TOU00000001 | K24: 0 | L24: 0 | M24: 0 | N24: 0 | O24: 0 | P24: 1 | Q24: 1 | R24: 0 | S24: ㈱ホクレン商事 | U24: ホクレン商事 | V24: ﾎｸﾚﾝ | AM24: 2 | AN24: グループ間取引 | BG24: 0 | BH24: 0 | BI24: 国内 | BJ24: 1 | BK24: 0 | BM24: 3 | BN24: 1 | BO24: 3 | BP24: － | BU24: 住商 二郎 | BV24: 2.023071e+16 | BW24: 住商 一郎 | BX24: 2.0240807e+16 | CZ24: 0 | DA24: 0 | EZ24: 0 | FB24: 0 | FC24: 1 | FD24: 0 | FE24: 0 | FF24: 0 | FG24: 送付後、1カ月以内にご連絡がない場合は内容を確認済みとさせていただきます。 | FH24: 1 | FI24: 1 | FJ24: 翌月末振込（経理課） | FK24: 翌月末振込（経理課） | FL24: 1 | FM24: 2 | FN24: 0 | FR24: 2 | FS24: 0 | FT24: 0 | FU24: 0 | FV24: 1 | GA24: S02 | GB24: 振込-ＦＢ | GC24: 1 | GZ24: 18 | HA24: 北洋銀行 | HB24: 28 | HC24: 本店 | HD24: 2 | HE24: 7 | HF24: ほくれん | HG24: ﾎｸﾚﾝ | HH24: 0 | IM24: 0 | IN24: 1 | IO24: 1 | IP24: 99
A25: 1 | C25: 0 | D25: 初期導入 | E25: 108521001 | H25: TOU00000001 | K25: 0 | L25: 0 | M25: 0 | N25: 0 | O25: 0 | P25: 1 | Q25: 1 | R25: 0 | S25: ㈱ホクレン商事 | U25: ホクレン商事 | V25: ﾎｸﾚﾝ | AM25: 2 | AN25: グループ間取引 | BG25: 0 | BH25: 0 | BI25: 国内 | BJ25: 1 | BK25: 0 | BM25: 3 | BN25: 1 | BO25: 3 | BP25: － | BU25: 住商 二郎 | BV25: 2.023071e+16 | BW25: 住商 一郎 | BX25: 2.0240807e+16 | CZ25: 0 | DA25: 0 | EZ25: 0 | FB25: 0 | FC25: 1 | FD25: 0 | FE25: 0 | FF25: 0 | FG25: 送付後、1カ月以内にご連絡がない場合は内容を確認済みとさせていただきます。 | FH25: 2 | FI25: 2 | FJ25: 翌月末振込（畜産生産部（飼料）） | FK25: 翌月末振込（飼料） | FL25: 1 | FM25: 2 | FN25: 0 | FR25: 2 | FS25: 0 | FT25: 0 | FU25: 0 | FV25: 1 | GA25: S02 | GB25: 振込-ＦＢ | GC25: 1 | GZ25: 18 | HA25: 北洋銀行 | HB25: 303 | HC25: 札幌南支店 | HD25: 1 | HE25: 9876543 | HF25: ホクレン商事 | HG25: ﾎｸﾚﾝｼﾖｳｼﾞ | HH25: 0 | IM25: 0 | IN25: 1 | IO25: 1 | IP25: 99
A26: 1 | C26: 0 | D26: 初期導入 | E26: 108521001 | H26: TOU00000001 | K26: 0 | L26: 0 | M26: 0 | N26: 0 | O26: 0 | P26: 1 | Q26: 1 | R26: 0 | S26: ㈱ホクレン商事 | U26: ホクレン商事 | V26: ﾎｸﾚﾝ | AM26: 2 | AN26: グループ間取引 | BG26: 0 | BH26: 0 | BI26: 国内 | BJ26: 1 | BK26: 0 | BM26: 3 | BN26: 1 | BO26: 3 | BP26: － | BU26: 住商 二郎 | BV26: 2.023071e+16 | BW26: 住商 一郎 | BX26: 2.0240807e+16 | CZ26: 0 | DA26: 0 | EZ26: 0 | FB26: 0 | FC26: 1 | FD26: 0 | FE26: 0 | FF26: 0 | FG26: 送付後、1カ月以内にご連絡がない場合は内容を確認済みとさせていただきます。 | FH26: 3 | FI26: 3 | FJ26: 翌月末振込（種苗課） | FK26: 翌月末振込（種苗課） | FL26: 1 | FM26: 2 | FN26: 0 | FR26: 2 | FS26: 0 | FT26: 0 | FU26: 0 | FV26: 1 | GA26: S02 | GB26: 振込-ＦＢ | GC26: 1 | GZ26: 18 | HA26: 北洋銀行 | HB26: 485 | HC26: 札幌市役所支店 | HD26: 1 | HE26: 8 | HF26: ホクレン商事 | HG26: ﾎｸﾚﾝ | HH26: 0 | IM26: 0 | IN26: 1 | IO26: 1 | IP26: 99
A27: 1 | C27: 0 | D27: 初期導入 | E27: 108521001 | H27: TOU00000001 | K27: 0 | L27: 0 | M27: 0 | N27: 0 | O27: 0 | P27: 1 | Q27: 1 | R27: 0 | S27: ㈱ホクレン商事 | U27: ホクレン商事 | V27: ﾎｸﾚﾝ | AM27: 2 | AN27: グループ間取引 | BG27: 0 | BH27: 0 | BI27: 国内 | BJ27: 1 | BK27: 0 | BM27: 3 | BN27: 1 | BO27: 3 | BP27: － | BU27: 住商 二郎 | BV27: 2.023071e+16 | BW27: 住商 一郎 | BX27: 2.0240807e+16 | CZ27: 0 | DA27: 0 | EZ27: 0 | FB27: 0 | FC27: 1 | FD27: 0 | FE27: 0 | FF27: 0 | FG27: 送付後、1カ月以内にご連絡がない場合は内容を確認済みとさせていただきます。 | FH27: 4 | FI27: 4 | FJ27: 翌月末振込（生産資材課（農薬）） | FK27: 翌月末振込（生資 | FL27: 1 | FM27: 2 | FN27: 0 | FR27: 2 | FS27: 0 | FT27: 0 | FU27: 0 | FV27: 1 | GA27: S02 | GB27: 振込-ＦＢ | GC27: 1 | GD27: 00200001 | GE27: 北信連本所 | GZ27: 20 | HA27: 北海道信金 | HB27: 1 | HC27: 本店 | HD27: 1 | HE27: 1112222 | HF27: ホクレン 生産資材課（農薬） | HG27: ﾎｸﾚﾝ | HH27: 0 | IM27: 0 | IN27: 1 | IO27: 1 | IP27: 99
A28: 1 | C28: 0 | D28: 初期導入 | E28: 108521001 | H28: TOU00000001 | K28: 0 | L28: 0 | M28: 0 | N28: 0 | O28: 0 | P28: 1 | Q28: 1 | R28: 0 | S28: ㈱ホクレン商事 | U28: ホクレン商事 | V28: ﾎｸﾚﾝ | AM28: 2 | AN28: グループ間取引 | BG28: 0 | BH28: 0 | BI28: 国内 | BJ28: 1 | BK28: 0 | BM28: 3 | BN28: 1 | BO28: 3 | BP28: － | BU28: 住商 二郎 | BV28: 2.023071e+16 | BW28: 住商 一郎 | BX28: 2.0240807e+16 | CZ28: 0 | DA28: 0 | EZ28: 0 | FB28: 0 | FC28: 1 | FD28: 0 | FE28: 0 | FF28: 0 | FG28: 送付後、1カ月以内にご連絡がない場合は内容を確認済みとさせていただきます。 | FH28: 5 | FI28: 5 | FJ28: 翌月末振込（酪農畜産課（生乳）） | FK28: 翌月末振込（酪畜） | FL28: 1 | FM28: 2 | FN28: 0 | FR28: 2 | FS28: 0 | FT28: 0 | FU28: 0 | FV28: 1 | GA28: S02 | GB28: 振込-ＦＢ | GC28: 1 | GD28: 00200002 | GE28: 北海道信金 山鼻中央 | GZ28: 20 | HA28: 北海道信金 | HB28: 5 | HC28: 山鼻中央支店 | HD28: 1 | HE28: 9995555 | HF28: ホクレン 北海道信金山鼻中央用 | HG28: ﾎｸﾚﾝ | HH28: 0 | IM28: 0 | IN28: 1 | IO28: 1 | IP28: 99
A29: 1 | C29: 0 | D29: 初期導入 | E29: 108521001 | H29: TOU00000001 | K29: 0 | L29: 0 | M29: 0 | N29: 0 | O29: 0 | P29: 1 | Q29: 1 | R29: 0 | S29: ㈱ホクレン商事 | U29: ホクレン商事 | V29: ﾎｸﾚﾝ | AM29: 2 | AN29: グループ間取引 | BG29: 0 | BH29: 0 | BI29: 国内 | BJ29: 1 | BK29: 0 | BM29: 3 | BN29: 1 | BO29: 3 | BP29: － | BU29: 住商 二郎 | BV29: 2.023071e+16 | BW29: 住商 一郎 | BX29: 2.0240807e+16 | CZ29: 0 | DA29: 0 | EZ29: 0 | FB29: 0 | FC29: 1 | FD29: 0 | FE29: 0 | FF29: 0 | FG29: 送付後、1カ月以内にご連絡がない場合は内容を確認済みとさせていただきます。 | FH29: 6 | FI29: 100 | FJ29: 随時支払 | FK29: 随時支払 | FL29: 1 | FM29: 2 | FN29: 0 | FR29: 1 | FS29: 0 | FT29: 0 | FU29: 0 | FV29: 1 | GA29: S02 | GB29: 振込-ＦＢ | GC29: 1 | GZ29: 3001 | HA29: 北海道信用農業協同組合連合会 | HB29: 820 | HC29: 本所 | HD29: 1 | HE29: 874 | HF29: ホクレン商事 | HG29: ﾎｸﾚﾝｼﾖｳｼﾞ | HH29: 0 | IM29: 0 | IN29: 1 | IO29: 0 | IP29: 1
A30: 1 | C30: 0 | D30: 初期導入 | E30: 108521001 | H30: TOU00000001 | K30: 0 | L30: 0 | M30: 0 | N30: 0 | O30: 0 | P30: 1 | Q30: 1 | R30: 0 | S30: ㈱ホクレン商事 | U30: ホクレン商事 | V30: ﾎｸﾚﾝ | AM30: 2 | AN30: グループ間取引 | BG30: 0 | BH30: 0 | BI30: 国内 | BJ30: 1 | BK30: 0 | BM30: 3 | BN30: 1 | BO30: 3 | BP30: － | BU30: 住商 二郎 | BV30: 2.023071e+16 | BW30: 住商 一郎 | BX30: 2.0240807e+16 | CZ30: 0 | DA30: 0 | EZ30: 0 | FB30: 0 | FC30: 1 | FD30: 0 | FE30: 0 | FF30: 0 | FG30: 送付後、1カ月以内にご連絡がない場合は内容を確認済みとさせていただきます。 | FH30: 7 | FI30: 6 | FJ30: 納付書支払 | FK30: 納付書支払 | FL30: 1 | FM30: 2 | FN30: 0 | FR30: 3 | FS30: 0 | FT30: 0 | FU30: 0 | FV30: 1 | GA30: S04 | GB30: 振込-総合 | GC30: 1 | GZ30: 19 | HA30: 北海道銀行 | HB30: 103 | HC30: 行啓通支店 | HD30: 1 | HE30: 8888884 | HF30: ホクレン商事 | HG30: ﾎｸﾚﾝｼﾖｳｼﾞ | HH30: 0 | IM30: 0 | IN30: 1 | IO30: 1 | IP30: 99
A31: 1 | C31: 0 | D31: 初期導入 | E31: 108521001 | H31: TOU00000001 | K31: 0 | L31: 0 | M31: 0 | N31: 0 | O31: 0 | P31: 1 | Q31: 1 | R31: 0 | S31: ㈱ホクレン商事 | U31: ホクレン商事 | V31: ﾎｸﾚﾝ | AM31: 2 | AN31: グループ間取引 | BG31: 0 | BH31: 0 | BI31: 国内 | BJ31: 1 | BK31: 0 | BM31: 3 | BN31: 1 | BO31: 3 | BP31: － | BU31: 住商 二郎 | BV31: 2.023071e+16 | BW31: 住商 一郎 | BX31: 2.0240807e+16 | CZ31: 0 | DA31: 0 | EZ31: 0 | FB31: 0 | FC31: 1 | FD31: 0 | FE31: 0 | FF31: 0 | FG31: 送付後、1カ月以内にご連絡がない場合は内容を確認済みとさせていただきます。 | FH31: 8 | FI31: 8 | FJ31: 一括決済_手形 | FK31: 一括決済_手形 | FL31: 1 | FM31: 2 | FN31: 0 | FR31: 1 | FS31: 0 | FT31: 0 | FU31: 0 | FV31: 1 | GA31: S07 | GB31: 支払手形 | GC31: 1 | HL31: 90 | HM31: 1 | HN31: 99 | HO31: 1 | HP31: ST005 | HQ31: 支払手形_一括決済 | IM31: 0 | IN31: 1 | IO31: 1 | IP31: 99
A32: 1 | C32: 0 | D32: 初期導入 | E32: 108521002 | H32: 10000000000010 | K32: 0 | L32: 0 | M32: 0 | N32: 0 | O32: 0 | P32: 0 | Q32: 0 | R32: 0 | S32: ㈱ホクレン商事 北見営業所 | U32: ホクレン 北見 | V32: ﾎｸﾚﾝ ｷﾀﾐ | BG32: 0 | BH32: 0 | BI32: 国内 | BJ32: 1 | BK32: 0 | BM32: 3 | BN32: 1 | BO32: 3 | BP32: － | BU32: 住商 二郎 | BV32: 2.023071e+16 | BW32: 住商 一郎 | BX32: 2.0240415e+16 | CZ32: 0 | DA32: 0 | EZ32: 0 | FB32: 0 | FC32: 1 | FD32: 1 | FE32: 0 | FF32: 0
A33: 1 | C33: 0 | D33: 初期導入 | E33: 108521003 | H33: SHOKUIN001 | K33: 0 | L33: 0 | M33: 0 | N33: 0 | O33: 0 | P33: 0 | Q33: 1 | R33: 0 | S33: ホクレン商事営業部 | U33: ﾎｸﾚﾝ商事営業部 | V33: ﾎｸﾚﾝｼｮｳｼﾞｴｲｷﾞｮｳﾌﾞ | BG33: 0 | BH33: 0 | BI33: 国内 | BJ33: 1 | BK33: 0 | BM33: 3 | BN33: 1 | BO33: 3 | BP33: － | BU33: 住商 一郎 | BV33: 2.0240422e+16 | BW33: 住商 一郎 | BX33: 2.0240702e+16 | CZ33: 0 | DA33: 0 | EZ33: 0 | FA33: 職員 | FB33: 0 | FC33: 1 | FD33: 0 | FE33: 0 | FF33: 0 | FG33: 職員向けの支払いです。 | FH33: 1 | FI33: 100 | FJ33: 翌月末振込（職員） | FK33: 翌月末振込（職員） | FL33: 1 | FM33: 2 | FN33: 0 | FR33: 2 | FS33: 0 | FT33: 0 | FU33: 0 | FV33: 1 | GA33: S02 | GB33: 振込-ＦＢ | GC33: 1 | GZ33: 3001 | HA33: 北海道信用農業協同組合連合会 | HB33: 820 | HC33: 本所 | HD33: 1 | HE33: 4808 | HF33: ホクレン商事営業部 | HG33: ﾎｸﾚﾝｼﾖｳｼﾞｴｲｷﾞﾖｳﾌﾞ | HH33: 0 | IM33: 0 | IN33: 1 | IO33: 1 | IP33: 99
A34: 1 | C34: 0 | D34: 初期導入 | E34: 108521003 | H34: SHOKUIN001 | K34: 0 | L34: 0 | M34: 0 | N34: 0 | O34: 0 | P34: 0 | Q34: 1 | R34: 0 | S34: ホクレン商事営業部 | U34: ﾎｸﾚﾝ商事営業部 | V34: ﾎｸﾚﾝｼｮｳｼﾞｴｲｷﾞｮｳﾌﾞ | BG34: 0 | BH34: 0 | BI34: 国内 | BJ34: 1 | BK34: 0 | BM34: 3 | BN34: 1 | BO34: 3 | BP34: － | BU34: 住商 一郎 | BV34: 2.0240422e+16 | BW34: 住商 一郎 | BX34: 2.0240702e+16 | CZ34: 0 | DA34: 0 | EZ34: 0 | FA34: 職員 | FB34: 0 | FC34: 1 | FD34: 0 | FE34: 0 | FF34: 0 | FG34: 職員向けの支払いです。 | FH34: 2 | FI34: 1 | FJ34: 翌月末振込（職員） | FK34: 翌月末振込（職員） | FL34: 1 | FM34: 2 | FN34: 0 | FR34: 2 | FS34: 0 | FT34: 0 | FU34: 0 | FV34: 1 | GA34: S02 | GB34: 振込-ＦＢ | GC34: 1 | GZ34: 19 | HA34: 北海道銀行 | HB34: 101 | HC34: 本店 | HD34: 1 | HE34: 9876543 | HF34: 職員口座 | HG34: ｼﾖｸｲﾝｺｳｻﾞ | HH34: 0 | IM34: 0 | IN34: 1 | IO34: 1 | IP34: 99
A35: 1 | C35: 0 | D35: 初期導入 | E35: 108521004 | K35: 0 | L35: 0 | M35: 0 | N35: 0 | O35: 0 | P35: 0 | Q35: 1 | R35: 0 | S35: ホクレン商事店舗部 | U35: ﾎｸﾚﾝ商事店舗部 | V35: ﾎｸﾚﾝｼｮｳｼﾞﾃﾝﾎﾟﾌﾞ | BG35: 0 | BH35: 0 | BI35: 国内 | BJ35: 1 | BK35: 0 | BM35: 3 | BN35: 1 | BO35: 3 | BP35: － | BU35: 住商 一郎 | BV35: 2.0240702e+16 | BW35: 住商 一郎 | BX35: 2.0240702e+16 | CZ35: 0 | DA35: 0 | EZ35: 0 | FB35: 0 | FC35: 1 | FD35: 1 | FE35: 1 | FF35: 0 | FG35: 送付後、1カ月以内にご連絡がない場合は内容を確認済みとさせていただきます。 | FH35: 1 | FI35: 100 | FJ35: 随時支払 FB振込 | FK35: 随時支払 FB振込 | FL35: 1 | FM35: 2 | FN35: 0 | FR35: 3 | FS35: 0 | FT35: 0 | FU35: 0 | FV35: 1 | GA35: S02 | GB35: 振込-ＦＢ | GC35: 1 | GZ35: 116 | HA35: 北海道銀行 | HB35: 151 | HC35: 札幌駅前店 | HD35: 2 | HE35: 1516743 | HF35: ホクレン商事店舗部 | HG35: ﾎｸﾚﾝｼﾖｳｼﾞﾃﾝﾎﾟﾌﾞ | HH35: 0 | IM35: 0 | IN35: 2 | IQ35: 10
A36: 1 | C36: 0 | D36: 初期導入 | E36: 108521006 | K36: 0 | L36: 0 | M36: 0 | N36: 0 | O36: 0 | P36: 0 | Q36: 1 | R36: 0 | S36: （株）ホクレン商事リース事業部 | U36: ﾎｸﾚﾝ商事ﾘｰｽ事業部 | V36: ﾎｸﾚﾝｼｮｳｼﾞﾘｰｽ | BG36: 0 | BH36: 0 | BI36: 国内 | BJ36: 1 | BK36: 0 | BM36: 3 | BN36: 1 | BO36: 3 | BP36: － | BU36: 住商 一郎 | BV36: 2.0240702e+16 | BW36: 住商 一郎 | BX36: 2.0240702e+16 | CZ36: 0 | DA36: 0 | EZ36: 0 | FB36: 0 | FC36: 1 | FD36: 0 | FE36: 0 | FF36: 0 | FG36: 送付後、1カ月以内にご連絡がない場合は内容を確認済みとさせていただきます。 | FH36: 1 | FI36: 100 | FJ36: 随時支払 FB振込 | FK36: 随時支払 FB振込 | FL36: 1 | FM36: 2 | FN36: 0 | FR36: 3 | FS36: 0 | FT36: 0 | FU36: 0 | FV36: 1 | GA36: S02 | GB36: 振込-ＦＢ | GC36: 1 | GZ36: 116 | HA36: 北海道銀行 | HB36: 151 | HC36: 札幌駅前店 | HD36: 2 | HE36: 1662545 | HF36: （株）ホクレン商事リース事業部 | HG36: ﾎｸﾚﾝｼﾖｳｼﾞﾘ-ｽ | HH36: 0 | IM36: 0 | IN36: 2 | IQ36: 10
A37: 1 | C37: 0 | D37: 初期導入 | E37: 108521007 | K37: 0 | L37: 0 | M37: 0 | N37: 0 | O37: 0 | P37: 0 | Q37: 1 | R37: 0 | S37: （株）ホクレン商事補聴器センタ | U37: ﾎｸﾚﾝ商事補聴器ｾﾝﾀ | V37: ﾎｸﾚﾝｼｮｳｼﾞﾎﾁｮｳｷｾﾝﾀｰ | BG37: 0 | BH37: 0 | BI37: 国内 | BJ37: 1 | BK37: 0 | BM37: 3 | BN37: 1 | BO37: 3 | BP37: － | BU37: 住商 一郎 | BV37: 2.0240702e+16 | BW37: 住商 一郎 | BX37: 2.0240702e+16 | CZ37: 0 | DA37: 0 | EZ37: 0 | FB37: 0 | FC37: 1 | FD37: 1 | FE37: 1 | FF37: 0 | FG37: 送付後、1カ月以内にご連絡がない場合は内容を確認済みとさせていただきます。 | FH37: 1 | FI37: 100 | FJ37: 随時支払 FB振込 | FK37: 随時支払 FB振込 | FL37: 1 | FM37: 2 | FN37: 0 | FR37: 3 | FS37: 0 | FT37: 0 | FU37: 0 | FV37: 1 | GA37: S02 | GB37: 振込-ＦＢ | GC37: 1 | GZ37: 3001 | HA37: 北海道信用農業協同組合連合会 | HB37: 820 | HC37: 本所 | HD37: 2 | HE37: 885 | HF37: （株）ホクレン商事補聴器センタ | HG37: ﾎｸﾚﾝｼﾖｳｼﾞﾎﾁﾖｳｷｾﾝﾀ- | HH37: 0 | IM37: 0 | IN37: 2 | IQ37: 10
A38: 1 | C38: 0 | D38: 初期導入 | E38: 108521011 | K38: 0 | L38: 0 | M38: 0 | N38: 0 | O38: 0 | P38: 0 | Q38: 1 | R38: 0 | S38: ホクレン商事営業部情報サービス | U38: ﾎｸﾚﾝ商事営業部情報 | V38: ﾎｸﾚﾝｼｮｳｼﾞｴｲｷﾞｮｳﾌﾞｼﾞｮｳﾎｳｻｰﾋﾞｽ | BG38: 0 | BH38: 0 | BI38: 国内 | BJ38: 1 | BK38: 0 | BM38: 3 | BN38: 1 | BO38: 3 | BP38: － | BU38: 住商 一郎 | BV38: 2.0240702e+16 | BW38: 住商 一郎 | BX38: 2.0240702e+16 | CZ38: 0 | DA38: 0 | EZ38: 0 | FB38: 0 | FC38: 1 | FD38: 0 | FE38: 0 | FF38: 0 | FG38: 送付後、1カ月以内にご連絡がない場合は内容を確認済みとさせていただきます。 | FH38: 1 | FI38: 100 | FJ38: 随時支払 FB振込 | FK38: 随時支払 FB振込 | FL38: 1 | FM38: 2 | FN38: 0 | FR38: 3 | FS38: 0 | FT38: 0 | FU38: 0 | FV38: 1 | GA38: S02 | GB38: 振込-ＦＢ | GC38: 1 | GZ38: 3001 | HA38: 北海道信用農業協同組合連合会 | HB38: 820 | HC38: 本所 | HD38: 2 | HE38: 885 | HF38: ホクレン商事営業部情報サービス | HG38: ﾎｸﾚﾝｼﾖｳｼﾞｴｲｷﾞﾖｳﾌﾞｼﾞﾖｳﾎｳｻ-ﾋﾞｽ | HH38: 0 | IM38: 0 | IN38: 2 | IQ38: 10
A39: 1 | C39: 0 | D39: 初期導入 | E39: 108521034 | K39: 0 | L39: 0 | M39: 0 | N39: 0 | O39: 0 | P39: 0 | Q39: 1 | R39: 0 | S39: （株）ホクレン商事 | U39: ﾎｸﾚﾝ商事 | V39: ﾎｸﾚﾝｼｮｳｼﾞ | BG39: 0 | BH39: 0 | BI39: 国内 | BJ39: 1 | BK39: 0 | BM39: 3 | BN39: 1 | BO39: 3 | BP39: － | BU39: 住商 一郎 | BV39: 2.0240702e+16 | BW39: 住商 一郎 | BX39: 2.0240702e+16 | CZ39: 0 | DA39: 0 | EZ39: 0 | FB39: 0 | FC39: 1 | FD39: 1 | FE39: 1 | FF39: 0 | FG39: 送付後、1カ月以内にご連絡がない場合は内容を確認済みとさせていただきます。 | FH39: 1 | FI39: 100 | FJ39: 随時支払 FB振込 | FK39: 随時支払 FB振込 | FL39: 1 | FM39: 2 | FN39: 0 | FR39: 3 | FS39: 0 | FT39: 0 | FU39: 0 | FV39: 1 | GA39: S02 | GB39: 振込-ＦＢ | GC39: 1 | GZ39: 3001 | HA39: 北海道信用農業協同組合連合会 | HB39: 820 | HC39: 本所 | HD39: 2 | HE39: 915 | HF39: （株）ホクレン商事 | HG39: ﾎｸﾚﾝｼﾖｳｼﾞ | HH39: 0 | IM39: 0 | IN39: 2 | IQ39: 10
A40: 1 | C40: 0 | D40: 初期導入 | E40: 108521100 | K40: 0 | L40: 0 | M40: 0 | N40: 0 | O40: 0 | P40: 0 | Q40: 1 | R40: 0 | S40: ホクレン商事 店舗本部 | U40: ﾎｸﾚﾝ商事 店舗本部 | V40: ﾎｸﾚﾝｼｮｳｼﾞ | BG40: 0 | BH40: 0 | BI40: 国内 | BJ40: 1 | BK40: 0 | BM40: 3 | BN40: 1 | BO40: 3 | BP40: － | BU40: 住商 一郎 | BV40: 2.0240702e+16 | BW40: 住商 一郎 | BX40: 2.0240702e+16 | CZ40: 0 | DA40: 0 | EZ40: 0 | FB40: 0 | FC40: 1 | FD40: 1 | FE40: 1 | FF40: 0 | FG40: 送付後、1カ月以内にご連絡がない場合は内容を確認済みとさせていただきます。 | FH40: 1 | FI40: 100 | FJ40: 随時支払 FB振込 | FK40: 随時支払 FB振込 | FL40: 1 | FM40: 2 | FN40: 0 | FR40: 3 | FS40: 0 | FT40: 0 | FU40: 0 | FV40: 1 | GA40: S02 | GB40: 振込-ＦＢ | GC40: 1 | GZ40: 116 | HA40: 北海道銀行 | HB40: 151 | HC40: 札幌駅前店 | HD40: 2 | HE40: 1662510 | HF40: ホクレン商事 店舗本部 | HG40: ﾎｸﾚﾝｼﾖｳｼﾞ | HH40: 0 | IM40: 0 | IN40: 2 | IQ40: 10
A41: 1 | C41: 0 | D41: 初期導入 | E41: 108521160 | K41: 0 | L41: 0 | M41: 0 | N41: 0 | O41: 0 | P41: 0 | Q41: 1 | R41: 0 | S41: ホクレン商事 道北地区 | U41: ﾎｸﾚﾝ商事 道北地区 | V41: ﾎｸﾚﾝｼｮｳｼﾞ | BG41: 0 | BH41: 0 | BI41: 国内 | BJ41: 1 | BK41: 0 | BM41: 3 | BN41: 1 | BO41: 3 | BP41: － | BU41: 住商 一郎 | BV41: 2.0240702e+16 | BW41: 住商 一郎 | BX41: 2.0240702e+16 | CZ41: 0 | DA41: 0 | EZ41: 0 | FB41: 0 | FC41: 1 | FD41: 1 | FE41: 1 | FF41: 0 | FG41: 送付後、1カ月以内にご連絡がない場合は内容を確認済みとさせていただきます。 | FH41: 1 | FI41: 100 | FJ41: 随時支払 FB振込 | FK41: 随時支払 FB振込 | FL41: 1 | FM41: 2 | FN41: 0 | FR41: 3 | FS41: 0 | FT41: 0 | FU41: 0 | FV41: 1 | GA41: S02 | GB41: 振込-ＦＢ | GC41: 1 | GZ41: 3210 | HA41: あさひかわ農業協同組合 | HB41: 2 | HC41: 北部支所 | HD41: 2 | HE41: 959033 | HF41: ホクレン商事 道北地区 | HG41: ﾎｸﾚﾝｼﾖｳｼﾞ | HH41: 0 | IM41: 0 | IN41: 2 | IQ41: 10
A42: 1 | C42: 0 | D42: 初期導入 | E42: 108521162 | K42: 0 | L42: 0 | M42: 0 | N42: 0 | O42: 0 | P42: 0 | Q42: 1 | R42: 0 | S42: ホクレン商事 道東地区 | U42: ﾎｸﾚﾝ商事 道東地区 | V42: ﾎｸﾚﾝｼｮｳｼﾞ | BG42: 0 | BH42: 0 | BI42: 国内 | BJ42: 1 | BK42: 0 | BM42: 3 | BN42: 1 | BO42: 3 | BP42: － | BU42: 住商 一郎 | BV42: 2.0240702e+16 | BW42: 住商 一郎 | BX42: 2.0240702e+16 | CZ42: 0 | DA42: 0 | EZ42: 0 | FB42: 0 | FC42: 1 | FD42: 1 | FE42: 1 | FF42: 0 | FG42: 送付後、1カ月以内にご連絡がない場合は内容を確認済みとさせていただきます。 | FH42: 1 | FI42: 100 | FJ42: 随時支払 FB振込 | FK42: 随時支払 FB振込 | FL42: 1 | FM42: 2 | FN42: 0 | FR42: 3 | FS42: 0 | FT42: 0 | FU42: 0 | FV42: 1 | GA42: S02 | GB42: 振込-ＦＢ | GC42: 1 | GZ42: 3001 | HA42: 北海道信用農業協同組合連合会 | HB42: 820 | HC42: 本所 | HD42: 2 | HE42: 498315 | HF42: ホクレン商事 道東地区 | HG42: ﾎｸﾚﾝｼﾖｳｼﾞ | HH42: 0 | IM42: 0 | IN42: 2 | IQ42: 10
A43: 1 | C43: 0 | D43: 初期導入 | E43: 108521635 | K43: 0 | L43: 0 | M43: 0 | N43: 0 | O43: 0 | P43: 0 | Q43: 1 | R43: 0 | S43: （株）ホクレン商事営業部保険課 | U43: ﾎｸﾚﾝ商事営業部保険課 | V43: ﾎｸﾚﾝｼｮｳｼﾞ | BG43: 0 | BH43: 0 | BI43: 国内 | BJ43: 1 | BK43: 0 | BM43: 3 | BN43: 1 | BO43: 3 | BP43: － | BU43: 住商 一郎 | BV43: 2.0240702e+16 | BW43: 住商 一郎 | BX43: 2.0240702e+16 | CZ43: 0 | DA43: 0 | EZ43: 0 | FB43: 0 | FC43: 1 | FD43: 0 | FE43: 0 | FF43: 0 | FG43: 送付後、1カ月以内にご連絡がない場合は内容を確認済みとさせていただきます。 | FH43: 1 | FI43: 100 | FJ43: 随時支払 FB振込 | FK43: 随時支払 FB振込 | FL43: 1 | FM43: 2 | FN43: 0 | FR43: 3 | FS43: 0 | FT43: 0 | FU43: 0 | FV43: 1 | GA43: S02 | GB43: 振込-ＦＢ | GC43: 1 | GZ43: 3001 | HA43: 北海道信用農業協同組合連合会 | HB43: 820 | HC43: 本所 | HD43: 2 | HE43: 926 | HF43: （株）ホクレン商事営業部保険課 | HG43: ﾎｸﾚﾝｼﾖｳｼﾞ | HH43: 0 | IM43: 0 | IN43: 2 | IQ43: 10
A44: 1 | C44: 0 | D44: 初期導入 | E44: 108521636 | K44: 0 | L44: 0 | M44: 0 | N44: 0 | O44: 0 | P44: 0 | Q44: 1 | R44: 0 | S44: ホクレン商事営業部情報サービス | U44: ﾎｸﾚﾝ商事営業部情報 | V44: ﾎｸﾚﾝｼｮｳｼﾞ | BG44: 0 | BH44: 0 | BI44: 国内 | BJ44: 1 | BK44: 0 | BM44: 3 | BN44: 1 | BO44: 3 | BP44: － | BU44: 住商 一郎 | BV44: 2.0240702e+16 | BW44: 住商 一郎 | BX44: 2.0240702e+16 | CZ44: 0 | DA44: 0 | EZ44: 0 | FB44: 0 | FC44: 1 | FD44: 0 | FE44: 0 | FF44: 0 | FG44: 送付後、1カ月以内にご連絡がない場合は内容を確認済みとさせていただきます。 | FH44: 1 | FI44: 100 | FJ44: 随時支払 FB振込 | FK44: 随時支払 FB振込 | FL44: 1 | FM44: 2 | FN44: 0 | FR44: 3 | FS44: 0 | FT44: 0 | FU44: 0 | FV44: 1 | GA44: S02 | GB44: 振込-ＦＢ | GC44: 1 | GZ44: 3001 | HA44: 北海道信用農業協同組合連合会 | HB44: 820 | HC44: 本所 | HD44: 2 | HE44: 885 | HF44: ホクレン商事営業部情報サービス | HG44: ﾎｸﾚﾝｼﾖｳｼﾞ | HH44: 0 | IM44: 0 | IN44: 2 | IQ44: 10
A45: 1 | C45: 0 | D45: 初期導入 | E45: 108521637 | K45: 0 | L45: 0 | M45: 0 | N45: 0 | O45: 0 | P45: 0 | Q45: 1 | R45: 0 | S45: （株）ホクレン商事 管理部 | U45: ﾎｸﾚﾝ商事 管理部 | V45: ﾎｸﾚﾝｼｮｳｼﾞ | BG45: 0 | BH45: 0 | BI45: 国内 | BJ45: 1 | BK45: 0 | BM45: 3 | BN45: 1 | BO45: 3 | BP45: － | BU45: 住商 一郎 | BV45: 2.0240702e+16 | BW45: 住商 一郎 | BX45: 2.0240702e+16 | CZ45: 0 | DA45: 0 | EZ45: 0 | FB45: 0 | FC45: 1 | FD45: 1 | FE45: 1 | FF45: 0 | FG45: 送付後、1カ月以内にご連絡がない場合は内容を確認済みとさせていただきます。 | FH45: 1 | FI45: 100 | FJ45: 随時支払 FB振込 | FK45: 随時支払 FB振込 | FL45: 1 | FM45: 2 | FN45: 0 | FR45: 3 | FS45: 0 | FT45: 0 | FU45: 0 | FV45: 1 | GA45: S02 | GB45: 振込-ＦＢ | GC45: 1 | GZ45: 116 | HA45: 北海道銀行 | HB45: 151 | HC45: 札幌駅前店 | HD45: 2 | HE45: 73991 | HF45: （株）ホクレン商事 管理部 | HG45: ﾎｸﾚﾝｼﾖｳｼﾞ | HH45: 0 | IM45: 0 | IN45: 2 | IQ45: 10
A46: 1 | C46: 0 | D46: 初期導入 | E46: 108521644 | K46: 0 | L46: 0 | M46: 0 | N46: 0 | O46: 0 | P46: 0 | Q46: 1 | R46: 0 | S46: （株）ホクレン商事 管理部 | U46: ﾎｸﾚﾝ商事 管理部 | V46: ﾎｸﾚﾝｼｮｳｼﾞ | BG46: 0 | BH46: 0 | BI46: 国内 | BJ46: 1 | BK46: 0 | BM46: 3 | BN46: 1 | BO46: 3 | BP46: － | BU46: 住商 一郎 | BV46: 2.0240702e+16 | BW46: 住商 一郎 | BX46: 2.0240702e+16 | CZ46: 0 | DA46: 0 | EZ46: 0 | FB46: 0 | FC46: 1 | FD46: 1 | FE46: 1 | FF46: 0 | FG46: 送付後、1カ月以内にご連絡がない場合は内容を確認済みとさせていただきます。 | FH46: 1 | FI46: 100 | FJ46: 随時支払 FB振込 | FK46: 随時支払 FB振込 | FL46: 1 | FM46: 2 | FN46: 0 | FR46: 3 | FS46: 0 | FT46: 0 | FU46: 0 | FV46: 1 | GA46: S02 | GB46: 振込-ＦＢ | GC46: 1 | GZ46: 116 | HA46: 北海道銀行 | HB46: 151 | HC46: 札幌駅前店 | HD46: 2 | HE46: 73991 | HF46: （株）ホクレン商事 管理部 | HG46: ﾎｸﾚﾝｼﾖｳｼﾞ | HH46: 0 | IM46: 0 | IN46: 2 | IQ46: 10
A47: 1 | C47: 0 | D47: 初期導入 | E47: 1085230001 | H47: H231231 | K47: 0 | L47: 0 | M47: 0 | N47: 0 | O47: 0 | P47: 1 | Q47: 1 | R47: 0 | S47: ㈱ホクレン通商 | U47: ホクレンショウジ | V47: ﾎｸﾚﾝﾂｳｼｮｳ | BG47: 0 | BH47: 0 | BI47: 国内 | BJ47: 1 | BK47: 0 | BM47: 3 | BN47: 1 | BO47: 3 | BP47: － | BU47: 住商 二郎 | BV47: 2.0230712e+16 | BW47: 住商 一郎 | BX47: 2.0240415e+16 | CZ47: 0 | DA47: 0 | EZ47: 0 | FA47: ホクレンショウジ | FB47: 0 | FC47: 1 | FD47: 1 | FE47: 1 | FF47: 0 | FG47: ※お支払い | FH47: 1 | FI47: 2 | FJ47: 定時支払（月末締め翌月末支払） | FK47: 月末締め翌月末支払 | FL47: 1 | FM47: 1 | FN47: 1 | FR47: 3 | FS47: 1 | FT47: 0 | FU47: 0 | FV47: 1 | GA47: S02 | GB47: 振込-ＦＢ | GC47: 1 | GZ47: 9 | HA47: 三井住友 | HB47: 1 | HC47: 銀座 | HD47: 2 | HE47: 1234567 | HF47: ホクレン商事 | HG47: ﾎｸﾚﾝｼﾖｳｼﾞ | HH47: 0 | IM47: 99 | IN47: 1 | IO47: 1 | IP47: 99
A48: 1 | C48: 0 | D48: 初期導入 | E48: 1085230001 | H48: H231231 | K48: 0 | L48: 0 | M48: 0 | N48: 0 | O48: 0 | P48: 1 | Q48: 1 | R48: 0 | S48: ㈱ホクレン通商 | U48: ホクレンショウジ | V48: ﾎｸﾚﾝﾂｳｼｮｳ | BG48: 0 | BH48: 0 | BI48: 国内 | BJ48: 1 | BK48: 0 | BM48: 3 | BN48: 1 | BO48: 3 | BP48: － | BU48: 住商 二郎 | BV48: 2.0230712e+16 | BW48: 住商 一郎 | BX48: 2.0240415e+16 | CZ48: 0 | DA48: 0 | EZ48: 0 | FA48: ホクレンショウジ | FB48: 0 | FC48: 1 | FD48: 1 | FE48: 1 | FF48: 0 | FG48: ※お支払い | FH48: 2 | FI48: 1 | FJ48: 末締め翌月末支払 | FK48: 末締め翌月末支払 | FL48: 1 | FM48: 2 | FN48: 0 | FR48: 3 | FS48: 0 | FT48: 0 | FU48: 0 | FV48: 1 | GA48: S02 | GB48: 振込-ＦＢ | GC48: 1 | GZ48: 1 | HA48: みずほ | HB48: 1 | HC48: 丸の内 | HD48: 2 | HE48: 1233456 | HF48: 住商一郎 | HG48: ｽﾐｼﾖｳｲﾁﾛｳ | HH48: 0 | IM48: 0 | IN48: 1 | IO48: 1 | IP48: 99
A49: 1 | C49: 0 | D49: 初期導入 | E49: 108523006 | H49: 10000000000011 | K49: 0 | L49: 0 | M49: 0 | N49: 0 | O49: 0 | P49: 1 | Q49: 1 | R49: 0 | S49: ㈱ホクレン通商 海外業務部 | U49: ホ通商 海外業務部 | V49: ﾎｸﾚﾝﾂｳｼｮｳ ｶｲｶﾞｲｷﾞｮﾑﾑ | BG49: 0 | BH49: 0 | BI49: 国内 | BJ49: 1 | BK49: 0 | BM49: 3 | BN49: 1 | BO49: 3 | BP49: － | BU49: 住商 二郎 | BV49: 2.0230712e+16 | BW49: 住商 一郎 | BX49: 2.0240415e+16 | CZ49: 0 | DA49: 0 | EZ49: 0 | FB49: 0 | FC49: 1 | FD49: 1 | FE49: 1 | FF49: 0 | FG49: 送付後、1カ月以内にご連絡がない場合は内容を確認済みとさせていただきます。
A50: 1 | C50: 0 | D50: 初期導入 | E50: 108525001 | H50: 10000000000012 | K50: 0 | L50: 0 | M50: 0 | N50: 0 | O50: 0 | P50: 0 | Q50: 0 | R50: 0 | S50: ホクレン包材㈱ | U50: ホクレン包材㈱ | V50: hokuren | BG50: 0 | BH50: 0 | BI50: 国内 | BJ50: 1 | BK50: 0 | BM50: 3 | BN50: 1 | BO50: 3 | BP50: － | BU50: 住商 一郎 | BV50: 2.023072e+16 | BW50: 住商 一郎 | BX50: 2.0240415e+16 | CZ50: 0 | DA50: 0 | EZ50: 0 | FB50: 0 | FC50: 1 | FD50: 1 | FE50: 0 | FF50: 0
A51: 1 | C51: 0 | D51: 初期導入 | E51: 109000001 | H51: 10000000000013 | K51: 0 | L51: 0 | M51: 0 | N51: 0 | O51: 0 | P51: 0 | Q51: 0 | R51: 0 | S51: 北海道信連 | U51: 北海道信連 | V51: hokkaido | BG51: 0 | BH51: 0 | BI51: 国内 | BJ51: 1 | BK51: 0 | BM51: 3 | BN51: 1 | BO51: 3 | BP51: － | BU51: 住商 一郎 | BV51: 2.023072e+16 | BW51: 住商 一郎 | BX51: 2.0240415e+16 | CZ51: 0 | DA51: 0 | EZ51: 0 | FB51: 0 | FC51: 1 | FD51: 1 | FE51: 0 | FF51: 0
A52: 1 | C52: 0 | D52: 初期導入 | E52: 1101 | H52: 00000001 | I52: KIGYO0000000001 | J52: 品川電気・本社 | K52: 0 | L52: 0 | M52: 0 | N52: 0 | O52: 0 | P52: 1 | Q52: 1 | R52: 0 | S52: 株式会社品川電気 | T52: 経理部 経理課 | U52: 品川電気・本社 | V52: ｼﾅｶﾞﾜﾃﾞﾝｷ | AD52: 140-0001 | AE52: 東京都品川区北品川1-1-1 | AH52: 03-3321-0012 | AI52: 03-3321-0010 | AJ52: 20030401 | AK52: 99991231 | AM52: 1 | AN52: 通常取引 | AO52: H | AP52: 情報通信業 | AQ52: 281 | AR52: 通信機械器具製造業 | AS52: 13 | AT52: 近畿 | AU52: 3 | AV52: 工数請負(製造) | BG52: 0 | BH52: 0 | BI52: 国内 | BJ52: 1 | BK52: 1 | BL52: JPY | BM52: 2 | BN52: 1 | BO52: 3 | BP52: － | BV52: 2.0041101e+16 | BW52: 住商 一郎 | BX52: 2.0231215e+16 | CZ52: 0 | DA52: 0 | EZ52: 0 | FA52: 株式会社品川電気 | FB52: 0 | FC52: 1 | FD52: 0 | FE52: 0 | FF52: 0 | FH52: 1 | FI52: 1 | FJ52: 当月15日締翌月15日払、当月末締翌月末払 | FK52: [締]15,末[払]翌15,末 | FL52: 1 | FM52: 1 | FN52: 0 | FR52: 2 | FS52: 0 | FT52: 0 | FU52: 0 | FV52: 1 | GA52: S02 | GB52: 振込-ＦＢ | GC52: 1 | GD52: JISHA001 | GE52: みずほ 築地 | GZ52: 5 | HA52: 三菱UFJ | HB52: 1 | HC52: 品川駅前 | HD52: 2 | HE52: 1234567 | HF52: 株式会社品川電気 | HG52: ｼﾅｶﾞﾜﾃﾞﾝｷ | HH52: 0 | IM52: 15 | IN52: 1 | IO52: 1 | IP52: 15
A53: 1 | C53: 0 | D53: 初期導入 | E53: 1101 | H53: 00000001 | I53: KIGYO0000000001 | J53: 品川電気・本社 | K53: 0 | L53: 0 | M53: 0 | N53: 0 | O53: 0 | P53: 1 | Q53: 1 | R53: 0 | S53: 株式会社品川電気 | T53: 経理部 経理課 | U53: 品川電気・本社 | V53: ｼﾅｶﾞﾜﾃﾞﾝｷ | AD53: 140-0001 | AE53: 東京都品川区北品川1-1-1 | AH53: 03-3321-0012 | AI53: 03-3321-0010 | AJ53: 20030401 | AK53: 99991231 | AM53: 1 | AN53: 通常取引 | AO53: H | AP53: 情報通信業 | AQ53: 281 | AR53: 通信機械器具製造業 | AS53: 13 | AT53: 近畿 | AU53: 3 | AV53: 工数請負(製造) | BG53: 0 | BH53: 0 | BI53: 国内 | BJ53: 1 | BK53: 1 | BL53: JPY | BM53: 2 | BN53: 1 | BO53: 3 | BP53: － | BV53: 2.0041101e+16 | BW53: 住商 一郎 | BX53: 2.0231215e+16 | CZ53: 0 | DA53: 0 | EZ53: 0 | FA53: 株式会社品川電気 | FB53: 0 | FC53: 1 | FD53: 0 | FE53: 0 | FF53: 0 | FH53: 1 | FI53: 1 | FJ53: 当月15日締翌月15日払、当月末締翌月末払 | FK53: [締]15,末[払]翌15,末 | FL53: 1 | FM53: 1 | FN53: 0 | FR53: 2 | FS53: 0 | FT53: 0 | FU53: 0 | FV53: 1 | GA53: S02 | GB53: 振込-ＦＢ | GC53: 1 | GD53: JISHA001 | GE53: みずほ 築地 | GZ53: 5 | HA53: 三菱UFJ | HB53: 1 | HC53: 品川駅前 | HD53: 2 | HE53: 1234567 | HF53: 株式会社品川電気 | HG53: ｼﾅｶﾞﾜﾃﾞﾝｷ | HH53: 0 | IM53: 99 | IN53: 1 | IO53: 1 | IP53: 99
A54: 1 | C54: 0 | D54: 初期導入 | E54: 1101 | H54: 00000001 | I54: KIGYO0000000001 | J54: 品川電気・本社 | K54: 0 | L54: 0 | M54: 0 | N54: 0 | O54: 0 | P54: 1 | Q54: 1 | R54: 0 | S54: 株式会社品川電気 | T54: 経理部 経理課 | U54: 品川電気・本社 | V54: ｼﾅｶﾞﾜﾃﾞﾝｷ | AD54: 140-0001 | AE54: 東京都品川区北品川1-1-1 | AH54: 03-3321-0012 | AI54: 03-3321-0010 | AJ54: 20030401 | AK54: 99991231 | AM54: 1 | AN54: 通常取引 | AO54: H | AP54: 情報通信業 | AQ54: 281 | AR54: 通信機械器具製造業 | AS54: 13 | AT54: 近畿 | AU54: 3 | AV54: 工数請負(製造) | BG54: 0 | BH54: 0 | BI54: 国内 | BJ54: 1 | BK54: 1 | BL54: JPY | BM54: 2 | BN54: 1 | BO54: 3 | BP54: － | BV54: 2.0041101e+16 | BW54: 住商 一郎 | BX54: 2.0231215e+16 | CZ54: 0 | DA54: 0 | EZ54: 0 | FA54: 株式会社品川電気 | FB54: 0 | FC54: 1 | FD54: 0 | FE54: 0 | FF54: 0 | FH54: 2 | FI54: 2 | FJ54: 外貨決済 | FK54: 外貨決済 | FL54: 2 | FM54: 2 | FN54: 0 | FR54: 9 | FS54: 0 | FT54: 0 | FU54: 0 | FV54: 1 | GA54: S10 | GB54: 外為取引 | GC54: 1 | GD54: 00000001 | GE54: 振込元口座（住友） | IM54: 0 | IN54: 1 | IO54: 0 | IP54: 20
A55: 1 | C55: 0 | D55: 初期導入 | E55: 1101 | H55: 00000001 | I55: KIGYO0000000001 | J55: 品川電気・本社 | K55: 0 | L55: 0 | M55: 0 | N55: 0 | O55: 0 | P55: 1 | Q55: 1 | R55: 0 | S55: 株式会社品川電気 | T55: 経理部 経理課 | U55: 品川電気・本社 | V55: ｼﾅｶﾞﾜﾃﾞﾝｷ | AD55: 140-0001 | AE55: 東京都品川区北品川1-1-1 | AH55: 03-3321-0012 | AI55: 03-3321-0010 | AJ55: 20030401 | AK55: 99991231 | AM55: 1 | AN55: 通常取引 | AO55: H | AP55: 情報通信業 | AQ55: 281 | AR55: 通信機械器具製造業 | AS55: 13 | AT55: 近畿 | AU55: 3 | AV55: 工数請負(製造) | BG55: 0 | BH55: 0 | BI55: 国内 | BJ55: 1 | BK55: 1 | BL55: JPY | BM55: 2 | BN55: 1 | BO55: 3 | BP55: － | BV55: 2.0041101e+16 | BW55: 住商 一郎 | BX55: 2.0231215e+16 | CZ55: 0 | DA55: 0 | EZ55: 0 | FA55: 株式会社品川電気 | FB55: 0 | FC55: 1 | FD55: 0 | FE55: 0 | FF55: 0 | FH55: 3 | FI55: 3 | FJ55: 当月末締翌月末支払 | FK55: 当月末締翌月末支払 | FL55: 1 | FM55: 2 | FN55: 0 | FR55: 2 | FS55: 0 | FT55: 0 | FU55: 0 | FV55: 1 | GA55: S02 | GB55: 振込-ＦＢ | GC55: 3 | GZ55: 5 | HA55: 三菱UFJ | HB55: 3 | HC55: 日本橋 | HD55: 1 | HE55: 1342300 | HF55: 品川電気 | HG55: ｼﾅｶﾞﾜﾃﾞﾝｷ | HH55: 0 | IM55: 0 | IN55: 1 | IO55: 1 | IP55: 99
A56: 1 | C56: 0 | D56: 初期導入 | E56: 1101 | H56: 00000001 | I56: KIGYO0000000001 | J56: 品川電気・本社 | K56: 0 | L56: 0 | M56: 0 | N56: 0 | O56: 0 | P56: 1 | Q56: 1 | R56: 0 | S56: 株式会社品川電気 | T56: 経理部 経理課 | U56: 品川電気・本社 | V56: ｼﾅｶﾞﾜﾃﾞﾝｷ | AD56: 140-0001 | AE56: 東京都品川区北品川1-1-1 | AH56: 03-3321-0012 | AI56: 03-3321-0010 | AJ56: 20030401 | AK56: 99991231 | AM56: 1 | AN56: 通常取引 | AO56: H | AP56: 情報通信業 | AQ56: 281 | AR56: 通信機械器具製造業 | AS56: 13 | AT56: 近畿 | AU56: 3 | AV56: 工数請負(製造) | BG56: 0 | BH56: 0 | BI56: 国内 | BJ56: 1 | BK56: 1 | BL56: JPY | BM56: 2 | BN56: 1 | BO56: 3 | BP56: － | BV56: 2.0041101e+16 | BW56: 住商 一郎 | BX56: 2.0231215e+16 | CZ56: 0 | DA56: 0 | EZ56: 0 | FA56: 株式会社品川電気 | FB56: 0 | FC56: 1 | FD56: 0 | FE56: 0 | FF56: 0 | FH56: 4 | FI56: 4 | FJ56: 20日締翌末振替翌25日払：ファクタリング振込 | FK56: 20締99振替25払：Ｆ振 | FL56: 1 | FM56: 1 | FN56: 1 | FR56: 3 | FS56: 0 | FT56: 0 | FU56: 0 | FV56: 1 | GA56: FC1 | GB56: ﾌｧｸﾀﾘﾝｸﾞ振込(住商Ｆ) | GC56: 1 | GZ56: 294 | HA56: 住友信託 | HB56: 1 | HC56: 晴海出張所 | HD56: 2 | HE56: 417001 | HF56: 品川電気・本社 | HG56: ｼﾅｶﾞﾜﾃﾞﾝｷ/ﾎﾝｼﾔ | HH56: 0 | HS56: 1 | HT56: 25 | HU56: 1 | IM56: 20 | IN56: 1 | IO56: 1 | IP56: 99
A57: 1 | C57: 0 | D57: 初期導入 | E57: 1101 | H57: 00000001 | I57: KIGYO0000000001 | J57: 品川電気・本社 | K57: 0 | L57: 0 | M57: 0 | N57: 0 | O57: 0 | P57: 1 | Q57: 1 | R57: 0 | S57: 株式会社品川電気 | T57: 経理部 経理課 | U57: 品川電気・本社 | V57: ｼﾅｶﾞﾜﾃﾞﾝｷ | AD57: 140-0001 | AE57: 東京都品川区北品川1-1-1 | AH57: 03-3321-0012 | AI57: 03-3321-0010 | AJ57: 20030401 | AK57: 99991231 | AM57: 1 | AN57: 通常取引 | AO57: H | AP57: 情報通信業 | AQ57: 281 | AR57: 通信機械器具製造業 | AS57: 13 | AT57: 近畿 | AU57: 3 | AV57: 工数請負(製造) | BG57: 0 | BH57: 0 | BI57: 国内 | BJ57: 1 | BK57: 1 | BL57: JPY | BM57: 2 | BN57: 1 | BO57: 3 | BP57: － | BV57: 2.0041101e+16 | BW57: 住商 一郎 | BX57: 2.0231215e+16 | CZ57: 0 | DA57: 0 | EZ57: 0 | FA57: 株式会社品川電気 | FB57: 0 | FC57: 1 | FD57: 0 | FE57: 0 | FF57: 0 | FH57: 5 | FI57: 5 | FJ57: 随時当末振替翌末払：ファクタリング引落 | FK57: 99振替99支払：Ｆ引落 | FL57: 1 | FM57: 2 | FN57: 0 | FR57: 3 | FS57: 0 | FT57: 0 | FU57: 0 | FV57: 1 | GA57: FC2 | GB57: ﾌｧｸﾀﾘﾝｸﾞ引落(住商Ｆ) | GC57: 1 | HS57: 1 | HT57: 99 | HU57: 1 | IM57: 0 | IN57: 1 | IO57: 1 | IP57: 99
A58: 1 | C58: 0 | D58: 初期導入 | E58: 1101 | H58: 00000001 | I58: KIGYO0000000001 | J58: 品川電気・本社 | K58: 0 | L58: 0 | M58: 0 | N58: 0 | O58: 0 | P58: 1 | Q58: 1 | R58: 0 | S58: 株式会社品川電気 | T58: 経理部 経理課 | U58: 品川電気・本社 | V58: ｼﾅｶﾞﾜﾃﾞﾝｷ | AD58: 140-0001 | AE58: 東京都品川区北品川1-1-1 | AH58: 03-3321-0012 | AI58: 03-3321-0010 | AJ58: 20030401 | AK58: 99991231 | AM58: 1 | AN58: 通常取引 | AO58: H | AP58: 情報通信業 | AQ58: 281 | AR58: 通信機械器具製造業 | AS58: 13 | AT58: 近畿 | AU58: 3 | AV58: 工数請負(製造) | BG58: 0 | BH58: 0 | BI58: 国内 | BJ58: 1 | BK58: 1 | BL58: JPY | BM58: 2 | BN58: 1 | BO58: 3 | BP58: － | BV58: 2.0041101e+16 | BW58: 住商 一郎 | BX58: 2.0231215e+16 | CZ58: 0 | DA58: 0 | EZ58: 0 | FA58: 株式会社品川電気 | FB58: 0 | FC58: 1 | FD58: 0 | FE58: 0 | FF58: 0 | FH58: 6 | FI58: 6 | FJ58: 振込-総合-期日なし | FK58: 振込-総合-期日なし | FL58: 1 | FM58: 2 | FN58: 0 | FR58: 2 | FS58: 0 | FT58: 0 | FU58: 0 | FV58: 1 | GA58: S04 | GB58: 振込-総合 | GC58: 1 | GZ58: 0 | HA58: 日本銀行 | HB58: 93 | HC58: 本店 | HD58: 1 | HE58: 9876543 | HF58: ホクレン太郎 | HG58: ﾎｸﾚﾝﾀﾛｳ | HH58: 0 | IM58: 0 | IN58: 1 | IO58: 0 | IP58: 99
A59: 1 | C59: 0 | D59: 初期導入 | E59: 1102 | H59: 10000000000014 | I59: KIGYO0000000002 | J59: 品川電気・購買 | K59: 0 | L59: 0 | M59: 0 | N59: 0 | O59: 0 | P59: 1 | Q59: 0 | R59: 0 | S59: 株式会社品川電気 | T59: 購買部 | U59: 品川電気・購買 | V59: ｼﾅｶﾞﾜﾃﾞﾝｷ | AD59: 140-0001 | AE59: 東京都品川区北品川1-1-1 | AH59: 03-3321-0021 | AI59: 03-3321-0020 | AJ59: 20030401 | AK59: 99991231 | AM59: 1 | AN59: 通常取引 | BG59: 0 | BH59: 0 | BI59: 国内 | BJ59: 1 | BK59: 0 | BM59: 2 | BN59: 1 | BO59: 3 | BP59: － | BV59: 2.0041101e+16 | BW59: 住商 一郎 | BX59: 2.0240415e+16 | CZ59: 0 | DA59: 0 | EZ59: 0 | FB59: 0 | FC59: 3 | FD59: 0 | FE59: 0 | FF59: 0
A60: 1 | C60: 0 | D60: 初期導入 | E60: 1103 | H60: 10000000000015 | I60: KIGYO0000000003 | J60: 品川電気・大崎 | K60: 0 | L60: 0 | M60: 0 | N60: 0 | O60: 0 | P60: 1 | Q60: 0 | R60: 0 | S60: 株式会社品川電気 | T60: 大崎営業所 OAサプライ営業部 | U60: 品川電気・大崎 | V60: ｼﾅｶﾞﾜﾃﾞﾝｷ | AD60: 141-0021 | AE60: 東京都品川区上大崎1-19-1 | AH60: 03-3000-1000 | AI60: 03-3000-2000 | AJ60: 20030401 | AK60: 99991231 | AM60: 1 | AN60: 通常取引 | BG60: 0 | BH60: 0 | BI60: 国内 | BJ60: 1 | BK60: 0 | BM60: 2 | BN60: 1 | BO60: 3 | BP60: － | BV60: 2.0041101e+16 | BW60: 住商 一郎 | BX60: 2.0240415e+16 | CZ60: 0 | DA60: 0 | EZ60: 0 | FB60: 0 | FC60: 3 | FD60: 0 | FE60: 0 | FF60: 0
A61: 1 | C61: 0 | D61: 初期導入 | E61: 1104 | H61: 123456XXXXXA | I61: KIGYO0000000004 | J61: 本牧商事 | K61: 0 | L61: 0 | M61: 0 | N61: 0 | O61: 0 | P61: 1 | Q61: 1 | R61: 0 | S61: 本牧商事株式会社 | T61: 経理部 経理課 | U61: 本牧商事 | V61: ﾎﾝﾓｸｼｮｳｼﾞｶﾌﾞｼｷｶﾞｲｼｬ | AD61: 231-0804 | AE61: 神奈川県横浜市中区本牧宮原11-10 | AH61: 045-440-0123 | AI61: 045-440-0124 | AJ61: 20030401 | AK61: 99991231 | AM61: 3 | AN61: 部門間取引 | BG61: 0 | BH61: 0 | BI61: 国内 | BJ61: 1 | BK61: 1 | BL61: JPY | BM61: 2 | BN61: 1 | BO61: 3 | BP61: － | BV61: 2.0041101e+16 | BW61: 住商 一郎 | BX61: 2.0231214e+16 | CZ61: 0 | DA61: 0 | EZ61: 0 | FB61: 0 | FC61: 1 | FD61: 0 | FE61: 0 | FF61: 0 | FH61: 1 | FI61: 1 | FJ61: 当月末締 翌月末払い | FK61: [締]当月末[払]翌月末 | FL61: 1 | FM61: 1 | FN61: 1 | FR61: 2 | FS61: 0 | FT61: 0 | FU61: 0 | FV61: 1 | GA61: S02 | GB61: 振込-ＦＢ | GC61: 1 | GD61: 00000001 | GE61: 振込元口座（住友） | GZ61: 5 | HA61: 三菱UFJ | HB61: 3 | HC61: 日本橋 | HD61: 2 | HE61: 1234567 | HF61: 株式会社本牧商事 | HG61: ﾎﾝﾓｸｼﾖｳｼﾞ | HH61: 1 | IM61: 99 | IN61: 1 | IO61: 1 | IP61: 99
A62: 1 | C62: 0 | D62: 初期導入 | E62: 1104 | H62: 123456XXXXXA | I62: KIGYO0000000004 | J62: 本牧商事 | K62: 0 | L62: 0 | M62: 0 | N62: 0 | O62: 0 | P62: 1 | Q62: 1 | R62: 0 | S62: 本牧商事株式会社 | T62: 経理部 経理課 | U62: 本牧商事 | V62: ﾎﾝﾓｸｼｮｳｼﾞｶﾌﾞｼｷｶﾞｲｼｬ | AD62: 231-0804 | AE62: 神奈川県横浜市中区本牧宮原11-10 | AH62: 045-440-0123 | AI62: 045-440-0124 | AJ62: 20030401 | AK62: 99991231 | AM62: 3 | AN62: 部門間取引 | BG62: 0 | BH62: 0 | BI62: 国内 | BJ62: 1 | BK62: 1 | BL62: JPY | BM62: 2 | BN62: 1 | BO62: 3 | BP62: － | BV62: 2.0041101e+16 | BW62: 住商 一郎 | BX62: 2.0231214e+16 | CZ62: 0 | DA62: 0 | EZ62: 0 | FB62: 0 | FC62: 1 | FD62: 0 | FE62: 0 | FF62: 0 | FH62: 2 | FI62: 2 | FJ62: 外貨決済 | FK62: 外貨決済 | FL62: 2 | FM62: 2 | FN62: 0 | FR62: 9 | FS62: 0 | FT62: 0 | FU62: 0 | FV62: 1 | GA62: S10 | GB62: 外為取引 | GC62: 1 | GD62: 00000001 | GE62: 振込元口座（住友） | IM62: 0 | IN62: 1 | IO62: 0 | IP62: 20
A63: 1 | C63: 0 | D63: 初期導入 | E63: 1104 | H63: 123456XXXXXA | I63: KIGYO0000000004 | J63: 本牧商事 | K63: 0 | L63: 0 | M63: 0 | N63: 0 | O63: 0 | P63: 1 | Q63: 1 | R63: 0 | S63: 本牧商事株式会社 | T63: 経理部 経理課 | U63: 本牧商事 | V63: ﾎﾝﾓｸｼｮｳｼﾞｶﾌﾞｼｷｶﾞｲｼｬ | AD63: 231-0804 | AE63: 神奈川県横浜市中区本牧宮原11-10 | AH63: 045-440-0123 | AI63: 045-440-0124 | AJ63: 20030401 | AK63: 99991231 | AM63: 3 | AN63: 部門間取引 | BG63: 0 | BH63: 0 | BI63: 国内 | BJ63: 1 | BK63: 1 | BL63: JPY | BM63: 2 | BN63: 1 | BO63: 3 | BP63: － | BV63: 2.0041101e+16 | BW63: 住商 一郎 | BX63: 2.0231214e+16 | CZ63: 0 | DA63: 0 | EZ63: 0 | FB63: 0 | FC63: 1 | FD63: 0 | FE63: 0 | FF63: 0 | FH63: 3 | FI63: 3 | FJ63: 20日締翌末振替翌25日払：ファクタリング振込 | FK63: 20締99振替25払：Ｆ振 | FL63: 1 | FM63: 1 | FN63: 1 | FR63: 3 | FS63: 0 | FT63: 0 | FU63: 0 | FV63: 1 | GA63: FC1 | GB63: ﾌｧｸﾀﾘﾝｸﾞ振込(住商Ｆ) | GC63: 1 | GZ63: 5 | HA63: 三菱UFJ | HB63: 3 | HC63: 日本橋 | HD63: 2 | HE63: 1234567 | HF63: 株式会社本牧商事 | HG63: ﾎﾝﾓｸｼﾖｳｼﾞ | HH63: 1 | HS63: 1 | HT63: 25 | HU63: 1 | IM63: 20 | IN63: 1 | IO63: 1 | IP63: 99
A64: 1 | C64: 0 | D64: 初期導入 | E64: 1104 | H64: 123456XXXXXA | I64: KIGYO0000000004 | J64: 本牧商事 | K64: 0 | L64: 0 | M64: 0 | N64: 0 | O64: 0 | P64: 1 | Q64: 1 | R64: 0 | S64: 本牧商事株式会社 | T64: 経理部 経理課 | U64: 本牧商事 | V64: ﾎﾝﾓｸｼｮｳｼﾞｶﾌﾞｼｷｶﾞｲｼｬ | AD64: 231-0804 | AE64: 神奈川県横浜市中区本牧宮原11-10 | AH64: 045-440-0123 | AI64: 045-440-0124 | AJ64: 20030401 | AK64: 99991231 | AM64: 3 | AN64: 部門間取引 | BG64: 0 | BH64: 0 | BI64: 国内 | BJ64: 1 | BK64: 1 | BL64: JPY | BM64: 2 | BN64: 1 | BO64: 3 | BP64: － | BV64: 2.0041101e+16 | BW64: 住商 一郎 | BX64: 2.0231214e+16 | CZ64: 0 | DA64: 0 | EZ64: 0 | FB64: 0 | FC64: 1 | FD64: 0 | FE64: 0 | FF64: 0 | FH64: 4 | FI64: 4 | FJ64: 随時当末振替翌末払：ファクタリング引落 | FK64: 99振替99支払：Ｆ引落 | FL64: 1 | FM64: 2 | FN64: 0 | FR64: 3 | FS64: 0 | FT64: 0 | FU64: 0 | FV64: 1 | GA64: FC2 | GB64: ﾌｧｸﾀﾘﾝｸﾞ引落(住商Ｆ) | GC64: 1 | HS64: 1 | HT64: 99 | HU64: 1 | IM64: 0 | IN64: 1 | IO64: 1 | IP64: 99
A65: 1 | C65: 0 | D65: 初期導入 | E65: 1105 | H65: 10000000000016 | I65: KIGYO0000000005 | J65: 三ツ沢工業経理 | K65: 0 | L65: 0 | M65: 0 | N65: 0 | O65: 0 | P65: 1 | Q65: 1 | R65: 0 | S65: 三ツ沢工業株式会社 | T65: 経理部 財務グループ | U65: 三ツ沢工業経理 | V65: ﾐﾂｻﾜｺｳｷﾞｮｳ | AD65: 240-8501 | AE65: 神奈川県横浜市保土ヶ谷区常盤台79-1 | AH65: 045-555-5555 | AI65: 045-555-5556 | AJ65: 20030401 | AK65: 99991231 | AM65: 3 | AN65: 部門間取引 | BG65: 0 | BH65: 0 | BI65: 国内 | BJ65: 1 | BK65: 0 | BM65: 2 | BN65: 1 | BO65: 3 | BP65: － | BV65: 2.0041101e+16 | BW65: 住商 一郎 | BX65: 2.0240704e+16 | CZ65: 0 | DA65: 0 | EZ65: 0 | FA65: 三ツ沢工業株式会社 | FB65: 0 | FC65: 2 | FD65: 0 | FE65: 0 | FF65: 0 | FH65: 1 | FI65: 1 | FJ65: 随時締め 翌月25日払い | FK65: [締]取引日[払]翌月25 | FL65: 1 | FM65: 2 | FN65: 0 | FR65: 2 | FS65: 0 | FT65: 0 | FU65: 0 | FV65: 1 | GA65: S02 | GB65: 振込-ＦＢ | GC65: 1 | GD65: JISHA007 | GE65: 三井住友 銀座 | GZ65: 10 | HA65: りそな | HB65: 1 | HC65: 横浜駅西口 | HD65: 2 | HE65: 123455 | HF65: 三ツ沢工業株式会社 | HG65: ﾐﾂｻﾜｺｳｷﾞﾖｳ(ｶ | HH65: 0 | IM65: 0 | IN65: 1 | IO65: 1 | IP65: 25
A66: 1 | C66: 0 | D66: 初期導入 | E66: 1106 | H66: 10000000000017 | I66: KIGYO0000000006 | J66: 三ツ沢工業総務 | K66: 0 | L66: 0 | M66: 0 | N66: 0 | O66: 0 | P66: 1 | Q66: 1 | R66: 0 | S66: 三ツ沢工業株式会社 | T66: 総務部 総務グループ | U66: 三ツ沢工業総務 | V66: ﾐﾂｻﾜｺｳｷﾞｮｳ | AD66: 240-8501 | AE66: 横浜市保土ヶ谷区常盤台79-1 | AH66: 045-555-5556 | AI66: 045-555-5567 | AJ66: 20030401 | AK66: 99991231 | AM66: 3 | AN66: 部門間取引 | BG66: 0 | BH66: 0 | BI66: 国内 | BJ66: 1 | BK66: 0 | BM66: 1 | BN66: 1 | BO66: 3 | BP66: － | BV66: 2.0041101e+16 | BW66: 住商 一郎 | BX66: 2.0240415e+16 | CZ66: 0 | DA66: 0 | EZ66: 0 | FA66: 三ツ沢工業株式会社 | FB66: 0 | FC66: 1 | FD66: 0 | FE66: 0 | FF66: 0 | FH66: 1 | FI66: 1 | FJ66: 当月末締め 翌々月末払い | FK66: [締]月末[払]翌々月末 | FL66: 1 | FM66: 1 | FN66: 0 | FR66: 2 | FS66: 0 | FT66: 0 | FU66: 0 | FV66: 1 | GA66: S02 | GB66: 振込-ＦＢ | GC66: 1 | GD66: JISHA001 | GE66: みずほ 築地 | GZ66: 1 | HA66: みずほ | HB66: 1 | HC66: 丸の内 | HD66: 1 | HE66: 1234568 | HF66: 三ツ沢工業株式会社 | HG66: ﾐﾂｻﾜｺｳｷﾞﾖｳ | HH66: 0 | IM66: 31 | IN66: 1 | IO66: 2 | IP66: 31
A67: 1 | C67: 0 | D67: 初期導入 | E67: 1106 | H67: 10000000000017 | I67: KIGYO0000000006 | J67: 三ツ沢工業総務 | K67: 0 | L67: 0 | M67: 0 | N67: 0 | O67: 0 | P67: 1 | Q67: 1 | R67: 0 | S67: 三ツ沢工業株式会社 | T67: 総務部 総務グループ | U67: 三ツ沢工業総務 | V67: ﾐﾂｻﾜｺｳｷﾞｮｳ | AD67: 240-8501 | AE67: 横浜市保土ヶ谷区常盤台79-1 | AH67: 045-555-5556 | AI67: 045-555-5567 | AJ67: 20030401 | AK67: 99991231 | AM67: 3 | AN67: 部門間取引 | BG67: 0 | BH67: 0 | BI67: 国内 | BJ67: 1 | BK67: 0 | BM67: 1 | BN67: 1 | BO67: 3 | BP67: － | BV67: 2.0041101e+16 | BW67: 住商 一郎 | BX67: 2.0240415e+16 | CZ67: 0 | DA67: 0 | EZ67: 0 | FA67: 三ツ沢工業株式会社 | FB67: 0 | FC67: 1 | FD67: 0 | FE67: 0 | FF67: 0 | FH67: 2 | FI67: 2 | FJ67: 20日締翌末振替翌25日払：ファクタリング振込 | FK67: 20締99振替25払：Ｆ振 | FL67: 1 | FM67: 1 | FN67: 1 | FR67: 3 | FS67: 0 | FT67: 0 | FU67: 0 | FV67: 1 | GA67: FC1 | GB67: ﾌｧｸﾀﾘﾝｸﾞ振込(住商Ｆ) | GC67: 1 | GZ67: 1 | HA67: みずほ | HB67: 1 | HC67: 丸の内 | HD67: 1 | HE67: 1234568 | HF67: 三ツ沢工業株式会社 | HG67: ﾐﾂｻﾜｺｳｷﾞﾖｳ | HH67: 0 | HS67: 1 | HT67: 25 | HU67: 1 | IM67: 20 | IN67: 1 | IO67: 1 | IP67: 99
A68: 1 | C68: 0 | D68: 初期導入 | E68: 1107 | H68: 10000000000018 | I68: KIGYO0000000007 | J68: 東京物産本社 | K68: 0 | L68: 0 | M68: 0 | N68: 0 | O68: 0 | P68: 1 | Q68: 1 | R68: 0 | S68: 東京物産株式会社 | U68: 東京物産本社 | V68: ﾄｳｷｮｳﾌﾞｯｻﾝ | AD68: 120-0006 | AE68: 東京都中央区晴海9-8-7 | AF68: 晴海中央ビルディング21階 | AH68: 03-5656-1111 | AI68: 03-5656-1117 | AJ68: 20030401 | AK68: 99991231 | AM68: 1 | AN68: 通常取引 | BG68: 0 | BH68: 0 | BI68: 国内 | BJ68: 1 | BK68: 1 | BL68: JPY | BM68: 2 | BN68: 1 | BO68: 3 | BP68: － | BV68: 2.0041101e+16 | BW68: 住商 一郎 | BX68: 2.0240415e+16 | CZ68: 0 | DA68: 0 | EZ68: 0 | FA68: 東京物産株式会社 | FB68: 0 | FC68: 1 | FD68: 0 | FE68: 0 | FF68: 0 | FH68: 1 | FI68: 1 | FJ68: 当月末締め 翌月末払い | FK68: [締]当月末[払]翌月末 | FL68: 1 | FM68: 1 | FN68: 0 | FR68: 2 | FS68: 0 | FT68: 1000000 | FU68: 0 | FV68: 1 | GA68: S04 | GB68: 振込-総合 | GC68: 1 | GD68: JISHA007 | GE68: 三井住友 銀座 | GK68: 1 | GP68: S07 | GQ68: 支払手形 | GR68: 9 | GS68: JISHA007 | GT68: 三井住友 銀座 | GZ68: 1 | HA68: みずほ | HB68: 3 | HC68: 八重洲口 | HD68: 2 | HE68: 76541 | HF68: 東京物産株式会社 | HG68: ﾄｳｷﾖｳﾌﾞﾂｻﾝ(ｶ | HH68: 0 | HL68: 60 | HM68: 2 | HN68: 31 | HO68: 1 | HP68: ST001 | HQ68: 支払手形（営業） | IM68: 31 | IN68: 1 | IO68: 1 | IP68: 31 | IV68: 1 | IW68: 1 | IX68: 31
A69: 1 | C69: 0 | D69: 初期導入 | E69: 1107 | H69: 10000000000018 | I69: KIGYO0000000007 | J69: 東京物産本社 | K69: 0 | L69: 0 | M69: 0 | N69: 0 | O69: 0 | P69: 1 | Q69: 1 | R69: 0 | S69: 東京物産株式会社 | U69: 東京物産本社 | V69: ﾄｳｷｮｳﾌﾞｯｻﾝ | AD69: 120-0006 | AE69: 東京都中央区晴海9-8-7 | AF69: 晴海中央ビルディング21階 | AH69: 03-5656-1111 | AI69: 03-5656-1117 | AJ69: 20030401 | AK69: 99991231 | AM69: 1 | AN69: 通常取引 | BG69: 0 | BH69: 0 | BI69: 国内 | BJ69: 1 | BK69: 1 | BL69: JPY | BM69: 2 | BN69: 1 | BO69: 3 | BP69: － | BV69: 2.0041101e+16 | BW69: 住商 一郎 | BX69: 2.0240415e+16 | CZ69: 0 | DA69: 0 | EZ69: 0 | FA69: 東京物産株式会社 | FB69: 0 | FC69: 1 | FD69: 0 | FE69: 0 | FF69: 0 | FH69: 2 | FI69: 2 | FJ69: 外貨決済 | FK69: 外貨決済 | FL69: 2 | FM69: 2 | FN69: 0 | FR69: 9 | FS69: 0 | FT69: 0 | FU69: 0 | FV69: 1 | GA69: S11 | GB69: 外為送金 | GC69: 1 | GD69: JISHA008 | GE69: 三井住友 外貨 | HV69: 1 | HW69: 1 | HX69: 0 | IA69: TEST | IB69: TEST-ADRESS | IC69: 123456789 | ID69: TEST-BANK | IE69: TEST-BANK-2 | IM69: 0 | IN69: 1 | IO69: 0 | IP69: 20
A70: 1 | C70: 0 | D70: 初期導入 | E70: 1108 | H70: 10000000000019 | I70: KIGYO0000000008 | J70: 東京物産名古屋 | K70: 0 | L70: 0 | M70: 0 | N70: 0 | O70: 0 | P70: 1 | Q70: 1 | R70: 0 | S70: 東京物産株式会社 | U70: 東京物産名古屋 | V70: ﾄｳｷｮｳﾌﾞｯｻﾝﾅｺﾞﾔ | AD70: 453-0000 | AE70: 名古屋市中村区中央9-8-7 | AH70: 052-3332-1111 | AI70: 052-5555-4444 | AJ70: 20030401 | AK70: 99991231 | BG70: 0 | BH70: 0 | BI70: 国内 | BJ70: 1 | BK70: 0 | BM70: 2 | BN70: 1 | BO70: 3 | BP70: － | BV70: 2.0041101e+16 | BW70: 住商 一郎 | BX70: 2.0240415e+16 | CZ70: 0 | DA70: 0 | EZ70: 0 | FA70: 東京物産株式会社 | FB70: 0 | FC70: 1 | FD70: 0 | FE70: 0 | FF70: 0 | FH70: 1 | FI70: 1 | FJ70: 当月末締め 翌月末払い | FK70: [締]当月末[払]翌月末 | FL70: 1 | FM70: 1 | FN70: 0 | FR70: 2 | FS70: 0 | FT70: 1000000 | FU70: 0 | FV70: 1 | GA70: S05 | GB70: 郵便振込 | GC70: 1 | GK70: 1 | GP70: S07 | GQ70: 支払手形 | GR70: 9 | GS70: JISHA007 | GT70: 三井住友 銀座 | HI70: 1108_00000001 | HJ70: 東京物産株式会社 名古屋営業所 | HK70: ﾄｳｷﾖｳﾌﾞﾂｻﾝ ﾅｺﾞﾔｴｲｷﾞﾖｳｼﾖ | HL70: 60 | HM70: 2 | HN70: 31 | HO70: 1 | HP70: ST001 | HQ70: 支払手形（営業） | IM70: 31 | IN70: 1 | IO70: 1 | IP70: 31 | IV70: 1 | IW70: 1 | IX70: 31
A71: 1 | C71: 0 | D71: 初期導入 | E71: 1108 | H71: 10000000000019 | I71: KIGYO0000000008 | J71: 東京物産名古屋 | K71: 0 | L71: 0 | M71: 0 | N71: 0 | O71: 0 | P71: 1 | Q71: 1 | R71: 0 | S71: 東京物産株式会社 | U71: 東京物産名古屋 | V71: ﾄｳｷｮｳﾌﾞｯｻﾝﾅｺﾞﾔ | AD71: 453-0000 | AE71: 名古屋市中村区中央9-8-7 | AH71: 052-3332-1111 | AI71: 052-5555-4444 | AJ71: 20030401 | AK71: 99991231 | BG71: 0 | BH71: 0 | BI71: 国内 | BJ71: 1 | BK71: 0 | BM71: 2 | BN71: 1 | BO71: 3 | BP71: － | BV71: 2.0041101e+16 | BW71: 住商 一郎 | BX71: 2.0240415e+16 | CZ71: 0 | DA71: 0 | EZ71: 0 | FA71: 東京物産株式会社 | FB71: 0 | FC71: 1 | FD71: 0 | FE71: 0 | FF71: 0 | FH71: 2 | FI71: 2 | FJ71: 当月末締翌末手形発行 | FK71: 当月末締翌末手形発行 | FL71: 1 | FM71: 1 | FN71: 0 | FR71: 3 | FS71: 0 | FT71: 0 | FU71: 0 | FV71: 1 | GA71: S16 | GB71: でんさいネット | GC71: 1 | GD71: JISHA007 | GE71: 三井住友 銀座 | HL71: 100 | HM71: 3 | HN71: 20 | HO71: 1 | HP71: ST004 | HQ71: 電子記録債務 | IM71: 29 | IN71: 1 | IO71: 0 | IP71: 29
A72: 1 | C72: 0 | D72: 初期導入 | E72: 1109 | H72: 10000000000020 | I72: KIGYO0000000009 | J72: 東京物産大阪 | K72: 0 | L72: 0 | M72: 0 | N72: 0 | O72: 0 | P72: 1 | Q72: 1 | R72: 0 | S72: 東京物産株式会社 | T72: 大阪支社 | U72: 東京物産大阪 | V72: ﾄｳｷｮｳﾌﾞｯｻﾝｵｵｻｶ | AD72: 556-5555 | AE72: 大阪市北区梅田3-165 | AH72: 06-5656-4444 | AI72: 06-5656-3333 | AJ72: 20030401 | AK72: 99991231 | BG72: 0 | BH72: 0 | BI72: 国内 | BJ72: 1 | BK72: 0 | BM72: 2 | BN72: 1 | BO72: 3 | BP72: － | BV72: 2.0041101e+16 | BW72: 住商 一郎 | BX72: 2.0240415e+16 | CZ72: 0 | DA72: 0 | EZ72: 0 | FA72: 東京物産株式会社 | FB72: 0 | FC72: 1 | FD72: 0 | FE72: 0 | FF72: 0 | FH72: 1 | FI72: 1 | FJ72: 当月末締め 翌月末払い | FK72: [締]当月末[払]翌月末 | FL72: 1 | FM72: 2 | FN72: 0 | FR72: 2 | FS72: 0 | FT72: 1000000 | FU72: 0 | FV72: 1 | GA72: S05 | GB72: 郵便振込 | GC72: 1 | GK72: 1 | GP72: S07 | GQ72: 支払手形 | GR72: 9 | GS72: JISHA007 | GT72: 三井住友 銀座 | HI72: 1109_00000001 | HJ72: 東京物産株式会社 大阪事業所 | HK72: ﾄｳｷﾖｳﾌﾞﾂｻﾝ ｵｵｻｶｼﾞｷﾞﾖｳｼ | HL72: 60 | HM72: 2 | HN72: 31 | HO72: 1 | HP72: ST001 | HQ72: 支払手形（営業） | IM72: 0 | IN72: 1 | IO72: 1 | IP72: 31 | IV72: 1 | IW72: 1 | IX72: 31
A73: 1 | C73: 0 | D73: 初期導入 | E73: 1110 | H73: 10000000000021 | I73: KIGYO0000000010 | J73: 東京物産札幌 | K73: 0 | L73: 0 | M73: 0 | N73: 0 | O73: 0 | P73: 1 | Q73: 1 | R73: 0 | S73: 東京物産株式会社 | T73: 札幌支店 | U73: 東京物産札幌 | V73: ﾄｳｷｮｳﾌﾞｯｻﾝｻｯﾎﾟﾛ | AD73: 060-0042 | AE73: 札幌市中央区大通西8-7-7 | AH73: 023-4444-1111 | AI73: 023-3333-1111 | AJ73: 20030101 | AK73: 99991231 | BG73: 0 | BH73: 0 | BI73: 国内 | BJ73: 1 | BK73: 0 | BM73: 2 | BN73: 1 | BO73: 3 | BP73: － | BV73: 2.0041101e+16 | BW73: 住商 一郎 | BX73: 2.0240415e+16 | CZ73: 0 | DA73: 0 | EZ73: 0 | FA73: 東京物産株式会社 | FB73: 0 | FC73: 1 | FD73: 0 | FE73: 0 | FF73: 0 | FH73: 1 | FI73: 1 | FJ73: 当月末締め 翌月末払い | FK73: [締]当月末[払]翌月末 | FL73: 1 | FM73: 2 | FN73: 0 | FR73: 2 | FS73: 0 | FT73: 1000000 | FU73: 0 | FV73: 1 | GA73: S01 | GB73: 振込-ＦＢ-期日する | GC73: 1 | GD73: JISHA007 | GE73: 三井住友 銀座 | GK73: 1 | GP73: S07 | GQ73: 支払手形 | GR73: 9 | GS73: JISHA007 | GT73: 三井住友 銀座 | GZ73: 1 | HA73: みずほ | HB73: 3 | HC73: 八重洲口 | HD73: 2 | HE73: 76541 | HF73: 東京物産株式会社 | HG73: ﾄｳｷﾖｳﾌﾞﾂｻﾝ(ｶ | HH73: 1 | HL73: 60 | HM73: 2 | HN73: 31 | HO73: 1 | HP73: ST001 | HQ73: 支払手形（営業） | HR73: 90 | HS73: 3 | HT73: 99 | HU73: 1 | IM73: 0 | IN73: 1 | IO73: 1 | IP73: 31 | IV73: 1 | IW73: 1 | IX73: 31
A74: 1 | C74: 0 | D74: 初期導入 | E74: 1111 | H74: 10000000000022 | I74: KIGYO0000000011 | J74: 東京物産福岡 | K74: 0 | L74: 0 | M74: 0 | N74: 0 | O74: 0 | P74: 1 | Q74: 1 | R74: 0 | S74: 東京物産株式会社 | T74: 福岡支店 | U74: 東京物産福岡 | V74: ｷﾆｲﾁｲﾁｼﾞｭｳｲﾁ | AD74: 816-0079 | AE74: 福岡市博多区神屋町3-9-7 | AH74: 092-444-1111 | AI74: 092-444-1112 | AJ74: 20030101 | AK74: 99991231 | BG74: 0 | BH74: 0 | BI74: 国内 | BJ74: 1 | BK74: 0 | BM74: 2 | BN74: 1 | BO74: 3 | BP74: － | BV74: 2.0041101e+16 | BW74: 住商 一郎 | BX74: 2.0240415e+16 | CZ74: 0 | DA74: 0 | EZ74: 0 | FA74: 東京物産株式会社 | FB74: 0 | FC74: 1 | FD74: 0 | FE74: 0 | FF74: 0 | FH74: 1 | FI74: 1 | FJ74: 当月末締め 翌月末払い | FK74: [締]当月末[払]翌月末 | FL74: 1 | FM74: 1 | FN74: 0 | FR74: 2 | FS74: 0 | FT74: 1000000 | FU74: 0 | FV74: 1 | GA74: S02 | GB74: 振込-ＦＢ | GC74: 1 | GD74: JISHA007 | GE74: 三井住友 銀座 | GK74: 1 | GP74: S07 | GQ74: 支払手形 | GR74: 9 | GS74: JISHA007 | GT74: 三井住友 銀座 | GZ74: 1 | HA74: みずほ | HB74: 3 | HC74: 八重洲口 | HD74: 2 | HE74: 76541 | HF74: 東京物産株式会社 | HG74: ﾄｳｷﾖｳﾌﾞﾂｻﾝ(ｶ | HH74: 1 | HL74: 60 | HM74: 2 | HN74: 31 | HO74: 1 | HP74: ST001 | HQ74: 支払手形（営業） | IM74: 31 | IN74: 1 | IO74: 1 | IP74: 31 | IV74: 1 | IW74: 1 | IX74: 31
A75: 1 | C75: 0 | D75: 初期導入 | E75: 1112 | H75: 10000000000023 | I75: KIGYO0000000012 | J75: 東京物産沖縄 | K75: 0 | L75: 0 | M75: 0 | N75: 0 | O75: 0 | P75: 0 | Q75: 0 | R75: 0 | S75: 東京物産株式会社 | T75: 沖縄支店 | U75: 東京物産沖縄 | V75: ﾄｳｷｮｳﾌﾞｯｻﾝｵｷﾅﾜ | AD75: 900-0002 | AE75: 沖縄県那覇市曙9-1-2 | AH75: 098-111-2222 | AI75: 098-222-1111 | AJ75: 20030401 | AK75: 99991231 | BG75: 0 | BH75: 0 | BI75: 国内 | BJ75: 1 | BK75: 0 | BM75: 2 | BN75: 1 | BO75: 3 | BP75: － | BV75: 2.0041101e+16 | BW75: 住商 一郎 | BX75: 2.0240415e+16 | CZ75: 0 | DA75: 0 | EZ75: 0 | FB75: 0 | FC75: 3 | FD75: 0 | FE75: 0 | FF75: 0
A76: 1 | C76: 0 | D76: 初期導入 | E76: 1113 | H76: 10000000000024 | I76: KIGYO0000000013 | J76: 東京物産不動産 | K76: 0 | L76: 0 | M76: 0 | N76: 0 | O76: 0 | P76: 0 | Q76: 0 | R76: 0 | S76: 東京物産株式会社 | T76: 不動産賃貸部 | U76: 東京物産不動産 | V76: ﾄｳｷｮｳﾌﾞｯｻﾝﾌﾄﾞｳｻﾝ | AJ76: 20030101 | AK76: 99991231 | BG76: 0 | BH76: 0 | BI76: 国内 | BJ76: 1 | BK76: 0 | BM76: 2 | BN76: 1 | BO76: 3 | BP76: － | BV76: 2.0041101e+16 | BW76: 住商 一郎 | BX76: 2.0240415e+16 | CZ76: 0 | DA76: 0 | EZ76: 0 | FB76: 0 | FC76: 3 | FD76: 0 | FE76: 0 | FF76: 0
A77: 1 | C77: 0 | D77: 初期導入 | E77: 1114 | I77: KIGYO0000000015 | J77: 角紅本社 | K77: 0 | L77: 0 | M77: 0 | N77: 0 | O77: 0 | P77: 1 | Q77: 1 | R77: 0 | S77: 株式会社角紅 | U77: 角紅本社 | V77: ｶｸﾍﾞﾆﾎﾝｼｬ | AD77: 100-8699 | AE77: 東京都千代田区大手町10-40-20 | AH77: 03-3333-7777 | AI77: 03-3333-5555 | AJ77: 20030401 | AK77: 99991231 | AM77: 3 | AN77: 部門間取引 | AO77: J | AP77: 卸売・小売業 | AQ77: 491 | AR77: 各種商品卸売業 | BG77: 0 | BH77: 0 | BI77: 国内 | BJ77: 1 | BK77: 1 | BL77: JPY | BM77: 3 | BN77: 1 | BO77: 3 | BP77: － | BV77: 2.0041101e+16 | BX77: 2.006071e+16 | CZ77: 0 | DA77: 0 | EZ77: 0 | FA77: 角紅本社 | FB77: 0 | FC77: 1 | FD77: 0 | FE77: 0 | FF77: 0 | FH77: 1 | FI77: 1 | FJ77: 当月末締翌月末払い | FK77: [締]月末[払]翌月末 | FL77: 1 | FM77: 1 | FN77: 1 | FO77: 100000000 | FP77: 本所 | FR77: 2 | FS77: 0 | FT77: 0 | FU77: 0 | FV77: 1 | GA77: S01 | GB77: 振込-ＦＢ-期日する | GC77: 1 | GD77: JISHA007 | GE77: 三井住友 銀座 | GZ77: 9 | HA77: 三井住友 | HB77: 2 | HC77: 虎ノ門 | HD77: 1 | HE77: 9876543 | HF77: 角紅 | HG77: ｶｸﾍﾞﾆ | HH77: 1 | HR77: 60 | HS77: 1 | HT77: 30 | HU77: 1 | IM77: 99 | IN77: 1 | IO77: 1 | IP77: 99
A78: 1 | C78: 0 | D78: 初期導入 | E78: 1114 | I78: KIGYO0000000015 | J78: 角紅本社 | K78: 0 | L78: 0 | M78: 0 | N78: 0 | O78: 0 | P78: 1 | Q78: 1 | R78: 0 | S78: 株式会社角紅 | U78: 角紅本社 | V78: ｶｸﾍﾞﾆﾎﾝｼｬ | AD78: 100-8699 | AE78: 東京都千代田区大手町10-40-20 | AH78: 03-3333-7777 | AI78: 03-3333-5555 | AJ78: 20030401 | AK78: 99991231 | AM78: 3 | AN78: 部門間取引 | AO78: J | AP78: 卸売・小売業 | AQ78: 491 | AR78: 各種商品卸売業 | BG78: 0 | BH78: 0 | BI78: 国内 | BJ78: 1 | BK78: 1 | BL78: JPY | BM78: 3 | BN78: 1 | BO78: 3 | BP78: － | BV78: 2.0041101e+16 | BX78: 2.006071e+16 | CZ78: 0 | DA78: 0 | EZ78: 0 | FA78: 角紅本社 | FB78: 0 | FC78: 1 | FD78: 0 | FE78: 0 | FF78: 0 | FH78: 2 | FI78: 2 | FJ78: 外貨決済 | FK78: 外貨決済 | FL78: 2 | FM78: 2 | FN78: 0 | FR78: 9 | FS78: 0 | FT78: 0 | FU78: 0 | FV78: 1 | GA78: S10 | GB78: 外為取引 | GC78: 1 | GD78: JISHA003 | GE78: 東京三菱 外貨 | IM78: 0 | IN78: 1 | IO78: 0 | IP78: 20
A79: 1 | C79: 0 | D79: 初期導入 | E79: 1115 | H79: 10000000000026 | I79: KIGYO0000000016 | J79: 角紅大阪 | K79: 0 | L79: 0 | M79: 0 | N79: 0 | O79: 0 | P79: 1 | Q79: 1 | R79: 0 | S79: 株式会社角紅 | U79: 角紅大阪 | V79: ｶｸﾍﾞﾆｵｵｻｶ | AD79: 100-8699 | AE79: 東京都千代田区大手町10-40-20 | AH79: 03-3333-7777 | AI79: 03-3333-5555 | AJ79: 20030401 | AK79: 99991231 | AO79: J | AP79: 卸売・小売業 | AQ79: 491 | AR79: 各種商品卸売業 | BG79: 0 | BH79: 0 | BI79: 国内 | BJ79: 1 | BK79: 0 | BM79: 3 | BN79: 1 | BO79: 3 | BP79: － | BV79: 2.0041101e+16 | BW79: 住商 一郎 | BX79: 2.0240415e+16 | CZ79: 0 | DA79: 0 | EZ79: 0 | FA79: 株式会社角紅 | FB79: 0 | FC79: 1 | FD79: 0 | FE79: 0 | FF79: 0
A80: 1 | C80: 0 | D80: 初期導入 | E80: 1116 | H80: 10000000000025 | I80: KIGYO0000000017 | J80: 角紅神戸 | K80: 0 | L80: 0 | M80: 0 | N80: 0 | O80: 0 | P80: 1 | Q80: 1 | R80: 0 | S80: 株式会社角紅 | U80: 角紅神戸 | V80: ｶｸﾍﾞﾆｺｳﾍﾞ | AD80: 100-8699 | AE80: 東京都千代田区大手町10-40-20 | AH80: 03-3333-7777 | AI80: 03-3333-5555 | AJ80: 20030401 | AK80: 99991231 | AO80: J | AP80: 卸売・小売業 | AQ80: 491 | AR80: 各種商品卸売業 | BG80: 0 | BH80: 0 | BI80: 国内 | BJ80: 1 | BK80: 0 | BM80: 3 | BN80: 1 | BO80: 3 | BP80: － | BV80: 2.0041101e+16 | BW80: 住商 一郎 | BX80: 2.0240415e+16 | CZ80: 0 | DA80: 0 | EZ80: 0 | FB80: 0 | FC80: 1 | FD80: 0 | FE80: 0 | FF80: 0
A81: 1 | C81: 0 | D81: 初期導入 | E81: 1117 | H81: 10000000000027 | I81: KIGYO0000000019 | J81: 葛飾竹田冷機 | K81: 0 | L81: 0 | M81: 0 | N81: 0 | O81: 0 | P81: 1 | Q81: 1 | R81: 0 | S81: 葛飾竹田冷凍機械株式会社 | U81: 葛飾竹田冷機 | V81: ｶﾂｼｶﾀｹﾀﾞﾚｲﾄｳｷｶｲ | AD81: 125-0001 | AE81: 葛飾区立石4-102-16 | AH81: 03-3600-0000 | AI81: 03-3600-9999 | AJ81: 20030401 | AK81: 99991231 | AM81: 1 | AN81: 通常取引 | AO81: J | AP81: 卸売・小売業 | AQ81: 533 | AR81: 電気機械器具卸売業 | BG81: 0 | BH81: 0 | BI81: 国内 | BJ81: 1 | BK81: 1 | BL81: USD | BM81: 3 | BN81: 1 | BO81: 3 | BP81: － | BV81: 2.0041101e+16 | BW81: 住商 一郎 | BX81: 2.0240415e+16 | CZ81: 0 | DA81: 0 | EZ81: 0 | FA81: 葛飾竹田冷凍機械株式会社 | FB81: 0 | FC81: 1 | FD81: 0 | FE81: 0 | FF81: 0 | FH81: 1 | FI81: 1 | FJ81: 外貨決済 | FK81: 外貨決済 | FL81: 2 | FM81: 2 | FN81: 0 | FR81: 9 | FS81: 0 | FT81: 0 | FU81: 0 | FV81: 1 | GA81: S11 | GB81: 外為送金 | GC81: 1 | GD81: JISHA008 | GE81: 三井住友 外貨 | HV81: 1 | HW81: 1 | HX81: 1 | HY81: AAA | IA81: TAKEDAREIKI | IB81: USA | IC81: 1234578 | ID81: BANK OF TOKYO-MITSUBISHI | IE81: NY | IM81: 0 | IN81: 1 | IO81: 0 | IP81: 20
A82: 1 | C82: 0 | D82: 初期導入 | E82: 1117 | H82: 10000000000027 | I82: KIGYO0000000019 | J82: 葛飾竹田冷機 | K82: 0 | L82: 0 | M82: 0 | N82: 0 | O82: 0 | P82: 1 | Q82: 1 | R82: 0 | S82: 葛飾竹田冷凍機械株式会社 | U82: 葛飾竹田冷機 | V82: ｶﾂｼｶﾀｹﾀﾞﾚｲﾄｳｷｶｲ | AD82: 125-0001 | AE82: 葛飾区立石4-102-16 | AH82: 03-3600-0000 | AI82: 03-3600-9999 | AJ82: 20030401 | AK82: 99991231 | AM82: 1 | AN82: 通常取引 | AO82: J | AP82: 卸売・小売業 | AQ82: 533 | AR82: 電気機械器具卸売業 | BG82: 0 | BH82: 0 | BI82: 国内 | BJ82: 1 | BK82: 1 | BL82: USD | BM82: 3 | BN82: 1 | BO82: 3 | BP82: － | BV82: 2.0041101e+16 | BW82: 住商 一郎 | BX82: 2.0240415e+16 | CZ82: 0 | DA82: 0 | EZ82: 0 | FA82: 葛飾竹田冷凍機械株式会社 | FB82: 0 | FC82: 1 | FD82: 0 | FE82: 0 | FF82: 0 | FH82: 2 | FI82: 2 | FJ82: 月末締翌月末支払い | FK82: 月末締翌月末支払い | FL82: 1 | FM82: 1 | FN82: 1 | FR82: 2 | FS82: 0 | FT82: 0 | FU82: 0 | FV82: 1 | GA82: S01 | GB82: 振込-ＦＢ-期日する | GC82: 1 | GZ82: 5 | HA82: 三菱UFJ | HB82: 4 | HC82: 名古屋 | HD82: 1 | HE82: 4234231 | HF82: 葛飾竹田冷機 | HG82: ｶﾂｼｶﾀｹﾀﾞﾚｲｷ | HH82: 1 | HR82: 30 | HS82: 0 | HT82: 30 | HU82: 1 | IM82: 99 | IN82: 1 | IO82: 1 | IP82: 99
A83: 1 | C83: 0 | D83: 初期導入 | E83: 1118 | H83: 10000000000028 | I83: KIGYO0000000020 | J83: 三ツ沢工業製造 | K83: 0 | L83: 0 | M83: 0 | N83: 0 | O83: 0 | P83: 1 | Q83: 0 | R83: 0 | S83: 三ツ沢工業株式会社 | T83: 製造部 | U83: 三ツ沢工業製造 | V83: ﾐﾂｻﾜｺｳｷﾞｮｳ | AD83: 240-8501 | AE83: 横浜市保土ヶ谷区常盤台79-2 | AF83: 三ツ沢第1工場 | AH83: 045-555-6666 | AI83: 045-555-6667 | AJ83: 20030401 | AK83: 99991231 | BG83: 0 | BH83: 0 | BI83: 国内 | BJ83: 1 | BK83: 0 | BM83: 1 | BN83: 1 | BO83: 3 | BP83: － | BV83: 2.0041101e+16 | BW83: 住商 一郎 | BX83: 2.0240415e+16 | CZ83: 0 | DA83: 0 | EZ83: 0 | FB83: 0 | FC83: 3 | FD83: 0 | FE83: 0 | FF83: 0
A84: 1 | C84: 0 | D84: 初期導入 | E84: 1119 | H84: 10000000000029 | I84: KIGYO0000000021 | J84: SapphireElectric | K84: 0 | L84: 0 | M84: 0 | N84: 0 | O84: 0 | P84: 1 | Q84: 1 | R84: 0 | S84: Sapphire Electric Co,Ltd. | U84: SapphireElectric | V84: ｻﾌｧｲｱｴﾚｸﾄﾘｯｸ | AE84: 600 THIRD AVENUE 18F NEW YORK NY 1001 | AJ84: 20030401 | AK84: 99991231 | BG84: 0 | BH84: 1 | BI84: 海外 | BJ84: 0 | BK84: 1 | BL84: USD | BM84: 3 | BN84: 1 | BO84: 3 | BP84: － | BV84: 2.0041101e+16 | BW84: 住商 一郎 | BX84: 2.0240415e+16 | CZ84: 0 | DA84: 0 | EZ84: 0 | FA84: Sapphire Electric Co,Ltd. | FB84: 0 | FC84: 1 | FD84: 0 | FE84: 0 | FF84: 0 | FH84: 1 | FI84: 1 | FJ84: 随時締め 10日後払い | FK84: [締]取引日[払]10日後 | FL84: 2 | FM84: 2 | FN84: 0 | FR84: 9 | FS84: 0 | FT84: 0 | FU84: 0 | FV84: 1 | GA84: S11 | GB84: 外為送金 | GC84: 1 | GD84: JISHA001 | GE84: みずほ 築地 | HV84: 1 | HW84: 2 | HX84: 0 | IA84: SAPPHIRE ELECTRIC INC. | IB84: 600 THIRD AVENUE 18F NEW YORK NY 10016 | IC84: 1234567890-098765432 | ID84: CITY BANK | IE84: NEW YORK | IM84: 0 | IN84: 2 | IQ84: 10
A85: 1 | C85: 0 | D85: 初期導入 | E85: 1119 | H85: 10000000000029 | I85: KIGYO0000000021 | J85: SapphireElectric | K85: 0 | L85: 0 | M85: 0 | N85: 0 | O85: 0 | P85: 1 | Q85: 1 | R85: 0 | S85: Sapphire Electric Co,Ltd. | U85: SapphireElectric | V85: ｻﾌｧｲｱｴﾚｸﾄﾘｯｸ | AE85: 600 THIRD AVENUE 18F NEW YORK NY 1001 | AJ85: 20030401 | AK85: 99991231 | BG85: 0 | BH85: 1 | BI85: 海外 | BJ85: 0 | BK85: 1 | BL85: USD | BM85: 3 | BN85: 1 | BO85: 3 | BP85: － | BV85: 2.0041101e+16 | BW85: 住商 一郎 | BX85: 2.0240415e+16 | CZ85: 0 | DA85: 0 | EZ85: 0 | FA85: Sapphire Electric Co,Ltd. | FB85: 0 | FC85: 1 | FD85: 0 | FE85: 0 | FF85: 0 | FH85: 2 | FI85: 2 | FJ85: 外貨取引（Ｌ／Ｃ付き） | FK85: 外貨取引（Ｌ／Ｃ付） | FL85: 2 | FM85: 2 | FN85: 0 | FR85: 9 | FS85: 0 | FT85: 0 | FU85: 0 | FV85: 1 | GA85: S14 | GB85: 外貨取引（Ｌ／Ｃ付） | GC85: 1 | IM85: 0 | IN85: 1 | IO85: 1 | IP85: 99
A86: 1 | C86: 0 | D86: 初期導入 | E86: 1120 | H86: 10000000000030 | I86: KIGYO0000000022 | J86: SocieteEmeraude | K86: 0 | L86: 0 | M86: 0 | N86: 0 | O86: 0 | P86: 1 | Q86: 1 | R86: 0 | S86: Societe Emeraude Inc. | U86: SocieteEmeraude | V86: ｿｼｴﾃｴﾒﾛｰﾄﾞ | AE86: 70 Avenue de Hambourg 13008 | AF86: Marseille France | AJ86: 20030401 | AK86: 99991231 | BG86: 0 | BH86: 1 | BI86: 海外 | BJ86: 0 | BK86: 1 | BL86: EUR | BM86: 1 | BN86: 1 | BO86: 3 | BP86: － | BV86: 2.0041101e+16 | BW86: 住商 一郎 | BX86: 2.0240415e+16 | CZ86: 0 | DA86: 0 | EZ86: 0 | FA86: Societe Emeraude Inc. | FB86: 0 | FC86: 1 | FD86: 0 | FE86: 0 | FF86: 0 | FH86: 1 | FI86: 1 | FJ86: 随時締め 60日後払い | FK86: [締]取引日[払]60日後 | FL86: 2 | FM86: 2 | FN86: 0 | FR86: 9 | FS86: 0 | FT86: 0 | FU86: 0 | FV86: 1 | GA86: S11 | GB86: 外為送金 | GC86: 1 | GD86: JISHA008 | GE86: 三井住友 外貨 | HV86: 1 | HW86: 1 | HX86: 0 | IA86: SOCIETE EMERAUDE | IB86: 70 AVENUE DE HAMBOURG 13008 MARSEILLE FRANCE | IC86: 1234567890-098765432 | ID86: CITY BANK | IE86: MARSEILLE | IM86: 0 | IN86: 2 | IQ86: 60
A87: 1 | C87: 0 | D87: 初期導入 | E87: 1121 | H87: 123456XXXXX | I87: KIGYO0000000023 | J87: ルビーリース | K87: 0 | L87: 0 | M87: 0 | N87: 0 | O87: 0 | P87: 1 | Q87: 1 | R87: 0 | S87: 株式会社ルビーリース | U87: ルビーリース | V87: ﾙﾋﾞｰﾘｰｽ | AD87: 110-0000 | AE87: 東京都中央区丸の内9-8-7 | AF87: 丸の内ビル8階 | AH87: 03-4444-2222 | AI87: 03-5555-1122 | AJ87: 20030401 | AK87: 99991231 | BG87: 0 | BH87: 0 | BI87: 国内 | BJ87: 1 | BK87: 0 | BM87: 1 | BN87: 1 | BO87: 3 | BP87: － | BV87: 2.0050207e+16 | BW87: 住商 一郎 | BX87: 2.0231214e+16 | CZ87: 0 | DA87: 0 | EZ87: 0 | FA87: 株式会社ルビーリース | FB87: 0 | FC87: 1 | FD87: 0 | FE87: 0 | FF87: 0 | FH87: 1 | FI87: 1 | FJ87: 随時締め 当月20日払い | FK87: [締]取引日[払]当月20 | FL87: 1 | FM87: 2 | FN87: 0 | FR87: 2 | FS87: 0 | FT87: 0 | FU87: 0 | FV87: 1 | GA87: S06 | GB87: 引落 | GC87: 1 | GD87: JISHA007 | GE87: 三井住友 銀座 | IM87: 0 | IN87: 1 | IO87: 0 | IP87: 20
A88: 1 | C88: 0 | D88: 初期導入 | E88: 1121 | H88: 123456XXXXX | I88: KIGYO0000000023 | J88: ルビーリース | K88: 0 | L88: 0 | M88: 0 | N88: 0 | O88: 0 | P88: 1 | Q88: 1 | R88: 0 | S88: 株式会社ルビーリース | U88: ルビーリース | V88: ﾙﾋﾞｰﾘｰｽ | AD88: 110-0000 | AE88: 東京都中央区丸の内9-8-7 | AF88: 丸の内ビル8階 | AH88: 03-4444-2222 | AI88: 03-5555-1122 | AJ88: 20030401 | AK88: 99991231 | BG88: 0 | BH88: 0 | BI88: 国内 | BJ88: 1 | BK88: 0 | BM88: 1 | BN88: 1 | BO88: 3 | BP88: － | BV88: 2.0050207e+16 | BW88: 住商 一郎 | BX88: 2.0231214e+16 | CZ88: 0 | DA88: 0 | EZ88: 0 | FA88: 株式会社ルビーリース | FB88: 0 | FC88: 1 | FD88: 0 | FE88: 0 | FF88: 0 | FH88: 2 | FI88: 2 | FJ88: 随時当末振替翌末払：ファクタリング引落 | FK88: 99振替99支払：Ｆ引落 | FL88: 1 | FM88: 2 | FN88: 0 | FR88: 3 | FS88: 0 | FT88: 0 | FU88: 0 | FV88: 1 | GA88: FC2 | GB88: ﾌｧｸﾀﾘﾝｸﾞ引落(住商Ｆ) | GC88: 1 | HS88: 1 | HT88: 99 | HU88: 1 | IM88: 0 | IN88: 1 | IO88: 1 | IP88: 99
A89: 1 | C89: 0 | D89: 初期導入 | E89: 1122 | I89: KIGYO0000000024 | J89: トリトンIT | K89: 0 | L89: 0 | M89: 0 | N89: 0 | O89: 0 | P89: 1 | Q89: 0 | R89: 0 | S89: 株式会社トリトンインフォーメーションテクノロジー | T89: 総務部 | U89: トリトンIT | V89: ﾄﾘﾄﾝｲﾝﾌｫｰﾒｰｼｮﾝﾃｸﾉﾛｼﾞｰ | AD89: 104-6241 | AE89: 東京都中央区晴海1-8-12 | AF89: 晴海トリトンスクエアオフィスタワーZ | AH89: 03-5166-1001 | AI89: 03-5166-2001 | AJ89: 20030401 | AK89: 99991231 | AM89: 1 | AN89: 通常取引 | BG89: 0 | BH89: 0 | BI89: 国内 | BJ89: 1 | BK89: 0 | BL89: JPY | BM89: 3 | BN89: 1 | BO89: 3 | BP89: － | BV89: 2.0050207e+16 | BX89: 2.006071e+16 | CZ89: 0 | DA89: 0 | EZ89: 0 | FB89: 0 | FC89: 3 | FD89: 0 | FE89: 0 | FF89: 0
A90: 1 | C90: 0 | D90: 初期導入 | E90: 1123 | I90: KIGYO0000000025 | J90: トリトン販売 | K90: 0 | L90: 0 | M90: 0 | N90: 0 | O90: 0 | P90: 1 | Q90: 0 | R90: 0 | S90: トリトンテクノロジー販売株式会社 | T90: 首都圏営業本部 首都圏営業第1課 | U90: トリトン販売 | V90: ﾄﾘﾄﾝﾃｸﾉﾛｼﾞｰﾊﾝﾊﾞｲ | AD90: 104-0054 | AE90: 東京都中央区勝どき3-13-1 | AF90: FOREFRONT TOWER2 | AH90: 03-5548-7260 | AI90: 03-5548-7262 | AJ90: 20030401 | AK90: 99991231 | AM90: 1 | AN90: 通常取引 | BG90: 0 | BH90: 0 | BI90: 国内 | BJ90: 1 | BK90: 0 | BL90: JPY | BM90: 3 | BN90: 1 | BO90: 3 | BP90: － | BV90: 2.0050207e+16 | BX90: 2.006071e+16 | CZ90: 0 | DA90: 0 | EZ90: 0 | FB90: 0 | FC90: 3 | FD90: 0 | FE90: 0 | FF90: 0
A91: 1 | C91: 0 | D91: 初期導入 | E91: 1124 | I91: KIGYO0000000026 | J91: トリトン総研 | K91: 0 | L91: 0 | M91: 0 | N91: 0 | O91: 0 | P91: 0 | Q91: 1 | R91: 0 | S91: 株式会社トリトン総合研究所 | T91: 業務コンサルティンググループ | U91: トリトン総研 | V91: ﾄﾘﾄﾝｿｳｺﾞｳｹﾝｼｭｳｼｮ | AD91: 104-6241 | AE91: 東京都中央区晴海1-8-12 | AF91: 晴海トリトンスクエア | AH91: 03-5166-9999 | AI91: 03-5166-8888 | AJ91: 20030401 | AK91: 99991231 | BG91: 0 | BH91: 0 | BI91: 国内 | BJ91: 1 | BK91: 0 | BM91: 2 | BN91: 1 | BO91: 3 | BP91: － | BV91: 2.0050207e+16 | BW91: ＳＣＳＫ 一郎 | BX91: 2.0100118e+16 | CZ91: 0 | DA91: 0 | EZ91: 0 | FA91: 株式会社トリトン総合研究所 | FB91: 0 | FC91: 1 | FD91: 0 | FE91: 0 | FF91: 0 | FH91: 1 | FI91: 1 | FJ91: 随時締め 翌月末払い | FK91: [締]取引日[払]翌月末 | FL91: 1 | FM91: 2 | FN91: 0 | FR91: 2 | FS91: 0 | FT91: 0 | FU91: 0 | FV91: 1 | GA91: S02 | GB91: 振込-ＦＢ | GC91: 1 | GD91: JISHA007 | GE91: 三井住友 銀座 | GZ91: 290 | HA91: ＵＦＪ信託 | HB91: 3 | HC91: 月島 | HD91: 2 | HE91: 1112345 | HF91: 株式会社トリトンコンサルティング | HG91: ﾄﾘﾄﾝｺﾝｻﾙﾃｲﾝｸﾞ | HH91: 0 | IM91: 0 | IN91: 1 | IO91: 1 | IP91: 31
A92: 1 | C92: 0 | D92: 初期導入 | E92: 1125 | I92: KIGYO0000000029 | J92: トリトン関西 | K92: 0 | L92: 0 | M92: 0 | N92: 0 | O92: 0 | P92: 1 | Q92: 0 | R92: 0 | S92: 株式会社トリトンテクノロジー販売関西 | T92: 営業本部 第一営業課 | U92: トリトン関西 | V92: ﾄﾘﾄﾝﾃｸﾉﾛｼﾞｰﾊﾝﾊﾞｲｶﾝｻｲ | AD92: 530-8822 | AE92: 大阪府大阪市北区中之島2-2-2 | AH92: 06-7777-2222 | AI92: 06-5555-1111 | AJ92: 20030401 | AK92: 99991231 | BG92: 0 | BH92: 0 | BI92: 国内 | BJ92: 1 | BK92: 0 | BL92: JPY | BM92: 2 | BN92: 1 | BO92: 3 | BP92: － | BV92: 2.0050207e+16 | BX92: 2.006071e+16 | CZ92: 0 | DA92: 0 | EZ92: 0 | FB92: 0 | FC92: 3 | FD92: 0 | FE92: 0 | FF92: 0
A93: 1 | C93: 0 | D93: 初期導入 | E93: 1126 | I93: KIGYO0000000027 | J93: ロジスティクス | K93: 0 | L93: 0 | M93: 0 | N93: 0 | O93: 0 | P93: 1 | Q93: 1 | R93: 0 | S93: トリトンロジスティクス株式会社 | U93: ロジスティクス | V93: ﾄﾘﾄﾝﾛｼﾞｽﾃｨｸｽ | AD93: 150-0000 | AE93: 東京都港区汐留9-8-8 | AH93: 03-1111-1111 | AI93: 03-2222-2222 | AJ93: 20030401 | AK93: 99991231 | BG93: 0 | BH93: 0 | BI93: 国内 | BJ93: 1 | BK93: 0 | BL93: JPY | BM93: 3 | BN93: 1 | BO93: 3 | BP93: － | BV93: 2.0050207e+16 | BX93: 2.006071e+16 | CZ93: 0 | DA93: 0 | EZ93: 0 | FA93: トリトンロジスティクス株式会社 | FB93: 0 | FC93: 1 | FD93: 0 | FE93: 0 | FF93: 0 | FH93: 1 | FI93: 1 | FJ93: 当月末締め 翌月末払い | FK93: [締]当月末[払]翌月末 | FL93: 1 | FM93: 1 | FN93: 0 | FR93: 2 | FS93: 0 | FT93: 0 | FU93: 0 | FV93: 1 | GA93: S02 | GB93: 振込-ＦＢ | GC93: 1 | GD93: JISHA007 | GE93: 三井住友 銀座 | GZ93: 10 | HA93: りそな | HB93: 3 | HC93: 赤坂 | HD93: 1 | HE93: 1111224 | HF93: トリトンロジスティクス株式会社 | HG93: ﾄﾘﾄﾝﾛｼﾞｽﾃｲｸｽ | HH93: 1 | IM93: 31 | IN93: 1 | IO93: 1 | IP93: 31
A94: 1 | C94: 0 | D94: 初期導入 | E94: 1127 | I94: KIGYO0000000028 | J94: 京橋税務署 | K94: 0 | L94: 0 | M94: 0 | N94: 0 | O94: 0 | P94: 0 | Q94: 1 | R94: 0 | S94: 京橋税務署 | U94: 京橋税務署 | V94: ｷｮｳﾊﾞｼｾﾞｲﾑｼｮ | AD94: 104-8557 | AE94: 東京都中央区新富町2丁目6番1号 | AH94: 03-3552-1151 | AJ94: 20030401 | AK94: 99991231 | BG94: 0 | BH94: 0 | BI94: 国内 | BJ94: 1 | BK94: 0 | BL94: JPY | BM94: 1 | BN94: 1 | BO94: 3 | BP94: － | BV94: 2.0050207e+16 | BX94: 2.006071e+16 | CZ94: 0 | DA94: 0 | EZ94: 0 | FA94: 京橋税務署 | FB94: 0 | FC94: 1 | FD94: 0 | FE94: 0 | FF94: 0 | FH94: 1 | FI94: 1 | FJ94: 当月末締め 翌月10日払い | FK94: [締]当月末[払]翌月10 | FL94: 1 | FM94: 1 | FN94: 0 | FR94: 2 | FS94: 0 | FT94: 0 | FU94: 0 | FV94: 1 | GA94: S09 | GB94: 現金 | GC94: 1 | IM94: 31 | IN94: 1 | IO94: 1 | IP94: 10
A95: 1 | C95: 0 | D95: 初期導入 | E95: 1128 | I95: KIGYO0000000030 | J95: ＮＤＤ東日本 | K95: 0 | L95: 0 | M95: 0 | N95: 0 | O95: 0 | P95: 0 | Q95: 1 | R95: 0 | S95: ＮＤＤ東日本株式会社 | U95: ＮＤＤ東日本 | V95: ｴﾇﾃﾞｨﾃﾞｨﾋｶﾞｼﾆﾎﾝ | AD95: 180-0021 | AE95: 東京都江戸川区飯田橋１丁目１０番１０号 | AF95: サニータワー | AH95: 03-3600-1234 | AI95: 03-3600-1235 | AJ95: 20040401 | AM95: 1 | AN95: 通常取引 | AO95: H | AP95: 情報通信業 | BG95: 0 | BH95: 0 | BI95: 国内 | BJ95: 1 | BK95: 0 | BL95: JPY | BM95: 3 | BN95: 1 | BO95: 3 | BP95: － | BU95: 新井 五郎 | BV95: 2.0050329e+16 | BX95: 2.006071e+16 | CZ95: 0 | DA95: 0 | EZ95: 0 | FA95: ＮＤＤ東日本 | FB95: 0 | FC95: 1 | FD95: 0 | FE95: 0 | FF95: 1 | FH95: 1 | FI95: 1 | FJ95: 月末締め翌月２０日支払 | FK95: 月末締翌２０日支払 | FL95: 1 | FM95: 1 | FN95: 1 | FO95: 100000000 | FP95: 本所 | FR95: 1 | FS95: 0 | FT95: 0 | FU95: 0 | FV95: 1 | GA95: S01 | GB95: 振込-ＦＢ-期日する | GC95: 1 | GZ95: 9 | HA95: 三井住友 | HB95: 3 | HC95: 丸の内 | HD95: 2 | HE95: 301060 | HF95: ＮＤＤ東日本 | HG95: ｴﾇﾃﾞｲﾃﾞｲﾋｶﾞｼﾆﾎﾝ | HH95: 0 | HR95: 60 | HS95: 3 | HT95: 20 | HU95: 1 | IM95: 99 | IN95: 1 | IO95: 1 | IP95: 20
A96: 1 | C96: 0 | D96: 初期導入 | E96: 1129 | K96: 0 | L96: 0 | M96: 0 | N96: 0 | O96: 0 | P96: 0 | Q96: 1 | R96: 0 | S96: 通電株式会社 | U96: 通電 | V96: ﾂｳﾃﾞﾝｶﾌﾞｼｷｶｲｼｬ | AM96: 1 | AN96: 通常取引 | AO96: Q | AP96: サービス業(その他) | AQ96: 891 | AR96: 広告代理業 | BG96: 0 | BH96: 0 | BI96: 国内 | BJ96: 1 | BK96: 0 | BL96: JPY | BM96: 3 | BN96: 1 | BO96: 3 | BP96: － | BU96: 新井 五郎 | BV96: 2.0050329e+16 | BX96: 2.006071e+16 | CZ96: 0 | DA96: 0 | EZ96: 0 | FA96: 通電株式会社 | FB96: 0 | FC96: 1 | FD96: 0 | FE96: 0 | FF96: 1 | FH96: 1 | FI96: 1 | FJ96: 当月末締め 翌月10日払い | FK96: [締]当月末[払]翌月10 | FL96: 1 | FM96: 1 | FN96: 0 | FR96: 2 | FS96: 0 | FT96: 0 | FU96: 0 | FV96: 1 | GA96: S02 | GB96: 振込-ＦＢ | GC96: 1 | GZ96: 1 | HA96: みずほ | HB96: 1 | HC96: 丸の内 | HD96: 1 | HE96: 1111222 | HF96: 通電 | HG96: ﾂｳﾃﾞﾝ | HH96: 0 | IM96: 31 | IN96: 1 | IO96: 1 | IP96: 10
A97: 1 | C97: 0 | D97: 初期導入 | E97: 1130 | K97: 0 | L97: 0 | M97: 0 | N97: 0 | O97: 0 | P97: 1 | Q97: 1 | R97: 0 | S97: 浪速リース | U97: 浪速リース | V97: ﾅﾆﾜﾘｰｽ | BG97: 0 | BH97: 0 | BI97: 国内 | BJ97: 1 | BK97: 0 | BL97: JPY | BM97: 3 | BN97: 1 | BO97: 3 | BP97: － | BU97: ＳＣＳＫ 一郎 | BV97: 2.0050526e+16 | BW97: ＳＣＳＫ 一郎 | BX97: 2.0061227e+16 | CZ97: 0 | DA97: 0 | EZ97: 0 | FA97: 浪速リース（株）本社営業部 | FB97: 0 | FC97: 1 | FD97: 0 | FE97: 0 | FF97: 0
A98: 1 | C98: 0 | D98: 初期導入 | E98: 114522002 | K98: 0 | L98: 0 | M98: 0 | N98: 0 | O98: 0 | P98: 0 | Q98: 1 | R98: 0 | S98: セイカン（株）帯広 | U98: セイカン（株）帯広 | V98: ｾｲｶﾝ | BG98: 0 | BH98: 0 | BI98: 国内 | BJ98: 1 | BK98: 0 | BM98: 3 | BN98: 1 | BO98: 3 | BP98: － | BU98: 住商 一郎 | BV98: 2.0240702e+16 | BW98: 住商 一郎 | BX98: 2.0240702e+16 | CZ98: 0 | DA98: 0 | EZ98: 0 | FB98: 0 | FC98: 1 | FD98: 1 | FE98: 1 | FF98: 0 | FG98: 送付後、1カ月以内にご連絡がない場合は内容を確認済みとさせていただきます。 | FH98: 1 | FI98: 100 | FJ98: 随時支払 FB振込 | FK98: 随時支払 FB振込 | FL98: 1 | FM98: 2 | FN98: 0 | FR98: 3 | FS98: 0 | FT98: 0 | FU98: 0 | FV98: 1 | GA98: S02 | GB98: 振込-ＦＢ | GC98: 1 | GZ98: 501 | HA98: 北洋銀行 | HB98: 486 | HC98: 厚別中央支店 | HD98: 2 | HE98: 2000662 | HF98: セイカン（株）帯広 | HG98: ｾｲｶﾝ | HH98: 0 | IM98: 0 | IN98: 2 | IQ98: 10
A99: 1 | C99: 0 | D99: 初期導入 | E99: 1200 | I99: KIGY00000000028 | J99: 青森工業機械 | K99: 0 | L99: 0 | M99: 0 | N99: 0 | O99: 0 | P99: 1 | Q99: 1 | R99: 0 | S99: 青森工業機械株式会社 | U99: 青森工業機械 | V99: ｱｵﾓﾘｺｳｷﾞｮｳｷｶｲ | AD99: 113-0033 | AE99: 東京都文京区本郷3丁目3-1 | AF99: 本郷ビル | AH99: 03-3666-2330 | AI99: 03-3666-2390 | AJ99: 20050101 | AM99: 1 | AN99: 通常取引 | AO99: F | AP99: 製造業 | AQ99: 84 | AR99: 機械器具設備工事業 | BG99: 0 | BH99: 0 | BI99: 国内 | BJ99: 1 | BK99: 0 | BL99: JPY | BM99: 3 | BN99: 1 | BO99: 3 | BP99: － | BU99: ＳＣＳＫ 一郎 | BV99: 2.0050512e+16 | BX99: 2.006071e+16 | CZ99: 0 | DA99: 0 | EZ99: 0 | FA99: 青森工業機械 | FB99: 0 | FC99: 1 | FD99: 0 | FE99: 0 | FF99: 0 | FH99: 1 | FI99: 1 | FJ99: 定時支払決済（通常） | FK99: 定時支払決済（通常） | FL99: 1 | FM99: 1 | FN99: 1 | FO99: 100000000 | FP99: 本所 | FR99: 2 | FS99: 0 | FT99: 500000 | FU99: 0 | FV99: 1 | GA99: S02 | GB99: 振込-ＦＢ | GC99: 3 | GD99: JISHA001 | GE99: みずほ 築地 | GK99: 2 | GL99: 50 | GM99: 3 | GN99: 2 | GP99: S07 | GQ99: 支払手形 | GR99: 9 | GS99: JISHA001 | GT99: みずほ 築地 | GU99: S01 | GV99: 振込-ＦＢ-期日する | GW99: 3 | GX99: JISHA001 | GY99: みずほ 築地 | GZ99: 1 | HA99: みずほ | HB99: 4 | HC99: 栄町 | HD99: 1 | HE99: 5236668 | HF99: 青森工業機械 | HG99: ｱｵﾓﾘｺｳｷﾞﾖｳｷｶｲ | HH99: 0 | HL99: 120 | HM99: 4 | HN99: 99 | HO99: 1 | HP99: ST001 | HQ99: 支払手形（営業） | HR99: 120 | HS99: 4 | HT99: 99 | HU99: 1 | IM99: 5 | IN99: 1 | IO99: 1 | IP99: 5 | IV99: 1 | IW99: 1 | IX99: 5 | IZ99: 1 | JA99: 1 | JB99: 5
A100: 1 | C100: 0 | D100: 初期導入 | E100: 1200 | I100: KIGY00000000028 | J100: 青森工業機械 | K100: 0 | L100: 0 | M100: 0 | N100: 0 | O100: 0 | P100: 1 | Q100: 1 | R100: 0 | S100: 青森工業機械株式会社 | U100: 青森工業機械 | V100: ｱｵﾓﾘｺｳｷﾞｮｳｷｶｲ | AD100: 113-0033 | AE100: 東京都文京区本郷3丁目3-1 | AF100: 本郷ビル | AH100: 03-3666-2330 | AI100: 03-3666-2390 | AJ100: 20050101 | AM100: 1 | AN100: 通常取引 | AO100: F | AP100: 製造業 | AQ100: 84 | AR100: 機械器具設備工事業 | BG100: 0 | BH100: 0 | BI100: 国内 | BJ100: 1 | BK100: 0 | BL100: JPY | BM100: 3 | BN100: 1 | BO100: 3 | BP100: － | BU100: ＳＣＳＫ 一郎 | BV100: 2.0050512e+16 | BX100: 2.006071e+16 | CZ100: 0 | DA100: 0 | EZ100: 0 | FA100: 青森工業機械 | FB100: 0 | FC100: 1 | FD100: 0 | FE100: 0 | FF100: 0 | FH100: 1 | FI100: 1 | FJ100: 定時支払決済（通常） | FK100: 定時支払決済（通常） | FL100: 1 | FM100: 1 | FN100: 1 | FO100: 100000000 | FP100: 本所 | FR100: 2 | FS100: 0 | FT100: 500000 | FU100: 0 | FV100: 1 | GA100: S02 | GB100: 振込-ＦＢ | GC100: 3 | GD100: JISHA001 | GE100: みずほ 築地 | GK100: 2 | GL100: 50 | GM100: 3 | GN100: 2 | GP100: S07 | GQ100: 支払手形 | GR100: 9 | GS100: JISHA001 | GT100: みずほ 築地 | GU100: S01 | GV100: 振込-ＦＢ-期日する | GW100: 3 | GX100: JISHA001 | GY100: みずほ 築地 | GZ100: 1 | HA100: みずほ | HB100: 4 | HC100: 栄町 | HD100: 1 | HE100: 5236668 | HF100: 青森工業機械 | HG100: ｱｵﾓﾘｺｳｷﾞﾖｳｷｶｲ | HH100: 0 | HL100: 120 | HM100: 4 | HN100: 99 | HO100: 1 | HP100: ST001 | HQ100: 支払手形（営業） | HR100: 120 | HS100: 4 | HT100: 99 | HU100: 1 | IM100: 10 | IN100: 1 | IO100: 1 | IP100: 10 | IV100: 1 | IW100: 1 | IX100: 10 | IZ100: 1 | JA100: 1 | JB100: 10
...

Sheet ⇒

Sheet データアクセス要領
A1: ドキュメント名 | L1: サブシステム | Q1: 業務機能名 | AJ1: 作成者 | AO1: =表紙!D51 -> SCSK位田 | AT1: 更新者
A2: 業務機能概要書 | G2: データアクセス要領 | L2: =業務機能概要!L2 -> 業務共通 | Q2: =業務機能概要!Q2 -> 取引先マスタ自動取込 | AJ2: 作成日付 | AO2: =表紙!C51 -> 45898 | AT2: 更新日付
A4: 【編集要領】
B6: データ更新要領は、標準の「取引先マスタ外部データ取込」の実行時と同様。

Sheet 補足1 取込結果判定
A1: ドキュメント名 | L1: サブシステム | Q1: 業務機能名 | AM1: 作成者 | AR1: =表紙!D51 -> SCSK位田 | AW1: 更新者
A2: 業務機能概要書 | G2: 補足説明 | L2: =業務機能概要!L2 -> 業務共通 | Q2: =業務機能概要!Q2 -> 取引先マスタ自動取込 | AM2: 作成日付 | AR2: =表紙!C51 -> 45898 | AW2: 更新日付
B4: 取引先マスタ取込結果の判定
C6: ProActiveC4の取引先マスタ取込では、取込した結果、業務的なエラー（マスタの存在チェックエラーなど）があった場合、
C7: 「バッチジョブ状況一覧」での「進行状況」は「正常終了」となる。
C8: 「取込コンソール」での「取込ステータス」は「取込完了、エラー有」となる。 | Y8: ※下画面参照
C10: 当プロジェクトでは、取引先マスタ取込はタスクスケジューラ（Hinemos）から起動され、処理結果を返却する必要があるが、
C11: 「取込ステータス」が「取込完了、エラー有」の場合は、「エラー」として結果を返却する。

Sheet 補足2 出金口座の導出
A1: ドキュメント名 | L1: サブシステム | Q1: 業務機能名 | AM1: 作成者 | AR1: =表紙!D51 -> SCSK位田 | AW1: 更新者
A2: 業務機能概要書 | G2: 補足説明 | L2: =業務機能概要!L2 -> 業務共通 | Q2: =業務機能概要!Q2 -> 取引先マスタ自動取込 | AM2: 作成日付 | AR2: =表紙!C51 -> 45898 | AW2: 更新日付
C6: ≪ProActiveC4の機能性≫
D8: ProActiveC4債務管理では、支払先の振込先口座に応じて、
D9: 振込手数料を最適化（節約）した出金口座を自動で判定することが
D10: 可能である。
D13: ※必要な設定
D14: ① | E14: 「債務システム設定」にて「振込元自社口座の自動判定を行う」
E15: にチェックを付加する。 ※ProActiveC4導入時の初期設定
D17: ② | E17: 「金融機関マスタ」にて、グループ金融機関の登録を実施する。
D19: ③ | E19: 「部門別口座マスタ」にて出納部門で使用する出金口座を登録する。
D42: ◆ | E42: ProActiveC4の出金口座の設定例
F44: 例 | H44: 出金口座として、みずほ銀行、三井住友銀行、三菱UFJ銀行の口座を保持しており、
H45: 振込先によって以下のように出金口座を判定する。
H47: ＜振込先＞ | M47: ＜出金口座＞
H48: みずほ銀行 | L48: → | M48: みずほ銀行
H49: 三井住友銀行 | L49: → | M49: 三井住友銀行
H50: 三菱UFJ銀行 | L50: → | M50: 三井住友銀行
H51: その他 | L51: → | M51: みずほ銀行
F55: 設定手順
G57: 1. | H57: 「金融機関マスタ」のグループ金融機関情報タブにて、三菱UFJ銀行を三井住友銀行のグループ金融機関とし登録する。
G59: 2. | H59: 「部門別口座マスタ」にて出納部門で使用する出金口座を登録する。

Sheet 補足3 スクラッチから連動する決済条件
P1: HOKUREN INTERNAL USE ONLY
A2: 検 討 シ ー ト
A3: システム名 | D3: 新会計システム | I3: 様式№ | M3: 作成日 | O3: 2025/8/29 | R3: ＰＡＧＥ
B6: 支払決済条件コードは、以下の方針で作成する。
B7: 001～020：振込以外の支払方法の場合に採番、 | F7: → 振込、締後振込以外の支払方法×出金口座の種類の分だけ固定的に登録する
B8: 021～999：決済条件マスタに登録されている振込払の場合に採番
B10: PA支払決済条件コード | C10: 相手先コード(9桁) | D10: 決済条件コード | E10: 支払方法区分 | F10: 出金口座
B11: 001 | C11: 相手先コードA | D11: NULL | E11: 外国送金 | F11: 三菱UFJ札幌支店
B12: 002 | C12: 相手先コードA | D12: NULL | E12: 外国送金 | F12: 三菱UFJ中央支店
B13: 003 | C13: 相手先コードA | D13: NULL | E13: 自動引落し | F13: 信連
B14: 004 | C14: 相手先コードA | D14: NULL | E14: 自動引落し | F14: 道銀
B15: 005 | C15: 相手先コードA | D15: NULL | E15: 電債（一括決済）
B16: 006 | C16: 相手先コードA | D16: NULL | E16: 納付書払 | F16: 信連
B17: 007 | C17: 相手先コードA | D17: NULL | E17: 納付書払 | F17: 道銀
B18: 008 | C18: 相手先コードA | D18: NULL | E18: 現金 | F18: －
B19: 009 | C19: 相手先コードA | D19: NULL | E19: 振替 | F19: －
B20: ・・・
B21: 021 | C21: 相手先コードA | D21: 000000000001 | E21: 振込 | F21: NULL
B22: 022 | C22: 相手先コードA | D22: 000000000002 | E22: 振込 | F22: NULL
B23: 023 | C23: 相手先コードA | D23: 000000000003 | E23: 振込 | F23: NULL
B24: ～
B25: 001 | C25: 職員A | D25: NULL | E25: 外国送金 | F25: 三菱UFJ札幌支店
B26: 002 | C26: 職員A | D26: NULL | E26: 外国送金 | F26: 三菱UFJ中央支店
B27: 003 | C27: 職員A | D27: NULL | E27: 自動引落し | F27: 信連
B28: 004 | C28: 職員A | D28: NULL | E28: 自動引落し | F28: 道銀
B29: 005 | C29: 職員A | D29: NULL | E29: 電債（一括決済）
B30: 006 | C30: 職員A | D30: NULL | E30: 納付書払 | F30: 信連
B31: 007 | C31: 職員A | D31: NULL | E31: 納付書払 | F31: 道銀
B32: 008 | C32: 職員A | D32: NULL | E32: 現金 | F32: －
B33: 009 | C33: 職員A | D33: NULL | E33: 振替 | F33: －
B34: ・・・
B35: 021 | C35: 職員A | D35: 000000000001 | E35: 振込 | F35: NULL
B36: ～
B37: 001 | C37: 諸口 | D37: NULL | E37: 外国送金 | F37: 三菱UFJ札幌支店
B38: 002 | C38: 諸口 | D38: NULL | E38: 外国送金 | F38: 三菱UFJ中央支店
B39: 003 | C39: 諸口 | D39: NULL | E39: 自動引落し | F39: 信連
B40: 004 | C40: 諸口 | D40: NULL | E40: 自動引落し | F40: 道銀
B41: 005 | C41: 諸口 | D41: NULL | E41: 電債（一括決済）
B42: 006 | C42: 諸口 | D42: NULL | E42: 納付書払 | F42: 信連
B43: 007 | C43: 諸口 | D43: NULL | E43: 納付書払 | F43: 道銀
B44: 008 | C44: 諸口 | D44: NULL | E44: 現金 | F44: －
B45: 009 | C45: 諸口 | D45: NULL | E45: 振替 | F45: －
B46: ・・・
B47: 021 | C47: 諸口 | D47: 000000000001 | E47: 振込 | F47: NULL
B50: 001 | C50: 35260001 (ホクレン職員給与口) | D50: NULL | E50: 振込(FBなし) | F50: 信連

Sheet 補足4 マスタ情報の有効開始日
A1: Ｐｈａｓｅ 要件定義局面 | U1: HOKUREN INTERNAL USE ONLY
A2: 検 討 シ ー ト
A3: システム名 | D3: 新会計システム | N3: 様式№ | R3: 作成日 | T3: 2024/12/27 | W3: ＰＡＧＥ
B6: １．目的
C8: スクラッチ開発機能のマスタ管理とProActiveのマスタ管理の機能性の違いを明確にして、
C9: マスタデータ連動時の留意点を整理する。
B12: ２．機能性の違いと留意点
C14: スクラッチのマスタでは「有効開始日」という考え方がある。一方、ProActiveのマスタではそのような考え方はなく、「使用可／不可」のみ管理される。
C15: このため、スクラッチのマスタで「有効開始日」以前に登録された変更は、変更日の夜間処理でスクラッチからProActiveに連動してはいけない。
C17: この点について、マスタ情報の新規登録／情報変更／情報変更（取引終了）の3ケースに分けて整理する。
C19: 例① 新規登録
C20: 有効開始日が6/13となる新取引先情報を6/10にマスタ登録した場合、ProActiveへの連動は6/12の夜間に実施する（6/10の夜間に連動してはいけない）
C22: 例② 情報変更
C23: 支払先の振込口座情報が6/13から変更となり、その変更を6/10に実施した場合、ProActiveへの変更情報の連動は6/12の夜間に
C24: 実施する（6/10の夜間に連動してはいけない）
C26: 例③ 情報変更（取引終了）
C27: 支払先との取引契約が6/13までとなり、その変更を6/10に実施した場合、ProActiveへの変更情報の連動は該当支払先への支払処理が
C28: 終了まで実施してはいけない。
C32: 「例① 新規登録」について、
D33: このケースでは、6/10時点でマスタ情報は追加されているが、その日の夜間処理で連動してはいけない。
D34: データ連動の機能（スクラッチ側）にて、連動対象データを抽出する際に、データの追加、更新日次だけでなく、
D35: 「有効開始日」を考慮する必要がある。
D36: もしも、追加した日の夜間処理で連動した場合、「有効開始日」以前に該当支払先の情報を使用可能となるが、
D37: ProActiveではデータ登録はほとんどしないため、業務上大きな影響はないと考えられる。 | O37: 「スクラッチ連動機能」にて注意
C40: 「例② 情報変更」について、
D41: このケースも、6/10時点でマスタ情報は追加されているが、その日の夜間処理で連動してはいけない。
D42: 例①と同様、連動対象データ抽出時に「有効開始日」を考慮する必要がある。 | O42: 「スクラッチ連動機能」にて注意
D44: 当ケースの場合はマスタ変更のタイミングと、取引伝票の登録のタイミングによっては運用上の注意点が発生する。 | O44: 「業務運用」にて注意 ※未来日付での起票がなければ問題なし
D46: 6/10 | G46: 6/11 | J46: 6/12 | M46: 6/13
D48: スクラッチマスタ更新 | G48: 6/13以降の支払伝票 | J48: 夜間処理で、 | M48: 6/13付の支払伝票
D49: （振込先口座変更） | G49: を起票（支払伝票①） | J49: ProActiveへマスタ連動 | M49: を起票（支払伝票②）
D50: ※6/13 から適用 | G50: ※本来はB口座が振込先
D52: ↓ | G52: ↓ | J52: ↓ | M52: ↓
G53: ProActiveへ支払データ連動 | M53: ProActiveへ支払データ連動
G54: 振込先はA口座としてデータ作成 | M54: 振込先はB口座としてデータ作成
G55: される | M55: される
G56: ※支払データ連動時には
G57: 直接、振込先口座情報を
G58: 連動するわけではないため | M58: ★ 6/12以前に起票された
M59: 6/13付の支払伝票（支払伝票①）については、
G60: ★未来日付での支払伝票起票時に | M60: ProActive側の支払予定修正にて
G61: 正しい振込先口座情報を付加できない | M61: 振込先口座情報を変更する必要がある。
D63: （スクラッチマスタ） | J63: （スクラッチマスタ）
D64: 6/13以前 | E64: A口座 | J64: 6/13以前 | K64: A口座
D65: 6/13以降 | E65: B口座 | J65: 6/13以降 | K65: B口座
D67: （ProActiveマスタ） | J67: （ProActiveマスタ）
D68: 振込先： | E68: A口座 | J68: 振込先： | K68: B口座
C72: 例③ 情報変更（取引終了）について、
D73: このケースでは、ProActiveで支払決済確定処理等が実施終了まで、ProActive上の取引先マスタ情報を使用不可にしてはいけない。
D74: スクラッチ側でProActiveでの未払情報をチェックした上で、使用不可とする情報を連動する仕組みを実装するのは難しいため、
D75: 取引契約終了した取引先情報はProActive上では使用可の状態のままとすることでよいと考えられる。 | O75: 「スクラッチ連動機能」にて注意
D76: ProActiveでは、取引先情報を使用した伝票登録はほとんどしないため、業務上大きな影響はないと考えられる。
