Workbook
Name 【債権】最新データ辞書: #REF!
Name oo: #REF!
Name 一般仕訳登録可否区分: #REF!
Name 科目タイプ: #REF!
Name 科目特性区分: #REF!
Name 科目分類: #REF!
Name 項科目摘要要否区分: #REF!
Name 項目辞書: #REF!
Name 項目辞書: #REF!
Name 債権債務対象区分: #REF!
Name 仕訳入力区分: #REF!
Name 所属: #REF!
Name 所属管理区分: #REF!
Name 消費税取引区分要否区分: #REF!
Name 節科目摘要要否区分: #REF!
Name 相手先要否区分: #REF!
Name 品目要否区分: #REF!
Name 目管理: #REF!

Sheet 表紙
F46: ProActive
B48: 変更履歴
B50: 項番 | C50: 変更発生日 | D50: 変更者 | E50: 変更箇所 | F50: 変更内容
B51: 1 | C51: 45898 | D51: SCSK位田 | F51: 新規作成
B52: 2
B53: 3
B54: 4
B55: 5
B56: 6
B57: 7
B58: 8
B59: 9
B60: 10
B61: 11
B62: 12
B63: 13
... B80: 30

Sheet 業務機能概要
A1: ドキュメント名 | L1: サブシステム | Q1: 業務機能名 | AJ1: 作成者 | AO1: =表紙!D51 -> SCSK位田 | AT1: 更新者
A2: 業務機能概要書 | G2: 業務機能概要 | L2: 業務共通 | Q2: 勘定科目・会計摘要マスタ自動取込 | AJ2: 作成日付 | AO2: =表紙!C51 -> 45898 | AT2: 更新日付
B4: 【目的・役割】
C5: ・ | D5: ホクレン様のシステムでは、伝票入力は部門システムやスクラッチ開発する機能で実施し、また、マスタ情報の管理も共通マスタや会計マスタのマスタ管理システムで実施する。
D6: このため、ProActiveC4では、仕訳、支払などの業務データや組織、勘定科目、取引先などのマスタ情報を外部のシステムから取込む必要がある。
D7: マスタデータは夜間処理にて、スクラッチ開発するマスタ（ProActiveC4外のシステム）の情報と同期をとる必要がある。
B10: 【利用者】
C11: ・ | D11: バッチ実行
B14: 【利用頻度】
C15: ・ | D15: 日次夜間（勘定科目マスタが変更、追加された場合のみ）
B18: 【対象要件定義書】
C19: ・ | D19: 要件定義書(他システムとのデータ連動)
B22: 【処理概要】
C23: １) | D23: ファイルによってデータ連動される勘定科目、会計摘要マスタの情報をProActiveC4標準の「勘定科目・補助科目取込」の処理を使用してProActiveC4に取込む。
D24: バッチファイルで定義された取込ディレクトリに配置されている連動データ（取込用のCSVファイル）の情報を取得する。
D25: ※ | E25: 会計摘要マスタの情報は、ProActiveC4の補助科目マスタに取込む
D26: ※ | E26: 勘定科目・補助科目取込では、取込項目のタイトルの行も必要となる
D27: ※ | E27: 勘定科目、補助科目はそれぞれ別の連動データとして別ファイルで作成される想定
F28: 勘定科目取込ファイル | O28: ： | P28: KANJOU_YYYYMMDDHHMMSSmmm.csv
F29: 会計摘要取込ファイル | O29: ： | P29: TEKIYOU_YYYYMMDDHHMMSSmmm.csv
C32: ２) | D32: 1)で取込データが取得できた場合は、登録済のマスタデータを全件削除する。（ただし、款科目より上位の統括科目は連動対象外のため、削除対象外とする）
D33: ※ | E33: 勘定科目情報、補助科目情報は常に最新情報を全件連動する想定とする
D34: ※ | E34: 勘定科目情報、補助科目情報の削除については、バッチファイルからSQLを実行して実現する
C37: ３) | D37: 1)で取得した取込ファイルをINPUTとして、勘定科目・補助科目取込をバッチ実行する。（オンライン機能「勘定科目・補助科目取込/出力」の取込動作を踏襲する。）
D38: ※ | E38: 標準の勘定科目・補助科目取込はオンライン処理可能なままとする
D40: 3-1. | F40: 勘定科目マスタ自動取込バッチ
F41: 標準機能の勘定科目・補助科目取込をバッチダイレクトで実行する。（※取込区分を「勘定科目・勘定科目属性」として実行する）
D43: 3-2. | F43: 会計摘要マスタ自動取込バッチ
F44: 標準機能の勘定科目・補助科目取込をバッチダイレクトで実行する。（※取込区分を「補助科目」として実行する）
C50: ４) | D50: バッチ実行される勘定科目・補助科目取込は、ProActiveC4外のタスク管理用のミドルウェア（以下、タスクスケジューラ）から実行する想定とする。
D51: 正常終了、対象データがない場合は、「異常なし」のステータスをタスクスケジューラに返却する。
D52: エラー終了の場合は、「エラーあり」のステータスをタスクスケジューラに返却する。
D54: [実行情報]
D55: No | F55: パラメータ | O55: 内容
D56: 1 | F56: ※イベント概要参照
D58: [終了情報]
D59: 戻り値 | F59: 内容 | O59: 内容
D60: 0 | F60: 正常終了
D61: 1 | F61: 異常終了 | O61: 業務エラー/システムエラー発生時
B64: 【共通要件】
D65: 共通要件内容 | J65: 対応内容（標準準拠の場合、記載省略）
D66: セキュリティ | J66: 部門制限、本人制限の機能性は実装しない。
D67: 承認WF | J67: 対応なし。承認WFの利用は不可とする。 | V67: ※標準の勘定科目、補助科目マスタ登録は承認WFは使用できない
D68: 組織変更 | J68: 対応なし。当機能は仕訳に関係しないため、組織変更を考慮しない。
B71: 【前提・制約事項】
C72: １) | D72: ProActiveC4の各データの取込機能では、固定の取込フォーマットがあるため、該当するフォーマットに合わせて連動データが作成される前提とする。
D73: （データ作成は、連動元システムまたは、連動処理（ProActiveC4外）で実施する）
D74: ※ | E74: 勘定科目・補助科目取込では、取込項目のタイトルの行も必要となる
C76: ２) | D76: ProActiveC4に連動されるデータ（CSVファイル）は、ProActiveC4のバッチサーバから参照可能な場所に配置されることを前提とする。
C78: ３) | D78: データ取込をバッチ実行した情報は、ProActiveC4標準の「バッチジョブ」として扱われ、「バッチジョブ状況一覧」機能で状況の確認が可能となる。
D79: 状況の確認は上記機能で実施する方針として、個別にエラーログ出力等の機能性は開発しない。
C81: ４) | D81: ProActiveC4標準の勘定科目・補助科目取込処理を改修せずバッチ実行する。
D82: 以下のようなケースでは、標準の取込処理にも改修が必要となるため、別途対応工数を見積もることとする。
E83: ① | F83: 禁止文字の置き換え、エスケープ文字の考慮が取込処理側で必要となる（文字を置き換えした上で取込処理が必要となる）
C86: 5) | D86: データ連動対象は、勘定科目マスタ、補助科目マスタのみとし、勘定科目情報を使用して設定する統括科目マスタ、帳票構成マスタ、科目グループマスタ、
D87: 勘定科目セキュリティ（各ユーザで使用可能な科目を制限する設定）、取引種類マスタ、自動仕訳初期値設定などの関連するマスタは手動でメンテナンスする運用ルールとする。
C89: ６) | D89: 勘定科目、会計摘要マスタ（ProActiveC4では補助科目）のデータは常に最新情報を全件連動する想定とする。
D90: このため、自動取込処理の前に既存データを一旦削除する。（ただし、款科目より上位の統括科目は連動対象外のため、削除対象外とする）
D91: ※ | E91: 「勘定科目マスタ履歴出力」機能でデータ出力した場合、全件削除の履歴情報が出力されるが、当機能は特に使用しないため業務上支障はない
C96: ７) | D96: 以下のProActiveC4禁止文字は連動ファイルにて使用しない前提とする。
E98: 禁止文字 | J98: 名称
E99: ― | J99: ダッシュ（全角）
E100: ∥ | J100: 双柱
E101: ￤ | J101: 破断線
C103: ８) | D103: ProActiveC4へ連動するファイルはコマンドにて移動等の操作を実施するため、ファイル名には空白を使用しない前提とする。
B106: 【主な取り扱い情報】
C107: ①バッチ実行時
D108: № | E108: 取り扱う情報 | O108: I/O | Q108: 用途
D109: 1 | E109: 勘定科目 | O109: OUT | Q109: 勘定科目情報を登録する。
D110: 2 | E110: 勘定科目属性 | O110: OUT | Q110: 勘定科目属性情報を登録する。
D111: 3 | E111: Ｃ／Ｆ勘定科目設定 | O111: OUT | Q111: 勘定科目コードとCF勘定科目コードの紐づけを登録する。
D112: 4 | E112: 勘定科目履歴 | O112: OUT | Q112: 勘定科目の変更履歴を登録する。
D113: 5 | E113: 補助科目 | O113: OUT | Q113: 補助科目情報を登録する。
D114: 6 | E114: バッチジョブ | O114: OUT | Q114: バッチ実行結果を反映する。
D115: 7 | E115: バッチジョブエラー | O115: OUT | Q115: バッチ実行結果を反映する。

Sheet 画面遷移図
A1: ドキュメント名 | L1: サブシステム | Q1: 業務機能名 | AJ1: 作成者 | AO1: =表紙!D51 -> SCSK位田 | AT1: 更新者 | AY1: SCSK相坂
A2: 業務機能概要書 | G2: 画面遷移図 | L2: =業務機能概要!L2 -> 業務共通 | Q2: =業務機能概要!Q2 -> 勘定科目・会計摘要マスタ自動取込 | AJ2: 作成日付 | AO2: =表紙!C51 -> 45898 | AT2: 更新日付 | AY2: 44103
B4: 【メニュー起動時の画面遷移】

Sheet 画面レイアウト
A1: ドキュメント名 | AH1: サブシステム | AX1: 業務機能名 | DF1: 作成者 | DV1: =表紙!D51 -> SCSK位田 | EL1: 更新者
A2: 業務機能概要書 | R2: 画面レイアウト | AH2: =業務機能概要!L2 -> 業務共通 | AX2: =業務機能概要!Q2 -> 勘定科目・会計摘要マスタ自動取込 | DF2: 作成日付 | DV2: =表紙!C51 -> 45898 | EL2: 更新日付
A3: 画面名 | FD3: 画面№ | FM3: ①
B4: 0 | H4: 40 | R4: 110 | AB4: 180 | AL4: 250 | AV4: 320 | BF4: 390 | BP4: 460 | BZ4: 530 | CJ4: 600 | CT4: 670 | DD4: 740 | DN4: 810 | DX4: 880 | EH4: 950 | EO4: 999 | ER4: ＜補足説明＞
A5: 0
A6: 5
A7: 20
A8: 35
A9: 50
A10: 65
A11: 80
A12: 95
A13: 110
A14: 125
A15: 140
A16: 155
... A47: 620
A57: 画面名 | J57: 自動消込確定情報登録画面 | FD57: 画面№ | FM57: ②
B58: 0 | H58: 40 | R58: 110 | AB58: 180 | AL58: 250 | AV58: 320 | BF58: 390 | BP58: 460 | BZ58: 530 | CJ58: 600 | CT58: 670 | DD58: 740 | DN58: 810 | DX58: 880 | EH58: 950 | EO58: 999 | ER58: ＜補足説明＞
A59: 0
A60: 5
A61: 20
A62: 35
A63: 50
A64: 65
A65: 80
A66: 95
A67: 110
A68: 125
A69: 140
A70: 155
... A101: 620
A111: 画面名 | FD111: 画面№ | FM111: ①
B112: 0 | H112: 40 | R112: 110 | AB112: 180 | AL112: 250 | AV112: 320 | BF112: 390 | BP112: 460 | BZ112: 530 | CJ112: 600 | CT112: 670 | DD112: 740 | DN112: 810 | DX112: 880 | EH112: 950 | EO112: 999 | ER112: ＜補足説明＞
A113: 0
A114: 5
A115: 20
A116: 35
A117: 50
A118: 65
A119: 80
A120: 95
A121: 110
A122: 125
A123: 140
A124: 155
... A155: 620
A165: 画面名 | FD165: 画面№ | FM165: ①
B166: 0 | H166: 40 | R166: 110 | AB166: 180 | AL166: 250 | AV166: 320 | BF166: 390 | BP166: 460 | BZ166: 530 | CJ166: 600 | CT166: 670 | DD166: 740 | DN166: 810 | DX166: 880 | EH166: 950 | EO166: 999 | ER166: ＜補足説明＞
A167: 0
A168: 5
A169: 20
A170: 35
A171: 50
A172: 65
A173: 80
A174: 95
A175: 110
A176: 125
A177: 140
A178: 155
... A209: 620
C221: 出力されるCSVファイル例

Sheet 項目概要
A1: ドキュメント名 | L1: サブシステム | Q1: 業務機能名 | AJ1: 作成者 | AO1: =表紙!D51 -> SCSK位田 | AT1: 更新者 | BE1: ○ | BF1: IN | BG1: 文字列
A2: 業務機能概要書 | G2: 項目概要 | L2: =業務機能概要!L2 -> 業務共通 | Q2: =業務機能概要!Q2 -> 勘定科目・会計摘要マスタ自動取込 | AJ2: 作成日付 | AO2: =表紙!C51 -> 45898 | AT2: 更新日付 | BE2: － | BF2: OUT | BG2: 数値
BF3: IN/OUT | BG3: 半英数
A4: 【画面項目説明】 | BG4: 半カナ
BG5: コード
B6: [①自動消込確定情報登録画面] | AQ6: ※追加及び変更項目のみ記載 | BG6: 日付
B7: № | C7: ラベル | J7: 項目名 | Q7: I/O | S7: 必須 | U7: 型 | W7: 桁数 | Y7: ソート | AA7: 初期表示 | AE7: 備考 | BG7: －
B8: 【ヘッダ部】
B9: 1 | C9: 一覧を最大化 | J9: 一覧を最大化ボタン | Q9: IN | S9: － | U9: － | W9: － | Y9: ー | AA9: ー
B10: 2 | Q10: IN | S10: ○ | U10: 日付 | W10: 8 | Y10: ー | AA10: システム日付
B11: 3 | Q11: OUT | S11: － | U11: コード | W11: 12 | Y11: ー | AA11: ー
B12: 4 | Q12: IN | S12: ○ | U12: コード | W12: 10 | Y12: ー | AA12: ー
Q13: IN | S13: － | U13: － | W13: ー | Y13: ー | AA13: ー
Q14: OUT | S14: － | U14: 文字列 | W14: 20 | Y14: ー | AA14: ー
B15: 5 | Q15: IN | S15: ○ | U15: コード | W15: 15 | Y15: ー | AA15: ー
Q16: IN | S16: － | U16: － | W16: ー | Y16: ー | AA16: ー
Q17: OUT | S17: － | U17: 文字列 | W17: 20 | Y17: ー | AA17: ー
B18: 6 | Q18: IN | S18: ○ | U18: － | W18: ー | Y18: ー
B20: 7 | Q20: IN | S20: ○ | U20: 数値 | W20: 13 | Y20: ー | AA20: ー
B21: 【】
B22: 1
B25: 2
B28: 3
B30: 4
B31: 5
B32: 【】 | AE32: ※ソート順は画面レイアウトシートの補足説明欄参照。
B33: 1
B34: 2
B35: 2
B36: 3
B37: 2
B38: 3
B39: 4
B40: 5
B41: 6
B42: 7
B43: 8
B44: 9
... B52: 16
B53: 【フッタ部】
B54: 1
B55: 2
B57: 3
B58: 4
B59: 5
B60: 6
B61: 7
B62: 8
B63: 9
B64: 10

Sheet イベント概要
A1: ドキュメント名 | L1: サブシステム | Q1: 業務機能名 | AJ1: 作成者 | AO1: =表紙!D51 -> SCSK位田 | AT1: 更新者
A2: 業務機能概要書 | G2: イベント概要 | L2: =業務機能概要!L2 -> 業務共通 | Q2: =業務機能概要!Q2 -> 勘定科目・会計摘要マスタ自動取込 | AJ2: 作成日付 | AO2: =表紙!C51 -> 45898 | AT2: 更新日付
A4: 【画面イベント処理】
EV5: 注１）初期表示は全ての
B6: № | C6: イベント名 | J6: 処理説明 | EV6: データを処理対象とする
B7: =IF(C7="","",MAX(B$6:B6)+1) -> 1 | C7: 勘定科目マスタ自動取込バッチイベント | J7: 1. | K7: バッチファイルで定義されたディレクトリに配置された取込用のCSVファイルをINPUTとし、
B8: =IF(C8="","",MAX(B$6:B7)+1) | K8: ProActiveC4標準機能の勘定科目・補助科目取込を実行する。（※取込区分は「勘定科目」として実行する）
B9: =IF(C9="","",MAX(B$6:B8)+1) | K9: ＜パラメータ＞
B10: =IF(C10="","",MAX(B$6:B9)+1) | K10: ・ | L10: 会社コード | T10: ： | U10: バッチ実行用のxmlで指定された会社コード
B11: =IF(C11="","",MAX(B$6:B10)+1) | K11: ・ | L11: 取込CSVファイル | T11: ： | U11: バッチファイルのパラメータにて指定されたファイル
B12: =IF(C12="","",MAX(B$6:B10)+1)
B13: =IF(C13="","",MAX(B$6:B11)+1) | K13: 取込用のCSVファイルが取得できなかった場合は、処理を中断する。バッチ実行結果はエラーとする。
B14: =IF(C14="","",MAX(B$6:B13)+1) | K14: 取得できた場合は、後続の処理を継続する。
B15: =IF(C15="","",MAX(B$6:B14)+1) | K15: ※ | L15: 上記のファイル取得、エラーハンドリングはバッチファイルで実施する（アプリケーションでの考慮は不要）
B16: =IF(C16="","",MAX(B$6:B15)+1) | K16: ※ | L16: 取込用CSVのファイルサイズが0byteの場合は、正常として処理終了する。（バッチファイルにてファイルを正常処理フォルダへ移動する）
B18: =IF(C18="","",MAX(B$6:B16)+1)
B19: =IF(C19="","",MAX(B$6:B18)+1) | K19: 取込用のCSVファイルが取得できた場合、登録済の勘定科目マスタのデータを全件削除する。
B20: =IF(C20="","",MAX(B$6:B19)+1) | K20: ※ | L20: 削除用のSQLは別途作成してバッチファイルで実行する（アプリケーションでの考慮は不要）
B21: =IF(C21="","",MAX(B$6:B20)+1)
B22: =IF(C22="","",MAX(B$6:B21)+1) | J22: ２．実行結果をバッチジョブ情報に反映する。
B23: =IF(C23="","",MAX(B$6:B22)+1) | M23: 標準仕様に準じる
B24: =IF(C24="","",MAX(B$6:B23)+1)
B25: =IF(C25="","",MAX(B$6:B24)+1) | M25: ※ | N25: ProActiveC4標準の勘定科目・補助科目取込の仕様では、
B26: =IF(C26="","",MAX(B$6:B25)+1) | N26: 取込ファイルに取込項目のタイトル行しか存在しない場合はエラーとなるが、今回のデータ連動では
B27: =IF(C27="","",MAX(B$6:B26)+1) | N27: 連動対象データがない場合（連動ファイルが0byte）は、バッチファイルで処理終了のハンドリングを実施するため、
B28: =IF(C28="","",MAX(B$6:B27)+1) | N28: 取込処理は実行されない。
B29: =IF(C29="","",MAX(B$6:B28)+1)
B30: =IF(C30="","",MAX(B$6:B29)+1)
B31: =IF(C31="","",MAX(B$6:B30)+1) | J31: ３．バッチ実行結果の終了情報を返却する。
B32: =IF(C32="","",MAX(B$6:B31)+1) | K32: ■ | L32: 正常終了できた場合
B33: =IF(C33="","",MAX(B$6:B32)+1) | M33: 「0:正常終了」
B34: =IF(C34="","",MAX(B$6:B33)+1) | K34: ■ | L34: エラーが発生した場合（※ProActiveC4標準機能のデータ取込でエラーが発生した場合は当ケースに該当する）
B35: =IF(C35="","",MAX(B$6:B34)+1) | M35: 「1:異常終了」
B36: =IF(C36="","",MAX(B$6:B35)+1)
B37: =IF(C37="","",MAX(B$6:B36)+1) | J37: ４．取込処理後、取込用のCSVファイルは処理済用ファイルのディレクトリに移動する
B38: =IF(C38="","",MAX(B$6:B37)+1) | K38: ※ | L38: アプリケーションではなくバッチファイルでファイル移動する
B39: =IF(C39="","",MAX(B$6:B38)+1) | K39: ※ | L39: 正常用、エラー用のディレクトリを作成して処理結果によって移動先ディレクトリを分岐させる
B42: =IF(C42="","",MAX(B$6:B39)+1)
B43: =IF(C43="","",MAX(B$6:B42)+1)
B44: =IF(C44="","",MAX(B$6:B43)+1)
B45: =IF(C45="","",MAX(B$6:B44)+1)
B46: =IF(C46="","",MAX(B$6:B45)+1)
B47: =IF(C47="","",MAX(B$6:B46)+1)
B48: =IF(C48="","",MAX(B$6:B47)+1)
B49: =IF(C49="","",MAX(B$6:B48)+1) -> 2 | C49: 補助科目マスタ自動取込バッチイベント | J49: 1. | K49: バッチファイルで定義されたディレクトリに配置された取込用のCSVファイルをINPUTとし、
B50: =IF(C50="","",MAX(B$6:B49)+1) | K50: ProActiveC4標準機能の勘定科目・補助科目取込を実行する。（※取込区分は「補助科目」として実行する）
B51: =IF(C51="","",MAX(B$6:B50)+1) | K51: ＜パラメータ＞
B52: =IF(C52="","",MAX(B$6:B51)+1) | K52: ・ | L52: 会社コード | T52: ： | U52: バッチ実行用のxmlで指定された会社コード
B53: =IF(C53="","",MAX(B$6:B52)+1) | K53: ・ | L53: 取込CSVファイル | T53: ： | U53: バッチファイルのパラメータにて指定されたファイル
B54: =IF(C54="","",MAX(B$6:B52)+1)
B55: =IF(C55="","",MAX(B$6:B53)+1) | K55: 取込用のCSVファイルが取得できなかった場合は、処理を中断する。バッチ実行結果はエラーとする。
B56: =IF(C56="","",MAX(B$6:B55)+1) | K56: 取得できた場合は、後続の処理を継続する。
B57: =IF(C57="","",MAX(B$6:B56)+1) | K57: ※ | L57: 上記のファイル取得、エラーハンドリングはバッチファイルで実施する（アプリケーションでの考慮は不要）
B58: =IF(C58="","",MAX(B$6:B57)+1) | K58: ※ | L58: 取込用CSVのファイルサイズが0byteの場合は、正常として処理終了する。（バッチファイルにてファイルを正常処理フォルダへ移動する）
B60: =IF(C60="","",MAX(B$6:B58)+1) | K60: 取込用のCSVファイルが取得できた場合、登録済の補助科目マスタのデータを全件削除する。
B61: =IF(C61="","",MAX(B$6:B60)+1) | K61: ※ | L61: 削除用のSQLは別途作成してバッチファイルで実行する（アプリケーションでの考慮は不要）
B62: =IF(C62="","",MAX(B$6:B61)+1)
B63: =IF(C63="","",MAX(B$6:B62)+1) | J63: ２．実行結果をバッチジョブ情報に反映する。
B64: =IF(C64="","",MAX(B$6:B63)+1) | M64: 標準仕様に準じる
B65: =IF(C65="","",MAX(B$6:B64)+1)
B66: =IF(C66="","",MAX(B$6:B65)+1) | M66: ※ | N66: ProActiveC4標準の勘定科目・補助科目取込の仕様では、
B67: =IF(C67="","",MAX(B$6:B66)+1) | N67: 取込ファイルに取込項目のタイトル行しか存在しない場合はエラーとなるが、今回のデータ連動では
B68: =IF(C68="","",MAX(B$6:B67)+1) | N68: 連動対象データがない場合（連動ファイルが0byte）は、バッチファイルで処理終了のハンドリングを実施するため、
B69: =IF(C69="","",MAX(B$6:B68)+1) | N69: 取込処理は実行されない。
B70: =IF(C70="","",MAX(B$6:B69)+1)
B71: =IF(C71="","",MAX(B$6:B70)+1)
B72: =IF(C72="","",MAX(B$6:B71)+1) | J72: ３．バッチ実行結果の終了情報を返却する。
B73: =IF(C73="","",MAX(B$6:B72)+1) | K73: ■ | L73: 正常終了できた場合
B74: =IF(C74="","",MAX(B$6:B73)+1) | M74: 「0:正常終了」
B75: =IF(C75="","",MAX(B$6:B74)+1) | K75: ■ | L75: エラーが発生した場合（※ProActiveC4標準機能のデータ取込でエラーが発生した場合は当ケースに該当する）
B76: =IF(C76="","",MAX(B$6:B75)+1) | M76: 「1:異常終了」
B77: =IF(C77="","",MAX(B$6:B76)+1)
B78: =IF(C78="","",MAX(B$6:B77)+1) | J78: ４．取込処理後、取込用のCSVファイルは処理済用ファイルのディレクトリに移動する
B79: =IF(C79="","",MAX(B$6:B78)+1) | K79: ※ | L79: アプリケーションではなくバッチファイルでファイル移動する
B80: =IF(C80="","",MAX(B$6:B79)+1) | K80: ※ | L80: 正常用、エラー用のディレクトリを作成して処理結果によって移動先ディレクトリを分岐させる
B81: =IF(C81="","",MAX(B$6:B80)+1)
B83: =IF(C83="","",MAX(B$6:B81)+1)
B84: =IF(C84="","",MAX(B$6:B83)+1)
B85: =IF(C85="","",MAX(B$6:B84)+1)

Sheet チェック仕様
A1: ドキュメント名 | L1: サブシステム | Q1: 業務機能名 | AJ1: 作成者 | AO1: =表紙!D51 -> SCSK位田 | AT1: 更新者
A2: 業務機能概要書 | G2: チェック仕様 | L2: =業務機能概要!L2 -> 業務共通 | Q2: =業務機能概要!Q2 -> 勘定科目・会計摘要マスタ自動取込 | AJ2: 作成日付 | AO2: =表紙!C51 -> 45898 | AT2: 更新日付
A4: 【チェック処理】
B6: １．初期処理時
B7: № | C7: 項目名 | L7: 条件必須 | O7: 存在 | R7: 範囲 | U7: 関連 | X7: その他 | AA7: 内容
B8: =IF(C8="","",MAX(B7:B$7)+1) -> 1 | C8: － | X8: ○
B9: =IF(C9="","",MAX(B$7:B8)+1)
B10: =IF(C10="","",MAX(B$7:B9)+1)
B11: =IF(C11="","",MAX(B$7:B10)+1)
B13: ２．検索ボタン押下時
B14: № | C14: 項目名 | L14: 条件必須 | O14: 存在 | R14: 範囲 | U14: 関連 | X14: その他 | AA14: 内容
B15: =IF(C15="","",MAX(B$14:B14)+1)
B16: =IF(C16="","",MAX(B$14:B15)+1)
B17: =IF(C17="","",MAX(B$14:B16)+1)
B18: =IF(C18="","",MAX(B$14:B17)+1)
B19: =IF(C19="","",MAX(B$14:B18)+1)
B20: =IF(C20="","",MAX(B$14:B19)+1)
B21: =IF(C21="","",MAX(B$14:B20)+1)
B22: =IF(C22="","",MAX(B$14:B21)+1)
B23: =IF(C23="","",MAX(B$14:B22)+1)
B24: =IF(C24="","",MAX(B$14:B23)+1)
B25: =IF(C25="","",MAX(B$14:B24)+1)
B26: =IF(C26="","",MAX(B$14:B25)+1)
... B31: =IF(C31="","",MAX(B$14:B30)+1)
B33: ３．データ取込ボタン
B34: № | C34: 項目名 | L34: 条件必須 | O34: 存在 | R34: 範囲 | U34: 関連 | X34: その他 | AA34: 内容
B35: =IF(C35="","",MAX(B$34:B34)+1)
B36: =IF(C36="","",MAX(B$34:B35)+1)
B37: =IF(C37="","",MAX(B$34:B36)+1)
B38: =IF(C38="","",MAX(B$34:B37)+1)
B39: =IF(C39="","",MAX(B$34:B38)+1)
B40: =IF(C40="","",MAX(B$34:B39)+1)
B41: =IF(C41="","",MAX(B$34:B40)+1)
B42: =IF(C42="","",MAX(B$34:B41)+1)
B43: =IF(C43="","",MAX(B$34:B42)+1)
B44: =IF(C44="","",MAX(B$34:B40)+1)
B45: =IF(C45="","",MAX(B$34:B44)+1)
B46: =IF(C46="","",MAX(B$34:B45)+1)
B47: 4
B48: =IF(C48="","",MAX(B$34:B47)+1)
B49: 4
B50: =IF(C50="","",MAX(B$34:B49)+1)
B51: =IF(C51="","",MAX(B48:B$60)+1)
B52: =IF(C52="","",MAX(B46:B$60)+1)
B53: =IF(C53="","",MAX(B47:B$60)+1)
B54: =IF(C54="","",MAX(B48:B$60)+1)
B55: =IF(C55="","",MAX(B51:B$60)+1)
B56: =IF(C56="","",MAX(B$7:B51)+1)
B57: =IF(C57="","",MAX(B$34:B48)+1)
B59: ４．登録ボタン
B60: № | C60: 項目名 | L60: 条件必須 | O60: 存在 | R60: 範囲 | U60: 関連 | X60: その他 | AA60: 内容
B62: =IF(C62="","",MAX(B$60:B61)+1)
B63: =IF(C63="","",MAX(B$60:B62)+1)
B64: =IF(C64="","",MAX(B$60:B63)+1)
B65: =IF(C65="","",MAX(B$60:B64)+1)
B66: =IF(C66="","",MAX(B$60:B65)+1)
B67: =IF(C67="","",MAX(B$60:B66)+1)
B68: =IF(C68="","",MAX(B$60:B67)+1)
B69: =IF(C69="","",MAX(B$60:B68)+1)
B70: =IF(C70="","",MAX(B$60:B69)+1)
B71: =IF(C71="","",MAX(B$60:B70)+1)
B72: =IF(C72="","",MAX(B$60:B71)+1)
B73: =IF(C73="","",MAX(B$60:B72)+1)
... B92: =IF(C92="","",MAX(B$60:B91)+1)

Sheet 出力CSV定義
A1: ドキュメント名 | E1: サブシステム | G1: 業務機能名 | P1: 作成者 | R1: =表紙!D51 -> SCSK位田 | T1: 更新者
A2: 業務機能概要書 | C2: 出力CSV定義 | E2: =業務機能概要!L2 -> 業務共通 | G2: =業務機能概要!Q2 -> 勘定科目・会計摘要マスタ自動取込 | P2: 作成日 | R2: =表紙!C51 -> 45898 | T2: 更新日
A4: データ名 | I4: ヘッダ行 | K4: あり | M4: なし | N4: ダブルクォーテーション | Q4: あり | S4: なし | X4: 文字列
A5: ﾌｧｲﾙ形式・ﾚｺｰﾄﾞ長 | D5: 固定長（ | G5: Byte） | I5: 可変長（区切り文字［ ，(カンマ) ］） | M5: バイナリデータ | P5: その他（ ） | X5: 半英数
A6: 文字コード | D6: UNI（Win系） | F6: EBCDIC(K) | I6: その他（UTF-8） | M6: 改行コード | O6: LF(UNIX系) | Q6: CRLF(Win系) | T6: なし | X6: 半カナ
A7: 全角(2byte)文字項目 | D7: あり | F7: なし | M7: 数値編集 | O7: 左詰め | Q7: 右詰め［ゼロ埋め］ | T7: 右詰め［スペース埋め］ | X7: コード
A8: 特記事項 | C8: 出力順：起票日付、仕訳伝票番号、仕訳自動作成フラグ、仕訳伝票行番号 | J8: ※「"」が含まれる項目は「""」に変換する。 | X8: 数値
A9: No. | B9: 項目名 | E9: 必須 | F9: 型 | G9: 桁数 | H9: 開始位置 | I9: 備考 | X9: 日付
H10: /列 | X10: 時間
A11: 1 | F11: 日付 | G11: 8 | H11: A | X11: 年月
A12: 2 | F12: 半英数 | G12: 12 | H12: B | X12: 区分
A13: 3 | F13: コード | G13: 10 | H13: C | X13: フラグ
A14: 4 | F14: 文字列 | G14: 40 | H14: D | X14: -
A15: 5
A16: 6
A17: 7
A18: 8
A19: 9
A20: 10
A21: 11
A22: 12
A23: 13
A24: 14
A25: 15

Sheet 出力CSVサンプル

Sheet 取込フォーマット定義（勘定科目）
A1: ドキュメント名 | E1: サブシステム | G1: 業務機能名 | P1: 作成者 | R1: SCSK位田 | T1: 更新者
A2: 業務機能概要書 | C2: 取込フォーマット定義 | E2: 業務共通 | G2: 勘定科目・会計摘要マスタ自動取込 | P2: 作成日 | R2: =表紙!C51 -> 45898 | T2: 更新日
A4: データ名 | C4: 勘定科目マスタ自動取込 | I4: ヘッダ行 | K4: あり | M4: なし | N4: ダブルクォーテーション | Q4: あり | S4: なし | X4: 文字列
A5: ﾌｧｲﾙ形式・ﾚｺｰﾄﾞ長 | D5: 固定長（ | G5: Byte） | I5: 可変長（区切り文字［ ，(カンマ) ］） | M5: バイナリデータ | P5: その他（ ） | X5: 半英数
A6: 文字コード | D6: UNI（Win系） | F6: EBCDIC(K) | I6: その他（ UTF-8） | M6: 改行コード | O6: LF(UNIX系) | Q6: CRLF(Win系) | T6: なし | X6: 半カナ
A7: 全角(2byte)文字項目 | D7: あり | F7: なし | M7: 数値編集 | O7: 左詰め | Q7: 右詰め［ゼロ埋め］ | T7: 右詰め［スペース埋め］ | X7: コード
A8: 特記事項 | C8: 取込ファイルには、取込項目のタイトル行が必要となる | X8: 数値
A9: No. | B9: 項目名 | E9: 必須 | F9: 型 | G9: 桁数 | H9: 開始位置 | I9: 項目説明 | O9: 設定値 | X9: 日付
H10: /列 | X10: 時間
A11: =MAX($A$10:$A10)+1 -> 1 | B11: 編集区分 | E11: 〇 | F11: 区分 | G11: 1 | H11: =SUBSTITUTE(SUBSTITUTE(ADDRESS(1,A11),"$1",""),"$","") -> A | I11: 「1:新規」 固定 | K11: ※全件連動の前提 | O11: １（固定値） | X11: 年月
A12: =MAX($A$10:$A11)+1 -> 2 | B12: 勘定科目コード | E12: 〇 | F12: コード | G12: 8 | H12: =SUBSTITUTE(SUBSTITUTE(ADDRESS(1,A12),"$1",""),"$","") -> B | O12: 勘定科目マスタ.勘定科目コード + 目節科目マスタ.目節科目コード | X12: 区分
A13: =MAX($A$10:$A12)+1 -> 3 | B13: 勘定科目名 | E13: 〇 | F13: 文字列 | G13: 30 | H13: =SUBSTITUTE(SUBSTITUTE(ADDRESS(1,A13),"$1",""),"$","") -> C | O13: PA連動用名称 ※新規追加項目 | AB13: 桁数たりない？ 要相談
A14: =MAX($A$10:$A13)+1 -> 4 | B14: 勘定科目名（カナ） | E14: 〇 | F14: 文字列 | G14: 60 | H14: =SUBSTITUTE(SUBSTITUTE(ADDRESS(1,A14),"$1",""),"$","") -> D | O14: PA連動用カナ名称 ※新規追加項目 | AB14: 要ユーザヒアリング
A15: =MAX($A$10:$A14)+1 -> 5 | B15: 勘定科目名（略） | E15: 〇 | F15: 文字列 | G15: 20 | H15: =SUBSTITUTE(SUBSTITUTE(ADDRESS(1,A15),"$1",""),"$","") -> E | O15: PA連動用略称 ※新規追加項目 | AB15: 要ユーザヒアリング
A16: =MAX($A$10:$A15)+1 -> 6 | B16: B／S・P／L | E16: 〇 | F16: 文字列 | G16: 1 | H16: =SUBSTITUTE(SUBSTITUTE(ADDRESS(1,A16),"$1",""),"$","") -> F | I16: 1:B／S科目、2:P／L科目 | O16: 勘定科目マスタ.科目タイプから導出（資産・負債・純資産・費用・収益）
O17: 資産・負債・純資産⇒１、費用・収益→2
A18: =MAX($A$10:$A16)+1 -> 7 | B18: B／S・P／L名 | F18: 文字列 | G18: 30 | H18: =SUBSTITUTE(SUBSTITUTE(ADDRESS(1,A18),"$1",""),"$","") -> G | I18: 空白（設定不要） | O18: 設定なし
A19: =MAX($A$10:$A18)+1 -> 8 | B19: 属性 | E19: 〇 | F19: 文字列 | G19: 1 | H19: =SUBSTITUTE(SUBSTITUTE(ADDRESS(1,A19),"$1",""),"$","") -> H | I19: 1:資産、2:負債、3:純資産、4:収益、5:費用、6:利益 | O19: 勘定科目マスタ.科目タイプ（資産・負債・純資産・費用・収益）
A20: =MAX($A$10:$A19)+1 -> 9 | B20: 属性名 | F20: 文字列 | G20: 6 | H20: =SUBSTITUTE(SUBSTITUTE(ADDRESS(1,A20),"$1",""),"$","") -> I | I20: 空白（設定不要） | O20: 設定なし
A21: =MAX($A$10:$A20)+1 -> 10 | B21: 科目区分 | E21: 〇 | F21: 文字列 | G21: 1 | H21: =SUBSTITUTE(SUBSTITUTE(ADDRESS(1,A21),"$1",""),"$","") -> J | I21: 1:一般科目（伝票入力で使用する科目） 2:統括科目 | O21: 勘定科目マスタ（6桁コードで管理）の情報は、統括科目として6桁コードで連動する。 目節科目マスタの情報は、一般科目として8桁コードで連動する。 ※補足１シート参照 | AB21: 要ユーザヒアリング（スクラッチのマスタで一般科目／統括科目を意識してもらえる？）
A22: =MAX($A$10:$A21)+1 -> 11 | B22: 科目区分名 | F22: 文字列 | G22: 8 | H22: =SUBSTITUTE(SUBSTITUTE(ADDRESS(1,A22),"$1",""),"$","") -> K | I22: 空白（設定不要） | O22: 設定なし
A23: =MAX($A$10:$A22)+1 -> 12 | B23: 貸借 | E23: 〇 | F23: 文字列 | G23: 1 | H23: =SUBSTITUTE(SUBSTITUTE(ADDRESS(1,A23),"$1",""),"$","") -> L | I23: 1:借方、2:貸方 | O23: 勘定科目マスタ.貸借区分
A24: =MAX($A$10:$A23)+1 -> 13 | B24: 貸借名 | F24: 文字列 | G24: 4 | H24: =SUBSTITUTE(SUBSTITUTE(ADDRESS(1,A24),"$1",""),"$","") -> M | I24: 空白（設定不要） | O24: 設定なし
A25: =MAX($A$10:$A24)+1 -> 14 | B25: 補助科目別計上フラグ | E25: 〇 | F25: 数値 | G25: 1 | H25: =SUBSTITUTE(SUBSTITUTE(ADDRESS(1,A25),"$1",""),"$","") -> N | I25: 会計摘要を管理する科目の場合は「1:計上する」、 | O25: 目節科目マスタ.目節科目コードが00の場合、
I26: それ以外は「0：計上しない」 | O26: 勘定科目マスタ.項科目摘要要否区分が要の場合、1
O27: それ以外は2
O28: 目節科目マスタ.目節科目コードが00の以外の場合、
O29: 目節科目マスタ.目節科目摘要要否区分が要の場合、1
O30: それ以外は2
A31: =MAX($A$10:$A25)+1 -> 15 | B31: 通貨別計上フラグ | E31: 〇 | F31: 数値 | G31: 1 | H31: =SUBSTITUTE(SUBSTITUTE(ADDRESS(1,A31),"$1",""),"$","") -> O | I31: 「0:計上しない」 固定 | O31: ０（固定値）
A32: =MAX($A$10:$A31)+1 -> 16 | B32: 調整計上フラグ | E32: △ | F32: 数値 | G32: 1 | H32: =SUBSTITUTE(SUBSTITUTE(ADDRESS(1,A32),"$1",""),"$","") -> P | I32: 「0:計上しない」 固定 | O32: ０（固定値）
A33: =MAX($A$10:$A32)+1 -> 17 | B33: 評価替対象フラグ | E33: △ | F33: 数値 | G33: 1 | H33: =SUBSTITUTE(SUBSTITUTE(ADDRESS(1,A33),"$1",""),"$","") -> Q | I33: 空白（設定不要） | O33: 設定なし
A34: =MAX($A$10:$A33)+1 -> 18 | B34: 入力レート区分 | F34: 文字列 | G34: 1 | H34: =SUBSTITUTE(SUBSTITUTE(ADDRESS(1,A34),"$1",""),"$","") -> R | I34: 空白（設定不要） | O34: 設定なし
A35: =MAX($A$10:$A34)+1 -> 19 | B35: 入力レート区分名 | F35: 文字列 | G35: 3 | H35: =SUBSTITUTE(SUBSTITUTE(ADDRESS(1,A35),"$1",""),"$","") -> S | I35: 空白（設定不要） | O35: 設定なし
A36: =MAX($A$10:$A35)+1 -> 20 | B36: 評価替レート区分 | F36: 文字列 | G36: 1 | H36: =SUBSTITUTE(SUBSTITUTE(ADDRESS(1,A36),"$1",""),"$","") -> T | I36: 空白（設定不要） | O36: 設定なし
A37: =MAX($A$10:$A36)+1 -> 21 | B37: 評価替レート区分名 | F37: 文字列 | G37: 3 | H37: =SUBSTITUTE(SUBSTITUTE(ADDRESS(1,A37),"$1",""),"$","") -> U | I37: 空白（設定不要） | O37: 設定なし
A38: =MAX($A$10:$A37)+1 -> 22 | B38: 消費税区分 | E38: 〇 | F38: コード | G38: 2 | H38: =SUBSTITUTE(SUBSTITUTE(ADDRESS(1,A38),"$1",""),"$","") -> V | I38: ProActiveC4の消費税区分マスタ．消費税区分コードを設定。 | O38: 99 ：対象外（固定値）
A39: =MAX($A$10:$A38)+1 -> 23 | B39: 消費税区分名 | F39: 文字列 | G39: 30 | H39: =SUBSTITUTE(SUBSTITUTE(ADDRESS(1,A39),"$1",""),"$","") -> W | I39: 空白（設定不要） | O39: 設定なし
A40: =MAX($A$10:$A39)+1 -> 24 | B40: 消費税率 | F40: 数値 | G40: 4,2 | H40: =SUBSTITUTE(SUBSTITUTE(ADDRESS(1,A40),"$1",""),"$","") -> X | I40: 空白（設定不要） | O40: 設定なし
A41: =MAX($A$10:$A40)+1 -> 25 | B41: 消費税区分使用制限区分 | E41: 〇 | F41: 文字列 | G41: 1 | H41: =SUBSTITUTE(SUBSTITUTE(ADDRESS(1,A41),"$1",""),"$","") -> Y | I41: 「4:制限なし」 | O41: ４（固定値）
A42: =MAX($A$10:$A41)+1 -> 26 | B42: 消費税区分使用制限区分名 | F42: 文字列 | G42: 30 | H42: =SUBSTITUTE(SUBSTITUTE(ADDRESS(1,A42),"$1",""),"$","") -> Z | I42: 空白（設定不要） | O42: 設定なし
A43: =MAX($A$10:$A42)+1 -> 27 | B43: 消費税計算区分 | E43: 〇 | F43: 文字列 | G43: 1 | H43: =SUBSTITUTE(SUBSTITUTE(ADDRESS(1,A43),"$1",""),"$","") -> AA | I43: 1:税込入力、2:税抜入力、3:計算しない | O43: ３（固定値）
A44: =MAX($A$10:$A43)+1 -> 28 | B44: 消費税計算区分名 | F44: 文字列 | G44: 10 | H44: =SUBSTITUTE(SUBSTITUTE(ADDRESS(1,A44),"$1",""),"$","") -> AB | I44: 空白（設定不要） | O44: 設定なし
A45: =MAX($A$10:$A44)+1 -> 29 | B45: 部門別計上区分 | E45: △ | F45: 文字列 | G45: 1 | H45: =SUBSTITUTE(SUBSTITUTE(ADDRESS(1,A45),"$1",""),"$","") -> AC | I45: 「1:全部門計上可」 | O45: １（固定値）
A46: =MAX($A$10:$A45)+1 -> 30 | B46: 部門別計上区分名 | F46: 文字列 | G46: 10 | H46: =SUBSTITUTE(SUBSTITUTE(ADDRESS(1,A46),"$1",""),"$","") -> AD | I46: 空白（設定不要） | O46: 設定なし
A47: =MAX($A$10:$A46)+1 -> 31 | B47: 計上部門コード | E47: △ | F47: コード | G47: 10 | H47: =SUBSTITUTE(SUBSTITUTE(ADDRESS(1,A47),"$1",""),"$","") -> AE | I47: 空白（設定不要） | O47: 設定なし
A48: =MAX($A$10:$A47)+1 -> 32 | B48: 計上部門名（略） | F48: 文字列 | G48: 20 | H48: =SUBSTITUTE(SUBSTITUTE(ADDRESS(1,A48),"$1",""),"$","") -> AF | I48: 空白（設定不要） | O48: 設定なし
A49: =MAX($A$10:$A48)+1 -> 33 | B49: 組織体系パターンコード | E49: △ | F49: コード | G49: 5 | H49: =SUBSTITUTE(SUBSTITUTE(ADDRESS(1,A49),"$1",""),"$","") -> AG | I49: 空白（設定不要） | O49: 設定なし
A50: =MAX($A$10:$A49)+1 -> 34 | B50: 組織体系パターン名 | F50: 文字列 | G50: 20 | H50: =SUBSTITUTE(SUBSTITUTE(ADDRESS(1,A50),"$1",""),"$","") -> AH | I50: 空白（設定不要） | O50: 設定なし
A51: =MAX($A$10:$A50)+1 -> 35 | B51: 部門コード | E51: △ | F51: コード | G51: 10 | H51: =SUBSTITUTE(SUBSTITUTE(ADDRESS(1,A51),"$1",""),"$","") -> AI | I51: 空白（設定不要） | O51: 設定なし
A52: =MAX($A$10:$A51)+1 -> 36 | B52: 部門名（略） | F52: 文字列 | G52: 20 | H52: =SUBSTITUTE(SUBSTITUTE(ADDRESS(1,A52),"$1",""),"$","") -> AJ | I52: 空白（設定不要） | O52: 設定なし
A53: =MAX($A$10:$A52)+1 -> 37 | B53: 取引先別計上フラグ | E53: △ | F53: 数値 | G53: 1 | H53: =SUBSTITUTE(SUBSTITUTE(ADDRESS(1,A53),"$1",""),"$","") -> AK | I53: ■登録する勘定科目が、目節科目で、かつ取引先別に計上する場合 | O53: 勘定科目マスタ（BE006）．相手先要否区分が'要'の場合
J54: 「1:計上する」
I55: ■それ以外
J56: 「0:計上しない」
I57: ※ProActiveの制約上、預り金消費税科目、立替金消費税科目は「０：計上しない」
A58: =MAX($A$10:$A53)+1 -> 38 | B58: 口座別計上フラグ | E58: △ | F58: 数値 | G58: 1 | H58: =SUBSTITUTE(SUBSTITUTE(ADDRESS(1,A58),"$1",""),"$","") -> AL | I58: ■登録する勘定科目が、目節科目で、かつ自社口座別に計上する場合 | O58: 預金科目の場合 １
J59: 「1:計上する」 | L59: ※預金科目 | O59: それ以外 ０
I60: ■それ以外 | O60: ※預金科目に該当する科目は一覧化しておく
J61: 「0:計上しない」
I62: ※ProActiveの制約上、預り金消費税科目、立替金消費税科目は「０：計上しない」
A63: =MAX($A$10:$A58)+1 -> 39 | B63: セグメント別計上フラグ | E63: △ | F63: 数値 | G63: 1 | H63: =SUBSTITUTE(SUBSTITUTE(ADDRESS(1,A63),"$1",""),"$","") -> AM | I63: ■登録する勘定科目が、目節科目で、かつセグメント別 | O63: 勘定科目マスタ.品目要否区分が「収支管理品目大分類」の場合 1※会計情報品名の区分にした方が良いか
I64: （会計情報品目別）に計上する場合 | O64: それ以外 0
J65: 「1:計上する」 | O65: → 「品目要否区分」で判断
I66: ■それ以外
J67: 「0:計上しない」
I68: ※ProActiveの制約上、預り金消費税科目、立替金消費税科目は「０：計上しない」
A69: =MAX($A$10:$A63)+1 -> 40 | B69: プロジェクト別計上フラグ | E69: △ | F69: 数値 | G69: 1 | H69: =SUBSTITUTE(SUBSTITUTE(ADDRESS(1,A69),"$1",""),"$","") -> AN | I69: ■登録する勘定科目が、目節科目で、かつプロジェクト別（業種別）に | O69: 預り金消費税科目、立替金消費税科目は「０：計上しない」とする
I70: 計上する場合 | O70: それ以外 １
J71: 「1:計上する」
I72: ■それ以外 | O72: ※内部取引用の消費税科目は1：計上するとする
J73: 「0:計上しない」
I74: ※ProActiveの制約上、預り金消費税科目、立替金消費税科目は「０：計上しない」
A75: =MAX($A$10:$A69)+1 -> 41 | B75: 担当者別計上フラグ | E75: △ | F75: 数値 | G75: 1 | H75: =SUBSTITUTE(SUBSTITUTE(ADDRESS(1,A75),"$1",""),"$","") -> AO | I75: 「0:計上しない」 固定 | O75: ０（固定値）
A76: =MAX($A$10:$A75)+1 -> 42 | B76: 代表内訳区分 | E76: △ | F76: 文字列 | G76: 1 | H76: =SUBSTITUTE(SUBSTITUTE(ADDRESS(1,A76),"$1",""),"$","") -> AP | I76: 「9:無し」 固定 | O76: ９（固定値）
A77: =MAX($A$10:$A76)+1 -> 43 | B77: 代表内訳区分名 | F77: 文字列 | G77: 10 | H77: =SUBSTITUTE(SUBSTITUTE(ADDRESS(1,A77),"$1",""),"$","") -> AQ | I77: 空白（設定不要） | O77: 設定なし
A78: =MAX($A$10:$A77)+1 -> 44 | B78: セグメント1使用区分 | E78: △ | F78: 文字列 | G78: 1 | H78: =SUBSTITUTE(SUBSTITUTE(ADDRESS(1,A78),"$1",""),"$","") -> AR | I78: 「1:使用しない」 固定 | O78: １（固定値）
A79: =MAX($A$10:$A78)+1 -> 45 | B79: セグメント1使用区分名 | F79: 文字列 | G79: 10 | H79: =SUBSTITUTE(SUBSTITUTE(ADDRESS(1,A79),"$1",""),"$","") -> AS | I79: 空白（設定不要） | O79: 設定なし
A80: =MAX($A$10:$A79)+1 -> 46 | B80: セグメント1ID | E80: △ | F80: 数値 | G80: 20 | H80: =SUBSTITUTE(SUBSTITUTE(ADDRESS(1,A80),"$1",""),"$","") -> AT | I80: 空白（設定不要） | O80: 設定なし
A81: =MAX($A$10:$A80)+1 -> 47 | B81: セグメント1名 | F81: 数値 | G81: 20 | H81: =SUBSTITUTE(SUBSTITUTE(ADDRESS(1,A81),"$1",""),"$","") -> AU | I81: 空白（設定不要） | O81: 設定なし
A82: =MAX($A$10:$A81)+1 -> 48 | B82: セグメント2使用区分 | E82: △ | F82: 文字列 | G82: 1 | H82: =SUBSTITUTE(SUBSTITUTE(ADDRESS(1,A82),"$1",""),"$","") -> AV | I82: 「1:使用しない」 固定 | O82: １（固定値）
A83: =MAX($A$10:$A82)+1 -> 49 | B83: セグメント2使用区分名 | F83: 文字列 | G83: 10 | H83: =SUBSTITUTE(SUBSTITUTE(ADDRESS(1,A83),"$1",""),"$","") -> AW | I83: 空白（設定不要） | O83: 設定なし
A84: =MAX($A$10:$A83)+1 -> 50 | B84: セグメント2ID | E84: △ | F84: 数値 | G84: 20 | H84: =SUBSTITUTE(SUBSTITUTE(ADDRESS(1,A84),"$1",""),"$","") -> AX | I84: 空白（設定不要） | O84: 設定なし
A85: =MAX($A$10:$A84)+1 -> 51 | B85: セグメント2名 | F85: 数値 | G85: 20 | H85: =SUBSTITUTE(SUBSTITUTE(ADDRESS(1,A85),"$1",""),"$","") -> AY | I85: 空白（設定不要） | O85: 設定なし
A86: =MAX($A$10:$A85)+1 -> 52 | B86: セグメント3使用区分 | E86: △ | F86: 文字列 | G86: 1 | H86: =SUBSTITUTE(SUBSTITUTE(ADDRESS(1,A86),"$1",""),"$","") -> AZ | I86: 「1:使用しない」 固定 | O86: １（固定値）
A87: =MAX($A$10:$A86)+1 -> 53 | B87: セグメント3使用区分名 | F87: 文字列 | G87: 10 | H87: =SUBSTITUTE(SUBSTITUTE(ADDRESS(1,A87),"$1",""),"$","") -> BA | I87: 空白（設定不要） | O87: 設定なし
A88: =MAX($A$10:$A87)+1 -> 54 | B88: セグメント3ID | E88: △ | F88: 数値 | G88: 20 | H88: =SUBSTITUTE(SUBSTITUTE(ADDRESS(1,A88),"$1",""),"$","") -> BB | I88: 空白（設定不要） | O88: 設定なし
A89: =MAX($A$10:$A88)+1 -> 55 | B89: セグメント3名 | F89: 数値 | G89: 20 | H89: =SUBSTITUTE(SUBSTITUTE(ADDRESS(1,A89),"$1",""),"$","") -> BC | I89: 空白（設定不要） | O89: 設定なし
A90: =MAX($A$10:$A89)+1 -> 56 | B90: セグメント4使用区分 | E90: △ | F90: 文字列 | G90: 1 | H90: =SUBSTITUTE(SUBSTITUTE(ADDRESS(1,A90),"$1",""),"$","") -> BD | I90: 「1:使用しない」 固定 | O90: １（固定値）
A91: =MAX($A$10:$A90)+1 -> 57 | B91: セグメント4使用区分名 | F91: 文字列 | G91: 10 | H91: =SUBSTITUTE(SUBSTITUTE(ADDRESS(1,A91),"$1",""),"$","") -> BE | I91: 空白（設定不要） | O91: 設定なし
A92: =MAX($A$10:$A91)+1 -> 58 | B92: セグメント4ID | E92: △ | F92: 数値 | G92: 20 | H92: =SUBSTITUTE(SUBSTITUTE(ADDRESS(1,A92),"$1",""),"$","") -> BF | I92: 空白（設定不要） | O92: 設定なし
A93: =MAX($A$10:$A92)+1 -> 59 | B93: セグメント4名 | F93: 数値 | G93: 20 | H93: =SUBSTITUTE(SUBSTITUTE(ADDRESS(1,A93),"$1",""),"$","") -> BG | I93: 空白（設定不要） | O93: 設定なし
A94: =MAX($A$10:$A93)+1 -> 60 | B94: セグメント5使用区分 | E94: △ | F94: 文字列 | G94: 1 | H94: =SUBSTITUTE(SUBSTITUTE(ADDRESS(1,A94),"$1",""),"$","") -> BH | I94: 「1:使用しない」 固定 | O94: １（固定値）
A95: =MAX($A$10:$A94)+1 -> 61 | B95: セグメント5使用区分名 | F95: 文字列 | G95: 10 | H95: =SUBSTITUTE(SUBSTITUTE(ADDRESS(1,A95),"$1",""),"$","") -> BI | I95: 空白（設定不要） | O95: 設定なし
A96: =MAX($A$10:$A95)+1 -> 62 | B96: セグメント5ID | E96: △ | F96: 数値 | G96: 20 | H96: =SUBSTITUTE(SUBSTITUTE(ADDRESS(1,A96),"$1",""),"$","") -> BJ | I96: 空白（設定不要） | O96: 設定なし
A97: =MAX($A$10:$A96)+1 -> 63 | B97: セグメント5名 | F97: 数値 | G97: 20 | H97: =SUBSTITUTE(SUBSTITUTE(ADDRESS(1,A97),"$1",""),"$","") -> BK | I97: 空白（設定不要） | O97: 設定なし
A98: =MAX($A$10:$A97)+1 -> 64 | B98: C/F勘定科目コード | E98: △ | F98: コード | G98: 8 | H98: =SUBSTITUTE(SUBSTITUTE(ADDRESS(1,A98),"$1",""),"$","") -> BL | I98: ProActiveC4のC/F勘定科目マスタに登録したコード | O98: 勘定科目マスタ.CF勘定科目コード
I99: ※一般科目（仕訳で使用する科目）の場合は必須
A100: =MAX($A$10:$A98)+1 -> 65 | B100: C/F勘定科目名 | F100: 文字列 | G100: 30 | H100: =SUBSTITUTE(SUBSTITUTE(ADDRESS(1,A100),"$1",""),"$","") -> BM | I100: 空白（設定不要） | O100: 設定なし
A101: =MAX($A$10:$A100)+1 -> 66 | B101: 借方C/F勘定科目内訳コード | F101: コード | G101: 2 | H101: =SUBSTITUTE(SUBSTITUTE(ADDRESS(1,A101),"$1",""),"$","") -> BN | I101: 空白（設定不要） | O101: 設定なし
...

Sheet 取込フォーマット定義（補助科目）
A1: ドキュメント名 | E1: サブシステム | G1: 業務機能名 | P1: 作成者 | R1: SCSK位田 | T1: 更新者
A2: 業務機能概要書 | C2: 取込フォーマット定義 | E2: 業務共通 | G2: 勘定科目・会計摘要マスタ自動取込 | P2: 作成日 | R2: =表紙!C51 -> 45898 | T2: 更新日
A4: データ名 | C4: 補助科目マスタ自動取込 | I4: ヘッダ行 | K4: あり | M4: なし | N4: ダブルクォーテーション | Q4: あり | S4: なし | X4: 文字列
A5: ﾌｧｲﾙ形式・ﾚｺｰﾄﾞ長 | D5: 固定長（ | G5: Byte） | I5: 可変長（区切り文字［ ，(カンマ) ］） | M5: バイナリデータ | P5: その他（ ） | X5: 半英数
A6: 文字コード | D6: UNI（Win系） | F6: EBCDIC(K) | I6: その他（ UTF-8） | M6: 改行コード | O6: LF(UNIX系) | Q6: CRLF(Win系) | T6: なし | X6: 半カナ
A7: 全角(2byte)文字項目 | D7: あり | F7: なし | M7: 数値編集 | O7: 左詰め | Q7: 右詰め［ゼロ埋め］ | T7: 右詰め［スペース埋め］ | X7: コード
A8: 特記事項 | C8: 取込ファイルには、取込項目のタイトル行が必要となる | X8: 数値
A9: No. | B9: 項目名 | E9: 必須 | F9: 型 | G9: 桁数 | H9: 開始位置 | I9: 項目説明 | O9: 設定値 | X9: 日付
H10: /列 | X10: 時間
A11: =MAX($A$10:$A10)+1 -> 1 | B11: 編集区分 | E11: 〇 | F11: 区分 | G11: 1 | H11: =SUBSTITUTE(SUBSTITUTE(ADDRESS(1,A11),"$1",""),"$","") -> A | I11: 「1:新規」 | K11: ※全件連動の前提 | O11: １（固定値） | X11: 年月
A12: =MAX($A$10:$A11)+1 -> 2 | B12: 勘定科目コード | E12: 〇 | F12: コード | G12: 8 | H12: =SUBSTITUTE(SUBSTITUTE(ADDRESS(1,A12),"$1",""),"$","") -> B | I12: ProActiveC4勘定科目マスタに登録した8桁の勘定科目コード | O12: 科目摘要マスタ.勘定科目コード | X12: 区分
A13: =MAX($A$10:$A12)+1 -> 3 | B13: 勘定科目名（略） | F13: 文字列 | G13: 20 | H13: =SUBSTITUTE(SUBSTITUTE(ADDRESS(1,A13),"$1",""),"$","") -> C | I13: 設定不要 | O13: 設定なし | X13: フラグ
A14: =MAX($A$10:$A13)+1 -> 4 | B14: 補助科目コード | E14: △ | F14: コード | G14: 4 | H14: =SUBSTITUTE(SUBSTITUTE(ADDRESS(1,A14),"$1",""),"$","") -> D | I14: 科目摘要のコード | O14: 科目摘要マスタ.科目摘要コード | X14: -
A15: =MAX($A$10:$A14)+1 -> 5 | B15: 補助科目名 | E15: △ | F15: 文字列 | G15: 30 | H15: =SUBSTITUTE(SUBSTITUTE(ADDRESS(1,A15),"$1",""),"$","") -> E | I15: 科目摘要の名称 | O15: 科目摘要マスタ.科目摘要名 | R15: 36byteのうち、先頭30byteを設定する
A16: =MAX($A$10:$A15)+1 -> 6 | B16: 借方資金繰コード | F16: コード | G16: 5 | H16: =SUBSTITUTE(SUBSTITUTE(ADDRESS(1,A16),"$1",""),"$","") -> F | I16: 空白 | O16: 設定なし
A17: =MAX($A$10:$A16)+1 -> 7 | B17: 借方資金繰科目名 | F17: 文字列 | G17: 30 | H17: =SUBSTITUTE(SUBSTITUTE(ADDRESS(1,A17),"$1",""),"$","") -> G | I17: 空白 | O17: 設定なし
A18: =MAX($A$10:$A17)+1 -> 8 | B18: 貸方資金繰コード | F18: コード | G18: 5 | H18: =SUBSTITUTE(SUBSTITUTE(ADDRESS(1,A18),"$1",""),"$","") -> H | I18: 空白 | O18: 設定なし
A19: =MAX($A$10:$A18)+1 -> 9 | B19: 貸方資金繰科目名 | F19: 文字列 | G19: 30 | H19: =SUBSTITUTE(SUBSTITUTE(ADDRESS(1,A19),"$1",""),"$","") -> I | I19: 空白 | O19: 設定なし
A20: =MAX($A$10:$A19)+1 -> 10 | B20: 使用不可フラグ | E20: △ | F20: 数値 | G20: 1 | H20: =SUBSTITUTE(SUBSTITUTE(ADDRESS(1,A20),"$1",""),"$","") -> J | I20: 「0:使用可」 ※論理削除対象は「1：使用不可」とする | O20: ０（固定値）※論理削除済みデータは１
A21: =MAX($A$10:$A20)+1 -> 11 | B21: 登録者 | F21: コード | G21: 15 | H21: =SUBSTITUTE(SUBSTITUTE(ADDRESS(1,A21),"$1",""),"$","") -> K | I21: 空白（設定不要） | O21: 設定なし
A22: =MAX($A$10:$A21)+1 -> 12 | B22: 登録者名 | F22: 文字列 | G22: 22 | H22: =SUBSTITUTE(SUBSTITUTE(ADDRESS(1,A22),"$1",""),"$","") -> L | I22: 空白（設定不要） | O22: 設定なし
A23: =MAX($A$10:$A22)+1 -> 13 | B23: 登録日時 | F23: 数値 | G23: 17 | H23: =SUBSTITUTE(SUBSTITUTE(ADDRESS(1,A23),"$1",""),"$","") -> M | I23: 空白（設定不要） | O23: 設定なし
A24: =MAX($A$10:$A23)+1 -> 14 | B24: 更新者 | F24: コード | G24: 15 | H24: =SUBSTITUTE(SUBSTITUTE(ADDRESS(1,A24),"$1",""),"$","") -> N | I24: 空白（設定不要） | O24: 設定なし
A25: =MAX($A$10:$A24)+1 -> 15 | B25: 更新者名 | F25: 文字列 | G25: 22 | H25: =SUBSTITUTE(SUBSTITUTE(ADDRESS(1,A25),"$1",""),"$","") -> O | I25: 空白（設定不要） | O25: 設定なし
A26: =MAX($A$10:$A25)+1 -> 16 | B26: 更新日時 | F26: 数値 | G26: 17 | H26: =SUBSTITUTE(SUBSTITUTE(ADDRESS(1,A26),"$1",""),"$","") -> P | I26: 空白（設定不要） | O26: 設定なし

Sheet 取込フォーマット定義（勘定科目）bk
A1: ドキュメント名 | E1: サブシステム | G1: 業務機能名 | P1: 作成者 | R1: =表紙!D51 -> SCSK位田 | T1: 更新者
A2: 業務機能概要書 | C2: 取込フォーマット定義 | E2: =業務機能概要!L2 -> 業務共通 | G2: =業務機能概要!Q2 -> 勘定科目・会計摘要マスタ自動取込 | P2: 作成日 | R2: =表紙!C51 -> 45898 | T2: 更新日
A4: データ名 | C4: 勘定科目マスタ自動取込 | I4: ヘッダ行 | K4: あり | M4: なし | N4: ダブルクォーテーション | Q4: あり | S4: なし | X4: 文字列
A5: ﾌｧｲﾙ形式・ﾚｺｰﾄﾞ長 | D5: 固定長（ | G5: Byte） | I5: 可変長（区切り文字［ ，(カンマ) ］） | M5: バイナリデータ | P5: その他（ ） | X5: 半英数
A6: 文字コード | D6: UNI（Win系） | F6: EBCDIC(K) | I6: その他（ UTF-8） | M6: 改行コード | O6: LF(UNIX系) | Q6: CRLF(Win系) | T6: なし | X6: 半カナ
A7: 全角(2byte)文字項目 | D7: あり | F7: なし | M7: 数値編集 | O7: 左詰め | Q7: 右詰め［ゼロ埋め］ | T7: 右詰め［スペース埋め］ | X7: コード
A8: 特記事項 | C8: 取込ファイルには、取込項目のタイトル行が必要となる | X8: 数値
A9: No. | B9: 項目名 | E9: 必須 | F9: 型 | G9: 桁数 | H9: 開始位置 | I9: 備考 | X9: 日付
H10: /列 | X10: 時間
A11: =MAX($A$10:$A10)+1 -> 1 | B11: 編集区分 | E11: 〇 | F11: 区分 | G11: 1 | H11: =SUBSTITUTE(SUBSTITUTE(ADDRESS(1,A11),"$1",""),"$","") -> A | I11: 「1:新規」 固定 | K11: ※差分連動の前提 | X11: 年月
A12: =MAX($A$10:$A11)+1 -> 2 | B12: 勘定科目コード | E12: 〇 | F12: コード | G12: 8 | H12: =SUBSTITUTE(SUBSTITUTE(ADDRESS(1,A12),"$1",""),"$","") -> B | X12: 区分 | Y12: ★連動元のテーブル情報が決定後に設定値を設計する
A13: =MAX($A$10:$A12)+1 -> 3 | B13: 勘定科目名 | E13: 〇 | F13: 文字列 | G13: 30 | H13: =SUBSTITUTE(SUBSTITUTE(ADDRESS(1,A13),"$1",""),"$","") -> C | Y13: ★連動元のテーブル情報が決定後に設定値を設計する
A14: =MAX($A$10:$A13)+1 -> 4 | B14: 勘定科目名（カナ） | E14: 〇 | F14: 文字列 | G14: 60 | H14: =SUBSTITUTE(SUBSTITUTE(ADDRESS(1,A14),"$1",""),"$","") -> D | Y14: ★連動元のテーブル情報が決定後に設定値を設計する
A15: =MAX($A$10:$A14)+1 -> 5 | B15: 勘定科目名（略） | E15: 〇 | F15: 文字列 | G15: 20 | H15: =SUBSTITUTE(SUBSTITUTE(ADDRESS(1,A15),"$1",""),"$","") -> E | Y15: ★連動元のテーブル情報が決定後に設定値を設計する
A16: =MAX($A$10:$A15)+1 -> 6 | B16: B／S・P／L | E16: 〇 | F16: 文字列 | G16: 1 | H16: =SUBSTITUTE(SUBSTITUTE(ADDRESS(1,A16),"$1",""),"$","") -> F | Y16: ★連動元のテーブル情報が決定後に設定値を設計する
A17: =MAX($A$10:$A16)+1 -> 7 | B17: B／S・P／L名 | F17: 文字列 | G17: 30 | H17: =SUBSTITUTE(SUBSTITUTE(ADDRESS(1,A17),"$1",""),"$","") -> G | I17: 空白（設定不要） ProActiveC4へ取込時は使用しない項目。※ProActiveC4から勘定科目情報を出力する際も同じフォーマットを使用。出力の際に値が設定される。
A18: =MAX($A$10:$A17)+1 -> 8 | B18: 属性 | E18: 〇 | F18: 文字列 | G18: 1 | H18: =SUBSTITUTE(SUBSTITUTE(ADDRESS(1,A18),"$1",""),"$","") -> H | Y18: ★連動元のテーブル情報が決定後に設定値を設計する
A19: =MAX($A$10:$A18)+1 -> 9 | B19: 属性名 | F19: 文字列 | G19: 6 | H19: =SUBSTITUTE(SUBSTITUTE(ADDRESS(1,A19),"$1",""),"$","") -> I | I19: 空白（設定不要） ProActiveC4へ取込時は使用しない項目。※ProActiveC4から勘定科目情報を出力する際も同じフォーマットを使用。出力の際に値が設定される。
A20: =MAX($A$10:$A19)+1 -> 10 | B20: 科目区分 | E20: 〇 | F20: 文字列 | G20: 1 | H20: =SUBSTITUTE(SUBSTITUTE(ADDRESS(1,A20),"$1",""),"$","") -> J | Y20: ★連動元のテーブル情報が決定後に設定値を設計する
A21: =MAX($A$10:$A20)+1 -> 11 | B21: 科目区分名 | F21: 文字列 | G21: 8 | H21: =SUBSTITUTE(SUBSTITUTE(ADDRESS(1,A21),"$1",""),"$","") -> K | I21: 空白（設定不要） ProActiveC4へ取込時は使用しない項目。※ProActiveC4から勘定科目情報を出力する際も同じフォーマットを使用。出力の際に値が設定される。
A22: =MAX($A$10:$A21)+1 -> 12 | B22: 貸借 | E22: 〇 | F22: 文字列 | G22: 1 | H22: =SUBSTITUTE(SUBSTITUTE(ADDRESS(1,A22),"$1",""),"$","") -> L | I22: 1:借方、2:貸方 | Y22: ★連動元のテーブル情報が決定後に設定値を設計する
A23: =MAX($A$10:$A22)+1 -> 13 | B23: 貸借名 | F23: 文字列 | G23: 4 | H23: =SUBSTITUTE(SUBSTITUTE(ADDRESS(1,A23),"$1",""),"$","") -> M | I23: 空白（設定不要） ProActiveC4へ取込時は使用しない項目。※ProActiveC4から勘定科目情報を出力する際も同じフォーマットを使用。出力の際に値が設定される。
A24: =MAX($A$10:$A23)+1 -> 14 | B24: 補助科目別計上フラグ | E24: 〇 | F24: 数値 | G24: 1 | H24: =SUBSTITUTE(SUBSTITUTE(ADDRESS(1,A24),"$1",""),"$","") -> N | I24: 会計摘要を管理する科目の場合は「1:計上する」、それ以外は「0：計上しない」 | Y24: ★連動元のテーブル情報が決定後に設定値を設計する
A25: =MAX($A$10:$A24)+1 -> 15 | B25: 通貨別計上フラグ | E25: 〇 | F25: 数値 | G25: 1 | H25: =SUBSTITUTE(SUBSTITUTE(ADDRESS(1,A25),"$1",""),"$","") -> O | I25: 「0:計上しない」 固定
A26: =MAX($A$10:$A25)+1 -> 16 | B26: 調整計上フラグ | E26: △ | F26: 数値 | G26: 1 | H26: =SUBSTITUTE(SUBSTITUTE(ADDRESS(1,A26),"$1",""),"$","") -> P | I26: 「0:計上しない」 固定
A27: =MAX($A$10:$A26)+1 -> 17 | B27: 評価替対象フラグ | E27: △ | F27: 数値 | G27: 1 | H27: =SUBSTITUTE(SUBSTITUTE(ADDRESS(1,A27),"$1",""),"$","") -> Q | I27: 空白（設定不要） ProActiveC4へ取込時は使用しない項目。※ProActiveC4から勘定科目情報を出力する際も同じフォーマットを使用。出力の際に値が設定される。
A28: =MAX($A$10:$A27)+1 -> 18 | B28: 入力レート区分 | F28: 文字列 | G28: 1 | H28: =SUBSTITUTE(SUBSTITUTE(ADDRESS(1,A28),"$1",""),"$","") -> R | I28: 空白（設定不要） ProActiveC4へ取込時は使用しない項目。※ProActiveC4から勘定科目情報を出力する際も同じフォーマットを使用。出力の際に値が設定される。
A29: =MAX($A$10:$A28)+1 -> 19 | B29: 入力レート区分名 | F29: 文字列 | G29: 3 | H29: =SUBSTITUTE(SUBSTITUTE(ADDRESS(1,A29),"$1",""),"$","") -> S | I29: 空白（設定不要） ProActiveC4へ取込時は使用しない項目。※ProActiveC4から勘定科目情報を出力する際も同じフォーマットを使用。出力の際に値が設定される。
A30: =MAX($A$10:$A29)+1 -> 20 | B30: 評価替レート区分 | F30: 文字列 | G30: 1 | H30: =SUBSTITUTE(SUBSTITUTE(ADDRESS(1,A30),"$1",""),"$","") -> T | I30: 空白（設定不要） ProActiveC4へ取込時は使用しない項目。※ProActiveC4から勘定科目情報を出力する際も同じフォーマットを使用。出力の際に値が設定される。
A31: =MAX($A$10:$A30)+1 -> 21 | B31: 評価替レート区分名 | F31: 文字列 | G31: 3 | H31: =SUBSTITUTE(SUBSTITUTE(ADDRESS(1,A31),"$1",""),"$","") -> U | I31: 空白（設定不要） ProActiveC4へ取込時は使用しない項目。※ProActiveC4から勘定科目情報を出力する際も同じフォーマットを使用。出力の際に値が設定される。
A32: =MAX($A$10:$A31)+1 -> 22 | B32: 消費税区分 | E32: 〇 | F32: コード | G32: 2 | H32: =SUBSTITUTE(SUBSTITUTE(ADDRESS(1,A32),"$1",""),"$","") -> V | I32: ProActiveC4の消費税区分マスタ．消費税区分コードを設定。 | Y32: ★連動元のテーブル情報が決定後に設定値を設計する
A33: =MAX($A$10:$A32)+1 -> 23 | B33: 消費税区分名 | F33: 文字列 | G33: 30 | H33: =SUBSTITUTE(SUBSTITUTE(ADDRESS(1,A33),"$1",""),"$","") -> W | I33: 空白（設定不要） ProActiveC4へ取込時は使用しない項目。※ProActiveC4から勘定科目情報を出力する際も同じフォーマットを使用。出力の際に値が設定される。
A34: =MAX($A$10:$A33)+1 -> 24 | B34: 消費税率 | F34: 数値 | G34: 4,2 | H34: =SUBSTITUTE(SUBSTITUTE(ADDRESS(1,A34),"$1",""),"$","") -> X | I34: 空白（設定不要） ProActiveC4へ取込時は使用しない項目。※ProActiveC4から勘定科目情報を出力する際も同じフォーマットを使用。出力の際に値が設定される。
A35: =MAX($A$10:$A34)+1 -> 25 | B35: 消費税区分使用制限区分 | E35: 〇 | F35: 文字列 | G35: 1 | H35: =SUBSTITUTE(SUBSTITUTE(ADDRESS(1,A35),"$1",""),"$","") -> Y | I35: 「4:制限なし」
A36: =MAX($A$10:$A35)+1 -> 26 | B36: 消費税区分使用制限区分名 | F36: 文字列 | G36: 30 | H36: =SUBSTITUTE(SUBSTITUTE(ADDRESS(1,A36),"$1",""),"$","") -> Z | I36: 空白（設定不要） ProActiveC4へ取込時は使用しない項目。※ProActiveC4から勘定科目情報を出力する際も同じフォーマットを使用。出力の際に値が設定される。
A37: =MAX($A$10:$A36)+1 -> 27 | B37: 消費税計算区分 | E37: 〇 | F37: 文字列 | G37: 1 | H37: =SUBSTITUTE(SUBSTITUTE(ADDRESS(1,A37),"$1",""),"$","") -> AA | I37: 登録する勘定科目の消費税の計算方法に合わせて登録。1:税込入力、2:税抜入力、3:計算しない | Y37: ★連動元のテーブル情報が決定後に設定値を設計する
A38: =MAX($A$10:$A37)+1 -> 28 | B38: 消費税計算区分名 | F38: 文字列 | G38: 10 | H38: =SUBSTITUTE(SUBSTITUTE(ADDRESS(1,A38),"$1",""),"$","") -> AB | I38: 空白（設定不要） ProActiveC4へ取込時は使用しない項目。※ProActiveC4から勘定科目情報を出力する際も同じフォーマットを使用。出力の際に値が設定される。
A39: =MAX($A$10:$A38)+1 -> 29 | B39: 部門別計上区分 | E39: △ | F39: 文字列 | G39: 1 | H39: =SUBSTITUTE(SUBSTITUTE(ADDRESS(1,A39),"$1",""),"$","") -> AC | I39: 「1:全部門計上可」
A40: =MAX($A$10:$A39)+1 -> 30 | B40: 部門別計上区分名 | F40: 文字列 | G40: 10 | H40: =SUBSTITUTE(SUBSTITUTE(ADDRESS(1,A40),"$1",""),"$","") -> AD | I40: 空白（設定不要） ProActiveC4へ取込時は使用しない項目。※ProActiveC4から勘定科目情報を出力する際も同じフォーマットを使用。出力の際に値が設定される。
A41: =MAX($A$10:$A40)+1 -> 31 | B41: 計上部門コード | E41: △ | F41: コード | G41: 10 | H41: =SUBSTITUTE(SUBSTITUTE(ADDRESS(1,A41),"$1",""),"$","") -> AE | I41: 空白（設定不要） ProActiveC4へ取込時は使用しない項目。※ProActiveC4から勘定科目情報を出力する際も同じフォーマットを使用。出力の際に値が設定される。
A42: =MAX($A$10:$A41)+1 -> 32 | B42: 計上部門名（略） | F42: 文字列 | G42: 20 | H42: =SUBSTITUTE(SUBSTITUTE(ADDRESS(1,A42),"$1",""),"$","") -> AF | I42: 空白（設定不要） ProActiveC4へ取込時は使用しない項目。※ProActiveC4から勘定科目情報を出力する際も同じフォーマットを使用。出力の際に値が設定される。
A43: =MAX($A$10:$A42)+1 -> 33 | B43: 組織体系パターンコード | E43: △ | F43: コード | G43: 5 | H43: =SUBSTITUTE(SUBSTITUTE(ADDRESS(1,A43),"$1",""),"$","") -> AG | I43: 空白（設定不要） ProActiveC4へ取込時は使用しない項目。※ProActiveC4から勘定科目情報を出力する際も同じフォーマットを使用。出力の際に値が設定される。
A44: =MAX($A$10:$A43)+1 -> 34 | B44: 組織体系パターン名 | F44: 文字列 | G44: 20 | H44: =SUBSTITUTE(SUBSTITUTE(ADDRESS(1,A44),"$1",""),"$","") -> AH | I44: 空白（設定不要） ProActiveC4へ取込時は使用しない項目。※ProActiveC4から勘定科目情報を出力する際も同じフォーマットを使用。出力の際に値が設定される。
A45: =MAX($A$10:$A44)+1 -> 35 | B45: 部門コード | E45: △ | F45: コード | G45: 10 | H45: =SUBSTITUTE(SUBSTITUTE(ADDRESS(1,A45),"$1",""),"$","") -> AI | I45: 空白（設定不要） ProActiveC4へ取込時は使用しない項目。※ProActiveC4から勘定科目情報を出力する際も同じフォーマットを使用。出力の際に値が設定される。
A46: =MAX($A$10:$A45)+1 -> 36 | B46: 部門名（略） | F46: 文字列 | G46: 20 | H46: =SUBSTITUTE(SUBSTITUTE(ADDRESS(1,A46),"$1",""),"$","") -> AJ | I46: 空白（設定不要） ProActiveC4へ取込時は使用しない項目。※ProActiveC4から勘定科目情報を出力する際も同じフォーマットを使用。出力の際に値が設定される。
A47: =MAX($A$10:$A46)+1 -> 37 | B47: 取引先別計上フラグ | E47: △ | F47: 数値 | G47: 1 | H47: =SUBSTITUTE(SUBSTITUTE(ADDRESS(1,A47),"$1",""),"$","") -> AK | I47: ■登録する勘定科目が、目科目もしくは節科目で、かつ勘定科目マスタ（BE006）．相手先要否区分が'要'の場合 | Y47: ★連動元のテーブル情報が決定後に設定値を設計する
J48: 「1:計上する」
I49: ■それ以外
J50: 「0:計上しない」 | L50: ★預り金消費税科目、立替金消費税科目、純資産の科目は「０：計上しない」とする
A51: =MAX($A$10:$A47)+1 -> 38 | B51: 口座別計上フラグ | E51: △ | F51: 数値 | G51: 1 | H51: =SUBSTITUTE(SUBSTITUTE(ADDRESS(1,A51),"$1",""),"$","") -> AL | I51: ■登録する勘定科目が、目科目もしくは節科目で、かつ自社口座別に計上する場合 | O51: ※預金科目のみ「１：計上する」とする | Y51: ★連動元のテーブル情報が決定後に設定値を設計する
J52: 「1:計上する」
I53: ■それ以外
J54: 「0:計上しない」 | L54: ★預り金消費税科目、立替金消費税科目、純資産の科目は「０：計上しない」とする
A55: =MAX($A$10:$A51)+1 -> 39 | B55: セグメント別計上フラグ | E55: △ | F55: 数値 | G55: 1 | H55: =SUBSTITUTE(SUBSTITUTE(ADDRESS(1,A55),"$1",""),"$","") -> AM | I55: ■登録する勘定科目が、目科目もしくは節科目で、かつセグメント別（会計情報品目別）に計上する場合 | Y55: ★連動元のテーブル情報が決定後に設定値を設計する
J56: 「1:計上する」
I57: ■それ以外
J58: 「0:計上しない」 | L58: ★預り金消費税科目、立替金消費税科目、純資産の科目は「０：計上しない」とする
A59: =MAX($A$10:$A55)+1 -> 40 | B59: プロジェクト別計上フラグ | E59: △ | F59: 数値 | G59: 1 | H59: =SUBSTITUTE(SUBSTITUTE(ADDRESS(1,A59),"$1",""),"$","") -> AN | I59: ■登録する勘定科目が、目科目もしくは節科目で、かつプロジェクト別（業種別）に計上する場合 | Y59: ★連動元のテーブル情報が決定後に設定値を設計する
J60: 「1:計上する」
I61: ■それ以外
J62: 「0:計上しない」 | L62: ★預り金消費税科目、立替金消費税科目、純資産の科目は「０：計上しない」とする
A63: =MAX($A$10:$A59)+1 -> 41 | B63: 担当者別計上フラグ | E63: △ | F63: 数値 | G63: 1 | H63: =SUBSTITUTE(SUBSTITUTE(ADDRESS(1,A63),"$1",""),"$","") -> AO | I63: 「0:計上しない」 固定
A64: =MAX($A$10:$A63)+1 -> 42 | B64: 代表内訳区分 | E64: △ | F64: 文字列 | G64: 1 | H64: =SUBSTITUTE(SUBSTITUTE(ADDRESS(1,A64),"$1",""),"$","") -> AP | I64: 「9:無し」 固定
A65: =MAX($A$10:$A64)+1 -> 43 | B65: 代表内訳区分名 | F65: 文字列 | G65: 10 | H65: =SUBSTITUTE(SUBSTITUTE(ADDRESS(1,A65),"$1",""),"$","") -> AQ | I65: 空白（設定不要） ProActiveC4へ取込時は使用しない項目。※ProActiveC4から勘定科目情報を出力する際も同じフォーマットを使用。出力の際に値が設定される。
A66: =MAX($A$10:$A65)+1 -> 44 | B66: セグメント1使用区分 | E66: △ | F66: 文字列 | G66: 1 | H66: =SUBSTITUTE(SUBSTITUTE(ADDRESS(1,A66),"$1",""),"$","") -> AR | I66: 「1:使用しない」 固定
A67: =MAX($A$10:$A66)+1 -> 45 | B67: セグメント1使用区分名 | F67: 文字列 | G67: 10 | H67: =SUBSTITUTE(SUBSTITUTE(ADDRESS(1,A67),"$1",""),"$","") -> AS | I67: 空白（設定不要） ProActiveC4へ取込時は使用しない項目。※ProActiveC4から勘定科目情報を出力する際も同じフォーマットを使用。出力の際に値が設定される。
A68: =MAX($A$10:$A67)+1 -> 46 | B68: セグメント1ID | E68: △ | F68: 数値 | G68: 20 | H68: =SUBSTITUTE(SUBSTITUTE(ADDRESS(1,A68),"$1",""),"$","") -> AT | I68: 空白（設定不要） ProActiveC4へ取込時は使用しない項目。※ProActiveC4から勘定科目情報を出力する際も同じフォーマットを使用。出力の際に値が設定される。
A69: =MAX($A$10:$A68)+1 -> 47 | B69: セグメント1名 | F69: 数値 | G69: 20 | H69: =SUBSTITUTE(SUBSTITUTE(ADDRESS(1,A69),"$1",""),"$","") -> AU | I69: 空白（設定不要） ProActiveC4へ取込時は使用しない項目。※ProActiveC4から勘定科目情報を出力する際も同じフォーマットを使用。出力の際に値が設定される。
A70: =MAX($A$10:$A69)+1 -> 48 | B70: セグメント2使用区分 | E70: △ | F70: 文字列 | G70: 1 | H70: =SUBSTITUTE(SUBSTITUTE(ADDRESS(1,A70),"$1",""),"$","") -> AV | I70: 「1:使用しない」 固定
A71: =MAX($A$10:$A70)+1 -> 49 | B71: セグメント2使用区分名 | F71: 文字列 | G71: 10 | H71: =SUBSTITUTE(SUBSTITUTE(ADDRESS(1,A71),"$1",""),"$","") -> AW | I71: 空白（設定不要） ProActiveC4へ取込時は使用しない項目。※ProActiveC4から勘定科目情報を出力する際も同じフォーマットを使用。出力の際に値が設定される。
A72: =MAX($A$10:$A71)+1 -> 50 | B72: セグメント2ID | E72: △ | F72: 数値 | G72: 20 | H72: =SUBSTITUTE(SUBSTITUTE(ADDRESS(1,A72),"$1",""),"$","") -> AX | I72: 空白（設定不要） ProActiveC4へ取込時は使用しない項目。※ProActiveC4から勘定科目情報を出力する際も同じフォーマットを使用。出力の際に値が設定される。
A73: =MAX($A$10:$A72)+1 -> 51 | B73: セグメント2名 | F73: 数値 | G73: 20 | H73: =SUBSTITUTE(SUBSTITUTE(ADDRESS(1,A73),"$1",""),"$","") -> AY | I73: 空白（設定不要） ProActiveC4へ取込時は使用しない項目。※ProActiveC4から勘定科目情報を出力する際も同じフォーマットを使用。出力の際に値が設定される。
A74: =MAX($A$10:$A73)+1 -> 52 | B74: セグメント3使用区分 | E74: △ | F74: 文字列 | G74: 1 | H74: =SUBSTITUTE(SUBSTITUTE(ADDRESS(1,A74),"$1",""),"$","") -> AZ | I74: 「1:使用しない」 固定
A75: =MAX($A$10:$A74)+1 -> 53 | B75: セグメント3使用区分名 | F75: 文字列 | G75: 10 | H75: =SUBSTITUTE(SUBSTITUTE(ADDRESS(1,A75),"$1",""),"$","") -> BA | I75: 空白（設定不要） ProActiveC4へ取込時は使用しない項目。※ProActiveC4から勘定科目情報を出力する際も同じフォーマットを使用。出力の際に値が設定される。
A76: =MAX($A$10:$A75)+1 -> 54 | B76: セグメント3ID | E76: △ | F76: 数値 | G76: 20 | H76: =SUBSTITUTE(SUBSTITUTE(ADDRESS(1,A76),"$1",""),"$","") -> BB | I76: 空白（設定不要） ProActiveC4へ取込時は使用しない項目。※ProActiveC4から勘定科目情報を出力する際も同じフォーマットを使用。出力の際に値が設定される。
A77: =MAX($A$10:$A76)+1 -> 55 | B77: セグメント3名 | F77: 数値 | G77: 20 | H77: =SUBSTITUTE(SUBSTITUTE(ADDRESS(1,A77),"$1",""),"$","") -> BC | I77: 空白（設定不要） ProActiveC4へ取込時は使用しない項目。※ProActiveC4から勘定科目情報を出力する際も同じフォーマットを使用。出力の際に値が設定される。
A78: =MAX($A$10:$A77)+1 -> 56 | B78: セグメント4使用区分 | E78: △ | F78: 文字列 | G78: 1 | H78: =SUBSTITUTE(SUBSTITUTE(ADDRESS(1,A78),"$1",""),"$","") -> BD | I78: 「1:使用しない」 固定
A79: =MAX($A$10:$A78)+1 -> 57 | B79: セグメント4使用区分名 | F79: 文字列 | G79: 10 | H79: =SUBSTITUTE(SUBSTITUTE(ADDRESS(1,A79),"$1",""),"$","") -> BE | I79: 空白（設定不要） ProActiveC4へ取込時は使用しない項目。※ProActiveC4から勘定科目情報を出力する際も同じフォーマットを使用。出力の際に値が設定される。
A80: =MAX($A$10:$A79)+1 -> 58 | B80: セグメント4ID | E80: △ | F80: 数値 | G80: 20 | H80: =SUBSTITUTE(SUBSTITUTE(ADDRESS(1,A80),"$1",""),"$","") -> BF | I80: 空白（設定不要） ProActiveC4へ取込時は使用しない項目。※ProActiveC4から勘定科目情報を出力する際も同じフォーマットを使用。出力の際に値が設定される。
A81: =MAX($A$10:$A80)+1 -> 59 | B81: セグメント4名 | F81: 数値 | G81: 20 | H81: =SUBSTITUTE(SUBSTITUTE(ADDRESS(1,A81),"$1",""),"$","") -> BG | I81: 空白（設定不要） ProActiveC4へ取込時は使用しない項目。※ProActiveC4から勘定科目情報を出力する際も同じフォーマットを使用。出力の際に値が設定される。
A82: =MAX($A$10:$A81)+1 -> 60 | B82: セグメント5使用区分 | E82: △ | F82: 文字列 | G82: 1 | H82: =SUBSTITUTE(SUBSTITUTE(ADDRESS(1,A82),"$1",""),"$","") -> BH | I82: 「1:使用しない」 固定
A83: =MAX($A$10:$A82)+1 -> 61 | B83: セグメント5使用区分名 | F83: 文字列 | G83: 10 | H83: =SUBSTITUTE(SUBSTITUTE(ADDRESS(1,A83),"$1",""),"$","") -> BI | I83: 空白（設定不要） ProActiveC4へ取込時は使用しない項目。※ProActiveC4から勘定科目情報を出力する際も同じフォーマットを使用。出力の際に値が設定される。
A84: =MAX($A$10:$A83)+1 -> 62 | B84: セグメント5ID | E84: △ | F84: 数値 | G84: 20 | H84: =SUBSTITUTE(SUBSTITUTE(ADDRESS(1,A84),"$1",""),"$","") -> BJ | I84: 空白（設定不要） ProActiveC4へ取込時は使用しない項目。※ProActiveC4から勘定科目情報を出力する際も同じフォーマットを使用。出力の際に値が設定される。
A85: =MAX($A$10:$A84)+1 -> 63 | B85: セグメント5名 | F85: 数値 | G85: 20 | H85: =SUBSTITUTE(SUBSTITUTE(ADDRESS(1,A85),"$1",""),"$","") -> BK | I85: 空白（設定不要） ProActiveC4へ取込時は使用しない項目。※ProActiveC4から勘定科目情報を出力する際も同じフォーマットを使用。出力の際に値が設定される。
A86: =MAX($A$10:$A85)+1 -> 64 | B86: C/F勘定科目コード | E86: △ | F86: コード | G86: 8 | H86: =SUBSTITUTE(SUBSTITUTE(ADDRESS(1,A86),"$1",""),"$","") -> BL | I86: ProActiveC4のC/F勘定科目マスタに登録したコード ※一般科目（仕訳で使用する科目）の場合は必須 | Y86: ★連動元のテーブル情報が決定後に設定値を設計する
A87: =MAX($A$10:$A86)+1 -> 65 | B87: C/F勘定科目名 | F87: 文字列 | G87: 30 | H87: =SUBSTITUTE(SUBSTITUTE(ADDRESS(1,A87),"$1",""),"$","") -> BM | I87: 空白（設定不要） ProActiveC4へ取込時は使用しない項目。※ProActiveC4から勘定科目情報を出力する際も同じフォーマットを使用。出力の際に値が設定される。
A88: =MAX($A$10:$A87)+1 -> 66 | B88: 借方C/F勘定科目内訳コード | F88: コード | G88: 2 | H88: =SUBSTITUTE(SUBSTITUTE(ADDRESS(1,A88),"$1",""),"$","") -> BN | I88: 空白（設定不要） ProActiveC4へ取込時は使用しない項目。※ProActiveC4から勘定科目情報を出力する際も同じフォーマットを使用。出力の際に値が設定される。 | Y88: ★連動元のテーブル情報が決定後に設定値を設計する
A89: =MAX($A$10:$A88)+1 -> 67 | B89: 借方C/F勘定科目内訳名 | F89: 文字列 | G89: 20 | H89: =SUBSTITUTE(SUBSTITUTE(ADDRESS(1,A89),"$1",""),"$","") -> BO | I89: 空白（設定不要） ProActiveC4へ取込時は使用しない項目。※ProActiveC4から勘定科目情報を出力する際も同じフォーマットを使用。出力の際に値が設定される。
A90: =MAX($A$10:$A89)+1 -> 68 | B90: 貸方C/F勘定科目内訳コード | F90: コード | G90: 2 | H90: =SUBSTITUTE(SUBSTITUTE(ADDRESS(1,A90),"$1",""),"$","") -> BP | I90: 空白（設定不要） ProActiveC4へ取込時は使用しない項目。※ProActiveC4から勘定科目情報を出力する際も同じフォーマットを使用。出力の際に値が設定される。 | Y90: ★連動元のテーブル情報が決定後に設定値を設計する
A91: =MAX($A$10:$A90)+1 -> 69 | B91: 貸方C/F勘定科目内訳名 | F91: 文字列 | G91: 20 | H91: =SUBSTITUTE(SUBSTITUTE(ADDRESS(1,A91),"$1",""),"$","") -> BQ | I91: 空白（設定不要） ProActiveC4へ取込時は使用しない項目。※ProActiveC4から勘定科目情報を出力する際も同じフォーマットを使用。出力の際に値が設定される。
A92: =MAX($A$10:$A91)+1 -> 70 | B92: 現預金フラグ | E92: △ | F92: 文字列 | G92: 1 | H92: =SUBSTITUTE(SUBSTITUTE(ADDRESS(1,A92),"$1",""),"$","") -> BR | I92: 資金繰科目か非資金繰科目かの識別を行う。0:現預金としない。1:現預金とする。 | O92: ホクレン様の場合、資金繰管理機能を使用しないため、全科目を「１：現預金とする」に設定する | Y92: ★連動元のテーブル情報が決定後に設定値を設計する
A93: =MAX($A$10:$A92)+1 -> 71 | B93: 借方資金繰科目コード | E93: △ | F93: コード | G93: 5 | H93: =SUBSTITUTE(SUBSTITUTE(ADDRESS(1,A93),"$1",""),"$","") -> BS | I93: 勘定科目に対応する資金繰科目コード。現預金フラグが「0:現預金としない」の場合必須。 | O93: ホクレン様の場合、資金繰管理機能を使用しないため、設定不要。 | Y93: ★連動元のテーブル情報が決定後に設定値を設計する
A94: =MAX($A$10:$A93)+1 -> 72 | B94: 借方資金繰科目名 | F94: 文字列 | G94: 30 | H94: =SUBSTITUTE(SUBSTITUTE(ADDRESS(1,A94),"$1",""),"$","") -> BT | I94: 空白（設定不要） ProActiveC4へ取込時は使用しない項目。※ProActiveC4から勘定科目情報を出力する際も同じフォーマットを使用。出力の際に値が設定される。
A95: =MAX($A$10:$A94)+1 -> 73 | B95: 貸方資金繰科目コード | E95: △ | F95: 文字列 | G95: 5 | H95: =SUBSTITUTE(SUBSTITUTE(ADDRESS(1,A95),"$1",""),"$","") -> BU | I95: 勘定科目に対応する資金繰科目コード。現預金フラグが「0:現預金としない」の場合必須。 | O95: ホクレン様の場合、資金繰管理機能を使用しないため、設定不要。 | Y95: ★連動元のテーブル情報が決定後に設定値を設計する
A96: =MAX($A$10:$A95)+1 -> 74 | B96: 貸方資金繰科目名 | F96: 文字列 | G96: 30 | H96: =SUBSTITUTE(SUBSTITUTE(ADDRESS(1,A96),"$1",""),"$","") -> BV | I96: 空白（設定不要） ProActiveC4へ取込時は使用しない項目。※ProActiveC4から勘定科目情報を出力する際も同じフォーマットを使用。出力の際に値が設定される。
A97: =MAX($A$10:$A96)+1 -> 75 | B97: 元帳出力フラグ | E97: △ | F97: 数値 | G97: 1 | H97: =SUBSTITUTE(SUBSTITUTE(ADDRESS(1,A97),"$1",""),"$","") -> BW | I97: 「1:出力する」 固定
A98: =MAX($A$10:$A97)+1 -> 76 | B98: 勘定消込対象フラグ | E98: △ | F98: 数値 | G98: 1 | H98: =SUBSTITUTE(SUBSTITUTE(ADDRESS(1,A98),"$1",""),"$","") -> BX | I98: 「0:消込対象外」 固定
A99: =MAX($A$10:$A98)+1 -> 77 | B99: 使用可否フラグ | E99: 〇 | F99: 数値 | G99: 1 | H99: =SUBSTITUTE(SUBSTITUTE(ADDRESS(1,A99),"$1",""),"$","") -> BY | I99: 「0:使用可」 ※論理削除対象の科目は「1：使用不可」とする
A100: =MAX($A$10:$A99)+1 -> 78 | B100: 登録者 | F100: コード | G100: 15 | H100: =SUBSTITUTE(SUBSTITUTE(ADDRESS(1,A100),"$1",""),"$","") -> BZ | I100: 空白（設定不要） ProActiveC4へ取込時は使用しない項目。※ProActiveC4から勘定科目情報を出力する際も同じフォーマットを使用。出力の際に値が設定される。
A101: =MAX($A$10:$A100)+1 -> 79 | B101: 登録者名 | F101: 文字列 | G101: 22 | H101: =SUBSTITUTE(SUBSTITUTE(ADDRESS(1,A101),"$1",""),"$","") -> CA | I101: 空白（設定不要） ProActiveC4へ取込時は使用しない項目。※ProActiveC4から勘定科目情報を出力する際も同じフォーマットを使用。出力の際に値が設定される。
...

Sheet 取込フォーマット定義（補助科目）bk
A1: ドキュメント名 | E1: サブシステム | G1: 業務機能名 | P1: 作成者 | R1: =表紙!D51 -> SCSK位田 | T1: 更新者
A2: 業務機能概要書 | C2: 取込フォーマット定義 | E2: =業務機能概要!L2 -> 業務共通 | G2: =業務機能概要!Q2 -> 勘定科目・会計摘要マスタ自動取込 | P2: 作成日 | R2: =表紙!C51 -> 45898 | T2: 更新日
A4: データ名 | C4: 補助科目マスタ自動取込 | I4: ヘッダ行 | K4: あり | M4: なし | N4: ダブルクォーテーション | Q4: あり | S4: なし | X4: 文字列
A5: ﾌｧｲﾙ形式・ﾚｺｰﾄﾞ長 | D5: 固定長（ | G5: Byte） | I5: 可変長（区切り文字［ ，(カンマ) ］） | M5: バイナリデータ | P5: その他（ ） | X5: 半英数
A6: 文字コード | D6: UNI（Win系） | F6: EBCDIC(K) | I6: その他（ UTF-8） | M6: 改行コード | O6: LF(UNIX系) | Q6: CRLF(Win系) | T6: なし | X6: 半カナ
A7: 全角(2byte)文字項目 | D7: あり | F7: なし | M7: 数値編集 | O7: 左詰め | Q7: 右詰め［ゼロ埋め］ | T7: 右詰め［スペース埋め］ | X7: コード
A8: 特記事項 | C8: 取込ファイルには、取込項目のタイトル行が必要となる | X8: 数値
A9: No. | B9: 項目名 | E9: 必須 | F9: 型 | G9: 桁数 | H9: 開始位置 | I9: 備考 | X9: 日付
H10: /列 | X10: 時間
A11: =MAX($A$10:$A10)+1 -> 1 | B11: 編集区分 | E11: 〇 | F11: 区分 | G11: 1 | H11: =SUBSTITUTE(SUBSTITUTE(ADDRESS(1,A11),"$1",""),"$","") -> A | I11: 「1:新規」 | K11: ※差分連動の前提 | X11: 年月
A12: =MAX($A$10:$A11)+1 -> 2 | B12: 勘定科目コード | E12: 〇 | F12: コード | G12: 8 | H12: =SUBSTITUTE(SUBSTITUTE(ADDRESS(1,A12),"$1",""),"$","") -> B | I12: ProActiveC4勘定科目マスタに登録した8桁の勘定科目コード | X12: 区分 | Y12: ★連動元のテーブル情報が決定後に設定値を設計する
A13: =MAX($A$10:$A12)+1 -> 3 | B13: 勘定科目名（略） | F13: 文字列 | G13: 20 | H13: =SUBSTITUTE(SUBSTITUTE(ADDRESS(1,A13),"$1",""),"$","") -> C | I13: 設定不要 | X13: フラグ
A14: =MAX($A$10:$A13)+1 -> 4 | B14: 補助科目コード | E14: △ | F14: コード | G14: 4 | H14: =SUBSTITUTE(SUBSTITUTE(ADDRESS(1,A14),"$1",""),"$","") -> D | I14: 科目摘要のコード | X14: - | Y14: ★連動元のテーブル情報が決定後に設定値を設計する
A15: =MAX($A$10:$A14)+1 -> 5 | B15: 補助科目名 | E15: △ | F15: 文字列 | G15: 30 | H15: =SUBSTITUTE(SUBSTITUTE(ADDRESS(1,A15),"$1",""),"$","") -> E | I15: 科目摘要の名称
A16: =MAX($A$10:$A15)+1 -> 6 | B16: 借方資金繰コード | F16: コード | G16: 5 | H16: =SUBSTITUTE(SUBSTITUTE(ADDRESS(1,A16),"$1",""),"$","") -> F | I16: 空白
A17: =MAX($A$10:$A16)+1 -> 7 | B17: 借方資金繰科目名 | F17: 文字列 | G17: 30 | H17: =SUBSTITUTE(SUBSTITUTE(ADDRESS(1,A17),"$1",""),"$","") -> G | I17: 空白
A18: =MAX($A$10:$A17)+1 -> 8 | B18: 貸方資金繰コード | F18: コード | G18: 5 | H18: =SUBSTITUTE(SUBSTITUTE(ADDRESS(1,A18),"$1",""),"$","") -> H | I18: 空白
A19: =MAX($A$10:$A18)+1 -> 9 | B19: 貸方資金繰科目名 | F19: 文字列 | G19: 30 | H19: =SUBSTITUTE(SUBSTITUTE(ADDRESS(1,A19),"$1",""),"$","") -> I | I19: 空白
A20: =MAX($A$10:$A19)+1 -> 10 | B20: 使用不可フラグ | E20: △ | F20: 数値 | G20: 1 | H20: =SUBSTITUTE(SUBSTITUTE(ADDRESS(1,A20),"$1",""),"$","") -> J | I20: 「0:使用可」 ※論理削除対象は「1：使用不可」とする
A21: =MAX($A$10:$A20)+1 -> 11 | B21: 登録者 | F21: コード | G21: 15 | H21: =SUBSTITUTE(SUBSTITUTE(ADDRESS(1,A21),"$1",""),"$","") -> K | I21: 空白（設定不要）
A22: =MAX($A$10:$A21)+1 -> 12 | B22: 登録者名 | F22: 文字列 | G22: 22 | H22: =SUBSTITUTE(SUBSTITUTE(ADDRESS(1,A22),"$1",""),"$","") -> L | I22: 空白（設定不要）
A23: =MAX($A$10:$A22)+1 -> 13 | B23: 登録日時 | F23: 数値 | G23: 17 | H23: =SUBSTITUTE(SUBSTITUTE(ADDRESS(1,A23),"$1",""),"$","") -> M | I23: 空白（設定不要）
A24: =MAX($A$10:$A23)+1 -> 14 | B24: 更新者 | F24: コード | G24: 15 | H24: =SUBSTITUTE(SUBSTITUTE(ADDRESS(1,A24),"$1",""),"$","") -> N | I24: 空白（設定不要）
A25: =MAX($A$10:$A24)+1 -> 15 | B25: 更新者名 | F25: 文字列 | G25: 22 | H25: =SUBSTITUTE(SUBSTITUTE(ADDRESS(1,A25),"$1",""),"$","") -> O | I25: 空白（設定不要）
A26: =MAX($A$10:$A25)+1 -> 16 | B26: 更新日時 | F26: 数値 | G26: 17 | H26: =SUBSTITUTE(SUBSTITUTE(ADDRESS(1,A26),"$1",""),"$","") -> P | I26: 空白（設定不要）
E27: 〇：必須 △：条件付き必須

Sheet ⇒

Sheet データアクセス要領
A1: ドキュメント名 | L1: サブシステム | Q1: 業務機能名 | AJ1: 作成者 | AO1: =表紙!D51 -> SCSK位田 | AT1: 更新者
A2: 業務機能概要書 | G2: データアクセス要領 | L2: =業務機能概要!L2 -> 業務共通 | Q2: =業務機能概要!Q2 -> 勘定科目・会計摘要マスタ自動取込 | AJ2: 作成日付 | AO2: =表紙!C51 -> 45898 | AT2: 更新日付
A4: 【編集要領】
B6: １. | C6: 登録済データの削除
C8: ① | D8: 勘定科目マスタ
D9: ・ | E9: 最新情報を取込む前に登録済データを全件削除する
E10: ただし、款科目より上位の統括科目（例．「流動資産」など）は連動対象外のため削除しない
D12: ■削除エンティティ
D13: № | E13: エンティティ名
D14: 1 | E14: 勘定科目
D15: 2 | E15: 勘定科目属性
D16: 3 | E16: Ｃ／Ｆ勘定科目設定
C18: ■削除条件
C19: № | D19: 取得条件 | AW19: 備考
C20: １ | F20: 勘定科目．会社コード | V20: ＝ | X20: 引数の会社コード
C21: ２ | F21: 勘定科目．勘定科目コード | V21: not like | Y21: 9%’
B24: ② | C24: 補助科目マスタ
C25: ・ | D25: 最新情報を取込む前に登録済データを全件削除する
C28: ■削除エンティティ
C29: № | D29: エンティティ名
C30: 1 | D30: 補助科目
C32: ■削除条件
C33: № | D33: 取得条件 | AW33: 備考
C34: １ | F34: 補助科目．会社コード | V34: ＝ | X34: 引数の会社コード
C35: ２
A39: ２. | B39: データの登録
C41: 標準の「勘定科目・補助科目取込」機能の実行時と同様。

Sheet 補足１
A1: ドキュメント名 | L1: サブシステム | Q1: 業務機能名 | AM1: 作成者 | AR1: =表紙!D51 -> SCSK位田 | AW1: 更新者
A2: 業務機能概要書 | G2: 補足説明 | L2: =業務機能概要!L2 -> 業務共通 | Q2: =業務機能概要!Q2 -> 勘定科目・会計摘要マスタ自動取込 | AM2: 作成日付 | AR2: =表紙!C51 -> 45898 | AW2: 更新日付
C4: スクラッチ機能からProActiveへ連動する勘定科目（一般科目／統括科目）のデータ
C6: 1 | D6: 連動仕様
E8: スクラッチ．勘定科目マスタ（6桁コードで管理）の情報は、統括科目として6桁コードで連動する。
E9: スクラッチ．目節科目マスタの情報は、一般科目として8桁コードで連動する。
C13: 2 | D13: 懸念
E15: 目節管理しない科目の場合、目節コードが00であるが、
E16: 目節管理する科目の場合も、目節コードが00のものがある。
E17: 両者が混在することで、ただしくデータ連動できるのか？
C20: 3 | D20: 整理
E22: 以下の3パターンがとりえるパターンのため、各パターンについて一般科目、統括科目の連動データを整理する。
E24: ケース１：目節管理なしの科目 | W24: → | X24: 目節マスタに8桁コード（6桁コード＋00）で管理される
E25: ケース２：目節管理ありでかつ目節コードが00の科目 | W25: → | X25: 目節マスタに8桁コードで管理される
E26: ケース３：目節管理ありでかつ目節コードが00以外の科目 | W26: → | X26: 目節マスタに8桁コードで管理される
E27: ケース４：6桁コードの下2桁が00のコード | W27: → | X27: 勘定科目マスタに6桁コードで管理される
E30: ケース１の具体列
E31: 11010100 現金 | O31: → | Q31: 一般科目として11010100（8桁）を連動、 | AH31: ※現行では、勘定科目コードは「1101010000」
Q32: 統括科目として110101（6桁）を連動
E34: ケース２の具体列
E35: 11020100 当座預金 | O35: → | Q35: 一般科目として11020100（8桁）を連動、 | AH35: ※現行では、勘定科目コードは「1102019800」
Q36: 統括科目として110201（6桁）を連動
E38: ケース３の具体列
E39: 11060101 販売共計支払金品代 | O39: → | Q39: 一般科目として11060101（8桁）を連動、 | AH39: ※現行では、勘定科目コードは「1106010100」
Q40: 統括科目として110601（6桁）を連動
E42: ケース４の具体例
E43: 110100 現金 | O43: → | Q43: 統括科目として110100（6桁）を連動

Sheet 補足２
A1: ドキュメント名 | L1: サブシステム | Q1: 業務機能名 | AM1: 作成者 | AR1: =表紙!D51 -> SCSK位田 | AW1: 更新者
A2: 業務機能概要書 | G2: 補足説明 | L2: =業務機能概要!L2 -> 業務共通 | Q2: =業務機能概要!Q2 -> 勘定科目・会計摘要マスタ自動取込 | AM2: 作成日付 | AR2: =表紙!C51 -> 45898 | AW2: 更新日付
B4: 当機能でのバッチファイル、xmlファイル、SQL実行の作成イメージ
C7: バッチファイル１ | P7: c4_import_kamoku.bat
D9: ①勘定科目取込 | AG9: SQL実行ファイル①（.sql）
E11: 取込ファイル探索 | J11: ※取込ファイルが0byteであった場合は正常として処理終了する | AH11: 勘定科目マスタを全件削除する | AR11: ※款科目より上位の統括科目は削除しない
E12: SQLの実行（既存データのバックアップ、削除）
E14: 取込実行バッチファイルの呼び出し | AG14: SQL実行ファイル②（.sql）
E16: 正常時 | AH16: 補助科目マスタを全件削除する
F17: 取込ファイルの退避（正常終了のファイル退避フォルダへ移動）
E18: エラー時
F19: 取込ファイルの退避（異常終了のファイル退避フォルダへ移動）
AG20: 入力データファイル（xml）
D21: ②補助科目取込
AH22: 会社コード
E23: 勘定科目取込と同様 | AH23: 取込区分 | AL23: を定義する
AH25: ※「cvo_sav_cd」は設定なしとして、取込ファイルはバッチファイルで定義する
C28: バッチファイル２ | I28: ※パタメータ定義用 | P28: param.bat
D30: 取込ファイルのフォルダパス、 | AG30: BRファイル（xml）
D31: SQLファイルのパスなどを定義する
AH32: バッチ処理の中で利用するビジネスリソースと、
AH33: J-SOXログ出力で利用するクライアント環境情報を定義
C37: バッチファイル３ | P37: Exec_kamokuImpBatch.bat
D39: 入力データファイル 読み込み
D41: BRファイル 読み込み
D43: バッチ実行
D44: 戻り値返却
C51: ディレクトリ構成
D54: ー | E54: ー | G54: c4_import_kamoku.bat | AD54: ・・・ | AF54: タスクスケジューラから起動されるbat
E55: ｜ | G55: param.bat | AD55: ・・・ | AF55: bat実行時に参照されるパラメータセットbat
E56: ｜
E57: ー | G57: CSV_DIR | AD57: ・・・ | AF57: 取込用のCSVファイルを配置するフォルダ
E58: ｜
E59: ー | G59: BATCH_SUB_DIR | Q59: ー | R59: c4_data_update_export.bat | AD59: ・・・ | AF59: SQLを実行するためのbat
E60: ｜ | R60: Exec_kamokuImpBatch.bat | AD60: ・・・ | AF60: 勘定科目取込を実行するためのbat
E61: ｜
E62: ー | G62: SQL_DIR | Q62: ー | R62: bk_zcmmhkanjoukamoku.sql | AD62: ・・・ | AF62: 勘定科目マスタ、属性の情報をバックアップテーブルにコピーしておく | AX62: ZCMMHKANJOUKAMOKU
E63: ｜ | R63: del_zcmmhkanjoukamoku.sql | AD63: ・・・ | AF63: 勘定科目マスタ、属性の情報を削除する | AX63: AGLMNKNKMKZOKUSEI
E64: ｜ | AX64: AGLMNCFKNKMKSET
E65: ｜
E66: ー | G66: SETTING_DIR | Q66: ー | R66: BR_CM.xml | AD66: ・・・ | AF66: BRファイル
E67: ｜ | R67: Input_KamokuImpBatch.xml | AD67: ・・・ | AF67: 取込用のインプットファイル
E68: ｜
E69: ｜
E70: ー | G70: SUCCESS_DIR | AD70: ・・・ | AF70: 正常取込できた取込ファイルを退避するフォルダ
E71: ｜
E72: ー | G72: ERR_DIR | AD72: ・・・ | AF72: 取込エラーとなった取込ファイルを退避するフォルダ
AF73: エラー時のログを出力するフォルダ
