Workbook
Name 【債権】最新データ辞書: #REF!
Name 項目辞書: #REF!
Name 項目辞書: #REF!

Sheet 表紙
F46: ProActive
B48: 変更履歴
B50: 項番 | C50: 変更発生日 | D50: 変更者 | E50: 変更箇所 | F50: 変更内容
B51: 1 | C51: 45898 | D51: SCSK大西 | F51: 新規作成
B52: 2
B53: 3
B54: 4
B55: 5
B56: 6
B57: 7
B58: 8
B59: 9
B60: 10
B61: 11
B62: 12
B63: 13
... B80: 30

Sheet 業務機能概要
A1: ドキュメント名 | L1: サブシステム | Q1: 業務機能名 | AJ1: 作成者 | AO1: =表紙!D51 -> SCSK大西 | AT1: 更新者
A2: 業務機能概要書 | G2: 業務機能概要 | L2: 財務会計 | Q2: 仕訳データ自動取込 | AJ2: 作成日付 | AO2: =表紙!C51 -> 45898 | AT2: 更新日付
B4: 【目的・役割】
C5: ・ | D5: ホクレン様の伝票入力は部門システムやスクラッチ開発機能で実施するため、ProActiveC4では、仕訳データを外部のシステムから取込する必要がある。
D6: 仕訳データの取込はバッチ処理で実行して、夜間処理後の翌営業日、または即時にProActiveC4で参照、更新するような状態となることが必要である。
B9: 【利用者】
C10: ・ | D10: バッチ実行
B13: 【利用頻度】
C14: ・ | D14: 随時
B17: 【対象要件定義書】
C18: ・ | D18: 要件定義書(他システムとのデータ連動)
B21: 【処理概要】
C22: １) | D22: ファイルによってデータ連動される仕訳データをProActiveC4標準の「仕訳外部データ取込」の処理を使用してProActiveC4に取込する。
D23: ※ | E23: ホクレン様の業務では1日あたりの仕訳データは最大で約200万件である。
E24: 取込処理のパフォーマンス向上のため、約8万件×25ファイル（＝200万件）に分割して連動された仕訳データファイルを並列で取込する。
D49: 当機能の責任範囲は以下となる。
D50: ※ | E50: スクラッチ開発機能から作成、連動される連動データ（CSVファイル）は、当機能の実行前に、ProActiveC4サーバ上から参照可能な取込ディレクトリに配置される想定とする。
D51: ※ | E51: 「仕訳外部データ取込バッチ」はProActiveC4外のタスク管理用ミドルウェア（以下、タスクスケジューラ）から実行する想定とする。
D52: ※ | E52: 「仕訳外部データ取込バッチ」は連動データ（CSVファイル）ごとに起動される想定とする。（処理結果も連動データごとにタスクスケジューラへ返却する）
AM55: ※ | AN55: 取込ディレクトリはProActiveC4の
AN56: バッチサーバ上から参照可能なディレクトリ
L60: 起動
AB62: ファイル参照
L63: 結果返却
Q69: 退避 | AK69: 登録
N83: ※削除処理は、当機能とは別にファイル削除処理を作成して、その処理で実施する
C94: ２) | D94: バッチ実行される「仕訳外部データ取込」について、以下の処理を実施する。
E96: ・ | F96: 取込ディレクトリに配置されている連動データ（取込用のCSVファイル）の情報を取得する。
F97: 取込データが取得できた場合は、取込ファイルをINPUTとして、「仕訳外部データ取込」をバッチ実行する。（オンライン機能「仕訳外部データ取込」の取込動作を踏襲する。）
F98: ※ | G98: 標準の「仕訳外部データ取込」はオンライン処理可能なままとする。
E100: ・ | F100: 「仕訳外部データ取込」のバッチ処理実行結果をバッチジョブ情報に登録する。（標準仕様に準じる）
E102: ・ | F102: 取込処理後、取込用のCSVファイルは処理済用ファイルのディレクトリに移動する。
F103: ※ | G103: アプリケーションではなく、バッチファイルで処理済ファイルを移動する。
F104: ※ | G104: 正常用、エラー用のディレクトリを作成して処理結果によって移動先ディレクトリを分岐させる。
E106: ・ | F106: バッチ処理実行結果の終了情報をタスクスケジューラに返却する。
F108: [実行情報]
F109: No | H109: パラメータ | Q109: 内容
F110: 1 | H110: ※イベント概要参照
F112: [終了情報]
F113: 戻り値 | H113: 内容 | Q113: 内容
F114: 0 | H114: 正常終了
F115: 1 | H115: 異常終了 | Q115: 業務エラー/システムエラー発生時
B119: 【共通要件】
D120: 共通要件内容 | J120: 対応内容（標準準拠の場合、記載省略）
D121: セキュリティ | J121: 部門制限、本人制限の機能性は実装しない。
D122: 承認WF | J122: 対応なし。承認WFの利用は不可とする。
D123: 組織変更 | J123: 標準準拠（財務会計サブシステムの組織変更で対応されるため、対象外）
B139: 【前提・制約事項】
C140: １) | D140: ProActiveC4の「仕訳外部データ取込」機能では、固定の取込フォーマットがあるため、該当するフォーマットに合わせて連動データが作成される前提とする。
D141: また、仕訳データを約8万件ごとに分割して連動データが作成される前提とする。
D142: （データ作成は、連動元システムまたは、連動処理（ProActiveC4外）で実施する。）
C145: ２) | D145: ProActiveC4の「仕訳外部データ取込」機能では、1ファイルにつき、仕訳データが10万件を超えるもの、または、ファイルサイズが35MBを超えるものは取込不可となる。
D146: また、ヘッダ行があるデータは取込不可となるため、ProActiveC4に連動されるデータ（CSVファイル）はヘッダ行がない状態で作成される前提とする。
C148: ３) | D148: ProActiveC4に連動されるデータ（CSVファイル）の以下の取込項目について、ProActiveC4のマスタ情報に合わせて連動データが作成される前提とする。（補足参照）
E150: ・ | F150: 「部門コード」には、「事業所コード」+「業種コード」＋「部課コード」で指定する。
E151: ・ | F151: 「消費税区分」には、ProActiveC4のマスタコードで指定する。
C154: ４) | D154: ProActiveC4に連動されるデータ（CSVファイル）は、ProActiveC4で消費税集計表を作成するために、本体科目と消費税科目を同一明細にした形式で連動データが作成される前提とする。
D155: ※ | E155: 計上タイミングの違いによって、本体科目と消費税科目が同一明細の形式で作成できない連動データについては、ユーザがProActiveC4で該当データを特定して、
E156: スクラッチ開発機能で該当データの取消伝票、同一明細の形式に修正した伝票を起票し、ProActiveC4に連動するという運用想定である。
D157: ※ | E157: 内部取引における消費税除去の仕訳は通常（対外）取引とは異なる消費税科目を使用する。
E158: このため、内部取引の消費税除去の仕訳は別明細の形式でProActiveC4に連動する。 | AA158: （補足参照）
C160: ５) | D160: ProActiveC4に連動されるデータ（CSVファイル）のファイル名は「siwkimp_」にシステム日時（タイムスタンプ）を付加した名称であることを前提とする。
D161: 例） | F161: siwkimp_YYYYMMDDHHMMSSmmm.csv
D162: 当機能で使用する各バッチファイルのパラメータには、上記の名称を取込ファイルとして定義する。
C164: ６) | D164: ProActiveC4に連動されるデータ（CSVファイル）は、ProActiveC4のバッチサーバから参照可能な一時保管用のディレクトリに配置されることを前提とする。
C167: ７) | D167: 「仕訳外部データ取込」をバッチ実行した情報は、ProActiveC4標準の「バッチジョブ」として扱われ、「バッチジョブ一覧検索」機能で状況の確認が可能となる。
D168: 状況の確認は上記機能で実施する方針として、個別にエラーログ出力等の機能性は開発しない。
C170: ８) | D170: ProActiveC4標準の「仕訳外部データ取込」処理を改修せずバッチ実行する。
D171: 以下のようなケースでは、標準の取込処理にも改修が必要となるため、別途対応工数を見積もることとする。
E172: ① | F172: 禁止文字の置き換え、エスケープ文字の考慮が取込処理側で必要となる。（文字を置き換えした上で取込処理が必要となる。）
C174: ９) | D174: 以下のProActiveC4禁止文字は連動ファイルにて使用しない前提とする。
E176: 禁止文字 | J176: 名称
E177: ― | J177: ダッシュ（全角）
E178: ∥ | J178: 双柱
E179: ￤ | J179: 破断線
C184: １０) | D184: ProActiveC4へ連動するファイルはコマンドにて移動等の操作を実施するため、ファイル名には空白を使用しない前提とする。
C186: １１) | D186: 取込処理後、処理済用ファイルのディレクトリに移動された取込用のCSVファイルは「エラー終了検知バッチ」実行後に削除する想定とする。
D187: （削除処理は、当機能とは別にファイル削除処理を作成して、その処理で実施する）
B190: 【主な取り扱い情報】
C191: ①バッチ実行時
D192: № | E192: 取り扱う情報 | O192: I/O | Q192: 用途
D193: 1 | E193: 仕訳データ | O193: OUT | Q193: 仕訳データを登録する。
D194: ２ | E194: バッチジョブ | O194: OUT | Q194: バッチ実行結果を反映する。
D195: ３ | E195: バッチジョブエラー | O195: OUT | Q195: バッチ実行結果を反映する。

Sheet 画面遷移図
A1: ドキュメント名 | L1: サブシステム | Q1: 業務機能名 | AJ1: 作成者 | AO1: =表紙!D51 -> SCSK大西 | AT1: 更新者 | AY1: SCSK相坂
A2: 業務機能概要書 | G2: 画面遷移図 | L2: =#REF! -> #REF! | Q2: =#REF! -> #REF! | AJ2: 作成日付 | AO2: =表紙!C51 -> 45898 | AT2: 更新日付 | AY2: 44103
B4: 【メニュー起動時の画面遷移】

Sheet 画面レイアウト
A1: ドキュメント名 | AH1: サブシステム | AX1: 業務機能名 | DF1: 作成者 | DV1: =表紙!D51 -> SCSK大西 | EL1: 更新者
A2: 業務機能概要書 | R2: 画面レイアウト | AH2: =#REF! -> #REF! | AX2: =#REF! -> #REF! | DF2: 作成日付 | DV2: =表紙!C51 -> 45898 | EL2: 更新日付
A3: 画面名 | FD3: 画面№ | FM3: ①
B4: 0 | H4: 40 | R4: 110 | AB4: 180 | AL4: 250 | AV4: 320 | BF4: 390 | BP4: 460 | BZ4: 530 | CJ4: 600 | CT4: 670 | DD4: 740 | DN4: 810 | DX4: 880 | EH4: 950 | EO4: 999 | ER4: ＜補足説明＞
A5: 0
A6: 5
A7: 20
A8: 35
A9: 50
A10: 65
A11: 80
A12: 95
A13: 110
A14: 125
A15: 140
A16: 155
... A47: 620
A57: 画面名 | J57: 自動消込確定情報登録画面 | FD57: 画面№ | FM57: ②
B58: 0 | H58: 40 | R58: 110 | AB58: 180 | AL58: 250 | AV58: 320 | BF58: 390 | BP58: 460 | BZ58: 530 | CJ58: 600 | CT58: 670 | DD58: 740 | DN58: 810 | DX58: 880 | EH58: 950 | EO58: 999 | ER58: ＜補足説明＞
A59: 0
A60: 5
A61: 20
A62: 35
A63: 50
A64: 65
A65: 80
A66: 95
A67: 110
A68: 125
A69: 140
A70: 155
... A101: 620
A111: 画面名 | FD111: 画面№ | FM111: ①
B112: 0 | H112: 40 | R112: 110 | AB112: 180 | AL112: 250 | AV112: 320 | BF112: 390 | BP112: 460 | BZ112: 530 | CJ112: 600 | CT112: 670 | DD112: 740 | DN112: 810 | DX112: 880 | EH112: 950 | EO112: 999 | ER112: ＜補足説明＞
A113: 0
A114: 5
A115: 20
A116: 35
A117: 50
A118: 65
A119: 80
A120: 95
A121: 110
A122: 125
A123: 140
A124: 155
... A155: 620
A165: 画面名 | FD165: 画面№ | FM165: ①
B166: 0 | H166: 40 | R166: 110 | AB166: 180 | AL166: 250 | AV166: 320 | BF166: 390 | BP166: 460 | BZ166: 530 | CJ166: 600 | CT166: 670 | DD166: 740 | DN166: 810 | DX166: 880 | EH166: 950 | EO166: 999 | ER166: ＜補足説明＞
A167: 0
A168: 5
A169: 20
A170: 35
A171: 50
A172: 65
A173: 80
A174: 95
A175: 110
A176: 125
A177: 140
A178: 155
... A209: 620
C221: 出力されるCSVファイル例

Sheet 項目概要
A1: ドキュメント名 | L1: サブシステム | Q1: 業務機能名 | AJ1: 作成者 | AO1: =表紙!D51 -> SCSK大西 | AT1: 更新者 | BE1: ○ | BF1: IN | BG1: 文字列
A2: 業務機能概要書 | G2: 項目概要 | L2: =#REF! -> #REF! | Q2: =#REF! -> #REF! | AJ2: 作成日付 | AO2: =表紙!C51 -> 45898 | AT2: 更新日付 | BE2: － | BF2: OUT | BG2: 数値
BF3: IN/OUT | BG3: 半英数
A4: 【画面項目説明】 | BG4: 半カナ
BG5: コード
B6: [①自動消込確定情報登録画面] | AQ6: ※追加及び変更項目のみ記載 | BG6: 日付
B7: № | C7: ラベル | J7: 項目名 | Q7: I/O | S7: 必須 | U7: 型 | W7: 桁数 | Y7: ソート | AA7: 初期表示 | AE7: 備考 | BG7: －
B8: 【ヘッダ部】
B9: 1 | C9: 一覧を最大化 | J9: 一覧を最大化ボタン | Q9: IN | S9: － | U9: － | W9: － | Y9: ー | AA9: ー
B10: 2 | Q10: IN | S10: ○ | U10: 日付 | W10: 8 | Y10: ー | AA10: システム日付
B11: 3 | Q11: OUT | S11: － | U11: コード | W11: 12 | Y11: ー | AA11: ー
B12: 4 | Q12: IN | S12: ○ | U12: コード | W12: 10 | Y12: ー | AA12: ー
Q13: IN | S13: － | U13: － | W13: ー | Y13: ー | AA13: ー
Q14: OUT | S14: － | U14: 文字列 | W14: 20 | Y14: ー | AA14: ー
B15: 5 | Q15: IN | S15: ○ | U15: コード | W15: 15 | Y15: ー | AA15: ー
Q16: IN | S16: － | U16: － | W16: ー | Y16: ー | AA16: ー
Q17: OUT | S17: － | U17: 文字列 | W17: 20 | Y17: ー | AA17: ー
B18: 6 | Q18: IN | S18: ○ | U18: － | W18: ー | Y18: ー
B20: 7 | Q20: IN | S20: ○ | U20: 数値 | W20: 13 | Y20: ー | AA20: ー
B21: 【】
B22: 1
B25: 2
B28: 3
B30: 4
B31: 5
B32: 【】 | AE32: ※ソート順は画面レイアウトシートの補足説明欄参照。
B33: 1
B34: 2
B35: 2
B36: 3
B37: 2
B38: 3
B39: 4
B40: 5
B41: 6
B42: 7
B43: 8
B44: 9
... B52: 16
B53: 【フッタ部】
B54: 1
B55: 2
B57: 3
B58: 4
B59: 5
B60: 6
B61: 7
B62: 8
B63: 9
B64: 10

Sheet イベント概要
A1: ドキュメント名 | L1: サブシステム | Q1: 業務機能名 | AJ1: 作成者 | AO1: =表紙!D51 -> SCSK大西 | AT1: 更新者
A2: 業務機能概要書 | G2: イベント概要 | L2: =業務機能概要!L2 -> 財務会計 | Q2: =業務機能概要!Q2 -> 仕訳データ自動取込 | AJ2: 作成日付 | AO2: =表紙!C51 -> 45898 | AT2: 更新日付
A4: 【イベント処理】
B6: № | C6: イベント名 | J6: 処理説明
B7: =IF(C7="","",MAX(B$6:B6)+1) -> 1 | C7: 仕訳データ自動取込 | J7: １. | L7: 取込ディレクトリに配置された取込用のCSVファイルをINPUTとし、ProActiveC4標準機能の「仕訳外部データ取込」を実行する。
C8: バッチイベント | L8: ＜パラメータ＞
L9: ・ | M9: 会社コード | U9: ： | V9: バッチ実行用のxmlで指定された会社コード
L10: ・ | M10: 取込CSVファイル | U10: ： | V10: バッチ実行用のxmlで指定されたファイル
L12: 取込用のCSVファイルが取得できなかった場合は、取込処理は実行されない。
B13: =IF(C13="","",MAX(B$6:B6)+1) | L13: 取込用のCSVファイルが取得できた場合は、後続の処理を継続する。
B14: =IF(C14="","",MAX(B$6:B13)+1) | L14: ※ | M14: 上記のファイル取得、エラーハンドリングはバッチファイルで実施する（アプリケーションでの考慮は不要）
B15: =IF(C15="","",MAX(B$6:B14)+1) | L15: ※ | M15: 取込用CSVのファイルサイズが0byteの場合は、正常として処理終了する。（バッチファイルにてファイルを正常処理フォルダへ移動する）
B16: =IF(C16="","",MAX(B$6:B15)+1)
B17: =IF(C17="","",MAX(B$6:B16)+1) | J17: ２. | L17: 「仕訳外部データ取込」のバッチ処理実行結果をバッチジョブ情報に登録する。（標準仕様に準じる）
B18: =IF(C18="","",MAX(B$6:B13)+1)
B19: =IF(C19="","",MAX(B$6:B8)+1) | J19: ３. | L19: 取込処理後、取込用のCSVファイルは処理済用ファイルのディレクトリに移動する。
B20: =IF(C20="","",MAX(B$6:B19)+1) | L20: ※ | M20: 正常用、エラー用のディレクトリを作成して、処理結果によって移動先ディレクトリを分岐させる。
B21: =IF(C21="","",MAX(B$6:B20)+1)
B22: =IF(C22="","",MAX(B$6:B21)+1) | J22: ４. | L22: バッチ処理実行結果の終了情報をタスクスケジューラに返却する。
B23: =IF(C23="","",MAX(B$6:B22)+1) | L23: ■ | M23: 正常終了できた場合
N24: 「0:正常終了」
L25: ■ | M25: エラーが発生した場合（※ProActiveC4標準機能のデータ取込でエラーが発生した場合は当ケースに該当する）
N26: 「1:異常終了」
B27: =IF(C27="","",MAX(B$6:B26)+1)
B28: =IF(C28="","",MAX(B$6:B27)+1)
B30: =IF(C30="","",MAX(B$6:B29)+1)
B31: =IF(C31="","",MAX(B$6:B30)+1)
B32: =IF(C32="","",MAX(B$6:B31)+1)
B33: =IF(C33="","",MAX(B$6:B32)+1)
B40: =IF(C40="","",MAX(B$6:B39)+1)
B41: =IF(C41="","",MAX(B$6:B40)+1)
B42: =IF(C42="","",MAX(B$6:B41)+1)
B43: =IF(C43="","",MAX(B$6:B42)+1)
B44: =IF(C44="","",MAX(B$6:B43)+1)
B45: =IF(C45="","",MAX(B$6:B44)+1)

Sheet チェック仕様
A1: ドキュメント名 | L1: サブシステム | Q1: 業務機能名 | AJ1: 作成者 | AO1: =表紙!D51 -> SCSK大西 | AT1: 更新者
A2: 業務機能概要書 | G2: チェック仕様 | L2: =#REF! -> #REF! | Q2: =#REF! -> #REF! | AJ2: 作成日付 | AO2: =表紙!C51 -> 45898 | AT2: 更新日付
A4: 【チェック処理】
B6: １．初期処理時
B7: № | C7: 項目名 | L7: 条件必須 | O7: 存在 | R7: 範囲 | U7: 関連 | X7: その他 | AA7: 内容
B8: =IF(C8="","",MAX(B7:B$7)+1) -> 1 | C8: － | X8: ○
B9: =IF(C9="","",MAX(B$7:B8)+1)
B10: =IF(C10="","",MAX(B$7:B9)+1)
B11: =IF(C11="","",MAX(B$7:B10)+1)
B13: ２．検索ボタン押下時
B14: № | C14: 項目名 | L14: 条件必須 | O14: 存在 | R14: 範囲 | U14: 関連 | X14: その他 | AA14: 内容
B15: =IF(C15="","",MAX(B$14:B14)+1)
B16: =IF(C16="","",MAX(B$14:B15)+1)
B17: =IF(C17="","",MAX(B$14:B16)+1)
B18: =IF(C18="","",MAX(B$14:B17)+1)
B19: =IF(C19="","",MAX(B$14:B18)+1)
B20: =IF(C20="","",MAX(B$14:B19)+1)
B21: =IF(C21="","",MAX(B$14:B20)+1)
B22: =IF(C22="","",MAX(B$14:B21)+1)
B23: =IF(C23="","",MAX(B$14:B22)+1)
B24: =IF(C24="","",MAX(B$14:B23)+1)
B25: =IF(C25="","",MAX(B$14:B24)+1)
B26: =IF(C26="","",MAX(B$14:B25)+1)
... B31: =IF(C31="","",MAX(B$14:B30)+1)
B33: ３．データ取込ボタン
B34: № | C34: 項目名 | L34: 条件必須 | O34: 存在 | R34: 範囲 | U34: 関連 | X34: その他 | AA34: 内容
B35: =IF(C35="","",MAX(B$34:B34)+1)
B36: =IF(C36="","",MAX(B$34:B35)+1)
B37: =IF(C37="","",MAX(B$34:B36)+1)
B38: =IF(C38="","",MAX(B$34:B37)+1)
B39: =IF(C39="","",MAX(B$34:B38)+1)
B40: =IF(C40="","",MAX(B$34:B39)+1)
B41: =IF(C41="","",MAX(B$34:B40)+1)
B42: =IF(C42="","",MAX(B$34:B41)+1)
B43: =IF(C43="","",MAX(B$34:B42)+1)
B44: =IF(C44="","",MAX(B$34:B40)+1)
B45: =IF(C45="","",MAX(B$34:B44)+1)
B46: =IF(C46="","",MAX(B$34:B45)+1)
B47: 4
B48: =IF(C48="","",MAX(B$34:B47)+1)
B49: 4
B50: =IF(C50="","",MAX(B$34:B49)+1)
B51: =IF(C51="","",MAX(B48:B$60)+1)
B52: =IF(C52="","",MAX(B46:B$60)+1)
B53: =IF(C53="","",MAX(B47:B$60)+1)
B54: =IF(C54="","",MAX(B48:B$60)+1)
B55: =IF(C55="","",MAX(B51:B$60)+1)
B56: =IF(C56="","",MAX(B$7:B51)+1)
B57: =IF(C57="","",MAX(B$34:B48)+1)
B59: ４．登録ボタン
B60: № | C60: 項目名 | L60: 条件必須 | O60: 存在 | R60: 範囲 | U60: 関連 | X60: その他 | AA60: 内容
B62: =IF(C62="","",MAX(B$60:B61)+1)
B63: =IF(C63="","",MAX(B$60:B62)+1)
B64: =IF(C64="","",MAX(B$60:B63)+1)
B65: =IF(C65="","",MAX(B$60:B64)+1)
B66: =IF(C66="","",MAX(B$60:B65)+1)
B67: =IF(C67="","",MAX(B$60:B66)+1)
B68: =IF(C68="","",MAX(B$60:B67)+1)
B69: =IF(C69="","",MAX(B$60:B68)+1)
B70: =IF(C70="","",MAX(B$60:B69)+1)
B71: =IF(C71="","",MAX(B$60:B70)+1)
B72: =IF(C72="","",MAX(B$60:B71)+1)
B73: =IF(C73="","",MAX(B$60:B72)+1)
... B92: =IF(C92="","",MAX(B$60:B91)+1)

Sheet 出力CSV定義
A1: ドキュメント名 | E1: サブシステム | G1: 業務機能名 | P1: 作成者 | R1: =表紙!D51 -> SCSK大西 | T1: 更新者
A2: 業務機能概要書 | C2: 出力CSV定義 | E2: =#REF! -> #REF! | G2: =#REF! -> #REF! | P2: 作成日 | R2: =表紙!C51 -> 45898 | T2: 更新日
A4: データ名 | I4: ヘッダ行 | K4: あり | M4: なし | N4: ダブルクォーテーション | Q4: あり | S4: なし | X4: 文字列
A5: ﾌｧｲﾙ形式・ﾚｺｰﾄﾞ長 | D5: 固定長（ | G5: Byte） | I5: 可変長（区切り文字［ ，(カンマ) ］） | M5: バイナリデータ | P5: その他（ ） | X5: 半英数
A6: 文字コード | D6: UNI（Win系） | F6: EBCDIC(K) | I6: その他（UTF-8） | M6: 改行コード | O6: LF(UNIX系) | Q6: CRLF(Win系) | T6: なし | X6: 半カナ
A7: 全角(2byte)文字項目 | D7: あり | F7: なし | M7: 数値編集 | O7: 左詰め | Q7: 右詰め［ゼロ埋め］ | T7: 右詰め［スペース埋め］ | X7: コード
A8: 特記事項 | C8: 出力順：起票日付、仕訳伝票番号、仕訳自動作成フラグ、仕訳伝票行番号 | J8: ※「"」が含まれる項目は「""」に変換する。 | X8: 数値
A9: No. | B9: 項目名 | E9: 必須 | F9: 型 | G9: 桁数 | H9: 開始位置 | I9: 備考 | X9: 日付
H10: /列 | X10: 時間
A11: 1 | F11: 日付 | G11: 8 | H11: A | X11: 年月
A12: 2 | F12: 半英数 | G12: 12 | H12: B | X12: 区分
A13: 3 | F13: コード | G13: 10 | H13: C | X13: フラグ
A14: 4 | F14: 文字列 | G14: 40 | H14: D | X14: -
A15: 5
A16: 6
A17: 7
A18: 8
A19: 9
A20: 10
A21: 11
A22: 12
A23: 13
A24: 14
A25: 15

Sheet 出力CSVサンプル

Sheet 取込フォーマット定義
A1: ドキュメント名 | E1: サブシステム | G1: 業務機能名 | P1: 作成者 | R1: SCSK大西 | T1: 更新者
A2: 業務機能概要書 | C2: 取込フォーマット定義 | E2: 財務会計 | G2: 仕訳データ自動取込 | P2: 作成日 | R2: =表紙!C51 -> 45898 | T2: 更新日
A4: データ名 | C4: 仕訳データ | I4: ヘッダ行 | K4: あり | M4: なし | N4: ダブルクォーテーション | Q4: あり | S4: なし | X4: 文字列
A5: ﾌｧｲﾙ形式・ﾚｺｰﾄﾞ長 | D5: 固定長（ | G5: Byte） | I5: 可変長（区切り文字［ ，(カンマ) ］） | M5: バイナリデータ | P5: その他（ ） | X5: 半英数
A6: 文字コード | D6: UNI（Win系） | F6: EBCDIC(K) | I6: その他（ UTF-8） | M6: 改行コード | O6: LF(UNIX系) | Q6: CRLF(Win系) | T6: なし | X6: 半カナ
A7: 全角(2byte)文字項目 | D7: あり | F7: なし | M7: 数値編集 | O7: 左詰め | Q7: 右詰め［ゼロ埋め］ | T7: 右詰め［スペース埋め］ | X7: コード
A8: 特記事項 | X8: 数値
A9: No. | B9: 項目名 | E9: 必須 | F9: 型 | G9: 桁数 | H9: 開始位置 | I9: 項目説明 | Q9: 設定値 | X9: 日付
H10: /列 | X10: 時間
A11: =MAX($A$10:$A10)+1 -> 1 | B11: 元帳領域コード | F11: コード | G11: 2 | H11: =SUBSTITUTE(SUBSTITUTE(ADDRESS(1,A11),"$1",""),"$","") -> A | I11: 仕訳の種類を判別するためのコード | Q11: 仕訳ヘッダ.仕訳種類コード | X11: 年月
I12: （01.一般仕訳、02.月次修正仕訳、03.管理会計仕訳、04.売上高・売上原価仕訳、05.組替仕訳）
A13: =MAX($A$10:$A11)+1 -> 2 | B13: 仕訳伝票番号 | E13: △ | F13: 文字列 | G13: 12 | H13: =SUBSTITUTE(SUBSTITUTE(ADDRESS(1,A13),"$1",""),"$","") -> B | I13: 仕訳伝票番号。ProActiveC4上一意の番号とする必要がある。 | Q13: 仕訳ヘッダ.仕訳番号 | X13: 区分
A14: =MAX($A$10:$A13)+1 -> 3 | B14: 仕訳伝票起票日付 | E14: 〇 | F14: 日付 | G14: 8 | H14: =SUBSTITUTE(SUBSTITUTE(ADDRESS(1,A14),"$1",""),"$","") -> C | I14: 経理日 | Q14: 仕訳ヘッダ.経理日
A15: =MAX($A$10:$A14)+1 -> 4 | B15: 起票部門表示コード | E15: 〇 | F15: コード | G15: 10 | H15: =SUBSTITUTE(SUBSTITUTE(ADDRESS(1,A15),"$1",""),"$","") -> D | I15: 伝票起票した部署のコード | Q15: 事業所コード＋ 所属に紐づく業種コードの一番若いコード ＋ 所属コード
A16: =MAX($A$10:$A15)+1 -> 5 | B16: 仕訳円貨区分 | E16: 〇 | F16: 区分 | G16: 1 | H16: =SUBSTITUTE(SUBSTITUTE(ADDRESS(1,A16),"$1",""),"$","") -> E | I16: 外貨建ての伝票か円貨の伝票かの区分（1.円貨、2.外貨） | Q16: 1（円貨）
A17: =MAX($A$10:$A16)+1 -> 6 | B17: 起票者コード | E17: 〇 | F17: コード | G17: 15 | H17: =SUBSTITUTE(SUBSTITUTE(ADDRESS(1,A17),"$1",""),"$","") -> F | I17: 仕訳伝票を起票したユーザーID | Q17: 999999999999999（ダミー）
A18: =MAX($A$10:$A17)+1 -> 7 | B18: 決算仕訳フラグ | E18: 〇 | F18: フラグ | G18: 1 | H18: =SUBSTITUTE(SUBSTITUTE(ADDRESS(1,A18),"$1",""),"$","") -> G | I18: 決算仕訳か否かのフラグ（0.通常仕訳、1.決算仕訳） | Q18: 0（通常仕訳）
A19: =MAX($A$10:$A18)+1 -> 8 | B19: 仕訳伝票摘要 | F19: 文字列 | G19: 80 | H19: =SUBSTITUTE(SUBSTITUTE(ADDRESS(1,A19),"$1",""),"$","") -> H | Q19: 仕訳ヘッダ.仕訳摘要
A20: =MAX($A$10:$A19)+1 -> 9 | B20: 洗替実施区分 | F20: 区分 | G20: 1 | H20: =SUBSTITUTE(SUBSTITUTE(ADDRESS(1,A20),"$1",""),"$","") -> I | I20: 9.不要 | Q20: 9（不要）
A21: =MAX($A$10:$A20)+1 -> 10 | B21: 洗替伝票起票日付 | E21: △ | F21: 日付 | G21: 8 | H21: =SUBSTITUTE(SUBSTITUTE(ADDRESS(1,A21),"$1",""),"$","") -> J | I21: 空白（設定不要） | Q21: 設定なし
A22: =MAX($A$10:$A21)+1 -> 11 | B22: 仕訳伝票行番号 | E22: 〇 | F22: 数値 | G22: 4 | H22: =SUBSTITUTE(SUBSTITUTE(ADDRESS(1,A22),"$1",""),"$","") -> K | I22: 仕訳伝票明細の行番号 | Q22: 連動時に仕訳伝票単位で採番
A23: =MAX($A$10:$A22)+1 -> 12 | B23: 仕訳伝票明細摘要 | F23: 文字列 | G23: 80 | H23: =SUBSTITUTE(SUBSTITUTE(ADDRESS(1,A23),"$1",""),"$","") -> L | Q23: 仕訳ヘッダ.仕訳摘要
A24: =MAX($A$10:$A23)+1 -> 13 | B24: 勘定科目コード（借方） | F24: コード | G24: 8 | H24: =SUBSTITUTE(SUBSTITUTE(ADDRESS(1,A24),"$1",""),"$","") -> M | Q24: 仕訳明細.勘定科目コード＋目節科目コード
A25: =MAX($A$10:$A24)+1 -> 14 | B25: 補助科目コード（借方） | E25: △ | F25: コード | G25: 4 | H25: =SUBSTITUTE(SUBSTITUTE(ADDRESS(1,A25),"$1",""),"$","") -> N | I25: 科目摘要を判別するコード | Q25: 仕訳明細.科目摘要コード
A26: =MAX($A$10:$A25)+1 -> 15 | B26: 計上部門表示コード（借方） | F26: コード | G26: 10 | H26: =SUBSTITUTE(SUBSTITUTE(ADDRESS(1,A26),"$1",""),"$","") -> O | I26: 借方科目残を計上する部署のコード | Q26: 仕訳明細.業種+予算組織コード
A27: =MAX($A$10:$A26)+1 -> 16 | B27: 取引先コード（借方） | E27: △ | F27: コード | G27: 15 | H27: =SUBSTITUTE(SUBSTITUTE(ADDRESS(1,A27),"$1",""),"$","") -> P | I27: ※借方科目を取引先計上する場合、必須 | Q27: 仕訳明細.取引先コード
A28: =MAX($A$10:$A27)+1 -> 17 | B28: 自社口座コード（借方） | E28: △ | F28: コード | G28: 8 | H28: =SUBSTITUTE(SUBSTITUTE(ADDRESS(1,A28),"$1",""),"$","") -> Q | I28: 出金を行う銀行口座のコード ※借方科目を口座別計上する場合、必須 | Q28: 仕訳明細.自社口座コード
A29: =MAX($A$10:$A28)+1 -> 18 | B29: プロジェクトコード（借方） | E29: △ | F29: コード | G29: 20 | H29: =SUBSTITUTE(SUBSTITUTE(ADDRESS(1,A29),"$1",""),"$","") -> R | I29: 業種を判別するコード ※借方科目を業種別計上する場合、必須 | Q29: 仕訳明細.業種コード
A30: =MAX($A$10:$A29)+1 -> 19 | B30: 担当者コード（借方） | E30: △ | F30: コード | G30: 15 | H30: =SUBSTITUTE(SUBSTITUTE(ADDRESS(1,A30),"$1",""),"$","") -> S | I30: 空白（設定不要） | Q30: 設定なし
A31: =MAX($A$10:$A30)+1 -> 20 | B31: セグメントコード（借方） | E31: △ | F31: コード | G31: 4 | H31: =SUBSTITUTE(SUBSTITUTE(ADDRESS(1,A31),"$1",""),"$","") -> T | I31: 会計品目を判別するコード ※借方科目を会計品目別計上する場合、必須 | Q31: 仕訳明細.会計情報品目コード
A32: =MAX($A$10:$A31)+1 -> 21 | B32: セグメントコード１（借方） | E32: △ | F32: コード | G32: 4 | H32: =SUBSTITUTE(SUBSTITUTE(ADDRESS(1,A32),"$1",""),"$","") -> U | I32: 空白（設定不要） | Q32: 設定なし
A33: =MAX($A$10:$A32)+1 -> 22 | B33: セグメントコード２（借方） | E33: △ | F33: コード | G33: 4 | H33: =SUBSTITUTE(SUBSTITUTE(ADDRESS(1,A33),"$1",""),"$","") -> V | I33: 空白（設定不要） | Q33: 設定なし
A34: =MAX($A$10:$A33)+1 -> 23 | B34: セグメントコード３（借方） | E34: △ | F34: コード | G34: 4 | H34: =SUBSTITUTE(SUBSTITUTE(ADDRESS(1,A34),"$1",""),"$","") -> W | I34: 空白（設定不要） | Q34: 設定なし
A35: =MAX($A$10:$A34)+1 -> 24 | B35: セグメントコード４（借方） | E35: △ | F35: コード | G35: 4 | H35: =SUBSTITUTE(SUBSTITUTE(ADDRESS(1,A35),"$1",""),"$","") -> X | I35: 空白（設定不要） | Q35: 設定なし
A36: =MAX($A$10:$A35)+1 -> 25 | B36: セグメントコード５（借方） | E36: △ | F36: コード | G36: 4 | H36: =SUBSTITUTE(SUBSTITUTE(ADDRESS(1,A36),"$1",""),"$","") -> Y | I36: 空白（設定不要） | Q36: 設定なし
A37: =MAX($A$10:$A36)+1 -> 26 | B37: 仕訳伝票明細金額（借方） | E37: 〇 | F37: 数値 | G37: 13 | H37: =SUBSTITUTE(SUBSTITUTE(ADDRESS(1,A37),"$1",""),"$","") -> Z | Q37: 仕訳明細.借方金額
A38: =MAX($A$10:$A37)+1 -> 27 | B38: 消費税額（借方） | F38: 数値 | G38: 13 | H38: =SUBSTITUTE(SUBSTITUTE(ADDRESS(1,A38),"$1",""),"$","") -> AA | Q38: （消費税発生元科目に一致する場合、消費税行の）仕訳明細.借方金額
A39: =MAX($A$10:$A38)+1 -> 28 | B39: 消費税区分（借方） | F39: 区分 | G39: 2 | H39: =SUBSTITUTE(SUBSTITUTE(ADDRESS(1,A39),"$1",""),"$","") -> AB | Q39: 仕訳明細.消費税取引区分（PA向けの変換処理あり）
A40: =MAX($A$10:$A39)+1 -> 29 | B40: 消費税計算区分（借方） | F40: 区分 | G40: 1 | H40: =SUBSTITUTE(SUBSTITUTE(ADDRESS(1,A40),"$1",""),"$","") -> AC | I40: 3.計算しない | Q40: 3（計算しない）
A41: =MAX($A$10:$A40)+1 -> 30 | B41: 調整計上フラグ | E41: △ | F41: フラグ | G41: 1 | H41: =SUBSTITUTE(SUBSTITUTE(ADDRESS(1,A41),"$1",""),"$","") -> AD | I41: 空白（設定不要） | Q41: 設定なし
A42: =MAX($A$10:$A41)+1 -> 31 | B42: 通貨コード | E42: △ | F42: コード | G42: 3 | H42: =SUBSTITUTE(SUBSTITUTE(ADDRESS(1,A42),"$1",""),"$","") -> AE | I42: 空白（設定不要） | Q42: 設定なし
A43: =MAX($A$10:$A42)+1 -> 32 | B43: 為替レート | F43: 数値 | G43: 8 | H43: =SUBSTITUTE(SUBSTITUTE(ADDRESS(1,A43),"$1",""),"$","") -> AF | I43: 空白（設定不要） | Q43: 設定なし
A44: =MAX($A$10:$A43)+1 -> 33 | B44: 為替予約フラグ | E44: △ | F44: フラグ | G44: 1 | H44: =SUBSTITUTE(SUBSTITUTE(ADDRESS(1,A44),"$1",""),"$","") -> AG | I44: 空白（設定不要） | Q44: 設定なし
A45: =MAX($A$10:$A44)+1 -> 34 | B45: 仕訳伝票明細金額（外貨）（借方） | E45: △ | F45: 数値 | G45: 15 | H45: =SUBSTITUTE(SUBSTITUTE(ADDRESS(1,A45),"$1",""),"$","") -> AH | I45: 空白（設定不要） | Q45: 設定なし
A46: =MAX($A$10:$A45)+1 -> 35 | B46: CF勘定科目内訳コード（借方） | F46: コード | G46: 2 | H46: =SUBSTITUTE(SUBSTITUTE(ADDRESS(1,A46),"$1",""),"$","") -> AI | I46: 借方科目の科目残発生理由を識別するコード（CF勘定科目内訳が必要な勘定科目の場合は必須） | Q46: 仕訳明細.CF勘定科目内訳コード
A47: =MAX($A$10:$A46)+1 -> 36 | B47: 資金繰科目コード（借方） | F47: コード | G47: 5 | H47: =SUBSTITUTE(SUBSTITUTE(ADDRESS(1,A47),"$1",""),"$","") -> AJ | I47: 借方科目の資金繰科目を特定するコード | Q47: 設定なし
A48: =MAX($A$10:$A47)+1 -> 37 | B48: 備忘フラグ（借方） | F48: フラグ | G48: 1 | H48: =SUBSTITUTE(SUBSTITUTE(ADDRESS(1,A48),"$1",""),"$","") -> AK | I48: 借方備忘摘要を入力するか否かのフラグ（0.チェックなし、1.チェック有） ※未設定の場合、0.チェックなし | Q48: 設定なし
A49: =MAX($A$10:$A48)+1 -> 38 | B49: 備忘摘要（借方） | F49: 文字列 | G49: 50 | H49: =SUBSTITUTE(SUBSTITUTE(ADDRESS(1,A49),"$1",""),"$","") -> AL | I49: 任意情報用項目（総勘定元帳に出力されないが、仕訳伝票明細データ出力（大量データ出力）で出力可） | Q49: 設定なし
A50: =MAX($A$10:$A49)+1 -> 39 | B50: システム連動項目１（借方） | F50: 文字列 | G50: 20 | H50: =SUBSTITUTE(SUBSTITUTE(ADDRESS(1,A50),"$1",""),"$","") -> AM | I50: システム連動項目（設定不要）※PA内でのデータ追跡用項目 | Q50: 設定なし
A51: =MAX($A$10:$A50)+1 -> 40 | B51: システム連動項目２（借方） | F51: 文字列 | G51: 20 | H51: =SUBSTITUTE(SUBSTITUTE(ADDRESS(1,A51),"$1",""),"$","") -> AN | I51: 任意情報用項目（総勘定元帳に出力される） ※PAのGL、AP（ホクレン様使用機能）では使用しないが、FAでは使用される | Q51: 設定なし
A52: =MAX($A$10:$A51)+1 -> 41 | B52: システム連動項目３（借方） | F52: 文字列 | G52: 20 | H52: =SUBSTITUTE(SUBSTITUTE(ADDRESS(1,A52),"$1",""),"$","") -> AO | I52: 任意情報用項目（総勘定元帳に出力される） | Q52: 仕訳明細.諸口取引先名称カナ
A53: =MAX($A$10:$A52)+1 -> 42 | B53: 仕訳予備項目１（文字列）（借方） | F53: 文字列 | G53: 50 | H53: =SUBSTITUTE(SUBSTITUTE(ADDRESS(1,A53),"$1",""),"$","") -> AP | I53: 任意情報用項目（総勘定元帳に出力されないが、仕訳伝票明細データ出力（大量データ出力）で出力可） | Q53: 仕訳ヘッダ.発生元システム取引番号
A54: =MAX($A$10:$A53)+1 -> 43 | B54: 仕訳予備項目２（文字列）（借方） | F54: 文字列 | G54: 50 | H54: =SUBSTITUTE(SUBSTITUTE(ADDRESS(1,A54),"$1",""),"$","") -> AQ | I54: 任意情報用項目（総勘定元帳に出力されないが、仕訳伝票明細データ出力（大量データ出力）で出力可） | Q54: 取扱区分（連結決算データで売上高の対象データを判別する、消費税繰延調書出力でも使用する）
A55: =MAX($A$10:$A54)+1 -> 44 | B55: 仕訳予備項目３（文字列）（借方） | F55: 文字列 | G55: 50 | H55: =SUBSTITUTE(SUBSTITUTE(ADDRESS(1,A55),"$1",""),"$","") -> AR | I55: 任意情報用項目（総勘定元帳に出力されないが、仕訳伝票明細データ出力（大量データ出力）で出力可） | Q55: 科目摘要補足（自由入力項目）
A56: =MAX($A$10:$A55)+1 -> 45 | B56: 仕訳予備項目１（数字）（借方） | F56: 数値 | G56: 17 | H56: =SUBSTITUTE(SUBSTITUTE(ADDRESS(1,A56),"$1",""),"$","") -> AS | I56: 任意情報用項目（総勘定元帳に出力されないが、仕訳伝票明細データ出力（大量データ出力）で出力可） | Q56: 仕訳ヘッダ.取引日（消費税繰延調書出力で使用する）
A57: =MAX($A$10:$A56)+1 -> 46 | B57: 仕訳予備項目２（数字）（借方） | F57: 数値 | G57: 17 | H57: =SUBSTITUTE(SUBSTITUTE(ADDRESS(1,A57),"$1",""),"$","") -> AT | I57: 任意情報用項目（総勘定元帳に出力されないが、仕訳伝票明細データ出力（大量データ出力）で出力可） | Q57: 設定なし
A58: =MAX($A$10:$A57)+1 -> 47 | B58: 仕訳予備項目３（数字）（借方） | F58: 数値 | G58: 17 | H58: =SUBSTITUTE(SUBSTITUTE(ADDRESS(1,A58),"$1",""),"$","") -> AU | I58: 任意情報用項目（総勘定元帳に出力されないが、仕訳伝票明細データ出力（大量データ出力）で出力可） | Q58: 設定なし
A59: =MAX($A$10:$A58)+1 -> 48 | B59: 勘定科目コード（貸方） | F59: コード | G59: 8 | H59: =SUBSTITUTE(SUBSTITUTE(ADDRESS(1,A59),"$1",""),"$","") -> AV | Q59: 仕訳明細.勘定科目コード＋目節科目コード
A60: =MAX($A$10:$A59)+1 -> 49 | B60: 補助科目コード（貸方） | E60: △ | F60: コード | G60: 4 | H60: =SUBSTITUTE(SUBSTITUTE(ADDRESS(1,A60),"$1",""),"$","") -> AW | I60: 科目摘要を判別するコード | Q60: 仕訳明細.科目摘要コード
A61: =MAX($A$10:$A60)+1 -> 50 | B61: 計上部門表示コード（貸方） | F61: コード | G61: 10 | H61: =SUBSTITUTE(SUBSTITUTE(ADDRESS(1,A61),"$1",""),"$","") -> AX | I61: 貸方科目残を計上する部署のコード | Q61: 仕訳明細.業種+予算組織コード
A62: =MAX($A$10:$A61)+1 -> 51 | B62: 取引先コード（貸方） | E62: △ | F62: コード | G62: 15 | H62: =SUBSTITUTE(SUBSTITUTE(ADDRESS(1,A62),"$1",""),"$","") -> AY | I62: 貸方科目を取引先計上する場合、必須 | Q62: 仕訳明細.取引先コード
A63: =MAX($A$10:$A62)+1 -> 52 | B63: 自社口座コード（貸方） | E63: △ | F63: コード | G63: 8 | H63: =SUBSTITUTE(SUBSTITUTE(ADDRESS(1,A63),"$1",""),"$","") -> AZ | I63: 出金を行う銀行口座のコード ※貸方科目を口座別計上する場合、必須 | Q63: 仕訳明細.自社口座コード
A64: =MAX($A$10:$A63)+1 -> 53 | B64: プロジェクトコード（貸方） | E64: △ | F64: コード | G64: 20 | H64: =SUBSTITUTE(SUBSTITUTE(ADDRESS(1,A64),"$1",""),"$","") -> BA | I64: 業種を判別するコード ※貸方科目を業種別計上する場合、必須 | Q64: 仕訳明細.業種コード
A65: =MAX($A$10:$A64)+1 -> 54 | B65: 担当者コード（貸方） | E65: △ | F65: コード | G65: 15 | H65: =SUBSTITUTE(SUBSTITUTE(ADDRESS(1,A65),"$1",""),"$","") -> BB | I65: 空白（設定不要） | Q65: 設定なし
A66: =MAX($A$10:$A65)+1 -> 55 | B66: セグメントコード（貸方） | E66: △ | F66: コード | G66: 4 | H66: =SUBSTITUTE(SUBSTITUTE(ADDRESS(1,A66),"$1",""),"$","") -> BC | I66: 会計品目を判別するコード ※貸方科目を会計品目別計上する場合、必須 | Q66: 仕訳明細.会計情報品目コード
A67: =MAX($A$10:$A66)+1 -> 56 | B67: セグメントコード１（貸方） | E67: △ | F67: コード | G67: 4 | H67: =SUBSTITUTE(SUBSTITUTE(ADDRESS(1,A67),"$1",""),"$","") -> BD | I67: 空白（設定不要） | Q67: 設定なし
A68: =MAX($A$10:$A67)+1 -> 57 | B68: セグメントコード２（貸方） | E68: △ | F68: コード | G68: 4 | H68: =SUBSTITUTE(SUBSTITUTE(ADDRESS(1,A68),"$1",""),"$","") -> BE | I68: 空白（設定不要） | Q68: 設定なし
A69: =MAX($A$10:$A68)+1 -> 58 | B69: セグメントコード３（貸方） | E69: △ | F69: コード | G69: 4 | H69: =SUBSTITUTE(SUBSTITUTE(ADDRESS(1,A69),"$1",""),"$","") -> BF | I69: 空白（設定不要） | Q69: 設定なし
A70: =MAX($A$10:$A69)+1 -> 59 | B70: セグメントコード４（貸方） | E70: △ | F70: コード | G70: 4 | H70: =SUBSTITUTE(SUBSTITUTE(ADDRESS(1,A70),"$1",""),"$","") -> BG | I70: 空白（設定不要） | Q70: 設定なし
A71: =MAX($A$10:$A70)+1 -> 60 | B71: セグメントコード５（貸方） | E71: △ | F71: コード | G71: 4 | H71: =SUBSTITUTE(SUBSTITUTE(ADDRESS(1,A71),"$1",""),"$","") -> BH | I71: 空白（設定不要） | Q71: 設定なし
A72: =MAX($A$10:$A71)+1 -> 61 | B72: 仕訳伝票明細金額（貸方） | E72: 〇 | F72: 数値 | G72: 13 | H72: =SUBSTITUTE(SUBSTITUTE(ADDRESS(1,A72),"$1",""),"$","") -> BI | Q72: 仕訳明細.借方金額
A73: =MAX($A$10:$A72)+1 -> 62 | B73: 消費税額（貸方） | F73: 数値 | G73: 13 | H73: =SUBSTITUTE(SUBSTITUTE(ADDRESS(1,A73),"$1",""),"$","") -> BJ | Q73: （消費税発生元科目に一致する場合、消費税行の）仕訳明細.借方金額
A74: =MAX($A$10:$A73)+1 -> 63 | B74: 消費税区分（貸方） | F74: 区分 | G74: 2 | H74: =SUBSTITUTE(SUBSTITUTE(ADDRESS(1,A74),"$1",""),"$","") -> BK | Q74: 仕訳明細.消費税取引区分（PA向けの変換処理あり）
A75: =MAX($A$10:$A74)+1 -> 64 | B75: 消費税計算区分（貸方） | F75: 区分 | G75: 1 | H75: =SUBSTITUTE(SUBSTITUTE(ADDRESS(1,A75),"$1",""),"$","") -> BL | I75: 3.計算しない | Q75: 3（計算しない）
A76: =MAX($A$10:$A75)+1 -> 65 | B76: 調整計上フラグ | E76: △ | F76: フラグ | G76: 1 | H76: =SUBSTITUTE(SUBSTITUTE(ADDRESS(1,A76),"$1",""),"$","") -> BM | I76: 空白（設定不要） | Q76: 設定なし
A77: =MAX($A$10:$A76)+1 -> 66 | B77: 通貨コード | E77: △ | F77: コード | G77: 3 | H77: =SUBSTITUTE(SUBSTITUTE(ADDRESS(1,A77),"$1",""),"$","") -> BN | I77: 空白（設定不要） | Q77: 設定なし
A78: =MAX($A$10:$A77)+1 -> 67 | B78: 為替レート | F78: 数値 | G78: 8 | H78: =SUBSTITUTE(SUBSTITUTE(ADDRESS(1,A78),"$1",""),"$","") -> BO | I78: 空白（設定不要） | Q78: 設定なし
A79: =MAX($A$10:$A78)+1 -> 68 | B79: 為替予約フラグ | E79: △ | F79: フラグ | G79: 1 | H79: =SUBSTITUTE(SUBSTITUTE(ADDRESS(1,A79),"$1",""),"$","") -> BP | I79: 空白（設定不要） | Q79: 設定なし
A80: =MAX($A$10:$A79)+1 -> 69 | B80: 仕訳伝票明細金額（外貨）（貸方） | E80: △ | F80: 数値 | G80: 15 | H80: =SUBSTITUTE(SUBSTITUTE(ADDRESS(1,A80),"$1",""),"$","") -> BQ | I80: 空白（設定不要） | Q80: 設定なし
A81: =MAX($A$10:$A80)+1 -> 70 | B81: CF勘定科目内訳コード（貸方） | F81: コード | G81: 2 | H81: =SUBSTITUTE(SUBSTITUTE(ADDRESS(1,A81),"$1",""),"$","") -> BR | I81: 貸方科目の科目残発生理由を識別するコード | Q81: 仕訳明細.CF勘定科目内訳コード
A82: =MAX($A$10:$A81)+1 -> 71 | B82: 資金繰科目コード（貸方） | F82: コード | G82: 5 | H82: =SUBSTITUTE(SUBSTITUTE(ADDRESS(1,A82),"$1",""),"$","") -> BS | I82: 貸方科目の資金繰科目を特定するコード | Q82: 設定なし
A83: =MAX($A$10:$A82)+1 -> 72 | B83: 備忘フラグ（貸方） | F83: フラグ | G83: 1 | H83: =SUBSTITUTE(SUBSTITUTE(ADDRESS(1,A83),"$1",""),"$","") -> BT | I83: 貸方備忘摘要を入力するか否かのフラグ（0.チェックなし、1.チェック有） ※未設定の場合、0.チェックなし | Q83: 設定なし
A84: =MAX($A$10:$A83)+1 -> 73 | B84: 備忘摘要（貸方） | F84: 文字列 | G84: 50 | H84: =SUBSTITUTE(SUBSTITUTE(ADDRESS(1,A84),"$1",""),"$","") -> BU | I84: 任意情報用項目（総勘定元帳に出力されないが、仕訳伝票明細データ出力（大量データ出力）で出力可） | Q84: 設定なし
A85: =MAX($A$10:$A84)+1 -> 74 | B85: システム連動項目１（貸方） | F85: 文字列 | G85: 20 | H85: =SUBSTITUTE(SUBSTITUTE(ADDRESS(1,A85),"$1",""),"$","") -> BV | I85: システム連動項目（設定不要）※PA内でのデータ追跡用項目 | Q85: 設定なし
A86: =MAX($A$10:$A85)+1 -> 75 | B86: システム連動項目２（貸方） | F86: 文字列 | G86: 20 | H86: =SUBSTITUTE(SUBSTITUTE(ADDRESS(1,A86),"$1",""),"$","") -> BW | I86: 任意情報用項目（総勘定元帳に出力される） ※PAのGL、AP（ホクレン様使用機能）では使用しないが、FAでは使用される | Q86: 設定なし
A87: =MAX($A$10:$A86)+1 -> 76 | B87: システム連動項目３（貸方） | F87: 文字列 | G87: 20 | H87: =SUBSTITUTE(SUBSTITUTE(ADDRESS(1,A87),"$1",""),"$","") -> BX | I87: 任意情報用項目（総勘定元帳に出力される） | Q87: 仕訳明細.諸口取引先名称カナ
A88: =MAX($A$10:$A87)+1 -> 77 | B88: 仕訳予備項目１（文字列）（貸方） | F88: 文字列 | G88: 50 | H88: =SUBSTITUTE(SUBSTITUTE(ADDRESS(1,A88),"$1",""),"$","") -> BY | I88: 任意情報用項目（総勘定元帳に出力されないが、仕訳伝票明細データ出力（大量データ出力）で出力可） | Q88: 仕訳ヘッダ.発生元システム取引番号
A89: =MAX($A$10:$A88)+1 -> 78 | B89: 仕訳予備項目２（文字列）（貸方） | F89: 文字列 | G89: 50 | H89: =SUBSTITUTE(SUBSTITUTE(ADDRESS(1,A89),"$1",""),"$","") -> BZ | I89: 任意情報用項目（総勘定元帳に出力されないが、仕訳伝票明細データ出力（大量データ出力）で出力可） | Q89: 取扱区分（連結決算データで売上高の対象データを判別する、消費税繰延調書出力でも使用する）
A90: =MAX($A$10:$A89)+1 -> 79 | B90: 仕訳予備項目３（文字列）（貸方） | F90: 文字列 | G90: 50 | H90: =SUBSTITUTE(SUBSTITUTE(ADDRESS(1,A90),"$1",""),"$","") -> CA | I90: 任意情報用項目（総勘定元帳に出力されないが、仕訳伝票明細データ出力（大量データ出力）で出力可） | Q90: 科目摘要補足（自由入力項目）
A91: =MAX($A$10:$A90)+1 -> 80 | B91: 仕訳予備項目１（数字）（貸方） | F91: 数値 | G91: 17 | H91: =SUBSTITUTE(SUBSTITUTE(ADDRESS(1,A91),"$1",""),"$","") -> CB | I91: 任意情報用項目（総勘定元帳に出力されないが、仕訳伝票明細データ出力（大量データ出力）で出力可） | Q91: 仕訳ヘッダ.取引日（消費税繰延調書出力で使用する）
A92: =MAX($A$10:$A91)+1 -> 81 | B92: 仕訳予備項目２（数字）（貸方） | F92: 数値 | G92: 17 | H92: =SUBSTITUTE(SUBSTITUTE(ADDRESS(1,A92),"$1",""),"$","") -> CC | I92: 任意情報用項目（総勘定元帳に出力されないが、仕訳伝票明細データ出力（大量データ出力）で出力可） | Q92: 設定なし
A93: =MAX($A$10:$A92)+1 -> 82 | B93: 仕訳予備項目３（数字）（貸方） | F93: 数値 | G93: 17 | H93: =SUBSTITUTE(SUBSTITUTE(ADDRESS(1,A93),"$1",""),"$","") -> CD | I93: 任意情報用項目（総勘定元帳に出力されないが、仕訳伝票明細データ出力（大量データ出力）で出力可） | Q93: 設定なし

Sheet 取込フォーマット定義 bk
A1: ドキュメント名 | E1: サブシステム | G1: 業務機能名 | P1: 作成者 | R1: =表紙!D51 -> SCSK大西 | T1: 更新者
A2: 業務機能概要書 | C2: 取込フォーマット定義 | E2: =業務機能概要!L2 -> 財務会計 | G2: =業務機能概要!Q2 -> 仕訳データ自動取込 | P2: 作成日 | R2: =表紙!C51 -> 45898 | T2: 更新日
A4: データ名 | C4: 仕訳データ | I4: ヘッダ行 | K4: あり | M4: なし | N4: ダブルクォーテーション | Q4: あり | S4: なし | X4: 文字列
A5: ﾌｧｲﾙ形式・ﾚｺｰﾄﾞ長 | D5: 固定長（ | G5: Byte） | I5: 可変長（区切り文字［ ，(カンマ) ］） | M5: バイナリデータ | P5: その他（ ） | X5: 半英数
A6: 文字コード | D6: UNI（Win系） | F6: EBCDIC(K) | I6: その他（ UTF-8） | M6: 改行コード | O6: LF(UNIX系) | Q6: CRLF(Win系) | T6: なし | X6: 半カナ
A7: 全角(2byte)文字項目 | D7: あり | F7: なし | M7: 数値編集 | O7: 左詰め | Q7: 右詰め［ゼロ埋め］ | T7: 右詰め［スペース埋め］ | X7: コード
A8: 特記事項 | X8: 数値
A9: No. | B9: 項目名 | E9: 必須 | F9: 型 | G9: 桁数 | H9: 開始位置 | I9: 備考 | X9: 日付
H10: /列 | X10: 時間
A11: =MAX($A$10:$A10)+1 -> 1 | B11: 元帳領域コード | F11: コード | G11: 2 | H11: =SUBSTITUTE(SUBSTITUTE(ADDRESS(1,A11),"$1",""),"$","") -> A | I11: 仕訳の種類を判別するためのコード（01.一般仕訳、02.月次修正仕訳、03.管理会計仕訳、04.売上高・売上原価仕訳、05.組替仕訳） | X11: 年月
A12: =MAX($A$10:$A11)+1 -> 2 | B12: 仕訳伝票番号 | E12: △ | F12: 文字列 | G12: 12 | H12: =SUBSTITUTE(SUBSTITUTE(ADDRESS(1,A12),"$1",""),"$","") -> B | I12: 仕訳伝票番号。ProActiveC4上一位の番号とする必要がある。 | X12: 区分
A13: =MAX($A$10:$A12)+1 -> 3 | B13: 仕訳伝票起票日付 | E13: 〇 | F13: 日付 | G13: 8 | H13: =SUBSTITUTE(SUBSTITUTE(ADDRESS(1,A13),"$1",""),"$","") -> C | I13: 経理日
A14: =MAX($A$10:$A13)+1 -> 4 | B14: 起票部門表示コード | E14: 〇 | F14: コード | G14: 10 | H14: =SUBSTITUTE(SUBSTITUTE(ADDRESS(1,A14),"$1",""),"$","") -> D | I14: 伝票起票した部署のコード（事業所コード＋業種コード（2桁）＋所属コード（3桁の場合は前0埋め）の8桁で指定する）
A15: =MAX($A$10:$A14)+1 -> 5 | B15: 仕訳円貨区分 | E15: 〇 | F15: 区分 | G15: 1 | H15: =SUBSTITUTE(SUBSTITUTE(ADDRESS(1,A15),"$1",""),"$","") -> E | I15: 外貨建ての伝票か円貨の伝票かの区分（1.円貨、2.外貨）
A16: =MAX($A$10:$A15)+1 -> 6 | B16: 起票者コード | E16: 〇 | F16: コード | G16: 15 | H16: =SUBSTITUTE(SUBSTITUTE(ADDRESS(1,A16),"$1",""),"$","") -> F | I16: 仕訳伝票を起票したユーザーID（固定値：999999999999999（ダミー））
A17: =MAX($A$10:$A16)+1 -> 7 | B17: 決算仕訳フラグ | E17: 〇 | F17: フラグ | G17: 1 | H17: =SUBSTITUTE(SUBSTITUTE(ADDRESS(1,A17),"$1",""),"$","") -> G | I17: 決算仕訳か否かのフラグ（0.通常仕訳、1.決算仕訳）
A18: =MAX($A$10:$A17)+1 -> 8 | B18: 仕訳伝票摘要 | F18: 文字列 | G18: 80 | H18: =SUBSTITUTE(SUBSTITUTE(ADDRESS(1,A18),"$1",""),"$","") -> H
A19: =MAX($A$10:$A18)+1 -> 9 | B19: 洗替実施区分 | F19: 区分 | G19: 1 | H19: =SUBSTITUTE(SUBSTITUTE(ADDRESS(1,A19),"$1",""),"$","") -> I | I19: 9.不要
A20: =MAX($A$10:$A19)+1 -> 10 | B20: 洗替伝票起票日付 | E20: △ | F20: 日付 | G20: 8 | H20: =SUBSTITUTE(SUBSTITUTE(ADDRESS(1,A20),"$1",""),"$","") -> J | I20: 空白（設定不要）
A21: =MAX($A$10:$A20)+1 -> 11 | B21: 仕訳伝票行番号 | E21: 〇 | F21: 数値 | G21: 4 | H21: =SUBSTITUTE(SUBSTITUTE(ADDRESS(1,A21),"$1",""),"$","") -> K | I21: 仕訳伝票明細の行番号
A22: =MAX($A$10:$A21)+1 -> 12 | B22: 仕訳伝票明細摘要 | F22: 文字列 | G22: 80 | H22: =SUBSTITUTE(SUBSTITUTE(ADDRESS(1,A22),"$1",""),"$","") -> L
A23: =MAX($A$10:$A22)+1 -> 13 | B23: 勘定科目コード（借方） | F23: コード | G23: 8 | H23: =SUBSTITUTE(SUBSTITUTE(ADDRESS(1,A23),"$1",""),"$","") -> M
A24: =MAX($A$10:$A23)+1 -> 14 | B24: 補助科目コード（借方） | E24: △ | F24: コード | G24: 4 | H24: =SUBSTITUTE(SUBSTITUTE(ADDRESS(1,A24),"$1",""),"$","") -> N | I24: 科目摘要を判別するコード
A25: =MAX($A$10:$A24)+1 -> 15 | B25: 計上部門表示コード（借方） | F25: コード | G25: 10 | H25: =SUBSTITUTE(SUBSTITUTE(ADDRESS(1,A25),"$1",""),"$","") -> O | I25: 借方科目残を計上する部署のコード（業種コード（2桁）＋所属コード（3桁の場合は前0埋め）の6桁で指定する） | Q25: ※費用科目の場合は費用管理組織。未収未払の場合は未収未払管理組織。
A26: =MAX($A$10:$A25)+1 -> 16 | B26: 取引先コード（借方） | E26: △ | F26: コード | G26: 15 | H26: =SUBSTITUTE(SUBSTITUTE(ADDRESS(1,A26),"$1",""),"$","") -> P | I26: ※借方科目を取引先計上する場合、必須
A27: =MAX($A$10:$A26)+1 -> 17 | B27: 自社口座コード（借方） | E27: △ | F27: コード | G27: 8 | H27: =SUBSTITUTE(SUBSTITUTE(ADDRESS(1,A27),"$1",""),"$","") -> Q | I27: 出金を行う銀行口座のコード ※借方科目を口座別計上する場合、必須
A28: =MAX($A$10:$A27)+1 -> 18 | B28: プロジェクトコード（借方） | E28: △ | F28: コード | G28: 20 | H28: =SUBSTITUTE(SUBSTITUTE(ADDRESS(1,A28),"$1",""),"$","") -> R | I28: 業種を判別するコード ※借方科目を業種別計上する場合、必須
A29: =MAX($A$10:$A28)+1 -> 19 | B29: 担当者コード（借方） | E29: △ | F29: コード | G29: 15 | H29: =SUBSTITUTE(SUBSTITUTE(ADDRESS(1,A29),"$1",""),"$","") -> S | I29: 空白（設定不要）
A30: =MAX($A$10:$A29)+1 -> 20 | B30: セグメントコード（借方） | E30: △ | F30: コード | G30: 4 | H30: =SUBSTITUTE(SUBSTITUTE(ADDRESS(1,A30),"$1",""),"$","") -> T | I30: 会計品目を判別するコード ※借方科目を会計品目別計上する場合、必須
A31: =MAX($A$10:$A30)+1 -> 21 | B31: セグメントコード１（借方） | E31: △ | F31: コード | G31: 4 | H31: =SUBSTITUTE(SUBSTITUTE(ADDRESS(1,A31),"$1",""),"$","") -> U | I31: 空白（設定不要）
A32: =MAX($A$10:$A31)+1 -> 22 | B32: セグメントコード２（借方） | E32: △ | F32: コード | G32: 4 | H32: =SUBSTITUTE(SUBSTITUTE(ADDRESS(1,A32),"$1",""),"$","") -> V | I32: 空白（設定不要）
A33: =MAX($A$10:$A32)+1 -> 23 | B33: セグメントコード３（借方） | E33: △ | F33: コード | G33: 4 | H33: =SUBSTITUTE(SUBSTITUTE(ADDRESS(1,A33),"$1",""),"$","") -> W | I33: 空白（設定不要）
A34: =MAX($A$10:$A33)+1 -> 24 | B34: セグメントコード４（借方） | E34: △ | F34: コード | G34: 4 | H34: =SUBSTITUTE(SUBSTITUTE(ADDRESS(1,A34),"$1",""),"$","") -> X | I34: 空白（設定不要）
A35: =MAX($A$10:$A34)+1 -> 25 | B35: セグメントコード５（借方） | E35: △ | F35: コード | G35: 4 | H35: =SUBSTITUTE(SUBSTITUTE(ADDRESS(1,A35),"$1",""),"$","") -> Y | I35: 空白（設定不要）
A36: =MAX($A$10:$A35)+1 -> 26 | B36: 仕訳伝票明細金額（借方） | E36: 〇 | F36: 数値 | G36: 13 | H36: =SUBSTITUTE(SUBSTITUTE(ADDRESS(1,A36),"$1",""),"$","") -> Z
A37: =MAX($A$10:$A36)+1 -> 27 | B37: 消費税額（借方） | F37: 数値 | G37: 13 | H37: =SUBSTITUTE(SUBSTITUTE(ADDRESS(1,A37),"$1",""),"$","") -> AA
A38: =MAX($A$10:$A37)+1 -> 28 | B38: 消費税区分（借方） | F38: 区分 | G38: 2 | H38: =SUBSTITUTE(SUBSTITUTE(ADDRESS(1,A38),"$1",""),"$","") -> AB
A39: =MAX($A$10:$A38)+1 -> 29 | B39: 消費税計算区分（借方） | F39: 区分 | G39: 1 | H39: =SUBSTITUTE(SUBSTITUTE(ADDRESS(1,A39),"$1",""),"$","") -> AC | I39: 3.計算しない
A40: =MAX($A$10:$A39)+1 -> 30 | B40: 調整計上フラグ | E40: △ | F40: フラグ | G40: 1 | H40: =SUBSTITUTE(SUBSTITUTE(ADDRESS(1,A40),"$1",""),"$","") -> AD | I40: 空白（設定不要）
A41: =MAX($A$10:$A40)+1 -> 31 | B41: 通貨コード | E41: △ | F41: コード | G41: 3 | H41: =SUBSTITUTE(SUBSTITUTE(ADDRESS(1,A41),"$1",""),"$","") -> AE | I41: 空白（設定不要）
A42: =MAX($A$10:$A41)+1 -> 32 | B42: 為替レート | F42: 数値 | G42: 8 | H42: =SUBSTITUTE(SUBSTITUTE(ADDRESS(1,A42),"$1",""),"$","") -> AF | I42: 空白（設定不要）
A43: =MAX($A$10:$A42)+1 -> 33 | B43: 為替予約フラグ | E43: △ | F43: フラグ | G43: 1 | H43: =SUBSTITUTE(SUBSTITUTE(ADDRESS(1,A43),"$1",""),"$","") -> AG | I43: 空白（設定不要）
A44: =MAX($A$10:$A43)+1 -> 34 | B44: 仕訳伝票明細金額（外貨）（借方） | E44: △ | F44: 数値 | G44: 15 | H44: =SUBSTITUTE(SUBSTITUTE(ADDRESS(1,A44),"$1",""),"$","") -> AH | I44: 空白（設定不要）
A45: =MAX($A$10:$A44)+1 -> 35 | B45: CF勘定科目内訳コード（借方） | F45: コード | G45: 2 | H45: =SUBSTITUTE(SUBSTITUTE(ADDRESS(1,A45),"$1",""),"$","") -> AI | I45: 借方科目の科目残発生理由を識別するコード（CF勘定科目内訳が必要な勘定科目の場合は必須）
A46: =MAX($A$10:$A45)+1 -> 36 | B46: 資金繰科目コード（借方） | F46: コード | G46: 5 | H46: =SUBSTITUTE(SUBSTITUTE(ADDRESS(1,A46),"$1",""),"$","") -> AJ | I46: 借方科目の資金繰科目を特定するコード
A47: =MAX($A$10:$A46)+1 -> 37 | B47: 備忘フラグ（借方） | F47: フラグ | G47: 1 | H47: =SUBSTITUTE(SUBSTITUTE(ADDRESS(1,A47),"$1",""),"$","") -> AK | I47: 借方備忘摘要を入力するか否かのフラグ（0.チェックなし、1.チェック有） ※未設定の場合、0.チェックなしが設定される
A48: =MAX($A$10:$A47)+1 -> 38 | B48: 備忘摘要（借方） | F48: 文字列 | G48: 50 | H48: =SUBSTITUTE(SUBSTITUTE(ADDRESS(1,A48),"$1",""),"$","") -> AL | I48: 発生元システム管理No.（前渡金と振替する対象のデータを識別する） ※「納品書番号」に相当する（20桁）
A49: =MAX($A$10:$A48)+1 -> 39 | B49: システム連動項目１（借方） | F49: 文字列 | G49: 20 | H49: =SUBSTITUTE(SUBSTITUTE(ADDRESS(1,A49),"$1",""),"$","") -> AM | I49: 空白（設定不要）
A50: =MAX($A$10:$A49)+1 -> 40 | B50: システム連動項目２（借方） | F50: 文字列 | G50: 20 | H50: =SUBSTITUTE(SUBSTITUTE(ADDRESS(1,A50),"$1",""),"$","") -> AN | I50: 諸口取引先名
A51: =MAX($A$10:$A50)+1 -> 41 | B51: システム連動項目３（借方） | F51: 文字列 | G51: 20 | H51: =SUBSTITUTE(SUBSTITUTE(ADDRESS(1,A51),"$1",""),"$","") -> AO | I51: 連携元伝票番号 → 元のシステムの番号は仕訳伝票番号にセットするので、設定不要？ | P51: 伝票トレーサビリティ要件次第
A52: =MAX($A$10:$A51)+1 -> 42 | B52: 仕訳予備項目１（文字列）（借方） | F52: 文字列 | G52: 50 | H52: =SUBSTITUTE(SUBSTITUTE(ADDRESS(1,A52),"$1",""),"$","") -> AP | I52: 出荷元コード（前渡金と振替する対象の未払金を識別する） | P52: Bチームに要否確認
A53: =MAX($A$10:$A52)+1 -> 43 | B53: 仕訳予備項目２（文字列）（借方） | F53: 文字列 | G53: 50 | H53: =SUBSTITUTE(SUBSTITUTE(ADDRESS(1,A53),"$1",""),"$","") -> AQ | I53: 取扱区分（連結決算データで売上高の対象データを判別する、消費税繰延調書出力でも使用する）
A54: =MAX($A$10:$A53)+1 -> 44 | B54: 仕訳予備項目３（文字列）（借方） | F54: 文字列 | G54: 50 | H54: =SUBSTITUTE(SUBSTITUTE(ADDRESS(1,A54),"$1",""),"$","") -> AR | I54: 入金番号（入金情報と仕訳を照合する） | P54: Bチームに要否確認
A55: =MAX($A$10:$A54)+1 -> 45 | B55: 仕訳予備項目１（数字）（借方） | F55: 数値 | G55: 17 | H55: =SUBSTITUTE(SUBSTITUTE(ADDRESS(1,A55),"$1",""),"$","") -> AS | I55: 取引日付（8桁）（前渡金と振替する対象のデータの識別する、消費税繰延調書出力で使用する）
A56: =MAX($A$10:$A55)+1 -> 46 | B56: 仕訳予備項目２（数字）（借方） | F56: 数値 | G56: 17 | H56: =SUBSTITUTE(SUBSTITUTE(ADDRESS(1,A56),"$1",""),"$","") -> AT
A57: =MAX($A$10:$A56)+1 -> 47 | B57: 仕訳予備項目３（数字）（借方） | F57: 数値 | G57: 17 | H57: =SUBSTITUTE(SUBSTITUTE(ADDRESS(1,A57),"$1",""),"$","") -> AU
A58: =MAX($A$10:$A57)+1 -> 48 | B58: 勘定科目コード（貸方） | F58: コード | G58: 8 | H58: =SUBSTITUTE(SUBSTITUTE(ADDRESS(1,A58),"$1",""),"$","") -> AV
A59: =MAX($A$10:$A58)+1 -> 49 | B59: 補助科目コード（貸方） | E59: △ | F59: コード | G59: 4 | H59: =SUBSTITUTE(SUBSTITUTE(ADDRESS(1,A59),"$1",""),"$","") -> AW | I59: 科目摘要を判別するコード
A60: =MAX($A$10:$A59)+1 -> 50 | B60: 計上部門表示コード（貸方） | F60: コード | G60: 10 | H60: =SUBSTITUTE(SUBSTITUTE(ADDRESS(1,A60),"$1",""),"$","") -> AX | I60: 貸方科目残を計上する部署のコード（業種コード（2桁）＋所属コード（3桁の場合は前0埋め）の6桁で指定する） | Q60: ※費用科目の場合は費用管理組織。未収未払の場合は未収未払管理組織。
A61: =MAX($A$10:$A60)+1 -> 51 | B61: 取引先コード（貸方） | E61: △ | F61: コード | G61: 15 | H61: =SUBSTITUTE(SUBSTITUTE(ADDRESS(1,A61),"$1",""),"$","") -> AY | I61: 貸方科目を取引先計上する場合、必須
A62: =MAX($A$10:$A61)+1 -> 52 | B62: 自社口座コード（貸方） | E62: △ | F62: コード | G62: 8 | H62: =SUBSTITUTE(SUBSTITUTE(ADDRESS(1,A62),"$1",""),"$","") -> AZ | I62: 出金を行う銀行口座のコード ※貸方科目を口座別計上する場合、必須
A63: =MAX($A$10:$A62)+1 -> 53 | B63: プロジェクトコード（貸方） | E63: △ | F63: コード | G63: 20 | H63: =SUBSTITUTE(SUBSTITUTE(ADDRESS(1,A63),"$1",""),"$","") -> BA | I63: 業種を判別するコード ※貸方科目を業種別計上する場合、必須
A64: =MAX($A$10:$A63)+1 -> 54 | B64: 担当者コード（貸方） | E64: △ | F64: コード | G64: 15 | H64: =SUBSTITUTE(SUBSTITUTE(ADDRESS(1,A64),"$1",""),"$","") -> BB | I64: 空白（設定不要）
A65: =MAX($A$10:$A64)+1 -> 55 | B65: セグメントコード（貸方） | E65: △ | F65: コード | G65: 4 | H65: =SUBSTITUTE(SUBSTITUTE(ADDRESS(1,A65),"$1",""),"$","") -> BC | I65: 会計品目を判別するコード ※貸方科目を会計品目別計上する場合、必須
A66: =MAX($A$10:$A65)+1 -> 56 | B66: セグメントコード１（貸方） | E66: △ | F66: コード | G66: 4 | H66: =SUBSTITUTE(SUBSTITUTE(ADDRESS(1,A66),"$1",""),"$","") -> BD | I66: 空白（設定不要）
A67: =MAX($A$10:$A66)+1 -> 57 | B67: セグメントコード２（貸方） | E67: △ | F67: コード | G67: 4 | H67: =SUBSTITUTE(SUBSTITUTE(ADDRESS(1,A67),"$1",""),"$","") -> BE | I67: 空白（設定不要）
A68: =MAX($A$10:$A67)+1 -> 58 | B68: セグメントコード３（貸方） | E68: △ | F68: コード | G68: 4 | H68: =SUBSTITUTE(SUBSTITUTE(ADDRESS(1,A68),"$1",""),"$","") -> BF | I68: 空白（設定不要）
A69: =MAX($A$10:$A68)+1 -> 59 | B69: セグメントコード４（貸方） | E69: △ | F69: コード | G69: 4 | H69: =SUBSTITUTE(SUBSTITUTE(ADDRESS(1,A69),"$1",""),"$","") -> BG | I69: 空白（設定不要）
A70: =MAX($A$10:$A69)+1 -> 60 | B70: セグメントコード５（貸方） | E70: △ | F70: コード | G70: 4 | H70: =SUBSTITUTE(SUBSTITUTE(ADDRESS(1,A70),"$1",""),"$","") -> BH | I70: 空白（設定不要）
A71: =MAX($A$10:$A70)+1 -> 61 | B71: 仕訳伝票明細金額（貸方） | E71: 〇 | F71: 数値 | G71: 13 | H71: =SUBSTITUTE(SUBSTITUTE(ADDRESS(1,A71),"$1",""),"$","") -> BI
A72: =MAX($A$10:$A71)+1 -> 62 | B72: 消費税額（貸方） | F72: 数値 | G72: 13 | H72: =SUBSTITUTE(SUBSTITUTE(ADDRESS(1,A72),"$1",""),"$","") -> BJ
A73: =MAX($A$10:$A72)+1 -> 63 | B73: 消費税区分（貸方） | F73: 区分 | G73: 2 | H73: =SUBSTITUTE(SUBSTITUTE(ADDRESS(1,A73),"$1",""),"$","") -> BK
A74: =MAX($A$10:$A73)+1 -> 64 | B74: 消費税計算区分（貸方） | F74: 区分 | G74: 1 | H74: =SUBSTITUTE(SUBSTITUTE(ADDRESS(1,A74),"$1",""),"$","") -> BL | I74: 3.計算しない
A75: =MAX($A$10:$A74)+1 -> 65 | B75: 調整計上フラグ | E75: △ | F75: フラグ | G75: 1 | H75: =SUBSTITUTE(SUBSTITUTE(ADDRESS(1,A75),"$1",""),"$","") -> BM | I75: 空白（設定不要）
A76: =MAX($A$10:$A75)+1 -> 66 | B76: 通貨コード | E76: △ | F76: コード | G76: 3 | H76: =SUBSTITUTE(SUBSTITUTE(ADDRESS(1,A76),"$1",""),"$","") -> BN | I76: 空白（設定不要）
A77: =MAX($A$10:$A76)+1 -> 67 | B77: 為替レート | F77: 数値 | G77: 8 | H77: =SUBSTITUTE(SUBSTITUTE(ADDRESS(1,A77),"$1",""),"$","") -> BO | I77: 空白（設定不要）
A78: =MAX($A$10:$A77)+1 -> 68 | B78: 為替予約フラグ | E78: △ | F78: フラグ | G78: 1 | H78: =SUBSTITUTE(SUBSTITUTE(ADDRESS(1,A78),"$1",""),"$","") -> BP | I78: 空白（設定不要）
A79: =MAX($A$10:$A78)+1 -> 69 | B79: 仕訳伝票明細金額（外貨）（貸方） | E79: △ | F79: 数値 | G79: 15 | H79: =SUBSTITUTE(SUBSTITUTE(ADDRESS(1,A79),"$1",""),"$","") -> BQ | I79: 空白（設定不要）
A80: =MAX($A$10:$A79)+1 -> 70 | B80: CF勘定科目内訳コード（貸方） | F80: コード | G80: 2 | H80: =SUBSTITUTE(SUBSTITUTE(ADDRESS(1,A80),"$1",""),"$","") -> BR | I80: 貸方科目の科目残発生理由を識別するコード
A81: =MAX($A$10:$A80)+1 -> 71 | B81: 資金繰科目コード（貸方） | F81: コード | G81: 5 | H81: =SUBSTITUTE(SUBSTITUTE(ADDRESS(1,A81),"$1",""),"$","") -> BS | I81: 貸方科目の資金繰科目を特定するコード
A82: =MAX($A$10:$A81)+1 -> 72 | B82: 備忘フラグ（貸方） | F82: フラグ | G82: 1 | H82: =SUBSTITUTE(SUBSTITUTE(ADDRESS(1,A82),"$1",""),"$","") -> BT | I82: 借方備忘摘要を入力するか否かのフラグ（0.チェックなし、1.チェック有） ※未設定の場合、0.チェックなしが設定される
A83: =MAX($A$10:$A82)+1 -> 73 | B83: 備忘摘要（貸方） | F83: 文字列 | G83: 50 | H83: =SUBSTITUTE(SUBSTITUTE(ADDRESS(1,A83),"$1",""),"$","") -> BU | I83: 発生元システム管理No.（前渡金と振替する対象のデータを識別する） ※「納品書番号」に相当する（20桁）
A84: =MAX($A$10:$A83)+1 -> 74 | B84: システム連動項目１（貸方） | F84: 文字列 | G84: 20 | H84: =SUBSTITUTE(SUBSTITUTE(ADDRESS(1,A84),"$1",""),"$","") -> BV | I84: 空白（設定不要）
A85: =MAX($A$10:$A84)+1 -> 75 | B85: システム連動項目２（貸方） | F85: 文字列 | G85: 20 | H85: =SUBSTITUTE(SUBSTITUTE(ADDRESS(1,A85),"$1",""),"$","") -> BW | I85: 諸口取引先名
A86: =MAX($A$10:$A85)+1 -> 76 | B86: システム連動項目３（貸方） | F86: 文字列 | G86: 20 | H86: =SUBSTITUTE(SUBSTITUTE(ADDRESS(1,A86),"$1",""),"$","") -> BX | I86: 連携元伝票番号 → 元のシステムの番号は仕訳伝票番号にセットするので、設定不要？
A87: =MAX($A$10:$A86)+1 -> 77 | B87: 仕訳予備項目１（文字列）（貸方） | F87: 文字列 | G87: 50 | H87: =SUBSTITUTE(SUBSTITUTE(ADDRESS(1,A87),"$1",""),"$","") -> BY | I87: 出荷元コード（前渡金と振替する対象の未払金を識別する）
A88: =MAX($A$10:$A87)+1 -> 78 | B88: 仕訳予備項目２（文字列）（貸方） | F88: 文字列 | G88: 50 | H88: =SUBSTITUTE(SUBSTITUTE(ADDRESS(1,A88),"$1",""),"$","") -> BZ | I88: 取扱区分（連結決算データで売上高の対象データを判別する、消費税繰延調書出力でも使用する）
A89: =MAX($A$10:$A88)+1 -> 79 | B89: 仕訳予備項目３（文字列）（貸方） | F89: 文字列 | G89: 50 | H89: =SUBSTITUTE(SUBSTITUTE(ADDRESS(1,A89),"$1",""),"$","") -> CA | I89: 入金番号（入金情報と仕訳を照合する）
A90: =MAX($A$10:$A89)+1 -> 80 | B90: 仕訳予備項目１（数字）（貸方） | F90: 数値 | G90: 17 | H90: =SUBSTITUTE(SUBSTITUTE(ADDRESS(1,A90),"$1",""),"$","") -> CB | I90: 取引日付（8桁）（前渡金と振替する対象のデータの識別する、消費税繰延調書出力で使用する）
A91: =MAX($A$10:$A90)+1 -> 81 | B91: 仕訳予備項目２（数字）（貸方） | F91: 数値 | G91: 17 | H91: =SUBSTITUTE(SUBSTITUTE(ADDRESS(1,A91),"$1",""),"$","") -> CC
A92: =MAX($A$10:$A91)+1 -> 82 | B92: 仕訳予備項目３（数字）（貸方） | F92: 数値 | G92: 17 | H92: =SUBSTITUTE(SUBSTITUTE(ADDRESS(1,A92),"$1",""),"$","") -> CD
E93: 〇：必須 △：条件付き必須

Sheet ⇒

Sheet データアクセス要領
A1: ドキュメント名 | L1: サブシステム | Q1: 業務機能名 | AJ1: 作成者 | AO1: =表紙!D51 -> SCSK大西 | AT1: 更新者
A2: 業務機能概要書 | G2: データアクセス要領 | L2: =業務機能概要!L2 -> 財務会計 | Q2: =業務機能概要!Q2 -> 仕訳データ自動取込 | AJ2: 作成日付 | AO2: =表紙!C51 -> 45898 | AT2: 更新日付
A4: 【編集要領】
B6: データ登録の要領は、標準の「仕訳外部データ取込」機能の実行時と同様。

Sheet 補足
A1: ドキュメント名 | L1: サブシステム | Q1: 業務機能名 | AM1: 作成者 | AR1: =表紙!D51 -> SCSK大西 | AW1: 更新者
A2: 業務機能概要書 | G2: 補足説明 | L2: =業務機能概要!L2 -> 財務会計 | Q2: =業務機能概要!Q2 -> 仕訳データ自動取込 | AM2: 作成日付 | AR2: =表紙!C51 -> 45898 | AW2: 更新日付
C4: 当機能でのバッチファイル、xmlファイルの作成イメージ
C7: バッチファイル１ | P7: c4_import_shiwak.bat
D9: ①仕訳データ取込 | AG9: 入力データファイル（xml）
E11: 取込ファイル探索 | J11: ※取込ファイルが0byteであった場合は正常として処理終了する | AH11: 会社コードを定義する
AH12: ※ | AI12: 「cvo_sav_cd」は設定なしとして、取込ファイルは
AI13: バッチ実行定義ファイルで定義する
E14: 取込実行バッチファイルの呼び出し
E16: 正常時 | AG16: BRファイル（xml）
F17: 取込ファイルの退避（正常終了のファイル退避フォルダへ移動）
E18: エラー時 | AH18: バッチ処理の中で利用するビジネスリソース
F19: 取込ファイルの退避（異常終了のファイル退避フォルダへ移動） | AH19: J-SOXログ出力で利用するクライアント環境情報 | AW19: を定義する
C28: バッチファイル２ | I28: ※パタメータ定義用 | P28: param.bat
D30: 取込ファイルのフォルダパス、
D31: SQLファイルのパスなどを定義する
C37: バッチファイル３ | P37: Exec_ShiwkImpBatch.bat
D39: 入力データファイル 読み込み
D41: BRファイル 読み込み
D43: バッチ実行
D44: 戻り値返却
C49: ディレクトリ構成
D52: ー | E52: ー | G52: c4_import_shiwk.bat | AD52: ・・・ | AF52: タスクスケジューラから起動されるbat
E53: ｜ | G53: param.bat | AD53: ・・・ | AF53: bat実行時に参照されるパラメータセットbat
E54: ｜
E55: ー | G55: CSV_DIR | AD55: ・・・ | AF55: 取込用のCSVファイルを配置するフォルダ
E56: ｜
E57: ー | G57: BATCH_SUB_DIR | Q57: ー | R57: Exec_ShiwkImpBatch.bat | AD57: ・・・ | AF57: 仕訳データ取込を実行するためのbat
E58: ｜
E59: ｜
E60: ー | G60: SETTING_DIR | Q60: ー | R60: BR_GL.xml | AD60: ・・・ | AF60: BRファイル
E61: ｜ | R61: Input_ShiwkImpBatch.xml | AD61: ・・・ | AF61: 取込用のインプットファイル
E62: ｜
E63: ｜
E64: ー | G64: SUCCESS_DIR | AD64: ・・・ | AF64: 正常取込できた取込ファイルを退避するフォルダ
E65: ｜
E66: ー | G66: ERR_DIR | AD66: ・・・ | AF66: 取込エラーとなった取込ファイルを退避するフォルダ
AF67: エラー時のログを出力するフォルダ
C94: スクラッチ開発機能からProActiveC4に連動する仕訳、支払の業務データで必要となるマスタコード
C97: ① | D97: ユーザID（起票者） | V97: → | X97: 夜間連動時のユーザIDは連動用ユーザ固定とする。 即時連動のときは伝票入力ユーザとする
C98: ② | D98: 勘定科目コード | V98: → | X98: データ連動機能で同期をとるので考慮不要
C99: ③ | D99: 取引先コード | V99: → | X99: データ連動機能で同期をとるので考慮不要
B100: ★ | C100: ④ | D100: 部門コード（ProActiveC4用コード ・・・ 事業所+業種+部課） | V100: → | X100: スクラッチ開発機能からProActiveC4へ仕訳/支払の業務データを連動する際に、
X101: 「事業所コード+業種コード＋部課コード」でセットする
C102: ⑤ | D102: 補助科目コード（会計摘要） | V102: → | X102: データ連動機能で同期をとるので考慮不要
C103: ⑥ | D103: セグメントコード（会計情報品目） | V103: → | X103: 手動でコードの同期をとるので考慮不要
C104: ⑦ | D104: プロジェクトコード（業種） | V104: → | X104: 手動でコードの同期をとるので考慮不要
C105: ⑧ | D105: 自社口座コード（出金口座） | V105: → | X105: 手動でコードの同期をとるので考慮不要
B106: ★ | C106: ⑨ | D106: 消費税区分 | H106: ※ | V106: → | X106: スクラッチ開発機能からProActiveC4へ仕訳の業務データを連動する際に、ProActiveC4のコードでセットする
C107: ⑩ | D107: 元帳領域（仕訳の種類） | V107: → | X107: 手動でコードの同期をとるので考慮不要。初期設定後、追加、変更はない想定。
C108: ⑪ | D108: 取引種類コード | V108: → | X108: 手動でコードの同期をとるので考慮不要
C109: ⑫ | D109: 支払決済条件コード | V109: → | X109: データ連動機能で同期をとるので考慮不要（スクラッチ開発機能側でコードを決定し、ProActiveC4のマスタ情報として連動する）
C110: ⑬ | D110: ＣＦ勘定科目内訳コード | V110: → | X110: 手動でコードの同期をとるので考慮不要
D113: ※ | E113: ProActiveC4の部門コードはスクラッチ開発機能のマスタ情報の「事業所」+「業種コード」+「部課コード」にするよう手動メンテナンス時に注意する
D114: ※ | E114: 消費税区分 | K114: 消費税の種類、消費税率を管理するマスタ
D139: 内部取引における消費税除去の仕訳パターン
D141: ①
D143: （購買部門の売上）
G145: 内部 未収金 | N145: 11,000 | Q145: / | S145: 購買品 | Z145: 10,000
Q146: / | S146: 預り金（消費税） | Z146: 1,000 | AE146: 税込計上
D148: （販売部門の仕入）
G150: 販売品 | N150: 10,000 | Q150: / | S150: 内部 未払金 | Z150: 10,000 | AE150: 税抜計上
D152: （債権債務の振替）
G154: 内部 未払金 | N154: 10,000 | Q154: / | S154: 内部 未収金 | Z154: 10,000
D156: （消費税の取消）
Q158: / | S158: 内部 未収金 | Z158: 1,000
Q159: / | S159: 内部 預り金（消費税） | Z159: -1,000 | AE159: 差額（消費税）を取消
D162: ②
D164: （購買部門の売上）
G166: 内部 未収金 | N166: 20,000 | Q166: / | S166: 購買品 | Z166: 20,000 | AE166: 税抜計上
D168: （販売部門の仕入）
G170: 販売品 | N170: 20,000 | Q170: / | S170: 内部 未払金 | Z170: 22,000
G171: 立替金（消費税） | N171: 2,000 | Q171: / | AE171: 税込計上
D173: （債権債務の振替）
G175: 内部 未払金 | N175: 20,000 | Q175: / | S175: 内部 未収金 | Z175: 20,000
D177: （消費税の取消）
G179: 内部 未払金 | N179: 2,000 | Q179: /
G180: 内部 立替金（消費税） | N180: -2,000 | Q180: / | AE180: 差額（消費税）を取消
D184: ③
D186: （購買部門の売上）
G188: 内部 未収金 | N188: 33,000 | Q188: / | S188: 購買品 | Z188: 30,000
Q189: / | S189: 預り金（消費税） | Z189: 3,000 | AE189: 税込計上
D191: （販売部門の仕入）
G193: 販売品 | N193: 30,000 | Q193: / | S193: 内部 未払金 | Z193: 33,000
G194: 立替金（消費税） | N194: 3,000 | AE194: 税込計上
D196: （債権債務の振替）
G198: 内部 未払金 | N198: 30,000 | Q198: / | S198: 内部 未収金 | Z198: 30,000
D200: （消費税の取消1.）
Q202: / | S202: 内部 未収金 | Z202: 3,000
Q203: / | S203: 内部 預り金（消費税） | Z203: -3,000 | AE203: 差額（消費税）を取消
D205: （消費税の取消2.）
G207: 内部 未払金 | N207: 3,000 | Q207: /
G208: 内部 立替金（消費税） | N208: -3,000 | Q208: / | AE208: 差額（消費税）を取消
