Workbook
Name 【債権】最新データ辞書: [1]データ辞書!$H$331:$O$5000
Name 項目辞書: [2]項目辞書!$A$3:$G$1238
Name 項目辞書: [3]項目辞書!$A$3:$G$1522

Sheet 表紙
F46: ProActive
B48: 変更履歴
B50: 項番 | C50: 変更発生日 | D50: 変更者 | E50: 変更箇所 | F50: 変更内容
B51: 1 | C51: 45898 | D51: SCSK大西 | F51: 新規作成
B52: 2
B53: 3
B54: 4
B55: 5
B56: 6
B57: 7
B58: 8
B59: 9
B60: 10
B61: 11
B62: 12
B63: 13
... B80: 30

Sheet 業務機能概要
A1: ドキュメント名 | L1: サブシステム | Q1: 業務機能名 | AJ1: 作成者 | AO1: =表紙!D51 -> SCSK大西 | AT1: 更新者
A2: 業務機能概要書 | G2: 業務機能概要 | L2: 債務管理 | Q2: 支払依頼データ自動取込 | AJ2: 作成日付 | AO2: =表紙!C51 -> 45898 | AT2: 更新日付
B4: 【目的・役割】
C5: ・ | D5: ホクレン様の債務管理業務は、ProActiveC4債務管理とスクラッチ開発機能にて実施する想定である。
D6: それぞれの機能のすみ分けは以下のとおり。
D8: ① | E8: 仕入（支払発生）取引入力 | S8: ・・・スクラッチ開発機能 or 部門システム
D9: ② | E9: 支払予定確認 | S9: ・・・ProActiveC4
D10: ③ | E10: 支払予定修正 | S10: ・・・ProActiveC4
D11: ④ | E11: 相殺 | S11: ・・・スクラッチ開発機能
D12: ⑤ | E12: 支払処理（FBデータ送信含む） | S12: ・・・ProActiveC4
D13: ⑥ | E13: 支払案内書作成、送付 | S13: ・・・スクラッチ開発機能
D15: 伝票入力は部門システムやスクラッチ開発機能で実施するため、ProActiveC4では、支払の業務データを外部のシステムから取込する必要がある。
D16: 支払の業務データの取込はバッチ処理で実行して、夜間処理後の翌営業日、または即時にProActiveC4で参照、更新するような状態となることが必要である。
B19: 【利用者】
C20: ・ | D20: バッチ実行
B23: 【利用頻度】
C24: ・ | D24: 随時
B27: 【対象要件定義書】
C28: ・ | D28: 要件定義書(他システムとのデータ連動)
B31: 【処理概要】
C32: １) | D32: ファイルによってデータ連動される支払の業務データ（取引計上単位（ProActiveC4では「支払依頼伝票」の単位））をProActiveC4標準の「支払外部データ取込」の処理を
D33: 使用してProActiveC4に取込する。
D34: ※ | E34: ホクレン様の業務では1日あたりの支払の業務データは最大で約30万件である。
E35: 取込処理のパフォーマンス向上のため、1万件×30ファイル（＝30万件）に分割して連動された支払の業務データを並列で取込する。（前提・制約事項を参照）
D49: 当機能の責任範囲は以下となる。
D50: ※ | E50: スクラッチ開発機能から作成、連動される連動データ（CSVファイル）は、当機能の実行前に、ProActiveC4サーバ上から参照可能な取込ディレクトリに配置される想定とする。
D51: ※ | E51: 「支払外部データ取込バッチ」はProActiveC4外のタスク管理用ミドルウェア（以下、タスクスケジューラ）から実行する想定とする。
D52: ※ | E52: 「支払外部データ取込バッチ」は連動データ（CSVファイル）ごとに起動される想定とする。（処理結果も連動データごとにタスクスケジューラへ返却する）
AM55: ※ | AN55: 取込ディレクトリはProActiveC4の
AN56: バッチサーバ上から参照可能なディレクトリ
L62: 起動 | AB62: 参照
L64: 結果返却
Q70: 退避
AJ71: 登録
C94: ２) | D94: バッチ実行される「支払外部データ取込」について、以下の処理を実施する。
E96: ・ | F96: 取込ディレクトリに配置されている連動データ（取込用のCSVファイル）の情報を取得する。
F97: 取込データが取得できた場合は、取込ファイルをINPUTとして、「支払外部データ取込」をバッチ実行する。（オンライン機能「支払外部データ取込」の取込動作を踏襲する。）
F98: ※ | G98: 標準の「支払外部データ取込」はオンライン処理可能なままとする。
E100: ・ | F100: 「支払外部データ取込」のバッチ処理実行結果をバッチジョブ情報に登録する。（標準仕様に準じる）
E102: ・ | F102: 取込処理後、取込用のCSVファイルは処理済用ファイルのディレクトリに移動する。
F103: ※ | G103: アプリケーションではなく、バッチファイルで処理済ファイルを移動する。
F104: ※ | G104: 正常用、エラー用のディレクトリを作成して処理結果によって移動先ディレクトリを分岐させる。
E106: ・ | F106: バッチ処理実行結果の終了情報をタスクスケジューラに返却する。
F108: [実行情報]
F109: No | H109: パラメータ | Q109: 内容
F110: 1 | H110: ※イベント概要参照
F112: [終了情報]
F113: 戻り値 | H113: 内容 | Q113: 内容
F114: 0 | H114: 正常終了
F115: 1 | H115: 異常終了 | Q115: 業務エラー/システムエラー発生時
B119: 【共通要件】
D120: 共通要件内容 | J120: 対応内容（標準準拠の場合、記載省略）
D121: セキュリティ | J121: 部門制限、本人制限の機能性は実装しない。
D122: 承認WF | J122: 対応なし。承認WFの利用は不可とする。
D123: 組織変更 | J123: 対応なし。当機能は仕訳に関係しないため、組織変更を考慮しない。
B139: 【前提・制約事項】
C140: １) | D140: ProActiveC4の「支払外部データ取込」機能では、固定の取込フォーマットがあるため、該当するフォーマットに合わせて連動データが作成される前提とする。
D141: また、支払の業務データを1万件ごとに分割して連動データが作成される前提とする。
D142: （データ作成は、連動元システムまたは、連動処理（ProActiveC4外）で実施する。）
C145: ２) | D145: ProActiveC4の「支払外部データ取込」機能では、1ファイルにつき、支払の業務データが10万件を超えるもの、または、ファイルサイズが35MBを超えるものは取込不可となる。
D146: また、ヘッダ行があるデータは取込不可となるため、ProActiveC4に連動されるデータ（CSVファイル）はヘッダ行がない状態で作成される前提とする。
C148: ３) | D148: ProActiveC4に連動されるデータ（CSVファイル）はファイルごとに異なる「担当部門コード」を採番される前提とする。
D149: 「担当部門コード」を分けることでProActiveC4内部で以下のような処理が実施される。
D150: ProActiveC4標準の「自動採番メンテナンス」機能にて、採番コード＝401、402の体系（支払依頼番号、支払依頼取込番号）を
D151: 「年1桁」+「月度1桁」+「部門採番コード」＋連番7桁とする。（999万伝票／月まで起票可能）
D152: これによって、「担当部門コード」ごとに採番されるようになり、採番の競合が軽減され、取込処理のパフォーマンスが向上する。
D153: ※ | E153: 「担当部門コード」はホクレン様の業務上、重要な意味を持たない情報であるため、上記対応を実施しても影響はない。
C155: ４) | D155: ProActiveC4に連動されるデータ（CSVファイル）の以下の取込項目について、ProActiveC4のマスタ情報に合わせてデータが作成される前提とする。（補足参照）
E157: ・ | F157: 「部門コード」には、「事業所コード」+「部課コード」＋「業種コード」で指定する。
C161: ５) | D161: ProActiveC4に連動されるデータ（CSVファイル）のファイル名は「shhariimp_」にシステム日時（タイムスタンプ）を付加した名称であることを前提とする。
D162: 例） | F162: shhariimp_YYYYMMDDHHMMSSmmm.csv
D163: 当機能で使用する各バッチファイルのパラメータには、上記の名称を取込ファイルとして定義する。
C165: ６) | D165: ProActiveC4に連動されるデータ（CSVファイル）は、ProActiveC4のバッチサーバから参照可能な一時保管用のディレクトリに配置されることを前提とする。
C168: ７) | D168: 「支払外部データ取込」をバッチ実行した情報は、ProActiveC4標準の「バッチジョブ」として扱われ、「バッチジョブ一覧検索」機能で状況の確認が可能となる。
D169: 状況の確認は上記機能で実施する方針として、個別にエラーログ出力等の機能性は開発しない。
C171: ８) | D171: ProActiveC4標準の「支払外部データ取込」処理を改修せずバッチ実行する。
D172: 以下のようなケースでは、標準の取込処理にも改修が必要となるため、別途対応工数を見積もることとする。
E173: ① | F173: 禁止文字の置き換え、エスケープ文字の考慮が取込処理側で必要となる。（文字を置き換えした上で取込処理が必要となる。）
C175: ９) | D175: 以下のProActiveC4禁止文字は連動ファイルにて使用しない前提とする。
E177: 禁止文字 | J177: 名称
E178: ― | J178: ダッシュ（全角）
E179: ∥ | J179: 双柱
E180: ￤ | J180: 破断線
C184: １０) | D184: ProActiveC4へ連動するファイルはコマンドにて移動等の操作を実施するため、ファイル名には空白を使用しない前提とする。
C186: １１) | D186: 取込処理後、処理済用ファイルのディレクトリに移動された取込用のCSVファイルは「エラー終了検知バッチ」実行後に削除する想定とする。
D187: （削除処理は、当機能とは別にファイル削除処理を作成して、その処理で実施する）
B190: 【主な取り扱い情報】
C191: ①バッチ実行時
D192: № | E192: 取り扱う情報 | O192: I/O | Q192: 用途
D193: 1 | E193: 支払依頼データ | O193: OUT | Q193: 支払依頼データを登録する。
D194: ２ | E194: バッチジョブ | O194: OUT | Q194: バッチ実行結果を反映する。
D195: ３ | E195: バッチジョブエラー | O195: OUT | Q195: バッチ実行結果を反映する。

Sheet 画面遷移図
A1: ドキュメント名 | L1: サブシステム | Q1: 業務機能名 | AJ1: 作成者 | AO1: =表紙!D51 -> SCSK大西 | AT1: 更新者 | AY1: SCSK相坂
A2: 業務機能概要書 | G2: 画面遷移図 | L2: =#REF! -> #REF! | Q2: =#REF! -> #REF! | AJ2: 作成日付 | AO2: =表紙!C51 -> 45898 | AT2: 更新日付 | AY2: 44103
B4: 【メニュー起動時の画面遷移】

Sheet 画面レイアウト
A1: ドキュメント名 | AH1: サブシステム | AX1: 業務機能名 | DF1: 作成者 | DV1: =表紙!D51 -> SCSK大西 | EL1: 更新者
A2: 業務機能概要書 | R2: 画面レイアウト | AH2: =#REF! -> #REF! | AX2: =#REF! -> #REF! | DF2: 作成日付 | DV2: =表紙!C51 -> 45898 | EL2: 更新日付
A3: 画面名 | FD3: 画面№ | FM3: ①
B4: 0 | H4: 40 | R4: 110 | AB4: 180 | AL4: 250 | AV4: 320 | BF4: 390 | BP4: 460 | BZ4: 530 | CJ4: 600 | CT4: 670 | DD4: 740 | DN4: 810 | DX4: 880 | EH4: 950 | EO4: 999 | ER4: ＜補足説明＞
A5: 0
A6: 5
A7: 20
A8: 35
A9: 50
A10: 65
A11: 80
A12: 95
A13: 110
A14: 125
A15: 140
A16: 155
... A47: 620
A57: 画面名 | J57: 自動消込確定情報登録画面 | FD57: 画面№ | FM57: ②
B58: 0 | H58: 40 | R58: 110 | AB58: 180 | AL58: 250 | AV58: 320 | BF58: 390 | BP58: 460 | BZ58: 530 | CJ58: 600 | CT58: 670 | DD58: 740 | DN58: 810 | DX58: 880 | EH58: 950 | EO58: 999 | ER58: ＜補足説明＞
A59: 0
A60: 5
A61: 20
A62: 35
A63: 50
A64: 65
A65: 80
A66: 95
A67: 110
A68: 125
A69: 140
A70: 155
... A101: 620
A111: 画面名 | FD111: 画面№ | FM111: ①
B112: 0 | H112: 40 | R112: 110 | AB112: 180 | AL112: 250 | AV112: 320 | BF112: 390 | BP112: 460 | BZ112: 530 | CJ112: 600 | CT112: 670 | DD112: 740 | DN112: 810 | DX112: 880 | EH112: 950 | EO112: 999 | ER112: ＜補足説明＞
A113: 0
A114: 5
A115: 20
A116: 35
A117: 50
A118: 65
A119: 80
A120: 95
A121: 110
A122: 125
A123: 140
A124: 155
... A155: 620
A165: 画面名 | FD165: 画面№ | FM165: ①
B166: 0 | H166: 40 | R166: 110 | AB166: 180 | AL166: 250 | AV166: 320 | BF166: 390 | BP166: 460 | BZ166: 530 | CJ166: 600 | CT166: 670 | DD166: 740 | DN166: 810 | DX166: 880 | EH166: 950 | EO166: 999 | ER166: ＜補足説明＞
A167: 0
A168: 5
A169: 20
A170: 35
A171: 50
A172: 65
A173: 80
A174: 95
A175: 110
A176: 125
A177: 140
A178: 155
... A209: 620
C221: 出力されるCSVファイル例

Sheet 項目概要
A1: ドキュメント名 | L1: サブシステム | Q1: 業務機能名 | AJ1: 作成者 | AO1: =表紙!D51 -> SCSK大西 | AT1: 更新者 | BE1: ○ | BF1: IN | BG1: 文字列
A2: 業務機能概要書 | G2: 項目概要 | L2: =#REF! -> #REF! | Q2: =#REF! -> #REF! | AJ2: 作成日付 | AO2: =表紙!C51 -> 45898 | AT2: 更新日付 | BE2: － | BF2: OUT | BG2: 数値
BF3: IN/OUT | BG3: 半英数
A4: 【画面項目説明】 | BG4: 半カナ
BG5: コード
B6: [①自動消込確定情報登録画面] | AQ6: ※追加及び変更項目のみ記載 | BG6: 日付
B7: № | C7: ラベル | J7: 項目名 | Q7: I/O | S7: 必須 | U7: 型 | W7: 桁数 | Y7: ソート | AA7: 初期表示 | AE7: 備考 | BG7: －
B8: 【ヘッダ部】
B9: 1 | C9: 一覧を最大化 | J9: 一覧を最大化ボタン | Q9: IN | S9: － | U9: － | W9: － | Y9: ー | AA9: ー
B10: 2 | Q10: IN | S10: ○ | U10: 日付 | W10: 8 | Y10: ー | AA10: システム日付
B11: 3 | Q11: OUT | S11: － | U11: コード | W11: 12 | Y11: ー | AA11: ー
B12: 4 | Q12: IN | S12: ○ | U12: コード | W12: 10 | Y12: ー | AA12: ー
Q13: IN | S13: － | U13: － | W13: ー | Y13: ー | AA13: ー
Q14: OUT | S14: － | U14: 文字列 | W14: 20 | Y14: ー | AA14: ー
B15: 5 | Q15: IN | S15: ○ | U15: コード | W15: 15 | Y15: ー | AA15: ー
Q16: IN | S16: － | U16: － | W16: ー | Y16: ー | AA16: ー
Q17: OUT | S17: － | U17: 文字列 | W17: 20 | Y17: ー | AA17: ー
B18: 6 | Q18: IN | S18: ○ | U18: － | W18: ー | Y18: ー
B20: 7 | Q20: IN | S20: ○ | U20: 数値 | W20: 13 | Y20: ー | AA20: ー
B21: 【】
B22: 1
B25: 2
B28: 3
B30: 4
B31: 5
B32: 【】 | AE32: ※ソート順は画面レイアウトシートの補足説明欄参照。
B33: 1
B34: 2
B35: 2
B36: 3
B37: 2
B38: 3
B39: 4
B40: 5
B41: 6
B42: 7
B43: 8
B44: 9
... B52: 16
B53: 【フッタ部】
B54: 1
B55: 2
B57: 3
B58: 4
B59: 5
B60: 6
B61: 7
B62: 8
B63: 9
B64: 10

Sheet イベント概要
A1: ドキュメント名 | L1: サブシステム | Q1: 業務機能名 | AJ1: 作成者 | AO1: =表紙!D51 -> SCSK大西 | AT1: 更新者
A2: 業務機能概要書 | G2: イベント概要 | L2: =業務機能概要!L2 -> 債務管理 | Q2: =業務機能概要!Q2 -> 支払依頼データ自動取込 | AJ2: 作成日付 | AO2: =表紙!C51 -> 45898 | AT2: 更新日付
A4: 【イベント処理】
B6: № | C6: イベント名 | J6: 処理説明
B7: =IF(C7="","",MAX(B$6:B6)+1) -> 1 | C7: 支払依頼データ自動取込 | J7: １. | L7: 取込ディレクトリに配置された取込用のCSVファイルをINPUTとし、ProActiveC4標準機能の「支払外部データ取込」を実行する。
C8: バッチイベント | L8: ＜パラメータ＞
L9: ・ | M9: 会社コード | U9: ： | V9: バッチ実行用のxmlで指定された会社コード
L10: ・ | M10: 仕訳計上 | U10: ： | V10: バッチ実行用のxmlファイルで指定された取込反映時の自動仕訳を計上するか否かのフラグ（計上しないとする）
L11: ・ | M11: 取込CSVファイル | U11: ： | V11: バッチ実行用のxmlで指定されたファイル
B13: =IF(C13="","",MAX(B$6:B6)+1) | L13: 取込用のCSVファイルが取得できなかった場合は、取込処理は実行されない。
B14: =IF(C14="","",MAX(B$6:B13)+1) | L14: 取込用のCSVファイルが取得できた場合は、後続の処理を継続する。
B15: =IF(C15="","",MAX(B$6:B14)+1) | L15: ※ | M15: 上記のファイル取得、エラーハンドリングはバッチファイルで実施する（アプリケーションでの考慮は不要）
B16: =IF(C16="","",MAX(B$6:B15)+1) | L16: ※ | M16: 取込用CSVのファイルサイズが0byteの場合は、正常として処理終了する。（バッチファイルにてファイルを正常処理フォルダへ移動する）
B17: =IF(C17="","",MAX(B$6:B16)+1)
B18: =IF(C18="","",MAX(B$6:B13)+1) | J18: ２. | L18: 「支払外部データ取込」のバッチ処理実行結果をバッチジョブ情報に登録する。（標準仕様に準じる）
B19: =IF(C19="","",MAX(B$6:B8)+1)
B20: =IF(C20="","",MAX(B$6:B19)+1) | J20: ３. | L20: 取込処理後、取込用のCSVファイルは処理済用ファイルのディレクトリに移動する。
B21: =IF(C21="","",MAX(B$6:B20)+1) | L21: ※ | M21: 正常用、エラー用のディレクトリを作成して、処理結果によって移動先ディレクトリを分岐させる。
B23: =IF(C23="","",MAX(B$6:B21)+1) | J23: ４. | L23: バッチ処理実行結果の終了情報をタスクスケジューラに返却する。
B24: =IF(C24="","",MAX(B$6:B23)+1) | L24: ■ | M24: 正常終了できた場合
N25: 「0:正常終了」
L26: ■ | M26: エラーが発生した場合（※ProActiveC4標準機能のデータ取込でエラーが発生した場合は当ケースに該当する）
N27: 「1:異常終了」
B28: =IF(C28="","",MAX(B$6:B27)+1)
B29: =IF(C29="","",MAX(B$6:B28)+1)
B31: =IF(C31="","",MAX(B$6:B30)+1)
B32: =IF(C32="","",MAX(B$6:B31)+1)
B33: =IF(C33="","",MAX(B$6:B32)+1)
B34: =IF(C34="","",MAX(B$6:B33)+1)
B41: =IF(C41="","",MAX(B$6:B40)+1)
B42: =IF(C42="","",MAX(B$6:B41)+1)
B43: =IF(C43="","",MAX(B$6:B42)+1)
B44: =IF(C44="","",MAX(B$6:B43)+1)
B45: =IF(C45="","",MAX(B$6:B44)+1)
B46: =IF(C46="","",MAX(B$6:B45)+1)

Sheet チェック仕様
A1: ドキュメント名 | L1: サブシステム | Q1: 業務機能名 | AJ1: 作成者 | AO1: =表紙!D51 -> SCSK大西 | AT1: 更新者
A2: 業務機能概要書 | G2: チェック仕様 | L2: =#REF! -> #REF! | Q2: =#REF! -> #REF! | AJ2: 作成日付 | AO2: =表紙!C51 -> 45898 | AT2: 更新日付
A4: 【チェック処理】
B6: １．初期処理時
B7: № | C7: 項目名 | L7: 条件必須 | O7: 存在 | R7: 範囲 | U7: 関連 | X7: その他 | AA7: 内容
B8: =IF(C8="","",MAX(B7:B$7)+1) -> 1 | C8: － | X8: ○
B9: =IF(C9="","",MAX(B$7:B8)+1)
B10: =IF(C10="","",MAX(B$7:B9)+1)
B11: =IF(C11="","",MAX(B$7:B10)+1)
B13: ２．検索ボタン押下時
B14: № | C14: 項目名 | L14: 条件必須 | O14: 存在 | R14: 範囲 | U14: 関連 | X14: その他 | AA14: 内容
B15: =IF(C15="","",MAX(B$14:B14)+1)
B16: =IF(C16="","",MAX(B$14:B15)+1)
B17: =IF(C17="","",MAX(B$14:B16)+1)
B18: =IF(C18="","",MAX(B$14:B17)+1)
B19: =IF(C19="","",MAX(B$14:B18)+1)
B20: =IF(C20="","",MAX(B$14:B19)+1)
B21: =IF(C21="","",MAX(B$14:B20)+1)
B22: =IF(C22="","",MAX(B$14:B21)+1)
B23: =IF(C23="","",MAX(B$14:B22)+1)
B24: =IF(C24="","",MAX(B$14:B23)+1)
B25: =IF(C25="","",MAX(B$14:B24)+1)
B26: =IF(C26="","",MAX(B$14:B25)+1)
... B31: =IF(C31="","",MAX(B$14:B30)+1)
B33: ３．データ取込ボタン
B34: № | C34: 項目名 | L34: 条件必須 | O34: 存在 | R34: 範囲 | U34: 関連 | X34: その他 | AA34: 内容
B35: =IF(C35="","",MAX(B$34:B34)+1)
B36: =IF(C36="","",MAX(B$34:B35)+1)
B37: =IF(C37="","",MAX(B$34:B36)+1)
B38: =IF(C38="","",MAX(B$34:B37)+1)
B39: =IF(C39="","",MAX(B$34:B38)+1)
B40: =IF(C40="","",MAX(B$34:B39)+1)
B41: =IF(C41="","",MAX(B$34:B40)+1)
B42: =IF(C42="","",MAX(B$34:B41)+1)
B43: =IF(C43="","",MAX(B$34:B42)+1)
B44: =IF(C44="","",MAX(B$34:B40)+1)
B45: =IF(C45="","",MAX(B$34:B44)+1)
B46: =IF(C46="","",MAX(B$34:B45)+1)
B47: 4
B48: =IF(C48="","",MAX(B$34:B47)+1)
B49: 4
B50: =IF(C50="","",MAX(B$34:B49)+1)
B51: =IF(C51="","",MAX(B48:B$60)+1)
B52: =IF(C52="","",MAX(B46:B$60)+1)
B53: =IF(C53="","",MAX(B47:B$60)+1)
B54: =IF(C54="","",MAX(B48:B$60)+1)
B55: =IF(C55="","",MAX(B51:B$60)+1)
B56: =IF(C56="","",MAX(B$7:B51)+1)
B57: =IF(C57="","",MAX(B$34:B48)+1)
B59: ４．登録ボタン
B60: № | C60: 項目名 | L60: 条件必須 | O60: 存在 | R60: 範囲 | U60: 関連 | X60: その他 | AA60: 内容
B62: =IF(C62="","",MAX(B$60:B61)+1)
B63: =IF(C63="","",MAX(B$60:B62)+1)
B64: =IF(C64="","",MAX(B$60:B63)+1)
B65: =IF(C65="","",MAX(B$60:B64)+1)
B66: =IF(C66="","",MAX(B$60:B65)+1)
B67: =IF(C67="","",MAX(B$60:B66)+1)
B68: =IF(C68="","",MAX(B$60:B67)+1)
B69: =IF(C69="","",MAX(B$60:B68)+1)
B70: =IF(C70="","",MAX(B$60:B69)+1)
B71: =IF(C71="","",MAX(B$60:B70)+1)
B72: =IF(C72="","",MAX(B$60:B71)+1)
B73: =IF(C73="","",MAX(B$60:B72)+1)
... B92: =IF(C92="","",MAX(B$60:B91)+1)

Sheet 出力CSV定義
A1: ドキュメント名 | E1: サブシステム | G1: 業務機能名 | P1: 作成者 | R1: =表紙!D51 -> SCSK大西 | T1: 更新者
A2: 業務機能概要書 | C2: 出力CSV定義 | E2: =#REF! -> #REF! | G2: =#REF! -> #REF! | P2: 作成日 | R2: =表紙!C51 -> 45898 | T2: 更新日
A4: データ名 | I4: ヘッダ行 | K4: あり | M4: なし | N4: ダブルクォーテーション | Q4: あり | S4: なし | X4: 文字列
A5: ﾌｧｲﾙ形式・ﾚｺｰﾄﾞ長 | D5: 固定長（ | G5: Byte） | I5: 可変長（区切り文字［ ，(カンマ) ］） | M5: バイナリデータ | P5: その他（ ） | X5: 半英数
A6: 文字コード | D6: UNI（Win系） | F6: EBCDIC(K) | I6: その他（UTF-8） | M6: 改行コード | O6: LF(UNIX系) | Q6: CRLF(Win系) | T6: なし | X6: 半カナ
A7: 全角(2byte)文字項目 | D7: あり | F7: なし | M7: 数値編集 | O7: 左詰め | Q7: 右詰め［ゼロ埋め］ | T7: 右詰め［スペース埋め］ | X7: コード
A8: 特記事項 | C8: 出力順：起票日付、仕訳伝票番号、仕訳自動作成フラグ、仕訳伝票行番号 | J8: ※「"」が含まれる項目は「""」に変換する。 | X8: 数値
A9: No. | B9: 項目名 | E9: 必須 | F9: 型 | G9: 桁数 | H9: 開始位置 | I9: 備考 | X9: 日付
H10: /列 | X10: 時間
A11: 1 | F11: 日付 | G11: 8 | H11: A | X11: 年月
A12: 2 | F12: 半英数 | G12: 12 | H12: B | X12: 区分
A13: 3 | F13: コード | G13: 10 | H13: C | X13: フラグ
A14: 4 | F14: 文字列 | G14: 40 | H14: D | X14: -
A15: 5
A16: 6
A17: 7
A18: 8
A19: 9
A20: 10
A21: 11
A22: 12
A23: 13
A24: 14
A25: 15

Sheet 出力CSVサンプル

Sheet 取込フォーマット定義（通常支払）
A1: ドキュメント名 | E1: サブシステム | G1: 業務機能名 | P1: 作成者 | R1: =表紙!D51 -> SCSK大西 | T1: 更新者
A2: 業務機能概要書 | C2: 取込フォーマット定義 | E2: =業務機能概要!L2 -> 債務管理 | G2: =業務機能概要!Q2 -> 支払依頼データ自動取込 | P2: 作成日 | R2: =表紙!C51 -> 45898 | T2: 更新日
A4: データ名 | C4: 支払依頼データ | I4: ヘッダ行 | K4: あり | M4: なし | N4: ダブルクォーテーション | Q4: あり | S4: なし | X4: 文字列
A5: ﾌｧｲﾙ形式・ﾚｺｰﾄﾞ長 | D5: 固定長（ | G5: Byte） | I5: 可変長（区切り文字［ ，(カンマ) ］） | M5: バイナリデータ | P5: その他（ ） | X5: 半英数
A6: 文字コード | D6: UNI（Win系） | F6: EBCDIC(K) | I6: その他（ UTF-8） | M6: 改行コード | O6: LF(UNIX系) | Q6: CRLF(Win系) | T6: なし | X6: 半カナ
A7: 全角(2byte)文字項目 | D7: あり | F7: なし | M7: 数値編集 | O7: 左詰め | Q7: 右詰め［ゼロ埋め］ | T7: 右詰め［スペース埋め］ | X7: コード
A8: 特記事項 | C8: ProActiveC4へ支払依頼データを連動する際には、債務計上の仕訳データを別途連動する必要がある。 | X8: 数値
A9: No. | B9: 項目名 | E9: 必須 | F9: 型 | G9: 桁数 | H9: 開始位置 | I9: 備考 | Q9: 設定値 | X9: 日付
H10: /列 | X10: 時間
A11: =MAX($A$10:$A10)+1 -> 1 | B11: 支払依頼取込参照番号 | E11: △ | F11: 文字列 | G11: 20 | H11: =SUBSTITUTE(SUBSTITUTE(ADDRESS(1,A11),"$1",""),"$","") -> A | I11: 空白（設定不要） | Q11: 設定なし | X11: 年月
A12: =MAX($A$10:$A11)+1 -> 2 | B12: 取引日付 | E12: 〇 | F12: 日付 | G12: 8 | H12: =SUBSTITUTE(SUBSTITUTE(ADDRESS(1,A12),"$1",""),"$","") -> B | I12: 経理日 | Q12: 債務明細データ・経理日 | X12: 区分
A13: =MAX($A$10:$A12)+1 -> 3 | B13: 担当部門表示コード | E13: 〇 | F13: コード | G13: 10 | H13: =SUBSTITUTE(SUBSTITUTE(ADDRESS(1,A13),"$1",""),"$","") -> C | I13: 取込処理のパフォーマンス向上のため、分割されたファイルごとに異なる部門コードを指定する必要がある。 | Q13: 債務明細データ・未払金管理組織コードより組織体系マスタに合わせて変換
I14: ただし、ProActiveの組織体系マスタに登録済のコードである必要がある。
A15: =MAX($A$10:$A13)+1 -> 4 | B15: 確証番号 | F15: 文字列 | G15: 20 | H15: =SUBSTITUTE(SUBSTITUTE(ADDRESS(1,A15),"$1",""),"$","") -> D | I15: 発生元システム管理No.（前渡金と振替する対象のデータを識別する） ※「納品書番号」に相当する（20桁） | Q15: 債務明細データ・債務受付番号(15桁)+債務明細データ・債務明細連番(2桁)
A16: =MAX($A$10:$A15)+1 -> 5 | B16: 取引件名 | F16: 文字列 | G16: 80 | H16: =SUBSTITUTE(SUBSTITUTE(ADDRESS(1,A16),"$1",""),"$","") -> E | I16: 取引内容の説明 | Q16: 債務発生元の仕訳データに設定された仕訳摘要
A17: =MAX($A$10:$A16)+1 -> 6 | B17: 取引指定区分 | E17: 〇 | F17: 区分 | G17: 1 | H17: =SUBSTITUTE(SUBSTITUTE(ADDRESS(1,A17),"$1",""),"$","") -> F | I17: 取引の種類（1.通常取引、2.諸口取引） | Q17: 1:通常取引
A18: =MAX($A$10:$A17)+1 -> 7 | B18: 取引先コード | E18: 〇 | F18: コード | G18: 15 | H18: =SUBSTITUTE(SUBSTITUTE(ADDRESS(1,A18),"$1",""),"$","") -> G | I18: 取引する相手先を識別する9桁コード ※債務科目を取引先別計上する場合、債務科目の内訳情報となる | Q18: 債務明細データ・支払先区分＋支払先コード(法人+枝番)
A19: =MAX($A$10:$A18)+1 -> 8 | B19: 諸口取引先名１ | E19: △ | F19: 文字列 | G19: 50 | H19: =SUBSTITUTE(SUBSTITUTE(ADDRESS(1,A19),"$1",""),"$","") -> H | I19: 設定不要 | Q19: 設定なし
A20: =MAX($A$10:$A19)+1 -> 9 | B20: 諸口取引先名２ | F20: 文字列 | G20: 50 | H20: =SUBSTITUTE(SUBSTITUTE(ADDRESS(1,A20),"$1",""),"$","") -> I | I20: 設定不要 | Q20: 設定なし
A21: =MAX($A$10:$A20)+1 -> 10 | B21: 諸口取引先名（カナ） | E21: △ | F21: 文字列 | G21: 40 | H21: =SUBSTITUTE(SUBSTITUTE(ADDRESS(1,A21),"$1",""),"$","") -> J | I21: 設定不要 | Q21: 設定なし
A22: =MAX($A$10:$A21)+1 -> 11 | B22: 諸口取引先名（略） | E22: △ | F22: 文字列 | G22: 20 | H22: =SUBSTITUTE(SUBSTITUTE(ADDRESS(1,A22),"$1",""),"$","") -> K | I22: 設定不要 | Q22: 設定なし
A23: =MAX($A$10:$A22)+1 -> 12 | B23: 郵便番号 | F23: 文字列 | G23: 10 | H23: =SUBSTITUTE(SUBSTITUTE(ADDRESS(1,A23),"$1",""),"$","") -> L | I23: 設定不要 | Q23: 設定なし
A24: =MAX($A$10:$A23)+1 -> 13 | B24: 諸口住所１ | F24: 文字列 | G24: 100 | H24: =SUBSTITUTE(SUBSTITUTE(ADDRESS(1,A24),"$1",""),"$","") -> M | I24: 設定不要 | Q24: 設定なし
A25: =MAX($A$10:$A24)+1 -> 14 | B25: 諸口住所２ | F25: 文字列 | G25: 100 | H25: =SUBSTITUTE(SUBSTITUTE(ADDRESS(1,A25),"$1",""),"$","") -> N | I25: 設定不要 | Q25: 設定なし
A26: =MAX($A$10:$A25)+1 -> 15 | B26: 諸口TEL | F26: 文字列 | G26: 20 | H26: =SUBSTITUTE(SUBSTITUTE(ADDRESS(1,A26),"$1",""),"$","") -> O | I26: 設定不要 | Q26: 設定なし
A27: =MAX($A$10:$A26)+1 -> 16 | B27: 諸口FAX | F27: 文字列 | G27: 20 | H27: =SUBSTITUTE(SUBSTITUTE(ADDRESS(1,A27),"$1",""),"$","") -> P | I27: 設定不要 | Q27: 設定なし
A28: =MAX($A$10:$A27)+1 -> 17 | B28: 振込先金融機関コード | E28: △ | F28: コード | G28: 4 | H28: =SUBSTITUTE(SUBSTITUTE(ADDRESS(1,A28),"$1",""),"$","") -> Q | I28: 設定不要 | Q28: 設定なし
A29: =MAX($A$10:$A28)+1 -> 18 | B29: 振込先金融機関店舗コード | E29: △ | F29: コード | G29: 3 | H29: =SUBSTITUTE(SUBSTITUTE(ADDRESS(1,A29),"$1",""),"$","") -> R | I29: 設定不要 | Q29: 設定なし
A30: =MAX($A$10:$A29)+1 -> 19 | B30: 振込先銀行口座種別区分 | E30: △ | F30: 区分 | G30: 1 | H30: =SUBSTITUTE(SUBSTITUTE(ADDRESS(1,A30),"$1",""),"$","") -> S | I30: 設定不要 | Q30: 設定なし
A31: =MAX($A$10:$A30)+1 -> 20 | B31: 振込先銀行口座番号 | E31: △ | F31: 文字列 | G31: 7 | H31: =SUBSTITUTE(SUBSTITUTE(ADDRESS(1,A31),"$1",""),"$","") -> T | I31: 設定不要 | Q31: 設定なし
A32: =MAX($A$10:$A31)+1 -> 21 | B32: 振込先郵便口座番号 | E32: △ | F32: 文字列 | G32: 13 | H32: =SUBSTITUTE(SUBSTITUTE(ADDRESS(1,A32),"$1",""),"$","") -> U | I32: 設定不要 | Q32: 設定なし
A33: =MAX($A$10:$A32)+1 -> 22 | B33: 振込先口座名義人 | E33: △ | F33: 文字列 | G33: 50 | H33: =SUBSTITUTE(SUBSTITUTE(ADDRESS(1,A33),"$1",""),"$","") -> V | I33: 設定不要 | Q33: 設定なし
A34: =MAX($A$10:$A33)+1 -> 23 | B34: 振込先口座名義人（カナ） | E34: △ | F34: 文字列 | G34: 30 | H34: =SUBSTITUTE(SUBSTITUTE(ADDRESS(1,A34),"$1",""),"$","") -> W | I34: 設定不要 | Q34: 設定なし
A35: =MAX($A$10:$A34)+1 -> 24 | B35: 先方負担振込手数料フラグ | E35: △ | F35: フラグ | G35: 1 | H35: =SUBSTITUTE(SUBSTITUTE(ADDRESS(1,A35),"$1",""),"$","") -> X | I35: 設定不要 | Q35: 設定なし
A36: =MAX($A$10:$A35)+1 -> 25 | B36: 備考 | F36: 文字列 | G36: 80 | H36: =SUBSTITUTE(SUBSTITUTE(ADDRESS(1,A36),"$1",""),"$","") -> Y | I36: 任意項目。発生元システム管理No.（前渡金と振替する対象のデータを識別する） ※「納品書番号」に相当する（20桁）などを設定する想定。 | Q36: 債務明細データ・発生元システム取引Ｎｏ+発生元システム取引Ｎｏ枝番
A37: =MAX($A$10:$A36)+1 -> 26 | B37: 支払先コード | F37: コード | G37: 15 | H37: =SUBSTITUTE(SUBSTITUTE(ADDRESS(1,A37),"$1",""),"$","") -> Z | I37: 支払先の取引先コード | Q37: 債務明細データ・支払先区分＋支払先コード(法人+枝番)
A38: =MAX($A$10:$A37)+1 -> 27 | B38: 支払締日付 | F38: 日付 | G38: 8 | H38: =SUBSTITUTE(SUBSTITUTE(ADDRESS(1,A38),"$1",""),"$","") -> AA | I38: 空白（設定不要） | Q38: 設定なし
A39: =MAX($A$10:$A38)+1 -> 28 | B39: 支払決済条件コード | F39: コード | G39: 3 | H39: =SUBSTITUTE(SUBSTITUTE(ADDRESS(1,A39),"$1",""),"$","") -> AB | I39: 支払先の決済条件を識別するコード | Q39: 債務明細データ・最新支払方法区分、支払先コードに応じて導出した支払決済条件コード
A40: =MAX($A$10:$A39)+1 -> 29 | B40: 支払締名寄項目 | F40: 文字列 | G40: 20 | H40: =SUBSTITUTE(SUBSTITUTE(ADDRESS(1,A40),"$1",""),"$","") -> AC | I40: 空白（設定不要） | Q40: 設定なし
A41: =MAX($A$10:$A40)+1 -> 30 | B41: 支払予定日付１ | F41: 日付 | G41: 8 | H41: =SUBSTITUTE(SUBSTITUTE(ADDRESS(1,A41),"$1",""),"$","") -> AD | I41: 支払を行う日付 | Q41: 債務明細データ・最新支払予定日
A42: =MAX($A$10:$A41)+1 -> 31 | B42: 支払予定日付２ | F42: 日付 | G42: 8 | H42: =SUBSTITUTE(SUBSTITUTE(ADDRESS(1,A42),"$1",""),"$","") -> AE | I42: 空白（設定不要） | Q42: 設定なし
A43: =MAX($A$10:$A42)+1 -> 32 | B43: 支払依頼取込行番号 | E43: 〇 | F43: 数値 | G43: 4 | H43: =SUBSTITUTE(SUBSTITUTE(ADDRESS(1,A43),"$1",""),"$","") -> AF | I43: 支払依頼取込明細の行番号 | Q43: 1（固定）
A44: =MAX($A$10:$A43)+1 -> 33 | B44: 取引種類コード | E44: 〇 | F44: コード | G44: 8 | H44: =SUBSTITUTE(SUBSTITUTE(ADDRESS(1,A44),"$1",""),"$","") -> AG | I44: 取引種類（計上される費用科目、債務科目の組合せ）を一意に識別するコード | Q44: 債務明細データ・項科目コード、目節科目コード、仕訳種別コードに応じて導出した取引種類コード
A45: =MAX($A$10:$A44)+1 -> 34 | B45: 費用計上部門表示コード | F45: コード | G45: 10 | H45: =SUBSTITUTE(SUBSTITUTE(ADDRESS(1,A45),"$1",""),"$","") -> AH | I45: 費用科目の計上部門コード | L45: ※当案件では当項目は仕訳作成には使用しないため債務計上部門と同じ。 | Q45: 債務計上部門コードと同じコード
A46: =MAX($A$10:$A45)+1 -> 35 | B46: 債務計上部門表示コード | F46: コード | G46: 10 | H46: =SUBSTITUTE(SUBSTITUTE(ADDRESS(1,A46),"$1",""),"$","") -> AI | I46: 債務科目の計上部門コード | L46: ※ProActiveの組織体系マスタに登録済のコードである必要がある | Q46: 債務明細データ・未払金管理組織コードより組織体系マスタに合わせて変換 事象所コード＋業種コード＋所属コード（未払金管理組織）の予定
A47: =MAX($A$10:$A46)+1 -> 36 | B47: 消費税区分 | F47: 区分 | G47: 2 | H47: =SUBSTITUTE(SUBSTITUTE(ADDRESS(1,A47),"$1",""),"$","") -> AJ | I47: 設定不要 | L47: ※未設定時は取引種類の消費税区分が自動で設定される。 | Q47: 設定なし
A48: =MAX($A$10:$A47)+1 -> 37 | B48: 取引金額（税込） | E48: △ | F48: 数値 | G48: 13 | H48: =SUBSTITUTE(SUBSTITUTE(ADDRESS(1,A48),"$1",""),"$","") -> AK | I48: 金額0は入力不可 | Q48: 通常時（債務発生時）：債務明細データ・支払予定金額、 相殺予約承認から連携時：相殺予約データ・相殺金額（明細）* -1債務明細データ・支払予定金額、 仕訳入力の債権債務振替から連携時：仕訳入力明細・借方金額 * -1 or 仕訳入力明細・貸方金額
A49: =MAX($A$10:$A48)+1 -> 38 | B49: 取引金額（税抜） | E49: △ | F49: 数値 | G49: 13 | H49: =SUBSTITUTE(SUBSTITUTE(ADDRESS(1,A49),"$1",""),"$","") -> AL | I49: 設定不要 | Q49: 設定なし
A50: =MAX($A$10:$A49)+1 -> 39 | B50: 消費税額 | F50: 数値 | G50: 13 | H50: =SUBSTITUTE(SUBSTITUTE(ADDRESS(1,A50),"$1",""),"$","") -> AM | I50: 設定不要 | Q50: 設定なし
A51: =MAX($A$10:$A50)+1 -> 40 | B51: 仕訳取引先コード | F51: コード | G51: 15 | H51: =SUBSTITUTE(SUBSTITUTE(ADDRESS(1,A51),"$1",""),"$","") -> AN | I51: 費用科目の内訳情報となる取引先（取引する相手先を識別する）コード | Q51: 債務明細データ・支払先区分＋支払先コード(法人+枝番)
A52: =MAX($A$10:$A51)+1 -> 41 | B52: 仕訳自社口座コード | E52: △ | F52: コード | G52: 8 | H52: =SUBSTITUTE(SUBSTITUTE(ADDRESS(1,A52),"$1",""),"$","") -> AO | I52: 費用科目の内訳情報となる出金を行う銀行口座のコード | Q52: 設定なし
I53: ※費用科目として預金科目を計上する場合、必須（実業務上ないと想定）
A54: =MAX($A$10:$A52)+1 -> 42 | B54: 仕訳プロジェクトコード | E54: △ | F54: コード | G54: 20 | H54: =SUBSTITUTE(SUBSTITUTE(ADDRESS(1,A54),"$1",""),"$","") -> AP | I54: 費用科目の内訳情報となる業種を判別するコード ※費用科目を業種別計上する場合、必須 | Q54: 債務明細データ・業種コード
A55: =MAX($A$10:$A54)+1 -> 43 | B55: 仕訳担当者コード | F55: コード | G55: 15 | H55: =SUBSTITUTE(SUBSTITUTE(ADDRESS(1,A55),"$1",""),"$","") -> AQ | I55: 空白（設定不要） | Q55: 設定なし
A56: =MAX($A$10:$A55)+1 -> 44 | B56: 仕訳セグメントコード | E56: △ | F56: コード | G56: 4 | H56: =SUBSTITUTE(SUBSTITUTE(ADDRESS(1,A56),"$1",""),"$","") -> AR | I56: 費用科目の内訳情報となる会計品目を判別するコード ※費用科目を会計品目別計上する場合、必須 | Q56: 債務明細データ・収支管理品目コードより収支管理品目マスタ・収支管理品目大分類コードに紐づく収支管理品目大分類マスタ・会計情報品目コード
A57: =MAX($A$10:$A56)+1 -> 45 | B57: 仕訳セグメントコード１ | E57: △ | F57: コード | G57: 4 | H57: =SUBSTITUTE(SUBSTITUTE(ADDRESS(1,A57),"$1",""),"$","") -> AS | I57: 空白（設定不要） | Q57: 設定なし
A58: =MAX($A$10:$A57)+1 -> 46 | B58: 仕訳セグメントコード２ | E58: △ | F58: コード | G58: 4 | H58: =SUBSTITUTE(SUBSTITUTE(ADDRESS(1,A58),"$1",""),"$","") -> AT | I58: 空白（設定不要） | Q58: 設定なし
A59: =MAX($A$10:$A58)+1 -> 47 | B59: 仕訳セグメントコード３ | E59: △ | F59: コード | G59: 4 | H59: =SUBSTITUTE(SUBSTITUTE(ADDRESS(1,A59),"$1",""),"$","") -> AU | I59: 空白（設定不要） | Q59: 設定なし
A60: =MAX($A$10:$A59)+1 -> 48 | B60: 仕訳セグメントコード４ | E60: △ | F60: コード | G60: 4 | H60: =SUBSTITUTE(SUBSTITUTE(ADDRESS(1,A60),"$1",""),"$","") -> AV | I60: 空白（設定不要） | Q60: 設定なし
A61: =MAX($A$10:$A60)+1 -> 49 | B61: 仕訳セグメントコード５ | E61: △ | F61: コード | G61: 4 | H61: =SUBSTITUTE(SUBSTITUTE(ADDRESS(1,A61),"$1",""),"$","") -> AW | I61: 空白（設定不要） | Q61: 設定なし
A62: =MAX($A$10:$A61)+1 -> 50 | B62: 費用補助科目コード | F62: コード | G62: 4 | H62: =SUBSTITUTE(SUBSTITUTE(ADDRESS(1,A62),"$1",""),"$","") -> AX | I62: 費用科目の科目摘要を判別するコード | Q62: 債務明細データ・科目摘要コード
A63: =MAX($A$10:$A62)+1 -> 51 | B63: 仕訳摘要 | F63: 文字列 | G63: 80 | H63: =SUBSTITUTE(SUBSTITUTE(ADDRESS(1,A63),"$1",""),"$","") -> AY | I63: 取引内容の説明（総勘定元帳に出力される） | Q63: 債務明細データ・経理日+債務明細データ・仕訳連番に紐づく仕訳ヘッダ・仕訳摘要
A64: =MAX($A$10:$A63)+1 -> 52 | B64: 立替金請求取引先コード | F64: コード | G64: 15 | H64: =SUBSTITUTE(SUBSTITUTE(ADDRESS(1,A64),"$1",""),"$","") -> AZ | I64: 空白（設定不要） | Q64: 設定なし
A65: =MAX($A$10:$A64)+1 -> 53 | B65: 回収予定日付 | F65: 日付 | G65: 8 | H65: =SUBSTITUTE(SUBSTITUTE(ADDRESS(1,A65),"$1",""),"$","") -> BA | I65: 空白（設定不要） | Q65: 設定なし
A66: =MAX($A$10:$A65)+1 -> 54 | B66: 立替金摘要 | F66: 文字列 | G66: 80 | H66: =SUBSTITUTE(SUBSTITUTE(ADDRESS(1,A66),"$1",""),"$","") -> BB | I66: 空白（設定不要） | Q66: 設定なし
A67: =MAX($A$10:$A66)+1 -> 55 | B67: 連携先担当部門コード | F67: コード | G67: 10 | H67: =SUBSTITUTE(SUBSTITUTE(ADDRESS(1,A67),"$1",""),"$","") -> BC | I67: 空白（設定不要） | Q67: 設定なし
A68: =MAX($A$10:$A67)+1 -> 56 | B68: 連携先計上部門コード | F68: コード | G68: 10 | H68: =SUBSTITUTE(SUBSTITUTE(ADDRESS(1,A68),"$1",""),"$","") -> BD | I68: 空白（設定不要） | Q68: 設定なし
A69: =MAX($A$10:$A68)+1 -> 57 | B69: 連携先取引種類コード | E69: △ | F69: コード | G69: 8 | H69: =SUBSTITUTE(SUBSTITUTE(ADDRESS(1,A69),"$1",""),"$","") -> BE | I69: 空白（設定不要） | Q69: 設定なし
E70: 〇：必須 △：条件付き必須

Sheet 取込フォーマット定義（人件費支払）
A1: ドキュメント名 | E1: サブシステム | G1: 業務機能名 | P1: 作成者 | R1: =表紙!D51 -> SCSK大西 | T1: 更新者
A2: 業務機能概要書 | C2: 取込フォーマット定義 | E2: =業務機能概要!L2 -> 債務管理 | G2: =業務機能概要!Q2 -> 支払依頼データ自動取込 | P2: 作成日 | R2: =表紙!C51 -> 45898 | T2: 更新日
A4: データ名 | C4: 支払依頼データ | I4: ヘッダ行 | K4: あり | M4: なし | N4: ダブルクォーテーション | Q4: あり | S4: なし | X4: 文字列
A5: ﾌｧｲﾙ形式・ﾚｺｰﾄﾞ長 | D5: 固定長（ | G5: Byte） | I5: 可変長（区切り文字［ ，(カンマ) ］） | M5: バイナリデータ | P5: その他（ ） | X5: 半英数
A6: 文字コード | D6: UNI（Win系） | F6: EBCDIC(K) | I6: その他（ UTF-8） | M6: 改行コード | O6: LF(UNIX系) | Q6: CRLF(Win系) | T6: なし | X6: 半カナ
A7: 全角(2byte)文字項目 | D7: あり | F7: なし | M7: 数値編集 | O7: 左詰め | Q7: 右詰め［ゼロ埋め］ | T7: 右詰め［スペース埋め］ | X7: コード
A8: 特記事項 | C8: ProActiveC4へ支払依頼データを連動する際には、債務計上の仕訳データを別途連動する必要がある。 | L8: ※人件費支払 ・・・ 給与、（通常の）賞与の支払 | X8: 数値
A9: No. | B9: 項目名 | E9: 必須 | F9: 型 | G9: 桁数 | H9: 開始位置 | I9: 備考 | Q9: 設定値 | X9: 日付
H10: /列 | X10: 時間
A11: =MAX($A$10:$A10)+1 -> 1 | B11: 支払依頼取込参照番号 | E11: △ | F11: 文字列 | G11: 20 | H11: =SUBSTITUTE(SUBSTITUTE(ADDRESS(1,A11),"$1",""),"$","") -> A | I11: 空白（設定不要） | Q11: 設定なし | X11: 年月
A12: =MAX($A$10:$A11)+1 -> 2 | B12: 取引日付 | E12: 〇 | F12: 日付 | G12: 8 | H12: =SUBSTITUTE(SUBSTITUTE(ADDRESS(1,A12),"$1",""),"$","") -> B | I12: 経理日 | Q12: 債務明細データ・経理日 | X12: 区分
A13: =MAX($A$10:$A12)+1 -> 3 | B13: 担当部門表示コード | E13: 〇 | F13: コード | G13: 10 | H13: =SUBSTITUTE(SUBSTITUTE(ADDRESS(1,A13),"$1",""),"$","") -> C | I13: 取込処理のパフォーマンス向上のため、分割されたファイルごとに異なる部門コードを指定する必要がある。 | Q13: 債務明細データ・未払金管理組織コードより組織体系マスタに合わせて変換
I14: ただし、ProActiveの組織体系マスタに登録済のコードである必要がある。
A15: =MAX($A$10:$A13)+1 -> 4 | B15: 確証番号 | F15: 文字列 | G15: 20 | H15: =SUBSTITUTE(SUBSTITUTE(ADDRESS(1,A15),"$1",""),"$","") -> D | I15: 発生元システム管理No.（前渡金と振替する対象のデータを識別する） ※「納品書番号」に相当する（20桁） | Q15: 債務明細データ・債務受付番号(15桁)+債務明細データ・債務明細連番(2桁)
A16: =MAX($A$10:$A15)+1 -> 5 | B16: 取引件名 | F16: 文字列 | G16: 80 | H16: =SUBSTITUTE(SUBSTITUTE(ADDRESS(1,A16),"$1",""),"$","") -> E | I16: 取引内容の説明 | Q16: 債務発生元の仕訳データに設定された仕訳摘要
A17: =MAX($A$10:$A16)+1 -> 6 | B17: 取引指定区分 | E17: 〇 | F17: 区分 | G17: 1 | H17: =SUBSTITUTE(SUBSTITUTE(ADDRESS(1,A17),"$1",""),"$","") -> F | I17: 取引の種類（1.通常取引、2.諸口取引） | Q17: 2：諸口取引
A18: =MAX($A$10:$A17)+1 -> 7 | B18: 取引先コード | E18: 〇 | F18: コード | G18: 15 | H18: =SUBSTITUTE(SUBSTITUTE(ADDRESS(1,A18),"$1",""),"$","") -> G | I18: 取引する相手先を識別する9桁コード ※債務科目を取引先別計上する場合、債務科目の内訳情報となる | Q18: 135260001：ホクレン職員給与口
A19: =MAX($A$10:$A18)+1 -> 8 | B19: 諸口取引先名１ | E19: △ | F19: 文字列 | G19: 50 | H19: =SUBSTITUTE(SUBSTITUTE(ADDRESS(1,A19),"$1",""),"$","") -> H | I19: 設定不要 | Q19: ホクレン職員給与口
A20: =MAX($A$10:$A19)+1 -> 9 | B20: 諸口取引先名２ | F20: 文字列 | G20: 50 | H20: =SUBSTITUTE(SUBSTITUTE(ADDRESS(1,A20),"$1",""),"$","") -> I | I20: 設定不要 | Q20: 設定なし
A21: =MAX($A$10:$A20)+1 -> 10 | B21: 諸口取引先名（カナ） | E21: △ | F21: 文字列 | G21: 40 | H21: =SUBSTITUTE(SUBSTITUTE(ADDRESS(1,A21),"$1",""),"$","") -> J | I21: 設定不要 | Q21: ﾎｸﾚﾝｼｮｸｲﾝｷｭｳﾖｸﾁ
A22: =MAX($A$10:$A21)+1 -> 11 | B22: 諸口取引先名（略） | E22: △ | F22: 文字列 | G22: 20 | H22: =SUBSTITUTE(SUBSTITUTE(ADDRESS(1,A22),"$1",""),"$","") -> K | I22: 設定不要 | Q22: ｷｭｳﾖｸﾁ
A23: =MAX($A$10:$A22)+1 -> 12 | B23: 郵便番号 | F23: 文字列 | G23: 10 | H23: =SUBSTITUTE(SUBSTITUTE(ADDRESS(1,A23),"$1",""),"$","") -> L | I23: 設定不要 | Q23: 設定なし
A24: =MAX($A$10:$A23)+1 -> 13 | B24: 諸口住所１ | F24: 文字列 | G24: 100 | H24: =SUBSTITUTE(SUBSTITUTE(ADDRESS(1,A24),"$1",""),"$","") -> M | I24: 設定不要 | Q24: 設定なし
A25: =MAX($A$10:$A24)+1 -> 14 | B25: 諸口住所２ | F25: 文字列 | G25: 100 | H25: =SUBSTITUTE(SUBSTITUTE(ADDRESS(1,A25),"$1",""),"$","") -> N | I25: 設定不要 | Q25: 設定なし
A26: =MAX($A$10:$A25)+1 -> 15 | B26: 諸口TEL | F26: 文字列 | G26: 20 | H26: =SUBSTITUTE(SUBSTITUTE(ADDRESS(1,A26),"$1",""),"$","") -> O | I26: 設定不要 | Q26: 設定なし
A27: =MAX($A$10:$A26)+1 -> 16 | B27: 諸口FAX | F27: 文字列 | G27: 20 | H27: =SUBSTITUTE(SUBSTITUTE(ADDRESS(1,A27),"$1",""),"$","") -> P | I27: 設定不要 | Q27: 設定なし
A28: =MAX($A$10:$A27)+1 -> 17 | B28: 振込先金融機関コード | E28: △ | F28: コード | G28: 4 | H28: =SUBSTITUTE(SUBSTITUTE(ADDRESS(1,A28),"$1",""),"$","") -> Q | I28: 設定不要 | Q28: ZZZZ：ダミー金融機関
A29: =MAX($A$10:$A28)+1 -> 18 | B29: 振込先金融機関店舗コード | E29: △ | F29: コード | G29: 3 | H29: =SUBSTITUTE(SUBSTITUTE(ADDRESS(1,A29),"$1",""),"$","") -> R | I29: 設定不要 | Q29: ZZZ：ダミー店舗
A30: =MAX($A$10:$A29)+1 -> 19 | B30: 振込先銀行口座種別区分 | E30: △ | F30: 区分 | G30: 1 | H30: =SUBSTITUTE(SUBSTITUTE(ADDRESS(1,A30),"$1",""),"$","") -> S | I30: 設定不要 | Q30: 1：普通預金
A31: =MAX($A$10:$A30)+1 -> 20 | B31: 振込先銀行口座番号 | E31: △ | F31: 文字列 | G31: 7 | H31: =SUBSTITUTE(SUBSTITUTE(ADDRESS(1,A31),"$1",""),"$","") -> T | I31: 設定不要 | Q31: ZZZZZZZ
A32: =MAX($A$10:$A31)+1 -> 21 | B32: 振込先郵便口座番号 | E32: △ | F32: 文字列 | G32: 13 | H32: =SUBSTITUTE(SUBSTITUTE(ADDRESS(1,A32),"$1",""),"$","") -> U | I32: 設定不要 | Q32: ZZZZZZZZZZZZZ
A33: =MAX($A$10:$A32)+1 -> 22 | B33: 振込先口座名義人 | E33: △ | F33: 文字列 | G33: 50 | H33: =SUBSTITUTE(SUBSTITUTE(ADDRESS(1,A33),"$1",""),"$","") -> V | I33: 設定不要 | Q33: ホクレン職員給与口
A34: =MAX($A$10:$A33)+1 -> 23 | B34: 振込先口座名義人（カナ） | E34: △ | F34: 文字列 | G34: 30 | H34: =SUBSTITUTE(SUBSTITUTE(ADDRESS(1,A34),"$1",""),"$","") -> W | I34: 設定不要 | Q34: ｷｭｳﾖｸﾞﾁ
A35: =MAX($A$10:$A34)+1 -> 24 | B35: 先方負担振込手数料フラグ | E35: △ | F35: フラグ | G35: 1 | H35: =SUBSTITUTE(SUBSTITUTE(ADDRESS(1,A35),"$1",""),"$","") -> X | I35: 設定不要 | Q35: 0
A36: =MAX($A$10:$A35)+1 -> 25 | B36: 備考 | F36: 文字列 | G36: 80 | H36: =SUBSTITUTE(SUBSTITUTE(ADDRESS(1,A36),"$1",""),"$","") -> Y | I36: 任意項目。発生元システム管理No.（前渡金と振替する対象のデータを識別する） ※「納品書番号」に相当する（20桁）などを設定する想定。 | Q36: 債務明細データ・発生元システム取引Ｎｏ+発生元システム取引Ｎｏ枝番
A37: =MAX($A$10:$A36)+1 -> 26 | B37: 支払先コード | F37: コード | G37: 15 | H37: =SUBSTITUTE(SUBSTITUTE(ADDRESS(1,A37),"$1",""),"$","") -> Z | I37: 支払先の取引先コード | Q37: 人件費支払用のダミー支払先コード
A38: =MAX($A$10:$A37)+1 -> 27 | B38: 支払締日付 | F38: 日付 | G38: 8 | H38: =SUBSTITUTE(SUBSTITUTE(ADDRESS(1,A38),"$1",""),"$","") -> AA | I38: 空白（設定不要） | Q38: 設定なし
A39: =MAX($A$10:$A38)+1 -> 28 | B39: 支払決済条件コード | F39: コード | G39: 3 | H39: =SUBSTITUTE(SUBSTITUTE(ADDRESS(1,A39),"$1",""),"$","") -> AB | I39: 支払先の決済条件を識別するコード | Q39: 振込（FBなし）の支払決済条件コード
A40: =MAX($A$10:$A39)+1 -> 29 | B40: 支払締名寄項目 | F40: 文字列 | G40: 20 | H40: =SUBSTITUTE(SUBSTITUTE(ADDRESS(1,A40),"$1",""),"$","") -> AC | I40: 空白（設定不要） | Q40: 設定なし
A41: =MAX($A$10:$A40)+1 -> 30 | B41: 支払予定日付１ | F41: 日付 | G41: 8 | H41: =SUBSTITUTE(SUBSTITUTE(ADDRESS(1,A41),"$1",""),"$","") -> AD | I41: 支払を行う日付 | Q41: 債務明細データ・最新支払予定日
A42: =MAX($A$10:$A41)+1 -> 31 | B42: 支払予定日付２ | F42: 日付 | G42: 8 | H42: =SUBSTITUTE(SUBSTITUTE(ADDRESS(1,A42),"$1",""),"$","") -> AE | I42: 空白（設定不要） | Q42: 設定なし
A43: =MAX($A$10:$A42)+1 -> 32 | B43: 支払依頼取込行番号 | E43: 〇 | F43: 数値 | G43: 4 | H43: =SUBSTITUTE(SUBSTITUTE(ADDRESS(1,A43),"$1",""),"$","") -> AF | I43: 支払依頼取込明細の行番号 | Q43: 1（固定）
A44: =MAX($A$10:$A43)+1 -> 33 | B44: 取引種類コード | E44: 〇 | F44: コード | G44: 8 | H44: =SUBSTITUTE(SUBSTITUTE(ADDRESS(1,A44),"$1",""),"$","") -> AG | I44: 取引種類（計上される費用科目、債務科目の組合せ）を一意に識別するコード | Q44: 債務明細データ・項科目コード、目節科目コード、仕訳種別コードに応じて導出した取引種類コード
A45: =MAX($A$10:$A44)+1 -> 34 | B45: 費用計上部門表示コード | F45: コード | G45: 10 | H45: =SUBSTITUTE(SUBSTITUTE(ADDRESS(1,A45),"$1",""),"$","") -> AH | I45: 費用科目の計上部門コード | L45: ※当案件では当項目は仕訳作成には使用しないため債務計上部門と同じ。 | Q45: 債務計上部門コードと同じコード
A46: =MAX($A$10:$A45)+1 -> 35 | B46: 債務計上部門表示コード | F46: コード | G46: 10 | H46: =SUBSTITUTE(SUBSTITUTE(ADDRESS(1,A46),"$1",""),"$","") -> AI | I46: 債務科目の計上部門コード | L46: ※ProActiveの組織体系マスタに登録済のコードである必要がある | Q46: 債務計上部門コードと同じコード
A47: =MAX($A$10:$A46)+1 -> 36 | B47: 消費税区分 | F47: 区分 | G47: 2 | H47: =SUBSTITUTE(SUBSTITUTE(ADDRESS(1,A47),"$1",""),"$","") -> AJ | I47: 設定不要 | L47: ※未設定時は取引種類の消費税区分が自動で設定される。 | Q47: 設定なし
A48: =MAX($A$10:$A47)+1 -> 37 | B48: 取引金額（税込） | E48: △ | F48: 数値 | G48: 13 | H48: =SUBSTITUTE(SUBSTITUTE(ADDRESS(1,A48),"$1",""),"$","") -> AK | I48: 金額0は入力不可 | Q48: 債務明細データ・支払予定金額
A49: =MAX($A$10:$A48)+1 -> 38 | B49: 取引金額（税抜） | E49: △ | F49: 数値 | G49: 13 | H49: =SUBSTITUTE(SUBSTITUTE(ADDRESS(1,A49),"$1",""),"$","") -> AL | I49: 設定不要 | Q49: 設定なし
A50: =MAX($A$10:$A49)+1 -> 39 | B50: 消費税額 | F50: 数値 | G50: 13 | H50: =SUBSTITUTE(SUBSTITUTE(ADDRESS(1,A50),"$1",""),"$","") -> AM | I50: 設定不要 | Q50: 設定なし
A51: =MAX($A$10:$A50)+1 -> 40 | B51: 仕訳取引先コード | F51: コード | G51: 15 | H51: =SUBSTITUTE(SUBSTITUTE(ADDRESS(1,A51),"$1",""),"$","") -> AN | I51: 費用科目の内訳情報となる取引先（取引する相手先を識別する）コード | Q51: 人件費支払用のダミー支払先コード
A52: =MAX($A$10:$A51)+1 -> 41 | B52: 仕訳自社口座コード | E52: △ | F52: コード | G52: 8 | H52: =SUBSTITUTE(SUBSTITUTE(ADDRESS(1,A52),"$1",""),"$","") -> AO | I52: 費用科目の内訳情報となる出金を行う銀行口座のコード | Q52: 設定なし
I53: ※費用科目として預金科目を計上する場合、必須（実業務上ないと想定）
A54: =MAX($A$10:$A52)+1 -> 42 | B54: 仕訳プロジェクトコード | E54: △ | F54: コード | G54: 20 | H54: =SUBSTITUTE(SUBSTITUTE(ADDRESS(1,A54),"$1",""),"$","") -> AP | I54: 費用科目の内訳情報となる業種を判別するコード ※費用科目を業種別計上する場合、必須 | Q54: 債務明細データ・業種コード
A55: =MAX($A$10:$A54)+1 -> 43 | B55: 仕訳担当者コード | F55: コード | G55: 15 | H55: =SUBSTITUTE(SUBSTITUTE(ADDRESS(1,A55),"$1",""),"$","") -> AQ | I55: 空白（設定不要） | Q55: 設定なし
A56: =MAX($A$10:$A55)+1 -> 44 | B56: 仕訳セグメントコード | E56: △ | F56: コード | G56: 4 | H56: =SUBSTITUTE(SUBSTITUTE(ADDRESS(1,A56),"$1",""),"$","") -> AR | I56: 費用科目の内訳情報となる会計品目を判別するコード ※費用科目を会計品目別計上する場合、必須 | Q56: 設定なし
A57: =MAX($A$10:$A56)+1 -> 45 | B57: 仕訳セグメントコード１ | E57: △ | F57: コード | G57: 4 | H57: =SUBSTITUTE(SUBSTITUTE(ADDRESS(1,A57),"$1",""),"$","") -> AS | I57: 空白（設定不要） | Q57: 設定なし
A58: =MAX($A$10:$A57)+1 -> 46 | B58: 仕訳セグメントコード２ | E58: △ | F58: コード | G58: 4 | H58: =SUBSTITUTE(SUBSTITUTE(ADDRESS(1,A58),"$1",""),"$","") -> AT | I58: 空白（設定不要） | Q58: 設定なし
A59: =MAX($A$10:$A58)+1 -> 47 | B59: 仕訳セグメントコード３ | E59: △ | F59: コード | G59: 4 | H59: =SUBSTITUTE(SUBSTITUTE(ADDRESS(1,A59),"$1",""),"$","") -> AU | I59: 空白（設定不要） | Q59: 設定なし
A60: =MAX($A$10:$A59)+1 -> 48 | B60: 仕訳セグメントコード４ | E60: △ | F60: コード | G60: 4 | H60: =SUBSTITUTE(SUBSTITUTE(ADDRESS(1,A60),"$1",""),"$","") -> AV | I60: 空白（設定不要） | Q60: 設定なし
A61: =MAX($A$10:$A60)+1 -> 49 | B61: 仕訳セグメントコード５ | E61: △ | F61: コード | G61: 4 | H61: =SUBSTITUTE(SUBSTITUTE(ADDRESS(1,A61),"$1",""),"$","") -> AW | I61: 空白（設定不要） | Q61: 設定なし
A62: =MAX($A$10:$A61)+1 -> 50 | B62: 費用補助科目コード | F62: コード | G62: 4 | H62: =SUBSTITUTE(SUBSTITUTE(ADDRESS(1,A62),"$1",""),"$","") -> AX | I62: 費用科目の科目摘要を判別するコード | Q62: 債務明細データ・科目摘要コード
A63: =MAX($A$10:$A62)+1 -> 51 | B63: 仕訳摘要 | F63: 文字列 | G63: 80 | H63: =SUBSTITUTE(SUBSTITUTE(ADDRESS(1,A63),"$1",""),"$","") -> AY | I63: 取引内容の説明（総勘定元帳に出力される） | Q63: 債務明細データ・経理日+債務明細データ・仕訳連番に紐づく仕訳ヘッダ・仕訳摘要
A64: =MAX($A$10:$A63)+1 -> 52 | B64: 立替金請求取引先コード | F64: コード | G64: 15 | H64: =SUBSTITUTE(SUBSTITUTE(ADDRESS(1,A64),"$1",""),"$","") -> AZ | I64: 空白（設定不要） | Q64: 設定なし
A65: =MAX($A$10:$A64)+1 -> 53 | B65: 回収予定日付 | F65: 日付 | G65: 8 | H65: =SUBSTITUTE(SUBSTITUTE(ADDRESS(1,A65),"$1",""),"$","") -> BA | I65: 空白（設定不要） | Q65: 設定なし
A66: =MAX($A$10:$A65)+1 -> 54 | B66: 立替金摘要 | F66: 文字列 | G66: 80 | H66: =SUBSTITUTE(SUBSTITUTE(ADDRESS(1,A66),"$1",""),"$","") -> BB | I66: 空白（設定不要） | Q66: 設定なし
A67: =MAX($A$10:$A66)+1 -> 55 | B67: 連携先担当部門コード | F67: コード | G67: 10 | H67: =SUBSTITUTE(SUBSTITUTE(ADDRESS(1,A67),"$1",""),"$","") -> BC | I67: 空白（設定不要） | Q67: 設定なし
A68: =MAX($A$10:$A67)+1 -> 56 | B68: 連携先計上部門コード | F68: コード | G68: 10 | H68: =SUBSTITUTE(SUBSTITUTE(ADDRESS(1,A68),"$1",""),"$","") -> BD | I68: 空白（設定不要） | Q68: 設定なし
A69: =MAX($A$10:$A68)+1 -> 57 | B69: 連携先取引種類コード | E69: △ | F69: コード | G69: 8 | H69: =SUBSTITUTE(SUBSTITUTE(ADDRESS(1,A69),"$1",""),"$","") -> BE | I69: 空白（設定不要） | Q69: 設定なし
E70: 〇：必須 △：条件付き必須

Sheet 取込フォーマット定義（振込先が決定している諸口支払）
A1: ドキュメント名 | E1: サブシステム | G1: 業務機能名 | P1: 作成者 | R1: =表紙!D51 -> SCSK大西 | T1: 更新者
A2: 業務機能概要書 | C2: 取込フォーマット定義 | E2: =業務機能概要!L2 -> 債務管理 | G2: =業務機能概要!Q2 -> 支払依頼データ自動取込 | P2: 作成日 | R2: =表紙!C51 -> 45898 | T2: 更新日
A4: データ名 | C4: 支払依頼データ | I4: ヘッダ行 | K4: あり | M4: なし | N4: ダブルクォーテーション | Q4: あり | S4: なし | X4: 文字列
A5: ﾌｧｲﾙ形式・ﾚｺｰﾄﾞ長 | D5: 固定長（ | G5: Byte） | I5: 可変長（区切り文字［ ，(カンマ) ］） | M5: バイナリデータ | P5: その他（ ） | X5: 半英数
A6: 文字コード | D6: UNI（Win系） | F6: EBCDIC(K) | I6: その他（ UTF-8） | M6: 改行コード | O6: LF(UNIX系) | Q6: CRLF(Win系) | T6: なし | X6: 半カナ
A7: 全角(2byte)文字項目 | D7: あり | F7: なし | M7: 数値編集 | O7: 左詰め | Q7: 右詰め［ゼロ埋め］ | T7: 右詰め［スペース埋め］ | X7: コード
A8: 特記事項 | C8: ProActiveC4へ支払依頼データを連動する際には、債務計上の仕訳データを別途連動する必要がある。 | X8: 数値
A9: No. | B9: 項目名 | E9: 必須 | F9: 型 | G9: 桁数 | H9: 開始位置 | I9: 備考 | Q9: 設定値 | X9: 日付
H10: /列 | X10: 時間
A11: =MAX($A$10:$A10)+1 -> 1 | B11: 支払依頼取込参照番号 | E11: △ | F11: 文字列 | G11: 20 | H11: =SUBSTITUTE(SUBSTITUTE(ADDRESS(1,A11),"$1",""),"$","") -> A | I11: 空白（設定不要） | Q11: 設定なし | X11: 年月
A12: =MAX($A$10:$A11)+1 -> 2 | B12: 取引日付 | E12: 〇 | F12: 日付 | G12: 8 | H12: =SUBSTITUTE(SUBSTITUTE(ADDRESS(1,A12),"$1",""),"$","") -> B | I12: 経理日 | Q12: 債務明細データ・経理日 | X12: 区分
A13: =MAX($A$10:$A12)+1 -> 3 | B13: 担当部門表示コード | E13: 〇 | F13: コード | G13: 10 | H13: =SUBSTITUTE(SUBSTITUTE(ADDRESS(1,A13),"$1",""),"$","") -> C | I13: 取込処理のパフォーマンス向上のため、分割されたファイルごとに異なる部門コードを指定する必要がある。 | Q13: 債務明細データ・未払金管理組織コードより組織体系マスタに合わせて変換
I14: ただし、ProActiveの組織体系マスタに登録済のコードである必要がある。
A15: =MAX($A$10:$A13)+1 -> 4 | B15: 確証番号 | F15: 文字列 | G15: 20 | H15: =SUBSTITUTE(SUBSTITUTE(ADDRESS(1,A15),"$1",""),"$","") -> D | I15: 発生元システム管理No.（前渡金と振替する対象のデータを識別する） ※「納品書番号」に相当する（20桁） | Q15: 債務明細データ・債務受付番号(15桁)+債務明細データ・債務明細連番(2桁)
A16: =MAX($A$10:$A15)+1 -> 5 | B16: 取引件名 | F16: 文字列 | G16: 80 | H16: =SUBSTITUTE(SUBSTITUTE(ADDRESS(1,A16),"$1",""),"$","") -> E | I16: 取引内容の説明 | Q16: 債務発生元の仕訳データに設定された仕訳摘要
A17: =MAX($A$10:$A16)+1 -> 6 | B17: 取引指定区分 | E17: 〇 | F17: 区分 | G17: 1 | H17: =SUBSTITUTE(SUBSTITUTE(ADDRESS(1,A17),"$1",""),"$","") -> F | I17: 取引の種類（1.通常取引、2.諸口取引） | Q17: 2:諸口取引
A18: =MAX($A$10:$A17)+1 -> 7 | B18: 取引先コード | E18: 〇 | F18: コード | G18: 15 | H18: =SUBSTITUTE(SUBSTITUTE(ADDRESS(1,A18),"$1",""),"$","") -> G | I18: 取引する相手先を識別するコード ※債務科目を取引先別計上する場合、債務科目の内訳情報となる | Q18: 諸口取引先用のコード
I19: 「取引指定区分」が「2:諸口取引」の場合は、諸口取引用の取引先コード | N19: ※補足2シート参照 | Q19: ※臨時賞与、退職金の場合は、135260001：ホクレン職員給与口
A20: =MAX($A$10:$A18)+1 -> 8 | B20: 諸口取引先名１ | E20: △ | F20: 文字列 | G20: 50 | H20: =SUBSTITUTE(SUBSTITUTE(ADDRESS(1,A20),"$1",""),"$","") -> H | I20: ※諸口取引の場合、必須 | Q20: 債務明細データ・諸口取引先カナ名称 、 諸口取引先の名称（「諸口」）
A21: =MAX($A$10:$A20)+1 -> 9 | B21: 諸口取引先名２ | F21: 文字列 | G21: 50 | H21: =SUBSTITUTE(SUBSTITUTE(ADDRESS(1,A21),"$1",""),"$","") -> I | Q21: 設定なし
A22: =MAX($A$10:$A21)+1 -> 10 | B22: 諸口取引先名（カナ） | E22: △ | F22: 文字列 | G22: 40 | H22: =SUBSTITUTE(SUBSTITUTE(ADDRESS(1,A22),"$1",""),"$","") -> J | I22: ※諸口取引の場合、必須 | Q22: 債務明細データ・諸口取引先カナ名称 、 諸口取引先のカナ名称（「ｼｮｸﾞﾁ」）
A23: =MAX($A$10:$A22)+1 -> 11 | B23: 諸口取引先名（略） | E23: △ | F23: 文字列 | G23: 20 | H23: =SUBSTITUTE(SUBSTITUTE(ADDRESS(1,A23),"$1",""),"$","") -> K | I23: ※諸口取引の場合、必須 | Q23: 債務明細データ・諸口取引先カナ名称 、 諸口取引先の名称（「諸口」）
A24: =MAX($A$10:$A23)+1 -> 12 | B24: 郵便番号 | F24: 文字列 | G24: 10 | H24: =SUBSTITUTE(SUBSTITUTE(ADDRESS(1,A24),"$1",""),"$","") -> L | Q24: 設定なし
A25: =MAX($A$10:$A24)+1 -> 13 | B25: 諸口住所１ | F25: 文字列 | G25: 100 | H25: =SUBSTITUTE(SUBSTITUTE(ADDRESS(1,A25),"$1",""),"$","") -> M | Q25: 設定なし
A26: =MAX($A$10:$A25)+1 -> 14 | B26: 諸口住所２ | F26: 文字列 | G26: 100 | H26: =SUBSTITUTE(SUBSTITUTE(ADDRESS(1,A26),"$1",""),"$","") -> N | Q26: 設定なし
A27: =MAX($A$10:$A26)+1 -> 15 | B27: 諸口TEL | F27: 文字列 | G27: 20 | H27: =SUBSTITUTE(SUBSTITUTE(ADDRESS(1,A27),"$1",""),"$","") -> O | Q27: 設定なし
A28: =MAX($A$10:$A27)+1 -> 16 | B28: 諸口FAX | F28: 文字列 | G28: 20 | H28: =SUBSTITUTE(SUBSTITUTE(ADDRESS(1,A28),"$1",""),"$","") -> P | Q28: 設定なし
A29: =MAX($A$10:$A28)+1 -> 17 | B29: 振込先金融機関コード | E29: △ | F29: コード | G29: 4 | H29: =SUBSTITUTE(SUBSTITUTE(ADDRESS(1,A29),"$1",""),"$","") -> Q | I29: 諸口取引、かつ、支払決済条件コード（No.28）から導出される支払方法が「振込」の場合は必須。 それ以外の場合は設定不要。 | Q29: 債務明細データ・振込先金融機関コード
A30: =MAX($A$10:$A29)+1 -> 18 | B30: 振込先金融機関店舗コード | E30: △ | F30: コード | G30: 3 | H30: =SUBSTITUTE(SUBSTITUTE(ADDRESS(1,A30),"$1",""),"$","") -> R | I30: 同上 | Q30: 債務明細データ・振込先金融機関店舗コード
A31: =MAX($A$10:$A30)+1 -> 19 | B31: 振込先銀行口座種別区分 | E31: △ | F31: 区分 | G31: 1 | H31: =SUBSTITUTE(SUBSTITUTE(ADDRESS(1,A31),"$1",""),"$","") -> S | I31: 同上 | Q31: 債務明細データ・振込先銀行口座種別区分
A32: =MAX($A$10:$A31)+1 -> 20 | B32: 振込先銀行口座番号 | E32: △ | F32: 文字列 | G32: 7 | H32: =SUBSTITUTE(SUBSTITUTE(ADDRESS(1,A32),"$1",""),"$","") -> T | I32: 同上 | Q32: 債務明細データ・振込先銀行口座番号
A33: =MAX($A$10:$A32)+1 -> 21 | B33: 振込先郵便口座番号 | E33: △ | F33: 文字列 | G33: 13 | H33: =SUBSTITUTE(SUBSTITUTE(ADDRESS(1,A33),"$1",""),"$","") -> U | I33: 同上 | Q33: 債務明細データ・振込先郵便口座番号
A34: =MAX($A$10:$A33)+1 -> 22 | B34: 振込先口座名義人 | E34: △ | F34: 文字列 | G34: 50 | H34: =SUBSTITUTE(SUBSTITUTE(ADDRESS(1,A34),"$1",""),"$","") -> V | I34: 同上 | Q34: 振込先口座名義人
A35: =MAX($A$10:$A34)+1 -> 23 | B35: 振込先口座名義人（カナ） | E35: △ | F35: 文字列 | G35: 30 | H35: =SUBSTITUTE(SUBSTITUTE(ADDRESS(1,A35),"$1",""),"$","") -> W | I35: 同上 | Q35: 振込先口座名義人（カナ）
A36: =MAX($A$10:$A35)+1 -> 24 | B36: 先方負担振込手数料フラグ | E36: △ | F36: フラグ | G36: 1 | H36: =SUBSTITUTE(SUBSTITUTE(ADDRESS(1,A36),"$1",""),"$","") -> X | I36: 0：当社負担 1：先方負担 | Q36: 0：当社負担
A37: =MAX($A$10:$A36)+1 -> 25 | B37: 備考 | F37: 文字列 | G37: 80 | H37: =SUBSTITUTE(SUBSTITUTE(ADDRESS(1,A37),"$1",""),"$","") -> Y | I37: 任意項目。発生元システム管理No.（前渡金と振替する対象のデータを識別する） ※「納品書番号」に相当する（20桁）などを設定する想定。 | Q37: 債務明細データ・発生元システム取引Ｎｏ+発生元システム取引Ｎｏ枝番
A38: =MAX($A$10:$A37)+1 -> 26 | B38: 支払先コード | F38: コード | G38: 15 | H38: =SUBSTITUTE(SUBSTITUTE(ADDRESS(1,A38),"$1",""),"$","") -> Z | I38: 支払先の取引先コード | Q38: 債務明細データ・支払先区分＋支払先コード(法人+枝番)
A39: =MAX($A$10:$A38)+1 -> 27 | B39: 支払締日付 | F39: 日付 | G39: 8 | H39: =SUBSTITUTE(SUBSTITUTE(ADDRESS(1,A39),"$1",""),"$","") -> AA | I39: 空白（設定不要） | Q39: 設定なし
A40: =MAX($A$10:$A39)+1 -> 28 | B40: 支払決済条件コード | F40: コード | G40: 3 | H40: =SUBSTITUTE(SUBSTITUTE(ADDRESS(1,A40),"$1",""),"$","") -> AB | I40: 支払先の決済条件を識別するコード | Q40: 諸口の振込用の決済条件コード
A41: =MAX($A$10:$A40)+1 -> 29 | B41: 支払締名寄項目 | F41: 文字列 | G41: 20 | H41: =SUBSTITUTE(SUBSTITUTE(ADDRESS(1,A41),"$1",""),"$","") -> AC | I41: 空白（設定不要） | Q41: 設定なし
A42: =MAX($A$10:$A41)+1 -> 30 | B42: 支払予定日付１ | F42: 日付 | G42: 8 | H42: =SUBSTITUTE(SUBSTITUTE(ADDRESS(1,A42),"$1",""),"$","") -> AD | I42: 支払を行う日付 | Q42: 債務明細データ・最新支払予定日
A43: =MAX($A$10:$A42)+1 -> 31 | B43: 支払予定日付２ | F43: 日付 | G43: 8 | H43: =SUBSTITUTE(SUBSTITUTE(ADDRESS(1,A43),"$1",""),"$","") -> AE | I43: 空白（設定不要） | Q43: 設定なし
A44: =MAX($A$10:$A43)+1 -> 32 | B44: 支払依頼取込行番号 | E44: 〇 | F44: 数値 | G44: 4 | H44: =SUBSTITUTE(SUBSTITUTE(ADDRESS(1,A44),"$1",""),"$","") -> AF | I44: 支払依頼取込明細の行番号 | Q44: 1（固定）
A45: =MAX($A$10:$A44)+1 -> 33 | B45: 取引種類コード | E45: 〇 | F45: コード | G45: 8 | H45: =SUBSTITUTE(SUBSTITUTE(ADDRESS(1,A45),"$1",""),"$","") -> AG | I45: 取引種類（計上される費用科目、債務科目の組合せ）を一意に識別するコード | Q45: 債務明細データ・項科目コード、目節科目コード、仕訳種別コードに応じて導出した取引種類コード
A46: =MAX($A$10:$A45)+1 -> 34 | B46: 費用計上部門表示コード | F46: コード | G46: 10 | H46: =SUBSTITUTE(SUBSTITUTE(ADDRESS(1,A46),"$1",""),"$","") -> AH | I46: 費用科目の計上部門コード | L46: ※当案件では当項目は仕訳作成には使用しないため債務計上部門と同じ。 | Q46: 債務計上部門コードと同じコード
A47: =MAX($A$10:$A46)+1 -> 35 | B47: 債務計上部門表示コード | F47: コード | G47: 10 | H47: =SUBSTITUTE(SUBSTITUTE(ADDRESS(1,A47),"$1",""),"$","") -> AI | I47: 債務科目の計上部門コード | L47: ※ProActiveの組織体系マスタに登録済のコードである必要がある | Q47: 債務計上部門コードと同じコード
A48: =MAX($A$10:$A47)+1 -> 36 | B48: 消費税区分 | F48: 区分 | G48: 2 | H48: =SUBSTITUTE(SUBSTITUTE(ADDRESS(1,A48),"$1",""),"$","") -> AJ | I48: 設定不要 | L48: ※未設定時は取引種類の消費税区分が自動で設定される。 | Q48: 設定なし
A49: =MAX($A$10:$A48)+1 -> 37 | B49: 取引金額（税込） | E49: △ | F49: 数値 | G49: 13 | H49: =SUBSTITUTE(SUBSTITUTE(ADDRESS(1,A49),"$1",""),"$","") -> AK | I49: 金額0は入力不可 | Q49: 債務明細データ・支払予定金額
A50: =MAX($A$10:$A49)+1 -> 38 | B50: 取引金額（税抜） | E50: △ | F50: 数値 | G50: 13 | H50: =SUBSTITUTE(SUBSTITUTE(ADDRESS(1,A50),"$1",""),"$","") -> AL | I50: 設定不要 | Q50: 設定なし
A51: =MAX($A$10:$A50)+1 -> 39 | B51: 消費税額 | F51: 数値 | G51: 13 | H51: =SUBSTITUTE(SUBSTITUTE(ADDRESS(1,A51),"$1",""),"$","") -> AM | I51: 設定不要 | Q51: 設定なし
A52: =MAX($A$10:$A51)+1 -> 40 | B52: 仕訳取引先コード | F52: コード | G52: 15 | H52: =SUBSTITUTE(SUBSTITUTE(ADDRESS(1,A52),"$1",""),"$","") -> AN | I52: 費用科目の内訳情報となる取引先（取引する相手先を識別する）コード | Q52: 債務明細データ・支払先区分＋支払先コード(法人+枝番)
A53: =MAX($A$10:$A52)+1 -> 41 | B53: 仕訳自社口座コード | E53: △ | F53: コード | G53: 8 | H53: =SUBSTITUTE(SUBSTITUTE(ADDRESS(1,A53),"$1",""),"$","") -> AO | I53: 費用科目の内訳情報となる出金を行う銀行口座のコード | Q53: 設定なし
I54: ※費用科目として預金科目を計上する場合、必須（実業務上ないと想定）
A55: =MAX($A$10:$A53)+1 -> 42 | B55: 仕訳プロジェクトコード | E55: △ | F55: コード | G55: 20 | H55: =SUBSTITUTE(SUBSTITUTE(ADDRESS(1,A55),"$1",""),"$","") -> AP | I55: 費用科目の内訳情報となる業種を判別するコード ※費用科目を業種別計上する場合、必須 | Q55: 債務明細データ・業種コード
A56: =MAX($A$10:$A55)+1 -> 43 | B56: 仕訳担当者コード | F56: コード | G56: 15 | H56: =SUBSTITUTE(SUBSTITUTE(ADDRESS(1,A56),"$1",""),"$","") -> AQ | I56: 空白（設定不要） | Q56: 設定なし
A57: =MAX($A$10:$A56)+1 -> 44 | B57: 仕訳セグメントコード | E57: △ | F57: コード | G57: 4 | H57: =SUBSTITUTE(SUBSTITUTE(ADDRESS(1,A57),"$1",""),"$","") -> AR | I57: 費用科目の内訳情報となる会計品目を判別するコード ※費用科目を会計品目別計上する場合、必須 | Q57: 設定なし
A58: =MAX($A$10:$A57)+1 -> 45 | B58: 仕訳セグメントコード１ | E58: △ | F58: コード | G58: 4 | H58: =SUBSTITUTE(SUBSTITUTE(ADDRESS(1,A58),"$1",""),"$","") -> AS | I58: 空白（設定不要） | Q58: 設定なし
A59: =MAX($A$10:$A58)+1 -> 46 | B59: 仕訳セグメントコード２ | E59: △ | F59: コード | G59: 4 | H59: =SUBSTITUTE(SUBSTITUTE(ADDRESS(1,A59),"$1",""),"$","") -> AT | I59: 空白（設定不要） | Q59: 設定なし
A60: =MAX($A$10:$A59)+1 -> 47 | B60: 仕訳セグメントコード３ | E60: △ | F60: コード | G60: 4 | H60: =SUBSTITUTE(SUBSTITUTE(ADDRESS(1,A60),"$1",""),"$","") -> AU | I60: 空白（設定不要） | Q60: 設定なし
A61: =MAX($A$10:$A60)+1 -> 48 | B61: 仕訳セグメントコード４ | E61: △ | F61: コード | G61: 4 | H61: =SUBSTITUTE(SUBSTITUTE(ADDRESS(1,A61),"$1",""),"$","") -> AV | I61: 空白（設定不要） | Q61: 設定なし
A62: =MAX($A$10:$A61)+1 -> 49 | B62: 仕訳セグメントコード５ | E62: △ | F62: コード | G62: 4 | H62: =SUBSTITUTE(SUBSTITUTE(ADDRESS(1,A62),"$1",""),"$","") -> AW | I62: 空白（設定不要） | Q62: 設定なし
A63: =MAX($A$10:$A62)+1 -> 50 | B63: 費用補助科目コード | F63: コード | G63: 4 | H63: =SUBSTITUTE(SUBSTITUTE(ADDRESS(1,A63),"$1",""),"$","") -> AX | I63: 費用科目の科目摘要を判別するコード | Q63: 債務明細データ・科目摘要コード
A64: =MAX($A$10:$A63)+1 -> 51 | B64: 仕訳摘要 | F64: 文字列 | G64: 80 | H64: =SUBSTITUTE(SUBSTITUTE(ADDRESS(1,A64),"$1",""),"$","") -> AY | I64: 取引内容の説明（総勘定元帳に出力される） | Q64: 債務明細データ・経理日+債務明細データ・仕訳連番に紐づく仕訳ヘッダ・仕訳摘要
A65: =MAX($A$10:$A64)+1 -> 52 | B65: 立替金請求取引先コード | F65: コード | G65: 15 | H65: =SUBSTITUTE(SUBSTITUTE(ADDRESS(1,A65),"$1",""),"$","") -> AZ | I65: 空白（設定不要） | Q65: 設定なし
A66: =MAX($A$10:$A65)+1 -> 53 | B66: 回収予定日付 | F66: 日付 | G66: 8 | H66: =SUBSTITUTE(SUBSTITUTE(ADDRESS(1,A66),"$1",""),"$","") -> BA | I66: 空白（設定不要） | Q66: 設定なし
A67: =MAX($A$10:$A66)+1 -> 54 | B67: 立替金摘要 | F67: 文字列 | G67: 80 | H67: =SUBSTITUTE(SUBSTITUTE(ADDRESS(1,A67),"$1",""),"$","") -> BB | I67: 空白（設定不要） | Q67: 設定なし
A68: =MAX($A$10:$A67)+1 -> 55 | B68: 連携先担当部門コード | F68: コード | G68: 10 | H68: =SUBSTITUTE(SUBSTITUTE(ADDRESS(1,A68),"$1",""),"$","") -> BC | I68: 空白（設定不要） | Q68: 設定なし
A69: =MAX($A$10:$A68)+1 -> 56 | B69: 連携先計上部門コード | F69: コード | G69: 10 | H69: =SUBSTITUTE(SUBSTITUTE(ADDRESS(1,A69),"$1",""),"$","") -> BD | I69: 空白（設定不要） | Q69: 設定なし
A70: =MAX($A$10:$A69)+1 -> 57 | B70: 連携先取引種類コード | E70: △ | F70: コード | G70: 8 | H70: =SUBSTITUTE(SUBSTITUTE(ADDRESS(1,A70),"$1",""),"$","") -> BE | I70: 空白（設定不要） | Q70: 設定なし
E71: 〇：必須 △：条件付き必須

Sheet 取込フォーマット定義（その他諸口支払）
A1: ドキュメント名 | E1: サブシステム | G1: 業務機能名 | P1: 作成者 | R1: =表紙!D51 -> SCSK大西 | T1: 更新者
A2: 業務機能概要書 | C2: 取込フォーマット定義 | E2: =業務機能概要!L2 -> 債務管理 | G2: =業務機能概要!Q2 -> 支払依頼データ自動取込 | P2: 作成日 | R2: =表紙!C51 -> 45898 | T2: 更新日
A4: データ名 | C4: 支払依頼データ | I4: ヘッダ行 | K4: あり | M4: なし | N4: ダブルクォーテーション | Q4: あり | S4: なし | X4: 文字列
A5: ﾌｧｲﾙ形式・ﾚｺｰﾄﾞ長 | D5: 固定長（ | G5: Byte） | I5: 可変長（区切り文字［ ，(カンマ) ］） | M5: バイナリデータ | P5: その他（ ） | X5: 半英数
A6: 文字コード | D6: UNI（Win系） | F6: EBCDIC(K) | I6: その他（ UTF-8） | M6: 改行コード | O6: LF(UNIX系) | Q6: CRLF(Win系) | T6: なし | X6: 半カナ
A7: 全角(2byte)文字項目 | D7: あり | F7: なし | M7: 数値編集 | O7: 左詰め | Q7: 右詰め［ゼロ埋め］ | T7: 右詰め［スペース埋め］ | X7: コード
A8: 特記事項 | C8: ProActiveC4へ支払依頼データを連動する際には、債務計上の仕訳データを別途連動する必要がある。 | X8: 数値
A9: No. | B9: 項目名 | E9: 必須 | F9: 型 | G9: 桁数 | H9: 開始位置 | I9: 備考 | Q9: 設定値 | X9: 日付
H10: /列 | X10: 時間
A11: =MAX($A$10:$A10)+1 -> 1 | B11: 支払依頼取込参照番号 | E11: △ | F11: 文字列 | G11: 20 | H11: =SUBSTITUTE(SUBSTITUTE(ADDRESS(1,A11),"$1",""),"$","") -> A | I11: 空白（設定不要） | Q11: 設定なし | X11: 年月
A12: =MAX($A$10:$A11)+1 -> 2 | B12: 取引日付 | E12: 〇 | F12: 日付 | G12: 8 | H12: =SUBSTITUTE(SUBSTITUTE(ADDRESS(1,A12),"$1",""),"$","") -> B | I12: 経理日 | Q12: 債務明細データ・経理日 | X12: 区分
A13: =MAX($A$10:$A12)+1 -> 3 | B13: 担当部門表示コード | E13: 〇 | F13: コード | G13: 10 | H13: =SUBSTITUTE(SUBSTITUTE(ADDRESS(1,A13),"$1",""),"$","") -> C | I13: 取込処理のパフォーマンス向上のため、分割されたファイルごとに異なる部門コードを指定する必要がある。 | Q13: 債務明細データ・未払金管理組織コードより組織体系マスタに合わせて変換
I14: ただし、ProActiveの組織体系マスタに登録済のコードである必要がある。
A15: =MAX($A$10:$A13)+1 -> 4 | B15: 確証番号 | F15: 文字列 | G15: 20 | H15: =SUBSTITUTE(SUBSTITUTE(ADDRESS(1,A15),"$1",""),"$","") -> D | I15: 発生元システム管理No.（前渡金と振替する対象のデータを識別する） ※「納品書番号」に相当する（20桁） | Q15: 債務明細データ・債務受付番号(15桁)+債務明細データ・債務明細連番(2桁)
A16: =MAX($A$10:$A15)+1 -> 5 | B16: 取引件名 | F16: 文字列 | G16: 80 | H16: =SUBSTITUTE(SUBSTITUTE(ADDRESS(1,A16),"$1",""),"$","") -> E | I16: 取引内容の説明 | Q16: 債務発生元の仕訳データに設定された仕訳摘要
A17: =MAX($A$10:$A16)+1 -> 6 | B17: 取引指定区分 | E17: 〇 | F17: 区分 | G17: 1 | H17: =SUBSTITUTE(SUBSTITUTE(ADDRESS(1,A17),"$1",""),"$","") -> F | I17: 取引の種類（1.通常取引、2.諸口取引） | Q17: 2:諸口取引
A18: =MAX($A$10:$A17)+1 -> 7 | B18: 取引先コード | E18: 〇 | F18: コード | G18: 15 | H18: =SUBSTITUTE(SUBSTITUTE(ADDRESS(1,A18),"$1",""),"$","") -> G | I18: 取引する相手先を識別するコード ※債務科目を取引先別計上する場合、債務科目の内訳情報となる | Q18: 諸口取引先用のコード
I19: 「取引指定区分」が「2:諸口取引」の場合は、諸口取引用の取引先コード | N19: ※補足2シート参照
A20: =MAX($A$10:$A18)+1 -> 8 | B20: 諸口取引先名１ | E20: △ | F20: 文字列 | G20: 50 | H20: =SUBSTITUTE(SUBSTITUTE(ADDRESS(1,A20),"$1",""),"$","") -> H | I20: ※諸口取引の場合、必須 | Q20: 債務明細データ・諸口取引先カナ名称 、 諸口取引先の名称（「諸口」）
A21: =MAX($A$10:$A20)+1 -> 9 | B21: 諸口取引先名２ | F21: 文字列 | G21: 50 | H21: =SUBSTITUTE(SUBSTITUTE(ADDRESS(1,A21),"$1",""),"$","") -> I | Q21: 設定なし
A22: =MAX($A$10:$A21)+1 -> 10 | B22: 諸口取引先名（カナ） | E22: △ | F22: 文字列 | G22: 40 | H22: =SUBSTITUTE(SUBSTITUTE(ADDRESS(1,A22),"$1",""),"$","") -> J | I22: ※諸口取引の場合、必須 | Q22: 債務明細データ・諸口取引先カナ名称 、 諸口取引先のカナ名称（「ｼｮｸﾞﾁ」）
A23: =MAX($A$10:$A22)+1 -> 11 | B23: 諸口取引先名（略） | E23: △ | F23: 文字列 | G23: 20 | H23: =SUBSTITUTE(SUBSTITUTE(ADDRESS(1,A23),"$1",""),"$","") -> K | I23: ※諸口取引の場合、必須 | Q23: 債務明細データ・諸口取引先カナ名称 、 諸口取引先の名称（「諸口」）
A24: =MAX($A$10:$A23)+1 -> 12 | B24: 郵便番号 | F24: 文字列 | G24: 10 | H24: =SUBSTITUTE(SUBSTITUTE(ADDRESS(1,A24),"$1",""),"$","") -> L | Q24: 設定なし
A25: =MAX($A$10:$A24)+1 -> 13 | B25: 諸口住所１ | F25: 文字列 | G25: 100 | H25: =SUBSTITUTE(SUBSTITUTE(ADDRESS(1,A25),"$1",""),"$","") -> M | Q25: 設定なし
A26: =MAX($A$10:$A25)+1 -> 14 | B26: 諸口住所２ | F26: 文字列 | G26: 100 | H26: =SUBSTITUTE(SUBSTITUTE(ADDRESS(1,A26),"$1",""),"$","") -> N | Q26: 設定なし
A27: =MAX($A$10:$A26)+1 -> 15 | B27: 諸口TEL | F27: 文字列 | G27: 20 | H27: =SUBSTITUTE(SUBSTITUTE(ADDRESS(1,A27),"$1",""),"$","") -> O | Q27: 設定なし
A28: =MAX($A$10:$A27)+1 -> 16 | B28: 諸口FAX | F28: 文字列 | G28: 20 | H28: =SUBSTITUTE(SUBSTITUTE(ADDRESS(1,A28),"$1",""),"$","") -> P | Q28: 設定なし
A29: =MAX($A$10:$A28)+1 -> 17 | B29: 振込先金融機関コード | E29: △ | F29: コード | G29: 4 | H29: =SUBSTITUTE(SUBSTITUTE(ADDRESS(1,A29),"$1",""),"$","") -> Q | Q29: 設定なし
A30: =MAX($A$10:$A29)+1 -> 18 | B30: 振込先金融機関店舗コード | E30: △ | F30: コード | G30: 3 | H30: =SUBSTITUTE(SUBSTITUTE(ADDRESS(1,A30),"$1",""),"$","") -> R | Q30: 設定なし
A31: =MAX($A$10:$A30)+1 -> 19 | B31: 振込先銀行口座種別区分 | E31: △ | F31: 区分 | G31: 1 | H31: =SUBSTITUTE(SUBSTITUTE(ADDRESS(1,A31),"$1",""),"$","") -> S | Q31: 設定なし
A32: =MAX($A$10:$A31)+1 -> 20 | B32: 振込先銀行口座番号 | E32: △ | F32: 文字列 | G32: 7 | H32: =SUBSTITUTE(SUBSTITUTE(ADDRESS(1,A32),"$1",""),"$","") -> T | Q32: 設定なし
A33: =MAX($A$10:$A32)+1 -> 21 | B33: 振込先郵便口座番号 | E33: △ | F33: 文字列 | G33: 13 | H33: =SUBSTITUTE(SUBSTITUTE(ADDRESS(1,A33),"$1",""),"$","") -> U | Q33: 設定なし
A34: =MAX($A$10:$A33)+1 -> 22 | B34: 振込先口座名義人 | E34: △ | F34: 文字列 | G34: 50 | H34: =SUBSTITUTE(SUBSTITUTE(ADDRESS(1,A34),"$1",""),"$","") -> V | Q34: 設定なし
A35: =MAX($A$10:$A34)+1 -> 23 | B35: 振込先口座名義人（カナ） | E35: △ | F35: 文字列 | G35: 30 | H35: =SUBSTITUTE(SUBSTITUTE(ADDRESS(1,A35),"$1",""),"$","") -> W | Q35: 設定なし
A36: =MAX($A$10:$A35)+1 -> 24 | B36: 先方負担振込手数料フラグ | E36: △ | F36: フラグ | G36: 1 | H36: =SUBSTITUTE(SUBSTITUTE(ADDRESS(1,A36),"$1",""),"$","") -> X | I36: 0：当社負担 1：先方負担 | Q36: 設定なし
A37: =MAX($A$10:$A36)+1 -> 25 | B37: 備考 | F37: 文字列 | G37: 80 | H37: =SUBSTITUTE(SUBSTITUTE(ADDRESS(1,A37),"$1",""),"$","") -> Y | I37: 任意項目。発生元システム管理No.（前渡金と振替する対象のデータを識別する） ※「納品書番号」に相当する（20桁）などを設定する想定。 | Q37: 債務明細データ・発生元システム取引Ｎｏ+発生元システム取引Ｎｏ枝番
A38: =MAX($A$10:$A37)+1 -> 26 | B38: 支払先コード | F38: コード | G38: 15 | H38: =SUBSTITUTE(SUBSTITUTE(ADDRESS(1,A38),"$1",""),"$","") -> Z | I38: 支払先の取引先コード | Q38: 債務明細データ・支払先区分＋支払先コード(法人+枝番)
A39: =MAX($A$10:$A38)+1 -> 27 | B39: 支払締日付 | F39: 日付 | G39: 8 | H39: =SUBSTITUTE(SUBSTITUTE(ADDRESS(1,A39),"$1",""),"$","") -> AA | I39: 空白（設定不要） | Q39: 設定なし
A40: =MAX($A$10:$A39)+1 -> 28 | B40: 支払決済条件コード | F40: コード | G40: 3 | H40: =SUBSTITUTE(SUBSTITUTE(ADDRESS(1,A40),"$1",""),"$","") -> AB | I40: 支払先の決済条件を識別するコード | Q40: 諸口の振替用の決済条件コード
A41: =MAX($A$10:$A40)+1 -> 29 | B41: 支払締名寄項目 | F41: 文字列 | G41: 20 | H41: =SUBSTITUTE(SUBSTITUTE(ADDRESS(1,A41),"$1",""),"$","") -> AC | I41: 空白（設定不要） | Q41: 設定なし
A42: =MAX($A$10:$A41)+1 -> 30 | B42: 支払予定日付１ | F42: 日付 | G42: 8 | H42: =SUBSTITUTE(SUBSTITUTE(ADDRESS(1,A42),"$1",""),"$","") -> AD | I42: 支払を行う日付 | Q42: 債務明細データ・最新支払予定日
A43: =MAX($A$10:$A42)+1 -> 31 | B43: 支払予定日付２ | F43: 日付 | G43: 8 | H43: =SUBSTITUTE(SUBSTITUTE(ADDRESS(1,A43),"$1",""),"$","") -> AE | I43: 空白（設定不要） | Q43: 設定なし
A44: =MAX($A$10:$A43)+1 -> 32 | B44: 支払依頼取込行番号 | E44: 〇 | F44: 数値 | G44: 4 | H44: =SUBSTITUTE(SUBSTITUTE(ADDRESS(1,A44),"$1",""),"$","") -> AF | I44: 支払依頼取込明細の行番号 | Q44: 1（固定）
A45: =MAX($A$10:$A44)+1 -> 33 | B45: 取引種類コード | E45: 〇 | F45: コード | G45: 8 | H45: =SUBSTITUTE(SUBSTITUTE(ADDRESS(1,A45),"$1",""),"$","") -> AG | I45: 取引種類（計上される費用科目、債務科目の組合せ）を一意に識別するコード | Q45: 債務明細データ・項科目コード、目節科目コード、仕訳種別コードに応じて導出した取引種類コード
A46: =MAX($A$10:$A45)+1 -> 34 | B46: 費用計上部門表示コード | F46: コード | G46: 10 | H46: =SUBSTITUTE(SUBSTITUTE(ADDRESS(1,A46),"$1",""),"$","") -> AH | I46: 費用科目の計上部門コード | L46: ※当案件では当項目は仕訳作成には使用しないため債務計上部門と同じ。 | Q46: 債務計上部門コードと同じコード
A47: =MAX($A$10:$A46)+1 -> 35 | B47: 債務計上部門表示コード | F47: コード | G47: 10 | H47: =SUBSTITUTE(SUBSTITUTE(ADDRESS(1,A47),"$1",""),"$","") -> AI | I47: 債務科目の計上部門コード | L47: ※ProActiveの組織体系マスタに登録済のコードである必要がある | Q47: 債務計上部門コードと同じコード
A48: =MAX($A$10:$A47)+1 -> 36 | B48: 消費税区分 | F48: 区分 | G48: 2 | H48: =SUBSTITUTE(SUBSTITUTE(ADDRESS(1,A48),"$1",""),"$","") -> AJ | I48: 設定不要 | L48: ※未設定時は取引種類の消費税区分が自動で設定される。 | Q48: 設定なし
A49: =MAX($A$10:$A48)+1 -> 37 | B49: 取引金額（税込） | E49: △ | F49: 数値 | G49: 13 | H49: =SUBSTITUTE(SUBSTITUTE(ADDRESS(1,A49),"$1",""),"$","") -> AK | I49: 金額0は入力不可 | Q49: 債務明細データ・支払予定金額
A50: =MAX($A$10:$A49)+1 -> 38 | B50: 取引金額（税抜） | E50: △ | F50: 数値 | G50: 13 | H50: =SUBSTITUTE(SUBSTITUTE(ADDRESS(1,A50),"$1",""),"$","") -> AL | I50: 設定不要 | Q50: 設定なし
A51: =MAX($A$10:$A50)+1 -> 39 | B51: 消費税額 | F51: 数値 | G51: 13 | H51: =SUBSTITUTE(SUBSTITUTE(ADDRESS(1,A51),"$1",""),"$","") -> AM | I51: 設定不要 | Q51: 設定なし
A52: =MAX($A$10:$A51)+1 -> 40 | B52: 仕訳取引先コード | F52: コード | G52: 15 | H52: =SUBSTITUTE(SUBSTITUTE(ADDRESS(1,A52),"$1",""),"$","") -> AN | I52: 費用科目の内訳情報となる取引先（取引する相手先を識別する）コード | Q52: 債務明細データ・支払先区分＋支払先コード(法人+枝番)
A53: =MAX($A$10:$A52)+1 -> 41 | B53: 仕訳自社口座コード | E53: △ | F53: コード | G53: 8 | H53: =SUBSTITUTE(SUBSTITUTE(ADDRESS(1,A53),"$1",""),"$","") -> AO | I53: 費用科目の内訳情報となる出金を行う銀行口座のコード | Q53: 設定なし
I54: ※費用科目として預金科目を計上する場合、必須（実業務上ないと想定）
A55: =MAX($A$10:$A53)+1 -> 42 | B55: 仕訳プロジェクトコード | E55: △ | F55: コード | G55: 20 | H55: =SUBSTITUTE(SUBSTITUTE(ADDRESS(1,A55),"$1",""),"$","") -> AP | I55: 費用科目の内訳情報となる業種を判別するコード ※費用科目を業種別計上する場合、必須 | Q55: 債務明細データ・業種コード
A56: =MAX($A$10:$A55)+1 -> 43 | B56: 仕訳担当者コード | F56: コード | G56: 15 | H56: =SUBSTITUTE(SUBSTITUTE(ADDRESS(1,A56),"$1",""),"$","") -> AQ | I56: 空白（設定不要） | Q56: 設定なし
A57: =MAX($A$10:$A56)+1 -> 44 | B57: 仕訳セグメントコード | E57: △ | F57: コード | G57: 4 | H57: =SUBSTITUTE(SUBSTITUTE(ADDRESS(1,A57),"$1",""),"$","") -> AR | I57: 費用科目の内訳情報となる会計品目を判別するコード ※費用科目を会計品目別計上する場合、必須 | Q57: 債務明細データ・収支管理品目コードより収支管理品目マスタ・収支管理品目大分類コードに紐づく収支管理品目大分類マスタ・会計情報品目コード
A58: =MAX($A$10:$A57)+1 -> 45 | B58: 仕訳セグメントコード１ | E58: △ | F58: コード | G58: 4 | H58: =SUBSTITUTE(SUBSTITUTE(ADDRESS(1,A58),"$1",""),"$","") -> AS | I58: 空白（設定不要） | Q58: 設定なし
A59: =MAX($A$10:$A58)+1 -> 46 | B59: 仕訳セグメントコード２ | E59: △ | F59: コード | G59: 4 | H59: =SUBSTITUTE(SUBSTITUTE(ADDRESS(1,A59),"$1",""),"$","") -> AT | I59: 空白（設定不要） | Q59: 設定なし
A60: =MAX($A$10:$A59)+1 -> 47 | B60: 仕訳セグメントコード３ | E60: △ | F60: コード | G60: 4 | H60: =SUBSTITUTE(SUBSTITUTE(ADDRESS(1,A60),"$1",""),"$","") -> AU | I60: 空白（設定不要） | Q60: 設定なし
A61: =MAX($A$10:$A60)+1 -> 48 | B61: 仕訳セグメントコード４ | E61: △ | F61: コード | G61: 4 | H61: =SUBSTITUTE(SUBSTITUTE(ADDRESS(1,A61),"$1",""),"$","") -> AV | I61: 空白（設定不要） | Q61: 設定なし
A62: =MAX($A$10:$A61)+1 -> 49 | B62: 仕訳セグメントコード５ | E62: △ | F62: コード | G62: 4 | H62: =SUBSTITUTE(SUBSTITUTE(ADDRESS(1,A62),"$1",""),"$","") -> AW | I62: 空白（設定不要） | Q62: 設定なし
A63: =MAX($A$10:$A62)+1 -> 50 | B63: 費用補助科目コード | F63: コード | G63: 4 | H63: =SUBSTITUTE(SUBSTITUTE(ADDRESS(1,A63),"$1",""),"$","") -> AX | I63: 費用科目の科目摘要を判別するコード | Q63: 債務明細データ・科目摘要コード
A64: =MAX($A$10:$A63)+1 -> 51 | B64: 仕訳摘要 | F64: 文字列 | G64: 80 | H64: =SUBSTITUTE(SUBSTITUTE(ADDRESS(1,A64),"$1",""),"$","") -> AY | I64: 取引内容の説明（総勘定元帳に出力される） | Q64: 債務明細データ・経理日+債務明細データ・仕訳連番に紐づく仕訳ヘッダ・仕訳摘要
A65: =MAX($A$10:$A64)+1 -> 52 | B65: 立替金請求取引先コード | F65: コード | G65: 15 | H65: =SUBSTITUTE(SUBSTITUTE(ADDRESS(1,A65),"$1",""),"$","") -> AZ | I65: 空白（設定不要） | Q65: 設定なし
A66: =MAX($A$10:$A65)+1 -> 53 | B66: 回収予定日付 | F66: 日付 | G66: 8 | H66: =SUBSTITUTE(SUBSTITUTE(ADDRESS(1,A66),"$1",""),"$","") -> BA | I66: 空白（設定不要） | Q66: 設定なし
A67: =MAX($A$10:$A66)+1 -> 54 | B67: 立替金摘要 | F67: 文字列 | G67: 80 | H67: =SUBSTITUTE(SUBSTITUTE(ADDRESS(1,A67),"$1",""),"$","") -> BB | I67: 空白（設定不要） | Q67: 設定なし
A68: =MAX($A$10:$A67)+1 -> 55 | B68: 連携先担当部門コード | F68: コード | G68: 10 | H68: =SUBSTITUTE(SUBSTITUTE(ADDRESS(1,A68),"$1",""),"$","") -> BC | I68: 空白（設定不要） | Q68: 設定なし
A69: =MAX($A$10:$A68)+1 -> 56 | B69: 連携先計上部門コード | F69: コード | G69: 10 | H69: =SUBSTITUTE(SUBSTITUTE(ADDRESS(1,A69),"$1",""),"$","") -> BD | I69: 空白（設定不要） | Q69: 設定なし
A70: =MAX($A$10:$A69)+1 -> 57 | B70: 連携先取引種類コード | E70: △ | F70: コード | G70: 8 | H70: =SUBSTITUTE(SUBSTITUTE(ADDRESS(1,A70),"$1",""),"$","") -> BE | I70: 空白（設定不要） | Q70: 設定なし
E71: 〇：必須 △：条件付き必須

Sheet ⇒

Sheet データアクセス要領
A1: ドキュメント名 | L1: サブシステム | Q1: 業務機能名 | AJ1: 作成者 | AO1: =表紙!D51 -> SCSK大西 | AT1: 更新者
A2: 業務機能概要書 | G2: データアクセス要領 | L2: =業務機能概要!L2 -> 債務管理 | Q2: =業務機能概要!Q2 -> 支払依頼データ自動取込 | AJ2: 作成日付 | AO2: =表紙!C51 -> 45898 | AT2: 更新日付
A4: 【編集要領】
B6: データ登録の要領は、標準の「支払外部データ取込」機能の実行時と同様。

Sheet 補足
A1: ドキュメント名 | L1: サブシステム | Q1: 業務機能名 | AM1: 作成者 | AR1: =表紙!D51 -> SCSK大西 | AW1: 更新者
A2: 業務機能概要書 | G2: 補足説明 | L2: =業務機能概要!L2 -> 債務管理 | Q2: =業務機能概要!Q2 -> 支払依頼データ自動取込 | AM2: 作成日付 | AR2: =表紙!C51 -> 45898 | AW2: 更新日付
C4: 当機能でのバッチファイル、xmlファイルの作成イメージ
C7: バッチファイル１ | P7: c4_import_shhar.bat
D9: ①支払外部データ取込 | AG9: 入力データファイル（xml）
E11: 取込ファイル探索 | J11: ※取込ファイルが0byteであった場合は正常として処理終了する | AH11: 会社コードを定義する
AH12: ※ | AI12: 「cvo_sav_cd」は設定なしとして、取込ファイルは
AI13: バッチ実行定義ファイルで定義する
E14: 取込実行バッチファイルの呼び出し
E16: 正常時 | AG16: BRファイル（xml）
F17: 取込ファイルの退避（正常終了のファイル退避フォルダへ移動）
E18: エラー時 | AH18: バッチ処理の中で利用するビジネスリソース
F19: 取込ファイルの退避（異常終了のファイル退避フォルダへ移動） | AH19: J-SOXログ出力で利用するクライアント環境情報 | AW19: を定義する
C28: バッチファイル２ | I28: ※パタメータ定義用 | P28: param.bat
D30: 取込ファイルのフォルダパス、
D31: SQLファイルのパスなどを定義する
C37: バッチファイル３ | P37: Exec_shharImpBatch.bat
D39: 入力データファイル 読み込み
D41: BRファイル 読み込み
D43: バッチ実行
D44: 戻り値返却
C49: ディレクトリ構成
D52: ー | E52: ー | G52: c4_import_shiwk.bat | AD52: ・・・ | AF52: タスクスケジューラから起動されるbat
E53: ｜ | G53: param.bat | AD53: ・・・ | AF53: bat実行時に参照されるパラメータセットbat
E54: ｜
E55: ー | G55: CSV_DIR | AD55: ・・・ | AF55: 取込用のCSVファイルを配置するフォルダ
E56: ｜
E57: ー | G57: BATCH_SUB_DIR | Q57: ー | R57: Exec_shharImpBatch.bat | AD57: ・・・ | AF57: 支払外部データ取込を実行するためのbat
E58: ｜
E59: ｜
E60: ー | G60: SETTING_DIR | Q60: ー | R60: BR_AP.xml | AD60: ・・・ | AF60: BRファイル
E61: ｜ | R61: Input_shharImpBatch.xml | AD61: ・・・ | AF61: 取込用のインプットファイル
E62: ｜
E63: ｜
E64: ー | G64: SUCCESS_DIR | AD64: ・・・ | AF64: 正常取込できた取込ファイルを退避するフォルダ
E65: ｜
E66: ー | G66: ERR_DIR | AD66: ・・・ | AF66: 取込エラーとなった取込ファイルを退避するフォルダ
AF67: エラー時のログを出力するフォルダ
C94: スクラッチ開発機能からProActiveC4に連動する仕訳、支払の業務データで必要となるマスタコード
C97: ① | D97: ユーザID（起票者） | V97: → | X97: 夜間連動時のユーザIDは連動用ユーザ固定とする。 即時連動のときは伝票入力ユーザとする
C98: ② | D98: 勘定科目コード | V98: → | X98: データ連動機能で同期をとるので考慮不要
C99: ③ | D99: 取引先コード | V99: → | X99: データ連動機能で同期をとるので考慮不要
B100: ★ | C100: ④ | D100: 部門コード（ProActiveC4用コード ・・・ 事業所+業種+部課） | V100: → | X100: スクラッチ開発機能からProActiveC4へ仕訳/支払の業務データを連動する際に、
X101: 「事業所コード+業種コード＋部課コード」でセットする
C102: ⑤ | D102: 補助科目コード（会計摘要） | V102: → | X102: データ連動機能で同期をとるので考慮不要
C103: ⑥ | D103: セグメントコード（会計情報品目） | V103: → | X103: 手動でコードの同期をとるので考慮不要
C104: ⑦ | D104: プロジェクトコード（業種） | V104: → | X104: 手動でコードの同期をとるので考慮不要
C105: ⑧ | D105: 自社口座コード（出金口座） | V105: → | X105: 手動でコードの同期をとるので考慮不要
B106: ★ | C106: ⑨ | D106: 消費税区分 | H106: ※ | V106: → | X106: スクラッチ開発機能からProActiveC4へ仕訳の業務データを連動する際に、ProActiveC4のコードでセットする
C107: ⑩ | D107: 元帳領域（仕訳の種類） | V107: → | X107: 手動でコードの同期をとるので考慮不要。初期設定後、追加、変更はない想定。
C108: ⑪ | D108: 取引種類コード | V108: → | X108: 手動でコードの同期をとるので考慮不要
C109: ⑫ | D109: 支払決済条件コード | V109: → | X109: データ連動機能で同期をとるので考慮不要（スクラッチ開発機能側でコードを決定し、ProActiveC4のマスタ情報として連動する）
C110: ⑬ | D110: ＣＦ勘定科目内訳コード | V110: → | X110: 手動でコードの同期をとるので考慮不要
D113: ※ | E113: ProActiveC4の部門コードはスクラッチ開発機能のマスタ情報の「事業所」+「業種コード」+「部課コード」にするよう手動メンテナンス時に注意する
D114: ※ | E114: 消費税区分 | K114: 消費税の種類、消費税率を管理するマスタ

Sheet 補足2
A1: ドキュメント名 | L1: サブシステム | Q1: 業務機能名 | AM1: 作成者 | AR1: =表紙!D51 -> SCSK大西 | AW1: 更新者
A2: 業務機能概要書 | G2: 補足説明 | L2: =業務機能概要!L2 -> 債務管理 | Q2: =業務機能概要!Q2 -> 支払依頼データ自動取込 | AM2: 作成日付 | AR2: =表紙!C51 -> 45898 | AW2: 更新日付
B5: ● | C5: 諸口取引時の設定値
C7: ProActiveでは、「取引指摘区分」を「2：諸口取引」とした場合、No.8 諸口取引先名1～ No.24 先方負担手数料フラグの項目値を設定する必要がある。
C8: また、No.17 振込先金融機関コード～No.24 先方負担手数料フラグは、諸口取引でかつ、支払方法が「振込」となる場合のみ設定が必要となる。
C9: 支払方法は、No.28 支払決済条件コードで決定する。
C50: ① | D50: No.7 取引先コード、No.28 支払決済条件コード
D52: ホクレン様業務では、諸口取引は、諸口取引の支払と、退職金の支払いを想定している。
D53: 諸口取引の場合は、取引先コードは諸口取引用のコードを指定する。
D55: また、諸口取引の支払の場合は、振込先の金融機関、口座等の情報は、伝票起票時には不明であると想定されるため、No.28 支払決済条件コードにて振込以外のコードを設定し、
D56: No.17 振込先金融機関コード～No.24 先方負担手数料フラグは設定不要とする想定である。
D58: 以下、取引先コードと支払決済条件コードのイメージを示す。以下の情報はProActiveの取引先マスタに初期設定する。
D61: 取引先コード | H61: 取引先名 | L61: ・・・ | N61: 支払決済条件コード | T61: 支払決済条件名 | Z61: 支払方法 | AD61: 出金口座 | AL61: ・・・ | AN61: 振込先金融機関 | AT61: 振込先店舗 | AY61: 口座番号
D62: 135260001 | H62: ホクレン職員給与口 | N62: 007 | T62: 人件費支払 | Z62: 振込（FBなし） | AD62: 信連 | AN62: - (指定不可) | AT62: - (指定不可) | AY62: - (指定不可)
D63: 135260001 | H63: ホクレン職員給与口 | N63: 021 | T63: 諸口振込 | Z63: 振込 | AD63: 信連 | AN63: - (指定不可) | AT63: - (指定不可) | AY63: - (指定不可)
D64: 135260001 | H64: ホクレン職員給与口 | N64: 022 | T64: 諸口振込 | Z64: 振込 | AD64: 道銀 | AN64: - (指定不可) | AT64: - (指定不可) | AY64: - (指定不可)
D65: 135260001 | H65: ホクレン職員給与口 | N65: 009 | T65: 諸口振込以外 | Z65: 振替 | AD65: － | AN65: - (指定不可) | AT65: - (指定不可) | AY65: - (指定不可)
AD66: ※諸口支払先の場合は振込先から導出できない
D68: 諸口取引の場合で、伝票起票時に振込先が未定の場合は、支払決済条件コードを「009」と設定する。その場合は、No.17 振込先金融機関コード～No.24 先方負担手数料フラグは設定不要。
D69: 諸口取引の場合で、伝票起票時に振込先が決定されている場合（退職金支払）は、支払決済条件コードを「021」と設定する。その場合は、No.17 振込先金融機関コード～No.24 先方負担手数料フラグ
D70: は設定が必要となる。
D72: ※ | E72: ProActiveでは、諸口支払の支払方法は「支払手段」が振込または現金のものしか設定できない
