Workbook
Name 【債権】最新データ辞書: [1]データ辞書!$H$331:$O$5000
Name 項目辞書: [2]項目辞書!$A$3:$G$1522

Sheet 表紙
F46: ProActive
B48: 変更履歴
B50: 項番 | C50: 変更発生日 | D50: 変更者 | E50: 変更箇所 | F50: 変更内容
B51: 1 | C51: 45898 | D51: SCSK井上 | F51: 新規作成
B52: 2
B53: 3
B54: 4
B55: 5
B56: 6
B57: 7
B58: 8
B59: 9
B60: 10
B61: 11
B62: 12
B63: 13
... B80: 30

Sheet 業務機能概要
A1: ドキュメント名 | L1: サブシステム | Q1: 業務機能名 | AJ1: 作成者 | AO1: =表紙!D51 -> SCSK井上 | AT1: 更新者
A2: 業務機能概要書 | G2: 業務機能概要 | L2: 財務会計 | Q2: 仕訳連動 | AJ2: 作成日付 | AO2: =表紙!C51 -> 45898 | AT2: 更新日付
B4: 【目的・役割】
C5: ・ | D5: ホクレン様の仕訳情報は、スクラッチ開発機能にて全量を持つ想定である。
D6: しかし、以下の仕訳データはProActiveC4にて作成する想定である。
D8: ① | E8: 支払決済時の仕訳 | L8: ・・・取引の支払を行った際の仕訳。ProActiveC4債務管理サブシステムにて支払決済確定処理を
M9: 実施したタイミングで自動的に起票される。
D10: ② | E10: 債務科目の振替仕訳 | L10: ・・・計上されている債務科目を別科目に振り替える仕訳。ProActiveC4債務管理サブシステムにて債務振替処理を
M11: 実施したタイミングで自動的に起票される。
D12: ③ | E12: 組替仕訳 | L12: ・・・決算時、帳簿上の勘定科目を財務諸表の表示科目に変換する仕訳。ProActiveC4財務会計サブシステムにて起票する。
M13: 翌期になったタイミングで洗替する。
D15: 上記①、②の仕訳はスクラッチ開発機能に連動する必要がある。
D16: 今回、ProActiveC4側で新規開発する仕訳連動機能にて、①、②の仕訳データをスクラッチ開発機能へ連動する。
B18: 【利用者】
C19: ・ | D19: バッチ
B22: 【利用頻度】
C23: ・ | D23: 日次
B26: 【対象要件定義書】
C27: ・ | D27: 要件定義書（仕訳連動）.xls
B30: 【処理概要】
C31: １) | D31: ProActiveC4で作成した仕訳情報を抽出する。
D33: ① | E33: 仕訳連動バッチ処理開始日時の取得
E35: 前回、仕訳連動バッチ処理を開始した日時以降かつ、今回仕訳連動バッチ処理を開始した日時までに作成された仕訳を抽出対象とする。
E36: そのため、仕訳連動バッチ処理を開始したタイミングで日時（YYYYMMDDHHMMSSmmm）を取得する。
E37: 日時は、ProActiveC4のシステム日時から取得する。
D39: ② | E39: 抽出条件
E41: 抽出対象となるデータの項目は、出力CSV定義シート参照。
E42: 以下の条件に合致するデータを抽出する。
F44: ・ProActiveC4で作成された仕訳（スクラッチ開発機能等から連動された仕訳は対象外）
F45: ・前回の仕訳連動バッチ処理の実行開始日時以降に作成された仕訳 | AC45: ※変数管理テーブルを作成し、仕訳連動バッチ処理実行開始日時の履歴情報を管理する。
F46: ・出力対象となる元帳領域を使用している仕訳 | AC46: ※変数管理テーブルを作成し、出力対象外の元帳領域コードを管理する。
D50: ③ | E50: 出力項目
E52: 出力CSV定義参照
D55: ④ | E55: コード変換
E57: 出力項目のうち、ProActiveC4固有のコードについて、スクラッチ開発機能に合わせたコード変換を実施する。
D60: ⑤ | E60: CSVファイル出力
E62: ③で出力対象データが1件以上取得できた場合、仕訳データをCSVファイル出力する。
F64: ・ | G64: ファイル名は「siwk_ 」に①で取得した仕訳連動バッチ処理開始日時を付加する。
G65: 例) | I65: ファイル名：siwk_YYYYMMDDHHMMSSmmm.csv
F67: ・ | G67: 変数管理テーブルから、ファイル出力先パスを取得する。 | AJ67: ※ | AK67: 変数管理テーブルを作成し、仕訳データ出力先の
AK68: フォルダパスを管理する。
C71: ２) | D71: 仕訳連動バッチ処理最終実行開始日時を更新する。
D72: 変数管理テーブルの仕訳連動バッチ処理最終実行開始日時を更新する。
D73: １)-①で取得した仕訳連動バッチ処理開始日時で更新する。
C96: ３) | D96: バッチ処理実行結果をバッチジョブ情報に登録する。
D97: 仕訳データ出力の処理状況は、ProActiveC4標準の「バッチジョブ一覧検索」機能にて確認可能とする。
D98: （機能名は「仕訳データ出力バッチイベント」とする。）
D100: ・ | E100: 正常終了の場合
E101: メッセージＩＤ | L101: メッセージ内容
E102: AI99_GLCST01 | L102: 仕訳データ出力の処理が完了しました。
D104: ・ | E104: 出力対象データがない場合（正常終了）
E105: メッセージＩＤ | L105: メッセージ内容
E106: AI99_GLCST02 | L106: 仕訳データ出力の処理が完了しました。出力対象のデータはありませんでした。
D108: ・ | E108: エラーが発生した場合
E109: メッセージＩＤ | L109: メッセージ内容
E110: AE99_GLCST01 | L110: 仕訳データ出力の処理が失敗しました。
E111: ※ | F111: 業務エラーは発生しない想定とする。
F112: また、処理時間のタイムアウトなどの予期しないエラーが発生した場合は、CSVファイル出力、バッチ処理最終実行開始日時の更新を未処理状態とする。
C115: ４) | D115: バッチ処理実行結果の終了情報をタスクスケジューラに返却する。
D116: 仕訳データ出力のバッチ処理は、ProActiveC4外のタスク管理用のミドルウェア（以下、タスクスケジューラ）から実行する想定とする。
D118: [実行情報]
D119: No | F119: パラメータ | O119: 内容
D120: 1 | F120: ※イベント概要参照
D122: [終了情報]
D123: 戻り値 | F123: 内容 | O123: 内容
D124: 0 | F124: 正常終了 | O124: 正常終了/出力対象データがない場合（正常終了）
D125: 1 | F125: 異常終了 | O125: 業務エラー/システムエラー発生時
B128: 【共通要件】
D129: 共通要件内容 | J129: 対応内容（標準準拠の場合、記載省略）
D130: セキュリティ | J130: 部門制限、本人制限の機能性は実装しない。
D131: 承認WF | J131: 対応なし。承認WFの利用は不可とする。
D132: 組織変更 | J132: 標準準拠（対象外（財務会計サブシステムの組織変更で対応されるため））
B142: 【前提・制約事項】
C143: １) | D143: 開発機能では、該当する情報を所定のディレクトリにファイル出力するところまでを範囲とし、
D144: スクラッチ開発機能のサーバ環境へのファイル転送は別途ミドルウエア（Hulft等）で実施する想定とする。
C146: ２) | D146: 開発機能と併せて変数管理テーブルを作成し、以下の項目を変数管理テーブルで管理する。
E147: ・ファイル出力の最終実行開始日時（ファイル出力を開始するタイミングで最終実行開始日時を更新する。）
E148: ・出力対象外の元帳領域コード（出力対象外としたい元帳領域の元帳領域コードは連番で採番するものとする。）
E149: ・外部連動用のユーザID
E150: ・スクラッチ開発機能への連動項目のうち、スクラッチ側から指定されている固定値
D151: 上記項目は、抽出条件、出力項目として使用する。
C153: ３) | D153: 出力項目のうち、ProActiveC4固有のコードについて、スクラッチ開発機能に合わせたコード変換が必要になるが、スクラッチ開発機能のマスタ情報を管理するマスタ管理システムと
D154: ProActiveC4間で連動するマスタ情報については、コード変換を不要とする。
C156: ４) | D156: 出力データの件数に応じて出力ファイルを分割するという考慮は行わない。
C158: ５) | D158: 仕訳データ出力の処理結果は、ProActiveC4標準の「バッチジョブ一覧検索」機能にて確認し、処理結果ログ等の出力機能の開発やOUTキューの登録は実施しない。
C160: ６) | D160: CSVファイルの出力先は、ProActiveC4のバッチサーバ上とする。
D161: また、ファイル転送を実施するミドルウェア（Hulft等）から参照可能なディレクトリとする。
C163: ７) | D163: 所定のディレクトリに出力されたCSVファイルは、スクラッチ開発機能のサーバ環境へのファイル転送後に削除する想定とする。
D164: （削除処理は、当機能とは別にファイル削除処理を作成して、その処理で実施する）
C166: ８) | D166: ProActiveC4標準機能の決済後データ取消機能は使用しないこととする。決済後データ取消の後に仕訳伝票を削除すると物理削除されてしまう。
D167: ProActiveC4上で仕訳伝票の物理削除が行われてしまうと、スクラッチ開発機能へ連動する仕訳情報の残高が合わなくなる。（補足シート参照）
B170: 【主な取り扱い情報】
C171: ①仕訳データ出力
D172: № | E172: 取り扱う情報 | O172: I/O | Q172: 用途
D173: 1 | E173: 変数管理テーブル | O173: IN | Q173: 仕訳データ出力処理の最終実行開始日付を管理する。出力対象データの抽出条件に使用する。
Q174: 仕訳データ出力処理のファイル出力先パスを管理する。ファイル出力先パスの取得に使用する。
Q175: スクラッチ開発機能への連動項目のうち、スクラッチ側から指定されている固定値を管理する。
Q176: 外部連動用のユーザIDを管理する。出力対象外の元帳領域コードを管理する。
D177: 2 | E177: 仕訳伝票テーブル | O177: OUT | Q177: 出力データに使用。
D178: 3 | E178: 仕訳伝票明細テーブル | O178: OUT | Q178: 出力データに使用。

Sheet イベント概要
A1: ドキュメント名 | L1: サブシステム | Q1: 業務機能名 | AJ1: 作成者 | AO1: =表紙!D51 -> SCSK井上 | AT1: 更新者
A2: 業務機能概要書 | G2: イベント概要 | L2: =業務機能概要!L2 -> 財務会計 | Q2: =業務機能概要!Q2 -> 仕訳連動 | AJ2: 作成日付 | AO2: =表紙!C51 -> 45898 | AT2: 更新日付
A4: 【イベント処理】
B5: № | C5: イベント名 | J5: 処理説明
B6: =IF(C6="","",MAX(B$5:B5)+1) -> 1 | C6: 仕訳連動 | J6: １． | L6: 仕訳連動バッチ処理開始日時（YYYYMMDDhhMMssmmm）を取得する。 | EV6: 注１）初期表示は全ての
C7: バッチイベント | EV7: データを処理対象とする
B8: =IF(C8="","",MAX(B$5:B7)+1) | J8: ２. | L8: 変数管理TBLから抽出条件（バッチ処理最終実行開始日時）を取得する。（データアクセス要領１．参照）
L9: <パラメータ>
L10: ・ | M10: 会社コード | Q10: ： | R10: バッチ実行用のxmlファイルで指定された会社コード
L11: ・ | M11: 変数ID | Q11: ： | R11: 変数管理テーブルで管理する「仕訳データ出力処理最終実行開始日時」の管理ID
B13: =IF(C13="","",MAX(B$5:B8)+1) | J13: ３. | L13: 変数管理TBLから抽出条件（出力対象外の元帳領域コード）を取得する。（データアクセス要領２．参照）
L14: <パラメータ>
L15: ・ | M15: 会社コード | Q15: ： | R15: バッチ実行用のxmlファイルで指定された会社コード
L16: ・ | M16: 変数ID | Q16: ： | R16: 変数管理テーブルで管理する「出力対象外の元帳領域コード」の管理ID
B17: =IF(C17="","",MAX(B$5:B9)+1)
J18: ４. | L18: 変数管理TBLから抽出条件（外部連動用ユーザID）を取得する。（データアクセス要領３．参照）
L19: <パラメータ>
L20: ・ | M20: 会社コード | Q20: ： | R20: バッチ実行用のxmlファイルで指定された会社コード
L21: ・ | M21: 変数ID | Q21: ： | R21: 変数管理テーブルで管理する「外部連動用ユーザID」の管理ID
J23: ５. | L23: 仕訳データを取得する。（データアクセス要領４．参照）
L24: <パラメータ>
L25: ・ | M25: 会社コード | Q25: ： | R25: バッチ実行用のxmlファイルで指定された会社コード
B26: =IF(C26="","",MAX(B$5:B25)+1) | L26: ・ | M26: 変数1 | Q26: ： | R26: ２．で取得した「仕訳データ出力処理最終実行開始日時」
L27: ・ | M27: 変数2 | Q27: ： | R27: ３．で取得した「出力対象外の元帳領域コードFROM」
L28: ・ | M28: 変数3 | Q28: ： | R28: ３．で取得した「出力対象外の元帳領域コードTO」
L29: ・ | M29: 変数4 | Q29: ： | R29: ４．で取得した「外部連動用ユーザID」
B30: =IF(C30="","",MAX(B$5:B26)+1)
B31: =IF(C31="","",MAX(B$5:B30)+1) | J31: ６. | L31: 仕訳データが1件以上取得できた場合、仕訳データをCSVファイルで出力する。（出力CSV定義参照）
L32: ※ | M32: 出力対象データがない場合、後続の処理に移行する。（当処理呼び出し用のbatファイルにて0byteファイルを作成する（ヘッダ行も作成しない））
L33: ・ | M33: ファイル名に１．で取得した仕訳連動バッチ処理実行開始日時を付加する。
L34: ・ | M34: 変数管理TBLからファイル出力先パスを取得する。（データアクセス要領５．参照）
M35: <パラメータ>
M36: ・ | N36: 会社コード | R36: ： | S36: バッチ実行用のxmlファイルで指定された会社コード
M37: ・ | N37: 変数1 | R37: ： | S37: 変数管理テーブルで管理する「仕訳データ出力先パス」の管理ID
J39: ７. | L39: 変数管理TBLのバッチ処理最終実行開始日時を更新する。（データアクセス要領６．参照）
L40: <パラメータ>
L41: ・ | M41: 会社コード | Q41: ： | R41: バッチ実行用のxmlファイルで指定された会社コード
L42: ・ | M42: 変数ID | Q42: ： | R42: 変数管理テーブルで管理する「仕訳データ出力処理最終実行開始日時」の管理ID
J44: ８. | L44: バッチ処理実行結果をバッチジョブ情報に登録する。
J46: ９. | L46: バッチ処理実行結果の終了情報をタスクスケジューラに返却する。

Sheet 出力CSV定義
A1: ドキュメント名 | E1: サブシステム | G1: 業務機能名 | P1: 作成者 | R1: =表紙!D51 -> SCSK井上 | T1: 更新者
A2: 業務機能概要書 | C2: 出力CSV定義 | E2: =業務機能概要!L2 -> 財務会計 | G2: =業務機能概要!Q2 -> 仕訳連動 | P2: 作成日 | R2: =表紙!C51 -> 45898 | T2: 更新日
A4: データ名 | C4: 仕訳データ | I4: ヘッダ行 | K4: あり | M4: なし | N4: ダブルクォーテーション | Q4: あり | S4: なし | AB4: 文字列
A5: ﾌｧｲﾙ形式・ﾚｺｰﾄﾞ長 | D5: 固定長（ | G5: Byte） | I5: 可変長（区切り文字［ ，(カンマ) ］） | M5: バイナリデータ | P5: その他（ ） | AB5: 半英数
A6: 文字コード | D6: UNI（Win系） | F6: EBCDIC(K) | I6: その他（UTF-8） | M6: 改行コード | O6: LF(UNIX系) | Q6: CRLF(Win系) | T6: なし | AB6: 半カナ
A7: 全角(2byte)文字項目 | D7: あり | F7: なし | M7: 数値編集 | O7: 左詰め | Q7: 右詰め［ゼロ埋め］ | T7: 右詰め［スペース埋め］ | AB7: コード
A8: 特記事項 | AB8: 数値
A9: No. | B9: 項目名 | E9: 必須 | F9: 型 | G9: 桁数 | H9: 開始位置 | I9: 項目説明 | S9: 設定値 | AB9: 日付
H10: /列 | AB10: 時間
A11: 1 | B11: 削除区分 | E11: 〇 | F11: 区分 | G11: 1 | H11: A | I11: 対象レコードの論理的な有効性を示す。0:有効、1:無効（論理削除状態） | S11: ０(固定値) | AB11: 年月
A12: 2 | B12: 排他カウンタ | E12: 〇 | F12: 数値 | G12: 1 | H12: B | I12: 排他制御に使用するカウンタ。 | S12: ０(固定値) | AB12: 区分
A13: 3 | B13: 作成日時 | E13: 〇 | F13: 時間 | H13: C | I13: 対象レコードが最初に作成された日時。 | S13: 空欄 | AB13: フラグ
A14: 4 | B14: 最終更新日時 | E14: 〇 | F14: 時間 | H14: D | I14: 対象レコードが最後に更新された日時。 | S14: 空欄 | AB14: -
A15: 5 | B15: 最終更新者ユーザーＩＤ | E15: 〇 | F15: 文字列 | G15: 8 | H15: E | I15: 対象レコードを最後に更新したユーザーのユーザーID。 | S15: CST変数管理．CST変数１
A16: 6 | B16: データ種別 | F16: 文字列 | G16: 2 | H16: F | I16: ＩＦ制御部、DEX登録申請で決定した種別。 | S16: 空欄
A17: 7 | B17: データ区分 | F17: 文字列 | G17: 1 | H17: G | I17: 連動データの登録、訂正、削除を表す区分。１：登録、２：訂正、３：削除。 | S17: １(固定値)
A18: 8 | B18: 経理日 | E18: 〇 | F18: 日付 | H18: H | I18: 会計帳簿上、取引が認識される日付 | S18: 仕訳伝票．仕訳伝票起票日付
A19: 9 | B19: 取引日 | F19: 日付 | H19: I | I19: 仕訳作成日付 | S19: 仕訳伝票．仕訳伝票起票日付
A20: 10 | B20: 連動元システム管理コード | F20: 文字列 | G20: 2 | H20: J | I20: 連動元のシステムを識別するためのコード。 | S20: CST変数管理．CST変数２
A21: 11 | B21: 発生元システム管理コード | F21: 文字列 | G21: 2 | H21: K | I21: 入力機能のシステム管理コード。 | S21: CST変数管理．CST変数３
A22: 12 | B22: 添付ファイル数 | F22: 数値 | G22: 1 | H22: L | I22: 添付ファイル数。 | S22: ０(固定値)
A23: 13 | B23: 仕訳種別コード | F23: 文字列 | G23: 2 | H23: M | I23: 仕訳伝票の発生元機能を識別する為のコード。 | S23: CST変数管理．CST変数４
A24: 14 | B24: 仕訳種類コード | F24: 文字列 | G24: 1 | H24: N | I24: 仕訳の種類を表すコード。 | S24: CST変数管理．CST変数５
A25: 15 | B25: 仕訳番号 | E25: 〇 | F25: 文字列 | G25: 11 | H25: O | I25: ホクレン財務会計システムで管理する仕訳番号。連動元システム管理コード[2桁]＋処理単位連番[2桁]＋連番[7桁]。 | S25: 空欄
A26: 16 | B26: 連動元仕訳番号 | F26: 文字列 | G26: 9 | H26: P | I26: 連動元システムで発番された発生元の仕訳番号 | S26: 仕訳伝票．仕訳伝票番号
A27: 17 | B27: 事業所コード | F27: 文字列 | G27: 2 | H27: Q | I27: ホクレンの事業所を分類するコード | S27: 組織体系．部門表示コードの先頭2桁
A28: 18 | B28: 業種コード | F28: 文字列 | G28: 2 | H28: R | I28: ホクレンの業種を分類するコード | S28: 組織体系．部門表示表示コードの3~4桁
A29: 19 | B29: 予算組織コード | F29: 文字列 | G29: 4 | H29: S | I29: ホクレンの組織コード | S29: 組織体系．部門表示表示コードの下4桁
A30: 20 | B30: 仕訳摘要 | F30: 文字列 | G30: 96 | H30: T | I30: 仕訳摘要 | S30: 仕訳伝票．仕訳伝票摘要
A31: 21 | B31: 出金時計上区分 | F31: 文字列 | G31: 1 | H31: U | I31: 支払時計上仕訳を起票をするか否かの区分。 | S31: 空欄
A32: 22 | B32: 発生元システム取引番号 | F32: 文字列 | G32: 24 | H32: V | I32: 各部門システムや経費システムで取引を照会するための番号 | S32: 仕訳伝票．仕訳伝票番号
A33: 23 | B33: 仕訳作成日時 | F33: 時間 | H33: W | I33: 仕訳の作成日時 | S33: 仕訳伝票．登録日時
A34: 24 | B34: 仕訳作成担当者 | F34: 文字列 | G34: 8 | H34: X | I34: 仕訳伝票の作成を行った職員の職員番号 | S34: 仕訳伝票．登録者
A35: 25 | B35: 仕訳作成担当者所属コード | F35: 文字列 | G35: 4 | H35: Y | I35: 仕訳伝票の作成を行った職員が所属する部署を示すコード | S35: 空欄（登録者のIDからスクラッチ側で取得）
A36: 26 | B36: 仕訳更新日時 | F36: 時間 | H36: Z | I36: 仕訳の更新日時（最後に行われた、一時保存、登録、承認依頼時の日時を保持） | S36: 仕訳伝票．更新日時
A37: 27 | B37: 仕訳更新担当者 | F37: 文字列 | G37: 8 | H37: AA | I37: 仕訳伝票の一時保存、登録、承認依頼を行った職員の職員番号 | S37: 仕訳伝票．更新者
A38: 28 | B38: 仕訳更新担当者所属コード | F38: 文字列 | G38: 4 | H38: AB | I38: 仕訳伝票の一時保存、登録、承認依頼を行った職員が所属する部署を示すコード | S38: 空欄（登録者のIDからスクラッチ側で取得）
A39: 29 | B39: 承認依頼日時 | F39: 時間 | H39: AC | I39: 仕訳伝票の承認依頼を行った際の日時 | S39: 仕訳伝票．更新日時
A40: 30 | B40: 承認依頼者 | F40: 文字列 | G40: 8 | H40: AD | I40: 承認依頼者の職員番号 | S40: 仕訳伝票．サブシステムID＝'AP'のとき、固定値。それ以外は仕訳伝票．更新者
A41: 31 | B41: 承認依頼者所属コード | F41: 文字列 | G41: 4 | H41: AE | I41: 承認依頼者が所属する部署を表すコード | S41: 空欄（更新者のIDからスクラッチ側で取得）
A42: 32 | B42: 承認差戻日時 | F42: 時間 | H42: AF | I42: 仕訳伝票の承認、差戻を行った際の日時 | S42: 仕訳伝票．更新日時
A43: 33 | B43: 承認差戻担当者 | F43: 文字列 | G43: 8 | H43: AG | I43: 承認差戻担当者の職員番号 | S43: 仕訳伝票．サブシステムID＝'AP'のとき、固定値。それ以外は仕訳伝票．更新者
A44: 34 | B44: 承認差戻担当者所属コード | F44: 文字列 | G44: 4 | H44: AH | I44: 承認差戻担当者が所属する部署を表すコード | S44: 空欄（更新者のIDからスクラッチ側で取得）
A45: 35 | B45: 決裁日時 | F45: 時間 | H45: AI | I45: 取引を経理計上した日時 | S45: 仕訳伝票．更新日時
A46: 36 | B46: 決裁者コード | F46: 文字列 | G46: 8 | H46: AJ | I46: 取引承認者の職員コード | S46: 仕訳伝票．サブシステムID＝'AP'のとき、固定値。それ以外は仕訳伝票．更新者
A47: 37 | B47: 決裁所属コード | F47: 文字列 | G47: 4 | H47: AK | I47: 取引承認者の所属コード | S47: 空欄（更新者のIDからスクラッチ側で取得）
A48: 38 | B48: 取消訂正理由コード | F48: 文字列 | G48: 2 | H48: AL | I48: 会計情報システムで管理されている取消訂正理由。 | S48: 空欄
A49: 39 | B49: 取消理由 | F49: 文字列 | G49: 45 | H49: AM | I49: 取消時に入力する理由（仕訳伝票の取消時に入力）。 | S49: 空欄
A50: 40 | B50: 元取引日 | F50: 日付 | H50: AN | I50: 赤伝に対する元伝の取引日付。 | S50: 空欄
A51: 41 | B51: 訂正元発生元システム取引番号 | F51: 文字列 | G51: 24 | H51: AO | I51: 赤黒の対象となった元伝の取引を照会するための番号。 | S51: 空欄
A52: 42 | B52: 元伝エラー区分 | F52: 文字列 | G52: 1 | H52: AP | I52: 元伝チェックの結果を識別する区分。 | S52: 空欄
A53: 43 | B53: りん議書ＵＲＬ | F53: 文字列 | G53: 500 | H53: AQ | I53: 仕訳に紐づくワークフローのURL | S53: 空欄
A54: 44 | B54: 伝票番号 | F54: 文字列 | G54: 14 | H54: AR | I54: 経理年度[西暦下2桁]＋事業所コード[2桁]＋仕訳種類[1桁]＋連番[7桁]＋枝番[2桁]。合計14桁、表示時ハイフンを含めるとMAX18桁。 | S54: 空欄
A55: 45 | B55: 共計区分 | F55: 文字列 | G55: 1 | H55: AS | I55: 全道共計か地区共計か全国共計かの区分。1：全道共計、2：地区共計、3：全国共計、4：購買在庫、5：購買直送。 | S55: 空欄
A56: 46 | B56: 入出荷日 | F56: 日付 | H56: AT | I56: 入荷・出荷の日付。 | S56: 空欄
A57: 47 | B57: 取扱区分 | F57: 文字列 | G57: 1 | H57: AU | I57: ホクレンでの取扱をあらわす区分 | S57: 空欄
A58: 48 | B58: ＰＡ集約先伝票番号 | F58: 文字列 | G58: 12 | H58: AV | I58: PA側の仕訳データを特定するための番号 | S58: 仕訳伝票．仕訳伝票番号
A59: 49 | B59: 仕訳番号 | E59: 〇 | F59: 文字列 | G59: 11 | H59: AW | I59: ホクレン財務会計システムで管理する仕訳番号。連動元システム管理コード[2桁]＋処理単位連番[2桁]＋連番[7桁]。 | S59: 空欄
A60: 50 | B60: 仕訳明細番号 | E60: 〇 | F60: 数値 | G60: 4 | H60: AX | I60: ホクレン財務会計システムで管理する仕訳番号配下の明細番号。 | S60: 空欄
A61: 51 | B61: 連動元仕訳番号 | F61: 文字列 | G61: 9 | H61: AY | I61: 連動元システムで発番された発生元の仕訳番号 | S61: 仕訳伝票．仕訳伝票番号
A62: 52 | B62: 連動元仕訳明細番号 | F62: 数値 | G62: 4 | H62: AZ | I62: 連動元システムで発番された発生元の仕訳明細番号 | S62: 仕訳伝票明細．仕訳伝票行番号
A63: 53 | B63: 業種コード | F63: 文字列 | G63: 2 | H63: BA | I63: ホクレンの業種を分類するコード | S63: 組織体系．部門表示表示コードの3~4桁
A64: 54 | B64: 予算組織コード | F64: 文字列 | G64: 4 | H64: BB | I64: ホクレンの組織コード | S64: 組織体系．部門表示表示コードの下4桁
A65: 55 | B65: 管理会計事業所コード | F65: 文字列 | G65: 2 | H65: BC | I65: ホクレンの事業所を分類するコード。予算組織コードより導き出され、管理会計要件において使用する。 | S65: 空欄
A66: 56 | B66: 購買販売区分 | F66: 文字列 | G66: 1 | H66: BD | I66: 購買、販売。 | S66: 空欄
A67: 57 | B67: 勘定科目コード | F67: 文字列 | G67: 6 | H67: BE | I67: 勘定科目の款分類＋項分類に相当するコード 款コード＋項コード | S67: 仕訳伝票明細．勘定科目コードの1~6桁
A68: 58 | B68: 款科目コード | F68: 文字列 | G68: 4 | H68: BF | I68: 勘定科目の款分類に相当するコード。款コード。 | S68: 空欄
A69: 59 | B69: 分類口座コード | F69: 文字列 | G69: 2 | H69: BG | I69: 広義の勘定科目の中での小分類に相当するコード。 | S69: 空欄
A70: 60 | B70: 管理項目コード | F70: 文字列 | G70: 3 | H70: BH | I70: 広義の勘定科目の中で、管理会計的要件のために使用されるコード。 | S70: 空欄
A71: 61 | B71: 目節科目コード | F71: 文字列 | G71: 2 | H71: BI | I71: 勘定科目コード（款＋項）に紐づく目節科目コード | S71: 仕訳伝票明細．勘定科目コードの7~8桁
A72: 62 | B72: 共計内訳コード | F72: 文字列 | G72: 2 | H72: BJ | I72: 共計勘定の管理項目的使い方で、品代、手数料等の分類するコード。 | S72: 空欄
... A83: 73 | B83: 科目摘要細目 | F83: 文字列 | G83: 4 | H83: BU | I83: 科目摘要の細目（年度、月度） | S83: 空欄
A84: 74 | B84: 消費税基準日 | F84: 日付 | H84: BV | I84: 消費税計上時の基準日 | S84: 仕訳伝票．仕訳伝票起票日付
A85: 75 | B85: 消費税取引区分 | F85: 文字列 | G85: 2 | H85: BW | I85: 取引毎の消費税種類 消費税の発生した取引における消費税を消費税法に基づき分類する種類の区分 | S85: 消費税区分変換テーブル．スクラッチ消費税区分
A86: 76 | B86: 消費税率（連動） | F86: 数値 | G86: 9,4 | H86: BX | I86: 消費税率の数値 | S86: 消費税率．消費税率
A87: 77 | B87: 消費税コード | F87: 文字列 | G87: 2 | H87: BY | I87: 消費税コード | S87: 空欄
A88: 78 | B88: 科目摘要補足 | F88: 文字列 | G88: 60 | H88: BZ | I88: 科目摘要の補足（年度、日付、回数等） | S88: 仕訳伝票明細．仕訳伝票明細摘要
A89: 79 | B89: 伝票番号 | F89: 文字列 | G89: 14 | H89: CA | I89: 経理年度[西暦下2桁]＋事業所コード[2桁]＋仕訳種類[1桁]＋連番[7桁]＋枝番[2桁]。合計14桁、表示時ハイフンを含めるとMAX18桁。 | S89: 空欄
A90: 80 | B90: 伝票明細番号 | F90: 数値 | G90: 3 | H90: CB | I90: 仕訳伝票の明細行番号を示す番号。 | S90: 空欄
A91: 81 | B91: 免税区分 | F91: 数値 | G91: 1 | H91: CB | I91: 課税仕入れ（戻し、軽減税率含む）における立替金消費税の免税対象となる仕訳明細を判別する区分（0：課税、1：免税） | S91: 消費税区分変換テーブル．免税区分
A92: 82 | B92: ＣＦ勘定科目内訳コード | F92: 文字列 | G92: 2 | H92: CB | I92: PAでC/F対象の仕訳明細（勘定科目）に対して発生事由を設定する為に必要な内訳コード | S92: 仕訳伝票明細．CF勘定科目内訳コード
A93: 83 | B93: 支払入金予定日 | F93: 文字列 | H93: CB | I93: 支払または入金を行う予定日 | S93: 空欄
A94: 84 | B94: 支払入金方法 | F94: 文字列 | G94: 1 | H94: CB | I94: 支払時の支払方法もしくは、入金時の入金方法の区分を表す | S94: 空欄
A95: 85 | B95: 入出金番号 | F95: 文字列 | G95: 14 | H95: CB | I95: システム入金、出金勘定に紐づく管理番号 | S95: 空欄
A96: 86 | B96: ＰＡ集約先伝票明細番号 | F96: 文字列 | G96: 12 | H96: CB | S96: 仕訳伝票明細．仕訳伝票行番号
A97: 87 | B97: 相手先区分 | F97: 文字列 | G97: 1 | H97: CB | I97: 相手先コードの種別（取引先や農協などを識別するための種別） | S97: 仕訳伝票明細．取引先コードの先頭1桁
A98: 88 | B98: 相手先コード | F98: 文字列 | G98: 9 | H98: CB | I98: 相手先を分類するコード | S98: 仕訳伝票明細．取引先コードの2~9桁目
A99: 89 | B99: 諸口取引先カナ名称 | F99: 文字列 | G99: 69 | H99: CB | I99: 相手先コードの相手先名称 | S99: 空欄
A100: 90 | B100: 会計情報品目コード | F100: 文字列 | G100: 3 | H100: CB | I100: 商品の大分類（決済単位の品目） | S100: 仕訳伝票明細．セグメントコード
A101: 91 | B101: 出荷元コード | F101: 文字列 | G101: 9 | H101: CB | I101: 相手先の出荷元を表すコード。 | S101: 空欄
A102: 92 | B102: 添付ファイル名称１ | E102: 〇 | F102: 文字列 | G102: 64 | H102: CB | I102: 添付ファイル名１。 | S102: 空欄
A103: 93 | B103: 添付ファイルパス１ | E103: 〇 | F103: 文字列 | G103: 1000 | H103: CB | I103: 添付ファイルパス１。 | S103: 空欄
A104: 94 | B104: 添付ファイル名称２ | E104: 〇 | F104: 文字列 | G104: 64 | H104: CB | I104: 添付ファイル名２。 | S104: 空欄
A105: 95 | B105: 添付ファイルパス２ | E105: 〇 | F105: 文字列 | G105: 1000 | H105: CB | I105: 添付ファイルパス２。 | S105: 空欄
A106: 96 | B106: 添付ファイル名称３ | E106: 〇 | F106: 文字列 | G106: 64 | H106: CB | I106: 添付ファイル名３。 | S106: 空欄
A107: 97 | B107: 添付ファイルパス３ | E107: 〇 | F107: 文字列 | G107: 1000 | H107: CB | I107: 添付ファイルパス３。 | S107: 空欄
A108: 98 | B108: 自社口座コード | F108: 文字列 | G108: 8 | H108: CB | I108: 自社の銀行口座コード | S108: 仕訳伝票明細．自社口座コード

Sheet 出力CSVサンプル
A1: 削除区分 | B1: 排他カウンタ | C1: 作成日時 | D1: 最終更新日時 | E1: 最終更新者ユーザーID | F1: データ種別 | G1: データ区分 | H1: 経理日 | I1: 取引日 | J1: 連携元システム管理コード | K1: 発生元システム管理コード | L1: 添付ファイル数 | M1: 仕訳種別コード | N1: 仕訳種類コード | O1: 仕訳番号 | P1: 連動元仕訳番号 | Q1: 事業所コード | R1: 業種コード | S1: 予算組織コード | T1: 仕訳摘要 | U1: 出金時計上区分 | V1: 発生元システム取引番号 | W1: 仕訳作成日時 | X1: 仕訳作成担当者 | Y1: 仕訳作成担当者所属コード | Z1: 仕訳更新日時 | AA1: 仕訳更新担当者 | AB1: 仕訳更新担当者所属コード | AC1: 承認依頼日時 | AD1: 承認依頼者 | AE1: 承認依頼者所属コード | AF1: 承認差戻日時 | AG1: 承認差戻担当者 | AH1: 承認差戻担当者所属コード | AI1: 決済日時 | AJ1: 決裁者コード | AK1: 決裁所属コード | AL1: 取消訂正理由コード | AM1: 取消理由 | AN1: 元取引日 | AO1: 訂正元発生元システム取引番号 | AP1: 元伝エラー区分 | AQ1: りん議書URL | AR1: 伝票番号 | AS1: 共計区分 | AT1: 入出荷日 | AU1: 取扱区分 | AV1: PA集約先伝票番号 | AW1: 仕訳番号 | AX1: 仕訳明細番号 | AY1: 連動元仕訳番号 | AZ1: 連動元仕訳明細番号 | BA1: 業種コード | BB1: 予算組織コード | BC1: 管理会計事業所コード | BD1: 購買販売区分 | BE1: 勘定科目コード | BF1: 款科目コード | BG1: 分類口座コード | BH1: 管理項目コード | BI1: 目節科目コード | BJ1: 共計内訳コード | BK1: 消費税発生元勘定科目コード | BL1: 消費税発生元分類口座コード | BM1: 消費税発生元管理項目コード | BN1: 消費税発生元目節科目コード | BO1: 計上金額 | BP1: 借方金額 | BQ1: 借方消費税額 | BR1: 貸方金額 | BS1: 貸方消費税額 | BT1: 科目摘要コード | BU1: 科目摘要細目 | BV1: 消費税基準日 | BW1: 消費税取引区分 | BX1: 消費税率（連動） | BY1: 消費税コード | BZ1: 科目摘要補足 | CA1: 伝票番号 | CB1: 伝票明細番号 | CC1: 免税区分 | CD1: CF勘定科目内訳コード | CE1: 支払入金予定日 | CF1: 支払入金方法 | CG1: 入出金番号 | CH1: PA集約先伝票明細番号 | CI1: 相手先区分 | CJ1: 相手先コード | CK1: 諸口取引先カナ名称 | CL1: 会計情報品目コード | CM1: 出荷元コード | CN1: 添付ファイル名称１ | CO1: 添付ファイルパス１ | CP1: 添付ファイル名称２ | CQ1: 添付ファイルパス２ | CR1: 添付ファイル名称３ | CS1: 添付ファイルパス３ | CT1: 自社口座コード
A2: 0 | B2: 0 | E2: ダミーユーザID | G2: 1 | H2: 20150513 | I2: 20150513 | J2: DA1 | K2: DA2 | L2: 0 | M2: DA3 | N2: A | P2: K15050000009 | Q2: 01 | R2: 20 | S2: 1000 | T2: « NULL » | V2: K15050000009 | W2: 2.0250514e+16 | X2: 0002 | Z2: 2.0250514e+16 | AA2: 0002 | AC2: 2.0250514e+16 | AD2: jidou | AF2: 2.0250514e+16 | AG2: jidou | AI2: 2.0250514e+16 | AJ2: jidou | AV2: K15050000009 | AY2: K15050000009 | AZ2: 1 | BA2: 20 | BB2: 1000 | BE2: 110701 | BI2: 00 | BO2: 18518 | BP2: 18518 | BQ2: 1482 | BT2: « NULL » | BV2: 20150513 | BW2: « NULL » | BX2: 10 | BZ2: « NULL » | CC2: « NULL » | CD2: « NULL » | CI2: « NULL » | CJ2: « NULL » | CL2: 0002 | CT2: « NULL »
A3: 0 | B3: 0 | E3: ダミーユーザID | G3: 1 | H3: 20150513 | I3: 20150513 | J3: DA1 | K3: DA2 | L3: 0 | M3: DA3 | N3: A | P3: K15050000009 | Q3: 01 | R3: 20 | S3: 1000 | T3: « NULL » | V3: K15050000009 | W3: 2.0250514e+16 | X3: 0002 | Z3: 2.0250514e+16 | AA3: 0002 | AC3: 2.0250514e+16 | AD3: jidou | AF3: 2.0250514e+16 | AG3: jidou | AI3: 2.0250514e+16 | AJ3: jidou | AV3: K15050000009 | AY3: K15050000009 | AZ3: 1 | BA3: 20 | BB3: 1000 | BE3: 210401 | BI3: 00 | BO3: 20000 | BR3: 20000 | BS3: 0 | BT3: « NULL » | BV3: 20150513 | BW3: 0 | BX3: 0 | BZ3: « NULL » | CC3: 0 | CD3: « NULL » | CI3: 1 | CJ3: 1101 | CL3: 0002 | CT3: « NULL »
A4: 0 | B4: 0 | E4: ダミーユーザID | G4: 1 | H4: 20150602 | I4: 20150602 | J4: DA1 | K4: DA2 | L4: 0 | M4: DA3 | N4: A | P4: K15060000005 | Q4: 01 | R4: 20 | S4: 2000 | T4: « NULL » | V4: K15060000005 | W4: 2.0250602e+16 | X4: 0002 | Z4: 2.0250602e+16 | AA4: 0002 | AC4: 2.0250602e+16 | AD4: jidou | AF4: 2.0250602e+16 | AG4: jidou | AI4: 2.0250602e+16 | AJ4: jidou | AV4: K15060000005 | AY4: K15060000005 | AZ4: 1 | BA4: 20 | BB4: 2000 | BE4: 110901 | BI4: 10 | BO4: 9259 | BP4: 9259 | BQ4: 741 | BT4: 0 | BV4: 20150602 | BW4: « NULL » | BX4: 10 | BZ4: « NULL » | CC4: « NULL » | CD4: « NULL » | CI4: 1 | CJ4: 1101 | CL4: 0002 | CT4: « NULL »
A5: 0 | B5: 0 | E5: ダミーユーザID | G5: 1 | H5: 20150602 | I5: 20150602 | J5: DA1 | K5: DA2 | L5: 0 | M5: DA3 | N5: A | P5: K15060000005 | Q5: 01 | R5: 20 | S5: 2000 | T5: « NULL » | V5: K15060000005 | W5: 2.0250602e+16 | X5: 0002 | Z5: 2.0250602e+16 | AA5: 0002 | AC5: 2.0250602e+16 | AD5: jidou | AF5: 2.0250602e+16 | AG5: jidou | AI5: 2.0250602e+16 | AJ5: jidou | AV5: K15060000005 | AY5: K15060000005 | AZ5: 1 | BA5: 20 | BB5: 1000 | BE5: 210701 | BI5: 10 | BO5: 10000 | BR5: 10000 | BS5: 0 | BT5: 0 | BV5: 20150602 | BW5: 0 | BX5: 0 | BZ5: « NULL » | CC5: 0 | CD5: « NULL » | CI5: 1 | CJ5: 1101 | CL5: 0002 | CT5: « NULL »
A6: 0 | B6: 0 | E6: ダミーユーザID | G6: 1 | H6: 20150602 | I6: 20150602 | J6: DA1 | K6: DA2 | L6: 0 | M6: DA3 | N6: A | P6: K15060000006 | Q6: 01 | R6: 10 | S6: 1010 | T6: « NULL » | V6: K15060000006 | W6: 2.0250602e+16 | X6: 0002 | Z6: 2.0250602e+16 | AA6: 0002 | AC6: 2.0250602e+16 | AD6: jidou | AF6: 2.0250602e+16 | AG6: jidou | AI6: 2.0250602e+16 | AJ6: jidou | AV6: K15060000006 | AY6: K15060000006 | AZ6: 1 | BA6: 10 | BB6: 1010 | BE6: 110701 | BI6: 00 | BO6: 9259 | BP6: 9259 | BQ6: 741 | BT6: « NULL » | BV6: 20150602 | BW6: « NULL » | BX6: 10 | BZ6: « NULL » | CC6: « NULL » | CD6: « NULL » | CI6: « NULL » | CJ6: « NULL » | CL6: 0001 | CT6: « NULL »
A7: 0 | B7: 0 | E7: ダミーユーザID | G7: 1 | H7: 20150602 | I7: 20150602 | J7: DA1 | K7: DA2 | L7: 0 | M7: DA3 | N7: A | P7: K15060000006 | Q7: 01 | R7: 10 | S7: 1010 | T7: « NULL » | V7: K15060000006 | W7: 2.0250602e+16 | X7: 0002 | Z7: 2.0250602e+16 | AA7: 0002 | AC7: 2.0250602e+16 | AD7: jidou | AF7: 2.0250602e+16 | AG7: jidou | AI7: 2.0250602e+16 | AJ7: jidou | AV7: K15060000006 | AY7: K15060000006 | AZ7: 1 | BA7: 10 | BB7: 2000 | BE7: 210401 | BI7: 00 | BO7: 10000 | BR7: 10000 | BS7: 0 | BT7: « NULL » | BV7: 20150602 | BW7: 0 | BX7: 0 | BZ7: « NULL » | CC7: 0 | CD7: « NULL » | CI7: 1 | CJ7: 1101 | CL7: 1 | CT7: « NULL »
A8: 0 | B8: 0 | E8: ダミーユーザID | G8: 1 | H8: 20150715 | I8: 20150715 | J8: DA1 | K8: DA2 | L8: 0 | M8: DA3 | N8: A | P8: K15070000001 | Q8: 01 | R8: 20 | S8: 1000 | T8: 支払決済 支払決済番号[PK1507000001] | V8: K15070000001 | W8: 2.0250602e+16 | X8: 0002 | Z8: 2.0250602e+16 | AA8: 0002 | AC8: 2.0250602e+16 | AD8: jidou | AF8: 2.0250602e+16 | AG8: jidou | AI8: 2.0250602e+16 | AJ8: jidou | AV8: K15070000001 | AY8: K15070000001 | AZ8: 1 | BA8: 20 | BB8: 1000 | BE8: 210701 | BI8: 10 | BO8: 10000 | BP8: 10000 | BQ8: 0 | BT8: 0 | BV8: 20150715 | BW8: 0 | BX8: 0 | BZ8: 支払決済 支払決済番号[PK1507000001] | CC8: 0 | CD8: « NULL » | CI8: 1 | CJ8: 1101 | CL8: 0002 | CT8: « NULL »
A9: 0 | B9: 0 | E9: ダミーユーザID | G9: 1 | H9: 20150715 | I9: 20150715 | J9: DA1 | K9: DA2 | L9: 0 | M9: DA3 | N9: A | P9: K15070000001 | Q9: 01 | R9: 20 | S9: 1000 | T9: 支払決済 支払決済番号[PK1507000001] | V9: K15070000001 | W9: 2.0250602e+16 | X9: 0002 | Z9: 2.0250602e+16 | AA9: 0002 | AC9: 2.0250602e+16 | AD9: jidou | AF9: 2.0250602e+16 | AG9: jidou | AI9: 2.0250602e+16 | AJ9: jidou | AV9: K15070000001 | AY9: K15070000001 | AZ9: 1 | BA9: 20 | BB9: 2000 | BE9: 11120 | BI9: 20 | BO9: 10000 | BR9: 10000 | BS9: 0 | BT9: « NULL » | BV9: 20150715 | BW9: 0 | BX9: 0 | BZ9: 支払決済 支払決済番号[PK1507000001] | CC9: 0 | CD9: « NULL » | CI9: 1 | CJ9: 1101 | CL9: « NULL » | CT9: JISHA001
A10: 0 | B10: 0 | E10: ダミーユーザID | G10: 1 | H10: 20150715 | I10: 20150715 | J10: DA1 | K10: DA2 | L10: 0 | M10: DA3 | N10: A | P10: K15070000002 | Q10: 02 | R10: 10 | S10: 2000 | T10: 支払決済 支払決済番号[PK1507000002] | V10: K15070000002 | W10: 2.0250602e+16 | X10: 0002 | Z10: 2.0250602e+16 | AA10: 0002 | AC10: 2.0250602e+16 | AD10: jidou | AF10: 2.0250602e+16 | AG10: jidou | AI10: 2.0250602e+16 | AJ10: jidou | AV10: K15070000002 | AY10: K15070000002 | AZ10: 1 | BA10: 10 | BB10: 2000 | BE10: 210401 | BI10: 00 | BO10: 10000 | BP10: 10000 | BQ10: 0 | BT10: « NULL » | BV10: 20150715 | BW10: 0 | BX10: 0 | BZ10: 支払決済 支払決済番号[PK1507000002] | CC10: 0 | CD10: « NULL » | CI10: 1 | CJ10: 1101 | CL10: 0001 | CT10: « NULL »
A11: 0 | B11: 0 | E11: ダミーユーザID | G11: 1 | H11: 20150715 | I11: 20150715 | J11: DA1 | K11: DA2 | L11: 0 | M11: DA3 | N11: A | P11: K15070000002 | Q11: 02 | R11: 10 | S11: 2000 | T11: 支払決済 支払決済番号[PK1507000002] | V11: K15070000002 | W11: 2.0250602e+16 | X11: 0002 | Z11: 2.0250602e+16 | AA11: 0002 | AC11: 2.0250602e+16 | AD11: jidou | AF11: 2.0250602e+16 | AG11: jidou | AI11: 2.0250602e+16 | AJ11: jidou | AV11: K15070000002 | AY11: K15070000002 | AZ11: 1 | BA11: 20 | BB11: 2000 | BE11: 110202 | BI11: 00 | BO11: 10000 | BR11: 10000 | BS11: 0 | BT11: 0 | BV11: 20150715 | BW11: 0 | BX11: 0 | BZ11: 支払決済 支払決済番号[PK1507000002] | CC11: 0 | CD11: « NULL » | CI11: « NULL » | CJ11: « NULL » | CL11: « NULL » | CT11: JISHA001
A12: 0 | B12: 0 | E12: ダミーユーザID | G12: 1 | H12: 20150501 | I12: 20150501 | J12: DA1 | K12: DA2 | L12: 0 | M12: DA3 | N12: A | P12: S15050000002 | Q12: 01 | R12: 20 | S12: 1000 | T12: « NULL » | V12: S15050000002 | W12: 2.0250417e+16 | X12: 0002 | Z12: 2.0250507e+16 | AA12: 0002 | AC12: 2.0250507e+16 | AD12: 0002 | AF12: 2.0250507e+16 | AG12: 0002 | AI12: 2.0250507e+16 | AJ12: 0002 | AV12: S15050000002 | AY12: S15050000002 | AZ12: 1 | BA12: 20 | BB12: 1000 | BE12: 110701 | BI12: 00 | BO12: 1000 | BP12: 1000 | BQ12: 0 | BT12: « NULL » | BV12: 20150501 | BW12: 0 | BX12: 0 | BZ12: « NULL » | CC12: 0 | CD12: « NULL » | CI12: « NULL » | CJ12: « NULL » | CL12: 0001 | CT12: « NULL »
A13: 0 | B13: 0 | E13: ダミーユーザID | G13: 1 | H13: 20150501 | I13: 20150501 | J13: DA1 | K13: DA2 | L13: 0 | M13: DA3 | N13: A | P13: S15050000002 | Q13: 01 | R13: 20 | S13: 1000 | T13: « NULL » | V13: S15050000002 | W13: 2.0250417e+16 | X13: 0002 | Z13: 2.0250507e+16 | AA13: 0002 | AC13: 2.0250507e+16 | AD13: 0002 | AF13: 2.0250507e+16 | AG13: 0002 | AI13: 2.0250507e+16 | AJ13: 0002 | AV13: S15050000002 | AY13: S15050000002 | AZ13: 1 | BA13: 20 | BB13: 1000 | BE13: 210401 | BI13: 00 | BO13: 1000 | BR13: 1000 | BS13: 0 | BT13: « NULL » | BV13: 20150501 | BW13: 0 | BX13: 0 | BZ13: « NULL » | CC13: 0 | CD13: « NULL » | CI13: 1 | CJ13: 1101 | CL13: 0001 | CT13: « NULL »
A14: 0 | B14: 0 | E14: ダミーユーザID | G14: 1 | H14: 20150507 | I14: 20150507 | J14: DA1 | K14: DA2 | L14: 0 | M14: DA3 | N14: A | P14: S15050000003 | Q14: 01 | R14: 20 | S14: 1000 | T14: « NULL » | V14: S15050000003 | W14: 2.0250507e+16 | X14: 0002 | Z14: 2.0250507e+16 | AA14: 0002 | AC14: 2.0250507e+16 | AD14: 0002 | AF14: 2.0250507e+16 | AG14: 0002 | AI14: 2.0250507e+16 | AJ14: 0002 | AV14: S15050000003 | AY14: S15050000003 | AZ14: 1 | BA14: 20 | BB14: 1000 | BE14: 210502 | BI14: 10 | BO14: 5500 | BP14: 5500 | BQ14: 0 | BT14: « NULL » | BV14: 20150507 | BW14: 0 | BX14: 0 | BZ14: « NULL » | CC14: 0 | CD14: « NULL » | CI14: « NULL » | CJ14: « NULL » | CL14: 2 | CT14: « NULL »
A15: 0 | B15: 0 | E15: ダミーユーザID | G15: 1 | H15: 20150507 | I15: 20150507 | J15: DA1 | K15: DA2 | L15: 0 | M15: DA3 | N15: A | P15: S15050000003 | Q15: 01 | R15: 20 | S15: 1000 | T15: « NULL » | V15: S15050000003 | W15: 2.0250507e+16 | X15: 0002 | Z15: 2.0250507e+16 | AA15: 0002 | AC15: 2.0250507e+16 | AD15: 0002 | AF15: 2.0250507e+16 | AG15: 0002 | AI15: 2.0250507e+16 | AJ15: 0002 | AV15: S15050000003 | AY15: S15050000003 | AZ15: 1 | BA15: 20 | BB15: 1000 | BE15: 300104 | BI15: 43 | BO15: 5000 | BR15: 5000 | BS15: 500 | BT15: 0 | BV15: 20150507 | BW15: « NULL » | BX15: 10 | BZ15: « NULL » | CC15: « NULL » | CD15: « NULL » | CI15: « NULL » | CJ15: « NULL » | CL15: 0001 | CT15: « NULL »
A16: 0 | B16: 0 | E16: ダミーユーザID | G16: 1 | H16: 20150507 | I16: 20150507 | J16: DA1 | K16: DA2 | L16: 0 | M16: DA3 | N16: A | P16: S15050000003 | Q16: 01 | R16: 20 | S16: 1000 | T16: « NULL » | V16: S15050000003 | W16: 2.0250507e+16 | X16: 0002 | Z16: 2.0250507e+16 | AA16: 0002 | AC16: 2.0250507e+16 | AD16: 0002 | AF16: 2.0250507e+16 | AG16: 0002 | AI16: 2.0250507e+16 | AJ16: 0002 | AV16: S15050000003 | AY16: S15050000003 | AZ16: 1 | BA16: 20 | BB16: 1000 | BE16: 110902 | BI16: 20 | BO16: 500 | BR16: 500 | BS16: 0 | BT16: « NULL » | BV16: 20150507 | BW16: 0 | BX16: 0 | BZ16: « NULL » | CC16: 0 | CD16: « NULL » | CI16: « NULL » | CJ16: « NULL » | CL16: « NULL » | CT16: « NULL »
A17: 0 | B17: 0 | E17: ダミーユーザID | G17: 1 | H17: 20150507 | I17: 20150507 | J17: DA1 | K17: DA2 | L17: 0 | M17: DA3 | N17: A | P17: S15050000003 | Q17: 01 | R17: 20 | S17: 1000 | T17: « NULL » | V17: S15050000003 | W17: 2.0250507e+16 | X17: 0002 | Z17: 2.0250507e+16 | AA17: 0002 | AC17: 2.0250507e+16 | AD17: 0002 | AF17: 2.0250507e+16 | AG17: 0002 | AI17: 2.0250507e+16 | AJ17: 0002 | AV17: S15050000003 | AY17: S15050000003 | AZ17: 2 | BA17: 20 | BB17: 1000 | BE17: 110602 | BI17: 70 | BO17: 13200 | BP17: 13200 | BQ17: 0 | BT17: « NULL » | BV17: 20150507 | BW17: 0 | BX17: 0 | BZ17: « NULL » | CC17: 0 | CD17: « NULL » | CI17: « NULL » | CJ17: « NULL » | CL17: 1 | CT17: « NULL »
A18: 0 | B18: 0 | E18: ダミーユーザID | G18: 1 | H18: 20150507 | I18: 20150507 | J18: DA1 | K18: DA2 | L18: 0 | M18: DA3 | N18: A | P18: S15050000003 | Q18: 01 | R18: 20 | S18: 1000 | T18: « NULL » | V18: S15050000003 | W18: 2.0250507e+16 | X18: 0002 | Z18: 2.0250507e+16 | AA18: 0002 | AC18: 2.0250507e+16 | AD18: 0002 | AF18: 2.0250507e+16 | AG18: 0002 | AI18: 2.0250507e+16 | AJ18: 0002 | AV18: S15050000003 | AY18: S15050000003 | AZ18: 2 | BA18: 20 | BB18: 1000 | BE18: 300104 | BI18: 4D | BO18: 12000 | BR18: 12000 | BS18: 1200 | BT18: 0 | BV18: 20150507 | BW18: « NULL » | BX18: 10 | BZ18: « NULL » | CC18: « NULL » | CD18: « NULL » | CI18: « NULL » | CJ18: « NULL » | CL18: 0001 | CT18: « NULL »
A19: 0 | B19: 0 | E19: ダミーユーザID | G19: 1 | H19: 20150507 | I19: 20150507 | J19: DA1 | K19: DA2 | L19: 0 | M19: DA3 | N19: A | P19: S15050000003 | Q19: 01 | R19: 20 | S19: 1000 | T19: « NULL » | V19: S15050000003 | W19: 2.0250507e+16 | X19: 0002 | Z19: 2.0250507e+16 | AA19: 0002 | AC19: 2.0250507e+16 | AD19: 0002 | AF19: 2.0250507e+16 | AG19: 0002 | AI19: 2.0250507e+16 | AJ19: 0002 | AV19: S15050000003 | AY19: S15050000003 | AZ19: 2 | BA19: 20 | BB19: 1000 | BE19: 110902 | BI19: 20 | BO19: 1200 | BR19: 1200 | BS19: 0 | BT19: « NULL » | BV19: 20150507 | BW19: 0 | BX19: 0 | BZ19: « NULL » | CC19: 0 | CD19: « NULL » | CI19: « NULL » | CJ19: « NULL » | CL19: « NULL » | CT19: « NULL »
A20: 0 | B20: 0 | E20: ダミーユーザID | G20: 1 | H20: 20150507 | I20: 20150507 | J20: DA1 | K20: DA2 | L20: 0 | M20: DA3 | N20: A | P20: S15050000003 | Q20: 01 | R20: 20 | S20: 1000 | T20: « NULL » | V20: S15050000003 | W20: 2.0250507e+16 | X20: 0002 | Z20: 2.0250507e+16 | AA20: 0002 | AC20: 2.0250507e+16 | AD20: 0002 | AF20: 2.0250507e+16 | AG20: 0002 | AI20: 2.0250507e+16 | AJ20: 0002 | AV20: S15050000003 | AY20: S15050000003 | AZ20: 3 | BA20: 20 | BB20: 1000 | BE20: 300104 | BI20: 4F | BO20: 44000 | BP20: 44000 | BQ20: 4400 | BT20: 0 | BV20: 20150507 | BW20: « NULL » | BX20: 10 | BZ20: « NULL » | CC20: « NULL » | CD20: « NULL » | CI20: « NULL » | CJ20: « NULL » | CL20: 1 | CT20: « NULL »
A21: 0 | B21: 0 | E21: ダミーユーザID | G21: 1 | H21: 20150507 | I21: 20150507 | J21: DA1 | K21: DA2 | L21: 0 | M21: DA3 | N21: A | P21: S15050000003 | Q21: 01 | R21: 20 | S21: 1000 | T21: « NULL » | V21: S15050000003 | W21: 2.0250507e+16 | X21: 0002 | Z21: 2.0250507e+16 | AA21: 0002 | AC21: 2.0250507e+16 | AD21: 0002 | AF21: 2.0250507e+16 | AG21: 0002 | AI21: 2.0250507e+16 | AJ21: 0002 | AV21: S15050000003 | AY21: S15050000003 | AZ21: 3 | BA21: 20 | BB21: 1000 | BE21: 210502 | BI21: 80 | BO21: 48400 | BR21: 48400 | BS21: 0 | BT21: « NULL » | BV21: 20150507 | BW21: 0 | BX21: 0 | BZ21: « NULL » | CC21: 0 | CD21: « NULL » | CI21: « NULL » | CJ21: « NULL » | CL21: 0001 | CT21: « NULL »
A22: 0 | B22: 0 | E22: ダミーユーザID | G22: 1 | H22: 20150507 | I22: 20150507 | J22: DA1 | K22: DA2 | L22: 0 | M22: DA3 | N22: A | P22: S15050000003 | Q22: 01 | R22: 20 | S22: 1000 | T22: « NULL » | V22: S15050000003 | W22: 2.0250507e+16 | X22: 0002 | Z22: 2.0250507e+16 | AA22: 0002 | AC22: 2.0250507e+16 | AD22: 0002 | AF22: 2.0250507e+16 | AG22: 0002 | AI22: 2.0250507e+16 | AJ22: 0002 | AV22: S15050000003 | AY22: S15050000003 | AZ22: 3 | BA22: 20 | BB22: 1000 | BE22: 110902 | BI22: 20 | BO22: 4400 | BP22: 4400 | BQ22: 0 | BT22: « NULL » | BV22: 20150507 | BW22: 0 | BX22: 0 | BZ22: « NULL » | CC22: 0 | CD22: « NULL » | CI22: « NULL » | CJ22: « NULL » | CL22: « NULL » | CT22: « NULL »
A23: 0 | B23: 0 | E23: ダミーユーザID | G23: 1 | H23: 20150507 | I23: 20150507 | J23: DA1 | K23: DA2 | L23: 0 | M23: DA3 | N23: A | P23: S15050000004 | Q23: 01 | R23: 20 | S23: 1000 | T23: « NULL » | V23: S15050000004 | W23: 2.0250507e+16 | X23: 0002 | Z23: 2.0250507e+16 | AA23: 0002 | AC23: 2.0250507e+16 | AD23: 0002 | AF23: 2.0250507e+16 | AG23: 0002 | AI23: 2.0250507e+16 | AJ23: 0002 | AV23: S15050000004 | AY23: S15050000004 | AZ23: 1 | BA23: 20 | BB23: 1000 | BE23: 300107 | BI23: 51 | BO23: 57000 | BP23: 57000 | BQ23: 4560 | BT23: 0 | BV23: 20150507 | BW23: « NULL » | BX23: 10 | BZ23: « NULL » | CC23: « NULL » | CD23: « NULL » | CI23: « NULL » | CJ23: « NULL » | CL23: 1 | CT23: « NULL »
A24: 0 | B24: 0 | E24: ダミーユーザID | G24: 1 | H24: 20150507 | I24: 20150507 | J24: DA1 | K24: DA2 | L24: 0 | M24: DA3 | N24: A | P24: S15050000004 | Q24: 01 | R24: 20 | S24: 1000 | T24: « NULL » | V24: S15050000004 | W24: 2.0250507e+16 | X24: 0002 | Z24: 2.0250507e+16 | AA24: 0002 | AC24: 2.0250507e+16 | AD24: 0002 | AF24: 2.0250507e+16 | AG24: 0002 | AI24: 2.0250507e+16 | AJ24: 0002 | AV24: S15050000004 | AY24: S15050000004 | AZ24: 1 | BA24: 20 | BB24: 1000 | BE24: 300108 | BI24: 51 | BO24: 57000 | BR24: 57000 | BS24: 4560 | BT24: 0 | BV24: 20150507 | BW24: « NULL » | BX24: 10 | BZ24: « NULL » | CC24: « NULL » | CD24: « NULL » | CI24: « NULL » | CJ24: « NULL » | CL24: 1 | CT24: « NULL »
A25: 0 | B25: 0 | E25: ダミーユーザID | G25: 1 | H25: 20150507 | I25: 20150507 | J25: DA1 | K25: DA2 | L25: 0 | M25: DA3 | N25: A | P25: S15050000004 | Q25: 01 | R25: 20 | S25: 1000 | T25: « NULL » | V25: S15050000004 | W25: 2.0250507e+16 | X25: 0002 | Z25: 2.0250507e+16 | AA25: 0002 | AC25: 2.0250507e+16 | AD25: 0002 | AF25: 2.0250507e+16 | AG25: 0002 | AI25: 2.0250507e+16 | AJ25: 0002 | AV25: S15050000004 | AY25: S15050000004 | AZ25: 1 | BA25: 20 | BB25: 1000 | BE25: 110902 | BI25: 20 | BO25: 4560 | BP25: 4560 | BQ25: 0 | BT25: « NULL » | BV25: 20150507 | BW25: 0 | BX25: 0 | BZ25: « NULL » | CC25: 0 | CD25: « NULL » | CI25: « NULL » | CJ25: « NULL » | CL25: « NULL » | CT25: « NULL »
A26: 0 | B26: 0 | E26: ダミーユーザID | G26: 1 | H26: 20150507 | I26: 20150507 | J26: DA1 | K26: DA2 | L26: 0 | M26: DA3 | N26: A | P26: S15050000004 | Q26: 01 | R26: 20 | S26: 1000 | T26: « NULL » | V26: S15050000004 | W26: 2.0250507e+16 | X26: 0002 | Z26: 2.0250507e+16 | AA26: 0002 | AC26: 2.0250507e+16 | AD26: 0002 | AF26: 2.0250507e+16 | AG26: 0002 | AI26: 2.0250507e+16 | AJ26: 0002 | AV26: S15050000004 | AY26: S15050000004 | AZ26: 1 | BA26: 20 | BB26: 1000 | BE26: 110902 | BI26: 20 | BO26: 4560 | BR26: 4560 | BS26: 0 | BT26: « NULL » | BV26: 20150507 | BW26: 0 | BX26: 0 | BZ26: « NULL » | CC26: 0 | CD26: « NULL » | CI26: « NULL » | CJ26: « NULL » | CL26: « NULL » | CT26: « NULL »
A27: 0 | B27: 0 | E27: ダミーユーザID | G27: 1 | H27: 20150507 | I27: 20150507 | J27: DA1 | K27: DA2 | L27: 0 | M27: DA3 | N27: A | P27: S15050000004 | Q27: 01 | R27: 20 | S27: 1000 | T27: « NULL » | V27: S15050000004 | W27: 2.0250507e+16 | X27: 0002 | Z27: 2.0250507e+16 | AA27: 0002 | AC27: 2.0250507e+16 | AD27: 0002 | AF27: 2.0250507e+16 | AG27: 0002 | AI27: 2.0250507e+16 | AJ27: 0002 | AV27: S15050000004 | AY27: S15050000004 | AZ27: 2 | BA27: 20 | BB27: 1000 | BE27: 300107 | BI27: 5A | BO27: 10000 | BP27: 10000 | BQ27: 800 | BT27: 0 | BV27: 20150507 | BW27: « NULL » | BX27: 10 | BZ27: « NULL » | CC27: « NULL » | CD27: « NULL » | CI27: « NULL » | CJ27: « NULL » | CL27: 3 | CT27: « NULL »
A28: 0 | B28: 0 | E28: ダミーユーザID | G28: 1 | H28: 20150507 | I28: 20150507 | J28: DA1 | K28: DA2 | L28: 0 | M28: DA3 | N28: A | P28: S15050000004 | Q28: 01 | R28: 20 | S28: 1000 | T28: « NULL » | V28: S15050000004 | W28: 2.0250507e+16 | X28: 0002 | Z28: 2.0250507e+16 | AA28: 0002 | AC28: 2.0250507e+16 | AD28: 0002 | AF28: 2.0250507e+16 | AG28: 0002 | AI28: 2.0250507e+16 | AJ28: 0002 | AV28: S15050000004 | AY28: S15050000004 | AZ28: 2 | BA28: 20 | BB28: 1000 | BE28: 300108 | BI28: 5E | BO28: 10000 | BR28: 10000 | BS28: 800 | BT28: 0 | BV28: 20150507 | BW28: « NULL » | BX28: 10 | BZ28: « NULL » | CC28: « NULL » | CD28: « NULL » | CI28: « NULL » | CJ28: « NULL » | CL28: 3 | CT28: « NULL »
A29: 0 | B29: 0 | E29: ダミーユーザID | G29: 1 | H29: 20150507 | I29: 20150507 | J29: DA1 | K29: DA2 | L29: 0 | M29: DA3 | N29: A | P29: S15050000004 | Q29: 01 | R29: 20 | S29: 1000 | T29: « NULL » | V29: S15050000004 | W29: 2.0250507e+16 | X29: 0002 | Z29: 2.0250507e+16 | AA29: 0002 | AC29: 2.0250507e+16 | AD29: 0002 | AF29: 2.0250507e+16 | AG29: 0002 | AI29: 2.0250507e+16 | AJ29: 0002 | AV29: S15050000004 | AY29: S15050000004 | AZ29: 2 | BA29: 20 | BB29: 1000 | BE29: 110902 | BI29: 20 | BO29: 800 | BP29: 800 | BQ29: 0 | BT29: « NULL » | BV29: 20150507 | BW29: 0 | BX29: 0 | BZ29: « NULL » | CC29: 0 | CD29: « NULL » | CI29: « NULL » | CJ29: « NULL » | CL29: « NULL » | CT29: « NULL »
A30: 0 | B30: 0 | E30: ダミーユーザID | G30: 1 | H30: 20150507 | I30: 20150507 | J30: DA1 | K30: DA2 | L30: 0 | M30: DA3 | N30: A | P30: S15050000004 | Q30: 01 | R30: 20 | S30: 1000 | T30: « NULL » | V30: S15050000004 | W30: 2.0250507e+16 | X30: 0002 | Z30: 2.0250507e+16 | AA30: 0002 | AC30: 2.0250507e+16 | AD30: 0002 | AF30: 2.0250507e+16 | AG30: 0002 | AI30: 2.0250507e+16 | AJ30: 0002 | AV30: S15050000004 | AY30: S15050000004 | AZ30: 2 | BA30: 20 | BB30: 1000 | BE30: 110902 | BI30: 20 | BO30: 800 | BR30: 800 | BS30: 0 | BT30: « NULL » | BV30: 20150507 | BW30: 0 | BX30: 0 | BZ30: « NULL » | CC30: 0 | CD30: « NULL » | CI30: « NULL » | CJ30: « NULL » | CL30: « NULL » | CT30: « NULL »
A31: 0 | B31: 0 | E31: ダミーユーザID | G31: 1 | H31: 20150507 | I31: 20150507 | J31: DA1 | K31: DA2 | L31: 0 | M31: DA3 | N31: A | P31: S15050000004 | Q31: 01 | R31: 20 | S31: 1000 | T31: « NULL » | V31: S15050000004 | W31: 2.0250507e+16 | X31: 0002 | Z31: 2.0250507e+16 | AA31: 0002 | AC31: 2.0250507e+16 | AD31: 0002 | AF31: 2.0250507e+16 | AG31: 0002 | AI31: 2.0250507e+16 | AJ31: 0002 | AV31: S15050000004 | AY31: S15050000004 | AZ31: 3 | BA31: 20 | BB31: 1000 | BE31: 300108 | BI31: 57 | BO31: 23000 | BP31: 23000 | BQ31: 1840 | BT31: 0 | BV31: 20150507 | BW31: « NULL » | BX31: 10 | BZ31: « NULL » | CC31: « NULL » | CD31: « NULL » | CI31: « NULL » | CJ31: « NULL » | CL31: 1 | CT31: « NULL »
A32: 0 | B32: 0 | E32: ダミーユーザID | G32: 1 | H32: 20150507 | I32: 20150507 | J32: DA1 | K32: DA2 | L32: 0 | M32: DA3 | N32: A | P32: S15050000004 | Q32: 01 | R32: 20 | S32: 1000 | T32: « NULL » | V32: S15050000004 | W32: 2.0250507e+16 | X32: 0002 | Z32: 2.0250507e+16 | AA32: 0002 | AC32: 2.0250507e+16 | AD32: 0002 | AF32: 2.0250507e+16 | AG32: 0002 | AI32: 2.0250507e+16 | AJ32: 0002 | AV32: S15050000004 | AY32: S15050000004 | AZ32: 3 | BA32: 20 | BB32: 1000 | BE32: 300107 | BI32: 5L | BO32: 23000 | BR32: 23000 | BS32: 1840 | BT32: 0 | BV32: 20150507 | BW32: « NULL » | BX32: 10 | BZ32: « NULL » | CC32: « NULL » | CD32: « NULL » | CI32: « NULL » | CJ32: « NULL » | CL32: 1 | CT32: « NULL »
A33: 0 | B33: 0 | E33: ダミーユーザID | G33: 1 | H33: 20150507 | I33: 20150507 | J33: DA1 | K33: DA2 | L33: 0 | M33: DA3 | N33: A | P33: S15050000004 | Q33: 01 | R33: 20 | S33: 1000 | T33: « NULL » | V33: S15050000004 | W33: 2.0250507e+16 | X33: 0002 | Z33: 2.0250507e+16 | AA33: 0002 | AC33: 2.0250507e+16 | AD33: 0002 | AF33: 2.0250507e+16 | AG33: 0002 | AI33: 2.0250507e+16 | AJ33: 0002 | AV33: S15050000004 | AY33: S15050000004 | AZ33: 3 | BA33: 20 | BB33: 1000 | BE33: 110902 | BI33: 20 | BO33: 1840 | BP33: 1840 | BQ33: 0 | BT33: « NULL » | BV33: 20150507 | BW33: 0 | BX33: 0 | BZ33: « NULL » | CC33: 0 | CD33: « NULL » | CI33: « NULL » | CJ33: « NULL » | CL33: « NULL » | CT33: « NULL »
A34: 0 | B34: 0 | E34: ダミーユーザID | G34: 1 | H34: 20150507 | I34: 20150507 | J34: DA1 | K34: DA2 | L34: 0 | M34: DA3 | N34: A | P34: S15050000004 | Q34: 01 | R34: 20 | S34: 1000 | T34: « NULL » | V34: S15050000004 | W34: 2.0250507e+16 | X34: 0002 | Z34: 2.0250507e+16 | AA34: 0002 | AC34: 2.0250507e+16 | AD34: 0002 | AF34: 2.0250507e+16 | AG34: 0002 | AI34: 2.0250507e+16 | AJ34: 0002 | AV34: S15050000004 | AY34: S15050000004 | AZ34: 3 | BA34: 20 | BB34: 1000 | BE34: 110902 | BI34: 20 | BO34: 1840 | BR34: 1840 | BS34: 0 | BT34: « NULL » | BV34: 20150507 | BW34: 0 | BX34: 0 | BZ34: « NULL » | CC34: 0 | CD34: « NULL » | CI34: « NULL » | CJ34: « NULL » | CL34: « NULL » | CT34: « NULL »
A35: 0 | B35: 0 | E35: ダミーユーザID | G35: 1 | H35: 20150507 | I35: 20150507 | J35: DA1 | K35: DA2 | L35: 0 | M35: DA3 | N35: A | P35: S15050000005 | Q35: 01 | R35: 20 | S35: 1000 | T35: « NULL » | V35: S15050000005 | W35: 2.0250507e+16 | X35: 0002 | Z35: 2.0250507e+16 | AA35: 0002 | AC35: 2.0250507e+16 | AD35: 0002 | AF35: 2.0250507e+16 | AG35: 0002 | AI35: 2.0250507e+16 | AJ35: 0002 | AV35: S15050000005 | AY35: S15050000005 | AZ35: 1 | BA35: 20 | BB35: 1000 | BE35: 210502 | BI35: 10 | BO35: -5500 | BP35: -5500 | BQ35: 0 | BT35: « NULL » | BV35: 20150507 | BW35: 0 | BX35: 0 | BZ35: « NULL » | CC35: 0 | CD35: « NULL » | CI35: « NULL » | CJ35: « NULL » | CL35: 2 | CT35: « NULL »
A36: 0 | B36: 0 | E36: ダミーユーザID | G36: 1 | H36: 20150507 | I36: 20150507 | J36: DA1 | K36: DA2 | L36: 0 | M36: DA3 | N36: A | P36: S15050000005 | Q36: 01 | R36: 20 | S36: 1000 | T36: « NULL » | V36: S15050000005 | W36: 2.0250507e+16 | X36: 0002 | Z36: 2.0250507e+16 | AA36: 0002 | AC36: 2.0250507e+16 | AD36: 0002 | AF36: 2.0250507e+16 | AG36: 0002 | AI36: 2.0250507e+16 | AJ36: 0002 | AV36: S15050000005 | AY36: S15050000005 | AZ36: 1 | BA36: 20 | BB36: 1000 | BE36: 300104 | BI36: 43 | BO36: -5000 | BR36: -5000 | BS36: -500 | BT36: 0 | BV36: 20150507 | BW36: « NULL » | BX36: 10 | BZ36: « NULL » | CC36: « NULL » | CD36: « NULL » | CI36: « NULL » | CJ36: « NULL » | CL36: 0001 | CT36: « NULL »
A37: 0 | B37: 0 | E37: ダミーユーザID | G37: 1 | H37: 20150507 | I37: 20150507 | J37: DA1 | K37: DA2 | L37: 0 | M37: DA3 | N37: A | P37: S15050000005 | Q37: 01 | R37: 20 | S37: 1000 | T37: « NULL » | V37: S15050000005 | W37: 2.0250507e+16 | X37: 0002 | Z37: 2.0250507e+16 | AA37: 0002 | AC37: 2.0250507e+16 | AD37: 0002 | AF37: 2.0250507e+16 | AG37: 0002 | AI37: 2.0250507e+16 | AJ37: 0002 | AV37: S15050000005 | AY37: S15050000005 | AZ37: 1 | BA37: 20 | BB37: 1000 | BE37: 110902 | BI37: 20 | BO37: -500 | BR37: -500 | BS37: 0 | BT37: « NULL » | BV37: 20150507 | BW37: 0 | BX37: 0 | BZ37: « NULL » | CC37: 0 | CD37: « NULL » | CI37: « NULL » | CJ37: « NULL » | CL37: « NULL » | CT37: « NULL »
A38: 0 | B38: 0 | E38: ダミーユーザID | G38: 1 | H38: 20150507 | I38: 20150507 | J38: DA1 | K38: DA2 | L38: 0 | M38: DA3 | N38: A | P38: S15050000005 | Q38: 01 | R38: 20 | S38: 1000 | T38: « NULL » | V38: S15050000005 | W38: 2.0250507e+16 | X38: 0002 | Z38: 2.0250507e+16 | AA38: 0002 | AC38: 2.0250507e+16 | AD38: 0002 | AF38: 2.0250507e+16 | AG38: 0002 | AI38: 2.0250507e+16 | AJ38: 0002 | AV38: S15050000005 | AY38: S15050000005 | AZ38: 2 | BA38: 20 | BB38: 1000 | BE38: 110602 | BI38: 70 | BO38: -13200 | BP38: -13200 | BQ38: 0 | BT38: « NULL » | BV38: 20150507 | BW38: 0 | BX38: 0 | BZ38: « NULL » | CC38: 0 | CD38: « NULL » | CI38: « NULL » | CJ38: « NULL » | CL38: 1 | CT38: « NULL »
A39: 0 | B39: 0 | E39: ダミーユーザID | G39: 1 | H39: 20150507 | I39: 20150507 | J39: DA1 | K39: DA2 | L39: 0 | M39: DA3 | N39: A | P39: S15050000005 | Q39: 01 | R39: 20 | S39: 1000 | T39: « NULL » | V39: S15050000005 | W39: 2.0250507e+16 | X39: 0002 | Z39: 2.0250507e+16 | AA39: 0002 | AC39: 2.0250507e+16 | AD39: 0002 | AF39: 2.0250507e+16 | AG39: 0002 | AI39: 2.0250507e+16 | AJ39: 0002 | AV39: S15050000005 | AY39: S15050000005 | AZ39: 2 | BA39: 20 | BB39: 1000 | BE39: 300104 | BI39: 4D | BO39: -12000 | BR39: -12000 | BS39: -1200 | BT39: 0 | BV39: 20150507 | BW39: « NULL » | BX39: 10 | BZ39: « NULL » | CC39: « NULL » | CD39: « NULL » | CI39: « NULL » | CJ39: « NULL » | CL39: 0001 | CT39: « NULL »
A40: 0 | B40: 0 | E40: ダミーユーザID | G40: 1 | H40: 20150507 | I40: 20150507 | J40: DA1 | K40: DA2 | L40: 0 | M40: DA3 | N40: A | P40: S15050000005 | Q40: 01 | R40: 20 | S40: 1000 | T40: « NULL » | V40: S15050000005 | W40: 2.0250507e+16 | X40: 0002 | Z40: 2.0250507e+16 | AA40: 0002 | AC40: 2.0250507e+16 | AD40: 0002 | AF40: 2.0250507e+16 | AG40: 0002 | AI40: 2.0250507e+16 | AJ40: 0002 | AV40: S15050000005 | AY40: S15050000005 | AZ40: 2 | BA40: 20 | BB40: 1000 | BE40: 110902 | BI40: 20 | BO40: -1200 | BR40: -1200 | BS40: 0 | BT40: « NULL » | BV40: 20150507 | BW40: 0 | BX40: 0 | BZ40: « NULL » | CC40: 0 | CD40: « NULL » | CI40: « NULL » | CJ40: « NULL » | CL40: « NULL » | CT40: « NULL »
A41: 0 | B41: 0 | E41: ダミーユーザID | G41: 1 | H41: 20150507 | I41: 20150507 | J41: DA1 | K41: DA2 | L41: 0 | M41: DA3 | N41: A | P41: S15050000005 | Q41: 01 | R41: 20 | S41: 1000 | T41: « NULL » | V41: S15050000005 | W41: 2.0250507e+16 | X41: 0002 | Z41: 2.0250507e+16 | AA41: 0002 | AC41: 2.0250507e+16 | AD41: 0002 | AF41: 2.0250507e+16 | AG41: 0002 | AI41: 2.0250507e+16 | AJ41: 0002 | AV41: S15050000005 | AY41: S15050000005 | AZ41: 3 | BA41: 20 | BB41: 1000 | BE41: 300104 | BI41: 4F | BO41: -44000 | BP41: -44000 | BQ41: -4400 | BT41: 0 | BV41: 20150507 | BW41: « NULL » | BX41: 10 | BZ41: « NULL » | CC41: « NULL » | CD41: « NULL » | CI41: « NULL » | CJ41: « NULL » | CL41: 1 | CT41: « NULL »
A42: 0 | B42: 0 | E42: ダミーユーザID | G42: 1 | H42: 20150507 | I42: 20150507 | J42: DA1 | K42: DA2 | L42: 0 | M42: DA3 | N42: A | P42: S15050000005 | Q42: 01 | R42: 20 | S42: 1000 | T42: « NULL » | V42: S15050000005 | W42: 2.0250507e+16 | X42: 0002 | Z42: 2.0250507e+16 | AA42: 0002 | AC42: 2.0250507e+16 | AD42: 0002 | AF42: 2.0250507e+16 | AG42: 0002 | AI42: 2.0250507e+16 | AJ42: 0002 | AV42: S15050000005 | AY42: S15050000005 | AZ42: 3 | BA42: 20 | BB42: 1000 | BE42: 210502 | BI42: 80 | BO42: -48400 | BR42: -48400 | BS42: 0 | BT42: « NULL » | BV42: 20150507 | BW42: 0 | BX42: 0 | BZ42: « NULL » | CC42: 0 | CD42: « NULL » | CI42: « NULL » | CJ42: « NULL » | CL42: 0001 | CT42: « NULL »
A43: 0 | B43: 0 | E43: ダミーユーザID | G43: 1 | H43: 20150507 | I43: 20150507 | J43: DA1 | K43: DA2 | L43: 0 | M43: DA3 | N43: A | P43: S15050000005 | Q43: 01 | R43: 20 | S43: 1000 | T43: « NULL » | V43: S15050000005 | W43: 2.0250507e+16 | X43: 0002 | Z43: 2.0250507e+16 | AA43: 0002 | AC43: 2.0250507e+16 | AD43: 0002 | AF43: 2.0250507e+16 | AG43: 0002 | AI43: 2.0250507e+16 | AJ43: 0002 | AV43: S15050000005 | AY43: S15050000005 | AZ43: 3 | BA43: 20 | BB43: 1000 | BE43: 110902 | BI43: 20 | BO43: -4400 | BP43: -4400 | BQ43: 0 | BT43: « NULL » | BV43: 20150507 | BW43: 0 | BX43: 0 | BZ43: « NULL » | CC43: 0 | CD43: « NULL » | CI43: « NULL » | CJ43: « NULL » | CL43: « NULL » | CT43: « NULL »
A44: 0 | B44: 0 | E44: ダミーユーザID | G44: 1 | H44: 20150507 | I44: 20150507 | J44: DA1 | K44: DA2 | L44: 0 | M44: DA3 | N44: A | P44: S15050000006 | Q44: 01 | R44: 20 | S44: 1000 | T44: « NULL » | V44: S15050000006 | W44: 2.0250507e+16 | X44: 0002 | Z44: 2.0250507e+16 | AA44: 0002 | AC44: 2.0250507e+16 | AD44: 0002 | AF44: 2.0250507e+16 | AG44: 0002 | AI44: 2.0250507e+16 | AJ44: 0002 | AV44: S15050000006 | AY44: S15050000006 | AZ44: 1 | BA44: 20 | BB44: 1000 | BE44: 210502 | BI44: 10 | BO44: 5500 | BP44: 5500 | BQ44: 0 | BT44: « NULL » | BV44: 20150507 | BW44: 0 | BX44: 0 | BZ44: « NULL » | CC44: 0 | CD44: « NULL » | CI44: « NULL » | CJ44: « NULL » | CL44: 2 | CT44: « NULL »
A45: 0 | B45: 0 | E45: ダミーユーザID | G45: 1 | H45: 20150507 | I45: 20150507 | J45: DA1 | K45: DA2 | L45: 0 | M45: DA3 | N45: A | P45: S15050000006 | Q45: 01 | R45: 20 | S45: 1000 | T45: « NULL » | V45: S15050000006 | W45: 2.0250507e+16 | X45: 0002 | Z45: 2.0250507e+16 | AA45: 0002 | AC45: 2.0250507e+16 | AD45: 0002 | AF45: 2.0250507e+16 | AG45: 0002 | AI45: 2.0250507e+16 | AJ45: 0002 | AV45: S15050000006 | AY45: S15050000006 | AZ45: 1 | BA45: 20 | BB45: 1000 | BE45: 300104 | BI45: 43 | BO45: 5000 | BR45: 5000 | BS45: 500 | BT45: 0 | BV45: 20150507 | BW45: « NULL » | BX45: 10 | BZ45: « NULL » | CC45: « NULL » | CD45: « NULL » | CI45: « NULL » | CJ45: « NULL » | CL45: 0001 | CT45: « NULL »
A46: 0 | B46: 0 | E46: ダミーユーザID | G46: 1 | H46: 20150507 | I46: 20150507 | J46: DA1 | K46: DA2 | L46: 0 | M46: DA3 | N46: A | P46: S15050000006 | Q46: 01 | R46: 20 | S46: 1000 | T46: « NULL » | V46: S15050000006 | W46: 2.0250507e+16 | X46: 0002 | Z46: 2.0250507e+16 | AA46: 0002 | AC46: 2.0250507e+16 | AD46: 0002 | AF46: 2.0250507e+16 | AG46: 0002 | AI46: 2.0250507e+16 | AJ46: 0002 | AV46: S15050000006 | AY46: S15050000006 | AZ46: 1 | BA46: 20 | BB46: 1000 | BE46: 110902 | BI46: 20 | BO46: 500 | BR46: 500 | BS46: 0 | BT46: « NULL » | BV46: 20150507 | BW46: 0 | BX46: 0 | BZ46: « NULL » | CC46: 0 | CD46: « NULL » | CI46: « NULL » | CJ46: « NULL » | CL46: « NULL » | CT46: « NULL »
A47: 0 | B47: 0 | E47: ダミーユーザID | G47: 1 | H47: 20150507 | I47: 20150507 | J47: DA1 | K47: DA2 | L47: 0 | M47: DA3 | N47: A | P47: S15050000006 | Q47: 01 | R47: 20 | S47: 1000 | T47: « NULL » | V47: S15050000006 | W47: 2.0250507e+16 | X47: 0002 | Z47: 2.0250507e+16 | AA47: 0002 | AC47: 2.0250507e+16 | AD47: 0002 | AF47: 2.0250507e+16 | AG47: 0002 | AI47: 2.0250507e+16 | AJ47: 0002 | AV47: S15050000006 | AY47: S15050000006 | AZ47: 2 | BA47: 20 | BB47: 1000 | BE47: 210502 | BI47: 30 | BO47: 13200 | BP47: 13200 | BQ47: 0 | BT47: « NULL » | BV47: 20150507 | BW47: 0 | BX47: 0 | BZ47: « NULL » | CC47: 0 | CD47: « NULL » | CI47: « NULL » | CJ47: « NULL » | CL47: 1 | CT47: « NULL »
A48: 0 | B48: 0 | E48: ダミーユーザID | G48: 1 | H48: 20150507 | I48: 20150507 | J48: DA1 | K48: DA2 | L48: 0 | M48: DA3 | N48: A | P48: S15050000006 | Q48: 01 | R48: 20 | S48: 1000 | T48: « NULL » | V48: S15050000006 | W48: 2.0250507e+16 | X48: 0002 | Z48: 2.0250507e+16 | AA48: 0002 | AC48: 2.0250507e+16 | AD48: 0002 | AF48: 2.0250507e+16 | AG48: 0002 | AI48: 2.0250507e+16 | AJ48: 0002 | AV48: S15050000006 | AY48: S15050000006 | AZ48: 2 | BA48: 20 | BB48: 1000 | BE48: 300104 | BI48: 4D | BO48: 12000 | BR48: 12000 | BS48: 1200 | BT48: 0 | BV48: 20150507 | BW48: « NULL » | BX48: 10 | BZ48: « NULL » | CC48: « NULL » | CD48: « NULL » | CI48: « NULL » | CJ48: « NULL » | CL48: 0001 | CT48: « NULL »
A49: 0 | B49: 0 | E49: ダミーユーザID | G49: 1 | H49: 20150507 | I49: 20150507 | J49: DA1 | K49: DA2 | L49: 0 | M49: DA3 | N49: A | P49: S15050000006 | Q49: 01 | R49: 20 | S49: 1000 | T49: « NULL » | V49: S15050000006 | W49: 2.0250507e+16 | X49: 0002 | Z49: 2.0250507e+16 | AA49: 0002 | AC49: 2.0250507e+16 | AD49: 0002 | AF49: 2.0250507e+16 | AG49: 0002 | AI49: 2.0250507e+16 | AJ49: 0002 | AV49: S15050000006 | AY49: S15050000006 | AZ49: 2 | BA49: 20 | BB49: 1000 | BE49: 110902 | BI49: 20 | BO49: 1200 | BR49: 1200 | BS49: 0 | BT49: « NULL » | BV49: 20150507 | BW49: 0 | BX49: 0 | BZ49: « NULL » | CC49: 0 | CD49: « NULL » | CI49: « NULL » | CJ49: « NULL » | CL49: « NULL » | CT49: « NULL »
A50: 0 | B50: 0 | E50: ダミーユーザID | G50: 1 | H50: 20150507 | I50: 20150507 | J50: DA1 | K50: DA2 | L50: 0 | M50: DA3 | N50: A | P50: S15050000006 | Q50: 01 | R50: 20 | S50: 1000 | T50: « NULL » | V50: S15050000006 | W50: 2.0250507e+16 | X50: 0002 | Z50: 2.0250507e+16 | AA50: 0002 | AC50: 2.0250507e+16 | AD50: 0002 | AF50: 2.0250507e+16 | AG50: 0002 | AI50: 2.0250507e+16 | AJ50: 0002 | AV50: S15050000006 | AY50: S15050000006 | AZ50: 3 | BA50: 20 | BB50: 1000 | BE50: 300104 | BI50: 4F | BO50: 44000 | BP50: 44000 | BQ50: 4400 | BT50: 0 | BV50: 20150507 | BW50: « NULL » | BX50: 10 | BZ50: « NULL » | CC50: « NULL » | CD50: « NULL » | CI50: « NULL » | CJ50: « NULL » | CL50: 1 | CT50: « NULL »
A51: 0 | B51: 0 | E51: ダミーユーザID | G51: 1 | H51: 20150507 | I51: 20150507 | J51: DA1 | K51: DA2 | L51: 0 | M51: DA3 | N51: A | P51: S15050000006 | Q51: 01 | R51: 20 | S51: 1000 | T51: « NULL » | V51: S15050000006 | W51: 2.0250507e+16 | X51: 0002 | Z51: 2.0250507e+16 | AA51: 0002 | AC51: 2.0250507e+16 | AD51: 0002 | AF51: 2.0250507e+16 | AG51: 0002 | AI51: 2.0250507e+16 | AJ51: 0002 | AV51: S15050000006 | AY51: S15050000006 | AZ51: 3 | BA51: 20 | BB51: 1000 | BE51: 210502 | BI51: 80 | BO51: 48400 | BR51: 48400 | BS51: 0 | BT51: « NULL » | BV51: 20150507 | BW51: 0 | BX51: 0 | BZ51: « NULL » | CC51: 0 | CD51: « NULL » | CI51: « NULL » | CJ51: « NULL » | CL51: 0001 | CT51: « NULL »
A52: 0 | B52: 0 | E52: ダミーユーザID | G52: 1 | H52: 20150507 | I52: 20150507 | J52: DA1 | K52: DA2 | L52: 0 | M52: DA3 | N52: A | P52: S15050000006 | Q52: 01 | R52: 20 | S52: 1000 | T52: « NULL » | V52: S15050000006 | W52: 2.0250507e+16 | X52: 0002 | Z52: 2.0250507e+16 | AA52: 0002 | AC52: 2.0250507e+16 | AD52: 0002 | AF52: 2.0250507e+16 | AG52: 0002 | AI52: 2.0250507e+16 | AJ52: 0002 | AV52: S15050000006 | AY52: S15050000006 | AZ52: 3 | BA52: 20 | BB52: 1000 | BE52: 110902 | BI52: 20 | BO52: 4400 | BP52: 4400 | BQ52: 0 | BT52: « NULL » | BV52: 20150507 | BW52: 0 | BX52: 0 | BZ52: « NULL » | CC52: 0 | CD52: « NULL » | CI52: « NULL » | CJ52: « NULL » | CL52: « NULL » | CT52: « NULL »
A53: 0 | B53: 0 | E53: ダミーユーザID | G53: 1 | H53: 20150508 | I53: 20150508 | J53: DA1 | K53: DA2 | L53: 0 | M53: DA3 | N53: A | P53: S15050000007 | Q53: 01 | R53: 20 | S53: 1000 | T53: « NULL » | V53: S15050000007 | W53: 2.0250508e+16 | X53: 0002 | Z53: 2.0250508e+16 | AA53: 0002 | AC53: 2.0250508e+16 | AD53: 0002 | AF53: 2.0250508e+16 | AG53: 0002 | AI53: 2.0250508e+16 | AJ53: 0002 | AV53: S15050000007 | AY53: S15050000007 | AZ53: 1 | BA53: 20 | BB53: 1000 | BE53: 110101 | BI53: 00 | BO53: 108000 | BP53: 108000 | BQ53: 0 | BT53: « NULL » | BV53: 20150508 | BW53: 0 | BX53: 0 | BZ53: « NULL » | CC53: 0 | CD53: « NULL » | CI53: « NULL » | CJ53: « NULL » | CL53: 1 | CT53: « NULL »
A54: 0 | B54: 0 | E54: ダミーユーザID | G54: 1 | H54: 20150508 | I54: 20150508 | J54: DA1 | K54: DA2 | L54: 0 | M54: DA3 | N54: A | P54: S15050000007 | Q54: 01 | R54: 20 | S54: 1000 | T54: « NULL » | V54: S15050000007 | W54: 2.0250508e+16 | X54: 0002 | Z54: 2.0250508e+16 | AA54: 0002 | AC54: 2.0250508e+16 | AD54: 0002 | AF54: 2.0250508e+16 | AG54: 0002 | AI54: 2.0250508e+16 | AJ54: 0002 | AV54: S15050000007 | AY54: S15050000007 | AZ54: 1 | BA54: 20 | BB54: 1000 | BE54: 400103 | BI54: 00 | BO54: 100000 | BR54: 100000 | BS54: 8000 | BT54: « NULL » | BV54: 20150508 | BW54: 12 | BX54: 10 | BZ54: « NULL » | CC54: 0 | CD54: « NULL » | CI54: « NULL » | CJ54: « NULL » | CL54: 0001 | CT54: « NULL »
A55: 0 | B55: 0 | E55: ダミーユーザID | G55: 1 | H55: 20150508 | I55: 20150508 | J55: DA1 | K55: DA2 | L55: 0 | M55: DA3 | N55: A | P55: S15050000007 | Q55: 01 | R55: 20 | S55: 1000 | T55: « NULL » | V55: S15050000007 | W55: 2.0250508e+16 | X55: 0002 | Z55: 2.0250508e+16 | AA55: 0002 | AC55: 2.0250508e+16 | AD55: 0002 | AF55: 2.0250508e+16 | AG55: 0002 | AI55: 2.0250508e+16 | AJ55: 0002 | AV55: S15050000007 | AY55: S15050000007 | AZ55: 1 | BA55: 20 | BB55: 1000 | BE55: 210703 | BI55: 30 | BO55: 8000 | BR55: 8000 | BS55: 0 | BT55: « NULL » | BV55: 20150508 | BW55: 0 | BX55: 0 | BZ55: « NULL » | CC55: 0 | CD55: « NULL » | CI55: « NULL » | CJ55: « NULL » | CL55: « NULL » | CT55: « NULL »
A56: 0 | B56: 0 | E56: ダミーユーザID | G56: 1 | H56: 20150508 | I56: 20150508 | J56: DA1 | K56: DA2 | L56: 0 | M56: DA3 | N56: A | P56: S15050000007 | Q56: 01 | R56: 20 | S56: 1000 | T56: « NULL » | V56: S15050000007 | W56: 2.0250508e+16 | X56: 0002 | Z56: 2.0250508e+16 | AA56: 0002 | AC56: 2.0250508e+16 | AD56: 0002 | AF56: 2.0250508e+16 | AG56: 0002 | AI56: 2.0250508e+16 | AJ56: 0002 | AV56: S15050000007 | AY56: S15050000007 | AZ56: 2 | BA56: 20 | BB56: 1000 | BE56: 110101 | BI56: 00 | BO56: 54000 | BP56: 54000 | BQ56: 0 | BT56: « NULL » | BV56: 20150508 | BW56: 0 | BX56: 0 | BZ56: « NULL » | CC56: 0 | CD56: « NULL » | CI56: « NULL » | CJ56: « NULL » | CL56: 1 | CT56: « NULL »
A57: 0 | B57: 0 | E57: ダミーユーザID | G57: 1 | H57: 20150508 | I57: 20150508 | J57: DA1 | K57: DA2 | L57: 0 | M57: DA3 | N57: A | P57: S15050000007 | Q57: 01 | R57: 20 | S57: 1000 | T57: « NULL » | V57: S15050000007 | W57: 2.0250508e+16 | X57: 0002 | Z57: 2.0250508e+16 | AA57: 0002 | AC57: 2.0250508e+16 | AD57: 0002 | AF57: 2.0250508e+16 | AG57: 0002 | AI57: 2.0250508e+16 | AJ57: 0002 | AV57: S15050000007 | AY57: S15050000007 | AZ57: 2 | BA57: 20 | BB57: 1000 | BE57: 400107 | BI57: 70 | BO57: 50000 | BR57: 50000 | BS57: 4000 | BT57: « NULL » | BV57: 20150508 | BW57: 12 | BX57: 10 | BZ57: « NULL » | CC57: 0 | CD57: « NULL » | CI57: « NULL » | CJ57: « NULL » | CL57: 0001 | CT57: « NULL »
A58: 0 | B58: 0 | E58: ダミーユーザID | G58: 1 | H58: 20150508 | I58: 20150508 | J58: DA1 | K58: DA2 | L58: 0 | M58: DA3 | N58: A | P58: S15050000007 | Q58: 01 | R58: 20 | S58: 1000 | T58: « NULL » | V58: S15050000007 | W58: 2.0250508e+16 | X58: 0002 | Z58: 2.0250508e+16 | AA58: 0002 | AC58: 2.0250508e+16 | AD58: 0002 | AF58: 2.0250508e+16 | AG58: 0002 | AI58: 2.0250508e+16 | AJ58: 0002 | AV58: S15050000007 | AY58: S15050000007 | AZ58: 2 | BA58: 20 | BB58: 1000 | BE58: 210703 | BI58: 30 | BO58: 4000 | BR58: 4000 | BS58: 0 | BT58: « NULL » | BV58: 20150508 | BW58: 0 | BX58: 0 | BZ58: « NULL » | CC58: 0 | CD58: « NULL » | CI58: « NULL » | CJ58: « NULL » | CL58: « NULL » | CT58: « NULL »
A59: 0 | B59: 0 | E59: ダミーユーザID | G59: 1 | H59: 20150508 | I59: 20150508 | J59: DA1 | K59: DA2 | L59: 0 | M59: DA3 | N59: A | P59: S15050000007 | Q59: 01 | R59: 20 | S59: 1000 | T59: « NULL » | V59: S15050000007 | W59: 2.0250508e+16 | X59: 0002 | Z59: 2.0250508e+16 | AA59: 0002 | AC59: 2.0250508e+16 | AD59: 0002 | AF59: 2.0250508e+16 | AG59: 0002 | AI59: 2.0250508e+16 | AJ59: 0002 | AV59: S15050000007 | AY59: S15050000007 | AZ59: 3 | BA59: 20 | BB59: 1000 | BE59: 110201 | BI59: 00 | BO59: 64800 | BP59: 64800 | BQ59: 0 | BT59: 0 | BV59: 20150508 | BW59: 0 | BX59: 0 | BZ59: « NULL » | CC59: 0 | CD59: « NULL » | CI59: « NULL » | CJ59: « NULL » | CL59: 1 | CT59: JISHA000
A60: 0 | B60: 0 | E60: ダミーユーザID | G60: 1 | H60: 20150508 | I60: 20150508 | J60: DA1 | K60: DA2 | L60: 0 | M60: DA3 | N60: A | P60: S15050000007 | Q60: 01 | R60: 20 | S60: 1000 | T60: « NULL » | V60: S15050000007 | W60: 2.0250508e+16 | X60: 0002 | Z60: 2.0250508e+16 | AA60: 0002 | AC60: 2.0250508e+16 | AD60: 0002 | AF60: 2.0250508e+16 | AG60: 0002 | AI60: 2.0250508e+16 | AJ60: 0002 | AV60: S15050000007 | AY60: S15050000007 | AZ60: 3 | BA60: 20 | BB60: 1000 | BE60: 400120 | BI60: 00 | BO60: 60000 | BR60: 60000 | BS60: 4800 | BT60: « NULL » | BV60: 20150508 | BW60: 12 | BX60: 10 | BZ60: « NULL » | CC60: 0 | CD60: « NULL » | CI60: « NULL » | CJ60: « NULL » | CL60: 0001 | CT60: « NULL »
A61: 0 | B61: 0 | E61: ダミーユーザID | G61: 1 | H61: 20150508 | I61: 20150508 | J61: DA1 | K61: DA2 | L61: 0 | M61: DA3 | N61: A | P61: S15050000007 | Q61: 01 | R61: 20 | S61: 1000 | T61: « NULL » | V61: S15050000007 | W61: 2.0250508e+16 | X61: 0002 | Z61: 2.0250508e+16 | AA61: 0002 | AC61: 2.0250508e+16 | AD61: 0002 | AF61: 2.0250508e+16 | AG61: 0002 | AI61: 2.0250508e+16 | AJ61: 0002 | AV61: S15050000007 | AY61: S15050000007 | AZ61: 3 | BA61: 20 | BB61: 1000 | BE61: 210703 | BI61: 30 | BO61: 4800 | BR61: 4800 | BS61: 0 | BT61: « NULL » | BV61: 20150508 | BW61: 0 | BX61: 0 | BZ61: « NULL » | CC61: 0 | CD61: « NULL » | CI61: « NULL » | CJ61: « NULL » | CL61: « NULL » | CT61: « NULL »
A62: 0 | B62: 0 | E62: ダミーユーザID | G62: 1 | H62: 20150617 | I62: 20150617 | J62: DA1 | K62: DA2 | L62: 0 | M62: DA3 | N62: A | P62: S15060000001 | Q62: 01 | R62: 20 | S62: 1000 | T62: テスト_更新日が変わるか | V62: S15060000001 | W62: 2.0250617e+16 | X62: 0002 | Z62: 2.0250617e+16 | AA62: 0002 | AC62: 2.0250617e+16 | AD62: 0002 | AF62: 2.0250617e+16 | AG62: 0002 | AI62: 2.0250617e+16 | AJ62: 0002 | AV62: S15060000001 | AY62: S15060000001 | AZ62: 1 | BA62: 20 | BB62: 1000 | BE62: 110201 | BI62: 00 | BO62: 20000 | BP62: 20000 | BQ62: 0 | BT62: 0 | BV62: 20150617 | BW62: 0 | BX62: 0 | BZ62: « NULL » | CC62: 0 | CD62: « NULL » | CI62: « NULL » | CJ62: « NULL » | CL62: 0001 | CT62: JISHA000
A63: 0 | B63: 0 | E63: ダミーユーザID | G63: 1 | H63: 20150617 | I63: 20150617 | J63: DA1 | K63: DA2 | L63: 0 | M63: DA3 | N63: A | P63: S15060000001 | Q63: 01 | R63: 20 | S63: 1000 | T63: テスト_更新日が変わるか | V63: S15060000001 | W63: 2.0250617e+16 | X63: 0002 | Z63: 2.0250617e+16 | AA63: 0002 | AC63: 2.0250617e+16 | AD63: 0002 | AF63: 2.0250617e+16 | AG63: 0002 | AI63: 2.0250617e+16 | AJ63: 0002 | AV63: S15060000001 | AY63: S15060000001 | AZ63: 1 | BA63: 20 | BB63: 1000 | BE63: 110701 | BI63: 00 | BO63: 20000 | BR63: 20000 | BS63: 0 | BT63: « NULL » | BV63: 20150617 | BW63: 0 | BX63: 0 | BZ63: « NULL » | CC63: 0 | CD63: « NULL » | CI63: « NULL » | CJ63: « NULL » | CL63: 0002 | CT63: « NULL »
A64: 0 | B64: 0 | E64: ダミーユーザID | G64: 1 | H64: 20150617 | I64: 20150617 | J64: DA1 | K64: DA2 | L64: 0 | M64: DA3 | N64: A | P64: S15060000002 | Q64: 01 | R64: 20 | S64: 1000 | T64: テスト_更新日が変わるか | V64: S15060000002 | W64: 2.0250617e+16 | X64: 0002 | Z64: 2.0250617e+16 | AA64: 0002 | AC64: 2.0250617e+16 | AD64: 0002 | AF64: 2.0250617e+16 | AG64: 0002 | AI64: 2.0250617e+16 | AJ64: 0002 | AV64: S15060000002 | AY64: S15060000002 | AZ64: 1 | BA64: 20 | BB64: 1000 | BE64: 110201 | BI64: 00 | BO64: -20000 | BP64: -20000 | BQ64: 0 | BT64: 0 | BV64: 20150617 | BW64: 0 | BX64: 0 | BZ64: « NULL » | CC64: 0 | CD64: « NULL » | CI64: « NULL » | CJ64: « NULL » | CL64: 0001 | CT64: JISHA000
A65: 0 | B65: 0 | E65: ダミーユーザID | G65: 1 | H65: 20150617 | I65: 20150617 | J65: DA1 | K65: DA2 | L65: 0 | M65: DA3 | N65: A | P65: S15060000002 | Q65: 01 | R65: 20 | S65: 1000 | T65: テスト_更新日が変わるか | V65: S15060000002 | W65: 2.0250617e+16 | X65: 0002 | Z65: 2.0250617e+16 | AA65: 0002 | AC65: 2.0250617e+16 | AD65: 0002 | AF65: 2.0250617e+16 | AG65: 0002 | AI65: 2.0250617e+16 | AJ65: 0002 | AV65: S15060000002 | AY65: S15060000002 | AZ65: 1 | BA65: 20 | BB65: 1000 | BE65: 110701 | BI65: 00 | BO65: -20000 | BR65: -20000 | BS65: 0 | BT65: « NULL » | BV65: 20150617 | BW65: 0 | BX65: 0 | BZ65: « NULL » | CC65: 0 | CD65: « NULL » | CI65: « NULL » | CJ65: « NULL » | CL65: 0002 | CT65: « NULL »
A66: 0 | B66: 0 | E66: ダミーユーザID | G66: 1 | H66: 20150617 | I66: 20150617 | J66: DA1 | K66: DA2 | L66: 0 | M66: DA3 | N66: A | P66: S15060000003 | Q66: 01 | R66: 20 | S66: 2000 | T66: テスト_更新日が変わるか | V66: S15060000003 | W66: 2.0250617e+16 | X66: 0002 | Z66: 2.0250617e+16 | AA66: 0002 | AC66: 2.0250617e+16 | AD66: 0002 | AF66: 2.0250617e+16 | AG66: 0002 | AI66: 2.0250617e+16 | AJ66: 0002 | AV66: S15060000003 | AY66: S15060000003 | AZ66: 1 | BA66: 20 | BB66: 2000 | BE66: 110201 | BI66: 00 | BO66: 20000 | BP66: 20000 | BQ66: 0 | BT66: 0 | BV66: 20150617 | BW66: 0 | BX66: 0 | BZ66: « NULL » | CC66: 0 | CD66: « NULL » | CI66: « NULL » | CJ66: « NULL » | CL66: 0001 | CT66: JISHA000
A67: 0 | B67: 0 | E67: ダミーユーザID | G67: 1 | H67: 20150617 | I67: 20150617 | J67: DA1 | K67: DA2 | L67: 0 | M67: DA3 | N67: A | P67: S15060000003 | Q67: 01 | R67: 20 | S67: 2000 | T67: テスト_更新日が変わるか | V67: S15060000003 | W67: 2.0250617e+16 | X67: 0002 | Z67: 2.0250617e+16 | AA67: 0002 | AC67: 2.0250617e+16 | AD67: 0002 | AF67: 2.0250617e+16 | AG67: 0002 | AI67: 2.0250617e+16 | AJ67: 0002 | AV67: S15060000003 | AY67: S15060000003 | AZ67: 1 | BA67: 20 | BB67: 1000 | BE67: 110701 | BI67: 00 | BO67: 20000 | BR67: 20000 | BS67: 0 | BT67: « NULL » | BV67: 20150617 | BW67: 0 | BX67: 0 | BZ67: « NULL » | CC67: 0 | CD67: « NULL » | CI67: « NULL » | CJ67: « NULL » | CL67: 0002 | CT67: « NULL »
A68: 0 | B68: 0 | E68: ダミーユーザID | G68: 1 | H68: 20150617 | I68: 20150617 | J68: DA1 | K68: DA2 | L68: 0 | M68: DA3 | N68: A | P68: S15060000004 | Q68: 01 | R68: 20 | S68: 2000 | T68: テスト_更新日が変わるか | V68: S15060000004 | W68: 2.0250617e+16 | X68: 0002 | Z68: 2.0250617e+16 | AA68: 0002 | AC68: 2.0250617e+16 | AD68: 0002 | AF68: 2.0250617e+16 | AG68: 0002 | AI68: 2.0250617e+16 | AJ68: 0002 | AV68: S15060000004 | AY68: S15060000004 | AZ68: 1 | BA68: 20 | BB68: 2000 | BE68: 110201 | BI68: 00 | BO68: -20000 | BP68: -20000 | BQ68: 0 | BT68: 0 | BV68: 20150617 | BW68: 0 | BX68: 0 | BZ68: « NULL » | CC68: 0 | CD68: « NULL » | CI68: « NULL » | CJ68: « NULL » | CL68: 0001 | CT68: JISHA000
A69: 0 | B69: 0 | E69: ダミーユーザID | G69: 1 | H69: 20150617 | I69: 20150617 | J69: DA1 | K69: DA2 | L69: 0 | M69: DA3 | N69: A | P69: S15060000004 | Q69: 01 | R69: 20 | S69: 2000 | T69: テスト_更新日が変わるか | V69: S15060000004 | W69: 2.0250617e+16 | X69: 0002 | Z69: 2.0250617e+16 | AA69: 0002 | AC69: 2.0250617e+16 | AD69: 0002 | AF69: 2.0250617e+16 | AG69: 0002 | AI69: 2.0250617e+16 | AJ69: 0002 | AV69: S15060000004 | AY69: S15060000004 | AZ69: 1 | BA69: 20 | BB69: 1000 | BE69: 110701 | BI69: 00 | BO69: -20000 | BR69: -20000 | BS69: 0 | BT69: « NULL » | BV69: 20150617 | BW69: 0 | BX69: 0 | BZ69: « NULL » | CC69: 0 | CD69: « NULL » | CI69: « NULL » | CJ69: « NULL » | CL69: 0002 | CT69: « NULL »
A70: 0 | B70: 0 | E70: ダミーユーザID | G70: 1 | H70: 20150617 | I70: 20150617 | J70: DA1 | K70: DA2 | L70: 0 | M70: DA3 | N70: A | P70: S15060000005 | Q70: 01 | R70: 20 | S70: 2000 | T70: テスト_更新日が変わるか | V70: S15060000005 | W70: 2.0250617e+16 | X70: 0002 | Z70: 2.0250617e+16 | AA70: 0002 | AC70: 2.0250617e+16 | AD70: 0002 | AF70: 2.0250617e+16 | AG70: 0002 | AI70: 2.0250617e+16 | AJ70: 0002 | AV70: S15060000005 | AY70: S15060000005 | AZ70: 1 | BA70: 20 | BB70: 2000 | BE70: 110201 | BI70: 00 | BO70: 20000 | BP70: 20000 | BQ70: 0 | BT70: 0 | BV70: 20150617 | BW70: 0 | BX70: 0 | BZ70: « NULL » | CC70: 0 | CD70: « NULL » | CI70: « NULL » | CJ70: « NULL » | CL70: 0001 | CT70: JISHA000
A71: 0 | B71: 0 | E71: ダミーユーザID | G71: 1 | H71: 20150617 | I71: 20150617 | J71: DA1 | K71: DA2 | L71: 0 | M71: DA3 | N71: A | P71: S15060000005 | Q71: 01 | R71: 20 | S71: 2000 | T71: テスト_更新日が変わるか | V71: S15060000005 | W71: 2.0250617e+16 | X71: 0002 | Z71: 2.0250617e+16 | AA71: 0002 | AC71: 2.0250617e+16 | AD71: 0002 | AF71: 2.0250617e+16 | AG71: 0002 | AI71: 2.0250617e+16 | AJ71: 0002 | AV71: S15060000005 | AY71: S15060000005 | AZ71: 1 | BA71: 20 | BB71: 1000 | BE71: 110701 | BI71: 00 | BO71: 20000 | BR71: 20000 | BS71: 0 | BT71: « NULL » | BV71: 20150617 | BW71: 0 | BX71: 0 | BZ71: « NULL » | CC71: 0 | CD71: « NULL » | CI71: « NULL » | CJ71: « NULL » | CL71: 0002 | CT71: « NULL »
A72: 0 | B72: 0 | E72: ダミーユーザID | G72: 1 | H72: 20150617 | I72: 20150617 | J72: DA1 | K72: DA2 | L72: 0 | M72: DA3 | N72: A | P72: S15060000006 | Q72: 01 | R72: 20 | S72: 2000 | T72: テスト_更新日が変わるか | V72: S15060000006 | W72: 2.0250617e+16 | X72: 0002 | Z72: 2.0250617e+16 | AA72: 0002 | AC72: 2.0250617e+16 | AD72: 0002 | AF72: 2.0250617e+16 | AG72: 0002 | AI72: 2.0250617e+16 | AJ72: 0002 | AV72: S15060000006 | AY72: S15060000006 | AZ72: 1 | BA72: 20 | BB72: 2000 | BE72: 110201 | BI72: 00 | BO72: -20000 | BP72: -20000 | BQ72: 0 | BT72: 0 | BV72: 20150617 | BW72: 0 | BX72: 0 | BZ72: « NULL » | CC72: 0 | CD72: « NULL » | CI72: « NULL » | CJ72: « NULL » | CL72: 0001 | CT72: JISHA000
A73: 0 | B73: 0 | E73: ダミーユーザID | G73: 1 | H73: 20150617 | I73: 20150617 | J73: DA1 | K73: DA2 | L73: 0 | M73: DA3 | N73: A | P73: S15060000006 | Q73: 01 | R73: 20 | S73: 2000 | T73: テスト_更新日が変わるか | V73: S15060000006 | W73: 2.0250617e+16 | X73: 0002 | Z73: 2.0250617e+16 | AA73: 0002 | AC73: 2.0250617e+16 | AD73: 0002 | AF73: 2.0250617e+16 | AG73: 0002 | AI73: 2.0250617e+16 | AJ73: 0002 | AV73: S15060000006 | AY73: S15060000006 | AZ73: 1 | BA73: 20 | BB73: 1000 | BE73: 110701 | BI73: 00 | BO73: -20000 | BR73: -20000 | BS73: 0 | BT73: « NULL » | BV73: 20150617 | BW73: 0 | BX73: 0 | BZ73: « NULL » | CC73: 0 | CD73: « NULL » | CI73: « NULL » | CJ73: « NULL » | CL73: 0002 | CT73: « NULL »
A74: 0 | B74: 0 | E74: ダミーユーザID | G74: 1 | H74: 20150618 | I74: 20150618 | J74: DA1 | K74: DA2 | L74: 0 | M74: DA3 | N74: A | P74: S15060000007 | Q74: 01 | R74: 20 | S74: 2000 | T74: テスト_更新日が変わるか | V74: S15060000007 | W74: 2.0250617e+16 | X74: 0002 | Z74: 2.0250617e+16 | AA74: 0002 | AC74: 2.0250617e+16 | AD74: 0002 | AF74: 2.0250617e+16 | AG74: 0002 | AI74: 2.0250617e+16 | AJ74: 0002 | AV74: S15060000007 | AY74: S15060000007 | AZ74: 1 | BA74: 20 | BB74: 2000 | BE74: 110201 | BI74: 00 | BO74: 20000 | BP74: 20000 | BQ74: 0 | BT74: 0 | BV74: 20150618 | BW74: 0 | BX74: 0 | BZ74: « NULL » | CC74: 0 | CD74: « NULL » | CI74: « NULL » | CJ74: « NULL » | CL74: 0001 | CT74: JISHA000
A75: 0 | B75: 0 | E75: ダミーユーザID | G75: 1 | H75: 20150618 | I75: 20150618 | J75: DA1 | K75: DA2 | L75: 0 | M75: DA3 | N75: A | P75: S15060000007 | Q75: 01 | R75: 20 | S75: 2000 | T75: テスト_更新日が変わるか | V75: S15060000007 | W75: 2.0250617e+16 | X75: 0002 | Z75: 2.0250617e+16 | AA75: 0002 | AC75: 2.0250617e+16 | AD75: 0002 | AF75: 2.0250617e+16 | AG75: 0002 | AI75: 2.0250617e+16 | AJ75: 0002 | AV75: S15060000007 | AY75: S15060000007 | AZ75: 1 | BA75: 20 | BB75: 1000 | BE75: 110701 | BI75: 00 | BO75: 20000 | BR75: 20000 | BS75: 0 | BT75: « NULL » | BV75: 20150618 | BW75: 0 | BX75: 0 | BZ75: « NULL » | CC75: 0 | CD75: « NULL » | CI75: « NULL » | CJ75: « NULL » | CL75: 0002 | CT75: « NULL »
A76: 0 | B76: 0 | E76: ダミーユーザID | G76: 1 | H76: 20150618 | I76: 20150618 | J76: DA1 | K76: DA2 | L76: 0 | M76: DA3 | N76: A | P76: S15060000008 | Q76: 01 | R76: 20 | S76: 2000 | T76: テスト_更新日が変わるか | V76: S15060000008 | W76: 2.0250617e+16 | X76: 0002 | Z76: 2.0250617e+16 | AA76: 0002 | AC76: 2.0250617e+16 | AD76: 0002 | AF76: 2.0250617e+16 | AG76: 0002 | AI76: 2.0250617e+16 | AJ76: 0002 | AV76: S15060000008 | AY76: S15060000008 | AZ76: 1 | BA76: 20 | BB76: 2000 | BE76: 110201 | BI76: 00 | BO76: -20000 | BP76: -20000 | BQ76: 0 | BT76: 0 | BV76: 20150618 | BW76: 0 | BX76: 0 | BZ76: « NULL » | CC76: 0 | CD76: « NULL » | CI76: « NULL » | CJ76: « NULL » | CL76: 0001 | CT76: JISHA000
A77: 0 | B77: 0 | E77: ダミーユーザID | G77: 1 | H77: 20150618 | I77: 20150618 | J77: DA1 | K77: DA2 | L77: 0 | M77: DA3 | N77: A | P77: S15060000008 | Q77: 01 | R77: 20 | S77: 2000 | T77: テスト_更新日が変わるか | V77: S15060000008 | W77: 2.0250617e+16 | X77: 0002 | Z77: 2.0250617e+16 | AA77: 0002 | AC77: 2.0250617e+16 | AD77: 0002 | AF77: 2.0250617e+16 | AG77: 0002 | AI77: 2.0250617e+16 | AJ77: 0002 | AV77: S15060000008 | AY77: S15060000008 | AZ77: 1 | BA77: 20 | BB77: 1000 | BE77: 110701 | BI77: 00 | BO77: -20000 | BR77: -20000 | BS77: 0 | BT77: « NULL » | BV77: 20150618 | BW77: 0 | BX77: 0 | BZ77: « NULL » | CC77: 0 | CD77: « NULL » | CI77: « NULL » | CJ77: « NULL » | CL77: 0002 | CT77: « NULL »
A78: 0 | B78: 0 | E78: ダミーユーザID | G78: 1 | H78: 20150618 | I78: 20150618 | J78: DA1 | K78: DA2 | L78: 0 | M78: DA3 | N78: A | P78: S15060000009 | Q78: 01 | R78: 20 | S78: 2000 | T78: テスト_更新日が変わるか | V78: S15060000009 | W78: 2.0250617e+16 | X78: 0002 | Z78: 2.0250617e+16 | AA78: 0002 | AC78: 2.0250617e+16 | AD78: 0002 | AF78: 2.0250617e+16 | AG78: 0002 | AI78: 2.0250617e+16 | AJ78: 0002 | AV78: S15060000009 | AY78: S15060000009 | AZ78: 1 | BA78: 20 | BB78: 2000 | BE78: 110201 | BI78: 00 | BO78: 20000 | BP78: 20000 | BQ78: 0 | BT78: 0 | BV78: 20150618 | BW78: 0 | BX78: 0 | BZ78: « NULL » | CC78: 0 | CD78: « NULL » | CI78: « NULL » | CJ78: « NULL » | CL78: 0001 | CT78: JISHA000
A79: 0 | B79: 0 | E79: ダミーユーザID | G79: 1 | H79: 20150618 | I79: 20150618 | J79: DA1 | K79: DA2 | L79: 0 | M79: DA3 | N79: A | P79: S15060000009 | Q79: 01 | R79: 20 | S79: 2000 | T79: テスト_更新日が変わるか | V79: S15060000009 | W79: 2.0250617e+16 | X79: 0002 | Z79: 2.0250617e+16 | AA79: 0002 | AC79: 2.0250617e+16 | AD79: 0002 | AF79: 2.0250617e+16 | AG79: 0002 | AI79: 2.0250617e+16 | AJ79: 0002 | AV79: S15060000009 | AY79: S15060000009 | AZ79: 1 | BA79: 20 | BB79: 1000 | BE79: 110701 | BI79: 00 | BO79: 20000 | BR79: 20000 | BS79: 0 | BT79: « NULL » | BV79: 20150618 | BW79: 0 | BX79: 0 | BZ79: « NULL » | CC79: 0 | CD79: « NULL » | CI79: « NULL » | CJ79: « NULL » | CL79: 0002 | CT79: « NULL »
A80: 0 | B80: 0 | E80: ダミーユーザID | G80: 1 | H80: 20150618 | I80: 20150618 | J80: DA1 | K80: DA2 | L80: 0 | M80: DA3 | N80: A | P80: S15060000010 | Q80: 01 | R80: 20 | S80: 2000 | T80: テスト_更新日が変わるか | V80: S15060000010 | W80: 2.0250617e+16 | X80: 0002 | Z80: 2.0250617e+16 | AA80: 0002 | AC80: 2.0250617e+16 | AD80: 0002 | AF80: 2.0250617e+16 | AG80: 0002 | AI80: 2.0250617e+16 | AJ80: 0002 | AV80: S15060000010 | AY80: S15060000010 | AZ80: 1 | BA80: 20 | BB80: 2000 | BE80: 110201 | BI80: 00 | BO80: -20000 | BP80: -20000 | BQ80: 0 | BT80: 0 | BV80: 20150618 | BW80: 0 | BX80: 0 | BZ80: « NULL » | CC80: 0 | CD80: « NULL » | CI80: « NULL » | CJ80: « NULL » | CL80: 0001 | CT80: JISHA000
A81: 0 | B81: 0 | E81: ダミーユーザID | G81: 1 | H81: 20150618 | I81: 20150618 | J81: DA1 | K81: DA2 | L81: 0 | M81: DA3 | N81: A | P81: S15060000010 | Q81: 01 | R81: 20 | S81: 2000 | T81: テスト_更新日が変わるか | V81: S15060000010 | W81: 2.0250617e+16 | X81: 0002 | Z81: 2.0250617e+16 | AA81: 0002 | AC81: 2.0250617e+16 | AD81: 0002 | AF81: 2.0250617e+16 | AG81: 0002 | AI81: 2.0250617e+16 | AJ81: 0002 | AV81: S15060000010 | AY81: S15060000010 | AZ81: 1 | BA81: 20 | BB81: 1000 | BE81: 110701 | BI81: 00 | BO81: -20000 | BR81: -20000 | BS81: 0 | BT81: « NULL » | BV81: 20150618 | BW81: 0 | BX81: 0 | BZ81: « NULL » | CC81: 0 | CD81: « NULL » | CI81: « NULL » | CJ81: « NULL » | CL81: 0002 | CT81: « NULL »
A82: 0 | B82: 0 | E82: ダミーユーザID | G82: 1 | H82: 20150618 | I82: 20150618 | J82: DA1 | K82: DA2 | L82: 0 | M82: DA3 | N82: A | P82: S15060000011 | Q82: 01 | R82: 20 | S82: 2000 | T82: テスト_更新日が変わるか | V82: S15060000011 | W82: 2.0250617e+16 | X82: 0002 | Z82: 2.0250617e+16 | AA82: 0002 | AC82: 2.0250617e+16 | AD82: 0002 | AF82: 2.0250617e+16 | AG82: 0002 | AI82: 2.0250617e+16 | AJ82: 0002 | AV82: S15060000011 | AY82: S15060000011 | AZ82: 1 | BA82: 20 | BB82: 2000 | BE82: 110201 | BI82: 00 | BO82: 18519 | BP82: 18519 | BQ82: 1481 | BT82: 0 | BV82: 20150618 | BW82: 12 | BX82: 10 | BZ82: « NULL » | CC82: 0 | CD82: « NULL » | CI82: « NULL » | CJ82: « NULL » | CL82: 1 | CT82: JISHA000
A83: 0 | B83: 0 | E83: ダミーユーザID | G83: 1 | H83: 20150618 | I83: 20150618 | J83: DA1 | K83: DA2 | L83: 0 | M83: DA3 | N83: A | P83: S15060000011 | Q83: 01 | R83: 20 | S83: 2000 | T83: テスト_更新日が変わるか | V83: S15060000011 | W83: 2.0250617e+16 | X83: 0002 | Z83: 2.0250617e+16 | AA83: 0002 | AC83: 2.0250617e+16 | AD83: 0002 | AF83: 2.0250617e+16 | AG83: 0002 | AI83: 2.0250617e+16 | AJ83: 0002 | AV83: S15060000011 | AY83: S15060000011 | AZ83: 1 | BA83: 20 | BB83: 1000 | BE83: 110701 | BI83: 00 | BO83: 20000 | BR83: 20000 | BS83: 0 | BT83: « NULL » | BV83: 20150618 | BW83: 0 | BX83: 0 | BZ83: « NULL » | CC83: 0 | CD83: « NULL » | CI83: « NULL » | CJ83: « NULL » | CL83: 0002 | CT83: « NULL »
A84: 0 | B84: 0 | E84: ダミーユーザID | G84: 1 | H84: 20150618 | I84: 20150618 | J84: DA1 | K84: DA2 | L84: 0 | M84: DA3 | N84: A | P84: S15060000011 | Q84: 01 | R84: 20 | S84: 2000 | T84: テスト_更新日が変わるか | V84: S15060000011 | W84: 2.0250617e+16 | X84: 0002 | Z84: 2.0250617e+16 | AA84: 0002 | AC84: 2.0250617e+16 | AD84: 0002 | AF84: 2.0250617e+16 | AG84: 0002 | AI84: 2.0250617e+16 | AJ84: 0002 | AV84: S15060000011 | AY84: S15060000011 | AZ84: 1 | BA84: 20 | BB84: 2000 | BE84: 210703 | BI84: 30 | BO84: 1481 | BP84: 1481 | BQ84: 0 | BT84: « NULL » | BV84: 20150618 | BW84: 0 | BX84: 0 | BZ84: « NULL » | CC84: 0 | CD84: « NULL » | CI84: « NULL » | CJ84: « NULL » | CL84: « NULL » | CT84: « NULL »
A85: 0 | B85: 0 | E85: ダミーユーザID | G85: 1 | H85: 20150618 | I85: 20150618 | J85: DA1 | K85: DA2 | L85: 0 | M85: DA3 | N85: A | P85: S15060000012 | Q85: 01 | R85: 20 | S85: 2000 | T85: テスト_更新日が変わるか | V85: S15060000012 | W85: 2.0250617e+16 | X85: 0002 | Z85: 2.0250617e+16 | AA85: 0002 | AC85: 2.0250617e+16 | AD85: 0002 | AF85: 2.0250617e+16 | AG85: 0002 | AI85: 2.0250617e+16 | AJ85: 0002 | AV85: S15060000012 | AY85: S15060000012 | AZ85: 1 | BA85: 20 | BB85: 2000 | BE85: 110201 | BI85: 00 | BO85: -18519 | BP85: -18519 | BQ85: -1481 | BT85: 0 | BV85: 20150618 | BW85: 12 | BX85: 10 | BZ85: « NULL » | CC85: 0 | CD85: « NULL » | CI85: « NULL » | CJ85: « NULL » | CL85: 1 | CT85: JISHA000
A86: 0 | B86: 0 | E86: ダミーユーザID | G86: 1 | H86: 20150618 | I86: 20150618 | J86: DA1 | K86: DA2 | L86: 0 | M86: DA3 | N86: A | P86: S15060000012 | Q86: 01 | R86: 20 | S86: 2000 | T86: テスト_更新日が変わるか | V86: S15060000012 | W86: 2.0250617e+16 | X86: 0002 | Z86: 2.0250617e+16 | AA86: 0002 | AC86: 2.0250617e+16 | AD86: 0002 | AF86: 2.0250617e+16 | AG86: 0002 | AI86: 2.0250617e+16 | AJ86: 0002 | AV86: S15060000012 | AY86: S15060000012 | AZ86: 1 | BA86: 20 | BB86: 1000 | BE86: 110701 | BI86: 00 | BO86: -20000 | BR86: -20000 | BS86: 0 | BT86: « NULL » | BV86: 20150618 | BW86: 0 | BX86: 0 | BZ86: « NULL » | CC86: 0 | CD86: « NULL » | CI86: « NULL » | CJ86: « NULL » | CL86: 0002 | CT86: « NULL »
A87: 0 | B87: 0 | E87: ダミーユーザID | G87: 1 | H87: 20150618 | I87: 20150618 | J87: DA1 | K87: DA2 | L87: 0 | M87: DA3 | N87: A | P87: S15060000012 | Q87: 01 | R87: 20 | S87: 2000 | T87: テスト_更新日が変わるか | V87: S15060000012 | W87: 2.0250617e+16 | X87: 0002 | Z87: 2.0250617e+16 | AA87: 0002 | AC87: 2.0250617e+16 | AD87: 0002 | AF87: 2.0250617e+16 | AG87: 0002 | AI87: 2.0250617e+16 | AJ87: 0002 | AV87: S15060000012 | AY87: S15060000012 | AZ87: 1 | BA87: 20 | BB87: 2000 | BE87: 210703 | BI87: 30 | BO87: -1481 | BP87: -1481 | BQ87: 0 | BT87: « NULL » | BV87: 20150618 | BW87: 0 | BX87: 0 | BZ87: « NULL » | CC87: 0 | CD87: « NULL » | CI87: « NULL » | CJ87: « NULL » | CL87: « NULL » | CT87: « NULL »
A88: 0 | B88: 0 | E88: ダミーユーザID | G88: 1 | H88: 20150618 | I88: 20150618 | J88: DA1 | K88: DA2 | L88: 0 | M88: DA3 | N88: A | P88: S15060000013 | Q88: 01 | R88: 20 | S88: 2000 | T88: テスト_更新日が変わるか | V88: S15060000013 | W88: 2.0250617e+16 | X88: 0002 | Z88: 2.0250617e+16 | AA88: 0002 | AC88: 2.0250617e+16 | AD88: 0002 | AF88: 2.0250617e+16 | AG88: 0002 | AI88: 2.0250617e+16 | AJ88: 0002 | AV88: S15060000013 | AY88: S15060000013 | AZ88: 1 | BA88: 20 | BB88: 2000 | BE88: 110201 | BI88: 00 | BO88: 18519 | BP88: 18519 | BQ88: 1481 | BT88: 0 | BV88: 20150618 | BW88: 0 | BX88: 0 | BZ88: « NULL » | CC88: 0 | CD88: « NULL » | CI88: « NULL » | CJ88: « NULL » | CL88: 1 | CT88: JISHA000
A89: 0 | B89: 0 | E89: ダミーユーザID | G89: 1 | H89: 20150618 | I89: 20150618 | J89: DA1 | K89: DA2 | L89: 0 | M89: DA3 | N89: A | P89: S15060000013 | Q89: 01 | R89: 20 | S89: 2000 | T89: テスト_更新日が変わるか | V89: S15060000013 | W89: 2.0250617e+16 | X89: 0002 | Z89: 2.0250617e+16 | AA89: 0002 | AC89: 2.0250617e+16 | AD89: 0002 | AF89: 2.0250617e+16 | AG89: 0002 | AI89: 2.0250617e+16 | AJ89: 0002 | AV89: S15060000013 | AY89: S15060000013 | AZ89: 1 | BA89: 20 | BB89: 1000 | BE89: 110701 | BI89: 00 | BO89: 20000 | BR89: 20000 | BS89: 0 | BT89: « NULL » | BV89: 20150618 | BW89: 0 | BX89: 0 | BZ89: « NULL » | CC89: 0 | CD89: 1 | CI89: « NULL » | CJ89: « NULL » | CL89: 0002 | CT89: « NULL »
A90: 0 | B90: 0 | E90: ダミーユーザID | G90: 1 | H90: 20150618 | I90: 20150618 | J90: DA1 | K90: DA2 | L90: 0 | M90: DA3 | N90: A | P90: S15060000013 | Q90: 01 | R90: 20 | S90: 2000 | T90: テスト_更新日が変わるか | V90: S15060000013 | W90: 2.0250617e+16 | X90: 0002 | Z90: 2.0250617e+16 | AA90: 0002 | AC90: 2.0250617e+16 | AD90: 0002 | AF90: 2.0250617e+16 | AG90: 0002 | AI90: 2.0250617e+16 | AJ90: 0002 | AV90: S15060000013 | AY90: S15060000013 | AZ90: 1 | BA90: 20 | BB90: 2000 | BE90: 210703 | BI90: 30 | BO90: 1481 | BP90: 1481 | BQ90: 0 | BT90: « NULL » | BV90: 20150618 | BW90: 0 | BX90: 0 | BZ90: « NULL » | CC90: 0 | CD90: « NULL » | CI90: « NULL » | CJ90: « NULL » | CL90: « NULL » | CT90: « NULL »
A91: 0 | B91: 0 | E91: ダミーユーザID | G91: 1 | H91: 20150617 | I91: 20150617 | J91: DA1 | K91: DA2 | L91: 0 | M91: DA3 | N91: A | P91: S15060000014 | Q91: 01 | R91: 20 | S91: 1000 | T91: « NULL » | V91: S15060000014 | W91: 2.0250617e+16 | X91: 0002 | Z91: 2.0250617e+16 | AA91: 0002 | AC91: 2.0250617e+16 | AD91: 0002 | AF91: 2.0250617e+16 | AG91: 0002 | AI91: 2.0250617e+16 | AJ91: 0002 | AV91: S15060000014 | AY91: S15060000014 | AZ91: 1 | BA91: 20 | BB91: 1000 | BE91: 110101 | BI91: 00 | BO91: 30000 | BP91: 30000 | BQ91: 0 | BT91: « NULL » | BV91: 20150617 | BW91: 0 | BX91: 0 | BZ91: « NULL » | CC91: 0 | CD91: « NULL » | CI91: « NULL » | CJ91: « NULL » | CL91: 0001 | CT91: « NULL »
A92: 0 | B92: 0 | E92: ダミーユーザID | G92: 1 | H92: 20150617 | I92: 20150617 | J92: DA1 | K92: DA2 | L92: 0 | M92: DA3 | N92: A | P92: S15060000014 | Q92: 01 | R92: 20 | S92: 1000 | T92: « NULL » | V92: S15060000014 | W92: 2.0250617e+16 | X92: 0002 | Z92: 2.0250617e+16 | AA92: 0002 | AC92: 2.0250617e+16 | AD92: 0002 | AF92: 2.0250617e+16 | AG92: 0002 | AI92: 2.0250617e+16 | AJ92: 0002 | AV92: S15060000014 | AY92: S15060000014 | AZ92: 1 | BA92: 20 | BB92: 1000 | BE92: 110501 | BI92: 00 | BO92: 30000 | BR92: 30000 | BS92: 0 | BT92: « NULL » | BV92: 20150617 | BW92: 0 | BX92: 0 | BZ92: « NULL » | CC92: 0 | CD92: « NULL » | CI92: 1 | CJ92: 1101 | CL92: 0003 | CT92: « NULL »
A93: 0 | B93: 0 | E93: ダミーユーザID | G93: 1 | H93: 20150617 | I93: 20150617 | J93: DA1 | K93: DA2 | L93: 0 | M93: DA3 | N93: A | P93: S15060000015 | Q93: 01 | R93: 20 | S93: 1000 | T93: « NULL » | V93: S15060000015 | W93: 2.0250617e+16 | X93: 0002 | Z93: 2.0250617e+16 | AA93: 0002 | AC93: 2.0250617e+16 | AD93: 0002 | AF93: 2.0250617e+16 | AG93: 0002 | AI93: 2.0250617e+16 | AJ93: 0002 | AV93: S15060000015 | AY93: S15060000015 | AZ93: 1 | BA93: 20 | BB93: 1000 | BE93: 110101 | BI93: 00 | BO93: -30000 | BP93: -30000 | BQ93: 0 | BT93: « NULL » | BV93: 20150617 | BW93: 0 | BX93: 0 | BZ93: « NULL » | CC93: 0 | CD93: « NULL » | CI93: « NULL » | CJ93: « NULL » | CL93: 0001 | CT93: « NULL »
A94: 0 | B94: 0 | E94: ダミーユーザID | G94: 1 | H94: 20150617 | I94: 20150617 | J94: DA1 | K94: DA2 | L94: 0 | M94: DA3 | N94: A | P94: S15060000015 | Q94: 01 | R94: 20 | S94: 1000 | T94: « NULL » | V94: S15060000015 | W94: 2.0250617e+16 | X94: 0002 | Z94: 2.0250617e+16 | AA94: 0002 | AC94: 2.0250617e+16 | AD94: 0002 | AF94: 2.0250617e+16 | AG94: 0002 | AI94: 2.0250617e+16 | AJ94: 0002 | AV94: S15060000015 | AY94: S15060000015 | AZ94: 1 | BA94: 20 | BB94: 1000 | BE94: 110501 | BI94: 00 | BO94: -30000 | BR94: -30000 | BS94: 0 | BT94: « NULL » | BV94: 20150617 | BW94: 0 | BX94: 0 | BZ94: « NULL » | CC94: 0 | CD94: « NULL » | CI94: 1 | CJ94: 1101 | CL94: 0003 | CT94: « NULL »
A95: 0 | B95: 0 | E95: ダミーユーザID | G95: 1 | H95: 20150617 | I95: 20150617 | J95: DA1 | K95: DA2 | L95: 0 | M95: DA3 | N95: A | P95: S15060000016 | Q95: 01 | R95: 20 | S95: 1000 | T95: « NULL » | V95: S15060000016 | W95: 2.0250617e+16 | X95: 0002 | Z95: 2.0250617e+16 | AA95: 0002 | AC95: 2.0250617e+16 | AD95: 0002 | AF95: 2.0250617e+16 | AG95: 0002 | AI95: 2.0250617e+16 | AJ95: 0002 | AV95: S15060000016 | AY95: S15060000016 | AZ95: 1 | BA95: 20 | BB95: 1000 | BE95: 110101 | BI95: 00 | BO95: 30000 | BP95: 30000 | BQ95: 0 | BT95: « NULL » | BV95: 20150617 | BW95: 0 | BX95: 0 | BZ95: « NULL » | CC95: 0 | CD95: « NULL » | CI95: « NULL » | CJ95: « NULL » | CL95: 0001 | CT95: « NULL »
A96: 0 | B96: 0 | E96: ダミーユーザID | G96: 1 | H96: 20150617 | I96: 20150617 | J96: DA1 | K96: DA2 | L96: 0 | M96: DA3 | N96: A | P96: S15060000016 | Q96: 01 | R96: 20 | S96: 1000 | T96: « NULL » | V96: S15060000016 | W96: 2.0250617e+16 | X96: 0002 | Z96: 2.0250617e+16 | AA96: 0002 | AC96: 2.0250617e+16 | AD96: 0002 | AF96: 2.0250617e+16 | AG96: 0002 | AI96: 2.0250617e+16 | AJ96: 0002 | AV96: S15060000016 | AY96: S15060000016 | AZ96: 1 | BA96: 20 | BB96: 1000 | BE96: 110501 | BI96: 00 | BO96: 30000 | BR96: 30000 | BS96: 0 | BT96: « NULL » | BV96: 20150617 | BW96: 0 | BX96: 0 | BZ96: « NULL » | CC96: 0 | CD96: « NULL » | CI96: 1 | CJ96: 1101 | CL96: 0003 | CT96: « NULL »
A97: 0 | B97: 0 | E97: ダミーユーザID | G97: 1 | H97: 20150619 | I97: 20150619 | J97: DA1 | K97: DA2 | L97: 0 | M97: DA3 | N97: A | P97: S15060000017 | Q97: 01 | R97: 20 | S97: 1000 | T97: « NULL » | V97: S15060000017 | W97: 2.0250617e+16 | X97: 0002 | Z97: 2.0250617e+16 | AA97: 0002 | AC97: 2.0250617e+16 | AD97: 0002 | AF97: 2.0250617e+16 | AG97: 0002 | AI97: 2.0250617e+16 | AJ97: 0002 | AV97: S15060000017 | AY97: S15060000017 | AZ97: 1 | BA97: 20 | BB97: 1000 | BE97: 110201 | BI97: 00 | BO97: 30000 | BP97: 30000 | BQ97: 0 | BT97: 0 | BV97: 20150619 | BW97: 12 | BX97: 10 | BZ97: « NULL » | CC97: 0 | CD97: « NULL » | CI97: « NULL » | CJ97: « NULL » | CL97: 0002 | CT97: JISHA000
A98: 0 | B98: 0 | E98: ダミーユーザID | G98: 1 | H98: 20150619 | I98: 20150619 | J98: DA1 | K98: DA2 | L98: 0 | M98: DA3 | N98: A | P98: S15060000017 | Q98: 01 | R98: 20 | S98: 1000 | T98: « NULL » | V98: S15060000017 | W98: 2.0250617e+16 | X98: 0002 | Z98: 2.0250617e+16 | AA98: 0002 | AC98: 2.0250617e+16 | AD98: 0002 | AF98: 2.0250617e+16 | AG98: 0002 | AI98: 2.0250617e+16 | AJ98: 0002 | AV98: S15060000017 | AY98: S15060000017 | AZ98: 1 | BA98: 20 | BB98: 1000 | BE98: 110501 | BI98: 00 | BO98: 30000 | BR98: 30000 | BS98: 0 | BT98: « NULL » | BV98: 20150619 | BW98: 0 | BX98: 0 | BZ98: « NULL » | CC98: 0 | CD98: « NULL » | CI98: 1 | CJ98: 1101 | CL98: 0002 | CT98: « NULL »
A99: 0 | B99: 0 | E99: ダミーユーザID | G99: 1 | H99: 20150619 | I99: 20150619 | J99: DA1 | K99: DA2 | L99: 0 | M99: DA3 | N99: A | P99: S15060000018 | Q99: 01 | R99: 20 | S99: 1000 | T99: « NULL » | V99: S15060000018 | W99: 2.0250617e+16 | X99: 0002 | Z99: 2.0250617e+16 | AA99: 0002 | AC99: 2.0250617e+16 | AD99: 0002 | AF99: 2.0250617e+16 | AG99: 0002 | AI99: 2.0250617e+16 | AJ99: 0002 | AV99: S15060000018 | AY99: S15060000018 | AZ99: 1 | BA99: 20 | BB99: 1000 | BE99: 110201 | BI99: 00 | BO99: -30000 | BP99: -30000 | BQ99: 0 | BT99: 0 | BV99: 20150619 | BW99: 12 | BX99: 10 | BZ99: « NULL » | CC99: 0 | CD99: « NULL » | CI99: « NULL » | CJ99: « NULL » | CL99: 0002 | CT99: JISHA000
A100: 0 | B100: 0 | E100: ダミーユーザID | G100: 1 | H100: 20150619 | I100: 20150619 | J100: DA1 | K100: DA2 | L100: 0 | M100: DA3 | N100: A | P100: S15060000018 | Q100: 01 | R100: 20 | S100: 1000 | T100: « NULL » | V100: S15060000018 | W100: 2.0250617e+16 | X100: 0002 | Z100: 2.0250617e+16 | AA100: 0002 | AC100: 2.0250617e+16 | AD100: 0002 | AF100: 2.0250617e+16 | AG100: 0002 | AI100: 2.0250617e+16 | AJ100: 0002 | AV100: S15060000018 | AY100: S15060000018 | AZ100: 1 | BA100: 20 | BB100: 1000 | BE100: 110501 | BI100: 00 | BO100: -30000 | BR100: -30000 | BS100: 0 | BT100: « NULL » | BV100: 20150619 | BW100: 0 | BX100: 0 | BZ100: « NULL » | CC100: 0 | CD100: « NULL » | CI100: 1 | CJ100: 1101 | CL100: 0002 | CT100: « NULL »
...

Sheet ⇒

Sheet データアクセス要領
A1: ドキュメント名 | L1: サブシステム | Q1: 業務機能名 | AJ1: 作成者 | AO1: =表紙!D51 -> SCSK井上 | AT1: 更新者
A2: 業務機能概要書 | G2: データアクセス要領 | L2: =業務機能概要!L2 -> 財務会計 | Q2: =業務機能概要!Q2 -> 仕訳連動 | AJ2: 作成日付 | AO2: =表紙!C51 -> 45898 | AT2: 更新日付
A4: 【編集要領】
B6: ※ | C6: 今回のProActiveC4環境では、AWSのRDSを使用するため、Java（APサーバ）でファイル書き出しを実施する。
C7: （DBサーバ上にファイル出力できないため、DBオブジェクトを使用してファイル出力することはできない。）
B9: １． | C9: 仕訳データ出力処理最終実行開始日時取得
D11: ■抽出エンティティ
D12: № | E12: エンティティ名
D13: 1 | E13: CST変数管理
D15: ■抽出項目
D16: № | E16: 項目名
D17: 1 | E17: CST変数1 AS 仕訳データ出力処理最終実行開始日時
D19: ■抽出条件
D20: № | E20: 取得条件 | AX20: 備考
D21: 1 | E21: 会社コード | Q21: = パラメータ．会社コード | AP21: AND
D22: ２ | E22: CST変数ID | Q22: = 変数名が「仕訳データ出力処理最終実行開始日時」の変数ID
B24: ２． | C24: 出力対象外の元帳領域コード取得
D26: ■抽出エンティティ
D27: № | E27: エンティティ名
D28: 1 | E28: CST変数管理
D30: ■抽出項目
D31: № | E31: 項目名
D32: 1 | E32: CST変数1 AS 出力対象外の元帳領域コードFROM 、 CST変数2 AS 出力対象外の元帳領域コードTO
D34: ■抽出条件
D35: № | E35: 取得条件 | AX35: 備考
D36: 1 | E36: 会社コード | Q36: = パラメータ．会社コード | AP36: AND
D37: ２ | E37: CST変数ID | Q37: = 変数名が「出力対象外の元帳領域コード」の変数ID
E40: ※出力対象外としたい元帳領域の元帳領域コードは連番となるように採番しておく。
B50: ３． | C50: 外部連動用ユーザIDの取得
D52: ■抽出エンティティ
D53: № | E53: エンティティ名
D54: 1 | E54: CST変数管理
D56: ■抽出項目
D57: № | E57: 項目名
D58: 1 | E58: CST変数1 AS 外部連動用ユーザID
D60: ■抽出条件
D61: № | E61: 取得条件 | AX61: 備考
D62: 1 | E62: 会社コード | Q62: = パラメータ．会社コード | AP62: AND
D63: ２ | E63: CST変数ID | Q63: = 変数名が「外部連動用ユーザID」の変数ID
B96: ４． | C96: 仕訳データ取得 （１）と（２）を内部結合する
D97: （１）仕訳ヘッダー情報
D98: ■抽出エンティティ
D99: № | E99: エンティティ名
D100: 1 | E100: 仕訳伝票
D101: 2 | E101: 仕訳伝票明細
D102: 3 | E102: 組織体系
D103: ４ | E103: CST変数管理
D105: ■抽出項目（出力CSV定義とNoを合わせている） | W105: 出力CSV定義のNo.1～51の情報を取得。No.17～19は仕訳明細の1行目の部門コードを取得する。
D106: № | E106: 項目名
D107: 1 | E107: 固定値（0）
D108: 2 | E108: 固定値（0）
D109: 3 | E109: ""（空欄）
D110: 4 | E110: ""（空欄）
D111: 5 | E111: CST変数管理．CST変数１
D112: 6 | E112: ""（空欄）
D113: 7 | E113: 固定値（1）
D114: 8 | E114: 仕訳伝票．仕訳伝票起票日付
D115: 9 | E115: 仕訳伝票．仕訳伝票起票日付
D116: 10 | E116: CST変数管理．CST変数２
D117: 11 | E117: CST変数管理．CST変数３
... D160: 51 | E160: 仕訳伝票．仕訳伝票番号
D188: ■抽出条件
D189: № | E189: 取得条件 | AS189: 備考
D190: 1 | E190: 仕訳伝票．登録日時 | Q190: > １．で取得したCST変数管理．仕訳データ出力処理最終実行開始日時 | AP190: AND | AS190: １．を参照
D191: 2 | E191: 仕訳伝票．登録日時 | Q191: ≦ 仕訳連動バッチ処理開始日時 | AP191: AND
D192: 3 | E192: 仕訳伝票．会社コード | Q192: = パラメータ．会社コード | AP192: AND
D193: 4 | E193: 仕訳伝票．仕訳伝票承認申請状況区分 | Q193: = '1' | AP193: AND | AS193: 承認済みのデータが対象
D194: 5 | E194: 仕訳伝票．仮伝票フラグ | Q194: = '0' | AP194: AND | AS194: 本登録されているデータが対象
D195: 6 | E195: 仕訳伝票．元帳領域コード | Q195: NOT BETWEEN ２．で取得したCST変数管理．出力対象外の元帳領域コードFROM AND | AS195: ２．を参照
V196: ２．で取得したCST変数管理．出力対象外の元帳領域コードTO | AP196: AND
D197: 7 | E197: 仕訳伝票．登録者 | Q197: <> ３．で取得したCST変数管理．外部連動用ユーザID | AS197: ３．を参照
Q198: ※抽出条件について補足シート参照。
D200: ■結合条件（INNER JOIN）
E201: ①仕訳伝票明細テーブル
E202: № | F202: 結合条件 | AX202: 備考
E203: 1 | F203: 仕訳伝票．会社コード | R203: = 仕訳伝票明細．会社コード | AQ203: AND
E204: ２ | F204: 仕訳伝票．仕訳伝票番号 | R204: = 仕訳伝票明細．仕訳伝票番号 | AQ204: AND
E205: ３ | F205: 仕訳伝票明細．仕訳伝票行番号 | R205: = 1
E206: ４ | F206: 仕訳伝票明細．仕訳自動作成フラグ | R206: = 0 | AX206: ※１
E207: ５ | F207: 仕訳伝票明細．仕訳伝票行枝番号 | R207: = 0
E208: ６ | F208: 仕訳伝票明細．貸借区分 | R208: = （ | AX208: ※２
E209: ７ | F209: SELECT 仕訳伝票明細2．MIN(貸借区分) | AX209: ※２
E210: ８ | F210: FROM 仕訳伝票明細 AS 仕訳伝票明細2 | AX210: ※２
E211: ９ | F211: WHERE 仕訳伝票明細2．会社コード | R211: = パラメータ．会社コード | AX211: ※２
E212: 10 | F212: AND 仕訳伝票明細2．仕訳伝票番号 | R212: = 仕訳伝票明細．仕訳伝票番号 | AX212: ※２
E213: 11 | F213: AND 仕訳伝票明細2．仕訳自動作成フラグ | R213: = 0 | AX213: ※２
E214: 12 | F214: AND 仕訳伝票明細2．仕訳伝票行番号 | R214: = 1 | AX214: ※２
E215: 13 | F215: AND 仕訳伝票明細2．仕訳伝票行枝番号 | R215: = 0） | AX215: ※２
E217: ②CST変数管理テーブル
E218: № | F218: 結合条件 | AX218: 備考
E219: 1 | F219: 仕訳伝票．会社コード | R219: = CST変数管理．会社コード | AQ219: AND
E220: ２ | F220: CST変数管理．CST変数ID | R220: = CST変数管理．CST変数名が「連動項目用固定値」の変数ID
D222: ■結合条件（LEFT OUTER JOIN）
E223: ③組織体系テーブル
E224: № | F224: 結合条件 | AX224: 備考
E225: 1 | F225: 仕訳伝票明細．会社コード | R225: = 組織体系．会社コード | AQ225: AND
E226: ２ | F226: 仕訳伝票明細．計上部門内部管理番号 | R226: = 組織体系．部門内部管理番号
E229: ※１ ホクレン様では部門振替は行わない設定とする。念のため部門振替により作成された仕訳は対象外とする。
E230: ※２ 仕訳伝票明細のレコードを一意に特定するために使用。補足シート「仕訳伝票明細のレコードの特定について」を参照
D234: （２）仕訳明細情報
...

Sheet 補足
A1: ドキュメント名 | L1: サブシステム | Q1: 業務機能名 | AM1: 作成者 | AR1: =表紙!D51 -> SCSK井上 | AW1: 更新者
A2: 業務機能概要書 | G2: 補足説明 | L2: =業務機能概要!L2 -> 財務会計 | Q2: =業務機能概要!Q2 -> 仕訳連動 | AM2: 作成日付 | AR2: =表紙!C51 -> 45898 | AW2: 更新日付
C4: １）データアクセス要領シート「２．仕訳データ取得」について
D6: ①仕訳の取得範囲について（いつ作成された仕訳を取得するか）
E8: 仕訳データを重複して取得しないよう、仕訳の作成日時を適切に範囲指定して仕訳データを取得する必要がある。
E10: データ取得までの流れの例
Y11: 変数管理テーブル | AS11: 仕訳テーブル
Y12: バッチ処理最終実行開始日時 | AH12: 2025/2/6 23:05:00:000 | AS12: 仕訳No | AV12: 登録日時
AS13: 001 | AV13: 2025/2/6 23:05:00:000
AS14: 002 | AV14: 2025/2/6 23:06:00:000
AS15: 003 | AV15: 2025/2/7 08:10:00:000
AS16: 004 | AV16: 2025/2/7 09:30:00:000
F17: １．今回の仕訳連動バッチ実行開始日時の取得 | AS17: 005 | AV17: 2025/2/7 23:00:00:000
AS18: 006 | AV18: 2025/2/7 23:01:00:000
H19: 2025/2/7 23:00:00:000 | AS19: 007 | AV19: 2025/2/7 23:30:00:000
F21: ２．仕訳データの取得
H23: 2025/2/6 23:05:00:000 < 仕訳テーブル.登録日時 ≦ 2025/2/7 23:00:00:000
I25: → | J25: 取得できるのは仕訳No.002,003,004,005 | Y25: ※仕訳データ取得するころには仕訳No.006が作成されているが、今回のバッチ実行時は取得しない。
F28: ３．バッチ処理最終実行開始日時を更新
H30: 2025/2/7 23:00:00:000
H34: ↓
G36: 次回は、「 2025/2/7 23:00:00:000 ＜ 仕訳テーブル.登録日時 ≦ 次回の仕訳連動バッチ実行開始日時」 の条件で仕訳を取得する。
G37: 仕訳No.006以降が取得できる。（取得できる仕訳データに重複や漏れはない）
D50: ②抽出対象の仕訳の種類について
E51: 以下の条件を満たす仕訳を抽出する。
F53: １． | G53: ProActiveC4上で承認済みの仕訳データ。
H54: 承認機能を使用しない場合、ProActiveC4では仕訳起票と同時に承認済みというステータスとなる。
F56: ２． | G56: ProActiveC4上で本登録されている仕訳データ。
H57: ProActiveC4では、仮登録というステータスで仕訳を起票することも可能。仮登録の伝票は帳票に出力できない。
F59: ３． | G59: 元帳領域コードが抽出対象となっている仕訳データ。
H60: ホクレン様は、元帳領域コードで仕訳の色分けを行う。仕訳の種類によっては抽出対象外となる可能性がある。
F62: ４． | G62: スクラッチ開発機能からProActiveC4へ連動された仕訳以外の仕訳データ
H63: 抽出対象は、ProActiveC4上で作成された仕訳データ。
E65: データアクセス要領シート「４．仕訳データ取得」の■抽出条件より
E66: 仕訳伝票．仕訳伝票承認申請状況区分 | Q66: = '1' | AN66: 条件１．に対応
E67: 仕訳伝票．仮伝票フラグ | Q67: = '0' | AN67: 条件２．に対応
E68: 仕訳伝票．元帳領域コード | Q68: NOT BETWEEN CST変数管理．出力対象外の元帳領域コードFROM AND | AN68: 条件３．に対応
V69: CST変数管理．出力対象外の元帳領域コードTO
E70: 仕訳伝票．登録者 | Q70: <> CST変数管理．外部連動用ユーザID | AN70: 条件４．に対応
F71: ※CST変数管理テーブルにて、抽出対象外の元帳領域コードを管理する。
F72: CST変数管理の「変数１」と「変数２」を使い、かつ、元帳領域コードを工夫して、連動対象外の元帳領域が複数になっても対応できるようにする
F74: 仕訳の種類と元帳領域コード
F75: 仕訳の種類 | M75: 元帳領域コード
F76: 一般仕訳 | N76: 01
F77: 売上高・売上原価仕訳 | N77: 02
F78: 組替仕訳 | N78: 91 | S78: ←出力対象外としたい元帳領域コードは9始まりの2桁の数字とする。
I81: 伝票区分 | T81: 起票者 | Y81: 仕訳出力要否 | AD81: 備考
E82: 財務会計 | I82: 仕訳伝票（組替仕訳） | T82: PAでの登録者 | Z82: 否
I83: 仕訳伝票（組替仕訳以外） | T83: PAでの登録者 | Z83: 要 | AD83: 一括決済の振替仕訳が該当
I84: 洗替仕訳 | T84: PAでの登録者 | Z84: 要
I85: 取込仕訳（ユーザがPAで取込） | T85: PAでの登録者 | Z85: 要
I86: 取込仕訳（スクラッチからPAへ連動） | T86: 連動用ユーザ | Z86: 否
E87: 債務管理 | I87: 債務振替 | T87: PAでの登録者 | Z87: 要
I88: 支払決済 | T88: PAでの登録者 | Z88: 要
I89: 外貨支払決済 ※現時点では未使用 | T89: PAでの登録者 | Z89: 要 | AD89: 使用することになった場合も想定しておく
E90: 上記以外 | I90: 手形、固定資産（今後追加？） | T90: PAでの登録者 | Z90: 要 | AD90: 追加は未定であるが、想定はしておく
I92: ※債務の支払依頼データ連動時には仕訳は作成しない想定であるため、上記表から除外する
C96: ２）ProActiveC4の仕訳データの作られ方について
E98: ProActiveC4では仕訳伝票を作成した際に、仕訳伝票テーブル、仕訳伝票明細テーブルにレコードが追加される。
E99: 仕訳伝票を修正した際のテーブルの変更は二通りある。
E101: １． | F101: 仕訳伝票テーブルと仕訳伝票明細テーブルの修正前レコードの更新日を更新。
F102: 仕訳伝票テーブルと仕訳伝票明細テーブルに、取消レコードと修正後のレコードを新規追加する。
F104: イメージ）
G105: 修正前
H106: 仕訳伝票テーブル
H107: 仕訳伝票番号 | M107: 仕訳起票日付 | R107: ・・・ | T107: 仕訳伝票合計金額 | Z107: 起票日時 | AG107: 更新日時
H108: 000001 | M108: 2025/6/10 | T108: 30,000 | Z108: 2025/6/5 10:30:40 | AG108: 2025/6/5 10:30:40
H110: 仕訳伝票明細テーブル
H111: 仕訳伝票番号 | M111: 仕訳起票日付 | R111: 仕訳伝票行番号 | W111: 貸借区分 | Z111: 勘定科目コード | AE111: 仕訳伝票明細合計金額 | AL111: ・・・ | AN111: 起票日時 | AU111: 更新日時
H112: 000001 | M112: 2025/6/10 | R112: 1 | W112: 1 | Z112: 1001 | AE112: 30,000 | AN112: 2025/6/5 10:30:40 | AU112: 2025/6/5 10:30:40
H113: 000001 | M113: 2025/6/10 | R113: 1 | W113: 2 | Z113: 1002 | AE113: 30,000 | AN113: 2025/6/5 10:30:40 | AU113: 2025/6/5 10:30:40
G116: 修正後
H117: 仕訳伝票テーブル
H118: 仕訳伝票番号 | M118: 仕訳起票日付 | R118: ・・・ | T118: 仕訳伝票合計金額 | Z118: 起票日時 | AG118: 更新日時
H119: 000001 | M119: 2025/6/10 | T119: 30,000 | Z119: 2025/6/5 10:30:40 | AG119: 2025/6/7 11:40:20 | AN119: ←更新日の変更
H120: 000002 | M120: 2025/6/10 | T120: -30,000 | Z120: 2025/6/7 11:40:20 | AG120: 2025/6/7 11:40:20 | AN120: ←取消
H121: 000003 | M121: 2025/6/10 | T121: 30,000 | Z121: 2025/6/7 11:40:20 | AG121: 2025/6/7 11:40:20 | AN121: ←修正後
H123: 仕訳伝票明細テーブル
H124: 仕訳伝票番号 | M124: 仕訳起票日付 | R124: 仕訳伝票行番号 | W124: 貸借区分 | Z124: 勘定科目コード | AE124: 仕訳伝票明細合計金額 | AL124: ・・・ | AN124: 起票日時 | AU124: 更新日時
H125: 000001 | M125: 2025/6/10 | R125: 1 | W125: 1 | Z125: 1001 | AE125: 30,000 | AN125: 2025/6/5 10:30:40 | AU125: 2025/6/7 11:40:20 | BB125: ←更新日の変更
H126: 000001 | M126: 2025/6/10 | R126: 1 | W126: 2 | Z126: 1002 | AE126: 30,000 | AN126: 2025/6/5 10:30:40 | AU126: 2025/6/7 11:40:20 | BB126: ←更新日の変更
H127: 000002 | M127: 2025/6/10 | R127: 1 | W127: 1 | Z127: 1001 | AE127: -30,000 | AN127: 2025/6/7 11:40:20 | AU127: 2025/6/7 11:40:20 | BB127: ←取消
H128: 000002 | M128: 2025/6/10 | R128: 1 | W128: 2 | Z128: 1002 | AE128: -30,000 | AN128: 2025/6/7 11:40:20 | AU128: 2025/6/7 11:40:20 | BB128: ←取消
H129: 000003 | M129: 2025/6/10 | R129: 1 | W129: 1 | Z129: 2001 | AE129: 30,000 | AN129: 2025/6/7 11:40:20 | AU129: 2025/6/7 11:40:20 | BB129: ←修正後
H130: 000003 | M130: 2025/6/10 | R130: 1 | W130: 2 | Z130: 2002 | AE130: 30,000 | AN130: 2025/6/7 11:40:20 | AU130: 2025/6/7 11:40:20 | BB130: ←修正後
E142: ２． | F142: 仕訳伝票テーブルと仕訳伝票明細テーブルの修正前レコードの更新日と修正対象のカラムを更新。
F144: イメージ）
G145: 修正前
H146: 仕訳伝票テーブル
H147: 仕訳伝票番号 | M147: 仕訳起票日付 | R147: ・・・ | T147: 仕訳伝票合計金額 | Z147: 起票日時 | AG147: 更新日時
H148: 000001 | M148: 2025/6/10 | T148: 30,000 | Z148: 2025/6/5 10:30:40 | AG148: 2025/6/5 10:30:40
H150: 仕訳伝票明細テーブル
H151: 仕訳伝票番号 | M151: 仕訳起票日付 | R151: 仕訳伝票行番号 | W151: 貸借区分 | Z151: 勘定科目コード | AE151: 仕訳伝票明細合計金額 | AL151: 消費税区分 | AP151: ・・・ | AR151: 起票日時 | AY151: 更新日時
H152: 000001 | M152: 2025/6/10 | R152: 1 | W152: 1 | Z152: 1001 | AE152: 30,000 | AL152: 10 | AR152: 2025/6/5 10:30:40 | AY152: 2025/6/5 10:30:40
H153: 000001 | M153: 2025/6/10 | R153: 1 | W153: 2 | Z153: 1002 | AE153: 30,000 | AL153: 10 | AR153: 2025/6/5 10:30:40 | AY153: 2025/6/5 10:30:40
G156: 修正後
H157: 仕訳伝票テーブル
H158: 仕訳伝票番号 | M158: 仕訳起票日付 | R158: ・・・ | T158: 仕訳伝票合計金額 | Z158: 起票日時 | AG158: 更新日時
H159: 000001 | M159: 2025/6/10 | T159: 30,000 | Z159: 2025/6/5 10:30:40 | AG159: 2025/6/7 11:40:20 | AN159: ←更新日の変更
H161: 仕訳伝票明細テーブル
...
